Workbook

Sheet 説明
B1: 第52期上期 担当者コード（予算策定用）
B3: ■ 元データ
B4: ・「20260905 1頁」シート（第52期上期担当者ファイル）の907得意先を、第51期上期担当者コードファイルと同じ構成で「全体」と部門別5シートに分割しています。
B5: ・前年度 = 第51期上期（2024/10〜2025/03）、今年度 = 第52期上期（2025/10〜2026/03）。金額の単位は元データのまま（千円）です。
B6: ・各シートは 担当者コード → 得意先コード の順に並んでいます。合計・集計・総計はすべて数式です。
B8: ■ 2026年10月以降の担当者の設定方法
B9: 1. 各部門シート（水産部X／鳥栖・静岡・東京／松江・境港／下関／石見）の E列「新担当者コード」（黄色セル）に、新しい担当者コードを入力します。
B10: 2. F列「新担当者」は「担当者マスタ」シートから自動表示されます。「※マスタ未登録」と出た場合は担当者マスタにコードを追加してください。
B11: 3. 新しい担当者（新規コード）は「担当者マスタ」シートの黄色の空行に コード・氏名・部門 を追加します。
B12: 4. 「全体」シートの E列・F列は部門別シートの入力を自動で反映します（全体シートでは入力不要）。
B13: 5. 「担当者別集計」シートで、現担当者ベース／新担当者ベースの得意先数・売上・粗利の合計を確認できます。「未設定」行が 0 になれば全得意先の割当完了です。
B15: ■ 部門と担当者コードの対応（第51期ファイルの部門別シート構成を踏襲）
... B25: ・黄色 = 入力欄（部門別シートのE列、担当者マスタの空行） ・緑文字 = 他シート参照 ・灰色 = 集計／総計行

Sheet 全体
A1: 得意先コード | B1: 得意先略称 | C1: 担当者コード | D1: 担当者名 | E1: 新担当者コード | F1: 新担当者 | G1: 2024/10売上 | H1: 2024/11売上 | I1: 2024/12売上 | J1: 2025/01売上 | K1: 2025/02売上 | L1: 2025/03売上 | M1: 前年度売上合計 | N1: 2024/10粗利益 | O1: 2024/11粗利益 | P1: 2024/12粗利益 | Q1: 2025/01粗利益 | R1: 2025/02粗利益 | S1: 2025/03粗利益 | T1: 前年度粗利益合計 | U1: 2025/10売上 | V1: 2025/11売上 | W1: 2025/12売上 | X1: 2026/01売上 | Y1: 2026/02売上 | Z1: 2026/03売上 | AA1: 今年度売上合計 | AB1: 2025/10粗利益 | AC1: 2025/11粗利益 | AD1: 2025/12粗利益 | AE1: 2026/01粗利益 | AF1: 2026/02粗利益 | AG1: 2026/03粗利益 | AH1: 今年度粗利益合計 | AI1: 部門
A2: 0000000000541 | B2: JFしまね冷蔵庫 | C2: 0010 | D2: JF | E2: =IFERROR(IF(INDEX(INDIRECT("'"&$AI2&"'!$E$2:$E$118"),MATCH($A2,INDIRECT("'"&$AI2&"'!$A$2:$A$118"),0))="","",INDEX(INDIRECT("'"&$AI2&"'!$E$2:$E$118"),MATCH($A2,INDIRECT("'"&$AI2&"'!$A$2:$A$118"),0))),"") | F2: =IF($E2="","",IFERROR(INDEX(担当者マスタ!$B$2:$B$101,MATCH($E2,担当者マスタ!$A$2:$A$101,0)),"※マスタ未登録")) | G2: 1727.964 | H2: 1845.035 | I2: 1015.906 | J2: 861.896 | K2: 1167.74 | L2: 1096.898 | M2: =SUM(G2:L2) -> 7715.439 | N2: 328.751 | O2: 408.366 | P2: 254.265 | Q2: 212.557 | R2: 257.125 | S2: 195.312 | T2: =SUM(N2:S2) -> 1656.376 | U2: 2143.798 | V2: 2047.515 | W2: 1351.109 | X2: 572.291 | Y2: 606.598 | Z2: 1948.328 | AA2: =SUM(U2:Z2) -> 8669.639 | AB2: 453.995 | AC2: 419.149 | AD2: 269.7 | AE2: 114.237 | AF2: 168.409 | AG2: 474.166 | AH2: =SUM(AB2:AG2) -> 1899.656 | AI2: 水産部X
A3: 0000000000561 | B3: JFしまねｻｰﾋﾞｽ | C3: 0010 | D3: JF | E3: =IFERROR(IF(INDEX(INDIRECT("'"&$AI3&"'!$E$2:$E$118"),MATCH($A3,INDIRECT("'"&$AI3&"'!$A$2:$A$118"),0))="","",INDEX(INDIRECT("'"&$AI3&"'!$E$2:$E$118"),MATCH($A3,INDIRECT("'"&$AI3&"'!$A$2:$A$118"),0))),"") | F3: =IF($E3="","",IFERROR(INDEX(担当者マスタ!$B$2:$B$101,MATCH($E3,担当者マスタ!$A$2:$A$101,0)),"※マスタ未登録")) | G3: 4904.582 | H3: 4227.566 | I3: 5001.807 | J3: 4524.559 | K3: 4927.58 | L3: 3992.029 | M3: =SUM(G3:L3) -> 27578.123 | N3: 663.403 | O3: 582.982 | P3: 684.031 | Q3: 611.08 | R3: 681.929 | S3: 542.967 | T3: =SUM(N3:S3) -> 3766.392 | U3: 4015.689 | V3: 4119.32 | W3: 3764.454 | X3: 3419.529 | Y3: 4470.593 | Z3: 4581.308 | AA3: =SUM(U3:Z3) -> 24370.893 | AB3: 658.181 | AC3: 719.382 | AD3: 647.591 | AE3: 587.202 | AF3: 722.863 | AG3: 793.162 | AH3: =SUM(AB3:AG3) -> 4128.381 | AI3: 水産部X
A4: 0000000000691 | B4: JFしまね浜田支所総務 | C4: 0010 | D4: JF | E4: =IFERROR(IF(INDEX(INDIRECT("'"&$AI4&"'!$E$2:$E$118"),MATCH($A4,INDIRECT("'"&$AI4&"'!$A$2:$A$118"),0))="","",INDEX(INDIRECT("'"&$AI4&"'!$E$2:$E$118"),MATCH($A4,INDIRECT("'"&$AI4&"'!$A$2:$A$118"),0))),"") | F4: =IF($E4="","",IFERROR(INDEX(担当者マスタ!$B$2:$B$101,MATCH($E4,担当者マスタ!$A$2:$A$101,0)),"※マスタ未登録")) | G4: 28.35 | H4: 0 | I4: 0 | J4: 0 | K4: 0 | L4: 0 | M4: =SUM(G4:L4) -> 28.35 | N4: 10.95 | O4: 0 | P4: 0 | Q4: 0 | R4: 0 | S4: 0 | T4: =SUM(N4:S4) -> 10.95 | U4: 0 | V4: 0 | W4: 0 | X4: 0 | Y4: 0 | Z4: 0 | AA4: =SUM(U4:Z4) -> 0 | AB4: 0 | AC4: 0 | AD4: 0 | AE4: 0 | AF4: 0 | AG4: 0 | AH4: =SUM(AB4:AG4) -> 0 | AI4: 水産部X
A5: 0000000100191 | B5: JF浜田販売部 | C5: 0010 | D5: JF | E5: =IFERROR(IF(INDEX(INDIRECT("'"&$AI5&"'!$E$2:$E$118"),MATCH($A5,INDIRECT("'"&$AI5&"'!$A$2:$A$118"),0))="","",INDEX(INDIRECT("'"&$AI5&"'!$E$2:$E$118"),MATCH($A5,INDIRECT("'"&$AI5&"'!$A$2:$A$118"),0))),"") | F5: =IF($E5="","",IFERROR(INDEX(担当者マスタ!$B$2:$B$101,MATCH($E5,担当者マスタ!$A$2:$A$101,0)),"※マスタ未登録")) | G5: 490.36 | H5: 417.535 | I5: 372.735 | J5: 367.135 | K5: 355.935 | L5: 378.334 | M5: =SUM(G5:L5) -> 2382.034 | N5: 371.089 | O5: 295.464 | P5: 253.464 | Q5: 247.864 | R5: 236.664 | S5: 258.34 | T5: =SUM(N5:S5) -> 1662.885 | U5: 371.533 | V5: 354.732 | W5: 168 | X5: 128.8 | Y5: 145.6 | Z5: 140 | AA5: =SUM(U5:Z5) -> 1308.665 | AB5: 361.641 | AC5: 344.84 | AD5: 168 | AE5: 128.8 | AF5: 145.6 | AG5: 140 | AH5: =SUM(AB5:AG5) -> 1288.881 | AI5: 水産部X
A6: 0000000015661 | B6: 156 中山 圭司 | C6: 0011 | D6: 佐々木邦 | E6: =IFERROR(IF(INDEX(INDIRECT("'"&$AI6&"'!$E$2:$E$320"),MATCH($A6,INDIRECT("'"&$AI6&"'!$A$2:$A$320"),0))="","",INDEX(INDIRECT("'"&$AI6&"'!$E$2:$E$320"),MATCH($A6,INDIRECT("'"&$AI6&"'!$A$2:$A$320"),0))),"") | F6: =IF($E6="","",IFERROR(INDEX(担当者マスタ!$B$2:$B$101,MATCH($E6,担当者マスタ!$A$2:$A$101,0)),"※マスタ未登録")) | G6: 66.139 | H6: 111.017 | I6: 36.415 | J6: 95.814 | K6: 187.302 | L6: 18.073 | M6: =SUM(G6:L6) -> 514.76 | N6: 35.007 | O6: 66.715 | P6: 21.262 | Q6: 52.948 | R6: 43.271 | S6: 8.333 | T6: =SUM(N6:S6) -> 227.536 | U6: 90.974 | V6: 139.449 | W6: 22.066 | X6: 70.992 | Y6: 38.098 | Z6: 9.843 | AA6: =SUM(U6:Z6) -> 371.422 | AB6: 65.217 | AC6: 100.891 | AD6: 13.616 | AE6: 46.68 | AF6: 18.406 | AG6: 4.806 | AH6: =SUM(AB6:AG6) -> 249.616 | AI6: 石見
A7: 0000000034561 | B7: 345 田中乾魚店 | C7: 0011 | D7: 佐々木邦 | E7: =IFERROR(IF(INDEX(INDIRECT("'"&$AI7&"'!$E$2:$E$320"),MATCH($A7,INDIRECT("'"&$AI7&"'!$A$2:$A$320"),0))="","",INDEX(INDIRECT("'"&$AI7&"'!$E$2:$E$320"),MATCH($A7,INDIRECT("'"&$AI7&"'!$A$2:$A$320"),0))),"") | F7: =IF($E7="","",IFERROR(INDEX(担当者マスタ!$B$2:$B$101,MATCH($E7,担当者マスタ!$A$2:$A$101,0)),"※マスタ未登録")) | G7: 3.4 | H7: 14.955 | I7: 6.375 | J7: 0 | K7: 3.08 | L7: 0 | M7: =SUM(G7:L7) -> 27.81 | N7: 3.4 | O7: 7.717 | P7: 2.8 | Q7: 0 | R7: 1.473 | S7: 0 | T7: =SUM(N7:S7) -> 15.39 | U7: 0 | V7: 0 | W7: 0 | X7: 0.5 | Y7: 0 | Z7: 3.05 | AA7: =SUM(U7:Z7) -> 3.55 | AB7: 0 | AC7: 0 | AD7: 0 | AE7: 0.5 | AF7: 0 | AG7: 1.721 | AH7: =SUM(AB7:AG7) -> 2.221 | AI7: 石見
A8: 0000000038561 | B8: 385 (有)吉本重義商店 | C8: 0011 | D8: 佐々木邦 | E8: =IFERROR(IF(INDEX(INDIRECT("'"&$AI8&"'!$E$2:$E$320"),MATCH($A8,INDIRECT("'"&$AI8&"'!$A$2:$A$320"),0))="","",INDEX(INDIRECT("'"&$AI8&"'!$E$2:$E$320"),MATCH($A8,INDIRECT("'"&$AI8&"'!$A$2:$A$320"),0))),"") | F8: =IF($E8="","",IFERROR(INDEX(担当者マスタ!$B$2:$B$101,MATCH($E8,担当者マスタ!$A$2:$A$101,0)),"※マスタ未登録")) | G8: 32.432 | H8: 0 | I8: 0 | J8: 11.35 | K8: 0 | L8: 3.339 | M8: =SUM(G8:L8) -> 47.121 | N8: 23.326 | O8: 0 | P8: 0 | Q8: 4.85 | R8: 0 | S8: 1.854 | T8: =SUM(N8:S8) -> 30.03 | U8: 36.111 | V8: 11.04 | W8: 3.339 | X8: 0 | Y8: 0 | Z8: 0 | AA8: =SUM(U8:Z8) -> 50.49 | AB8: 22.156 | AC8: 5.556 | AD8: 1.659 | AE8: 0 | AF8: 0 | AG8: 0 | AH8: =SUM(AB8:AG8) -> 29.371 | AI8: 石見
A9: 0000000052561 | B9: 525 植野 信幸 | C9: 0011 | D9: 佐々木邦 | E9: =IFERROR(IF(INDEX(INDIRECT("'"&$AI9&"'!$E$2:$E$320"),MATCH($A9,INDIRECT("'"&$AI9&"'!$A$2:$A$320"),0))="","",INDEX(INDIRECT("'"&$AI9&"'!$E$2:$E$320"),MATCH($A9,INDIRECT("'"&$AI9&"'!$A$2:$A$320"),0))),"") | F9: =IF($E9="","",IFERROR(INDEX(担当者マスタ!$B$2:$B$101,MATCH($E9,担当者マスタ!$A$2:$A$101,0)),"※マスタ未登録")) | G9: 0 | H9: 1.52 | I9: 7.25 | J9: 0 | K9: 0 | L9: 1.36 | M9: =SUM(G9:L9) -> 10.13 | N9: 0 | O9: 0.852 | P9: 3.783 | Q9: 0 | R9: 0 | S9: 0.38 | T9: =SUM(N9:S9) -> 5.015 | U9: 0 | V9: 0 | W9: 5.11 | X9: 0 | Y9: 0 | Z9: 0 | AA9: =SUM(U9:Z9) -> 5.11 | AB9: 0 | AC9: 0 | AD9: 2.757 | AE9: 0 | AF9: 0 | AG9: 0 | AH9: =SUM(AB9:AG9) -> 2.757 | AI9: 石見
A10: 0000000052761 | B10: ※527 中井 浩 | C10: 0011 | D10: 佐々木邦 | E10: =IFERROR(IF(INDEX(INDIRECT("'"&$AI10&"'!$E$2:$E$320"),MATCH($A10,INDIRECT("'"&$AI10&"'!$A$2:$A$320"),0))="","",INDEX(INDIRECT("'"&$AI10&"'!$E$2:$E$320"),MATCH($A10,INDIRECT("'"&$AI10&"'!$A$2:$A$320"),0))),"") | F10: =IF($E10="","",IFERROR(INDEX(担当者マスタ!$B$2:$B$101,MATCH($E10,担当者マスタ!$A$2:$A$101,0)),"※マスタ未登録")) | G10: 209.322 | H10: 83.69 | I10: 103.08 | J10: 3.621 | K10: 73.377 | L10: 62.471 | M10: =SUM(G10:L10) -> 535.561 | N10: 82.094 | O10: 52.626 | P10: 54.96 | Q10: 1.926 | R10: 36.533 | S10: 36.068 | T10: =SUM(N10:S10) -> 264.207 | U10: 40.799 | V10: 62.98 | W10: 83.153 | X10: 0 | Y10: 0 | Z10: 0 | AA10: =SUM(U10:Z10) -> 186.932 | AB10: 23.037 | AC10: 38.526 | AD10: 50.38 | AE10: 0 | AF10: 0 | AG10: 0 | AH10: =SUM(AB10:AG10) -> 111.943 | AI10: 石見
A11: 0000000053661 | B11: 536 新田健二 (魚新) | C11: 0011 | D11: 佐々木邦 | E11: =IFERROR(IF(INDEX(INDIRECT("'"&$AI11&"'!$E$2:$E$320"),MATCH($A11,INDIRECT("'"&$AI11&"'!$A$2:$A$320"),0))="","",INDEX(INDIRECT("'"&$AI11&"'!$E$2:$E$320"),MATCH($A11,INDIRECT("'"&$AI11&"'!$A$2:$A$320"),0))),"") | F11: =IF($E11="","",IFERROR(INDEX(担当者マスタ!$B$2:$B$101,MATCH($E11,担当者マスタ!$A$2:$A$101,0)),"※マスタ未登録")) | G11: 4.239 | H11: 6.693 | I11: 2.34 | J11: 0 | K11: 2.34 | L11: 6.693 | M11: =SUM(G11:L11) -> 22.305 | N11: 2.392 | O11: 2.848 | P11: 1.273 | Q11: 0 | R11: 1.273 | S11: 2.848 | T11: =SUM(N11:S11) -> 10.634 | U11: 1.128 | V11: 0 | W11: 11.332 | X11: 0 | Y11: 3.468 | Z11: 5.565 | AA11: =SUM(U11:Z11) -> 21.493 | AB11: 0.733 | AC11: 0 | AD11: 5.413 | AE11: 0 | AF11: 2.006 | AG11: 2.115 | AH11: =SUM(AB11:AG11) -> 10.267 | AI11: 石見
A12: 0000000054061 | B12: 540 浜原 | C12: 0011 | D12: 佐々木邦 | E12: =IFERROR(IF(INDEX(INDIRECT("'"&$AI12&"'!$E$2:$E$320"),MATCH($A12,INDIRECT("'"&$AI12&"'!$A$2:$A$320"),0))="","",INDEX(INDIRECT("'"&$AI12&"'!$E$2:$E$320"),MATCH($A12,INDIRECT("'"&$AI12&"'!$A$2:$A$320"),0))),"") | F12: =IF($E12="","",IFERROR(INDEX(担当者マスタ!$B$2:$B$101,MATCH($E12,担当者マスタ!$A$2:$A$101,0)),"※マスタ未登録")) | G12: 0 | H12: 0 | I12: 0 | J12: 5.565 | K12: 0 | L12: 1.36 | M12: =SUM(G12:L12) -> 6.925 | N12: 0 | O12: 0 | P12: 0 | Q12: 2.115 | R12: 0 | S12: 0.38 | T12: =SUM(N12:S12) -> 2.495 | U12: 12.3 | V12: 0 | W12: 0 | X12: 0 | Y12: 0 | Z12: 0 | AA12: =SUM(U12:Z12) -> 12.3 | AB12: 7.36 | AC12: 0 | AD12: 0 | AE12: 0 | AF12: 0 | AG12: 0 | AH12: =SUM(AB12:AG12) -> 7.36 | AI12: 石見
A13: 0000000055761 | B13: 557山末鮮魚店 | C13: 0011 | D13: 佐々木邦 | E13: =IFERROR(IF(INDEX(INDIRECT("'"&$AI13&"'!$E$2:$E$320"),MATCH($A13,INDIRECT("'"&$AI13&"'!$A$2:$A$320"),0))="","",INDEX(INDIRECT("'"&$AI13&"'!$E$2:$E$320"),MATCH($A13,INDIRECT("'"&$AI13&"'!$A$2:$A$320"),0))),"") | F13: =IF($E13="","",IFERROR(INDEX(担当者マスタ!$B$2:$B$101,MATCH($E13,担当者マスタ!$A$2:$A$101,0)),"※マスタ未登録")) | G13: 12.138 | H13: 42.301 | I13: 203.145 | J13: -30.188 | K13: 25.386 | L13: 84.022 | M13: =SUM(G13:L13) -> 336.804 | N13: 6.817 | O13: 23.374 | P13: 102.421 | Q13: -15.475 | R13: 12.409 | S13: 23.692 | T13: =SUM(N13:S13) -> 153.238 | U13: 35.263 | V13: 24.819 | W13: 116.324 | X13: 5.615 | Y13: 101.697 | Z13: 21.525 | AA13: =SUM(U13:Z13) -> 305.243 | AB13: 18.983 | AC13: 13.872 | AD13: 49.442 | AE13: 2.946 | AF13: 32.017 | AG13: 8.522 | AH13: =SUM(AB13:AG13) -> 125.782 | AI13: 石見
A14: 0000000056461 | B14: 564渡辺鮮魚店㈱ | C14: 0011 | D14: 佐々木邦 | E14: =IFERROR(IF(INDEX(INDIRECT("'"&$AI14&"'!$E$2:$E$320"),MATCH($A14,INDIRECT("'"&$AI14&"'!$A$2:$A$320"),0))="","",INDEX(INDIRECT("'"&$AI14&"'!$E$2:$E$320"),MATCH($A14,INDIRECT("'"&$AI14&"'!$A$2:$A$320"),0))),"") | F14: =IF($E14="","",IFERROR(INDEX(担当者マスタ!$B$2:$B$101,MATCH($E14,担当者マスタ!$A$2:$A$101,0)),"※マスタ未登録")) | G14: 199.66 | H14: 85.905 | I14: 106.962 | J14: 61.555 | K14: 72.31 | L14: 78.24 | M14: =SUM(G14:L14) -> 604.632 | N14: 72.783 | O14: 29.191 | P14: 34.663 | Q14: 21.201 | R14: 22.532 | S14: 20.17 | T14: =SUM(N14:S14) -> 200.54 | U14: 83.7 | V14: 41.17 | W14: 112.518 | X14: 52.6 | Y14: 75.59 | Z14: 115.225 | AA14: =SUM(U14:Z14) -> 480.803 | AB14: 23.787 | AC14: 10.86 | AD14: 36.634 | AE14: 16.819 | AF14: 21.22 | AG14: 37.85 | AH14: =SUM(AB14:AG14) -> 147.17 | AI14: 石見
A15: 0000000090081 | B15: ｾﾌﾞﾝｲﾚﾌﾞﾝ浅利店 | C15: 0011 | D15: 佐々木邦 | E15: =IFERROR(IF(INDEX(INDIRECT("'"&$AI15&"'!$E$2:$E$320"),MATCH($A15,INDIRECT("'"&$AI15&"'!$A$2:$A$320"),0))="","",INDEX(INDIRECT("'"&$AI15&"'!$E$2:$E$320"),MATCH($A15,INDIRECT("'"&$AI15&"'!$A$2:$A$320"),0))),"") | F15: =IF($E15="","",IFERROR(INDEX(担当者マスタ!$B$2:$B$101,MATCH($E15,担当者マスタ!$A$2:$A$101,0)),"※マスタ未登録")) | G15: 0 | H15: 0 | I15: 23.1 | J15: 0 | K15: 0 | L15: 8.96 | M15: =SUM(G15:L15) -> 32.06 | N15: 0 | O15: 0 | P15: 4.95 | Q15: 0 | R15: 0 | S15: 1.8 | T15: =SUM(N15:S15) -> 6.75 | U15: 0 | V15: 0 | W15: 0 | X15: 0 | Y15: 0 | Z15: 0 | AA15: =SUM(U15:Z15) -> 0 | AB15: 0 | AC15: 0 | AD15: 0 | AE15: 0 | AF15: 0 | AG15: 0 | AH15: =SUM(AB15:AG15) -> 0 | AI15: 石見
A16: 0000000100481 | B16: (有)江木蒲鉾店 | C16: 0011 | D16: 佐々木邦 | E16: =IFERROR(IF(INDEX(INDIRECT("'"&$AI16&"'!$E$2:$E$320"),MATCH($A16,INDIRECT("'"&$AI16&"'!$A$2:$A$320"),0))="","",INDEX(INDIRECT("'"&$AI16&"'!$E$2:$E$320"),MATCH($A16,INDIRECT("'"&$AI16&"'!$A$2:$A$320"),0))),"") | F16: =IF($E16="","",IFERROR(INDEX(担当者マスタ!$B$2:$B$101,MATCH($E16,担当者マスタ!$A$2:$A$101,0)),"※マスタ未登録")) | G16: 1150.858 | H16: 598 | I16: 0 | J16: 237.8 | K16: 479.33 | L16: 125.88 | M16: =SUM(G16:L16) -> 2591.868 | N16: 228.633 | O16: 33 | P16: 0 | Q16: 38.1 | R16: 97.446 | S16: 19.84 | T16: =SUM(N16:S16) -> 417.019 | U16: 4.2 | V16: 0 | W16: 8.4 | X16: 0 | Y16: 6.3 | Z16: 4.2 | AA16: =SUM(U16:Z16) -> 23.1 | AB16: 0.6 | AC16: 0 | AD16: 1.2 | AE16: 0 | AF16: 0.9 | AG16: 0.6 | AH16: =SUM(AB16:AG16) -> 3.3 | AI16: 石見
A17: 0000000100691 | B17: 石見糀屋 発酵-LABO | C17: 0011 | D17: 佐々木邦 | E17: =IFERROR(IF(INDEX(INDIRECT("'"&$AI17&"'!$E$2:$E$320"),MATCH($A17,INDIRECT("'"&$AI17&"'!$A$2:$A$320"),0))="","",INDEX(INDIRECT("'"&$AI17&"'!$E$2:$E$320"),MATCH($A17,INDIRECT("'"&$AI17&"'!$A$2:$A$320"),0))),"") | F17: =IF($E17="","",IFERROR(INDEX(担当者マスタ!$B$2:$B$101,MATCH($E17,担当者マスタ!$A$2:$A$101,0)),"※マスタ未登録")) | G17: 11.328 | H17: 10.152 | I17: 13.992 | J17: 10.896 | K17: 14.712 | L17: 10.896 | M17: =SUM(G17:L17) -> 71.976 | N17: 2.376 | O17: 2.136 | P17: 3.048 | Q17: 2.352 | R17: 3.096 | S17: 2.352 | T17: =SUM(N17:S17) -> 15.36 | U17: 9.912 | V17: 8.616 | W17: 6.48 | X17: 12.048 | Y17: 8.616 | Z17: 8.616 | AA17: =SUM(U17:Z17) -> 54.288 | AB17: 2.832 | AC17: 2.472 | AD17: 1.8 | AE17: 2.928 | AF17: 1.992 | AG17: 1.992 | AH17: =SUM(AB17:AG17) -> 14.016 | AI17: 石見
... A284: 0000000909031 | B284: ㈱大磯-機械- | C284: 0014 | D284: 木村 | E284: =IFERROR(IF(INDEX(INDIRECT("'"&$AI284&"'!$E$2:$E$320"),MATCH($A284,INDIRECT("'"&$AI284&"'!$A$2:$A$320"),0))="","",INDEX(INDIRECT("'"&$AI284&"'!$E$2:$E$320"),MATCH($A284,INDIRECT("'"&$AI284&"'!$A$2:$A$320"),0))),"") | F284: =IF($E284="","",IFERROR(INDEX(担当者マスタ!$B$2:$B$101,MATCH($E284,担当者マスタ!$A$2:$A$101,0)),"※マスタ未登録")) | G284: 0 | H284: 0 | I284: 94.1 | J284: 20 | K284: 133 | L284: 0 | M284: =SUM(G284:L284) -> 247.1 | N284: 0 | O284: 0 | P284: 16.36 | Q284: 4 | R284: 37.8 | S284: 0 | T284: =SUM(N284:S284) -> 58.16 | U284: 0 | V284: 0 | W284: 302.802 | X284: 0 | Y284: 0 | Z284: 33.52 | AA284: =SUM(U284:Z284) -> 336.322 | AB284: 0 | AC284: 0 | AD284: 98.457 | AE284: 0 | AF284: 0 | AG284: 9.62 | AH284: =SUM(AB284:AG284) -> 108.077 | AI284: 石見
A285: 0000000000341 | B285: 153 新家商店 | C285: 0017 | D285: 鮮魚 | E285: =IFERROR(IF(INDEX(INDIRECT("'"&$AI285&"'!$E$2:$E$118"),MATCH($A285,INDIRECT("'"&$AI285&"'!$A$2:$A$118"),0))="","",INDEX(INDIRECT("'"&$AI285&"'!$E$2:$E$118"),MATCH($A285,INDIRECT("'"&$AI285&"'!$A$2:$A$118"),0))),"") | F285: =IF($E285="","",IFERROR(INDEX(担当者マスタ!$B$2:$B$101,MATCH($E285,担当者マスタ!$A$2:$A$101,0)),"※マスタ未登録")) | G285: 39.1 | H285: 14.423 | I285: 11.76 | J285: 17.036 | K285: 11.688 | L285: 8.097 | M285: =SUM(G285:L285) -> 102.104 | N285: 20.201 | O285: 6.885 | P285: 5.061 | Q285: 7.85 | R285: 5.304 | S285: 3.461 | T285: =SUM(N285:S285) -> 48.762 | U285: 26.513 | V285: 14.266 | W285: 18.887 | X285: 5.19 | Y285: 19.191 | Z285: 11.024 | AA285: =SUM(U285:Z285) -> 95.071 | AB285: 12.505 | AC285: 5.797 | AD285: 8.625 | AE285: 2.248 | AF285: 9.099 | AG285: 4.024 | AH285: =SUM(AB285:AG285) -> 42.298 | AI285: 水産部X
A286: 0000000090221 | B286: 西部農林水産振興ｾﾝﾀｰ | C286: 0017 | D286: 鮮魚 | E286: =IFERROR(IF(INDEX(INDIRECT("'"&$AI286&"'!$E$2:$E$118"),MATCH($A286,INDIRECT("'"&$AI286&"'!$A$2:$A$118"),0))="","",INDEX(INDIRECT("'"&$AI286&"'!$E$2:$E$118"),MATCH($A286,INDIRECT("'"&$AI286&"'!$A$2:$A$118"),0))),"") | F286: =IF($E286="","",IFERROR(INDEX(担当者マスタ!$B$2:$B$101,MATCH($E286,担当者マスタ!$A$2:$A$101,0)),"※マスタ未登録")) | G286: 0 | H286: 0 | I286: 0 | J286: 0 | K286: 0 | L286: 0 | M286: =SUM(G286:L286) -> 0 | N286: 0 | O286: 0 | P286: 0 | Q286: 0 | R286: 0 | S286: 0 | T286: =SUM(N286:S286) -> 0 | U286: 7 | V286: 0 | W286: 0 | X286: 0 | Y286: 0 | Z286: 0 | AA286: =SUM(U286:Z286) -> 7 | AB286: 1.72 | AC286: 0 | AD286: 0 | AE286: 0 | AF286: 0 | AG286: 0 | AH286: =SUM(AB286:AG286) -> 1.72 | AI286: 水産部X
A287: 0000000103121 | B287: (有)浜田運送 | C287: 0017 | D287: 鮮魚 | E287: =IFERROR(IF(INDEX(INDIRECT("'"&$AI287&"'!$E$2:$E$118"),MATCH($A287,INDIRECT("'"&$AI287&"'!$A$2:$A$118"),0))="","",INDEX(INDIRECT("'"&$AI287&"'!$E$2:$E$118"),MATCH($A287,INDIRECT("'"&$AI287&"'!$A$2:$A$118"),0))),"") | F287: =IF($E287="","",IFERROR(INDEX(担当者マスタ!$B$2:$B$101,MATCH($E287,担当者マスタ!$A$2:$A$101,0)),"※マスタ未登録")) | G287: 0 | H287: 0 | I287: 0 | J287: 0 | K287: 0 | L287: 0 | M287: =SUM(G287:L287) -> 0 | N287: 0 | O287: 0 | P287: 0 | Q287: 0 | R287: 0 | S287: 0 | T287: =SUM(N287:S287) -> 0 | U287: 0 | V287: 0 | W287: 0 | X287: 0 | Y287: 0 | Z287: 1.164 | AA287: =SUM(U287:Z287) -> 1.164 | AB287: 0 | AC287: 0 | AD287: 0 | AE287: 0 | AF287: 0 | AG287: 0.495 | AH287: =SUM(AB287:AG287) -> 0.495 | AI287: 水産部X
A288: 0000000202131 | B288: 220 福田水産㈱ | C288: 0017 | D288: 鮮魚 | E288: =IFERROR(IF(INDEX(INDIRECT("'"&$AI288&"'!$E$2:$E$118"),MATCH($A288,INDIRECT("'"&$AI288&"'!$A$2:$A$118"),0))="","",INDEX(INDIRECT("'"&$AI288&"'!$E$2:$E$118"),MATCH($A288,INDIRECT("'"&$AI288&"'!$A$2:$A$118"),0))),"") | F288: =IF($E288="","",IFERROR(INDEX(担当者マスタ!$B$2:$B$101,MATCH($E288,担当者マスタ!$A$2:$A$101,0)),"※マスタ未登録")) | G288: 69.5 | H288: 80.845 | I288: 29.36 | J288: 20.562 | K288: 114.97 | L288: 71.34 | M288: =SUM(G288:L288) -> 386.577 | N288: 68.25 | O288: 64.478 | P288: 16.16 | Q288: 20.03 | R288: 114.97 | S288: 71.34 | T288: =SUM(N288:S288) -> 355.228 | U288: 44 | V288: 142.4 | W288: 62.66 | X288: 20 | Y288: 10.6 | Z288: 3 | AA288: =SUM(U288:Z288) -> 282.66 | AB288: 44 | AC288: 141.15 | AD288: 62.243 | AE288: 20 | AF288: 10.6 | AG288: 3 | AH288: =SUM(AB288:AG288) -> 280.993 | AI288: 水産部X
A289: 0000000202471 | B289: ㈱浜田あけぼの水産 | C289: 0017 | D289: 鮮魚 | E289: =IFERROR(IF(INDEX(INDIRECT("'"&$AI289&"'!$E$2:$E$118"),MATCH($A289,INDIRECT("'"&$AI289&"'!$A$2:$A$118"),0))="","",INDEX(INDIRECT("'"&$AI289&"'!$E$2:$E$118"),MATCH($A289,INDIRECT("'"&$AI289&"'!$A$2:$A$118"),0))),"") | F289: =IF($E289="","",IFERROR(INDEX(担当者マスタ!$B$2:$B$101,MATCH($E289,担当者マスタ!$A$2:$A$101,0)),"※マスタ未登録")) | G289: 0 | H289: 0 | I289: 0 | J289: 0 | K289: 0 | L289: 0 | M289: =SUM(G289:L289) -> 0 | N289: 0 | O289: 0 | P289: 0 | Q289: 0 | R289: 0 | S289: 0 | T289: =SUM(N289:S289) -> 0 | U289: 0 | V289: 0 | W289: 0 | X289: 0 | Y289: 473.2 | Z289: 0 | AA289: =SUM(U289:Z289) -> 473.2 | AB289: 0 | AC289: 0 | AD289: 0 | AE289: 0 | AF289: 92.4 | AG289: 0 | AH289: =SUM(AB289:AG289) -> 92.4 | AI289: 水産部X
A290: 0000000202601 | B290: 103㈲山本一枝(鮮魚) | C290: 0017 | D290: 鮮魚 | E290: =IFERROR(IF(INDEX(INDIRECT("'"&$AI290&"'!$E$2:$E$118"),MATCH($A290,INDIRECT("'"&$AI290&"'!$A$2:$A$118"),0))="","",INDEX(INDIRECT("'"&$AI290&"'!$E$2:$E$118"),MATCH($A290,INDIRECT("'"&$AI290&"'!$A$2:$A$118"),0))),"") | F290: =IF($E290="","",IFERROR(INDEX(担当者マスタ!$B$2:$B$101,MATCH($E290,担当者マスタ!$A$2:$A$101,0)),"※マスタ未登録")) | G290: 496.65 | H290: 231.55 | I290: 55.45 | J290: 66.2 | K290: 34.25 | L290: 41.25 | M290: =SUM(G290:L290) -> 925.35 | N290: 449.596 | O290: 213.992 | P290: 55.45 | Q290: 59.177 | R290: 34.25 | S290: 41.25 | T290: =SUM(N290:S290) -> 853.715 | U290: 27.9 | V290: 84.5 | W290: 561.75 | X290: 412.4 | Y290: 546.4 | Z290: 51.7 | AA290: =SUM(U290:Z290) -> 1684.65 | AB290: 27.9 | AC290: 84.5 | AD290: 326.811 | AE290: 365.409 | AF290: 405.898 | AG290: 46.894 | AH290: =SUM(AB290:AG290) -> 1257.412 | AI290: 水産部X
A291: 0000000202891 | B291: ㈱かもしま資材 | C291: 0017 | D291: 鮮魚 | E291: =IFERROR(IF(INDEX(INDIRECT("'"&$AI291&"'!$E$2:$E$118"),MATCH($A291,INDIRECT("'"&$AI291&"'!$A$2:$A$118"),0))="","",INDEX(INDIRECT("'"&$AI291&"'!$E$2:$E$118"),MATCH($A291,INDIRECT("'"&$AI291&"'!$A$2:$A$118"),0))),"") | F291: =IF($E291="","",IFERROR(INDEX(担当者マスタ!$B$2:$B$101,MATCH($E291,担当者マスタ!$A$2:$A$101,0)),"※マスタ未登録")) | G291: 1927.301 | H291: 896.31 | I291: 384.75 | J291: 232.53 | K291: 131.08 | L291: 304.45 | M291: =SUM(G291:L291) -> 3876.421 | N291: 432.615 | O291: 199.95 | P291: 87.61 | Q291: 53.55 | R291: 30.92 | S291: 71.28 | T291: =SUM(N291:S291) -> 875.925 | U291: 1160.935 | V291: 696.99 | W291: 540.014 | X291: 434.97 | Y291: 266.45 | Z291: 417.96 | AA291: =SUM(U291:Z291) -> 3517.319 | AB291: 252.081 | AC291: 151.96 | AD291: 117.586 | AE291: 99.88 | AF291: 60.93 | AG291: 93.45 | AH291: =SUM(AB291:AG291) -> 775.887 | AI291: 水産部X
A292: 0000000820021 | B292: 116ﾏﾙｾｲ商店 ｽﾁﾛｰﾙ他 | C292: 0017 | D292: 鮮魚 | E292: =IFERROR(IF(INDEX(INDIRECT("'"&$AI292&"'!$E$2:$E$118"),MATCH($A292,INDIRECT("'"&$AI292&"'!$A$2:$A$118"),0))="","",INDEX(INDIRECT("'"&$AI292&"'!$E$2:$E$118"),MATCH($A292,INDIRECT("'"&$AI292&"'!$A$2:$A$118"),0))),"") | F292: =IF($E292="","",IFERROR(INDEX(担当者マスタ!$B$2:$B$101,MATCH($E292,担当者マスタ!$A$2:$A$101,0)),"※マスタ未登録")) | G292: 0 | H292: 0 | I292: 0 | J292: 0 | K292: 0 | L292: 0 | M292: =SUM(G292:L292) -> 0 | N292: 0 | O292: 0 | P292: 0 | Q292: 0 | R292: 0 | S292: 0 | T292: =SUM(N292:S292) -> 0 | U292: 5041.8 | V292: 6213.805 | W292: 4525.811 | X292: 4430.911 | Y292: 3797.025 | Z292: 4362.168 | AA292: =SUM(U292:Z292) -> 28371.52 | AB292: 1982.663 | AC292: 2331.152 | AD292: 1754.948 | AE292: 1655.38 | AF292: 1390.295 | AG292: 1680.919 | AH292: =SUM(AB292:AG292) -> 10795.357 | AI292: 水産部X
A293: 0000000000011 | B293: 現金 | C293: 0019 | D293: その他 | E293: =IFERROR(IF(INDEX(INDIRECT("'"&$AI293&"'!$E$2:$E$320"),MATCH($A293,INDIRECT("'"&$AI293&"'!$A$2:$A$320"),0))="","",INDEX(INDIRECT("'"&$AI293&"'!$E$2:$E$320"),MATCH($A293,INDIRECT("'"&$AI293&"'!$A$2:$A$320"),0))),"") | F293: =IF($E293="","",IFERROR(INDEX(担当者マスタ!$B$2:$B$101,MATCH($E293,担当者マスタ!$A$2:$A$101,0)),"※マスタ未登録")) | G293: 219.564 | H293: 77.791 | I293: 183.928 | J293: 52.388 | K293: 42.213 | L293: 73.638 | M293: =SUM(G293:L293) -> 649.522 | N293: 146.58 | O293: 31.779 | P293: 83.206 | Q293: 31.447 | R293: 21.221 | S293: 37.945 | T293: =SUM(N293:S293) -> 352.178 | U293: 30.176 | V293: 201.538 | W293: 192.535 | X293: 58.168 | Y293: 6.56 | Z293: 154.97 | AA293: =SUM(U293:Z293) -> 643.947 | AB293: 13.8 | AC293: 73.075 | AD293: 78.541 | AE293: 29.898 | AF293: 3.921 | AG293: 68.503 | AH293: =SUM(AB293:AG293) -> 267.738 | AI293: 石見
A294: 0000000000031 | B294: 現金(営業) | C294: 0019 | D294: その他 | E294: =IFERROR(IF(INDEX(INDIRECT("'"&$AI294&"'!$E$2:$E$320"),MATCH($A294,INDIRECT("'"&$AI294&"'!$A$2:$A$320"),0))="","",INDEX(INDIRECT("'"&$AI294&"'!$E$2:$E$320"),MATCH($A294,INDIRECT("'"&$AI294&"'!$A$2:$A$320"),0))),"") | F294: =IF($E294="","",IFERROR(INDEX(担当者マスタ!$B$2:$B$101,MATCH($E294,担当者マスタ!$A$2:$A$101,0)),"※マスタ未登録")) | G294: 0 | H294: 0 | I294: 0 | J294: 0 | K294: 0 | L294: 0 | M294: =SUM(G294:L294) -> 0 | N294: 0 | O294: 0 | P294: 0 | Q294: 0 | R294: 0 | S294: 0 | T294: =SUM(N294:S294) -> 0 | U294: 0 | V294: 0 | W294: 30 | X294: 0 | Y294: 0 | Z294: 0 | AA294: =SUM(U294:Z294) -> 30 | AB294: 0 | AC294: 0 | AD294: 30 | AE294: 0 | AF294: 0 | AG294: 0 | AH294: =SUM(AB294:AG294) -> 30 | AI294: 石見
A295: 0000000009001 | B295: ㈱ｴﾌﾋﾟｺ ﾍﾟｯﾄﾎﾞﾄﾙ回収 | C295: 0019 | D295: その他 | E295: =IFERROR(IF(INDEX(INDIRECT("'"&$AI295&"'!$E$2:$E$320"),MATCH($A295,INDIRECT("'"&$AI295&"'!$A$2:$A$320"),0))="","",INDEX(INDIRECT("'"&$AI295&"'!$E$2:$E$320"),MATCH($A295,INDIRECT("'"&$AI295&"'!$A$2:$A$320"),0))),"") | F295: =IF($E295="","",IFERROR(INDEX(担当者マスタ!$B$2:$B$101,MATCH($E295,担当者マスタ!$A$2:$A$101,0)),"※マスタ未登録")) | G295: 21.6 | H295: 0 | I295: 0 | J295: 15.9 | K295: 0 | L295: 0 | M295: =SUM(G295:L295) -> 37.5 | N295: 2.592 | O295: 0 | P295: 0 | Q295: 1.908 | R295: 0 | S295: 0 | T295: =SUM(N295:S295) -> 4.5 | U295: 20.85 | V295: 0 | W295: 0 | X295: 13.95 | Y295: 0 | Z295: 0 | AA295: =SUM(U295:Z295) -> 34.8 | AB295: 2.502 | AC295: 0 | AD295: 0 | AE295: 1.674 | AF295: 0 | AG295: 0 | AH295: =SUM(AB295:AG295) -> 4.176 | AI295: 石見
A296: 0000000090011 | B296: 杉の森ﾃﾞｲｻｰﾋﾞｽ *運 | C296: 0019 | D296: その他 | E296: =IFERROR(IF(INDEX(INDIRECT("'"&$AI296&"'!$E$2:$E$320"),MATCH($A296,INDIRECT("'"&$AI296&"'!$A$2:$A$320"),0))="","",INDEX(INDIRECT("'"&$AI296&"'!$E$2:$E$320"),MATCH($A296,INDIRECT("'"&$AI296&"'!$A$2:$A$320"),0))),"") | F296: =IF($E296="","",IFERROR(INDEX(担当者マスタ!$B$2:$B$101,MATCH($E296,担当者マスタ!$A$2:$A$101,0)),"※マスタ未登録")) | G296: 18.708 | H296: 18.708 | I296: 10.143 | J296: 0 | K296: 0 | L296: 0 | M296: =SUM(G296:L296) -> 47.559 | N296: 6.828 | O296: 6.828 | P296: 3.753 | Q296: 0 | R296: 0 | S296: 0 | T296: =SUM(N296:S296) -> 17.409 | U296: 0 | V296: 0 | W296: 0 | X296: 0 | Y296: 10.143 | Z296: 18.708 | AA296: =SUM(U296:Z296) -> 28.851 | AB296: 0 | AC296: 0 | AD296: 0 | AE296: 0 | AF296: 3.753 | AG296: 6.828 | AH296: =SUM(AB296:AG296) -> 10.581 | AI296: 石見
A297: 0000000090061 | B297: 金城支所産業建設課 | C297: 0019 | D297: その他 | E297: =IFERROR(IF(INDEX(INDIRECT("'"&$AI297&"'!$E$2:$E$320"),MATCH($A297,INDIRECT("'"&$AI297&"'!$A$2:$A$320"),0))="","",INDEX(INDIRECT("'"&$AI297&"'!$E$2:$E$320"),MATCH($A297,INDIRECT("'"&$AI297&"'!$A$2:$A$320"),0))),"") | F297: =IF($E297="","",IFERROR(INDEX(担当者マスタ!$B$2:$B$101,MATCH($E297,担当者マスタ!$A$2:$A$101,0)),"※マスタ未登録")) | G297: 15.515 | H297: 0 | I297: 0 | J297: 0 | K297: 0 | L297: 0 | M297: =SUM(G297:L297) -> 15.515 | N297: 6.195 | O297: 0 | P297: 0 | Q297: 0 | R297: 0 | S297: 0 | T297: =SUM(N297:S297) -> 6.195 | U297: 0 | V297: 0 | W297: 0 | X297: 0 | Y297: 0 | Z297: 0 | AA297: =SUM(U297:Z297) -> 0 | AB297: 0 | AC297: 0 | AD297: 0 | AE297: 0 | AF297: 0 | AG297: 0 | AH297: =SUM(AB297:AG297) -> 0 | AI297: 石見
A298: 0000000090091 | B298: 浜田市社会福祉協金城 | C298: 0019 | D298: その他 | E298: =IFERROR(IF(INDEX(INDIRECT("'"&$AI298&"'!$E$2:$E$320"),MATCH($A298,INDIRECT("'"&$AI298&"'!$A$2:$A$320"),0))="","",INDEX(INDIRECT("'"&$AI298&"'!$E$2:$E$320"),MATCH($A298,INDIRECT("'"&$AI298&"'!$A$2:$A$320"),0))),"") | F298: =IF($E298="","",IFERROR(INDEX(担当者マスタ!$B$2:$B$101,MATCH($E298,担当者マスタ!$A$2:$A$101,0)),"※マスタ未登録")) | G298: 0 | H298: 19.35 | I298: 0 | J298: 0 | K298: 0 | L298: 0 | M298: =SUM(G298:L298) -> 19.35 | N298: 0 | O298: 7.434 | P298: 0 | Q298: 0 | R298: 0 | S298: 0 | T298: =SUM(N298:S298) -> 7.434 | U298: 0 | V298: 0 | W298: 0 | X298: 0 | Y298: 0 | Z298: 0 | AA298: =SUM(U298:Z298) -> 0 | AB298: 0 | AC298: 0 | AD298: 0 | AE298: 0 | AF298: 0 | AG298: 0 | AH298: =SUM(AB298:AG298) -> 0 | AI298: 石見
A299: 0000000090131 | B299: 土井屋 | C299: 0019 | D299: その他 | E299: =IFERROR(IF(INDEX(INDIRECT("'"&$AI299&"'!$E$2:$E$320"),MATCH($A299,INDIRECT("'"&$AI299&"'!$A$2:$A$320"),0))="","",INDEX(INDIRECT("'"&$AI299&"'!$E$2:$E$320"),MATCH($A299,INDIRECT("'"&$AI299&"'!$A$2:$A$320"),0))),"") | F299: =IF($E299="","",IFERROR(INDEX(担当者マスタ!$B$2:$B$101,MATCH($E299,担当者マスタ!$A$2:$A$101,0)),"※マスタ未登録")) | G299: 0 | H299: 0 | I299: 9.81 | J299: 0 | K299: 0 | L299: 0 | M299: =SUM(G299:L299) -> 9.81 | N299: 0 | O299: 0 | P299: 2.123 | Q299: 0 | R299: 0 | S299: 0 | T299: =SUM(N299:S299) -> 2.123 | U299: 0 | V299: 0 | W299: 0 | X299: 0 | Y299: 0 | Z299: 0 | AA299: =SUM(U299:Z299) -> 0 | AB299: 0 | AC299: 0 | AD299: 0 | AE299: 0 | AF299: 0 | AG299: 0 | AH299: =SUM(AB299:AG299) -> 0 | AI299: 石見
A300: 0000000100601 | B300: 大下船具店 *ﾚｼﾞ* | C300: 0019 | D300: その他 | E300: =IFERROR(IF(INDEX(INDIRECT("'"&$AI300&"'!$E$2:$E$320"),MATCH($A300,INDIRECT("'"&$AI300&"'!$A$2:$A$320"),0))="","",INDEX(INDIRECT("'"&$AI300&"'!$E$2:$E$320"),MATCH($A300,INDIRECT("'"&$AI300&"'!$A$2:$A$320"),0))),"") | F300: =IF($E300="","",IFERROR(INDEX(担当者マスタ!$B$2:$B$101,MATCH($E300,担当者マスタ!$A$2:$A$101,0)),"※マスタ未登録")) | G300: 3.5 | H300: 0 | I300: 0 | J300: 0 | K300: 0 | L300: 4.22 | M300: =SUM(G300:L300) -> 7.72 | N300: 2.27 | O300: 0 | P300: 0 | Q300: 0 | R300: 0 | S300: 2.99 | T300: =SUM(N300:S300) -> 5.26 | U300: 0 | V300: 0 | W300: 0 | X300: 0 | Y300: 0 | Z300: 0 | AA300: =SUM(U300:Z300) -> 0 | AB300: 0 | AC300: 0 | AD300: 0 | AE300: 0 | AF300: 0 | AG300: 0 | AH300: =SUM(AB300:AG300) -> 0 | AI300: 石見
A301: 0000000100751 | B301: くいしん坊 *ﾚｼﾞ* | C301: 0019 | D301: その他 | E301: =IFERROR(IF(INDEX(INDIRECT("'"&$AI301&"'!$E$2:$E$320"),MATCH($A301,INDIRECT("'"&$AI301&"'!$A$2:$A$320"),0))="","",INDEX(INDIRECT("'"&$AI301&"'!$E$2:$E$320"),MATCH($A301,INDIRECT("'"&$AI301&"'!$A$2:$A$320"),0))),"") | F301: =IF($E301="","",IFERROR(INDEX(担当者マスタ!$B$2:$B$101,MATCH($E301,担当者マスタ!$A$2:$A$101,0)),"※マスタ未登録")) | G301: 0 | H301: 0 | I301: 0 | J301: 0 | K301: 0 | L301: 0 | M301: =SUM(G301:L301) -> 0 | N301: 0 | O301: 0 | P301: 0 | Q301: 0 | R301: 0 | S301: 0 | T301: =SUM(N301:S301) -> 0 | U301: 0 | V301: 0 | W301: 0 | X301: 13.12 | Y301: 0 | Z301: 0 | AA301: =SUM(U301:Z301) -> 13.12 | AB301: 0 | AC301: 0 | AD301: 0 | AE301: 4.12 | AF301: 0 | AG301: 0 | AH301: =SUM(AB301:AG301) -> 4.12 | AI301: 石見
A302: 0000000101101 | B302: ｽｰﾊﾟｰさいとう | C302: 0019 | D302: その他 | E302: =IFERROR(IF(INDEX(INDIRECT("'"&$AI302&"'!$E$2:$E$320"),MATCH($A302,INDIRECT("'"&$AI302&"'!$A$2:$A$320"),0))="","",INDEX(INDIRECT("'"&$AI302&"'!$E$2:$E$320"),MATCH($A302,INDIRECT("'"&$AI302&"'!$A$2:$A$320"),0))),"") | F302: =IF($E302="","",IFERROR(INDEX(担当者マスタ!$B$2:$B$101,MATCH($E302,担当者マスタ!$A$2:$A$101,0)),"※マスタ未登録")) | G302: 3.21 | H302: 5.378 | I302: 16 | J302: 7.52 | K302: 3.12 | L302: 8.82 | M302: =SUM(G302:L302) -> 44.048 | N302: 1.54 | O302: 2.644 | P302: 12.54 | Q302: 4.05 | R302: 2.22 | S302: 6.46 | T302: =SUM(N302:S302) -> 29.454 | U302: 15.193 | V302: 11.63 | W302: 0 | X302: 7.987 | Y302: 1.8 | Z302: 7.11 | AA302: =SUM(U302:Z302) -> 43.72 | AB302: 7.895 | AC302: 8.39 | AD302: 0 | AE302: 3.748 | AF302: 0.7 | AG302: 5.5 | AH302: =SUM(AB302:AG302) -> 26.233 | AI302: 石見
A303: 0000000120181 | B303: むさしの *ﾚｼﾞ* | C303: 0019 | D303: その他 | E303: =IFERROR(IF(INDEX(INDIRECT("'"&$AI303&"'!$E$2:$E$320"),MATCH($A303,INDIRECT("'"&$AI303&"'!$A$2:$A$320"),0))="","",INDEX(INDIRECT("'"&$AI303&"'!$E$2:$E$320"),MATCH($A303,INDIRECT("'"&$AI303&"'!$A$2:$A$320"),0))),"") | F303: =IF($E303="","",IFERROR(INDEX(担当者マスタ!$B$2:$B$101,MATCH($E303,担当者マスタ!$A$2:$A$101,0)),"※マスタ未登録")) | G303: 8.046 | H303: 0 | I303: 1.98 | J303: 0.8 | K303: 4.986 | L303: 16.304 | M303: =SUM(G303:L303) -> 32.116 | N303: 3.488 | O303: 0 | P303: 1.068 | Q303: 0.324 | R303: 2.347 | S303: 6.589 | T303: =SUM(N303:S303) -> 13.816 | U303: 6.84 | V303: 2.49 | W303: 7.84 | X303: 19.963 | Y303: 0 | Z303: 17.876 | AA303: =SUM(U303:Z303) -> 55.009 | AB303: 2.759 | AC303: 1.074 | AD303: 2.745 | AE303: 8.792 | AF303: 0 | AG303: 6.707 | AH303: =SUM(AB303:AG303) -> 22.077 | AI303: 石見
A304: 0000000190041 | B304: ｸﾞﾘｰﾝｽﾎﾟｯﾄF *ﾚｼﾞ* | C304: 0019 | D304: その他 | E304: =IFERROR(IF(INDEX(INDIRECT("'"&$AI304&"'!$E$2:$E$320"),MATCH($A304,INDIRECT("'"&$AI304&"'!$A$2:$A$320"),0))="","",INDEX(INDIRECT("'"&$AI304&"'!$E$2:$E$320"),MATCH($A304,INDIRECT("'"&$AI304&"'!$A$2:$A$320"),0))),"") | F304: =IF($E304="","",IFERROR(INDEX(担当者マスタ!$B$2:$B$101,MATCH($E304,担当者マスタ!$A$2:$A$101,0)),"※マスタ未登録")) | G304: 0 | H304: 0 | I304: 34.059 | J304: 0 | K304: 0 | L304: 26.039 | M304: =SUM(G304:L304) -> 60.098 | N304: 0 | O304: 0 | P304: 13.342 | Q304: 0 | R304: 0 | S304: 11.412 | T304: =SUM(N304:S304) -> 24.754 | U304: 17.085 | V304: 9.5 | W304: 30.438 | X304: 0 | Y304: 0 | Z304: 4.209 | AA304: =SUM(U304:Z304) -> 61.232 | AB304: 8.666 | AC304: 4.79 | AD304: 12.924 | AE304: 0 | AF304: 0 | AG304: 2.772 | AH304: =SUM(AB304:AG304) -> 29.152 | AI304: 石見
... A317: 0000000703521 | B317: 大田市ごみ袋 | C317: 0020 | D317: 自治体 | E317: =IFERROR(IF(INDEX(INDIRECT("'"&$AI317&"'!$E$2:$E$320"),MATCH($A317,INDIRECT("'"&$AI317&"'!$A$2:$A$320"),0))="","",INDEX(INDIRECT("'"&$AI317&"'!$E$2:$E$320"),MATCH($A317,INDIRECT("'"&$AI317&"'!$A$2:$A$320"),0))),"") | F317: =IF($E317="","",IFERROR(INDEX(担当者マスタ!$B$2:$B$101,MATCH($E317,担当者マスタ!$A$2:$A$101,0)),"※マスタ未登録")) | G317: 0 | H317: 0 | I317: 0 | J317: 0 | K317: 0 | L317: 0 | M317: =SUM(G317:L317) -> 0 | N317: 0 | O317: 0 | P317: 0 | Q317: 0 | R317: 0 | S317: 0 | T317: =SUM(N317:S317) -> 0 | U317: 0 | V317: 11222.8 | W317: 0 | X317: 0 | Y317: 0 | Z317: 0 | AA317: =SUM(U317:Z317) -> 11222.8 | AB317: 0 | AC317: 564.4 | AD317: 0 | AE317: 0 | AF317: 0 | AG317: 0 | AH317: =SUM(AB317:AG317) -> 564.4 | AI317: 石見
A318: 0000000100682 | B318: 深川養鶏田屋 | C318: 0021 | D318: 高橋所長 | E318: =IFERROR(IF(INDEX(INDIRECT("'"&$AI318&"'!$E$2:$E$121"),MATCH($A318,INDIRECT("'"&$AI318&"'!$A$2:$A$121"),0))="","",INDEX(INDIRECT("'"&$AI318&"'!$E$2:$E$121"),MATCH($A318,INDIRECT("'"&$AI318&"'!$A$2:$A$121"),0))),"") | F318: =IF($E318="","",IFERROR(INDEX(担当者マスタ!$B$2:$B$101,MATCH($E318,担当者マスタ!$A$2:$A$101,0)),"※マスタ未登録")) | G318: 627.274 | H318: 586.766 | I318: 636.98 | J318: 439.889 | K318: 558.988 | L318: 479.596 | M318: =SUM(G318:L318) -> 3329.493 | N318: 111.011 | O318: 102.985 | P318: 118.218 | Q318: 88.206 | R318: 105.834 | S318: 80.049 | T318: =SUM(N318:S318) -> 606.303 | U318: 666.94 | V318: 555.38 | W318: 750.908 | X318: 556.719 | Y318: 500.888 | Z318: 588.448 | AA318: =SUM(U318:Z318) -> 3619.283 | AB318: 128.876 | AC318: 107.97 | AD318: 148.097 | AE318: 110.398 | AF318: 91.165 | AG318: 105.138 | AH318: =SUM(AB318:AG318) -> 691.644 | AI318: 下関
A319: 0000000101112 | B319: ﾌｼﾞﾐﾂ㈱ | C319: 0021 | D319: 高橋所長 | E319: =IFERROR(IF(INDEX(INDIRECT("'"&$AI319&"'!$E$2:$E$121"),MATCH($A319,INDIRECT("'"&$AI319&"'!$A$2:$A$121"),0))="","",INDEX(INDIRECT("'"&$AI319&"'!$E$2:$E$121"),MATCH($A319,INDIRECT("'"&$AI319&"'!$A$2:$A$121"),0))),"") | F319: =IF($E319="","",IFERROR(INDEX(担当者マスタ!$B$2:$B$101,MATCH($E319,担当者マスタ!$A$2:$A$101,0)),"※マスタ未登録")) | G319: 0 | H319: 7.5 | I319: 0 | J319: 0 | K319: 0 | L319: 0 | M319: =SUM(G319:L319) -> 7.5 | N319: 0 | O319: 1.522 | P319: 0 | Q319: 0 | R319: 0 | S319: 0 | T319: =SUM(N319:S319) -> 1.522 | U319: 0 | V319: 0 | W319: 0 | X319: 0 | Y319: 0 | Z319: 0 | AA319: =SUM(U319:Z319) -> 0 | AB319: 0 | AC319: 0 | AD319: 0 | AE319: 0 | AF319: 0 | AG319: 0 | AH319: =SUM(AB319:AG319) -> 0 | AI319: 下関
A320: 0000000101202 | B320: ㈱ﾔﾏﾓ水産 | C320: 0021 | D320: 高橋所長 | E320: =IFERROR(IF(INDEX(INDIRECT("'"&$AI320&"'!$E$2:$E$121"),MATCH($A320,INDIRECT("'"&$AI320&"'!$A$2:$A$121"),0))="","",INDEX(INDIRECT("'"&$AI320&"'!$E$2:$E$121"),MATCH($A320,INDIRECT("'"&$AI320&"'!$A$2:$A$121"),0))),"") | F320: =IF($E320="","",IFERROR(INDEX(担当者マスタ!$B$2:$B$101,MATCH($E320,担当者マスタ!$A$2:$A$101,0)),"※マスタ未登録")) | G320: 2583.956 | H320: 4914.968 | I320: 5317.348 | J320: 1981.78 | K320: 1361.999 | L320: 1233.177 | M320: =SUM(G320:L320) -> 17393.228 | N320: 616.553 | O320: 1111.27 | P320: 1271.882 | Q320: 479.304 | R320: 275.037 | S320: 246.329 | T320: =SUM(N320:S320) -> 4000.375 | U320: 3265.723 | V320: 5615.846 | W320: 7145.665 | X320: 1999.467 | Y320: 1450.982 | Z320: 904.831 | AA320: =SUM(U320:Z320) -> 20382.514 | AB320: 763.622 | AC320: 1293.181 | AD320: 1656.737 | AE320: 424.358 | AF320: 305.558 | AG320: 181.14 | AH320: =SUM(AB320:AG320) -> 4624.596 | AI320: 下関
A321: 0000000101232 | B321: (有)森本商店 | C321: 0021 | D321: 高橋所長 | E321: =IFERROR(IF(INDEX(INDIRECT("'"&$AI321&"'!$E$2:$E$121"),MATCH($A321,INDIRECT("'"&$AI321&"'!$A$2:$A$121"),0))="","",INDEX(INDIRECT("'"&$AI321&"'!$E$2:$E$121"),MATCH($A321,INDIRECT("'"&$AI321&"'!$A$2:$A$121"),0))),"") | F321: =IF($E321="","",IFERROR(INDEX(担当者マスタ!$B$2:$B$101,MATCH($E321,担当者マスタ!$A$2:$A$101,0)),"※マスタ未登録")) | G321: 42.24 | H321: 131.38 | I321: 148.94 | J321: 10.56 | K321: 120.92 | L321: 31.68 | M321: =SUM(G321:L321) -> 485.72 | N321: 7.04 | O321: 28.592 | P321: 39.94 | Q321: 1.76 | R321: 33.24 | S321: 5.28 | T321: =SUM(N321:S321) -> 115.852 | U321: 35.312 | V321: 158.49 | W321: 432.92 | X321: 86.16 | Y321: 28.49 | Z321: 99.14 | AA321: =SUM(U321:Z321) -> 840.512 | AB321: 7.072 | AC321: 40.9 | AD321: 115.4 | AE321: 23.18 | AF321: 5.71 | AG321: 27.09 | AH321: =SUM(AB321:AG321) -> 219.352 | AI321: 下関
A322: 0000000101242 | B322: (有)海人 門司港本店 | C322: 0021 | D322: 高橋所長 | E322: =IFERROR(IF(INDEX(INDIRECT("'"&$AI322&"'!$E$2:$E$121"),MATCH($A322,INDIRECT("'"&$AI322&"'!$A$2:$A$121"),0))="","",INDEX(INDIRECT("'"&$AI322&"'!$E$2:$E$121"),MATCH($A322,INDIRECT("'"&$AI322&"'!$A$2:$A$121"),0))),"") | F322: =IF($E322="","",IFERROR(INDEX(担当者マスタ!$B$2:$B$101,MATCH($E322,担当者マスタ!$A$2:$A$101,0)),"※マスタ未登録")) | G322: 21.6 | H322: 0 | I322: 62.7 | J322: 24.98 | K322: 21.6 | L322: 0 | M322: =SUM(G322:L322) -> 130.88 | N322: 6.99 | O322: 0 | P322: 7.224 | Q322: 7.2 | R322: 6.99 | S322: 0 | T322: =SUM(N322:S322) -> 28.404 | U322: 0 | V322: 0 | W322: 42.78 | X322: 46.88 | Y322: 0 | Z322: 0 | AA322: =SUM(U322:Z322) -> 89.66 | AB322: 0 | AC322: 0 | AD322: 7.609 | AE322: 14.19 | AF322: 0 | AG322: 0 | AH322: =SUM(AB322:AG322) -> 21.799 | AI322: 下関
A323: 0000000101272 | B323: 海転からと市場寿司 | C323: 0021 | D323: 高橋所長 | E323: =IFERROR(IF(INDEX(INDIRECT("'"&$AI323&"'!$E$2:$E$121"),MATCH($A323,INDIRECT("'"&$AI323&"'!$A$2:$A$121"),0))="","",INDEX(INDIRECT("'"&$AI323&"'!$E$2:$E$121"),MATCH($A323,INDIRECT("'"&$AI323&"'!$A$2:$A$121"),0))),"") | F323: =IF($E323="","",IFERROR(INDEX(担当者マスタ!$B$2:$B$101,MATCH($E323,担当者マスタ!$A$2:$A$101,0)),"※マスタ未登録")) | G323: 0 | H323: 0 | I323: 0 | J323: 0 | K323: 0 | L323: 0 | M323: =SUM(G323:L323) -> 0 | N323: 0 | O323: 0 | P323: 0 | Q323: 0 | R323: 0 | S323: 0 | T323: =SUM(N323:S323) -> 0 | U323: 13.62 | V323: 0 | W323: 0 | X323: 0 | Y323: 0 | Z323: 0 | AA323: =SUM(U323:Z323) -> 13.62 | AB323: 4.32 | AC323: 0 | AD323: 0 | AE323: 0 | AF323: 0 | AG323: 0 | AH323: =SUM(AB323:AG323) -> 4.32 | AI323: 下関
A324: 0000000101752 | B324: (有)萩陶苑 | C324: 0021 | D324: 高橋所長 | E324: =IFERROR(IF(INDEX(INDIRECT("'"&$AI324&"'!$E$2:$E$121"),MATCH($A324,INDIRECT("'"&$AI324&"'!$A$2:$A$121"),0))="","",INDEX(INDIRECT("'"&$AI324&"'!$E$2:$E$121"),MATCH($A324,INDIRECT("'"&$AI324&"'!$A$2:$A$121"),0))),"") | F324: =IF($E324="","",IFERROR(INDEX(担当者マスタ!$B$2:$B$101,MATCH($E324,担当者マスタ!$A$2:$A$101,0)),"※マスタ未登録")) | G324: 86.409 | H324: 50.322 | I324: 244.57 | J324: 0 | K324: 109.831 | L324: 276.201 | M324: =SUM(G324:L324) -> 767.333 | N324: 23.722 | O324: 13.597 | P324: 66.994 | Q324: 0 | R324: 30.847 | S324: 76.645 | T324: =SUM(N324:S324) -> 211.805 | U324: 83.827 | V324: 51.25 | W324: 206.802 | X324: 109.442 | Y324: 159.463 | Z324: 126.015 | AA324: =SUM(U324:Z324) -> 736.799 | AB324: 24.306 | AC324: 13.41 | AD324: 58.163 | AE324: 30.106 | AF324: 44.727 | AG324: 36.636 | AH324: =SUM(AB324:AG324) -> 207.348 | AI324: 下関
A325: 0000000101762 | B325: ㈱ﾅｶｵ | C325: 0021 | D325: 高橋所長 | E325: =IFERROR(IF(INDEX(INDIRECT("'"&$AI325&"'!$E$2:$E$121"),MATCH($A325,INDIRECT("'"&$AI325&"'!$A$2:$A$121"),0))="","",INDEX(INDIRECT("'"&$AI325&"'!$E$2:$E$121"),MATCH($A325,INDIRECT("'"&$AI325&"'!$A$2:$A$121"),0))),"") | F325: =IF($E325="","",IFERROR(INDEX(担当者マスタ!$B$2:$B$101,MATCH($E325,担当者マスタ!$A$2:$A$101,0)),"※マスタ未登録")) | G325: 90.048 | H325: 346.4 | I325: 30 | J325: 187 | K325: 159 | L325: 136.526 | M325: =SUM(G325:L325) -> 948.974 | N325: 20.824 | O325: 68.72 | P325: 7 | Q325: 34.5 | R325: 30.2 | S325: 30.896 | T325: =SUM(N325:S325) -> 192.14 | U325: 225.584 | V325: 51 | W325: 136.2 | X325: 244.47 | Y325: 166.2 | Z325: 473.95 | AA325: =SUM(U325:Z325) -> 1297.404 | AB325: 47.204 | AC325: 8 | AD325: 30.2 | AE325: 53.82 | AF325: 36.3 | AG325: 104.63 | AH325: =SUM(AB325:AG325) -> 280.154 | AI325: 下関
A326: 0000000101972 | B326: 山陽食品工業㈱ | C326: 0021 | D326: 高橋所長 | E326: =IFERROR(IF(INDEX(INDIRECT("'"&$AI326&"'!$E$2:$E$121"),MATCH($A326,INDIRECT("'"&$AI326&"'!$A$2:$A$121"),0))="","",INDEX(INDIRECT("'"&$AI326&"'!$E$2:$E$121"),MATCH($A326,INDIRECT("'"&$AI326&"'!$A$2:$A$121"),0))),"") | F326: =IF($E326="","",IFERROR(INDEX(担当者マスタ!$B$2:$B$101,MATCH($E326,担当者マスタ!$A$2:$A$101,0)),"※マスタ未登録")) | G326: 2243.321 | H326: 1971.139 | I326: 1782.016 | J326: 1355.819 | K326: 1429.735 | L326: 2072.647 | M326: =SUM(G326:L326) -> 10854.677 | N326: 506.575 | O326: 458.214 | P326: 415.525 | Q326: 297.15 | R326: 312.246 | S326: 452.533 | T326: =SUM(N326:S326) -> 2442.243 | U326: 1897.326 | V326: 1752.698 | W326: 2138.748 | X326: 1387.22 | Y326: 1521.007 | Z326: 1888.689 | AA326: =SUM(U326:Z326) -> 10585.688 | AB326: 448.308 | AC326: 415.46 | AD326: 484.266 | AE326: 302.932 | AF326: 319.391 | AG326: 390.061 | AH326: =SUM(AB326:AG326) -> 2360.418 | AI326: 下関
A327: 0000000102102 | B327: ㈱土晃 | C327: 0021 | D327: 高橋所長 | E327: =IFERROR(IF(INDEX(INDIRECT("'"&$AI327&"'!$E$2:$E$121"),MATCH($A327,INDIRECT("'"&$AI327&"'!$A$2:$A$121"),0))="","",INDEX(INDIRECT("'"&$AI327&"'!$E$2:$E$121"),MATCH($A327,INDIRECT("'"&$AI327&"'!$A$2:$A$121"),0))),"") | F327: =IF($E327="","",IFERROR(INDEX(担当者マスタ!$B$2:$B$101,MATCH($E327,担当者マスタ!$A$2:$A$101,0)),"※マスタ未登録")) | G327: 0 | H327: 0 | I327: 0 | J327: 0 | K327: 0 | L327: 118.65 | M327: =SUM(G327:L327) -> 118.65 | N327: 0 | O327: 0 | P327: 0 | Q327: 0 | R327: 0 | S327: 30.45 | T327: =SUM(N327:S327) -> 30.45 | U327: 0 | V327: 0 | W327: 0 | X327: 0 | Y327: 0 | Z327: 0 | AA327: =SUM(U327:Z327) -> 0 | AB327: 0 | AC327: 0 | AD327: 0 | AE327: 0 | AF327: 0 | AG327: 0 | AH327: =SUM(AB327:AG327) -> 0 | AI327: 下関
A328: 0000000102302 | B328: ㈱山京 | C328: 0021 | D328: 高橋所長 | E328: =IFERROR(IF(INDEX(INDIRECT("'"&$AI328&"'!$E$2:$E$121"),MATCH($A328,INDIRECT("'"&$AI328&"'!$A$2:$A$121"),0))="","",INDEX(INDIRECT("'"&$AI328&"'!$E$2:$E$121"),MATCH($A328,INDIRECT("'"&$AI328&"'!$A$2:$A$121"),0))),"") | F328: =IF($E328="","",IFERROR(INDEX(担当者マスタ!$B$2:$B$101,MATCH($E328,担当者マスタ!$A$2:$A$101,0)),"※マスタ未登録")) | G328: 0 | H328: 0 | I328: 22.2 | J328: 0 | K328: 0 | L328: 0 | M328: =SUM(G328:L328) -> 22.2 | N328: 0 | O328: 0 | P328: 4.695 | Q328: 0 | R328: 0 | S328: 0 | T328: =SUM(N328:S328) -> 4.695 | U328: 0 | V328: 23.975 | W328: 0 | X328: 0 | Y328: 0 | Z328: 23.975 | AA328: =SUM(U328:Z328) -> 47.95 | AB328: 0 | AC328: 5.594 | AD328: 0 | AE328: 0 | AF328: 0 | AG328: 5.594 | AH328: =SUM(AB328:AG328) -> 11.188 | AI328: 下関
A329: 0000000102492 | B329: (協)萩大井浦加工場 | C329: 0021 | D329: 高橋所長 | E329: =IFERROR(IF(INDEX(INDIRECT("'"&$AI329&"'!$E$2:$E$121"),MATCH($A329,INDIRECT("'"&$AI329&"'!$A$2:$A$121"),0))="","",INDEX(INDIRECT("'"&$AI329&"'!$E$2:$E$121"),MATCH($A329,INDIRECT("'"&$AI329&"'!$A$2:$A$121"),0))),"") | F329: =IF($E329="","",IFERROR(INDEX(担当者マスタ!$B$2:$B$101,MATCH($E329,担当者マスタ!$A$2:$A$101,0)),"※マスタ未登録")) | G329: 1724.145 | H329: 1335.487 | I329: 1915.001 | J329: 1205.26 | K329: 1177.54 | L329: 1422.668 | M329: =SUM(G329:L329) -> 8780.101 | N329: 470.723 | O329: 370.242 | P329: 463.538 | Q329: 276.744 | R329: 281.906 | S329: 371.531 | T329: =SUM(N329:S329) -> 2234.684 | U329: 1149.225 | V329: 729.05 | W329: 999.905 | X329: 479.54 | Y329: 387.624 | Z329: 650.449 | AA329: =SUM(U329:Z329) -> 4395.793 | AB329: 279.047 | AC329: 155.947 | AD329: 217.056 | AE329: 133.83 | AF329: 91.77 | AG329: 113.81 | AH329: =SUM(AB329:AG329) -> 991.46 | AI329: 下関
... A431: 0000000100812 | B431: 上様 | C431: 0029 | D431: その他 | E431: =IFERROR(IF(INDEX(INDIRECT("'"&$AI431&"'!$E$2:$E$121"),MATCH($A431,INDIRECT("'"&$AI431&"'!$A$2:$A$121"),0))="","",INDEX(INDIRECT("'"&$AI431&"'!$E$2:$E$121"),MATCH($A431,INDIRECT("'"&$AI431&"'!$A$2:$A$121"),0))),"") | F431: =IF($E431="","",IFERROR(INDEX(担当者マスタ!$B$2:$B$101,MATCH($E431,担当者マスタ!$A$2:$A$101,0)),"※マスタ未登録")) | G431: 0 | H431: 0 | I431: 4.8 | J431: 0 | K431: 0 | L431: 0 | M431: =SUM(G431:L431) -> 4.8 | N431: 0 | O431: 0 | P431: 1.68 | Q431: 0 | R431: 0 | S431: 0 | T431: =SUM(N431:S431) -> 1.68 | U431: 0 | V431: 0 | W431: 13.5 | X431: 0 | Y431: 0 | Z431: 5.1 | AA431: =SUM(U431:Z431) -> 18.6 | AB431: 0 | AC431: 0 | AD431: 4.5 | AE431: 0 | AF431: 0 | AG431: 0.9 | AH431: =SUM(AB431:AG431) -> 5.4 | AI431: 下関
A432: 0000000000043 | B432: JFしまね本所総務部 | C432: 0031 | D432: JF境 | E432: =IFERROR(IF(INDEX(INDIRECT("'"&$AI432&"'!$E$2:$E$118"),MATCH($A432,INDIRECT("'"&$AI432&"'!$A$2:$A$118"),0))="","",INDEX(INDIRECT("'"&$AI432&"'!$E$2:$E$118"),MATCH($A432,INDIRECT("'"&$AI432&"'!$A$2:$A$118"),0))),"") | F432: =IF($E432="","",IFERROR(INDEX(担当者マスタ!$B$2:$B$101,MATCH($E432,担当者マスタ!$A$2:$A$101,0)),"※マスタ未登録")) | G432: 0 | H432: 0 | I432: 0 | J432: 0 | K432: 0 | L432: 0 | M432: =SUM(G432:L432) -> 0 | N432: 0 | O432: 0 | P432: 0 | Q432: 0 | R432: 0 | S432: 0 | T432: =SUM(N432:S432) -> 0 | U432: 86 | V432: 0 | W432: 0 | X432: 0 | Y432: 0 | Z432: 0 | AA432: =SUM(U432:Z432) -> 86 | AB432: 18.8 | AC432: 0 | AD432: 0 | AE432: 0 | AF432: 0 | AG432: 0 | AH432: =SUM(AB432:AG432) -> 18.8 | AI432: 水産部X
A433: 0000000101293 | B433: JFしまね購買部購買課 | C433: 0031 | D433: JF境 | E433: =IFERROR(IF(INDEX(INDIRECT("'"&$AI433&"'!$E$2:$E$118"),MATCH($A433,INDIRECT("'"&$AI433&"'!$A$2:$A$118"),0))="","",INDEX(INDIRECT("'"&$AI433&"'!$E$2:$E$118"),MATCH($A433,INDIRECT("'"&$AI433&"'!$A$2:$A$118"),0))),"") | F433: =IF($E433="","",IFERROR(INDEX(担当者マスタ!$B$2:$B$101,MATCH($E433,担当者マスタ!$A$2:$A$101,0)),"※マスタ未登録")) | G433: 14712.216 | H433: 11725.807 | I433: 7290.434 | J433: 10119.517 | K433: 7444.632 | L433: 13124.855 | M433: =SUM(G433:L433) -> 64417.461 | N433: 2351.322 | O433: 2302.986 | P433: 1294.6 | Q433: 1794.514 | R433: 1168.471 | S433: 1962.078 | T433: =SUM(N433:S433) -> 10873.971 | U433: 19329.169 | V433: 14724.818 | W433: 11926.7 | X433: 3662.924 | Y433: 8960.96 | Z433: 18624.798 | AA433: =SUM(U433:Z433) -> 77229.369 | AB433: 4171.382 | AC433: 3372.675 | AD433: 2702.494 | AE433: 789.899 | AF433: 1917.207 | AG433: 3597.906 | AH433: =SUM(AB433:AG433) -> 16551.563 | AI433: 水産部X
A434: 0000000010013 | B434: ㈱まつした米子 | C434: 0032 | D434: 飯塚 | E434: =IFERROR(IF(INDEX(INDIRECT("'"&$AI434&"'!$E$2:$E$327"),MATCH($A434,INDIRECT("'"&$AI434&"'!$A$2:$A$327"),0))="","",INDEX(INDIRECT("'"&$AI434&"'!$E$2:$E$327"),MATCH($A434,INDIRECT("'"&$AI434&"'!$A$2:$A$327"),0))),"") | F434: =IF($E434="","",IFERROR(INDEX(担当者マスタ!$B$2:$B$101,MATCH($E434,担当者マスタ!$A$2:$A$101,0)),"※マスタ未登録")) | G434: 7.225 | H434: 23.4 | I434: 23.4 | J434: 0 | K434: 18.925 | L434: 23.4 | M434: =SUM(G434:L434) -> 96.35 | N434: 1.015 | O434: 3.24 | P434: 1.44 | Q434: 0 | R434: 1.735 | S434: 1.44 | T434: =SUM(N434:S434) -> 8.87 | U434: 11.7 | V434: 22.11 | W434: 42.325 | X434: 0 | Y434: 18.925 | Z434: 35.1 | AA434: =SUM(U434:Z434) -> 130.16 | AB434: 0.72 | AC434: 2.49 | AD434: 3.175 | AE434: 0 | AF434: 1.735 | AG434: 2.16 | AH434: =SUM(AB434:AG434) -> 10.28 | AI434: 松江・境港
A435: 0000000034103 | B435: (株)岡田本店生花 | C435: 0032 | D435: 飯塚 | E435: =IFERROR(IF(INDEX(INDIRECT("'"&$AI435&"'!$E$2:$E$327"),MATCH($A435,INDIRECT("'"&$AI435&"'!$A$2:$A$327"),0))="","",INDEX(INDIRECT("'"&$AI435&"'!$E$2:$E$327"),MATCH($A435,INDIRECT("'"&$AI435&"'!$A$2:$A$327"),0))),"") | F435: =IF($E435="","",IFERROR(INDEX(担当者マスタ!$B$2:$B$101,MATCH($E435,担当者マスタ!$A$2:$A$101,0)),"※マスタ未登録")) | G435: 20.64 | H435: 39.6 | I435: 78 | J435: 16.6 | K435: 57.55 | L435: 73 | M435: =SUM(G435:L435) -> 285.39 | N435: 4.28 | O435: 9.585 | P435: 16.53 | Q435: 3.786 | R435: 12.6 | S435: 15.824 | T435: =SUM(N435:S435) -> 62.605 | U435: 18.45 | V435: 0 | W435: 0 | X435: 0 | Y435: 0 | Z435: 0 | AA435: =SUM(U435:Z435) -> 18.45 | AB435: 4.238 | AC435: 0 | AD435: 0 | AE435: 0 | AF435: 0 | AG435: 0 | AH435: =SUM(AB435:AG435) -> 4.238 | AI435: 松江・境港
A436: 0000000039023 | B436: ㈱米吾(共管費)030 | C436: 0032 | D436: 飯塚 | E436: =IFERROR(IF(INDEX(INDIRECT("'"&$AI436&"'!$E$2:$E$327"),MATCH($A436,INDIRECT("'"&$AI436&"'!$A$2:$A$327"),0))="","",INDEX(INDIRECT("'"&$AI436&"'!$E$2:$E$327"),MATCH($A436,INDIRECT("'"&$AI436&"'!$A$2:$A$327"),0))),"") | F436: =IF($E436="","",IFERROR(INDEX(担当者マスタ!$B$2:$B$101,MATCH($E436,担当者マスタ!$A$2:$A$101,0)),"※マスタ未登録")) | G436: 0 | H436: 0 | I436: 4.8 | J436: 0 | K436: 3.63 | L436: 3.63 | M436: =SUM(G436:L436) -> 12.06 | N436: 0 | O436: 0 | P436: 0.45 | Q436: 0 | R436: 0.73 | S436: 0.73 | T436: =SUM(N436:S436) -> 1.91 | U436: 0 | V436: 0 | W436: 0 | X436: 0 | Y436: 0 | Z436: 3.3 | AA436: =SUM(U436:Z436) -> 3.3 | AB436: 0 | AC436: 0 | AD436: 0 | AE436: 0 | AF436: 0 | AG436: 0.66 | AH436: =SUM(AB436:AG436) -> 0.66 | AI436: 松江・境港
A437: 0000000039033 | B437: ㈱米吾(厚生会)006 | C437: 0032 | D437: 飯塚 | E437: =IFERROR(IF(INDEX(INDIRECT("'"&$AI437&"'!$E$2:$E$327"),MATCH($A437,INDIRECT("'"&$AI437&"'!$A$2:$A$327"),0))="","",INDEX(INDIRECT("'"&$AI437&"'!$E$2:$E$327"),MATCH($A437,INDIRECT("'"&$AI437&"'!$A$2:$A$327"),0))),"") | F437: =IF($E437="","",IFERROR(INDEX(担当者マスタ!$B$2:$B$101,MATCH($E437,担当者マスタ!$A$2:$A$101,0)),"※マスタ未登録")) | G437: 9.6 | H437: 0 | I437: 0 | J437: 0 | K437: 0 | L437: 0 | M437: =SUM(G437:L437) -> 9.6 | N437: 0.9 | O437: 0 | P437: 0 | Q437: 0 | R437: 0 | S437: 0 | T437: =SUM(N437:S437) -> 0.9 | U437: 0 | V437: 0 | W437: 0 | X437: 0 | Y437: 0 | Z437: 0 | AA437: =SUM(U437:Z437) -> 0 | AB437: 0 | AC437: 0 | AD437: 0 | AE437: 0 | AF437: 0 | AG437: 0 | AH437: =SUM(AB437:AG437) -> 0 | AI437: 松江・境港
A438: 0000000100203 | B438: (有)ﾋﾟｰｹｨｼｰ | C438: 0032 | D438: 飯塚 | E438: =IFERROR(IF(INDEX(INDIRECT("'"&$AI438&"'!$E$2:$E$327"),MATCH($A438,INDIRECT("'"&$AI438&"'!$A$2:$A$327"),0))="","",INDEX(INDIRECT("'"&$AI438&"'!$E$2:$E$327"),MATCH($A438,INDIRECT("'"&$AI438&"'!$A$2:$A$327"),0))),"") | F438: =IF($E438="","",IFERROR(INDEX(担当者マスタ!$B$2:$B$101,MATCH($E438,担当者マスタ!$A$2:$A$101,0)),"※マスタ未登録")) | G438: 1371.91 | H438: 1256.094 | I438: 1626.56 | J438: 1406.29 | K438: 576.98 | L438: 1431.969 | M438: =SUM(G438:L438) -> 7669.803 | N438: 421.462 | O438: 442.378 | P438: 566.97 | Q438: 462.864 | R438: 181.711 | S438: 465.614 | T438: =SUM(N438:S438) -> 2540.999 | U438: 1341.002 | V438: 589.964 | W438: 1582.672 | X438: 1421.844 | Y438: 652.276 | Z438: 582.644 | AA438: =SUM(U438:Z438) -> 6170.402 | AB438: 416.824 | AC438: 193.7 | AD438: 492.898 | AE438: 375.356 | AF438: 207.898 | AG438: 193.028 | AH438: =SUM(AB438:AG438) -> 1879.704 | AI438: 松江・境港
A439: 0000000100673 | B439: ㈱味屋ｺｰﾎﾟﾚｰｼｮﾝ | C439: 0032 | D439: 飯塚 | E439: =IFERROR(IF(INDEX(INDIRECT("'"&$AI439&"'!$E$2:$E$327"),MATCH($A439,INDIRECT("'"&$AI439&"'!$A$2:$A$327"),0))="","",INDEX(INDIRECT("'"&$AI439&"'!$E$2:$E$327"),MATCH($A439,INDIRECT("'"&$AI439&"'!$A$2:$A$327"),0))),"") | F439: =IF($E439="","",IFERROR(INDEX(担当者マスタ!$B$2:$B$101,MATCH($E439,担当者マスタ!$A$2:$A$101,0)),"※マスタ未登録")) | G439: 0 | H439: 0 | I439: 0 | J439: 0 | K439: 0 | L439: 0 | M439: =SUM(G439:L439) -> 0 | N439: 0 | O439: 0 | P439: 0 | Q439: 0 | R439: 0 | S439: 0 | T439: =SUM(N439:S439) -> 0 | U439: 7.08 | V439: 0 | W439: 0 | X439: 0 | Y439: 0 | Z439: 0 | AA439: =SUM(U439:Z439) -> 7.08 | AB439: 3.312 | AC439: 0 | AD439: 0 | AE439: 0 | AF439: 0 | AG439: 0 | AH439: =SUM(AB439:AG439) -> 3.312 | AI439: 松江・境港
A440: 0000000101063 | B440: 東亜産業(有) | C440: 0032 | D440: 飯塚 | E440: =IFERROR(IF(INDEX(INDIRECT("'"&$AI440&"'!$E$2:$E$327"),MATCH($A440,INDIRECT("'"&$AI440&"'!$A$2:$A$327"),0))="","",INDEX(INDIRECT("'"&$AI440&"'!$E$2:$E$327"),MATCH($A440,INDIRECT("'"&$AI440&"'!$A$2:$A$327"),0))),"") | F440: =IF($E440="","",IFERROR(INDEX(担当者マスタ!$B$2:$B$101,MATCH($E440,担当者マスタ!$A$2:$A$101,0)),"※マスタ未登録")) | G440: 0 | H440: 20.7 | I440: 0 | J440: 0 | K440: 0 | L440: 0 | M440: =SUM(G440:L440) -> 20.7 | N440: 0 | O440: 3.75 | P440: 0 | Q440: 0 | R440: 0 | S440: 0 | T440: =SUM(N440:S440) -> 3.75 | U440: 0 | V440: 0 | W440: 0 | X440: 0 | Y440: 0 | Z440: 20.7 | AA440: =SUM(U440:Z440) -> 20.7 | AB440: 0 | AC440: 0 | AD440: 0 | AE440: 0 | AF440: 0 | AG440: 3.75 | AH440: =SUM(AB440:AG440) -> 3.75 | AI440: 松江・境港
A441: 0000000102203 | B441: 岸本和久 | C441: 0032 | D441: 飯塚 | E441: =IFERROR(IF(INDEX(INDIRECT("'"&$AI441&"'!$E$2:$E$327"),MATCH($A441,INDIRECT("'"&$AI441&"'!$A$2:$A$327"),0))="","",INDEX(INDIRECT("'"&$AI441&"'!$E$2:$E$327"),MATCH($A441,INDIRECT("'"&$AI441&"'!$A$2:$A$327"),0))),"") | F441: =IF($E441="","",IFERROR(INDEX(担当者マスタ!$B$2:$B$101,MATCH($E441,担当者マスタ!$A$2:$A$101,0)),"※マスタ未登録")) | G441: 0 | H441: 0 | I441: 0 | J441: 0 | K441: 0 | L441: 0 | M441: =SUM(G441:L441) -> 0 | N441: 0 | O441: 0 | P441: 0 | Q441: 0 | R441: 0 | S441: 0 | T441: =SUM(N441:S441) -> 0 | U441: 0 | V441: 40.5 | W441: 0 | X441: 0 | Y441: 0 | Z441: 0 | AA441: =SUM(U441:Z441) -> 40.5 | AB441: 0 | AC441: 12 | AD441: 0 | AE441: 0 | AF441: 0 | AG441: 0 | AH441: =SUM(AB441:AG441) -> 12 | AI441: 松江・境港
A442: 0000000102553 | B442: ﾜｰｸｾﾝﾀｰほほえみ | C442: 0032 | D442: 飯塚 | E442: =IFERROR(IF(INDEX(INDIRECT("'"&$AI442&"'!$E$2:$E$327"),MATCH($A442,INDIRECT("'"&$AI442&"'!$A$2:$A$327"),0))="","",INDEX(INDIRECT("'"&$AI442&"'!$E$2:$E$327"),MATCH($A442,INDIRECT("'"&$AI442&"'!$A$2:$A$327"),0))),"") | F442: =IF($E442="","",IFERROR(INDEX(担当者マスタ!$B$2:$B$101,MATCH($E442,担当者マスタ!$A$2:$A$101,0)),"※マスタ未登録")) | G442: 128.58 | H442: 0 | I442: 0 | J442: 0 | K442: 0 | L442: 0 | M442: =SUM(G442:L442) -> 128.58 | N442: 37.28 | O442: 0 | P442: 0 | Q442: 0 | R442: 0 | S442: 0 | T442: =SUM(N442:S442) -> 37.28 | U442: 0 | V442: 0 | W442: 0 | X442: 0 | Y442: 0 | Z442: 0 | AA442: =SUM(U442:Z442) -> 0 | AB442: 0 | AC442: 0 | AD442: 0 | AE442: 0 | AF442: 0 | AG442: 0 | AH442: =SUM(AB442:AG442) -> 0 | AI442: 松江・境港
A443: 0000000103293 | B443: ㈲岡田商店本店(資材) | C443: 0032 | D443: 飯塚 | E443: =IFERROR(IF(INDEX(INDIRECT("'"&$AI443&"'!$E$2:$E$327"),MATCH($A443,INDIRECT("'"&$AI443&"'!$A$2:$A$327"),0))="","",INDEX(INDIRECT("'"&$AI443&"'!$E$2:$E$327"),MATCH($A443,INDIRECT("'"&$AI443&"'!$A$2:$A$327"),0))),"") | F443: =IF($E443="","",IFERROR(INDEX(担当者マスタ!$B$2:$B$101,MATCH($E443,担当者マスタ!$A$2:$A$101,0)),"※マスタ未登録")) | G443: 1547.564 | H443: 1406 | I443: 1615.548 | J443: 863.426 | K443: 1042.139 | L443: 1264.186 | M443: =SUM(G443:L443) -> 7738.863 | N443: 623.457 | O443: 527.519 | P443: 603.989 | Q443: 321.099 | R443: 387.532 | S443: 470.47 | T443: =SUM(N443:S443) -> 2934.066 | U443: 1326.714 | V443: 2443.521 | W443: 3792.533 | X443: 1392.358 | Y443: 1962.283 | Z443: 2334.544 | AA443: =SUM(U443:Z443) -> 13251.953 | AB443: 506.714 | AC443: 903.301 | AD443: 1382.363 | AE443: 517.465 | AF443: 731.053 | AG443: 867.793 | AH443: =SUM(AB443:AG443) -> 4908.689 | AI443: 松江・境港
A444: 0000000103383 | B444: ㈲こめや産業本社工場 | C444: 0032 | D444: 飯塚 | E444: =IFERROR(IF(INDEX(INDIRECT("'"&$AI444&"'!$E$2:$E$327"),MATCH($A444,INDIRECT("'"&$AI444&"'!$A$2:$A$327"),0))="","",INDEX(INDIRECT("'"&$AI444&"'!$E$2:$E$327"),MATCH($A444,INDIRECT("'"&$AI444&"'!$A$2:$A$327"),0))),"") | F444: =IF($E444="","",IFERROR(INDEX(担当者マスタ!$B$2:$B$101,MATCH($E444,担当者マスタ!$A$2:$A$101,0)),"※マスタ未登録")) | G444: 1191.935 | H444: 1112.696 | I444: 2205.124 | J444: 890.156 | K444: 648.212 | L444: 857.469 | M444: =SUM(G444:L444) -> 6905.592 | N444: 376.384 | O444: 342.913 | P444: 654.786 | Q444: 263.309 | R444: 199.727 | S444: 252.433 | T444: =SUM(N444:S444) -> 2089.552 | U444: 1173.37 | V444: 805.49 | W444: 1487.927 | X444: 626.609 | Y444: 661.329 | Z444: 916.771 | AA444: =SUM(U444:Z444) -> 5671.496 | AB444: 339.855 | AC444: 240.608 | AD444: 471.405 | AE444: 193.717 | AF444: 200.79 | AG444: 266.247 | AH444: =SUM(AB444:AG444) -> 1712.622 | AI444: 松江・境港
A445: 0000000104033 | B445: 九州惣菜㈱ | C445: 0032 | D445: 飯塚 | E445: =IFERROR(IF(INDEX(INDIRECT("'"&$AI445&"'!$E$2:$E$327"),MATCH($A445,INDIRECT("'"&$AI445&"'!$A$2:$A$327"),0))="","",INDEX(INDIRECT("'"&$AI445&"'!$E$2:$E$327"),MATCH($A445,INDIRECT("'"&$AI445&"'!$A$2:$A$327"),0))),"") | F445: =IF($E445="","",IFERROR(INDEX(担当者マスタ!$B$2:$B$101,MATCH($E445,担当者マスタ!$A$2:$A$101,0)),"※マスタ未登録")) | G445: 384.783 | H445: 336.247 | I445: 390.402 | J445: 239.207 | K445: 248.551 | L445: 379.936 | M445: =SUM(G445:L445) -> 1979.126 | N445: 102.827 | O445: 84.486 | P445: 98.692 | Q445: 63.066 | R445: 61.868 | S445: 86.348 | T445: =SUM(N445:S445) -> 497.287 | U445: 294.317 | V445: 305.119 | W445: 362.849 | X445: 188.841 | Y445: 176.299 | Z445: 255.538 | AA445: =SUM(U445:Z445) -> 1582.963 | AB445: 68.426 | AC445: 75.103 | AD445: 87.018 | AE445: 39.573 | AF445: 37.862 | AG445: 56.028 | AH445: =SUM(AB445:AG445) -> 364.01 | AI445: 松江・境港
... A548: 0000000102373 | B548: 中国調理食品 | C548: 0039 | D548: その他 | E548: =IFERROR(IF(INDEX(INDIRECT("'"&$AI548&"'!$E$2:$E$327"),MATCH($A548,INDIRECT("'"&$AI548&"'!$A$2:$A$327"),0))="","",INDEX(INDIRECT("'"&$AI548&"'!$E$2:$E$327"),MATCH($A548,INDIRECT("'"&$AI548&"'!$A$2:$A$327"),0))),"") | F548: =IF($E548="","",IFERROR(INDEX(担当者マスタ!$B$2:$B$101,MATCH($E548,担当者マスタ!$A$2:$A$101,0)),"※マスタ未登録")) | G548: 0 | H548: 0 | I548: 0 | J548: 0 | K548: 12.48 | L548: 0 | M548: =SUM(G548:L548) -> 12.48 | N548: 0 | O548: 0 | P548: 0 | Q548: 0 | R548: 2.72 | S548: 0 | T548: =SUM(N548:S548) -> 2.72 | U548: 0 | V548: 0 | W548: 30.595 | X548: 0 | Y548: 0 | Z548: 0 | AA548: =SUM(U548:Z548) -> 30.595 | AB548: 0 | AC548: 0 | AD548: 7.235 | AE548: 0 | AF548: 0 | AG548: 0 | AH548: =SUM(AB548:AG548) -> 7.235 | AI548: 松江・境港
A549: 0000000001124 | B549: ｶﾈｹﾞﾝ | C549: 0042 | D549: 馬場部長 | E549: =IFERROR(IF(INDEX(INDIRECT("'"&$AI549&"'!$E$2:$E$71"),MATCH($A549,INDIRECT("'"&$AI549&"'!$A$2:$A$71"),0))="","",INDEX(INDIRECT("'"&$AI549&"'!$E$2:$E$71"),MATCH($A549,INDIRECT("'"&$AI549&"'!$A$2:$A$71"),0))),"") | F549: =IF($E549="","",IFERROR(INDEX(担当者マスタ!$B$2:$B$101,MATCH($E549,担当者マスタ!$A$2:$A$101,0)),"※マスタ未登録")) | G549: 1530.202 | H549: 1331.485 | I549: 1865.623 | J549: 394.99 | K549: 1245.073 | L549: 1051.65 | M549: =SUM(G549:L549) -> 7419.023 | N549: 176.074 | O549: 155.217 | P549: 216.279 | Q549: 32.626 | R549: 125.93 | S549: 125.627 | T549: =SUM(N549:S549) -> 831.753 | U549: 889.595 | V549: 897.82 | W549: 1410.589 | X549: 691.51 | Y549: 1010.252 | Z549: 981.539 | AA549: =SUM(U549:Z549) -> 5881.305 | AB549: 58.735 | AC549: 65.553 | AD549: 134.763 | AE549: 77.664 | AF549: 84.594 | AG549: 76.589 | AH549: =SUM(AB549:AG549) -> 497.898 | AI549: 鳥栖・静岡・東京
A550: 0000000005624 | B550: ㈱ﾘﾝｶﾞｰﾊｯﾄ東京本社 | C550: 0042 | D550: 馬場部長 | E550: =IFERROR(IF(INDEX(INDIRECT("'"&$AI550&"'!$E$2:$E$71"),MATCH($A550,INDIRECT("'"&$AI550&"'!$A$2:$A$71"),0))="","",INDEX(INDIRECT("'"&$AI550&"'!$E$2:$E$71"),MATCH($A550,INDIRECT("'"&$AI550&"'!$A$2:$A$71"),0))),"") | F550: =IF($E550="","",IFERROR(INDEX(担当者マスタ!$B$2:$B$101,MATCH($E550,担当者マスタ!$A$2:$A$101,0)),"※マスタ未登録")) | G550: 27357.149 | H550: 29842.14 | I550: 35394.144 | J550: 28095.015 | K550: 29989.885 | L550: 33407.761 | M550: =SUM(G550:L550) -> 184086.09 | N550: 3739.394 | O550: 4189.368 | P550: 5089.205 | Q550: 3916.215 | R550: 4233.37 | S550: 5641.747 | T550: =SUM(N550:S550) -> 26809.299 | U550: 28564.537 | V550: 30135.229 | W550: 37931.299 | X550: 26226.4 | Y550: 27549.329 | Z550: 29111.012 | AA550: =SUM(U550:Z550) -> 179517.81 | AB550: 3889.708 | AC550: 4241.439 | AD550: 5138.571 | AE550: 3462.655 | AF550: 3900.067 | AG550: 5139.252 | AH550: =SUM(AB550:AG550) -> 25771.692 | AI550: 鳥栖・静岡・東京
A551: 0000000105624 | B551: ㈱ﾘﾝｶﾞｰﾊｯﾄ東京本社 | C551: 0042 | D551: 馬場部長 | E551: =IFERROR(IF(INDEX(INDIRECT("'"&$AI551&"'!$E$2:$E$71"),MATCH($A551,INDIRECT("'"&$AI551&"'!$A$2:$A$71"),0))="","",INDEX(INDIRECT("'"&$AI551&"'!$E$2:$E$71"),MATCH($A551,INDIRECT("'"&$AI551&"'!$A$2:$A$71"),0))),"") | F551: =IF($E551="","",IFERROR(INDEX(担当者マスタ!$B$2:$B$101,MATCH($E551,担当者マスタ!$A$2:$A$101,0)),"※マスタ未登録")) | G551: 0 | H551: 0 | I551: 0 | J551: 0 | K551: 0 | L551: 0 | M551: =SUM(G551:L551) -> 0 | N551: 0 | O551: 0 | P551: 0 | Q551: 0 | R551: 0 | S551: 0 | T551: =SUM(N551:S551) -> 0 | U551: 0 | V551: 3 | W551: 0 | X551: 0 | Y551: 0 | Z551: 0 | AA551: =SUM(U551:Z551) -> 3 | AB551: 0 | AC551: 1.552 | AD551: 0 | AE551: 0 | AF551: 0 | AG551: 0 | AH551: =SUM(AB551:AG551) -> 1.552 | AI551: 鳥栖・静岡・東京
A552: 0000000000134 | B552: ㈱蔵出しめんたい本舗 | C552: 0046 | D552: 角田 | E552: =IFERROR(IF(INDEX(INDIRECT("'"&$AI552&"'!$E$2:$E$71"),MATCH($A552,INDIRECT("'"&$AI552&"'!$A$2:$A$71"),0))="","",INDEX(INDIRECT("'"&$AI552&"'!$E$2:$E$71"),MATCH($A552,INDIRECT("'"&$AI552&"'!$A$2:$A$71"),0))),"") | F552: =IF($E552="","",IFERROR(INDEX(担当者マスタ!$B$2:$B$101,MATCH($E552,担当者マスタ!$A$2:$A$101,0)),"※マスタ未登録")) | G552: 926.207 | H552: 759.301 | I552: 1096.286 | J552: 652.599 | K552: 449.989 | L552: 781.715 | M552: =SUM(G552:L552) -> 4666.097 | N552: 228.524 | O552: 194.533 | P552: 245.062 | Q552: 158.8 | R552: 102.124 | S552: 196.424 | T552: =SUM(N552:S552) -> 1125.467 | U552: 506.412 | V552: 663.9 | W552: 1205.97 | X552: 369.917 | Y552: 513.973 | Z552: 847.946 | AA552: =SUM(U552:Z552) -> 4108.118 | AB552: 108.136 | AC552: 151.327 | AD552: 268.297 | AE552: 70.888 | AF552: 114.738 | AG552: 197.093 | AH552: =SUM(AB552:AG552) -> 910.479 | AI552: 鳥栖・静岡・東京
A553: 0000000000144 | B553: ㈲東洋ﾃｸﾆｶﾙﾌｰﾂﾞ | C553: 0046 | D553: 角田 | E553: =IFERROR(IF(INDEX(INDIRECT("'"&$AI553&"'!$E$2:$E$71"),MATCH($A553,INDIRECT("'"&$AI553&"'!$A$2:$A$71"),0))="","",INDEX(INDIRECT("'"&$AI553&"'!$E$2:$E$71"),MATCH($A553,INDIRECT("'"&$AI553&"'!$A$2:$A$71"),0))),"") | F553: =IF($E553="","",IFERROR(INDEX(担当者マスタ!$B$2:$B$101,MATCH($E553,担当者マスタ!$A$2:$A$101,0)),"※マスタ未登録")) | G553: 37.375 | H553: 0 | I553: 109.8 | J553: 72 | K553: 97 | L553: 191.696 | M553: =SUM(G553:L553) -> 507.871 | N553: 7.15 | O553: 0 | P553: 19.44 | Q553: 14.4 | R553: 23.4 | S553: 38.61 | T553: =SUM(N553:S553) -> 103 | U553: 204.59 | V553: 37.03 | W553: 0 | X553: 169.3 | Y553: 159.41 | Z553: 123.41 | AA553: =SUM(U553:Z553) -> 693.74 | AB553: 37.688 | AC553: 7.084 | AD553: 0 | AE553: 30.94 | AF553: 31.01 | AG553: 23.81 | AH553: =SUM(AB553:AG553) -> 130.532 | AI553: 鳥栖・静岡・東京
A554: 0000000000164 | B554: SUS㈱ | C554: 0046 | D554: 角田 | E554: =IFERROR(IF(INDEX(INDIRECT("'"&$AI554&"'!$E$2:$E$71"),MATCH($A554,INDIRECT("'"&$AI554&"'!$A$2:$A$71"),0))="","",INDEX(INDIRECT("'"&$AI554&"'!$E$2:$E$71"),MATCH($A554,INDIRECT("'"&$AI554&"'!$A$2:$A$71"),0))),"") | F554: =IF($E554="","",IFERROR(INDEX(担当者マスタ!$B$2:$B$101,MATCH($E554,担当者マスタ!$A$2:$A$101,0)),"※マスタ未登録")) | G554: 49.09 | H554: 0 | I554: 81.1 | J554: 0 | K554: 44.1 | L554: 37 | M554: =SUM(G554:L554) -> 211.29 | N554: 10.18 | O554: 0 | P554: 7.92 | Q554: 0 | R554: 2.52 | S554: 5.4 | T554: =SUM(N554:S554) -> 26.02 | U554: 80.85 | V554: 0 | W554: 0 | X554: 0 | Y554: 0 | Z554: 0 | AA554: =SUM(U554:Z554) -> 80.85 | AB554: 11.55 | AC554: 0 | AD554: 0 | AE554: 0 | AF554: 0 | AG554: 0 | AH554: =SUM(AB554:AG554) -> 11.55 | AI554: 鳥栖・静岡・東京
A555: 0000000000224 | B555: ㈲東龍食品★ | C555: 0046 | D555: 角田 | E555: =IFERROR(IF(INDEX(INDIRECT("'"&$AI555&"'!$E$2:$E$71"),MATCH($A555,INDIRECT("'"&$AI555&"'!$A$2:$A$71"),0))="","",INDEX(INDIRECT("'"&$AI555&"'!$E$2:$E$71"),MATCH($A555,INDIRECT("'"&$AI555&"'!$A$2:$A$71"),0))),"") | F555: =IF($E555="","",IFERROR(INDEX(担当者マスタ!$B$2:$B$101,MATCH($E555,担当者マスタ!$A$2:$A$101,0)),"※マスタ未登録")) | G555: 7.725 | H555: 0 | I555: 0 | J555: 0 | K555: 0 | L555: 0 | M555: =SUM(G555:L555) -> 7.725 | N555: 0.99 | O555: 0 | P555: 0 | Q555: 0 | R555: 0 | S555: 0 | T555: =SUM(N555:S555) -> 0.99 | U555: 0 | V555: 0 | W555: 0 | X555: 0 | Y555: 0 | Z555: 0 | AA555: =SUM(U555:Z555) -> 0 | AB555: 0 | AC555: 0 | AD555: 0 | AE555: 0 | AF555: 0 | AG555: 0 | AH555: =SUM(AB555:AG555) -> 0 | AI555: 鳥栖・静岡・東京
A556: 0000000000584 | B556: みよしの食堂 | C556: 0046 | D556: 角田 | E556: =IFERROR(IF(INDEX(INDIRECT("'"&$AI556&"'!$E$2:$E$71"),MATCH($A556,INDIRECT("'"&$AI556&"'!$A$2:$A$71"),0))="","",INDEX(INDIRECT("'"&$AI556&"'!$E$2:$E$71"),MATCH($A556,INDIRECT("'"&$AI556&"'!$A$2:$A$71"),0))),"") | F556: =IF($E556="","",IFERROR(INDEX(担当者マスタ!$B$2:$B$101,MATCH($E556,担当者マスタ!$A$2:$A$101,0)),"※マスタ未登録")) | G556: 0 | H556: 59.968 | I556: 26.51 | J556: 2.88 | K556: 17.119 | L556: 35.247 | M556: =SUM(G556:L556) -> 141.724 | N556: 0 | O556: 15.543 | P556: 5.516 | Q556: 1 | R556: 3.168 | S556: 7.718 | T556: =SUM(N556:S556) -> 32.945 | U556: 29.76 | V556: 18.713 | W556: 22.492 | X556: 22.213 | Y556: 10.748 | Z556: 29.211 | AA556: =SUM(U556:Z556) -> 133.137 | AB556: 8.48 | AC556: 3.481 | AD556: 4.588 | AE556: 4.391 | AF556: 2.261 | AG556: 5.913 | AH556: =SUM(AB556:AG556) -> 29.114 | AI556: 鳥栖・静岡・東京
A557: 0000000000764 | B557: ㈱堀内 | C557: 0046 | D557: 角田 | E557: =IFERROR(IF(INDEX(INDIRECT("'"&$AI557&"'!$E$2:$E$71"),MATCH($A557,INDIRECT("'"&$AI557&"'!$A$2:$A$71"),0))="","",INDEX(INDIRECT("'"&$AI557&"'!$E$2:$E$71"),MATCH($A557,INDIRECT("'"&$AI557&"'!$A$2:$A$71"),0))),"") | F557: =IF($E557="","",IFERROR(INDEX(担当者マスタ!$B$2:$B$101,MATCH($E557,担当者マスタ!$A$2:$A$101,0)),"※マスタ未登録")) | G557: 631.209 | H557: 580.319 | I557: 1276.172 | J557: 523.884 | K557: 569.164 | L557: 1150.085 | M557: =SUM(G557:L557) -> 4730.833 | N557: 151.826 | O557: 140.356 | P557: 193.924 | Q557: 113.591 | R557: 118.768 | S557: 257.024 | T557: =SUM(N557:S557) -> 975.489 | U557: 834.816 | V557: 556.825 | W557: 726.23 | X557: 538.467 | Y557: 631.999 | Z557: 742.886 | AA557: =SUM(U557:Z557) -> 4031.223 | AB557: 170.074 | AC557: 114.111 | AD557: 172.466 | AE557: 104.994 | AF557: 126.37 | AG557: 149.427 | AH557: =SUM(AB557:AG557) -> 837.442 | AI557: 鳥栖・静岡・東京
A558: 0000000000834 | B558: ㈱どんどんﾗｲｽ福岡 | C558: 0046 | D558: 角田 | E558: =IFERROR(IF(INDEX(INDIRECT("'"&$AI558&"'!$E$2:$E$71"),MATCH($A558,INDIRECT("'"&$AI558&"'!$A$2:$A$71"),0))="","",INDEX(INDIRECT("'"&$AI558&"'!$E$2:$E$71"),MATCH($A558,INDIRECT("'"&$AI558&"'!$A$2:$A$71"),0))),"") | F558: =IF($E558="","",IFERROR(INDEX(担当者マスタ!$B$2:$B$101,MATCH($E558,担当者マスタ!$A$2:$A$101,0)),"※マスタ未登録")) | G558: 349.65 | H558: 286.5 | I558: 1646.462 | J558: 1908.85 | K558: 146.45 | L558: 276.1 | M558: =SUM(G558:L558) -> 4614.012 | N558: 44.7 | O558: 37.5 | P558: 306.793 | Q558: 295.3 | R558: 14.1 | S558: 37.2 | T558: =SUM(N558:S558) -> 735.593 | U558: 332.029 | V558: 350.142 | W558: 1916.059 | X558: 1027.65 | Y558: 203.2 | Z558: 357.75 | AA558: =SUM(U558:Z558) -> 4186.83 | AB558: 42.949 | AC558: 49.093 | AD558: 364.779 | AE558: 154.7 | AF558: 30.6 | AG558: 52.25 | AH558: =SUM(AB558:AG558) -> 694.371 | AI558: 鳥栖・静岡・東京
A559: 0000000000864 | B559: ㈱堀江本店 | C559: 0046 | D559: 角田 | E559: =IFERROR(IF(INDEX(INDIRECT("'"&$AI559&"'!$E$2:$E$71"),MATCH($A559,INDIRECT("'"&$AI559&"'!$A$2:$A$71"),0))="","",INDEX(INDIRECT("'"&$AI559&"'!$E$2:$E$71"),MATCH($A559,INDIRECT("'"&$AI559&"'!$A$2:$A$71"),0))),"") | F559: =IF($E559="","",IFERROR(INDEX(担当者マスタ!$B$2:$B$101,MATCH($E559,担当者マスタ!$A$2:$A$101,0)),"※マスタ未登録")) | G559: 181.147 | H559: 141.154 | I559: 166.796 | J559: 89.283 | K559: 115.844 | L559: 107.151 | M559: =SUM(G559:L559) -> 801.375 | N559: 32.262 | O559: 24.655 | P559: 28.868 | Q559: 16.072 | R559: 19.799 | S559: 18.885 | T559: =SUM(N559:S559) -> 140.541 | U559: 152.698 | V559: 93.917 | W559: 151.24 | X559: 112.514 | Y559: 126.757 | Z559: 127.74 | AA559: =SUM(U559:Z559) -> 764.866 | AB559: 26.155 | AC559: 16.939 | AD559: 25.993 | AE559: 18.658 | AF559: 21.924 | AG559: 21.246 | AH559: =SUM(AB559:AG559) -> 130.915 | AI559: 鳥栖・静岡・東京
A560: 0000000000924 | B560: ㈱ﾌﾚｯｼｭﾐｰﾄ | C560: 0046 | D560: 角田 | E560: =IFERROR(IF(INDEX(INDIRECT("'"&$AI560&"'!$E$2:$E$71"),MATCH($A560,INDIRECT("'"&$AI560&"'!$A$2:$A$71"),0))="","",INDEX(INDIRECT("'"&$AI560&"'!$E$2:$E$71"),MATCH($A560,INDIRECT("'"&$AI560&"'!$A$2:$A$71"),0))),"") | F560: =IF($E560="","",IFERROR(INDEX(担当者マスタ!$B$2:$B$101,MATCH($E560,担当者マスタ!$A$2:$A$101,0)),"※マスタ未登録")) | G560: 0 | H560: 0 | I560: 0 | J560: 11.49 | K560: 19.15 | L560: 0 | M560: =SUM(G560:L560) -> 30.64 | N560: 0 | O560: 0 | P560: 0 | Q560: 3.66 | R560: 6.1 | S560: 0 | T560: =SUM(N560:S560) -> 9.76 | U560: 0 | V560: 61.28 | W560: 30.64 | X560: 0 | Y560: 0 | Z560: 53.62 | AA560: =SUM(U560:Z560) -> 145.54 | AB560: 0 | AC560: 15.344 | AD560: 7.672 | AE560: 0 | AF560: 0 | AG560: 13.426 | AH560: =SUM(AB560:AG560) -> 36.442 | AI560: 鳥栖・静岡・東京
... A587: 0000000122714 | B587: ㈱梅の花ｸﾞﾙｰﾌﾟ | C587: 0046 | D587: 角田 | E587: =IFERROR(IF(INDEX(INDIRECT("'"&$AI587&"'!$E$2:$E$71"),MATCH($A587,INDIRECT("'"&$AI587&"'!$A$2:$A$71"),0))="","",INDEX(INDIRECT("'"&$AI587&"'!$E$2:$E$71"),MATCH($A587,INDIRECT("'"&$AI587&"'!$A$2:$A$71"),0))),"") | F587: =IF($E587="","",IFERROR(INDEX(担当者マスタ!$B$2:$B$101,MATCH($E587,担当者マスタ!$A$2:$A$101,0)),"※マスタ未登録")) | G587: 883.57 | H587: 930.036 | I587: 1458.576 | J587: 319.336 | K587: 383.991 | L587: 189.788 | M587: =SUM(G587:L587) -> 4165.297 | N587: 133.69 | O587: 163.063 | P587: 231.505 | Q587: 42.096 | R587: 50.184 | S587: 34.342 | T587: =SUM(N587:S587) -> 654.88 | U587: 824.354 | V587: 482.994 | W587: 1421.256 | X587: 143.308 | Y587: 568.138 | Z587: 307.246 | AA587: =SUM(U587:Z587) -> 3747.296 | AB587: 144.314 | AC587: 83.604 | AD587: 241.593 | AE587: 21.738 | AF587: 96.439 | AG587: 47.786 | AH587: =SUM(AB587:AG587) -> 635.474 | AI587: 鳥栖・静岡・東京
A588: 0000000000211 | B588: ㈲漁協ｻｰﾋﾞｽ | C588: 0101 | D588: 漁協サービス | E588: =IFERROR(IF(INDEX(INDIRECT("'"&$AI588&"'!$E$2:$E$118"),MATCH($A588,INDIRECT("'"&$AI588&"'!$A$2:$A$118"),0))="","",INDEX(INDIRECT("'"&$AI588&"'!$E$2:$E$118"),MATCH($A588,INDIRECT("'"&$AI588&"'!$A$2:$A$118"),0))),"") | F588: =IF($E588="","",IFERROR(INDEX(担当者マスタ!$B$2:$B$101,MATCH($E588,担当者マスタ!$A$2:$A$101,0)),"※マスタ未登録")) | G588: 525.78 | H588: 628.263 | I588: 707.48 | J588: 687.09 | K588: 948.98 | L588: 834.972 | M588: =SUM(G588:L588) -> 4332.565 | N588: 284.751 | O588: 412.73 | P588: 399.469 | Q588: 390.432 | R588: 734.144 | S588: 536.921 | T588: =SUM(N588:S588) -> 2758.447 | U588: 529.547 | V588: 834.739 | W588: 929.941 | X588: 654.036 | Y588: 817.589 | Z588: 607.232 | AA588: =SUM(U588:Z588) -> 4373.084 | AB588: 430.158 | AC588: 660.75 | AD588: 647.324 | AE588: 465.198 | AF588: 580.017 | AG588: 348.719 | AH588: =SUM(AB588:AG588) -> 3132.166 | AI588: 水産部X
A589: 0000000000391 | B589: JF大田支所経費 | C589: 0102 | D589: JF大田 | E589: =IFERROR(IF(INDEX(INDIRECT("'"&$AI589&"'!$E$2:$E$118"),MATCH($A589,INDIRECT("'"&$AI589&"'!$A$2:$A$118"),0))="","",INDEX(INDIRECT("'"&$AI589&"'!$E$2:$E$118"),MATCH($A589,INDIRECT("'"&$AI589&"'!$A$2:$A$118"),0))),"") | F589: =IF($E589="","",IFERROR(INDEX(担当者マスタ!$B$2:$B$101,MATCH($E589,担当者マスタ!$A$2:$A$101,0)),"※マスタ未登録")) | G589: 0 | H589: 201.8 | I589: 150 | J589: 0 | K589: 165 | L589: 0 | M589: =SUM(G589:L589) -> 516.8 | N589: 0 | O589: 40.52 | P589: 150 | Q589: 0 | R589: 30 | S589: 0 | T589: =SUM(N589:S589) -> 220.52 | U589: 165 | V589: 0 | W589: 0 | X589: 0 | Y589: 6.5 | Z589: 0 | AA589: =SUM(U589:Z589) -> 171.5 | AB589: 30 | AC589: 0 | AD589: 0 | AE589: 0 | AF589: 6.5 | AG589: 0 | AH589: =SUM(AB589:AG589) -> 36.5 | AI589: 水産部X
A590: 0000000000471 | B590: JFしまね大田支所 | C590: 0102 | D590: JF大田 | E590: =IFERROR(IF(INDEX(INDIRECT("'"&$AI590&"'!$E$2:$E$118"),MATCH($A590,INDIRECT("'"&$AI590&"'!$A$2:$A$118"),0))="","",INDEX(INDIRECT("'"&$AI590&"'!$E$2:$E$118"),MATCH($A590,INDIRECT("'"&$AI590&"'!$A$2:$A$118"),0))),"") | F590: =IF($E590="","",IFERROR(INDEX(担当者マスタ!$B$2:$B$101,MATCH($E590,担当者マスタ!$A$2:$A$101,0)),"※マスタ未登録")) | G590: 11181.448 | H590: 9787.562 | I590: 3937.089 | J590: 4402.895 | K590: 5739.73 | L590: 6618.195 | M590: =SUM(G590:L590) -> 41666.919 | N590: 2192.469 | O590: 2024.613 | P590: 799.796 | Q590: 930.288 | R590: 1182.906 | S590: 1412.294 | T590: =SUM(N590:S590) -> 8542.366 | U590: 11002.024 | V590: 12709.28 | W590: 7292.45 | X590: 4099.222 | Y590: 5195.947 | Z590: 10845.253 | AA590: =SUM(U590:Z590) -> 51144.176 | AB590: 2495.362 | AC590: 2948.673 | AD590: 1710.851 | AE590: 945.286 | AF590: 1266.53 | AG590: 2687.809 | AH590: =SUM(AB590:AG590) -> 12054.511 | AI590: 水産部X
A591: 0000000000201 | B591: JF大田ｼｰﾄ料 | C591: 0104 | D591: 大田荷役 | E591: =IFERROR(IF(INDEX(INDIRECT("'"&$AI591&"'!$E$2:$E$118"),MATCH($A591,INDIRECT("'"&$AI591&"'!$A$2:$A$118"),0))="","",INDEX(INDIRECT("'"&$AI591&"'!$E$2:$E$118"),MATCH($A591,INDIRECT("'"&$AI591&"'!$A$2:$A$118"),0))),"") | F591: =IF($E591="","",IFERROR(INDEX(担当者マスタ!$B$2:$B$101,MATCH($E591,担当者マスタ!$A$2:$A$101,0)),"※マスタ未登録")) | G591: 959.76 | H591: 1128.58 | I591: 497.66 | J591: 489.04 | K591: 599.84 | L591: 781.28 | M591: =SUM(G591:L591) -> 4456.16 | N591: 361.574 | O591: 577.482 | P591: 200.481 | Q591: 146.504 | R591: 247.664 | S591: 328.86 | T591: =SUM(N591:S591) -> 1862.565 | U591: 972.52 | V591: 1096.88 | W591: 671.92 | X591: 298.6 | Y591: 542.18 | Z591: 1110.38 | AA591: =SUM(U591:Z591) -> 4692.48 | AB591: 413.851 | AC591: 471.414 | AD591: 265.663 | AE591: 61.76 | AF591: 183.971 | AG591: 453.31 | AH591: =SUM(AB591:AG591) -> 1849.969 | AI591: 水産部X
A592: 0000000000261 | B592: JF大田製氷工場 | C592: 0104 | D592: 大田荷役 | E592: =IFERROR(IF(INDEX(INDIRECT("'"&$AI592&"'!$E$2:$E$118"),MATCH($A592,INDIRECT("'"&$AI592&"'!$A$2:$A$118"),0))="","",INDEX(INDIRECT("'"&$AI592&"'!$E$2:$E$118"),MATCH($A592,INDIRECT("'"&$AI592&"'!$A$2:$A$118"),0))),"") | F592: =IF($E592="","",IFERROR(INDEX(担当者マスタ!$B$2:$B$101,MATCH($E592,担当者マスタ!$A$2:$A$101,0)),"※マスタ未登録")) | G592: 533.52 | H592: 470.34 | I592: 184.86 | J592: 222.3 | K592: 175.5 | L592: 250.2 | M592: =SUM(G592:L592) -> 1836.72 | N592: 533.52 | O592: 470.34 | P592: 184.86 | Q592: 222.3 | R592: 175.5 | S592: 250.2 | T592: =SUM(N592:S592) -> 1836.72 | U592: 487.5 | V592: 474.96 | W592: 253.2 | X592: 154.44 | Y592: 184.86 | Z592: 382.02 | AA592: =SUM(U592:Z592) -> 1936.98 | AB592: 487.5 | AC592: 474.96 | AD592: 253.2 | AE592: 154.44 | AF592: 184.86 | AG592: 382.02 | AH592: =SUM(AB592:AG592) -> 1936.98 | AI592: 水産部X
A593: 0000000000271 | B593: ※JF大田巻網定置荷役 | C593: 0104 | D593: 大田荷役 | E593: =IFERROR(IF(INDEX(INDIRECT("'"&$AI593&"'!$E$2:$E$118"),MATCH($A593,INDIRECT("'"&$AI593&"'!$A$2:$A$118"),0))="","",INDEX(INDIRECT("'"&$AI593&"'!$E$2:$E$118"),MATCH($A593,INDIRECT("'"&$AI593&"'!$A$2:$A$118"),0))),"") | F593: =IF($E593="","",IFERROR(INDEX(担当者マスタ!$B$2:$B$101,MATCH($E593,担当者マスタ!$A$2:$A$101,0)),"※マスタ未登録")) | G593: 15 | H593: 0 | I593: 0 | J593: 0 | K593: 0 | L593: 0 | M593: =SUM(G593:L593) -> 15 | N593: 15 | O593: 0 | P593: 0 | Q593: 0 | R593: 0 | S593: 0 | T593: =SUM(N593:S593) -> 15 | U593: 0 | V593: 0 | W593: 0 | X593: 0 | Y593: 0 | Z593: 7.5 | AA593: =SUM(U593:Z593) -> 7.5 | AB593: 0 | AC593: 0 | AD593: 0 | AE593: 0 | AF593: 0 | AG593: 7.5 | AH593: =SUM(AB593:AG593) -> 7.5 | AI593: 水産部X
A594: 0000000000281 | B594: JF大田ｺﾝﾍﾞｱｰ洗浄料 | C594: 0104 | D594: 大田荷役 | E594: =IFERROR(IF(INDEX(INDIRECT("'"&$AI594&"'!$E$2:$E$118"),MATCH($A594,INDIRECT("'"&$AI594&"'!$A$2:$A$118"),0))="","",INDEX(INDIRECT("'"&$AI594&"'!$E$2:$E$118"),MATCH($A594,INDIRECT("'"&$AI594&"'!$A$2:$A$118"),0))),"") | F594: =IF($E594="","",IFERROR(INDEX(担当者マスタ!$B$2:$B$101,MATCH($E594,担当者マスタ!$A$2:$A$101,0)),"※マスタ未登録")) | G594: 18 | H594: 12 | I594: 0 | J594: 4 | K594: 4 | L594: 6 | M594: =SUM(G594:L594) -> 44 | N594: 18 | O594: 12 | P594: 0 | Q594: 4 | R594: 4 | S594: 6 | T594: =SUM(N594:S594) -> 44 | U594: 16 | V594: 20 | W594: 14 | X594: 4 | Y594: 6 | Z594: 10 | AA594: =SUM(U594:Z594) -> 70 | AB594: 16 | AC594: 20 | AD594: 14 | AE594: 4 | AF594: 6 | AG594: 10 | AH594: =SUM(AB594:AG594) -> 70 | AI594: 水産部X
A595: 0000000000291 | B595: JF大田小底荷役料 | C595: 0104 | D595: 大田荷役 | E595: =IFERROR(IF(INDEX(INDIRECT("'"&$AI595&"'!$E$2:$E$118"),MATCH($A595,INDIRECT("'"&$AI595&"'!$A$2:$A$118"),0))="","",INDEX(INDIRECT("'"&$AI595&"'!$E$2:$E$118"),MATCH($A595,INDIRECT("'"&$AI595&"'!$A$2:$A$118"),0))),"") | F595: =IF($E595="","",IFERROR(INDEX(担当者マスタ!$B$2:$B$101,MATCH($E595,担当者マスタ!$A$2:$A$101,0)),"※マスタ未登録")) | G595: 1654.8 | H595: 1977.93 | I595: 798.6 | J595: 829.805 | K595: 987.265 | L595: 1251.6 | M595: =SUM(G595:L595) -> 7500 | N595: 623.422 | O595: 1012.088 | P595: 321.716 | Q595: 248.59 | R595: 407.628 | S595: 526.832 | T595: =SUM(N595:S595) -> 3140.276 | U595: 1741.14 | V595: 1939.56 | W595: 1147.86 | X595: 539.79 | Y595: 906.63 | Z595: 1817.76 | AA595: =SUM(U595:Z595) -> 8092.74 | AB595: 740.934 | AC595: 833.579 | AD595: 453.841 | AE595: 111.646 | AF595: 307.637 | AG595: 742.098 | AH595: =SUM(AB595:AG595) -> 3189.735 | AI595: 水産部X
A596: 0000000000301 | B596: JF大田魚集荷料 | C596: 0104 | D596: 大田荷役 | E596: =IFERROR(IF(INDEX(INDIRECT("'"&$AI596&"'!$E$2:$E$118"),MATCH($A596,INDIRECT("'"&$AI596&"'!$A$2:$A$118"),0))="","",INDEX(INDIRECT("'"&$AI596&"'!$E$2:$E$118"),MATCH($A596,INDIRECT("'"&$AI596&"'!$A$2:$A$118"),0))),"") | F596: =IF($E596="","",IFERROR(INDEX(担当者マスタ!$B$2:$B$101,MATCH($E596,担当者マスタ!$A$2:$A$101,0)),"※マスタ未登録")) | G596: 324.02 | H596: 342.285 | I596: 126.905 | J596: 169.83 | K596: 194.395 | L596: 235.235 | M596: =SUM(G596:L596) -> 1392.67 | N596: 324.02 | O596: 342.285 | P596: 126.905 | Q596: 169.83 | R596: 194.395 | S596: 235.235 | T596: =SUM(N596:S596) -> 1392.67 | U596: 404.685 | V596: 382.16 | W596: 183.675 | X596: 98.515 | Y596: 161.67 | Z596: 260.95 | AA596: =SUM(U596:Z596) -> 1491.655 | AB596: 404.685 | AC596: 382.16 | AD596: 183.675 | AE596: 98.515 | AF596: 161.67 | AG596: 260.95 | AH596: =SUM(AB596:AG596) -> 1491.655 | AI596: 水産部X
A597: 0000000000321 | B597: JF大田市場洗浄料 | C597: 0104 | D597: 大田荷役 | E597: =IFERROR(IF(INDEX(INDIRECT("'"&$AI597&"'!$E$2:$E$118"),MATCH($A597,INDIRECT("'"&$AI597&"'!$A$2:$A$118"),0))="","",INDEX(INDIRECT("'"&$AI597&"'!$E$2:$E$118"),MATCH($A597,INDIRECT("'"&$AI597&"'!$A$2:$A$118"),0))),"") | F597: =IF($E597="","",IFERROR(INDEX(担当者マスタ!$B$2:$B$101,MATCH($E597,担当者マスタ!$A$2:$A$101,0)),"※マスタ未登録")) | G597: 208 | H597: 104 | I597: 96 | J597: 86 | K597: 72 | L597: 94 | M597: =SUM(G597:L597) -> 660 | N597: 208 | O597: 104 | P597: 96 | Q597: 86 | R597: 72 | S597: 94 | T597: =SUM(N597:S597) -> 660 | U597: 156 | V597: 151 | W597: 128 | X597: 64 | Y597: 99 | Z597: 162 | AA597: =SUM(U597:Z597) -> 760 | AB597: 156 | AC597: 151 | AD597: 128 | AE597: 64 | AF597: 99 | AG597: 162 | AH597: =SUM(AB597:AG597) -> 760 | AI597: 水産部X
A598: 0000000000381 | B598: JF大田買取荷役料 | C598: 0104 | D598: 大田荷役 | E598: =IFERROR(IF(INDEX(INDIRECT("'"&$AI598&"'!$E$2:$E$118"),MATCH($A598,INDIRECT("'"&$AI598&"'!$A$2:$A$118"),0))="","",INDEX(INDIRECT("'"&$AI598&"'!$E$2:$E$118"),MATCH($A598,INDIRECT("'"&$AI598&"'!$A$2:$A$118"),0))),"") | F598: =IF($E598="","",IFERROR(INDEX(担当者マスタ!$B$2:$B$101,MATCH($E598,担当者マスタ!$A$2:$A$101,0)),"※マスタ未登録")) | G598: 299.1 | H598: 282 | I598: 145.5 | J598: 193.5 | K598: 184.2 | L598: 244.2 | M598: =SUM(G598:L598) -> 1348.5 | N598: 299.1 | O598: 282 | P598: 145.5 | Q598: 193.5 | R598: 184.2 | S598: 244.2 | T598: =SUM(N598:S598) -> 1348.5 | U598: 252.6 | V598: 299.4 | W598: 181.8 | X598: 130.5 | Y598: 170.4 | Z598: 323.1 | AA598: =SUM(U598:Z598) -> 1357.8 | AB598: 252.6 | AC598: 299.4 | AD598: 181.8 | AE598: 130.5 | AF598: 170.4 | AG598: 323.1 | AH598: =SUM(AB598:AG598) -> 1357.8 | AI598: 水産部X
A599: 0000000002011 | B599: 琴代丸 | C599: 0104 | D599: 大田荷役 | E599: =IFERROR(IF(INDEX(INDIRECT("'"&$AI599&"'!$E$2:$E$118"),MATCH($A599,INDIRECT("'"&$AI599&"'!$A$2:$A$118"),0))="","",INDEX(INDIRECT("'"&$AI599&"'!$E$2:$E$118"),MATCH($A599,INDIRECT("'"&$AI599&"'!$A$2:$A$118"),0))),"") | F599: =IF($E599="","",IFERROR(INDEX(担当者マスタ!$B$2:$B$101,MATCH($E599,担当者マスタ!$A$2:$A$101,0)),"※マスタ未登録")) | G599: 90.695 | H599: 95.2 | I599: 47.855 | J599: 62.22 | K599: 41.395 | L599: 62.815 | M599: =SUM(G599:L599) -> 400.18 | N599: 90.695 | O599: 95.2 | P599: 47.855 | Q599: 62.22 | R599: 41.395 | S599: 62.815 | T599: =SUM(N599:S599) -> 400.18 | U599: 100.64 | V599: 120.87 | W599: 63.07 | X599: 20.825 | Y599: 33.83 | Z599: 110.245 | AA599: =SUM(U599:Z599) -> 449.48 | AB599: 100.64 | AC599: 120.87 | AD599: 63.07 | AE599: 20.825 | AF599: 33.83 | AG599: 110.245 | AH599: =SUM(AB599:AG599) -> 449.48 | AI599: 水産部X
... A683: 0000000301291 | B683: 村田漁村㈱-荷役- | C683: 0106 | D683: 浜田荷役 | E683: =IFERROR(IF(INDEX(INDIRECT("'"&$AI683&"'!$E$2:$E$118"),MATCH($A683,INDIRECT("'"&$AI683&"'!$A$2:$A$118"),0))="","",INDEX(INDIRECT("'"&$AI683&"'!$E$2:$E$118"),MATCH($A683,INDIRECT("'"&$AI683&"'!$A$2:$A$118"),0))),"") | F683: =IF($E683="","",IFERROR(INDEX(担当者マスタ!$B$2:$B$101,MATCH($E683,担当者マスタ!$A$2:$A$101,0)),"※マスタ未登録")) | G683: 324.61 | H683: 312.33 | I683: 180.11 | J683: 172.49 | K683: 148.23 | L683: 179.46 | M683: =SUM(G683:L683) -> 1317.23 | N683: 249.474 | O683: 233.087 | P683: 135.951 | Q683: 128.57 | R683: 111.774 | S683: 134.542 | T683: =SUM(N683:S683) -> 993.398 | U683: 195.94 | V683: 306.73 | W683: 337.05 | X683: 186.82 | Y683: 150.18 | Z683: 57.86 | AA683: =SUM(U683:Z683) -> 1234.58 | AB683: 160.176 | AC683: 251.71 | AD683: 271.931 | AE683: 147.973 | AF683: 111.406 | AG683: 43.001 | AH683: =SUM(AB683:AG683) -> 986.197 | AI683: 水産部X
A684: 0000000002408 | B684: ｲﾆｼｵﾌｰｽﾞ㈱ | C684: 0552 | D684: 馬場部長(東京) | E684: =IFERROR(IF(INDEX(INDIRECT("'"&$AI684&"'!$E$2:$E$71"),MATCH($A684,INDIRECT("'"&$AI684&"'!$A$2:$A$71"),0))="","",INDEX(INDIRECT("'"&$AI684&"'!$E$2:$E$71"),MATCH($A684,INDIRECT("'"&$AI684&"'!$A$2:$A$71"),0))),"") | F684: =IF($E684="","",IFERROR(INDEX(担当者マスタ!$B$2:$B$101,MATCH($E684,担当者マスタ!$A$2:$A$101,0)),"※マスタ未登録")) | G684: 369.6 | H684: 369.6 | I684: 369.6 | J684: 369.6 | K684: 369.6 | L684: 369.6 | M684: =SUM(G684:L684) -> 2217.6 | N684: 35.2 | O684: 35.2 | P684: 35.2 | Q684: 35.2 | R684: 35.2 | S684: 35.2 | T684: =SUM(N684:S684) -> 211.2 | U684: 369.6 | V684: 369.6 | W684: 277.2 | X684: 277.2 | Y684: 369.6 | Z684: 462 | AA684: =SUM(U684:Z684) -> 2125.2 | AB684: 35.2 | AC684: 35.2 | AD684: 26.4 | AE684: 26.4 | AF684: 35.2 | AG684: 44 | AH684: =SUM(AB684:AG684) -> 202.4 | AI684: 鳥栖・静岡・東京
A685: 0000000003708 | B685: ㈱栄和ﾌﾟﾗﾝﾆﾝｸﾞ | C685: 0552 | D685: 馬場部長(東京) | E685: =IFERROR(IF(INDEX(INDIRECT("'"&$AI685&"'!$E$2:$E$71"),MATCH($A685,INDIRECT("'"&$AI685&"'!$A$2:$A$71"),0))="","",INDEX(INDIRECT("'"&$AI685&"'!$E$2:$E$71"),MATCH($A685,INDIRECT("'"&$AI685&"'!$A$2:$A$71"),0))),"") | F685: =IF($E685="","",IFERROR(INDEX(担当者マスタ!$B$2:$B$101,MATCH($E685,担当者マスタ!$A$2:$A$101,0)),"※マスタ未登録")) | G685: 0 | H685: 74.4 | I685: 975.883 | J685: 73.16 | K685: 0 | L685: 392.64 | M685: =SUM(G685:L685) -> 1516.083 | N685: 0 | O685: 9.9 | P685: 135.902 | Q685: 9.735 | R685: 0 | S685: 47.04 | T685: =SUM(N685:S685) -> 202.577 | U685: 247.895 | V685: 42.3 | W685: 488.768 | X685: 0 | Y685: 430.268 | Z685: 331.928 | AA685: =SUM(U685:Z685) -> 1541.159 | AB685: 29.67 | AC685: 7.572 | AD685: 59.948 | AE685: 0 | AF685: 51.548 | AG685: 40.713 | AH685: =SUM(AB685:AG685) -> 189.451 | AI685: 鳥栖・静岡・東京
A686: 0000000005628 | B686: ㈱ﾘﾝｶﾞｰﾊｯﾄ東京本社 | C686: 0552 | D686: 馬場部長(東京) | E686: =IFERROR(IF(INDEX(INDIRECT("'"&$AI686&"'!$E$2:$E$71"),MATCH($A686,INDIRECT("'"&$AI686&"'!$A$2:$A$71"),0))="","",INDEX(INDIRECT("'"&$AI686&"'!$E$2:$E$71"),MATCH($A686,INDIRECT("'"&$AI686&"'!$A$2:$A$71"),0))),"") | F686: =IF($E686="","",IFERROR(INDEX(担当者マスタ!$B$2:$B$101,MATCH($E686,担当者マスタ!$A$2:$A$101,0)),"※マスタ未登録")) | G686: 17.475 | H686: 17.475 | I686: 17.475 | J686: 17.475 | K686: 450 | L686: 17.475 | M686: =SUM(G686:L686) -> 537.375 | N686: 3.375 | O686: 3.375 | P686: 3.375 | Q686: 3.375 | R686: 15 | S686: 3.375 | T686: =SUM(N686:S686) -> 31.875 | U686: 17.475 | V686: 17.475 | W686: 17.475 | X686: 0 | Y686: 17.475 | Z686: 17.475 | AA686: =SUM(U686:Z686) -> 87.375 | AB686: 3.375 | AC686: 3.375 | AD686: 3.375 | AE686: 0 | AF686: 3.375 | AG686: 3.375 | AH686: =SUM(AB686:AG686) -> 16.875 | AI686: 鳥栖・静岡・東京
A687: 0000000011628 | B687: ﾘﾝｶﾞｰﾌｰｽﾞ㈱ | C687: 0552 | D687: 馬場部長(東京) | E687: =IFERROR(IF(INDEX(INDIRECT("'"&$AI687&"'!$E$2:$E$71"),MATCH($A687,INDIRECT("'"&$AI687&"'!$A$2:$A$71"),0))="","",INDEX(INDIRECT("'"&$AI687&"'!$E$2:$E$71"),MATCH($A687,INDIRECT("'"&$AI687&"'!$A$2:$A$71"),0))),"") | F687: =IF($E687="","",IFERROR(INDEX(担当者マスタ!$B$2:$B$101,MATCH($E687,担当者マスタ!$A$2:$A$101,0)),"※マスタ未登録")) | G687: 100 | H687: 100 | I687: 100 | J687: 100 | K687: 700 | L687: 100 | M687: =SUM(G687:L687) -> 1200 | N687: 50 | O687: 50 | P687: 50 | Q687: 50 | R687: 120 | S687: 100 | T687: =SUM(N687:S687) -> 420 | U687: 100 | V687: 100 | W687: 100 | X687: 130.002 | Y687: 100 | Z687: 100 | AA687: =SUM(U687:Z687) -> 630.002 | AB687: 100 | AC687: 100 | AD687: 100 | AE687: 109.212 | AF687: 100 | AG687: 100 | AH687: =SUM(AB687:AG687) -> 609.212 | AI687: 鳥栖・静岡・東京
A688: 0000000029808 | B688: ﾃｨｰﾌｰｽﾞ･ｼﾞｬﾊﾟﾝ㈱ | C688: 0552 | D688: 馬場部長(東京) | E688: =IFERROR(IF(INDEX(INDIRECT("'"&$AI688&"'!$E$2:$E$71"),MATCH($A688,INDIRECT("'"&$AI688&"'!$A$2:$A$71"),0))="","",INDEX(INDIRECT("'"&$AI688&"'!$E$2:$E$71"),MATCH($A688,INDIRECT("'"&$AI688&"'!$A$2:$A$71"),0))),"") | F688: =IF($E688="","",IFERROR(INDEX(担当者マスタ!$B$2:$B$101,MATCH($E688,担当者マスタ!$A$2:$A$101,0)),"※マスタ未登録")) | G688: 54.5 | H688: 18 | I688: 49 | J688: 83.1 | K688: 42.7 | L688: 18 | M688: =SUM(G688:L688) -> 265.3 | N688: 7 | O688: 3 | P688: 9 | Q688: 9.6 | R688: 7.75 | S688: 3 | T688: =SUM(N688:S688) -> 39.35 | U688: 23.87 | V688: 83.1 | W688: 18 | X688: 43.5 | Y688: 18 | Z688: 18 | AA688: =SUM(U688:Z688) -> 204.47 | AB688: 8.87 | AC688: 9.6 | AD688: 3 | AE688: 14.1 | AF688: 3 | AG688: 3 | AH688: =SUM(AB688:AG688) -> 41.57 | AI688: 鳥栖・静岡・東京
A689: 0000000067008 | B689: ㈱ｻﾝｷ | C689: 0552 | D689: 馬場部長(東京) | E689: =IFERROR(IF(INDEX(INDIRECT("'"&$AI689&"'!$E$2:$E$71"),MATCH($A689,INDIRECT("'"&$AI689&"'!$A$2:$A$71"),0))="","",INDEX(INDIRECT("'"&$AI689&"'!$E$2:$E$71"),MATCH($A689,INDIRECT("'"&$AI689&"'!$A$2:$A$71"),0))),"") | F689: =IF($E689="","",IFERROR(INDEX(担当者マスタ!$B$2:$B$101,MATCH($E689,担当者マスタ!$A$2:$A$101,0)),"※マスタ未登録")) | G689: 394.41 | H689: 202.183 | I689: 628.526 | J689: 399.146 | K689: 688.847 | L689: 339.586 | M689: =SUM(G689:L689) -> 2652.698 | N689: 42.993 | O689: 21.536 | P689: 56.354 | Q689: 38.912 | R689: 75.835 | S689: 45.418 | T689: =SUM(N689:S689) -> 281.048 | U689: 332.029 | V689: 319.839 | W689: 776.969 | X689: 479.833 | Y689: 246.164 | Z689: 514.108 | AA689: =SUM(U689:Z689) -> 2668.942 | AB689: 36.484 | AC689: 49.707 | AD689: 102.373 | AE689: 66.216 | AF689: 42.94 | AG689: 66.86 | AH689: =SUM(AB689:AG689) -> 364.58 | AI689: 鳥栖・静岡・東京
A690: 0000000067208 | B690: 千倉水産加工販売㈱ | C690: 0552 | D690: 馬場部長(東京) | E690: =IFERROR(IF(INDEX(INDIRECT("'"&$AI690&"'!$E$2:$E$71"),MATCH($A690,INDIRECT("'"&$AI690&"'!$A$2:$A$71"),0))="","",INDEX(INDIRECT("'"&$AI690&"'!$E$2:$E$71"),MATCH($A690,INDIRECT("'"&$AI690&"'!$A$2:$A$71"),0))),"") | F690: =IF($E690="","",IFERROR(INDEX(担当者マスタ!$B$2:$B$101,MATCH($E690,担当者マスタ!$A$2:$A$101,0)),"※マスタ未登録")) | G690: 53.4 | H690: 10.3 | I690: 0 | J690: 0 | K690: 0 | L690: 12.8 | M690: =SUM(G690:L690) -> 76.5 | N690: 20.9 | O690: 1.5 | P690: 0 | Q690: 0 | R690: 0 | S690: 12.8 | T690: =SUM(N690:S690) -> 35.2 | U690: 10.3 | V690: 154.5 | W690: 0 | X690: 10.8 | Y690: 0 | Z690: 0 | AA690: =SUM(U690:Z690) -> 175.6 | AB690: 10.3 | AC690: 154.5 | AD690: 0 | AE690: 10.8 | AF690: 0 | AG690: 0 | AH690: =SUM(AB690:AG690) -> 175.6 | AI690: 鳥栖・静岡・東京
...

Sheet 水産部X
A1: 得意先コード | B1: 得意先略称 | C1: 担当者コード | D1: 担当者名 | E1: 新担当者コード | F1: 新担当者 | G1: 2024/10売上 | H1: 2024/11売上 | I1: 2024/12売上 | J1: 2025/01売上 | K1: 2025/02売上 | L1: 2025/03売上 | M1: 前年度売上合計 | N1: 2024/10粗利益 | O1: 2024/11粗利益 | P1: 2024/12粗利益 | Q1: 2025/01粗利益 | R1: 2025/02粗利益 | S1: 2025/03粗利益 | T1: 前年度粗利益合計 | U1: 2025/10売上 | V1: 2025/11売上 | W1: 2025/12売上 | X1: 2026/01売上 | Y1: 2026/02売上 | Z1: 2026/03売上 | AA1: 今年度売上合計 | AB1: 2025/10粗利益 | AC1: 2025/11粗利益 | AD1: 2025/12粗利益 | AE1: 2026/01粗利益 | AF1: 2026/02粗利益 | AG1: 2026/03粗利益 | AH1: 今年度粗利益合計
A2: 0000000000541 | B2: JFしまね冷蔵庫 | C2: 0010 | D2: JF | F2: =IF($E2="","",IFERROR(INDEX(担当者マスタ!$B$2:$B$101,MATCH($E2,担当者マスタ!$A$2:$A$101,0)),"※マスタ未登録")) | G2: 1727.964 | H2: 1845.035 | I2: 1015.906 | J2: 861.896 | K2: 1167.74 | L2: 1096.898 | M2: =SUM(G2:L2) -> 7715.439 | N2: 328.751 | O2: 408.366 | P2: 254.265 | Q2: 212.557 | R2: 257.125 | S2: 195.312 | T2: =SUM(N2:S2) -> 1656.376 | U2: 2143.798 | V2: 2047.515 | W2: 1351.109 | X2: 572.291 | Y2: 606.598 | Z2: 1948.328 | AA2: =SUM(U2:Z2) -> 8669.639 | AB2: 453.995 | AC2: 419.149 | AD2: 269.7 | AE2: 114.237 | AF2: 168.409 | AG2: 474.166 | AH2: =SUM(AB2:AG2) -> 1899.656
A3: 0000000000561 | B3: JFしまねｻｰﾋﾞｽ | C3: 0010 | D3: JF | F3: =IF($E3="","",IFERROR(INDEX(担当者マスタ!$B$2:$B$101,MATCH($E3,担当者マスタ!$A$2:$A$101,0)),"※マスタ未登録")) | G3: 4904.582 | H3: 4227.566 | I3: 5001.807 | J3: 4524.559 | K3: 4927.58 | L3: 3992.029 | M3: =SUM(G3:L3) -> 27578.123 | N3: 663.403 | O3: 582.982 | P3: 684.031 | Q3: 611.08 | R3: 681.929 | S3: 542.967 | T3: =SUM(N3:S3) -> 3766.392 | U3: 4015.689 | V3: 4119.32 | W3: 3764.454 | X3: 3419.529 | Y3: 4470.593 | Z3: 4581.308 | AA3: =SUM(U3:Z3) -> 24370.893 | AB3: 658.181 | AC3: 719.382 | AD3: 647.591 | AE3: 587.202 | AF3: 722.863 | AG3: 793.162 | AH3: =SUM(AB3:AG3) -> 4128.381
A4: 0000000000691 | B4: JFしまね浜田支所総務 | C4: 0010 | D4: JF | F4: =IF($E4="","",IFERROR(INDEX(担当者マスタ!$B$2:$B$101,MATCH($E4,担当者マスタ!$A$2:$A$101,0)),"※マスタ未登録")) | G4: 28.35 | H4: 0 | I4: 0 | J4: 0 | K4: 0 | L4: 0 | M4: =SUM(G4:L4) -> 28.35 | N4: 10.95 | O4: 0 | P4: 0 | Q4: 0 | R4: 0 | S4: 0 | T4: =SUM(N4:S4) -> 10.95 | U4: 0 | V4: 0 | W4: 0 | X4: 0 | Y4: 0 | Z4: 0 | AA4: =SUM(U4:Z4) -> 0 | AB4: 0 | AC4: 0 | AD4: 0 | AE4: 0 | AF4: 0 | AG4: 0 | AH4: =SUM(AB4:AG4) -> 0
A5: 0000000100191 | B5: JF浜田販売部 | C5: 0010 | D5: JF | F5: =IF($E5="","",IFERROR(INDEX(担当者マスタ!$B$2:$B$101,MATCH($E5,担当者マスタ!$A$2:$A$101,0)),"※マスタ未登録")) | G5: 490.36 | H5: 417.535 | I5: 372.735 | J5: 367.135 | K5: 355.935 | L5: 378.334 | M5: =SUM(G5:L5) -> 2382.034 | N5: 371.089 | O5: 295.464 | P5: 253.464 | Q5: 247.864 | R5: 236.664 | S5: 258.34 | T5: =SUM(N5:S5) -> 1662.885 | U5: 371.533 | V5: 354.732 | W5: 168 | X5: 128.8 | Y5: 145.6 | Z5: 140 | AA5: =SUM(U5:Z5) -> 1308.665 | AB5: 361.641 | AC5: 344.84 | AD5: 168 | AE5: 128.8 | AF5: 145.6 | AG5: 140 | AH5: =SUM(AB5:AG5) -> 1288.881
C6: 0010 集計 | D6: JF | G6: =SUBTOTAL(9,G2:G5) -> 7151.256 | H6: =SUBTOTAL(9,H2:H5) -> 6490.136 | I6: =SUBTOTAL(9,I2:I5) -> 6390.448 | J6: =SUBTOTAL(9,J2:J5) -> 5753.59 | K6: =SUBTOTAL(9,K2:K5) -> 6451.255 | L6: =SUBTOTAL(9,L2:L5) -> 5467.261 | M6: =SUBTOTAL(9,M2:M5) -> 37703.946 | N6: =SUBTOTAL(9,N2:N5) -> 1374.193 | ... AH6: =SUBTOTAL(9,AH2:AH5) -> 7316.918
A7: 0000000000341 | B7: 153 新家商店 | C7: 0017 | D7: 鮮魚 | F7: =IF($E7="","",IFERROR(INDEX(担当者マスタ!$B$2:$B$101,MATCH($E7,担当者マスタ!$A$2:$A$101,0)),"※マスタ未登録")) | G7: 39.1 | H7: 14.423 | I7: 11.76 | J7: 17.036 | K7: 11.688 | L7: 8.097 | M7: =SUM(G7:L7) -> 102.104 | N7: 20.201 | O7: 6.885 | P7: 5.061 | Q7: 7.85 | R7: 5.304 | S7: 3.461 | T7: =SUM(N7:S7) -> 48.762 | U7: 26.513 | V7: 14.266 | W7: 18.887 | X7: 5.19 | Y7: 19.191 | Z7: 11.024 | AA7: =SUM(U7:Z7) -> 95.071 | AB7: 12.505 | AC7: 5.797 | AD7: 8.625 | AE7: 2.248 | AF7: 9.099 | AG7: 4.024 | AH7: =SUM(AB7:AG7) -> 42.298
A8: 0000000090221 | B8: 西部農林水産振興ｾﾝﾀｰ | C8: 0017 | D8: 鮮魚 | F8: =IF($E8="","",IFERROR(INDEX(担当者マスタ!$B$2:$B$101,MATCH($E8,担当者マスタ!$A$2:$A$101,0)),"※マスタ未登録")) | G8: 0 | H8: 0 | I8: 0 | J8: 0 | K8: 0 | L8: 0 | M8: =SUM(G8:L8) -> 0 | N8: 0 | O8: 0 | P8: 0 | Q8: 0 | R8: 0 | S8: 0 | T8: =SUM(N8:S8) -> 0 | U8: 7 | V8: 0 | W8: 0 | X8: 0 | Y8: 0 | Z8: 0 | AA8: =SUM(U8:Z8) -> 7 | AB8: 1.72 | AC8: 0 | AD8: 0 | AE8: 0 | AF8: 0 | AG8: 0 | AH8: =SUM(AB8:AG8) -> 1.72
A9: 0000000103121 | B9: (有)浜田運送 | C9: 0017 | D9: 鮮魚 | F9: =IF($E9="","",IFERROR(INDEX(担当者マスタ!$B$2:$B$101,MATCH($E9,担当者マスタ!$A$2:$A$101,0)),"※マスタ未登録")) | G9: 0 | H9: 0 | I9: 0 | J9: 0 | K9: 0 | L9: 0 | M9: =SUM(G9:L9) -> 0 | N9: 0 | O9: 0 | P9: 0 | Q9: 0 | R9: 0 | S9: 0 | T9: =SUM(N9:S9) -> 0 | U9: 0 | V9: 0 | W9: 0 | X9: 0 | Y9: 0 | Z9: 1.164 | AA9: =SUM(U9:Z9) -> 1.164 | AB9: 0 | AC9: 0 | AD9: 0 | AE9: 0 | AF9: 0 | AG9: 0.495 | AH9: =SUM(AB9:AG9) -> 0.495
A10: 0000000202131 | B10: 220 福田水産㈱ | C10: 0017 | D10: 鮮魚 | F10: =IF($E10="","",IFERROR(INDEX(担当者マスタ!$B$2:$B$101,MATCH($E10,担当者マスタ!$A$2:$A$101,0)),"※マスタ未登録")) | G10: 69.5 | H10: 80.845 | I10: 29.36 | J10: 20.562 | K10: 114.97 | L10: 71.34 | M10: =SUM(G10:L10) -> 386.577 | N10: 68.25 | O10: 64.478 | P10: 16.16 | Q10: 20.03 | R10: 114.97 | S10: 71.34 | T10: =SUM(N10:S10) -> 355.228 | U10: 44 | V10: 142.4 | W10: 62.66 | X10: 20 | Y10: 10.6 | Z10: 3 | AA10: =SUM(U10:Z10) -> 282.66 | AB10: 44 | AC10: 141.15 | AD10: 62.243 | AE10: 20 | AF10: 10.6 | AG10: 3 | AH10: =SUM(AB10:AG10) -> 280.993
A11: 0000000202471 | B11: ㈱浜田あけぼの水産 | C11: 0017 | D11: 鮮魚 | F11: =IF($E11="","",IFERROR(INDEX(担当者マスタ!$B$2:$B$101,MATCH($E11,担当者マスタ!$A$2:$A$101,0)),"※マスタ未登録")) | G11: 0 | H11: 0 | I11: 0 | J11: 0 | K11: 0 | L11: 0 | M11: =SUM(G11:L11) -> 0 | N11: 0 | O11: 0 | P11: 0 | Q11: 0 | R11: 0 | S11: 0 | T11: =SUM(N11:S11) -> 0 | U11: 0 | V11: 0 | W11: 0 | X11: 0 | Y11: 473.2 | Z11: 0 | AA11: =SUM(U11:Z11) -> 473.2 | AB11: 0 | AC11: 0 | AD11: 0 | AE11: 0 | AF11: 92.4 | AG11: 0 | AH11: =SUM(AB11:AG11) -> 92.4
A12: 0000000202601 | B12: 103㈲山本一枝(鮮魚) | C12: 0017 | D12: 鮮魚 | F12: =IF($E12="","",IFERROR(INDEX(担当者マスタ!$B$2:$B$101,MATCH($E12,担当者マスタ!$A$2:$A$101,0)),"※マスタ未登録")) | G12: 496.65 | H12: 231.55 | I12: 55.45 | J12: 66.2 | K12: 34.25 | L12: 41.25 | M12: =SUM(G12:L12) -> 925.35 | N12: 449.596 | O12: 213.992 | P12: 55.45 | Q12: 59.177 | R12: 34.25 | S12: 41.25 | T12: =SUM(N12:S12) -> 853.715 | U12: 27.9 | V12: 84.5 | W12: 561.75 | X12: 412.4 | Y12: 546.4 | Z12: 51.7 | AA12: =SUM(U12:Z12) -> 1684.65 | AB12: 27.9 | AC12: 84.5 | AD12: 326.811 | AE12: 365.409 | AF12: 405.898 | AG12: 46.894 | AH12: =SUM(AB12:AG12) -> 1257.412
A13: 0000000202891 | B13: ㈱かもしま資材 | C13: 0017 | D13: 鮮魚 | F13: =IF($E13="","",IFERROR(INDEX(担当者マスタ!$B$2:$B$101,MATCH($E13,担当者マスタ!$A$2:$A$101,0)),"※マスタ未登録")) | G13: 1927.301 | H13: 896.31 | I13: 384.75 | J13: 232.53 | K13: 131.08 | L13: 304.45 | M13: =SUM(G13:L13) -> 3876.421 | N13: 432.615 | O13: 199.95 | P13: 87.61 | Q13: 53.55 | R13: 30.92 | S13: 71.28 | T13: =SUM(N13:S13) -> 875.925 | U13: 1160.935 | V13: 696.99 | W13: 540.014 | X13: 434.97 | Y13: 266.45 | Z13: 417.96 | AA13: =SUM(U13:Z13) -> 3517.319 | AB13: 252.081 | AC13: 151.96 | AD13: 117.586 | AE13: 99.88 | AF13: 60.93 | AG13: 93.45 | AH13: =SUM(AB13:AG13) -> 775.887
A14: 0000000820021 | B14: 116ﾏﾙｾｲ商店 ｽﾁﾛｰﾙ他 | C14: 0017 | D14: 鮮魚 | F14: =IF($E14="","",IFERROR(INDEX(担当者マスタ!$B$2:$B$101,MATCH($E14,担当者マスタ!$A$2:$A$101,0)),"※マスタ未登録")) | G14: 0 | H14: 0 | I14: 0 | J14: 0 | K14: 0 | L14: 0 | M14: =SUM(G14:L14) -> 0 | N14: 0 | O14: 0 | P14: 0 | Q14: 0 | R14: 0 | S14: 0 | T14: =SUM(N14:S14) -> 0 | U14: 5041.8 | V14: 6213.805 | W14: 4525.811 | X14: 4430.911 | Y14: 3797.025 | Z14: 4362.168 | AA14: =SUM(U14:Z14) -> 28371.52 | AB14: 1982.663 | AC14: 2331.152 | AD14: 1754.948 | AE14: 1655.38 | AF14: 1390.295 | AG14: 1680.919 | AH14: =SUM(AB14:AG14) -> 10795.357
C15: 0017 集計 | D15: 鮮魚 | G15: =SUBTOTAL(9,G7:G14) -> 2532.551 | H15: =SUBTOTAL(9,H7:H14) -> 1223.128 | I15: =SUBTOTAL(9,I7:I14) -> 481.32 | J15: =SUBTOTAL(9,J7:J14) -> 336.328 | K15: =SUBTOTAL(9,K7:K14) -> 291.988 | L15: =SUBTOTAL(9,L7:L14) -> 425.137 | M15: =SUBTOTAL(9,M7:M14) -> 5290.452 | N15: =SUBTOTAL(9,N7:N14) -> 970.662 | ... AH15: =SUBTOTAL(9,AH7:AH14) -> 13246.562
A16: 0000000000043 | B16: JFしまね本所総務部 | C16: 0031 | D16: JF境 | F16: =IF($E16="","",IFERROR(INDEX(担当者マスタ!$B$2:$B$101,MATCH($E16,担当者マスタ!$A$2:$A$101,0)),"※マスタ未登録")) | G16: 0 | H16: 0 | I16: 0 | J16: 0 | K16: 0 | L16: 0 | M16: =SUM(G16:L16) -> 0 | N16: 0 | O16: 0 | P16: 0 | Q16: 0 | R16: 0 | S16: 0 | T16: =SUM(N16:S16) -> 0 | U16: 86 | V16: 0 | W16: 0 | X16: 0 | Y16: 0 | Z16: 0 | AA16: =SUM(U16:Z16) -> 86 | AB16: 18.8 | AC16: 0 | AD16: 0 | AE16: 0 | AF16: 0 | AG16: 0 | AH16: =SUM(AB16:AG16) -> 18.8
A17: 0000000101293 | B17: JFしまね購買部購買課 | C17: 0031 | D17: JF境 | F17: =IF($E17="","",IFERROR(INDEX(担当者マスタ!$B$2:$B$101,MATCH($E17,担当者マスタ!$A$2:$A$101,0)),"※マスタ未登録")) | G17: 14712.216 | H17: 11725.807 | I17: 7290.434 | J17: 10119.517 | K17: 7444.632 | L17: 13124.855 | M17: =SUM(G17:L17) -> 64417.461 | N17: 2351.322 | O17: 2302.986 | P17: 1294.6 | Q17: 1794.514 | R17: 1168.471 | S17: 1962.078 | T17: =SUM(N17:S17) -> 10873.971 | U17: 19329.169 | V17: 14724.818 | W17: 11926.7 | X17: 3662.924 | Y17: 8960.96 | Z17: 18624.798 | AA17: =SUM(U17:Z17) -> 77229.369 | AB17: 4171.382 | AC17: 3372.675 | AD17: 2702.494 | AE17: 789.899 | AF17: 1917.207 | AG17: 3597.906 | AH17: =SUM(AB17:AG17) -> 16551.563
C18: 0031 集計 | D18: JF境 | G18: =SUBTOTAL(9,G16:G17) -> 14712.216 | H18: =SUBTOTAL(9,H16:H17) -> 11725.807 | I18: =SUBTOTAL(9,I16:I17) -> 7290.434 | J18: =SUBTOTAL(9,J16:J17) -> 10119.517 | K18: =SUBTOTAL(9,K16:K17) -> 7444.632 | L18: =SUBTOTAL(9,L16:L17) -> 13124.855 | M18: =SUBTOTAL(9,M16:M17) -> 64417.461 | N18: =SUBTOTAL(9,N16:N17) -> 2351.322 | ... AH18: =SUBTOTAL(9,AH16:AH17) -> 16570.363
A19: 0000000000211 | B19: ㈲漁協ｻｰﾋﾞｽ | C19: 0101 | D19: 漁協サービス | F19: =IF($E19="","",IFERROR(INDEX(担当者マスタ!$B$2:$B$101,MATCH($E19,担当者マスタ!$A$2:$A$101,0)),"※マスタ未登録")) | G19: 525.78 | H19: 628.263 | I19: 707.48 | J19: 687.09 | K19: 948.98 | L19: 834.972 | M19: =SUM(G19:L19) -> 4332.565 | N19: 284.751 | O19: 412.73 | P19: 399.469 | Q19: 390.432 | R19: 734.144 | S19: 536.921 | T19: =SUM(N19:S19) -> 2758.447 | U19: 529.547 | V19: 834.739 | W19: 929.941 | X19: 654.036 | Y19: 817.589 | Z19: 607.232 | AA19: =SUM(U19:Z19) -> 4373.084 | AB19: 430.158 | AC19: 660.75 | AD19: 647.324 | AE19: 465.198 | AF19: 580.017 | AG19: 348.719 | AH19: =SUM(AB19:AG19) -> 3132.166
C20: 0101 集計 | D20: 漁協サービス | G20: =SUBTOTAL(9,G19:G19) -> 525.78 | H20: =SUBTOTAL(9,H19:H19) -> 628.263 | I20: =SUBTOTAL(9,I19:I19) -> 707.48 | J20: =SUBTOTAL(9,J19:J19) -> 687.09 | K20: =SUBTOTAL(9,K19:K19) -> 948.98 | L20: =SUBTOTAL(9,L19:L19) -> 834.972 | M20: =SUBTOTAL(9,M19:M19) -> 4332.565 | N20: =SUBTOTAL(9,N19:N19) -> 284.751 | ... AH20: =SUBTOTAL(9,AH19:AH19) -> 3132.166
A21: 0000000000391 | B21: JF大田支所経費 | C21: 0102 | D21: JF大田 | F21: =IF($E21="","",IFERROR(INDEX(担当者マスタ!$B$2:$B$101,MATCH($E21,担当者マスタ!$A$2:$A$101,0)),"※マスタ未登録")) | G21: 0 | H21: 201.8 | I21: 150 | J21: 0 | K21: 165 | L21: 0 | M21: =SUM(G21:L21) -> 516.8 | N21: 0 | O21: 40.52 | P21: 150 | Q21: 0 | R21: 30 | S21: 0 | T21: =SUM(N21:S21) -> 220.52 | U21: 165 | V21: 0 | W21: 0 | X21: 0 | Y21: 6.5 | Z21: 0 | AA21: =SUM(U21:Z21) -> 171.5 | AB21: 30 | AC21: 0 | AD21: 0 | AE21: 0 | AF21: 6.5 | AG21: 0 | AH21: =SUM(AB21:AG21) -> 36.5
A22: 0000000000471 | B22: JFしまね大田支所 | C22: 0102 | D22: JF大田 | F22: =IF($E22="","",IFERROR(INDEX(担当者マスタ!$B$2:$B$101,MATCH($E22,担当者マスタ!$A$2:$A$101,0)),"※マスタ未登録")) | G22: 11181.448 | H22: 9787.562 | I22: 3937.089 | J22: 4402.895 | K22: 5739.73 | L22: 6618.195 | M22: =SUM(G22:L22) -> 41666.919 | N22: 2192.469 | O22: 2024.613 | P22: 799.796 | Q22: 930.288 | R22: 1182.906 | S22: 1412.294 | T22: =SUM(N22:S22) -> 8542.366 | U22: 11002.024 | V22: 12709.28 | W22: 7292.45 | X22: 4099.222 | Y22: 5195.947 | Z22: 10845.253 | AA22: =SUM(U22:Z22) -> 51144.176 | AB22: 2495.362 | AC22: 2948.673 | AD22: 1710.851 | AE22: 945.286 | AF22: 1266.53 | AG22: 2687.809 | AH22: =SUM(AB22:AG22) -> 12054.511
C23: 0102 集計 | D23: JF大田 | G23: =SUBTOTAL(9,G21:G22) -> 11181.448 | H23: =SUBTOTAL(9,H21:H22) -> 9989.362 | I23: =SUBTOTAL(9,I21:I22) -> 4087.089 | J23: =SUBTOTAL(9,J21:J22) -> 4402.895 | K23: =SUBTOTAL(9,K21:K22) -> 5904.73 | L23: =SUBTOTAL(9,L21:L22) -> 6618.195 | M23: =SUBTOTAL(9,M21:M22) -> 42183.719 | N23: =SUBTOTAL(9,N21:N22) -> 2192.469 | ... AH23: =SUBTOTAL(9,AH21:AH22) -> 12091.011
A24: 0000000000201 | B24: JF大田ｼｰﾄ料 | C24: 0104 | D24: 大田荷役 | F24: =IF($E24="","",IFERROR(INDEX(担当者マスタ!$B$2:$B$101,MATCH($E24,担当者マスタ!$A$2:$A$101,0)),"※マスタ未登録")) | G24: 959.76 | H24: 1128.58 | I24: 497.66 | J24: 489.04 | K24: 599.84 | L24: 781.28 | M24: =SUM(G24:L24) -> 4456.16 | N24: 361.574 | O24: 577.482 | P24: 200.481 | Q24: 146.504 | R24: 247.664 | S24: 328.86 | T24: =SUM(N24:S24) -> 1862.565 | U24: 972.52 | V24: 1096.88 | W24: 671.92 | X24: 298.6 | Y24: 542.18 | Z24: 1110.38 | AA24: =SUM(U24:Z24) -> 4692.48 | AB24: 413.851 | AC24: 471.414 | AD24: 265.663 | AE24: 61.76 | AF24: 183.971 | AG24: 453.31 | AH24: =SUM(AB24:AG24) -> 1849.969
A25: 0000000000261 | B25: JF大田製氷工場 | C25: 0104 | D25: 大田荷役 | F25: =IF($E25="","",IFERROR(INDEX(担当者マスタ!$B$2:$B$101,MATCH($E25,担当者マスタ!$A$2:$A$101,0)),"※マスタ未登録")) | G25: 533.52 | H25: 470.34 | I25: 184.86 | J25: 222.3 | K25: 175.5 | L25: 250.2 | M25: =SUM(G25:L25) -> 1836.72 | N25: 533.52 | O25: 470.34 | P25: 184.86 | Q25: 222.3 | R25: 175.5 | S25: 250.2 | T25: =SUM(N25:S25) -> 1836.72 | U25: 487.5 | V25: 474.96 | W25: 253.2 | X25: 154.44 | Y25: 184.86 | Z25: 382.02 | AA25: =SUM(U25:Z25) -> 1936.98 | AB25: 487.5 | AC25: 474.96 | AD25: 253.2 | AE25: 154.44 | AF25: 184.86 | AG25: 382.02 | AH25: =SUM(AB25:AG25) -> 1936.98
A26: 0000000000271 | B26: ※JF大田巻網定置荷役 | C26: 0104 | D26: 大田荷役 | F26: =IF($E26="","",IFERROR(INDEX(担当者マスタ!$B$2:$B$101,MATCH($E26,担当者マスタ!$A$2:$A$101,0)),"※マスタ未登録")) | G26: 15 | H26: 0 | I26: 0 | J26: 0 | K26: 0 | L26: 0 | M26: =SUM(G26:L26) -> 15 | N26: 15 | O26: 0 | P26: 0 | Q26: 0 | R26: 0 | S26: 0 | T26: =SUM(N26:S26) -> 15 | U26: 0 | V26: 0 | W26: 0 | X26: 0 | Y26: 0 | Z26: 7.5 | AA26: =SUM(U26:Z26) -> 7.5 | AB26: 0 | AC26: 0 | AD26: 0 | AE26: 0 | AF26: 0 | AG26: 7.5 | AH26: =SUM(AB26:AG26) -> 7.5
A27: 0000000000281 | B27: JF大田ｺﾝﾍﾞｱｰ洗浄料 | C27: 0104 | D27: 大田荷役 | F27: =IF($E27="","",IFERROR(INDEX(担当者マスタ!$B$2:$B$101,MATCH($E27,担当者マスタ!$A$2:$A$101,0)),"※マスタ未登録")) | G27: 18 | H27: 12 | I27: 0 | J27: 4 | K27: 4 | L27: 6 | M27: =SUM(G27:L27) -> 44 | N27: 18 | O27: 12 | P27: 0 | Q27: 4 | R27: 4 | S27: 6 | T27: =SUM(N27:S27) -> 44 | U27: 16 | V27: 20 | W27: 14 | X27: 4 | Y27: 6 | Z27: 10 | AA27: =SUM(U27:Z27) -> 70 | AB27: 16 | AC27: 20 | AD27: 14 | AE27: 4 | AF27: 6 | AG27: 10 | AH27: =SUM(AB27:AG27) -> 70
A28: 0000000000291 | B28: JF大田小底荷役料 | C28: 0104 | D28: 大田荷役 | F28: =IF($E28="","",IFERROR(INDEX(担当者マスタ!$B$2:$B$101,MATCH($E28,担当者マスタ!$A$2:$A$101,0)),"※マスタ未登録")) | G28: 1654.8 | H28: 1977.93 | I28: 798.6 | J28: 829.805 | K28: 987.265 | L28: 1251.6 | M28: =SUM(G28:L28) -> 7500 | N28: 623.422 | O28: 1012.088 | P28: 321.716 | Q28: 248.59 | R28: 407.628 | S28: 526.832 | T28: =SUM(N28:S28) -> 3140.276 | U28: 1741.14 | V28: 1939.56 | W28: 1147.86 | X28: 539.79 | Y28: 906.63 | Z28: 1817.76 | AA28: =SUM(U28:Z28) -> 8092.74 | AB28: 740.934 | AC28: 833.579 | AD28: 453.841 | AE28: 111.646 | AF28: 307.637 | AG28: 742.098 | AH28: =SUM(AB28:AG28) -> 3189.735
A29: 0000000000301 | B29: JF大田魚集荷料 | C29: 0104 | D29: 大田荷役 | F29: =IF($E29="","",IFERROR(INDEX(担当者マスタ!$B$2:$B$101,MATCH($E29,担当者マスタ!$A$2:$A$101,0)),"※マスタ未登録")) | G29: 324.02 | H29: 342.285 | I29: 126.905 | J29: 169.83 | K29: 194.395 | L29: 235.235 | M29: =SUM(G29:L29) -> 1392.67 | N29: 324.02 | O29: 342.285 | P29: 126.905 | Q29: 169.83 | R29: 194.395 | S29: 235.235 | T29: =SUM(N29:S29) -> 1392.67 | U29: 404.685 | V29: 382.16 | W29: 183.675 | X29: 98.515 | Y29: 161.67 | Z29: 260.95 | AA29: =SUM(U29:Z29) -> 1491.655 | AB29: 404.685 | AC29: 382.16 | AD29: 183.675 | AE29: 98.515 | AF29: 161.67 | AG29: 260.95 | AH29: =SUM(AB29:AG29) -> 1491.655
A30: 0000000000321 | B30: JF大田市場洗浄料 | C30: 0104 | D30: 大田荷役 | F30: =IF($E30="","",IFERROR(INDEX(担当者マスタ!$B$2:$B$101,MATCH($E30,担当者マスタ!$A$2:$A$101,0)),"※マスタ未登録")) | G30: 208 | H30: 104 | I30: 96 | J30: 86 | K30: 72 | L30: 94 | M30: =SUM(G30:L30) -> 660 | N30: 208 | O30: 104 | P30: 96 | Q30: 86 | R30: 72 | S30: 94 | T30: =SUM(N30:S30) -> 660 | U30: 156 | V30: 151 | W30: 128 | X30: 64 | Y30: 99 | Z30: 162 | AA30: =SUM(U30:Z30) -> 760 | AB30: 156 | AC30: 151 | AD30: 128 | AE30: 64 | AF30: 99 | AG30: 162 | AH30: =SUM(AB30:AG30) -> 760
A31: 0000000000381 | B31: JF大田買取荷役料 | C31: 0104 | D31: 大田荷役 | F31: =IF($E31="","",IFERROR(INDEX(担当者マスタ!$B$2:$B$101,MATCH($E31,担当者マスタ!$A$2:$A$101,0)),"※マスタ未登録")) | G31: 299.1 | H31: 282 | I31: 145.5 | J31: 193.5 | K31: 184.2 | L31: 244.2 | M31: =SUM(G31:L31) -> 1348.5 | N31: 299.1 | O31: 282 | P31: 145.5 | Q31: 193.5 | R31: 184.2 | S31: 244.2 | T31: =SUM(N31:S31) -> 1348.5 | U31: 252.6 | V31: 299.4 | W31: 181.8 | X31: 130.5 | Y31: 170.4 | Z31: 323.1 | AA31: =SUM(U31:Z31) -> 1357.8 | AB31: 252.6 | AC31: 299.4 | AD31: 181.8 | AE31: 130.5 | AF31: 170.4 | AG31: 323.1 | AH31: =SUM(AB31:AG31) -> 1357.8
A32: 0000000002011 | B32: 琴代丸 | C32: 0104 | D32: 大田荷役 | F32: =IF($E32="","",IFERROR(INDEX(担当者マスタ!$B$2:$B$101,MATCH($E32,担当者マスタ!$A$2:$A$101,0)),"※マスタ未登録")) | G32: 90.695 | H32: 95.2 | I32: 47.855 | J32: 62.22 | K32: 41.395 | L32: 62.815 | M32: =SUM(G32:L32) -> 400.18 | N32: 90.695 | O32: 95.2 | P32: 47.855 | Q32: 62.22 | R32: 41.395 | S32: 62.815 | T32: =SUM(N32:S32) -> 400.18 | U32: 100.64 | V32: 120.87 | W32: 63.07 | X32: 20.825 | Y32: 33.83 | Z32: 110.245 | AA32: =SUM(U32:Z32) -> 449.48 | AB32: 100.64 | AC32: 120.87 | AD32: 63.07 | AE32: 20.825 | AF32: 33.83 | AG32: 110.245 | AH32: =SUM(AB32:AG32) -> 449.48
A33: 0000000002021 | B33: 玉千代丸 | C33: 0104 | D33: 大田荷役 | F33: =IF($E33="","",IFERROR(INDEX(担当者マスタ!$B$2:$B$101,MATCH($E33,担当者マスタ!$A$2:$A$101,0)),"※マスタ未登録")) | G33: 10.115 | H33: 0 | I33: 0 | J33: 0 | K33: 0.85 | L33: 8.415 | M33: =SUM(G33:L33) -> 19.38 | N33: 10.115 | O33: 0 | P33: 0 | Q33: 0 | R33: 0.85 | S33: 8.415 | T33: =SUM(N33:S33) -> 19.38 | U33: 10.2 | V33: 0 | W33: 0 | X33: 0 | Y33: 0 | Z33: 9.52 | AA33: =SUM(U33:Z33) -> 19.72 | AB33: 10.2 | AC33: 0 | AD33: 0 | AE33: 0 | AF33: 0 | AG33: 9.52 | AH33: =SUM(AB33:AG33) -> 19.72
A34: 0000000002031 | B34: 三和丸 | C34: 0104 | D34: 大田荷役 | F34: =IF($E34="","",IFERROR(INDEX(担当者マスタ!$B$2:$B$101,MATCH($E34,担当者マスタ!$A$2:$A$101,0)),"※マスタ未登録")) | G34: 94.35 | H34: 124.695 | I34: 64.855 | J34: 45.05 | K34: 87.975 | L34: 60.18 | M34: =SUM(G34:L34) -> 477.105 | N34: 94.35 | O34: 124.695 | P34: 64.855 | Q34: 45.05 | R34: 87.975 | S34: 60.18 | T34: =SUM(N34:S34) -> 477.105 | U34: 108.63 | V34: 117.555 | W34: 73.865 | X34: 25.84 | Y34: 73.695 | Z34: 88.655 | AA34: =SUM(U34:Z34) -> 488.24 | AB34: 108.63 | AC34: 117.555 | AD34: 73.865 | AE34: 25.84 | AF34: 73.695 | AG34: 88.655 | AH34: =SUM(AB34:AG34) -> 488.24
A35: 0000000002041 | B35: 漁神丸 | C35: 0104 | D35: 大田荷役 | F35: =IF($E35="","",IFERROR(INDEX(担当者マスタ!$B$2:$B$101,MATCH($E35,担当者マスタ!$A$2:$A$101,0)),"※マスタ未登録")) | G35: 65.875 | H35: 71.4 | I35: 42.755 | J35: 44.71 | K35: 58.65 | L35: 79.39 | M35: =SUM(G35:L35) -> 362.78 | N35: 65.875 | O35: 71.4 | P35: 42.755 | Q35: 44.71 | R35: 58.65 | S35: 79.39 | T35: =SUM(N35:S35) -> 362.78 | U35: 84.32 | V35: 91.375 | W35: 24.565 | X35: 19.04 | Y35: 68.425 | Z35: 107.695 | AA35: =SUM(U35:Z35) -> 395.42 | AB35: 84.32 | AC35: 91.375 | AD35: 24.565 | AE35: 19.04 | AF35: 68.425 | AG35: 107.695 | AH35: =SUM(AB35:AG35) -> 395.42
... A41: 0000000703291 | B41: ㈱ｻﾝﾏﾙｺ-運送委託- | C41: 0104 | D41: 大田荷役 | F41: =IF($E41="","",IFERROR(INDEX(担当者マスタ!$B$2:$B$101,MATCH($E41,担当者マスタ!$A$2:$A$101,0)),"※マスタ未登録")) | G41: 0 | H41: 0 | I41: 0 | J41: 0 | K41: 0 | L41: 0 | M41: =SUM(G41:L41) -> 0 | N41: 0 | O41: 0 | P41: 0 | Q41: 0 | R41: 0 | S41: 0 | T41: =SUM(N41:S41) -> 0 | U41: 200 | V41: 160 | W41: 160 | X41: 160 | Y41: 160 | Z41: 160 | AA41: =SUM(U41:Z41) -> 1000 | AB41: 200 | AC41: 160 | AD41: 160 | AE41: 160 | AF41: 160 | AG41: 160 | AH41: =SUM(AB41:AG41) -> 1000
C42: 0104 集計 | D42: 大田荷役 | G42: =SUBTOTAL(9,G24:G41) -> 4648.265 | H42: =SUBTOTAL(9,H24:H41) -> 5210.065 | I42: =SUBTOTAL(9,I24:I41) -> 2151.435 | J42: =SUBTOTAL(9,J24:J41) -> 2392.025 | K42: =SUBTOTAL(9,K24:K41) -> 2549.38 | L42: =SUBTOTAL(9,L24:L41) -> 3275.315 | M42: =SUBTOTAL(9,M24:M41) -> 20226.485 | N42: =SUBTOTAL(9,N24:N41) -> 3018.701 | ... AH42: =SUBTOTAL(9,AH24:AH41) -> 14913.779
A43: 0000000000461 | B43: JFしまね冷蔵庫経費 | C43: 0106 | D43: 浜田荷役 | F43: =IF($E43="","",IFERROR(INDEX(担当者マスタ!$B$2:$B$101,MATCH($E43,担当者マスタ!$A$2:$A$101,0)),"※マスタ未登録")) | G43: 601.85 | H43: 504.56 | I43: 497.71 | J43: 815.24 | K43: 665.8 | L43: 528.65 | M43: =SUM(G43:L43) -> 3613.81 | N43: 201.35 | O43: 176.077 | P43: 199.912 | Q43: 427.699 | R43: 319.403 | S43: 183.618 | T43: =SUM(N43:S43) -> 1508.059 | U43: 907.04 | V43: 998.405 | W43: 1589.864 | X43: 676.25 | Y43: 518.45 | Z43: 736.25 | AA43: =SUM(U43:Z43) -> 5426.259 | AB43: 547.938 | AC43: 661.597 | AD43: 854.845 | AE43: 376.682 | AF43: 273.077 | AG43: 382.053 | AH43: =SUM(AB43:AG43) -> 3096.192
A44: 0000000003011 | B44: 弘氣丸 | C44: 0106 | D44: 浜田荷役 | F44: =IF($E44="","",IFERROR(INDEX(担当者マスタ!$B$2:$B$101,MATCH($E44,担当者マスタ!$A$2:$A$101,0)),"※マスタ未登録")) | G44: 0 | H44: 0 | I44: 0 | J44: 0.2 | K44: 0 | L44: 0 | M44: =SUM(G44:L44) -> 0.2 | N44: 0 | O44: 0 | P44: 0 | Q44: 0.2 | R44: 0 | S44: 0 | T44: =SUM(N44:S44) -> 0.2 | U44: 0 | V44: 0 | W44: 0 | X44: 0 | Y44: 0 | Z44: 0 | AA44: =SUM(U44:Z44) -> 0 | AB44: 0 | AC44: 0 | AD44: 0 | AE44: 0 | AF44: 0 | AG44: 0 | AH44: =SUM(AB44:AG44) -> 0
A45: 0000000003021 | B45: TT19 1豊生丸 | C45: 0106 | D45: 浜田荷役 | F45: =IF($E45="","",IFERROR(INDEX(担当者マスタ!$B$2:$B$101,MATCH($E45,担当者マスタ!$A$2:$A$101,0)),"※マスタ未登録")) | G45: 0 | H45: 0 | I45: 0 | J45: 0 | K45: 0 | L45: 0 | M45: =SUM(G45:L45) -> 0 | N45: 0 | O45: 0 | P45: 0 | Q45: 0 | R45: 0 | S45: 0 | T45: =SUM(N45:S45) -> 0 | U45: 7.2 | V45: 0 | W45: 0 | X45: 0 | Y45: 0 | Z45: 0 | AA45: =SUM(U45:Z45) -> 7.2 | AB45: 7.2 | AC45: 0 | AD45: 0 | AE45: 0 | AF45: 0 | AG45: 0 | AH45: =SUM(AB45:AG45) -> 7.2
A46: 0000000003031 | B46: 71天王丸 | C46: 0106 | D46: 浜田荷役 | F46: =IF($E46="","",IFERROR(INDEX(担当者マスタ!$B$2:$B$101,MATCH($E46,担当者マスタ!$A$2:$A$101,0)),"※マスタ未登録")) | G46: 0 | H46: 0 | I46: 0 | J46: 0 | K46: 0 | L46: 0 | M46: =SUM(G46:L46) -> 0 | N46: 0 | O46: 0 | P46: 0 | Q46: 0 | R46: 0 | S46: 0 | T46: =SUM(N46:S46) -> 0 | U46: 0 | V46: 0 | W46: 0 | X46: 469.65 | Y46: 0 | Z46: 186 | AA46: =SUM(U46:Z46) -> 655.65 | AB46: 0 | AC46: 0 | AD46: 0 | AE46: 236.749 | AF46: 0 | AG46: 86.832 | AH46: =SUM(AB46:AG46) -> 323.581
A47: 0000000003051 | B47: 第 25大祐丸 | C47: 0106 | D47: 浜田荷役 | F47: =IF($E47="","",IFERROR(INDEX(担当者マスタ!$B$2:$B$101,MATCH($E47,担当者マスタ!$A$2:$A$101,0)),"※マスタ未登録")) | G47: 0 | H47: 0 | I47: 0 | J47: 0 | K47: 0 | L47: 0 | M47: =SUM(G47:L47) -> 0 | N47: 0 | O47: 0 | P47: 0 | Q47: 0 | R47: 0 | S47: 0 | T47: =SUM(N47:S47) -> 0 | U47: 0 | V47: 0 | W47: 0 | X47: 0 | Y47: 0 | Z47: 189.876 | AA47: =SUM(U47:Z47) -> 189.876 | AB47: 0 | AC47: 0 | AD47: 0 | AE47: 0 | AF47: 0 | AG47: 85.012 | AH47: =SUM(AB47:AG47) -> 85.012
A48: 0000000003061 | B48: 大田 協和丸 | C48: 0106 | D48: 浜田荷役 | F48: =IF($E48="","",IFERROR(INDEX(担当者マスタ!$B$2:$B$101,MATCH($E48,担当者マスタ!$A$2:$A$101,0)),"※マスタ未登録")) | G48: 0 | H48: 0 | I48: 0 | J48: 0 | K48: 0 | L48: 0 | M48: =SUM(G48:L48) -> 0 | N48: 0 | O48: 0 | P48: 0 | Q48: 0 | R48: 0 | S48: 0 | T48: =SUM(N48:S48) -> 0 | U48: 0 | V48: 147 | W48: 0 | X48: 0 | Y48: 0 | Z48: 20.928 | AA48: =SUM(U48:Z48) -> 167.928 | AB48: 0 | AC48: 72.5 | AD48: 0 | AE48: 0 | AF48: 0 | AG48: 20.928 | AH48: =SUM(AB48:AG48) -> 93.428
A49: 0000000003101 | B49: 第85 天王丸 | C49: 0106 | D49: 浜田荷役 | F49: =IF($E49="","",IFERROR(INDEX(担当者マスタ!$B$2:$B$101,MATCH($E49,担当者マスタ!$A$2:$A$101,0)),"※マスタ未登録")) | G49: 0 | H49: 0 | I49: 0 | J49: 0 | K49: 0 | L49: 0 | M49: =SUM(G49:L49) -> 0 | N49: 0 | O49: 0 | P49: 0 | Q49: 0 | R49: 0 | S49: 0 | T49: =SUM(N49:S49) -> 0 | U49: 0 | V49: 0 | W49: 170.5 | X49: 0 | Y49: 696.726 | Z49: 0 | AA49: =SUM(U49:Z49) -> 867.226 | AB49: 0 | AC49: 0 | AD49: 84.745 | AE49: 0 | AF49: 355.627 | AG49: 0 | AH49: =SUM(AB49:AG49) -> 440.372
A50: 0000000003141 | B50: FK19 2弘氣丸 | C50: 0106 | D50: 浜田荷役 | F50: =IF($E50="","",IFERROR(INDEX(担当者マスタ!$B$2:$B$101,MATCH($E50,担当者マスタ!$A$2:$A$101,0)),"※マスタ未登録")) | G50: 0 | H50: 0 | I50: 0 | J50: 0 | K50: 0 | L50: 0 | M50: =SUM(G50:L50) -> 0 | N50: 0 | O50: 0 | P50: 0 | Q50: 0 | R50: 0 | S50: 0 | T50: =SUM(N50:S50) -> 0 | U50: 19.3 | V50: 0 | W50: 0 | X50: 0 | Y50: 0 | Z50: 0 | AA50: =SUM(U50:Z50) -> 19.3 | AB50: 19.3 | AC50: 0 | AD50: 0 | AE50: 0 | AF50: 0 | AG50: 0 | AH50: =SUM(AB50:AG50) -> 19.3
A51: 0000000003151 | B51: YM19T 21清栄丸 | C51: 0106 | D51: 浜田荷役 | F51: =IF($E51="","",IFERROR(INDEX(担当者マスタ!$B$2:$B$101,MATCH($E51,担当者マスタ!$A$2:$A$101,0)),"※マスタ未登録")) | G51: 0 | H51: 0 | I51: 0 | J51: 0 | K51: 0 | L51: 0 | M51: =SUM(G51:L51) -> 0 | N51: 0 | O51: 0 | P51: 0 | Q51: 0 | R51: 0 | S51: 0 | T51: =SUM(N51:S51) -> 0 | U51: 4.5 | V51: 0 | W51: 0 | X51: 0 | Y51: 0 | Z51: 0 | AA51: =SUM(U51:Z51) -> 4.5 | AB51: 4.5 | AC51: 0 | AD51: 0 | AE51: 0 | AF51: 0 | AG51: 0 | AH51: =SUM(AB51:AG51) -> 4.5
A52: 0000000003161 | B52: 第28わかば丸 | C52: 0106 | D52: 浜田荷役 | F52: =IF($E52="","",IFERROR(INDEX(担当者マスタ!$B$2:$B$101,MATCH($E52,担当者マスタ!$A$2:$A$101,0)),"※マスタ未登録")) | G52: 0 | H52: 0 | I52: 0 | J52: 0 | K52: 0 | L52: 0 | M52: =SUM(G52:L52) -> 0 | N52: 0 | O52: 0 | P52: 0 | Q52: 0 | R52: 0 | S52: 0 | T52: =SUM(N52:S52) -> 0 | U52: 604.5 | V52: 694.126 | W52: 0 | X52: 0 | Y52: 0 | Z52: 0 | AA52: =SUM(U52:Z52) -> 1298.626 | AB52: 284.25 | AC52: 376.38 | AD52: 0 | AE52: 0 | AF52: 0 | AG52: 0 | AH52: =SUM(AB52:AG52) -> 660.63
A53: 0000000003181 | B53: HK19 21光漁丸 | C53: 0106 | D53: 浜田荷役 | F53: =IF($E53="","",IFERROR(INDEX(担当者マスタ!$B$2:$B$101,MATCH($E53,担当者マスタ!$A$2:$A$101,0)),"※マスタ未登録")) | G53: 0 | H53: 0 | I53: 0 | J53: 0 | K53: 0 | L53: 0 | M53: =SUM(G53:L53) -> 0 | N53: 0 | O53: 0 | P53: 0 | Q53: 0 | R53: 0 | S53: 0 | T53: =SUM(N53:S53) -> 0 | U53: 21.55 | V53: 0 | W53: 0 | X53: 0 | Y53: 0 | Z53: 0 | AA53: =SUM(U53:Z53) -> 21.55 | AB53: 21.55 | AC53: 0 | AD53: 0 | AE53: 0 | AF53: 0 | AG53: 0 | AH53: =SUM(AB53:AG53) -> 21.55
A54: 0000000003191 | B54: HK19 88松宝丸 | C54: 0106 | D54: 浜田荷役 | F54: =IF($E54="","",IFERROR(INDEX(担当者マスタ!$B$2:$B$101,MATCH($E54,担当者マスタ!$A$2:$A$101,0)),"※マスタ未登録")) | G54: 0 | H54: 0 | I54: 0 | J54: 0 | K54: 0 | L54: 0 | M54: =SUM(G54:L54) -> 0 | N54: 0 | O54: 0 | P54: 0 | Q54: 0 | R54: 0 | S54: 0 | T54: =SUM(N54:S54) -> 0 | U54: 8.85 | V54: 0 | W54: 0 | X54: 0 | Y54: 0 | Z54: 0 | AA54: =SUM(U54:Z54) -> 8.85 | AB54: 8.85 | AC54: 0 | AD54: 0 | AE54: 0 | AF54: 0 | AG54: 0 | AH54: =SUM(AB54:AG54) -> 8.85
... A117: 0000000301291 | B117: 村田漁村㈱-荷役- | C117: 0106 | D117: 浜田荷役 | F117: =IF($E117="","",IFERROR(INDEX(担当者マスタ!$B$2:$B$101,MATCH($E117,担当者マスタ!$A$2:$A$101,0)),"※マスタ未登録")) | G117: 324.61 | H117: 312.33 | I117: 180.11 | J117: 172.49 | K117: 148.23 | L117: 179.46 | M117: =SUM(G117:L117) -> 1317.23 | N117: 249.474 | O117: 233.087 | P117: 135.951 | Q117: 128.57 | R117: 111.774 | S117: 134.542 | T117: =SUM(N117:S117) -> 993.398 | U117: 195.94 | V117: 306.73 | W117: 337.05 | X117: 186.82 | Y117: 150.18 | Z117: 57.86 | AA117: =SUM(U117:Z117) -> 1234.58 | AB117: 160.176 | AC117: 251.71 | AD117: 271.931 | AE117: 147.973 | AF117: 111.406 | AG117: 43.001 | AH117: =SUM(AB117:AG117) -> 986.197
C118: 0106 集計 | D118: 浜田荷役 | G118: =SUBTOTAL(9,G43:G117) -> 7510.666 | H118: =SUBTOTAL(9,H43:H117) -> 4196.93 | I118: =SUBTOTAL(9,I43:I117) -> 2706.666 | J118: =SUBTOTAL(9,J43:J117) -> 3420.63 | K118: =SUBTOTAL(9,K43:K117) -> 1710.847 | L118: =SUBTOTAL(9,L43:L117) -> 2077.47 | M118: =SUBTOTAL(9,M43:M117) -> 21623.209 | N118: =SUBTOTAL(9,N43:N117) -> 4147.866 | ... AH118: =SUBTOTAL(9,AH43:AH117) -> 13207.823
C119: 総計 | G119: =SUBTOTAL(9,G2:G118) -> 48262.182 | H119: =SUBTOTAL(9,H2:H118) -> 39463.691 | I119: =SUBTOTAL(9,I2:I118) -> 23814.872 | J119: =SUBTOTAL(9,J2:J118) -> 27112.075 | K119: =SUBTOTAL(9,K2:K118) -> 25301.812 | L119: =SUBTOTAL(9,L2:L118) -> 31823.205 | M119: =SUBTOTAL(9,M2:M118) -> 195777.84 | N119: =SUBTOTAL(9,N2:N118) -> 14339.964 | ... AH119: =SUBTOTAL(9,AH2:AH118) -> 80478.622

Sheet 鳥栖・静岡・東京
A1: 得意先コード | B1: 得意先略称 | C1: 担当者コード | D1: 担当者名 | E1: 新担当者コード | F1: 新担当者 | G1: 2024/10売上 | H1: 2024/11売上 | I1: 2024/12売上 | J1: 2025/01売上 | K1: 2025/02売上 | L1: 2025/03売上 | M1: 前年度売上合計 | N1: 2024/10粗利益 | O1: 2024/11粗利益 | P1: 2024/12粗利益 | Q1: 2025/01粗利益 | R1: 2025/02粗利益 | S1: 2025/03粗利益 | T1: 前年度粗利益合計 | U1: 2025/10売上 | V1: 2025/11売上 | W1: 2025/12売上 | X1: 2026/01売上 | Y1: 2026/02売上 | Z1: 2026/03売上 | AA1: 今年度売上合計 | AB1: 2025/10粗利益 | AC1: 2025/11粗利益 | AD1: 2025/12粗利益 | AE1: 2026/01粗利益 | AF1: 2026/02粗利益 | AG1: 2026/03粗利益 | AH1: 今年度粗利益合計
A2: 0000000001124 | B2: ｶﾈｹﾞﾝ | C2: 0042 | D2: 馬場部長 | F2: =IF($E2="","",IFERROR(INDEX(担当者マスタ!$B$2:$B$101,MATCH($E2,担当者マスタ!$A$2:$A$101,0)),"※マスタ未登録")) | G2: 1530.202 | H2: 1331.485 | I2: 1865.623 | J2: 394.99 | K2: 1245.073 | L2: 1051.65 | M2: =SUM(G2:L2) -> 7419.023 | N2: 176.074 | O2: 155.217 | P2: 216.279 | Q2: 32.626 | R2: 125.93 | S2: 125.627 | T2: =SUM(N2:S2) -> 831.753 | U2: 889.595 | V2: 897.82 | W2: 1410.589 | X2: 691.51 | Y2: 1010.252 | Z2: 981.539 | AA2: =SUM(U2:Z2) -> 5881.305 | AB2: 58.735 | AC2: 65.553 | AD2: 134.763 | AE2: 77.664 | AF2: 84.594 | AG2: 76.589 | AH2: =SUM(AB2:AG2) -> 497.898
A3: 0000000005624 | B3: ㈱ﾘﾝｶﾞｰﾊｯﾄ東京本社 | C3: 0042 | D3: 馬場部長 | F3: =IF($E3="","",IFERROR(INDEX(担当者マスタ!$B$2:$B$101,MATCH($E3,担当者マスタ!$A$2:$A$101,0)),"※マスタ未登録")) | G3: 27357.149 | H3: 29842.14 | I3: 35394.144 | J3: 28095.015 | K3: 29989.885 | L3: 33407.761 | M3: =SUM(G3:L3) -> 184086.09 | N3: 3739.394 | O3: 4189.368 | P3: 5089.205 | Q3: 3916.215 | R3: 4233.37 | S3: 5641.747 | T3: =SUM(N3:S3) -> 26809.299 | U3: 28564.537 | V3: 30135.229 | W3: 37931.299 | X3: 26226.4 | Y3: 27549.329 | Z3: 29111.012 | AA3: =SUM(U3:Z3) -> 179517.81 | AB3: 3889.708 | AC3: 4241.439 | AD3: 5138.571 | AE3: 3462.655 | AF3: 3900.067 | AG3: 5139.252 | AH3: =SUM(AB3:AG3) -> 25771.692
A4: 0000000105624 | B4: ㈱ﾘﾝｶﾞｰﾊｯﾄ東京本社 | C4: 0042 | D4: 馬場部長 | F4: =IF($E4="","",IFERROR(INDEX(担当者マスタ!$B$2:$B$101,MATCH($E4,担当者マスタ!$A$2:$A$101,0)),"※マスタ未登録")) | G4: 0 | H4: 0 | I4: 0 | J4: 0 | K4: 0 | L4: 0 | M4: =SUM(G4:L4) -> 0 | N4: 0 | O4: 0 | P4: 0 | Q4: 0 | R4: 0 | S4: 0 | T4: =SUM(N4:S4) -> 0 | U4: 0 | V4: 3 | W4: 0 | X4: 0 | Y4: 0 | Z4: 0 | AA4: =SUM(U4:Z4) -> 3 | AB4: 0 | AC4: 1.552 | AD4: 0 | AE4: 0 | AF4: 0 | AG4: 0 | AH4: =SUM(AB4:AG4) -> 1.552
C5: 0042 集計 | D5: 馬場部長 | G5: =SUBTOTAL(9,G2:G4) -> 28887.351 | H5: =SUBTOTAL(9,H2:H4) -> 31173.625 | I5: =SUBTOTAL(9,I2:I4) -> 37259.767 | J5: =SUBTOTAL(9,J2:J4) -> 28490.005 | K5: =SUBTOTAL(9,K2:K4) -> 31234.958 | L5: =SUBTOTAL(9,L2:L4) -> 34459.411 | M5: =SUBTOTAL(9,M2:M4) -> 191505.12 | N5: =SUBTOTAL(9,N2:N4) -> 3915.468 | ... AH5: =SUBTOTAL(9,AH2:AH4) -> 26271.142
A6: 0000000000134 | B6: ㈱蔵出しめんたい本舗 | C6: 0046 | D6: 角田 | F6: =IF($E6="","",IFERROR(INDEX(担当者マスタ!$B$2:$B$101,MATCH($E6,担当者マスタ!$A$2:$A$101,0)),"※マスタ未登録")) | G6: 926.207 | H6: 759.301 | I6: 1096.286 | J6: 652.599 | K6: 449.989 | L6: 781.715 | M6: =SUM(G6:L6) -> 4666.097 | N6: 228.524 | O6: 194.533 | P6: 245.062 | Q6: 158.8 | R6: 102.124 | S6: 196.424 | T6: =SUM(N6:S6) -> 1125.467 | U6: 506.412 | V6: 663.9 | W6: 1205.97 | X6: 369.917 | Y6: 513.973 | Z6: 847.946 | AA6: =SUM(U6:Z6) -> 4108.118 | AB6: 108.136 | AC6: 151.327 | AD6: 268.297 | AE6: 70.888 | AF6: 114.738 | AG6: 197.093 | AH6: =SUM(AB6:AG6) -> 910.479
A7: 0000000000144 | B7: ㈲東洋ﾃｸﾆｶﾙﾌｰﾂﾞ | C7: 0046 | D7: 角田 | F7: =IF($E7="","",IFERROR(INDEX(担当者マスタ!$B$2:$B$101,MATCH($E7,担当者マスタ!$A$2:$A$101,0)),"※マスタ未登録")) | G7: 37.375 | H7: 0 | I7: 109.8 | J7: 72 | K7: 97 | L7: 191.696 | M7: =SUM(G7:L7) -> 507.871 | N7: 7.15 | O7: 0 | P7: 19.44 | Q7: 14.4 | R7: 23.4 | S7: 38.61 | T7: =SUM(N7:S7) -> 103 | U7: 204.59 | V7: 37.03 | W7: 0 | X7: 169.3 | Y7: 159.41 | Z7: 123.41 | AA7: =SUM(U7:Z7) -> 693.74 | AB7: 37.688 | AC7: 7.084 | AD7: 0 | AE7: 30.94 | AF7: 31.01 | AG7: 23.81 | AH7: =SUM(AB7:AG7) -> 130.532
A8: 0000000000164 | B8: SUS㈱ | C8: 0046 | D8: 角田 | F8: =IF($E8="","",IFERROR(INDEX(担当者マスタ!$B$2:$B$101,MATCH($E8,担当者マスタ!$A$2:$A$101,0)),"※マスタ未登録")) | G8: 49.09 | H8: 0 | I8: 81.1 | J8: 0 | K8: 44.1 | L8: 37 | M8: =SUM(G8:L8) -> 211.29 | N8: 10.18 | O8: 0 | P8: 7.92 | Q8: 0 | R8: 2.52 | S8: 5.4 | T8: =SUM(N8:S8) -> 26.02 | U8: 80.85 | V8: 0 | W8: 0 | X8: 0 | Y8: 0 | Z8: 0 | AA8: =SUM(U8:Z8) -> 80.85 | AB8: 11.55 | AC8: 0 | AD8: 0 | AE8: 0 | AF8: 0 | AG8: 0 | AH8: =SUM(AB8:AG8) -> 11.55
A9: 0000000000224 | B9: ㈲東龍食品★ | C9: 0046 | D9: 角田 | F9: =IF($E9="","",IFERROR(INDEX(担当者マスタ!$B$2:$B$101,MATCH($E9,担当者マスタ!$A$2:$A$101,0)),"※マスタ未登録")) | G9: 7.725 | H9: 0 | I9: 0 | J9: 0 | K9: 0 | L9: 0 | M9: =SUM(G9:L9) -> 7.725 | N9: 0.99 | O9: 0 | P9: 0 | Q9: 0 | R9: 0 | S9: 0 | T9: =SUM(N9:S9) -> 0.99 | U9: 0 | V9: 0 | W9: 0 | X9: 0 | Y9: 0 | Z9: 0 | AA9: =SUM(U9:Z9) -> 0 | AB9: 0 | AC9: 0 | AD9: 0 | AE9: 0 | AF9: 0 | AG9: 0 | AH9: =SUM(AB9:AG9) -> 0
A10: 0000000000584 | B10: みよしの食堂 | C10: 0046 | D10: 角田 | F10: =IF($E10="","",IFERROR(INDEX(担当者マスタ!$B$2:$B$101,MATCH($E10,担当者マスタ!$A$2:$A$101,0)),"※マスタ未登録")) | G10: 0 | H10: 59.968 | I10: 26.51 | J10: 2.88 | K10: 17.119 | L10: 35.247 | M10: =SUM(G10:L10) -> 141.724 | N10: 0 | O10: 15.543 | P10: 5.516 | Q10: 1 | R10: 3.168 | S10: 7.718 | T10: =SUM(N10:S10) -> 32.945 | U10: 29.76 | V10: 18.713 | W10: 22.492 | X10: 22.213 | Y10: 10.748 | Z10: 29.211 | AA10: =SUM(U10:Z10) -> 133.137 | AB10: 8.48 | AC10: 3.481 | AD10: 4.588 | AE10: 4.391 | AF10: 2.261 | AG10: 5.913 | AH10: =SUM(AB10:AG10) -> 29.114
A11: 0000000000764 | B11: ㈱堀内 | C11: 0046 | D11: 角田 | F11: =IF($E11="","",IFERROR(INDEX(担当者マスタ!$B$2:$B$101,MATCH($E11,担当者マスタ!$A$2:$A$101,0)),"※マスタ未登録")) | G11: 631.209 | H11: 580.319 | I11: 1276.172 | J11: 523.884 | K11: 569.164 | L11: 1150.085 | M11: =SUM(G11:L11) -> 4730.833 | N11: 151.826 | O11: 140.356 | P11: 193.924 | Q11: 113.591 | R11: 118.768 | S11: 257.024 | T11: =SUM(N11:S11) -> 975.489 | U11: 834.816 | V11: 556.825 | W11: 726.23 | X11: 538.467 | Y11: 631.999 | Z11: 742.886 | AA11: =SUM(U11:Z11) -> 4031.223 | AB11: 170.074 | AC11: 114.111 | AD11: 172.466 | AE11: 104.994 | AF11: 126.37 | AG11: 149.427 | AH11: =SUM(AB11:AG11) -> 837.442
A12: 0000000000834 | B12: ㈱どんどんﾗｲｽ福岡 | C12: 0046 | D12: 角田 | F12: =IF($E12="","",IFERROR(INDEX(担当者マスタ!$B$2:$B$101,MATCH($E12,担当者マスタ!$A$2:$A$101,0)),"※マスタ未登録")) | G12: 349.65 | H12: 286.5 | I12: 1646.462 | J12: 1908.85 | K12: 146.45 | L12: 276.1 | M12: =SUM(G12:L12) -> 4614.012 | N12: 44.7 | O12: 37.5 | P12: 306.793 | Q12: 295.3 | R12: 14.1 | S12: 37.2 | T12: =SUM(N12:S12) -> 735.593 | U12: 332.029 | V12: 350.142 | W12: 1916.059 | X12: 1027.65 | Y12: 203.2 | Z12: 357.75 | AA12: =SUM(U12:Z12) -> 4186.83 | AB12: 42.949 | AC12: 49.093 | AD12: 364.779 | AE12: 154.7 | AF12: 30.6 | AG12: 52.25 | AH12: =SUM(AB12:AG12) -> 694.371
A13: 0000000000864 | B13: ㈱堀江本店 | C13: 0046 | D13: 角田 | F13: =IF($E13="","",IFERROR(INDEX(担当者マスタ!$B$2:$B$101,MATCH($E13,担当者マスタ!$A$2:$A$101,0)),"※マスタ未登録")) | G13: 181.147 | H13: 141.154 | I13: 166.796 | J13: 89.283 | K13: 115.844 | L13: 107.151 | M13: =SUM(G13:L13) -> 801.375 | N13: 32.262 | O13: 24.655 | P13: 28.868 | Q13: 16.072 | R13: 19.799 | S13: 18.885 | T13: =SUM(N13:S13) -> 140.541 | U13: 152.698 | V13: 93.917 | W13: 151.24 | X13: 112.514 | Y13: 126.757 | Z13: 127.74 | AA13: =SUM(U13:Z13) -> 764.866 | AB13: 26.155 | AC13: 16.939 | AD13: 25.993 | AE13: 18.658 | AF13: 21.924 | AG13: 21.246 | AH13: =SUM(AB13:AG13) -> 130.915
A14: 0000000000924 | B14: ㈱ﾌﾚｯｼｭﾐｰﾄ | C14: 0046 | D14: 角田 | F14: =IF($E14="","",IFERROR(INDEX(担当者マスタ!$B$2:$B$101,MATCH($E14,担当者マスタ!$A$2:$A$101,0)),"※マスタ未登録")) | G14: 0 | H14: 0 | I14: 0 | J14: 11.49 | K14: 19.15 | L14: 0 | M14: =SUM(G14:L14) -> 30.64 | N14: 0 | O14: 0 | P14: 0 | Q14: 3.66 | R14: 6.1 | S14: 0 | T14: =SUM(N14:S14) -> 9.76 | U14: 0 | V14: 61.28 | W14: 30.64 | X14: 0 | Y14: 0 | Z14: 53.62 | AA14: =SUM(U14:Z14) -> 145.54 | AB14: 0 | AC14: 15.344 | AD14: 7.672 | AE14: 0 | AF14: 0 | AG14: 13.426 | AH14: =SUM(AB14:AG14) -> 36.442
A15: 0000000000944 | B15: ㈱紀文ﾌﾚｯｼｭｼｽﾃﾑ | C15: 0046 | D15: 角田 | F15: =IF($E15="","",IFERROR(INDEX(担当者マスタ!$B$2:$B$101,MATCH($E15,担当者マスタ!$A$2:$A$101,0)),"※マスタ未登録")) | G15: 215.808 | H15: 227.776 | I15: 341.622 | J15: 33.752 | K15: 236.224 | L15: 236.224 | M15: =SUM(G15:L15) -> 1291.406 | N15: 79.6 | O15: 83.816 | P15: 126.154 | Q15: -32.85 | R15: 86.792 | S15: 86.792 | T15: =SUM(N15:S15) -> 430.304 | U15: 229.184 | V15: 228.48 | W15: 340.992 | X15: 112.636 | Y15: 227.072 | Z15: 229.184 | AA15: =SUM(U15:Z15) -> 1367.548 | AB15: 84.312 | AC15: 84.064 | AD15: 125.13 | AE15: 41.445 | AF15: 83.568 | AG15: 84.312 | AH15: =SUM(AB15:AG15) -> 502.831
A16: 0000000000954 | B16: ㈲ｱｲｹｰﾌｰｽﾞ | C16: 0046 | D16: 角田 | F16: =IF($E16="","",IFERROR(INDEX(担当者マスタ!$B$2:$B$101,MATCH($E16,担当者マスタ!$A$2:$A$101,0)),"※マスタ未登録")) | G16: 0 | H16: 0 | I16: 56.705 | J16: 12 | K16: 0 | L16: 0 | M16: =SUM(G16:L16) -> 68.705 | N16: 0 | O16: 0 | P16: 18.445 | Q16: 2.4 | R16: 0 | S16: 0 | T16: =SUM(N16:S16) -> 20.845 | U16: 34.27 | V16: 56.597 | W16: 18.187 | X16: 44.626 | Y16: 66.159 | Z16: 9.683 | AA16: =SUM(U16:Z16) -> 229.522 | AB16: 6.187 | AC16: 16.516 | AD16: 3.283 | AE16: 8.056 | AF16: 18.266 | AG16: 1.748 | AH16: =SUM(AB16:AG16) -> 54.056
A17: 0000000000964 | B17: ㈱ｱﾙﾐｽ | C17: 0046 | D17: 角田 | F17: =IF($E17="","",IFERROR(INDEX(担当者マスタ!$B$2:$B$101,MATCH($E17,担当者マスタ!$A$2:$A$101,0)),"※マスタ未登録")) | G17: 0 | H17: 18.9 | I17: 20.856 | J17: 7.5 | K17: 9.456 | L17: 11.4 | M17: =SUM(G17:L17) -> 68.112 | N17: 0 | O17: 3 | P17: 2.916 | Q17: 1.5 | R17: 1.656 | S17: 1.5 | T17: =SUM(N17:S17) -> 10.572 | U17: 0 | V17: 25.584 | W17: 7.5 | X17: 11.4 | Y17: 9.456 | Z17: 174.4 | AA17: =SUM(U17:Z17) -> 228.34 | AB17: 0 | AC17: 3.984 | AD17: 1.5 | AE17: 1.5 | AF17: 1.656 | AG17: 17.5 | AH17: =SUM(AB17:AG17) -> 26.14
... A41: 0000000122714 | B41: ㈱梅の花ｸﾞﾙｰﾌﾟ | C41: 0046 | D41: 角田 | F41: =IF($E41="","",IFERROR(INDEX(担当者マスタ!$B$2:$B$101,MATCH($E41,担当者マスタ!$A$2:$A$101,0)),"※マスタ未登録")) | G41: 883.57 | H41: 930.036 | I41: 1458.576 | J41: 319.336 | K41: 383.991 | L41: 189.788 | M41: =SUM(G41:L41) -> 4165.297 | N41: 133.69 | O41: 163.063 | P41: 231.505 | Q41: 42.096 | R41: 50.184 | S41: 34.342 | T41: =SUM(N41:S41) -> 654.88 | U41: 824.354 | V41: 482.994 | W41: 1421.256 | X41: 143.308 | Y41: 568.138 | Z41: 307.246 | AA41: =SUM(U41:Z41) -> 3747.296 | AB41: 144.314 | AC41: 83.604 | AD41: 241.593 | AE41: 21.738 | AF41: 96.439 | AG41: 47.786 | AH41: =SUM(AB41:AG41) -> 635.474
C42: 0046 集計 | D42: 角田 | G42: =SUBTOTAL(9,G6:G41) -> 5555.408 | H42: =SUBTOTAL(9,H6:H41) -> 5677.615 | I42: =SUBTOTAL(9,I6:I41) -> 8435.442 | J42: =SUBTOTAL(9,J6:J41) -> 5428.488 | K42: =SUBTOTAL(9,K6:K41) -> 4451.975 | L42: =SUBTOTAL(9,L6:L41) -> 4939.475 | M42: =SUBTOTAL(9,M6:M41) -> 34488.403 | N42: =SUBTOTAL(9,N6:N41) -> 1108.937 | ... AH42: =SUBTOTAL(9,AH6:AH41) -> 6243.223
A43: 0000000002408 | B43: ｲﾆｼｵﾌｰｽﾞ㈱ | C43: 0552 | D43: 馬場部長(東京) | F43: =IF($E43="","",IFERROR(INDEX(担当者マスタ!$B$2:$B$101,MATCH($E43,担当者マスタ!$A$2:$A$101,0)),"※マスタ未登録")) | G43: 369.6 | H43: 369.6 | I43: 369.6 | J43: 369.6 | K43: 369.6 | L43: 369.6 | M43: =SUM(G43:L43) -> 2217.6 | N43: 35.2 | O43: 35.2 | P43: 35.2 | Q43: 35.2 | R43: 35.2 | S43: 35.2 | T43: =SUM(N43:S43) -> 211.2 | U43: 369.6 | V43: 369.6 | W43: 277.2 | X43: 277.2 | Y43: 369.6 | Z43: 462 | AA43: =SUM(U43:Z43) -> 2125.2 | AB43: 35.2 | AC43: 35.2 | AD43: 26.4 | AE43: 26.4 | AF43: 35.2 | AG43: 44 | AH43: =SUM(AB43:AG43) -> 202.4
A44: 0000000003708 | B44: ㈱栄和ﾌﾟﾗﾝﾆﾝｸﾞ | C44: 0552 | D44: 馬場部長(東京) | F44: =IF($E44="","",IFERROR(INDEX(担当者マスタ!$B$2:$B$101,MATCH($E44,担当者マスタ!$A$2:$A$101,0)),"※マスタ未登録")) | G44: 0 | H44: 74.4 | I44: 975.883 | J44: 73.16 | K44: 0 | L44: 392.64 | M44: =SUM(G44:L44) -> 1516.083 | N44: 0 | O44: 9.9 | P44: 135.902 | Q44: 9.735 | R44: 0 | S44: 47.04 | T44: =SUM(N44:S44) -> 202.577 | U44: 247.895 | V44: 42.3 | W44: 488.768 | X44: 0 | Y44: 430.268 | Z44: 331.928 | AA44: =SUM(U44:Z44) -> 1541.159 | AB44: 29.67 | AC44: 7.572 | AD44: 59.948 | AE44: 0 | AF44: 51.548 | AG44: 40.713 | AH44: =SUM(AB44:AG44) -> 189.451
A45: 0000000005628 | B45: ㈱ﾘﾝｶﾞｰﾊｯﾄ東京本社 | C45: 0552 | D45: 馬場部長(東京) | F45: =IF($E45="","",IFERROR(INDEX(担当者マスタ!$B$2:$B$101,MATCH($E45,担当者マスタ!$A$2:$A$101,0)),"※マスタ未登録")) | G45: 17.475 | H45: 17.475 | I45: 17.475 | J45: 17.475 | K45: 450 | L45: 17.475 | M45: =SUM(G45:L45) -> 537.375 | N45: 3.375 | O45: 3.375 | P45: 3.375 | Q45: 3.375 | R45: 15 | S45: 3.375 | T45: =SUM(N45:S45) -> 31.875 | U45: 17.475 | V45: 17.475 | W45: 17.475 | X45: 0 | Y45: 17.475 | Z45: 17.475 | AA45: =SUM(U45:Z45) -> 87.375 | AB45: 3.375 | AC45: 3.375 | AD45: 3.375 | AE45: 0 | AF45: 3.375 | AG45: 3.375 | AH45: =SUM(AB45:AG45) -> 16.875
A46: 0000000011628 | B46: ﾘﾝｶﾞｰﾌｰｽﾞ㈱ | C46: 0552 | D46: 馬場部長(東京) | F46: =IF($E46="","",IFERROR(INDEX(担当者マスタ!$B$2:$B$101,MATCH($E46,担当者マスタ!$A$2:$A$101,0)),"※マスタ未登録")) | G46: 100 | H46: 100 | I46: 100 | J46: 100 | K46: 700 | L46: 100 | M46: =SUM(G46:L46) -> 1200 | N46: 50 | O46: 50 | P46: 50 | Q46: 50 | R46: 120 | S46: 100 | T46: =SUM(N46:S46) -> 420 | U46: 100 | V46: 100 | W46: 100 | X46: 130.002 | Y46: 100 | Z46: 100 | AA46: =SUM(U46:Z46) -> 630.002 | AB46: 100 | AC46: 100 | AD46: 100 | AE46: 109.212 | AF46: 100 | AG46: 100 | AH46: =SUM(AB46:AG46) -> 609.212
A47: 0000000029808 | B47: ﾃｨｰﾌｰｽﾞ･ｼﾞｬﾊﾟﾝ㈱ | C47: 0552 | D47: 馬場部長(東京) | F47: =IF($E47="","",IFERROR(INDEX(担当者マスタ!$B$2:$B$101,MATCH($E47,担当者マスタ!$A$2:$A$101,0)),"※マスタ未登録")) | G47: 54.5 | H47: 18 | I47: 49 | J47: 83.1 | K47: 42.7 | L47: 18 | M47: =SUM(G47:L47) -> 265.3 | N47: 7 | O47: 3 | P47: 9 | Q47: 9.6 | R47: 7.75 | S47: 3 | T47: =SUM(N47:S47) -> 39.35 | U47: 23.87 | V47: 83.1 | W47: 18 | X47: 43.5 | Y47: 18 | Z47: 18 | AA47: =SUM(U47:Z47) -> 204.47 | AB47: 8.87 | AC47: 9.6 | AD47: 3 | AE47: 14.1 | AF47: 3 | AG47: 3 | AH47: =SUM(AB47:AG47) -> 41.57
A48: 0000000067008 | B48: ㈱ｻﾝｷ | C48: 0552 | D48: 馬場部長(東京) | F48: =IF($E48="","",IFERROR(INDEX(担当者マスタ!$B$2:$B$101,MATCH($E48,担当者マスタ!$A$2:$A$101,0)),"※マスタ未登録")) | G48: 394.41 | H48: 202.183 | I48: 628.526 | J48: 399.146 | K48: 688.847 | L48: 339.586 | M48: =SUM(G48:L48) -> 2652.698 | N48: 42.993 | O48: 21.536 | P48: 56.354 | Q48: 38.912 | R48: 75.835 | S48: 45.418 | T48: =SUM(N48:S48) -> 281.048 | U48: 332.029 | V48: 319.839 | W48: 776.969 | X48: 479.833 | Y48: 246.164 | Z48: 514.108 | AA48: =SUM(U48:Z48) -> 2668.942 | AB48: 36.484 | AC48: 49.707 | AD48: 102.373 | AE48: 66.216 | AF48: 42.94 | AG48: 66.86 | AH48: =SUM(AB48:AG48) -> 364.58
A49: 0000000067208 | B49: 千倉水産加工販売㈱ | C49: 0552 | D49: 馬場部長(東京) | F49: =IF($E49="","",IFERROR(INDEX(担当者マスタ!$B$2:$B$101,MATCH($E49,担当者マスタ!$A$2:$A$101,0)),"※マスタ未登録")) | G49: 53.4 | H49: 10.3 | I49: 0 | J49: 0 | K49: 0 | L49: 12.8 | M49: =SUM(G49:L49) -> 76.5 | N49: 20.9 | O49: 1.5 | P49: 0 | Q49: 0 | R49: 0 | S49: 12.8 | T49: =SUM(N49:S49) -> 35.2 | U49: 10.3 | V49: 154.5 | W49: 0 | X49: 10.8 | Y49: 0 | Z49: 0 | AA49: =SUM(U49:Z49) -> 175.6 | AB49: 10.3 | AC49: 154.5 | AD49: 0 | AE49: 10.8 | AF49: 0 | AG49: 0 | AH49: =SUM(AB49:AG49) -> 175.6
A50: 0000000077608 | B50: 日鉄ｽﾃﾝﾚｽ鋼管㈱ | C50: 0552 | D50: 馬場部長(東京) | F50: =IF($E50="","",IFERROR(INDEX(担当者マスタ!$B$2:$B$101,MATCH($E50,担当者マスタ!$A$2:$A$101,0)),"※マスタ未登録")) | G50: 586 | H50: 250 | I50: 1005.6 | J50: 1780 | K50: 2163.2 | L50: 82.5 | M50: =SUM(G50:L50) -> 5867.3 | N50: 63.2 | O50: 25 | P50: 105.6 | Q50: 199.224 | R50: 246.4 | S50: 82.5 | T50: =SUM(N50:S50) -> 721.924 | U50: 873.6 | V50: 689.6 | W50: 0 | X50: 913.6 | Y50: 689.6 | Z50: 873.6 | AA50: =SUM(U50:Z50) -> 4040 | AB50: 100.2 | AC50: 76.4 | AD50: 0 | AE50: 101.4 | AF50: 76.4 | AG50: 100.2 | AH50: =SUM(AB50:AG50) -> 454.6
A51: 0000000077618 | B51: 日鉄ｽﾃﾝﾚｽ鋼管北関東 | C51: 0552 | D51: 馬場部長(東京) | F51: =IF($E51="","",IFERROR(INDEX(担当者マスタ!$B$2:$B$101,MATCH($E51,担当者マスタ!$A$2:$A$101,0)),"※マスタ未登録")) | G51: 0 | H51: 0 | I51: 0 | J51: 0 | K51: 7.492 | L51: 0 | M51: =SUM(G51:L51) -> 7.492 | N51: 0 | O51: 0 | P51: 0 | Q51: 0 | R51: 0.752 | S51: 0 | T51: =SUM(N51:S51) -> 0.752 | U51: 0 | V51: 0 | W51: 0 | X51: 0 | Y51: 0 | Z51: 0 | AA51: =SUM(U51:Z51) -> 0 | AB51: 0 | AC51: 0 | AD51: 0 | AE51: 0 | AF51: 0 | AG51: 0 | AH51: =SUM(AB51:AG51) -> 0
A52: 0000000078508 | B52: ㈱ﾌｼﾞｼﾛ | C52: 0552 | D52: 馬場部長(東京) | F52: =IF($E52="","",IFERROR(INDEX(担当者マスタ!$B$2:$B$101,MATCH($E52,担当者マスタ!$A$2:$A$101,0)),"※マスタ未登録")) | G52: 1323.6 | H52: 2273.85 | I52: 0 | J52: 0 | K52: 0 | L52: 1267 | M52: =SUM(G52:L52) -> 4864.45 | N52: 61.6 | O52: 104.5 | P52: 0 | Q52: 0 | R52: 0 | S52: 57.2 | T52: =SUM(N52:S52) -> 223.3 | U52: 0 | V52: 1466.2 | W52: 0 | X52: 3370.35 | Y52: 0 | Z52: 0 | AA52: =SUM(U52:Z52) -> 4836.55 | AB52: 0 | AC52: 66.2 | AD52: 0 | AE52: 154.35 | AF52: 0 | AG52: 0 | AH52: =SUM(AB52:AG52) -> 220.55
A53: 0000000085508 | B53: ㈱ﾏｰﾙ | C53: 0552 | D53: 馬場部長(東京) | F53: =IF($E53="","",IFERROR(INDEX(担当者マスタ!$B$2:$B$101,MATCH($E53,担当者マスタ!$A$2:$A$101,0)),"※マスタ未登録")) | G53: 0 | H53: 0 | I53: 0 | J53: 0 | K53: 151.92 | L53: 0 | M53: =SUM(G53:L53) -> 151.92 | N53: 0 | O53: 0 | P53: 0 | Q53: 0 | R53: 25.32 | S53: 0 | T53: =SUM(N53:S53) -> 25.32 | U53: 0 | V53: 601.36 | W53: 0 | X53: 0 | Y53: 0 | Z53: 0 | AA53: =SUM(U53:Z53) -> 601.36 | AB53: 0 | AC53: 100.16 | AD53: 0 | AE53: 0 | AF53: 0 | AG53: 0 | AH53: =SUM(AB53:AG53) -> 100.16
A54: 0000000100108 | B54: ㈱柴田屋酒店 | C54: 0552 | D54: 馬場部長(東京) | F54: =IF($E54="","",IFERROR(INDEX(担当者マスタ!$B$2:$B$101,MATCH($E54,担当者マスタ!$A$2:$A$101,0)),"※マスタ未登録")) | G54: 101.3 | H54: 183.05 | I54: 0 | J54: 0 | K54: 0 | L54: 0 | M54: =SUM(G54:L54) -> 284.35 | N54: 15.3 | O54: 21.55 | P54: 0 | Q54: 0 | R54: 0 | S54: 0 | T54: =SUM(N54:S54) -> 36.85 | U54: 0 | V54: 0 | W54: 0 | X54: 0 | Y54: 0 | Z54: 0 | AA54: =SUM(U54:Z54) -> 0 | AB54: 0 | AC54: 0 | AD54: 0 | AE54: 0 | AF54: 0 | AG54: 0 | AH54: =SUM(AB54:AG54) -> 0
... A70: 0000000112628 | B70: ﾘﾝｶﾞｰﾌｰｽﾞ㈱ | C70: 0552 | D70: 馬場部長(東京) | F70: =IF($E70="","",IFERROR(INDEX(担当者マスタ!$B$2:$B$101,MATCH($E70,担当者マスタ!$A$2:$A$101,0)),"※マスタ未登録")) | G70: 0 | H70: 0 | I70: 0 | J70: 1274 | K70: 0 | L70: 30 | M70: =SUM(G70:L70) -> 1304 | N70: 0 | O70: 0 | P70: 0 | Q70: 110.049 | R70: 0 | S70: 0 | T70: =SUM(N70:S70) -> 110.049 | U70: 175 | V70: 0 | W70: 0 | X70: 5068.736 | Y70: 0 | Z70: 0 | AA70: =SUM(U70:Z70) -> 5243.736 | AB70: 0 | AC70: 0 | AD70: 0 | AE70: 523.437 | AF70: 0 | AG70: 0 | AH70: =SUM(AB70:AG70) -> 523.437
C71: 0552 集計 | D71: 馬場部長(東京) | G71: =SUBTOTAL(9,G43:G70) -> 4268.315 | H71: =SUBTOTAL(9,H43:H70) -> 4138.386 | I71: =SUBTOTAL(9,I43:I70) -> 4990.354 | J71: =SUBTOTAL(9,J43:J70) -> 4412.269 | K71: =SUBTOTAL(9,K43:K70) -> 5294.179 | L71: =SUBTOTAL(9,L43:L70) -> 5516.358 | M71: =SUBTOTAL(9,M43:M70) -> 28619.861 | N71: =SUBTOTAL(9,N43:N70) -> 464.983 | ... AH71: =SUBTOTAL(9,AH43:AH70) -> 3947.438
C72: 総計 | G72: =SUBTOTAL(9,G2:G71) -> 38711.074 | H72: =SUBTOTAL(9,H2:H71) -> 40989.626 | I72: =SUBTOTAL(9,I2:I71) -> 50685.563 | J72: =SUBTOTAL(9,J2:J71) -> 38330.762 | K72: =SUBTOTAL(9,K2:K71) -> 40981.112 | L72: =SUBTOTAL(9,L2:L71) -> 44915.244 | M72: =SUBTOTAL(9,M2:M71) -> 254613.38 | N72: =SUBTOTAL(9,N2:N71) -> 5489.388 | ... AH72: =SUBTOTAL(9,AH2:AH71) -> 36461.803

Sheet 松江・境港
A1: 得意先コード | B1: 得意先略称 | C1: 担当者コード | D1: 担当者名 | E1: 新担当者コード | F1: 新担当者 | G1: 2024/10売上 | H1: 2024/11売上 | I1: 2024/12売上 | J1: 2025/01売上 | K1: 2025/02売上 | L1: 2025/03売上 | M1: 前年度売上合計 | N1: 2024/10粗利益 | O1: 2024/11粗利益 | P1: 2024/12粗利益 | Q1: 2025/01粗利益 | R1: 2025/02粗利益 | S1: 2025/03粗利益 | T1: 前年度粗利益合計 | U1: 2025/10売上 | V1: 2025/11売上 | W1: 2025/12売上 | X1: 2026/01売上 | Y1: 2026/02売上 | Z1: 2026/03売上 | AA1: 今年度売上合計 | AB1: 2025/10粗利益 | AC1: 2025/11粗利益 | AD1: 2025/12粗利益 | AE1: 2026/01粗利益 | AF1: 2026/02粗利益 | AG1: 2026/03粗利益 | AH1: 今年度粗利益合計
A2: 0000000010013 | B2: ㈱まつした米子 | C2: 0032 | D2: 飯塚 | F2: =IF($E2="","",IFERROR(INDEX(担当者マスタ!$B$2:$B$101,MATCH($E2,担当者マスタ!$A$2:$A$101,0)),"※マスタ未登録")) | G2: 7.225 | H2: 23.4 | I2: 23.4 | J2: 0 | K2: 18.925 | L2: 23.4 | M2: =SUM(G2:L2) -> 96.35 | N2: 1.015 | O2: 3.24 | P2: 1.44 | Q2: 0 | R2: 1.735 | S2: 1.44 | T2: =SUM(N2:S2) -> 8.87 | U2: 11.7 | V2: 22.11 | W2: 42.325 | X2: 0 | Y2: 18.925 | Z2: 35.1 | AA2: =SUM(U2:Z2) -> 130.16 | AB2: 0.72 | AC2: 2.49 | AD2: 3.175 | AE2: 0 | AF2: 1.735 | AG2: 2.16 | AH2: =SUM(AB2:AG2) -> 10.28
A3: 0000000034103 | B3: (株)岡田本店生花 | C3: 0032 | D3: 飯塚 | F3: =IF($E3="","",IFERROR(INDEX(担当者マスタ!$B$2:$B$101,MATCH($E3,担当者マスタ!$A$2:$A$101,0)),"※マスタ未登録")) | G3: 20.64 | H3: 39.6 | I3: 78 | J3: 16.6 | K3: 57.55 | L3: 73 | M3: =SUM(G3:L3) -> 285.39 | N3: 4.28 | O3: 9.585 | P3: 16.53 | Q3: 3.786 | R3: 12.6 | S3: 15.824 | T3: =SUM(N3:S3) -> 62.605 | U3: 18.45 | V3: 0 | W3: 0 | X3: 0 | Y3: 0 | Z3: 0 | AA3: =SUM(U3:Z3) -> 18.45 | AB3: 4.238 | AC3: 0 | AD3: 0 | AE3: 0 | AF3: 0 | AG3: 0 | AH3: =SUM(AB3:AG3) -> 4.238
A4: 0000000039023 | B4: ㈱米吾(共管費)030 | C4: 0032 | D4: 飯塚 | F4: =IF($E4="","",IFERROR(INDEX(担当者マスタ!$B$2:$B$101,MATCH($E4,担当者マスタ!$A$2:$A$101,0)),"※マスタ未登録")) | G4: 0 | H4: 0 | I4: 4.8 | J4: 0 | K4: 3.63 | L4: 3.63 | M4: =SUM(G4:L4) -> 12.06 | N4: 0 | O4: 0 | P4: 0.45 | Q4: 0 | R4: 0.73 | S4: 0.73 | T4: =SUM(N4:S4) -> 1.91 | U4: 0 | V4: 0 | W4: 0 | X4: 0 | Y4: 0 | Z4: 3.3 | AA4: =SUM(U4:Z4) -> 3.3 | AB4: 0 | AC4: 0 | AD4: 0 | AE4: 0 | AF4: 0 | AG4: 0.66 | AH4: =SUM(AB4:AG4) -> 0.66
A5: 0000000039033 | B5: ㈱米吾(厚生会)006 | C5: 0032 | D5: 飯塚 | F5: =IF($E5="","",IFERROR(INDEX(担当者マスタ!$B$2:$B$101,MATCH($E5,担当者マスタ!$A$2:$A$101,0)),"※マスタ未登録")) | G5: 9.6 | H5: 0 | I5: 0 | J5: 0 | K5: 0 | L5: 0 | M5: =SUM(G5:L5) -> 9.6 | N5: 0.9 | O5: 0 | P5: 0 | Q5: 0 | R5: 0 | S5: 0 | T5: =SUM(N5:S5) -> 0.9 | U5: 0 | V5: 0 | W5: 0 | X5: 0 | Y5: 0 | Z5: 0 | AA5: =SUM(U5:Z5) -> 0 | AB5: 0 | AC5: 0 | AD5: 0 | AE5: 0 | AF5: 0 | AG5: 0 | AH5: =SUM(AB5:AG5) -> 0
A6: 0000000100203 | B6: (有)ﾋﾟｰｹｨｼｰ | C6: 0032 | D6: 飯塚 | F6: =IF($E6="","",IFERROR(INDEX(担当者マスタ!$B$2:$B$101,MATCH($E6,担当者マスタ!$A$2:$A$101,0)),"※マスタ未登録")) | G6: 1371.91 | H6: 1256.094 | I6: 1626.56 | J6: 1406.29 | K6: 576.98 | L6: 1431.969 | M6: =SUM(G6:L6) -> 7669.803 | N6: 421.462 | O6: 442.378 | P6: 566.97 | Q6: 462.864 | R6: 181.711 | S6: 465.614 | T6: =SUM(N6:S6) -> 2540.999 | U6: 1341.002 | V6: 589.964 | W6: 1582.672 | X6: 1421.844 | Y6: 652.276 | Z6: 582.644 | AA6: =SUM(U6:Z6) -> 6170.402 | AB6: 416.824 | AC6: 193.7 | AD6: 492.898 | AE6: 375.356 | AF6: 207.898 | AG6: 193.028 | AH6: =SUM(AB6:AG6) -> 1879.704
A7: 0000000100673 | B7: ㈱味屋ｺｰﾎﾟﾚｰｼｮﾝ | C7: 0032 | D7: 飯塚 | F7: =IF($E7="","",IFERROR(INDEX(担当者マスタ!$B$2:$B$101,MATCH($E7,担当者マスタ!$A$2:$A$101,0)),"※マスタ未登録")) | G7: 0 | H7: 0 | I7: 0 | J7: 0 | K7: 0 | L7: 0 | M7: =SUM(G7:L7) -> 0 | N7: 0 | O7: 0 | P7: 0 | Q7: 0 | R7: 0 | S7: 0 | T7: =SUM(N7:S7) -> 0 | U7: 7.08 | V7: 0 | W7: 0 | X7: 0 | Y7: 0 | Z7: 0 | AA7: =SUM(U7:Z7) -> 7.08 | AB7: 3.312 | AC7: 0 | AD7: 0 | AE7: 0 | AF7: 0 | AG7: 0 | AH7: =SUM(AB7:AG7) -> 3.312
A8: 0000000101063 | B8: 東亜産業(有) | C8: 0032 | D8: 飯塚 | F8: =IF($E8="","",IFERROR(INDEX(担当者マスタ!$B$2:$B$101,MATCH($E8,担当者マスタ!$A$2:$A$101,0)),"※マスタ未登録")) | G8: 0 | H8: 20.7 | I8: 0 | J8: 0 | K8: 0 | L8: 0 | M8: =SUM(G8:L8) -> 20.7 | N8: 0 | O8: 3.75 | P8: 0 | Q8: 0 | R8: 0 | S8: 0 | T8: =SUM(N8:S8) -> 3.75 | U8: 0 | V8: 0 | W8: 0 | X8: 0 | Y8: 0 | Z8: 20.7 | AA8: =SUM(U8:Z8) -> 20.7 | AB8: 0 | AC8: 0 | AD8: 0 | AE8: 0 | AF8: 0 | AG8: 3.75 | AH8: =SUM(AB8:AG8) -> 3.75
A9: 0000000102203 | B9: 岸本和久 | C9: 0032 | D9: 飯塚 | F9: =IF($E9="","",IFERROR(INDEX(担当者マスタ!$B$2:$B$101,MATCH($E9,担当者マスタ!$A$2:$A$101,0)),"※マスタ未登録")) | G9: 0 | H9: 0 | I9: 0 | J9: 0 | K9: 0 | L9: 0 | M9: =SUM(G9:L9) -> 0 | N9: 0 | O9: 0 | P9: 0 | Q9: 0 | R9: 0 | S9: 0 | T9: =SUM(N9:S9) -> 0 | U9: 0 | V9: 40.5 | W9: 0 | X9: 0 | Y9: 0 | Z9: 0 | AA9: =SUM(U9:Z9) -> 40.5 | AB9: 0 | AC9: 12 | AD9: 0 | AE9: 0 | AF9: 0 | AG9: 0 | AH9: =SUM(AB9:AG9) -> 12
A10: 0000000102553 | B10: ﾜｰｸｾﾝﾀｰほほえみ | C10: 0032 | D10: 飯塚 | F10: =IF($E10="","",IFERROR(INDEX(担当者マスタ!$B$2:$B$101,MATCH($E10,担当者マスタ!$A$2:$A$101,0)),"※マスタ未登録")) | G10: 128.58 | H10: 0 | I10: 0 | J10: 0 | K10: 0 | L10: 0 | M10: =SUM(G10:L10) -> 128.58 | N10: 37.28 | O10: 0 | P10: 0 | Q10: 0 | R10: 0 | S10: 0 | T10: =SUM(N10:S10) -> 37.28 | U10: 0 | V10: 0 | W10: 0 | X10: 0 | Y10: 0 | Z10: 0 | AA10: =SUM(U10:Z10) -> 0 | AB10: 0 | AC10: 0 | AD10: 0 | AE10: 0 | AF10: 0 | AG10: 0 | AH10: =SUM(AB10:AG10) -> 0
A11: 0000000103293 | B11: ㈲岡田商店本店(資材) | C11: 0032 | D11: 飯塚 | F11: =IF($E11="","",IFERROR(INDEX(担当者マスタ!$B$2:$B$101,MATCH($E11,担当者マスタ!$A$2:$A$101,0)),"※マスタ未登録")) | G11: 1547.564 | H11: 1406 | I11: 1615.548 | J11: 863.426 | K11: 1042.139 | L11: 1264.186 | M11: =SUM(G11:L11) -> 7738.863 | N11: 623.457 | O11: 527.519 | P11: 603.989 | Q11: 321.099 | R11: 387.532 | S11: 470.47 | T11: =SUM(N11:S11) -> 2934.066 | U11: 1326.714 | V11: 2443.521 | W11: 3792.533 | X11: 1392.358 | Y11: 1962.283 | Z11: 2334.544 | AA11: =SUM(U11:Z11) -> 13251.953 | AB11: 506.714 | AC11: 903.301 | AD11: 1382.363 | AE11: 517.465 | AF11: 731.053 | AG11: 867.793 | AH11: =SUM(AB11:AG11) -> 4908.689
A12: 0000000103383 | B12: ㈲こめや産業本社工場 | C12: 0032 | D12: 飯塚 | F12: =IF($E12="","",IFERROR(INDEX(担当者マスタ!$B$2:$B$101,MATCH($E12,担当者マスタ!$A$2:$A$101,0)),"※マスタ未登録")) | G12: 1191.935 | H12: 1112.696 | I12: 2205.124 | J12: 890.156 | K12: 648.212 | L12: 857.469 | M12: =SUM(G12:L12) -> 6905.592 | N12: 376.384 | O12: 342.913 | P12: 654.786 | Q12: 263.309 | R12: 199.727 | S12: 252.433 | T12: =SUM(N12:S12) -> 2089.552 | U12: 1173.37 | V12: 805.49 | W12: 1487.927 | X12: 626.609 | Y12: 661.329 | Z12: 916.771 | AA12: =SUM(U12:Z12) -> 5671.496 | AB12: 339.855 | AC12: 240.608 | AD12: 471.405 | AE12: 193.717 | AF12: 200.79 | AG12: 266.247 | AH12: =SUM(AB12:AG12) -> 1712.622
A13: 0000000104033 | B13: 九州惣菜㈱ | C13: 0032 | D13: 飯塚 | F13: =IF($E13="","",IFERROR(INDEX(担当者マスタ!$B$2:$B$101,MATCH($E13,担当者マスタ!$A$2:$A$101,0)),"※マスタ未登録")) | G13: 384.783 | H13: 336.247 | I13: 390.402 | J13: 239.207 | K13: 248.551 | L13: 379.936 | M13: =SUM(G13:L13) -> 1979.126 | N13: 102.827 | O13: 84.486 | P13: 98.692 | Q13: 63.066 | R13: 61.868 | S13: 86.348 | T13: =SUM(N13:S13) -> 497.287 | U13: 294.317 | V13: 305.119 | W13: 362.849 | X13: 188.841 | Y13: 176.299 | Z13: 255.538 | AA13: =SUM(U13:Z13) -> 1582.963 | AB13: 68.426 | AC13: 75.103 | AD13: 87.018 | AE13: 39.573 | AF13: 37.862 | AG13: 56.028 | AH13: =SUM(AB13:AG13) -> 364.01
... A46: 0000000111003 | B46: ｲｵﾝﾘﾃｰﾙ㈱松江店 | C46: 0032 | D46: 飯塚 | F46: =IF($E46="","",IFERROR(INDEX(担当者マスタ!$B$2:$B$101,MATCH($E46,担当者マスタ!$A$2:$A$101,0)),"※マスタ未登録")) | G46: 5.15 | H46: 16.58 | I46: 8.24 | J46: 10.3 | K46: 5.15 | L46: 0 | M46: =SUM(G46:L46) -> 45.42 | N46: 1.9 | O46: 6.27 | P46: 3.04 | Q46: 3.8 | R46: 1.9 | S46: 0 | T46: =SUM(N46:S46) -> 16.91 | U46: 2.06 | V46: 12.46 | W46: 4.12 | X46: 10.4 | Y46: 0 | Z46: 2.06 | AA46: =SUM(U46:Z46) -> 31.1 | AB46: 0.76 | AC46: 4.75 | AD46: 1.52 | AE46: 3.99 | AF46: 0 | AG46: 0.76 | AH46: =SUM(AB46:AG46) -> 11.78
C47: 0032 集計 | D47: 飯塚 | G47: =SUBTOTAL(9,G2:G46) -> 12313.277 | H47: =SUBTOTAL(9,H2:H46) -> 10082.311 | I47: =SUBTOTAL(9,I2:I46) -> 15102.043 | J47: =SUBTOTAL(9,J2:J46) -> 7386.229 | K47: =SUBTOTAL(9,K2:K46) -> 7267.935 | L47: =SUBTOTAL(9,L2:L46) -> 11226.433 | M47: =SUBTOTAL(9,M2:M46) -> 63378.228 | N47: =SUBTOTAL(9,N2:N46) -> 3702.724 | ... AH47: =SUBTOTAL(9,AH2:AH46) -> 17703.555
A48: 0000000000113 | B48: JAしまね資材課 | C48: 0033 | D48: 前田 | F48: =IF($E48="","",IFERROR(INDEX(担当者マスタ!$B$2:$B$101,MATCH($E48,担当者マスタ!$A$2:$A$101,0)),"※マスタ未登録")) | G48: 107.9 | H48: 284.92 | I48: 21 | J48: 0 | K48: 0 | L48: 0 | M48: =SUM(G48:L48) -> 413.82 | N48: 26.9 | O48: 63.56 | P48: 4.5 | Q48: 0 | R48: 0 | S48: 0 | T48: =SUM(N48:S48) -> 94.96 | U48: 4.12 | V48: 372.6 | W48: 0 | X48: 0 | Y48: 0 | Z48: 0 | AA48: =SUM(U48:Z48) -> 376.72 | AB48: 0.6 | AC48: 82.8 | AD48: 0 | AE48: 0 | AF48: 0 | AG48: 0 | AH48: =SUM(AB48:AG48) -> 83.4
A49: 0000000000303 | B49: JAしまね出雲地区本部 | C49: 0033 | D49: 前田 | F49: =IF($E49="","",IFERROR(INDEX(担当者マスタ!$B$2:$B$101,MATCH($E49,担当者マスタ!$A$2:$A$101,0)),"※マスタ未登録")) | G49: 5891.895 | H49: 3313.479 | I49: 1635.806 | J49: 458.65 | K49: 577.895 | L49: 1235.012 | M49: =SUM(G49:L49) -> 13112.737 | N49: 1233.4245 | O49: 1128.282 | P49: 516.536 | Q49: 75.1 | R49: 137.292 | S49: 187.208 | T49: =SUM(N49:S49) -> 3277.8425 | U49: 3591.125 | V49: 1612.054 | W49: 1573.635 | X49: 436.426 | Y49: 1807.737 | Z49: 18723.57 | AA49: =SUM(U49:Z49) -> 27744.547 | AB49: 920.9965 | AC49: 489.575 | AD49: 500.915 | AE49: 79.674 | AF49: 347.44 | AG49: 5663.174 | AH49: =SUM(AB49:AG49) -> 8001.7745
A50: 0000000000603 | B50: JA全農農機ｻﾎﾟｰﾄ本店 | C50: 0033 | D50: 前田 | F50: =IF($E50="","",IFERROR(INDEX(担当者マスタ!$B$2:$B$101,MATCH($E50,担当者マスタ!$A$2:$A$101,0)),"※マスタ未登録")) | G50: 230.6 | H50: 0 | I50: 0 | J50: 0 | K50: 0 | L50: 0 | M50: =SUM(G50:L50) -> 230.6 | N50: 38.346 | O50: 0 | P50: 0 | Q50: 0 | R50: 0 | S50: 0 | T50: =SUM(N50:S50) -> 38.346 | U50: 77.98 | V50: 46.025 | W50: 12 | X50: 0 | Y50: 0 | Z50: 0 | AA50: =SUM(U50:Z50) -> 136.005 | AB50: 6.903 | AC50: 4.065 | AD50: 1.38 | AE50: 0 | AF50: 0 | AG50: 0 | AH50: =SUM(AB50:AG50) -> 12.348
A51: 0000000004013 | B51: ｴﾑｹｲ開発㈱湯梨浜青果 | C51: 0033 | D51: 前田 | F51: =IF($E51="","",IFERROR(INDEX(担当者マスタ!$B$2:$B$101,MATCH($E51,担当者マスタ!$A$2:$A$101,0)),"※マスタ未登録")) | G51: 0 | H51: 0 | I51: 0 | J51: 0 | K51: 0 | L51: 0 | M51: =SUM(G51:L51) -> 0 | N51: 0 | O51: 0 | P51: 0 | Q51: 0 | R51: 0 | S51: 0 | T51: =SUM(N51:S51) -> 0 | U51: 81.267 | V51: 83.52 | W51: 63.214 | X51: 22.32 | Y51: 61.775 | Z51: 58.629 | AA51: =SUM(U51:Z51) -> 370.725 | AB51: 19.351 | AC51: 19.861 | AD51: 15.962 | AE51: 4.57 | AF51: 14.459 | AG51: 13.705 | AH51: =SUM(AB51:AG51) -> 87.908
A52: 0000000004023 | B52: ｴﾑｹｲ開発㈱西倉吉青果 | C52: 0033 | D52: 前田 | F52: =IF($E52="","",IFERROR(INDEX(担当者マスタ!$B$2:$B$101,MATCH($E52,担当者マスタ!$A$2:$A$101,0)),"※マスタ未登録")) | G52: 0 | H52: 0 | I52: 0 | J52: 0 | K52: 0 | L52: 0 | M52: =SUM(G52:L52) -> 0 | N52: 0 | O52: 0 | P52: 0 | Q52: 0 | R52: 0 | S52: 0 | T52: =SUM(N52:S52) -> 0 | U52: 66.537 | V52: 76.508 | W52: 82.816 | X52: 63.971 | Y52: 72.32 | Z52: 93.672 | AA52: =SUM(U52:Z52) -> 455.824 | AB52: 18.253 | AC52: 19.107 | AD52: 21.9 | AE52: 16.936 | AF52: 17.854 | AG52: 24.589 | AH52: =SUM(AB52:AG52) -> 118.639
A53: 0000000033013 | B53: 業務ｽｰﾊﾟｰよどえ精肉 | C53: 0033 | D53: 前田 | F53: =IF($E53="","",IFERROR(INDEX(担当者マスタ!$B$2:$B$101,MATCH($E53,担当者マスタ!$A$2:$A$101,0)),"※マスタ未登録")) | G53: 0 | H53: 0 | I53: 0 | J53: 168.686 | K53: 48.736 | L53: 125.575 | M53: =SUM(G53:L53) -> 342.997 | N53: 0 | O53: 0 | P53: 0 | Q53: 42.266 | R53: 10.815 | S53: 33.505 | T53: =SUM(N53:S53) -> 86.586 | U53: 158.137 | V53: 146.798 | W53: 143.236 | X53: 121.472 | Y53: 163.74 | Z53: 208.391 | AA53: =SUM(U53:Z53) -> 941.774 | AB53: 45.215 | AC53: 50.443 | AD53: 46.015 | AE53: 40.881 | AF53: 58.584 | AG53: 72.082 | AH53: =SUM(AB53:AG53) -> 313.22
A54: 0000000079909 | B54: 出雲国大社食品 | C54: 0033 | D54: 前田 | F54: =IF($E54="","",IFERROR(INDEX(担当者マスタ!$B$2:$B$101,MATCH($E54,担当者マスタ!$A$2:$A$101,0)),"※マスタ未登録")) | G54: 1310.6 | H54: 0 | I54: 45.6 | J54: 50.4 | K54: 50.4 | L54: 0 | M54: =SUM(G54:L54) -> 1457 | N54: 86.432 | O54: 0 | P54: 8.232 | Q54: 9.288 | R54: 9.288 | S54: 0 | T54: =SUM(N54:S54) -> 113.24 | U54: 0 | V54: 0 | W54: 0 | X54: 0 | Y54: 0 | Z54: 0 | AA54: =SUM(U54:Z54) -> 0 | AB54: 0 | AC54: 0 | AD54: 0 | AE54: 0 | AF54: 0 | AG54: 0 | AH54: =SUM(AB54:AG54) -> 0
A55: 0000000100273 | B55: 別石地区ｲﾁｺﾞ生産組合 | C55: 0033 | D55: 前田 | F55: =IF($E55="","",IFERROR(INDEX(担当者マスタ!$B$2:$B$101,MATCH($E55,担当者マスタ!$A$2:$A$101,0)),"※マスタ未登録")) | G55: 0 | H55: 0 | I55: 0 | J55: 0 | K55: 0 | L55: 0 | M55: =SUM(G55:L55) -> 0 | N55: 0 | O55: 0 | P55: 0 | Q55: 0 | R55: 0 | S55: 0 | T55: =SUM(N55:S55) -> 0 | U55: 0 | V55: 0 | W55: 33 | X55: 0 | Y55: 0 | Z55: 0 | AA55: =SUM(U55:Z55) -> 33 | AB55: 0 | AC55: 0 | AD55: 9.6 | AE55: 0 | AF55: 0 | AG55: 0 | AH55: =SUM(AB55:AG55) -> 9.6
A56: 0000000100433 | B56: (有)渡邊水産 | C56: 0033 | D56: 前田 | F56: =IF($E56="","",IFERROR(INDEX(担当者マスタ!$B$2:$B$101,MATCH($E56,担当者マスタ!$A$2:$A$101,0)),"※マスタ未登録")) | G56: 1659.323 | H56: 2039.21 | I56: 1697.39 | J56: 2170.313 | K56: 1388.229 | L56: 1797.535 | M56: =SUM(G56:L56) -> 10752 | N56: 676.5908 | O56: 810.53 | P56: 618.023 | Q56: 815.3998 | R56: 604.545 | S56: 726.255 | T56: =SUM(N56:S56) -> 4251.3436 | U56: 1769.574 | V56: 1694.5 | W56: 1543.81 | X56: 2892.62 | Y56: 914.739 | Z56: 3710.655 | AA56: =SUM(U56:Z56) -> 12525.898 | AB56: 695.263 | AC56: 619.3858 | AD56: 592.048 | AE56: 1054.2318 | AF56: 339.979 | AG56: 1220.623 | AH56: =SUM(AB56:AG56) -> 4521.5306
A57: 0000000101203 | B57: やすぎ営農部資材課 | C57: 0033 | D57: 前田 | F57: =IF($E57="","",IFERROR(INDEX(担当者マスタ!$B$2:$B$101,MATCH($E57,担当者マスタ!$A$2:$A$101,0)),"※マスタ未登録")) | G57: 334 | H57: 842.903 | I57: 129.133 | J57: 95.13 | K57: 9.3 | L57: 308.094 | M57: =SUM(G57:L57) -> 1718.56 | N57: 79.2 | O57: 198.775 | P57: 28.316 | Q57: 21.48 | R57: 1.296 | S57: 69.38 | T57: =SUM(N57:S57) -> 398.447 | U57: 41.575 | V57: 692.8 | W57: 191.74 | X57: 56.39 | Y57: 3.81 | Z57: 418.905 | AA57: =SUM(U57:Z57) -> 1405.22 | AB57: 11.856 | AC57: 144.35 | AD57: 44.856 | AE57: 16.196 | AF57: 0.542 | AG57: 104.973 | AH57: =SUM(AB57:AG57) -> 322.773
A58: 0000000101733 | B58: ㈱ｴﾎﾟﾗ(旧ｸﾛﾚﾗ) | C58: 0033 | D58: 前田 | F58: =IF($E58="","",IFERROR(INDEX(担当者マスタ!$B$2:$B$101,MATCH($E58,担当者マスタ!$A$2:$A$101,0)),"※マスタ未登録")) | G58: 0 | H58: 0 | I58: 0 | J58: 14.85 | K58: 0 | L58: 0 | M58: =SUM(G58:L58) -> 14.85 | N58: 0 | O58: 0 | P58: 0 | Q58: 4.65 | R58: 0 | S58: 0 | T58: =SUM(N58:S58) -> 4.65 | U58: 0 | V58: 13.2 | W58: 0 | X58: 13.2 | Y58: 0 | Z58: 0 | AA58: =SUM(U58:Z58) -> 26.4 | AB58: 0 | AC58: 1.936 | AD58: 0 | AE58: 1.936 | AF58: 0 | AG58: 0 | AH58: =SUM(AB58:AG58) -> 3.872
A59: 0000000102343 | B59: 日御碕ﾄﾞﾗｲﾌﾞｲﾝ | C59: 0033 | D59: 前田 | F59: =IF($E59="","",IFERROR(INDEX(担当者マスタ!$B$2:$B$101,MATCH($E59,担当者マスタ!$A$2:$A$101,0)),"※マスタ未登録")) | G59: 0 | H59: 0 | I59: 11 | J59: 0 | K59: 0 | L59: 0 | M59: =SUM(G59:L59) -> 11 | N59: 0 | O59: 0 | P59: 6.45 | Q59: 0 | R59: 0 | S59: 0 | T59: =SUM(N59:S59) -> 6.45 | U59: 0 | V59: 0 | W59: 0 | X59: 0 | Y59: 0 | Z59: 0 | AA59: =SUM(U59:Z59) -> 0 | AB59: 0 | AC59: 0 | AD59: 0 | AE59: 0 | AF59: 0 | AG59: 0 | AH59: =SUM(AB59:AG59) -> 0
... A90: 0000000109983 | B90: MARVELOUS㈱ﾏｰﾍﾞﾗｽ | C90: 0033 | D90: 前田 | F90: =IF($E90="","",IFERROR(INDEX(担当者マスタ!$B$2:$B$101,MATCH($E90,担当者マスタ!$A$2:$A$101,0)),"※マスタ未登録")) | G90: 0 | H90: 0 | I90: 0 | J90: 0 | K90: 0 | L90: 0 | M90: =SUM(G90:L90) -> 0 | N90: 0 | O90: 0 | P90: 0 | Q90: 0 | R90: 0 | S90: 0 | T90: =SUM(N90:S90) -> 0 | U90: 0 | V90: 0 | W90: 0 | X90: 0 | Y90: 0 | Z90: 40.31 | AA90: =SUM(U90:Z90) -> 40.31 | AB90: 0 | AC90: 0 | AD90: 0 | AE90: 0 | AF90: 0 | AG90: 9.6 | AH90: =SUM(AB90:AG90) -> 9.6
C91: 0033 集計 | D91: 前田 | G91: =SUBTOTAL(9,G48:G90) -> 16686.153 | H91: =SUBTOTAL(9,H48:H90) -> 14070.31 | I91: =SUBTOTAL(9,I48:I90) -> 9742.13 | J91: =SUBTOTAL(9,J48:J90) -> 6255.551 | K91: =SUBTOTAL(9,K48:K90) -> 6012.508 | L91: =SUBTOTAL(9,L48:L90) -> 8167.325 | M91: =SUBTOTAL(9,M48:M90) -> 60933.977 | N91: =SUBTOTAL(9,N48:N90) -> 3741.4363 | ... AH91: =SUBTOTAL(9,AH48:AH90) -> 20564.109
A92: 0000000001003 | B92: ㈱ﾔﾏﾀﾞﾔ | C92: 0034 | D92: 原田 | F92: =IF($E92="","",IFERROR(INDEX(担当者マスタ!$B$2:$B$101,MATCH($E92,担当者マスタ!$A$2:$A$101,0)),"※マスタ未登録")) | G92: 3124.129 | H92: 3606.358 | I92: 5825.969 | J92: 1823.068 | K92: 2436.318 | L92: 3350.792 | M92: =SUM(G92:L92) -> 20166.634 | N92: 947.565 | O92: 1001.352 | P92: 1638.88 | Q92: 497.355 | R92: 660.783 | S92: 913.678 | T92: =SUM(N92:S92) -> 5659.613 | U92: 5677.932 | V92: 4759.609 | W92: 6019.039 | X92: 2402.929 | Y92: 2878.958 | Z92: 4556.155 | AA92: =SUM(U92:Z92) -> 26294.622 | AB92: 1436.882 | AC92: 1208.327 | AD92: 1744.081 | AE92: 701.612 | AF92: 802.988 | AG92: 1384.264 | AH92: =SUM(AB92:AG92) -> 7278.154
A93: 0000000101013 | B93: (有)松崎製菓 | C93: 0034 | D93: 原田 | F93: =IF($E93="","",IFERROR(INDEX(担当者マスタ!$B$2:$B$101,MATCH($E93,担当者マスタ!$A$2:$A$101,0)),"※マスタ未登録")) | G93: 89.64 | H93: 0 | I93: 0 | J93: 89.64 | K93: 0 | L93: 89.64 | M93: =SUM(G93:L93) -> 268.92 | N93: 25.68 | O93: 0 | P93: 0 | Q93: 25.68 | R93: 0 | S93: 25.68 | T93: =SUM(N93:S93) -> 77.04 | U93: 89.64 | V93: 0 | W93: 89.64 | X93: 0 | Y93: 0 | Z93: 89.64 | AA93: =SUM(U93:Z93) -> 268.92 | AB93: 25.68 | AC93: 0 | AD93: 25.68 | AE93: 0 | AF93: 0 | AG93: 25.68 | AH93: =SUM(AB93:AG93) -> 77.04
A94: 0000000101613 | B94: ㈱門脇正司商店 | C94: 0034 | D94: 原田 | F94: =IF($E94="","",IFERROR(INDEX(担当者マスタ!$B$2:$B$101,MATCH($E94,担当者マスタ!$A$2:$A$101,0)),"※マスタ未登録")) | G94: 0 | H94: 75.912 | I94: 0 | J94: 0 | K94: 0 | L94: 0 | M94: =SUM(G94:L94) -> 75.912 | N94: 0 | O94: 38.556 | P94: 0 | Q94: 0 | R94: 0 | S94: 0 | T94: =SUM(N94:S94) -> 38.556 | U94: 0 | V94: 55.324 | W94: 25.608 | X94: 0 | Y94: 0 | Z94: 25.2 | AA94: =SUM(U94:Z94) -> 106.132 | AB94: 0 | AC94: 28.364 | AD94: 10.428 | AE94: 0 | AF94: 0 | AG94: 3.048 | AH94: =SUM(AB94:AG94) -> 41.84
A95: 0000000101693 | B95: ㈱ｻﾝｱｲ安来店 | C95: 0034 | D95: 原田 | F95: =IF($E95="","",IFERROR(INDEX(担当者マスタ!$B$2:$B$101,MATCH($E95,担当者マスタ!$A$2:$A$101,0)),"※マスタ未登録")) | G95: 1093.133 | H95: 1172.899 | I95: 1670.547 | J95: 428.508 | K95: 761.312 | L95: 1112.727 | M95: =SUM(G95:L95) -> 6239.126 | N95: 440.329 | O95: 464.547 | P95: 621.088 | Q95: 167.579 | R95: 285.888 | S95: 421.962 | T95: =SUM(N95:S95) -> 2401.393 | U95: 1223.682 | V95: 1078.767 | W95: 1660.631 | X95: 631.196 | Y95: 915.027 | Z95: 1129.685 | AA95: =SUM(U95:Z95) -> 6638.988 | AB95: 487.443 | AC95: 427.401 | AD95: 673.501 | AE95: 252.432 | AF95: 363.247 | AG95: 459.921 | AH95: =SUM(AB95:AG95) -> 2663.945
A96: 0000000102543 | B96: ㈱華商会HanaBakery | C96: 0034 | D96: 原田 | F96: =IF($E96="","",IFERROR(INDEX(担当者マスタ!$B$2:$B$101,MATCH($E96,担当者マスタ!$A$2:$A$101,0)),"※マスタ未登録")) | G96: 8 | H96: 0 | I96: 0 | J96: 0 | K96: 0 | L96: 0 | M96: =SUM(G96:L96) -> 8 | N96: 2.7 | O96: 0 | P96: 0 | Q96: 0 | R96: 0 | S96: 0 | T96: =SUM(N96:S96) -> 2.7 | U96: 0 | V96: 0 | W96: 0 | X96: 0 | Y96: 0 | Z96: 4.8 | AA96: =SUM(U96:Z96) -> 4.8 | AB96: 0 | AC96: 0 | AD96: 0 | AE96: 0 | AF96: 0 | AG96: 1.284 | AH96: =SUM(AB96:AG96) -> 1.284
A97: 0000000104733 | B97: (有)本田商店神原工場 | C97: 0034 | D97: 原田 | F97: =IF($E97="","",IFERROR(INDEX(担当者マスタ!$B$2:$B$101,MATCH($E97,担当者マスタ!$A$2:$A$101,0)),"※マスタ未登録")) | G97: 965.939 | H97: 1319.638 | I97: 1506.23 | J97: 0 | K97: 12.6 | L97: 693.42 | M97: =SUM(G97:L97) -> 4497.827 | N97: 161.176 | O97: 191.838 | P97: 209.021 | Q97: 0 | R97: 3.4 | S97: 45.117 | T97: =SUM(N97:S97) -> 610.552 | U97: 459.72 | V97: 1130.4 | W97: 1090.204 | X97: 342.639 | Y97: 448.642 | Z97: 173.016 | AA97: =SUM(U97:Z97) -> 3644.621 | AB97: 80.296 | AC97: 195.64 | AD97: 178.164 | AE97: 39.679 | AF97: 37.482 | AG97: 36.788 | AH97: =SUM(AB97:AG97) -> 568.049
A98: 0000000104763 | B98: ㈱小林栄太郎商店 | C98: 0034 | D98: 原田 | F98: =IF($E98="","",IFERROR(INDEX(担当者マスタ!$B$2:$B$101,MATCH($E98,担当者マスタ!$A$2:$A$101,0)),"※マスタ未登録")) | G98: 36.411 | H98: 32.474 | I98: 37.562 | J98: 7.103 | K98: 32.364 | L98: 12.273 | M98: =SUM(G98:L98) -> 158.187 | N98: 11.109 | O98: 9.366 | P98: 9.844 | Q98: 2.193 | R98: 8.698 | S98: 3.293 | T98: =SUM(N98:S98) -> 44.503 | U98: 57.852 | V98: 13.077 | W98: 16.158 | X98: 26.064 | Y98: 4.9 | Z98: 38.739 | AA98: =SUM(U98:Z98) -> 156.79 | AB98: 15.328 | AC98: 3.688 | AD98: 4.91 | AE98: 6.702 | AF98: 1.8 | AG98: 10.699 | AH98: =SUM(AB98:AG98) -> 43.127
A99: 0000000106103 | B99: ㈱ｲｰﾃｨｰｽﾞ伯耆店 | C99: 0034 | D99: 原田 | F99: =IF($E99="","",IFERROR(INDEX(担当者マスタ!$B$2:$B$101,MATCH($E99,担当者マスタ!$A$2:$A$101,0)),"※マスタ未登録")) | G99: 2440.765 | H99: 3038.557 | I99: 4240.751 | J99: 2203.213 | K99: 2216.873 | L99: 2623.192 | M99: =SUM(G99:L99) -> 16763.351 | N99: 309.262 | O99: 390.742 | P99: 612.166 | Q99: 329.115 | R99: 332.769 | S99: 366.845 | T99: =SUM(N99:S99) -> 2340.899 | U99: 2716.464 | V99: 2207.712 | W99: 3680.012 | X99: 1784.758 | Y99: 2058.612 | Z99: 2452.381 | AA99: =SUM(U99:Z99) -> 14899.939 | AB99: 359.979 | AC99: 295.845 | AD99: 509.358 | AE99: 250.092 | AF99: 289.848 | AG99: 342.296 | AH99: =SUM(AB99:AG99) -> 2047.418
A100: 0000000106153 | B100: ㈱ｲｰﾃｨｰｽﾞ境港店 | C100: 0034 | D100: 原田 | F100: =IF($E100="","",IFERROR(INDEX(担当者マスタ!$B$2:$B$101,MATCH($E100,担当者マスタ!$A$2:$A$101,0)),"※マスタ未登録")) | G100: 359.914 | H100: 393.051 | I100: 576.475 | J100: 223.326 | K100: 285.465 | L100: 353.479 | M100: =SUM(G100:L100) -> 2191.71 | N100: 45.513 | O100: 51.197 | P100: 82.609 | Q100: 35.121 | R100: 43.095 | S100: 49.098 | T100: =SUM(N100:S100) -> 306.633 | U100: 431.471 | V100: 260.567 | W100: 456.866 | X100: 224.404 | Y100: 279.13 | Z100: 339.281 | AA100: =SUM(U100:Z100) -> 1991.719 | AB100: 56.782 | AC100: 35.573 | AD100: 62.54 | AE100: 30.551 | AF100: 37.636 | AG100: 46.052 | AH100: =SUM(AB100:AG100) -> 269.134
A101: 0000000106203 | B101: ㈱ｺﾊﾟｯｸｽ | C101: 0034 | D101: 原田 | F101: =IF($E101="","",IFERROR(INDEX(担当者マスタ!$B$2:$B$101,MATCH($E101,担当者マスタ!$A$2:$A$101,0)),"※マスタ未登録")) | G101: 93.395 | H101: 0 | I101: 9.906 | J101: 0 | K101: 0 | L101: 0 | M101: =SUM(G101:L101) -> 103.301 | N101: 23.052 | O101: 0 | P101: 7.806 | Q101: 0 | R101: 0 | S101: 0 | T101: =SUM(N101:S101) -> 30.858 | U101: 0 | V101: 0 | W101: 0 | X101: 0 | Y101: 0 | Z101: 0 | AA101: =SUM(U101:Z101) -> 0 | AB101: 0 | AC101: 0 | AD101: 0 | AE101: 0 | AF101: 0 | AG101: 0 | AH101: =SUM(AB101:AG101) -> 0
A102: 0000000108393 | B102: ｸﾆﾋﾛ㈱(源内亭) | C102: 0034 | D102: 原田 | F102: =IF($E102="","",IFERROR(INDEX(担当者マスタ!$B$2:$B$101,MATCH($E102,担当者マスタ!$A$2:$A$101,0)),"※マスタ未登録")) | G102: 162.363 | H102: 319.486 | I102: 210.21 | J102: 139.029 | K102: 138.315 | L102: 135.443 | M102: =SUM(G102:L102) -> 1104.846 | N102: 66.919 | O102: 124.986 | P102: 87.615 | Q102: 55.432 | R102: 57.121 | S102: 52.411 | T102: =SUM(N102:S102) -> 444.484 | U102: 164.169 | V102: 137.269 | W102: 381.713 | X102: 108.881 | Y102: 86.845 | Z102: 103.149 | AA102: =SUM(U102:Z102) -> 982.026 | AB102: 66.48 | AC102: 56.438 | AD102: 156.815 | AE102: 42.982 | AF102: 35.415 | AG102: 43.273 | AH102: =SUM(AB102:AG102) -> 401.403
A103: 0000000109143 | B103: 城東化成㈱ | C103: 0034 | D103: 原田 | F103: =IF($E103="","",IFERROR(INDEX(担当者マスタ!$B$2:$B$101,MATCH($E103,担当者マスタ!$A$2:$A$101,0)),"※マスタ未登録")) | G103: 275.628 | H103: 215.236 | I103: 281.266 | J103: 221.828 | K103: 174.68 | L103: 277.86 | M103: =SUM(G103:L103) -> 1446.498 | N103: 47.586 | O103: 32.488 | P103: 41.884 | Q103: 32.8 | R103: 25.778 | S103: 41.768 | T103: =SUM(N103:S103) -> 222.304 | U103: 318.98 | V103: 177.74 | W103: 327.408 | X103: 136.52 | Y103: 256.56 | Z103: 281.088 | AA103: =SUM(U103:Z103) -> 1498.296 | AB103: 44.76 | AC103: 26.962 | AD103: 48.126 | AE103: 19.582 | AF103: 34.714 | AG103: 40.956 | AH103: =SUM(AB103:AG103) -> 215.1
... A108: 0000000118463 | B108: ㈱山光食品 | C108: 0034 | D108: 原田 | F108: =IF($E108="","",IFERROR(INDEX(担当者マスタ!$B$2:$B$101,MATCH($E108,担当者マスタ!$A$2:$A$101,0)),"※マスタ未登録")) | G108: 24.9 | H108: 65.89 | I108: 76.2 | J108: 22.7 | K108: 0 | L108: 76.1 | M108: =SUM(G108:L108) -> 265.79 | N108: 4.6 | O108: 12.45 | P108: 10.8 | Q108: 6.59 | R108: 0 | S108: 10.577 | T108: =SUM(N108:S108) -> 45.017 | U108: 0 | V108: 20.175 | W108: 17.075 | X108: 69 | Y108: 51.545 | Z108: 69 | AA108: =SUM(U108:Z108) -> 226.795 | AB108: 0 | AC108: 5.647 | AD108: 4.989 | AE108: 9 | AF108: 9.659 | AG108: 9 | AH108: =SUM(AB108:AG108) -> 38.295
C109: 0034 集計 | D109: 原田 | G109: =SUBTOTAL(9,G92:G108) -> 8717.791 | H109: =SUBTOTAL(9,H92:H108) -> 10259.445 | I109: =SUBTOTAL(9,I92:I108) -> 14531.836 | J109: =SUBTOTAL(9,J92:J108) -> 5165.529 | K109: =SUBTOTAL(9,K92:K108) -> 6067.701 | L109: =SUBTOTAL(9,L92:L108) -> 8724.926 | M109: =SUBTOTAL(9,M92:M108) -> 53467.228 | N109: =SUBTOTAL(9,N92:N108) -> 2097.771 | ... AH109: =SUBTOTAL(9,AH92:AH108) -> 13658.296
A110: 0000000109693 | B110: 境港魚凾㈱ | C110: 0035 | D110: 自治体 | F110: =IF($E110="","",IFERROR(INDEX(担当者マスタ!$B$2:$B$101,MATCH($E110,担当者マスタ!$A$2:$A$101,0)),"※マスタ未登録")) | G110: 0 | H110: 0 | I110: 0 | J110: 0 | K110: 0 | L110: 0 | M110: =SUM(G110:L110) -> 0 | N110: 0 | O110: 0 | P110: 0 | Q110: 0 | R110: 0 | S110: 0 | T110: =SUM(N110:S110) -> 0 | U110: 8085.32 | V110: 0 | W110: 0 | X110: 0 | Y110: 0 | Z110: 0 | AA110: =SUM(U110:Z110) -> 8085.32 | AB110: 299.72 | AC110: 0 | AD110: 0 | AE110: 0 | AF110: 0 | AG110: 0 | AH110: =SUM(AB110:AG110) -> 299.72
A111: 0000000800003 | B111: 松江市長 | C111: 0035 | D111: 自治体 | F111: =IF($E111="","",IFERROR(INDEX(担当者マスタ!$B$2:$B$101,MATCH($E111,担当者マスタ!$A$2:$A$101,0)),"※マスタ未登録")) | G111: 5928.28 | H111: 6152.72 | I111: 7138.22 | J111: 5920.77 | K111: 0 | L111: 509.5 | M111: =SUM(G111:L111) -> 25649.49 | N111: 113.36 | O111: 101.72 | P111: 112.52 | Q111: 104.42 | R111: 0 | S111: 25.5 | T111: =SUM(N111:S111) -> 457.52 | U111: 5676.032 | V111: 6905.36 | W111: 9060.364 | X111: 5021.712 | Y111: 3741.12 | Z111: 0 | AA111: =SUM(U111:Z111) -> 30404.588 | AB111: 104.512 | AC111: 118.9 | AD111: 156.524 | AE111: 78.912 | AF111: 55.08 | AG111: 0 | AH111: =SUM(AB111:AG111) -> 513.928
A112: 0000000810013 | B112: 境港市福祉保健部 | C112: 0035 | D112: 自治体 | F112: =IF($E112="","",IFERROR(INDEX(担当者マスタ!$B$2:$B$101,MATCH($E112,担当者マスタ!$A$2:$A$101,0)),"※マスタ未登録")) | G112: 9.4 | H112: 0 | I112: 0 | J112: 0 | K112: 0 | L112: 0 | M112: =SUM(G112:L112) -> 9.4 | N112: 2.5 | O112: 0 | P112: 0 | Q112: 0 | R112: 0 | S112: 0 | T112: =SUM(N112:S112) -> 2.5 | U112: 0 | V112: 0 | W112: 0 | X112: 0 | Y112: 0 | Z112: 0 | AA112: =SUM(U112:Z112) -> 0 | AB112: 0 | AC112: 0 | AD112: 0 | AE112: 0 | AF112: 0 | AG112: 0 | AH112: =SUM(AB112:AG112) -> 0
C113: 0035 集計 | D113: 自治体 | G113: =SUBTOTAL(9,G110:G112) -> 5937.68 | H113: =SUBTOTAL(9,H110:H112) -> 6152.72 | I113: =SUBTOTAL(9,I110:I112) -> 7138.22 | J113: =SUBTOTAL(9,J110:J112) -> 5920.77 | K113: =SUBTOTAL(9,K110:K112) -> 0 | L113: =SUBTOTAL(9,L110:L112) -> 509.5 | M113: =SUBTOTAL(9,M110:M112) -> 25658.89 | N113: =SUBTOTAL(9,N110:N112) -> 115.86 | ... AH113: =SUBTOTAL(9,AH110:AH112) -> 813.648
A114: 0000000004003 | B114: ㈱ﾏﾙｹﾝ商店 | C114: 0038 | D114: 境その他 | F114: =IF($E114="","",IFERROR(INDEX(担当者マスタ!$B$2:$B$101,MATCH($E114,担当者マスタ!$A$2:$A$101,0)),"※マスタ未登録")) | G114: 0 | H114: 0 | I114: 26.72 | J114: 0 | K114: 4.79 | L114: 2.95 | M114: =SUM(G114:L114) -> 34.46 | N114: 0 | O114: 0 | P114: 4.135 | Q114: 0 | R114: 1.296 | S114: 0.909 | T114: =SUM(N114:S114) -> 6.34 | U114: 12.115 | V114: 3.8 | W114: 16.821 | X114: 12.96 | Y114: 27.92 | Z114: 4.2 | AA114: =SUM(U114:Z114) -> 77.816 | AB114: 1.801 | AC114: 1.5 | AD114: 3.403 | AE114: 2.064 | AF114: 3.303 | AG114: 0.432 | AH114: =SUM(AB114:AG114) -> 12.503
C115: 0038 集計 | D115: 境その他 | G115: =SUBTOTAL(9,G114:G114) -> 0 | H115: =SUBTOTAL(9,H114:H114) -> 0 | I115: =SUBTOTAL(9,I114:I114) -> 26.72 | J115: =SUBTOTAL(9,J114:J114) -> 0 | K115: =SUBTOTAL(9,K114:K114) -> 4.79 | L115: =SUBTOTAL(9,L114:L114) -> 2.95 | M115: =SUBTOTAL(9,M114:M114) -> 34.46 | N115: =SUBTOTAL(9,N114:N114) -> 0 | ... AH115: =SUBTOTAL(9,AH114:AH114) -> 12.503
A116: 0000000000013 | B116: 現金売上 | C116: 0039 | D116: その他 | F116: =IF($E116="","",IFERROR(INDEX(担当者マスタ!$B$2:$B$101,MATCH($E116,担当者マスタ!$A$2:$A$101,0)),"※マスタ未登録")) | G116: 1.1 | H116: 7.194 | I116: 7.6 | J116: 7.001 | K116: 10.144 | L116: 1.9 | M116: =SUM(G116:L116) -> 34.939 | N116: 0.325 | O116: 2.647 | P116: 2.115 | Q116: 1.454 | R116: 2.19 | S116: 0.45 | T116: =SUM(N116:S116) -> 9.181 | U116: 0 | V116: 0 | W116: 1.1 | X116: 0 | Y116: 7.26 | Z116: 1.1 | AA116: =SUM(U116:Z116) -> 9.46 | AB116: 0 | AC116: 0 | AD116: 0.375 | AE116: 0 | AF116: 2.44 | AG116: 0.375 | AH116: =SUM(AB116:AG116) -> 3.19
A117: 0000000000503 | B117: 現金売上 | C117: 0039 | D117: その他 | F117: =IF($E117="","",IFERROR(INDEX(担当者マスタ!$B$2:$B$101,MATCH($E117,担当者マスタ!$A$2:$A$101,0)),"※マスタ未登録")) | G117: 0 | H117: 0 | I117: 0 | J117: 0 | K117: 0 | L117: 0 | M117: =SUM(G117:L117) -> 0 | N117: 0 | O117: 0 | P117: 0 | Q117: 0 | R117: 0 | S117: 0 | T117: =SUM(N117:S117) -> 0 | U117: 0 | V117: 0 | W117: 0 | X117: 0 | Y117: 30 | Z117: 0 | AA117: =SUM(U117:Z117) -> 30 | AB117: 0 | AC117: 0 | AD117: 0 | AE117: 0 | AF117: 0 | AG117: 0 | AH117: =SUM(AB117:AG117) -> 0
A118: 0000000009003 | B118: ㈱ｴﾌﾋﾟｺ ﾍﾟｯﾄﾎﾞﾄﾙ回収 | C118: 0039 | D118: その他 | F118: =IF($E118="","",IFERROR(INDEX(担当者マスタ!$B$2:$B$101,MATCH($E118,担当者マスタ!$A$2:$A$101,0)),"※マスタ未登録")) | G118: 2.4 | H118: 0 | I118: 0 | J118: 1.5 | K118: 0 | L118: 0 | M118: =SUM(G118:L118) -> 3.9 | N118: 0.288 | O118: 0 | P118: 0 | Q118: 0.18 | R118: 0 | S118: 0 | T118: =SUM(N118:S118) -> 0.468 | U118: 1.35 | V118: 0 | W118: 0 | X118: 0.15 | Y118: 0 | Z118: 0 | AA118: =SUM(U118:Z118) -> 1.5 | AB118: 0.162 | AC118: 0 | AD118: 0 | AE118: 0.018 | AF118: 0 | AG118: 0 | AH118: =SUM(AB118:AG118) -> 0.18
A119: 0000000100853 | B119: 常松修 | C119: 0039 | D119: その他 | F119: =IF($E119="","",IFERROR(INDEX(担当者マスタ!$B$2:$B$101,MATCH($E119,担当者マスタ!$A$2:$A$101,0)),"※マスタ未登録")) | G119: 10.9 | H119: 3.9 | I119: 0 | J119: 0 | K119: 0 | L119: 0 | M119: =SUM(G119:L119) -> 14.8 | N119: 3.36 | O119: 0.96 | P119: 0 | Q119: 0 | R119: 0 | S119: 0 | T119: =SUM(N119:S119) -> 4.32 | U119: 0 | V119: 4.55 | W119: 0 | X119: 0 | Y119: 0 | Z119: 0 | AA119: =SUM(U119:Z119) -> 4.55 | AB119: 0 | AC119: 1.12 | AD119: 0 | AE119: 0 | AF119: 0 | AG119: 0 | AH119: =SUM(AB119:AG119) -> 1.12
A120: 0000000101283 | B120: 松江東宝5 | C120: 0039 | D120: その他 | F120: =IF($E120="","",IFERROR(INDEX(担当者マスタ!$B$2:$B$101,MATCH($E120,担当者マスタ!$A$2:$A$101,0)),"※マスタ未登録")) | G120: 0 | H120: 25.64 | I120: 22.34 | J120: 0 | K120: 0 | L120: 0 | M120: =SUM(G120:L120) -> 47.98 | N120: 0 | O120: 9.567 | P120: 7.677 | Q120: 0 | R120: 0 | S120: 0 | T120: =SUM(N120:S120) -> 17.244 | U120: 0 | V120: 0 | W120: 0 | X120: 0 | Y120: 0 | Z120: 0 | AA120: =SUM(U120:Z120) -> 0 | AB120: 0 | AC120: 0 | AD120: 0 | AE120: 0 | AF120: 0 | AG120: 0 | AH120: =SUM(AB120:AG120) -> 0
A121: 0000000102373 | B121: 中国調理食品 | C121: 0039 | D121: その他 | F121: =IF($E121="","",IFERROR(INDEX(担当者マスタ!$B$2:$B$101,MATCH($E121,担当者マスタ!$A$2:$A$101,0)),"※マスタ未登録")) | G121: 0 | H121: 0 | I121: 0 | J121: 0 | K121: 12.48 | L121: 0 | M121: =SUM(G121:L121) -> 12.48 | N121: 0 | O121: 0 | P121: 0 | Q121: 0 | R121: 2.72 | S121: 0 | T121: =SUM(N121:S121) -> 2.72 | U121: 0 | V121: 0 | W121: 30.595 | X121: 0 | Y121: 0 | Z121: 0 | AA121: =SUM(U121:Z121) -> 30.595 | AB121: 0 | AC121: 0 | AD121: 7.235 | AE121: 0 | AF121: 0 | AG121: 0 | AH121: =SUM(AB121:AG121) -> 7.235
C122: 0039 集計 | D122: その他 | G122: =SUBTOTAL(9,G116:G121) -> 14.4 | H122: =SUBTOTAL(9,H116:H121) -> 36.734 | I122: =SUBTOTAL(9,I116:I121) -> 29.94 | J122: =SUBTOTAL(9,J116:J121) -> 8.501 | K122: =SUBTOTAL(9,K116:K121) -> 22.624 | L122: =SUBTOTAL(9,L116:L121) -> 1.9 | M122: =SUBTOTAL(9,M116:M121) -> 114.099 | N122: =SUBTOTAL(9,N116:N121) -> 3.973 | ... AH122: =SUBTOTAL(9,AH116:AH121) -> 11.725
A123: 0000000000109 | B123: ㈱ｱｲｽﾞ | C123: 0903 | D123: 西岡 | F123: =IF($E123="","",IFERROR(INDEX(担当者マスタ!$B$2:$B$101,MATCH($E123,担当者マスタ!$A$2:$A$101,0)),"※マスタ未登録")) | G123: 7.864 | H123: 0 | I123: 2.23 | J123: 0 | K123: 120.015 | L123: 0 | M123: =SUM(G123:L123) -> 130.109 | N123: 2.086 | O123: 0 | P123: 0.36 | Q123: 0 | R123: 33.163 | S123: 0 | T123: =SUM(N123:S123) -> 35.609 | U123: 3.75 | V123: 2.23 | W123: 7.5 | X123: 110.848 | Y123: 13.07 | Z123: 0 | AA123: =SUM(U123:Z123) -> 137.398 | AB123: 1.14 | AC123: 0.38 | AD123: 2.28 | AE123: 30.982 | AF123: 3.581 | AG123: 0 | AH123: =SUM(AB123:AG123) -> 38.363
A124: 0000000002109 | B124: (有)市川製麺 | C124: 0903 | D124: 西岡 | F124: =IF($E124="","",IFERROR(INDEX(担当者マスタ!$B$2:$B$101,MATCH($E124,担当者マスタ!$A$2:$A$101,0)),"※マスタ未登録")) | G124: 0 | H124: 0 | I124: 20.65 | J124: 0 | K124: 0 | L124: 0 | M124: =SUM(G124:L124) -> 20.65 | N124: 0 | O124: 0 | P124: 6.915 | Q124: 0 | R124: 0 | S124: 0 | T124: =SUM(N124:S124) -> 6.915 | U124: 0 | V124: 21.07 | W124: 0 | X124: 0 | Y124: 0 | Z124: 1.64 | AA124: =SUM(U124:Z124) -> 22.71 | AB124: 0 | AC124: 8.78 | AD124: 0 | AE124: 0 | AF124: 0 | AG124: 0.116 | AH124: =SUM(AB124:AG124) -> 8.896
A125: 0000000003509 | B125: (有)うつわ屋 | C125: 0903 | D125: 西岡 | F125: =IF($E125="","",IFERROR(INDEX(担当者マスタ!$B$2:$B$101,MATCH($E125,担当者マスタ!$A$2:$A$101,0)),"※マスタ未登録")) | G125: 71.845 | H125: 31.296 | I125: 22.87 | J125: 17.019 | K125: 42.05 | L125: 52.317 | M125: =SUM(G125:L125) -> 237.397 | N125: 9.174 | O125: 3.462 | P125: 2.52 | Q125: 1.874 | R125: 3.901 | S125: 6.087 | T125: =SUM(N125:S125) -> 27.018 | U125: 51.501 | V125: 70.728 | W125: 93.364 | X125: 5.845 | Y125: 47.253 | Z125: 63.29 | AA125: =SUM(U125:Z125) -> 331.981 | AB125: 4.821 | AC125: 7.805 | AD125: 10.462 | AE125: 0.644 | AF125: 5.231 | AG125: 6.261 | AH125: =SUM(AB125:AG125) -> 35.224
A126: 0000000006109 | B126: ㈱小川商店 | C126: 0903 | D126: 西岡 | F126: =IF($E126="","",IFERROR(INDEX(担当者マスタ!$B$2:$B$101,MATCH($E126,担当者マスタ!$A$2:$A$101,0)),"※マスタ未登録")) | G126: 16.55 | H126: 31.9 | I126: 14.2 | J126: 9.8 | K126: 9.8 | L126: 21.25 | M126: =SUM(G126:L126) -> 103.5 | N126: 6.85 | O126: 12.8 | P126: 5.52 | Q126: 3.52 | R126: 3.52 | S126: 7.79 | T126: =SUM(N126:S126) -> 40 | U126: 12.55 | V126: 28.57 | W126: 11.45 | X126: 12.6 | Y126: 21.25 | Z126: 15.35 | AA126: =SUM(U126:Z126) -> 101.77 | AB126: 4.77 | AC126: 11.345 | AD126: 4.27 | AE126: 5.06 | AF126: 7.79 | AG126: 5.98 | AH126: =SUM(AB126:AG126) -> 39.215
A127: 0000000007209 | B127: (有)景山水産 | C127: 0903 | D127: 西岡 | F127: =IF($E127="","",IFERROR(INDEX(担当者マスタ!$B$2:$B$101,MATCH($E127,担当者マスタ!$A$2:$A$101,0)),"※マスタ未登録")) | G127: 14.537 | H127: 8.419 | I127: 8.071 | J127: 23.587 | K127: 1.317 | L127: 15.27 | M127: =SUM(G127:L127) -> 71.201 | N127: 4.537 | O127: 1.154 | P127: 1.533 | Q127: 5.364 | R127: 0.227 | S127: 4.137 | T127: =SUM(N127:S127) -> 16.952 | U127: 18.637 | V127: 5.27 | W127: 14.802 | X127: 8.79 | Y127: 17.557 | Z127: 1.317 | AA127: =SUM(U127:Z127) -> 66.373 | AB127: 3.777 | AC127: 0.662 | AD127: 2.776 | AE127: 1.708 | AF127: 3.669 | AG127: 0.165 | AH127: =SUM(AB127:AG127) -> 12.757
A128: 0000000007309 | B128: 境港水産加工業(協組) | C128: 0903 | D128: 西岡 | F128: =IF($E128="","",IFERROR(INDEX(担当者マスタ!$B$2:$B$101,MATCH($E128,担当者マスタ!$A$2:$A$101,0)),"※マスタ未登録")) | G128: 0 | H128: 0 | I128: 53.95 | J128: 0 | K128: 0 | L128: 0 | M128: =SUM(G128:L128) -> 53.95 | N128: 0 | O128: 0 | P128: 5.95 | Q128: 0 | R128: 0 | S128: 0 | T128: =SUM(N128:S128) -> 5.95 | U128: 53.95 | V128: 0 | W128: 0 | X128: 0 | Y128: 0 | Z128: 0 | AA128: =SUM(U128:Z128) -> 53.95 | AB128: 5.95 | AC128: 0 | AD128: 0 | AE128: 0 | AF128: 0 | AG128: 0 | AH128: =SUM(AB128:AG128) -> 5.95
A129: 0000000008909 | B129: ﾘﾊﾞｰﾄﾞ米子 | C129: 0903 | D129: 西岡 | F129: =IF($E129="","",IFERROR(INDEX(担当者マスタ!$B$2:$B$101,MATCH($E129,担当者マスタ!$A$2:$A$101,0)),"※マスタ未登録")) | G129: 10.45 | H129: 7.6 | I129: 3.8 | J129: 2.85 | K129: 4.4 | L129: 13.385 | M129: =SUM(G129:L129) -> 42.485 | N129: 2.589 | O129: 1.984 | P129: 0.992 | Q129: 0.605 | R129: 1.9 | S129: 3.695 | T129: =SUM(N129:S129) -> 11.765 | U129: 11.9 | V129: 16.2 | W129: 4.3 | X129: 14 | Y129: 4.3 | Z129: 17.175 | AA129: =SUM(U129:Z129) -> 67.875 | AB129: 3.464 | AC129: 4.944 | AD129: 1.48 | AE129: 4.184 | AF129: 1.48 | AG129: 4.77 | AH129: =SUM(AB129:AG129) -> 20.322
A130: 0000000008959 | B130: ﾘﾊﾞｰﾄﾞ本社 | C130: 0903 | D130: 西岡 | F130: =IF($E130="","",IFERROR(INDEX(担当者マスタ!$B$2:$B$101,MATCH($E130,担当者マスタ!$A$2:$A$101,0)),"※マスタ未登録")) | G130: 0 | H130: 18.56 | I130: 18.56 | J130: 0 | K130: 0 | L130: 0 | M130: =SUM(G130:L130) -> 37.12 | N130: 0 | O130: 1.952 | P130: 1.952 | Q130: 0 | R130: 0 | S130: 0 | T130: =SUM(N130:S130) -> 3.904 | U130: 20.56 | V130: 0 | W130: 0 | X130: 0 | Y130: 0 | Z130: 0 | AA130: =SUM(U130:Z130) -> 20.56 | AB130: 3.952 | AC130: 0 | AD130: 0 | AE130: 0 | AF130: 0 | AG130: 0 | AH130: =SUM(AB130:AG130) -> 3.952
A131: 0000000009409 | B131: 環境ﾌﾟﾗﾝﾄ工業㈱ | C131: 0903 | D131: 西岡 | F131: =IF($E131="","",IFERROR(INDEX(担当者マスタ!$B$2:$B$101,MATCH($E131,担当者マスタ!$A$2:$A$101,0)),"※マスタ未登録")) | G131: 44.06 | H131: 65.12 | I131: 433.5 | J131: 28.3 | K131: 69.925 | L131: 160 | M131: =SUM(G131:L131) -> 800.905 | N131: 8.42 | O131: 13.324 | P131: 72.872 | Q131: 5.44 | R131: 15.225 | S131: 43.5 | T131: =SUM(N131:S131) -> 158.781 | U131: 474.03 | V131: 846.55 | W131: 28.61 | X131: 62.57 | Y131: 323.7 | Z131: 282.2 | AA131: =SUM(U131:Z131) -> 2017.66 | AB131: 101.17 | AC131: 166.205 | AD131: 19.595 | AE131: 17.07 | AF131: 63.345 | AG131: 51.05 | AH131: =SUM(AB131:AG131) -> 418.435
A132: 0000000012509 | B132: 甲陽ｹﾐｶﾙ㈱ | C132: 0903 | D132: 西岡 | F132: =IF($E132="","",IFERROR(INDEX(担当者マスタ!$B$2:$B$101,MATCH($E132,担当者マスタ!$A$2:$A$101,0)),"※マスタ未登録")) | G132: 11 | H132: 85.78 | I132: 20.52 | J132: 21.26 | K132: 11 | L132: 37.885 | M132: =SUM(G132:L132) -> 187.445 | N132: 1.5 | O132: 12.9 | P132: 3.6 | Q132: 3.3 | R132: 1.5 | S132: 6.275 | T132: =SUM(N132:S132) -> 29.075 | U132: 37.4 | V132: 66 | W132: 0 | X132: 22 | Y132: 55 | Z132: 7.416 | AA132: =SUM(U132:Z132) -> 187.816 | AB132: 5.82 | AC132: 9 | AD132: 0 | AE132: 3 | AF132: 7.5 | AG132: 1.123 | AH132: =SUM(AB132:AG132) -> 26.443
A133: 0000000015609 | B133: 境港福ｸﾞﾙｰﾌﾟﾎｰﾑ夕日 | C133: 0903 | D133: 西岡 | F133: =IF($E133="","",IFERROR(INDEX(担当者マスタ!$B$2:$B$101,MATCH($E133,担当者マスタ!$A$2:$A$101,0)),"※マスタ未登録")) | G133: 0 | H133: 0 | I133: 26.36 | J133: 15.45 | K133: 14.214 | L133: 0 | M133: =SUM(G133:L133) -> 56.024 | N133: 0 | O133: 0 | P133: 10.2 | Q133: 7.65 | R133: 7.038 | S133: 0 | T133: =SUM(N133:S133) -> 24.888 | U133: 22.45 | V133: 0 | W133: 0 | X133: 22.45 | Y133: 15.45 | Z133: 0 | AA133: =SUM(U133:Z133) -> 60.35 | AB133: 8.99 | AC133: 0 | AD133: 0 | AE133: 8.99 | AF133: 6.95 | AG133: 0 | AH133: =SUM(AB133:AG133) -> 24.93
A134: 0000000017409 | B134: 鳥取県産業技術ｾﾝﾀｰ | C134: 0903 | D134: 西岡 | F134: =IF($E134="","",IFERROR(INDEX(担当者マスタ!$B$2:$B$101,MATCH($E134,担当者マスタ!$A$2:$A$101,0)),"※マスタ未登録")) | G134: 0 | H134: 0 | I134: 74.4 | J134: 0 | K134: 32.8 | L134: 0 | M134: =SUM(G134:L134) -> 107.2 | N134: 0 | O134: 0 | P134: 13.5 | Q134: 0 | R134: 6.32 | S134: 0 | T134: =SUM(N134:S134) -> 19.82 | U134: 0 | V134: 0 | W134: 29.82 | X134: 0 | Y134: 0 | Z134: 0 | AA134: =SUM(U134:Z134) -> 29.82 | AB134: 0 | AC134: 0 | AD134: 5.22 | AE134: 0 | AF134: 0 | AG134: 0 | AH134: =SUM(AB134:AG134) -> 5.22
... A183: 0000000092609 | B183: FOOD Marico | C183: 0903 | D183: 西岡 | F183: =IF($E183="","",IFERROR(INDEX(担当者マスタ!$B$2:$B$101,MATCH($E183,担当者マスタ!$A$2:$A$101,0)),"※マスタ未登録")) | G183: 0 | H183: 0 | I183: 0 | J183: 0 | K183: 0 | L183: 0 | M183: =SUM(G183:L183) -> 0 | N183: 0 | O183: 0 | P183: 0 | Q183: 0 | R183: 0 | S183: 0 | T183: =SUM(N183:S183) -> 0 | U183: 0 | V183: 0 | W183: 30 | X183: 85 | Y183: 0 | Z183: 0 | AA183: =SUM(U183:Z183) -> 115 | AB183: 0 | AC183: 0 | AD183: 8 | AE183: 12.5 | AF183: 0 | AG183: 0 | AH183: =SUM(AB183:AG183) -> 20.5
C184: 0903 集計 | D184: 西岡 | G184: =SUBTOTAL(9,G123:G183) -> 3602.202 | H184: =SUBTOTAL(9,H123:H183) -> 6469.391 | I184: =SUBTOTAL(9,I123:I183) -> 4364.931 | J184: =SUBTOTAL(9,J123:J183) -> 2515.664 | K184: =SUBTOTAL(9,K123:K183) -> 2340.059 | L184: =SUBTOTAL(9,L123:L183) -> 8989.104 | M184: =SUBTOTAL(9,M123:M183) -> 28281.351 | N184: =SUBTOTAL(9,N123:N183) -> 787.913 | ... AH184: =SUBTOTAL(9,AH123:AH183) -> 4897.7575
A185: 0000000001209 | B185: ADEKAﾌｧｲﾝﾌｰｽﾞ㈱ | C185: 0904 | D185: 足立(直) | F185: =IF($E185="","",IFERROR(INDEX(担当者マスタ!$B$2:$B$101,MATCH($E185,担当者マスタ!$A$2:$A$101,0)),"※マスタ未登録")) | G185: 12.8 | H185: 19.9 | I185: 496.1 | J185: 0 | K185: 198.8 | L185: 839.2 | M185: =SUM(G185:L185) -> 1566.8 | N185: 2.3 | O185: 3.94 | P185: 97.105 | Q185: 0 | R185: 30.03 | S185: 108 | T185: =SUM(N185:S185) -> 241.375 | U185: 26.39 | V185: 5.2 | W185: 4040 | X185: 93.02 | Y185: 176.99 | Z185: 264 | AA185: =SUM(U185:Z185) -> 4605.6 | AB185: 6.04 | AC185: 0.52 | AD185: 640.6 | AE185: 17.956 | AF185: 30.74 | AG185: 43.59 | AH185: =SUM(AB185:AG185) -> 739.446
A186: 0000000001409 | B186: ADEKAﾌｧｲﾝﾌｰｽﾞ㈱包装 | C186: 0904 | D186: 足立(直) | F186: =IF($E186="","",IFERROR(INDEX(担当者マスタ!$B$2:$B$101,MATCH($E186,担当者マスタ!$A$2:$A$101,0)),"※マスタ未登録")) | G186: 1847.849 | H186: 3283.188 | I186: 2835.888 | J186: 2642.064 | K186: 3008.25 | L186: 2020.148 | M186: =SUM(G186:L186) -> 15637.387 | N186: 519.398 | O186: 920.558 | P186: 792.795 | Q186: 748.779 | R186: 855.596 | S186: 558.973 | T186: =SUM(N186:S186) -> 4396.099 | U186: 3260.068 | V186: 2896.38 | W186: 2644.612 | X186: 2281.002 | Y186: 2636.228 | Z186: 2432.224 | AA186: =SUM(U186:Z186) -> 16150.514 | AB186: 891.295 | AC186: 793.915 | AD186: 729.462 | AE186: 635.967 | AF186: 725.964 | AG186: 659.733 | AH186: =SUM(AB186:AG186) -> 4436.336
A187: 0000000005709 | B187: (有)岡野青果 | C187: 0904 | D187: 足立(直) | F187: =IF($E187="","",IFERROR(INDEX(担当者マスタ!$B$2:$B$101,MATCH($E187,担当者マスタ!$A$2:$A$101,0)),"※マスタ未登録")) | G187: 500.475 | H187: 708.258 | I187: 1091.373 | J187: 314.1 | K187: 1599.83 | L187: 324.94 | M187: =SUM(G187:L187) -> 4538.976 | N187: 90.42 | O187: 152.08 | P187: 221.024 | Q187: 65.02 | R187: 450.43 | S187: 65.69 | T187: =SUM(N187:S187) -> 1044.664 | U187: 1811.047 | V187: 109.52 | W187: 1966.5 | X187: 390.475 | Y187: 992.58 | Z187: 359.191 | AA187: =SUM(U187:Z187) -> 5629.313 | AB187: 434.665 | AC187: 24.246 | AD187: 542.285 | AE187: 79.93 | AF187: 249.24 | AG187: 88.746 | AH187: =SUM(AB187:AG187) -> 1419.112
A188: 0000000005909 | B188: (有)岡野農場 | C188: 0904 | D188: 足立(直) | F188: =IF($E188="","",IFERROR(INDEX(担当者マスタ!$B$2:$B$101,MATCH($E188,担当者マスタ!$A$2:$A$101,0)),"※マスタ未登録")) | G188: 221.272 | H188: 297.18 | I188: 292.615 | J188: 997.71 | K188: 489.775 | L188: 947.906 | M188: =SUM(G188:L188) -> 3246.458 | N188: 62.608 | O188: 42.22 | P188: 60.81 | Q188: 185.657 | R188: 77.565 | S188: 171.686 | T188: =SUM(N188:S188) -> 600.546 | U188: 144.5 | V188: 17.56 | W188: 2653.97 | X188: 0 | Y188: 35.12 | Z188: 0 | AA188: =SUM(U188:Z188) -> 2851.15 | AB188: 22 | AC188: 3 | AD188: 410.073 | AE188: 0 | AF188: 6 | AG188: 0 | AH188: =SUM(AB188:AG188) -> 441.073
A189: 0000000015209 | B189: 境港魚凾㈱ | C189: 0904 | D189: 足立(直) | F189: =IF($E189="","",IFERROR(INDEX(担当者マスタ!$B$2:$B$101,MATCH($E189,担当者マスタ!$A$2:$A$101,0)),"※マスタ未登録")) | G189: 1808.2 | H189: 1011.712 | I189: 202.8 | J189: 164.015 | K189: 114.13 | L189: 465.156 | M189: =SUM(G189:L189) -> 3766.013 | N189: 271.679 | O189: 206.183 | P189: 18.135 | Q189: 14.295 | R189: 11.085 | S189: 72.036 | T189: =SUM(N189:S189) -> 593.413 | U189: 795.44 | V189: 790.038 | W189: 84 | X189: 128 | Y189: 239.322 | Z189: 82.468 | AA189: =SUM(U189:Z189) -> 2119.268 | AB189: 122.603 | AC189: 137.267 | AD189: 5.6 | AE189: 8.4 | AF189: 24.362 | AG189: 11.148 | AH189: =SUM(AB189:AG189) -> 309.38
A190: 0000000015309 | B190: 境港ｾﾝﾀｰ冷蔵㈱ | C190: 0904 | D190: 足立(直) | F190: =IF($E190="","",IFERROR(INDEX(担当者マスタ!$B$2:$B$101,MATCH($E190,担当者マスタ!$A$2:$A$101,0)),"※マスタ未登録")) | G190: 46.75 | H190: 12.24 | I190: 95.03 | J190: 0 | K190: 40.49 | L190: 37.8 | M190: =SUM(G190:L190) -> 232.31 | N190: 7.625 | O190: 1.8 | P190: 12.485 | Q190: 0 | R190: 8.925 | S190: 2.94 | T190: =SUM(N190:S190) -> 33.775 | U190: 12.24 | V190: 28.25 | W190: 48.96 | X190: 99.14 | Y190: 0 | Z190: 52.39 | AA190: =SUM(U190:Z190) -> 240.98 | AB190: 1.8 | AC190: 7.125 | AD190: 7.2 | AE190: 17.18 | AF190: 0 | AG190: 9.555 | AH190: =SUM(AB190:AG190) -> 42.86
A191: 0000000024209 | B191: (有)西米食品 | C191: 0904 | D191: 足立(直) | F191: =IF($E191="","",IFERROR(INDEX(担当者マスタ!$B$2:$B$101,MATCH($E191,担当者マスタ!$A$2:$A$101,0)),"※マスタ未登録")) | G191: 201.485 | H191: 856.957 | I191: 360.507 | J191: 285.385 | K191: 188.75 | L191: 123.555 | M191: =SUM(G191:L191) -> 2016.639 | N191: 56.915 | O191: 130.6 | P191: 71.065 | Q191: 50.695 | R191: 30.677 | S191: 24.165 | T191: =SUM(N191:S191) -> 364.117 | U191: 556.945 | V191: 396.016 | W191: 838.563 | X191: 241.296 | Y191: 120.605 | Z191: 232.915 | AA191: =SUM(U191:Z191) -> 2386.34 | AB191: 94.897 | AC191: 73.996 | AD191: 143.772 | AE191: 43.64 | AF191: 20.07 | AG191: 42.291 | AH191: =SUM(AB191:AG191) -> 418.666
A192: 0000000025709 | B192: (有)大根屋 | C192: 0904 | D192: 足立(直) | F192: =IF($E192="","",IFERROR(INDEX(担当者マスタ!$B$2:$B$101,MATCH($E192,担当者マスタ!$A$2:$A$101,0)),"※マスタ未登録")) | G192: 785.685 | H192: 797.317 | I192: 127.9 | J192: 1136.529 | K192: 0 | L192: 56.9 | M192: =SUM(G192:L192) -> 2904.331 | N192: 139.269 | O192: 144.113 | P192: 40.15 | Q192: 151.089 | R192: 0 | S192: 10.7 | T192: =SUM(N192:S192) -> 485.321 | U192: 3881.37 | V192: 2598.258 | W192: 1470.362 | X192: 231.8 | Y192: 45.6 | Z192: 30 | AA192: =SUM(U192:Z192) -> 8257.39 | AB192: 556.24 | AC192: 422.427 | AD192: 185.687 | AE192: 44.325 | AF192: 4.6 | AG192: 10.1 | AH192: =SUM(AB192:AG192) -> 1223.379
A193: 0000000030109 | B193: ㈱ユニバックシール | C193: 0904 | D193: 足立(直) | F193: =IF($E193="","",IFERROR(INDEX(担当者マスタ!$B$2:$B$101,MATCH($E193,担当者マスタ!$A$2:$A$101,0)),"※マスタ未登録")) | G193: 0 | H193: 27.8 | I193: 0 | J193: 0 | K193: 0 | L193: 0 | M193: =SUM(G193:L193) -> 27.8 | N193: 0 | O193: 2.94 | P193: 0 | Q193: 0 | R193: 0 | S193: 0 | T193: =SUM(N193:S193) -> 2.94 | U193: 0 | V193: 0 | W193: 0 | X193: 0 | Y193: 0 | Z193: 0 | AA193: =SUM(U193:Z193) -> 0 | AB193: 0 | AC193: 0 | AD193: 0 | AE193: 0 | AF193: 0 | AG193: 0 | AH193: =SUM(AB193:AG193) -> 0
A194: 0000000034609 | B194: 日本海冷凍魚㈱資材 | C194: 0904 | D194: 足立(直) | F194: =IF($E194="","",IFERROR(INDEX(担当者マスタ!$B$2:$B$101,MATCH($E194,担当者マスタ!$A$2:$A$101,0)),"※マスタ未登録")) | G194: 2602.042 | H194: 2798.943 | I194: 3424.208 | J194: 2190.732 | K194: 2545.201 | L194: 2984.971 | M194: =SUM(G194:L194) -> 16546.097 | N194: 604.389 | O194: 619.371 | P194: 721.013 | Q194: 461.334 | R194: 578.242 | S194: 670.156 | T194: =SUM(N194:S194) -> 3654.505 | U194: 3154.742 | V194: 2827.904 | W194: 3412.941 | X194: 2388.104 | Y194: 2115.427 | Z194: 3828.073 | AA194: =SUM(U194:Z194) -> 17727.191 | AB194: 703.469 | AC194: 639.943 | AD194: 715.264 | AE194: 507.902 | AF194: 432.85 | AG194: 789.817 | AH194: =SUM(AB194:AG194) -> 3789.245
A195: 0000000034709 | B195: 日本海冷凍魚㈱部品 | C195: 0904 | D195: 足立(直) | F195: =IF($E195="","",IFERROR(INDEX(担当者マスタ!$B$2:$B$101,MATCH($E195,担当者マスタ!$A$2:$A$101,0)),"※マスタ未登録")) | G195: 40.86 | H195: 140.06 | I195: 64.225 | J195: 42.7 | K195: 0 | L195: 72.58 | M195: =SUM(G195:L195) -> 360.425 | N195: 12.48 | O195: 19.1 | P195: 17.48 | Q195: 11.65 | R195: 0 | S195: 16.82 | T195: =SUM(N195:S195) -> 77.53 | U195: 61.2 | V195: 9.2 | W195: 0 | X195: 71.4 | Y195: 50.6 | Z195: 403.45 | AA195: =SUM(U195:Z195) -> 595.85 | AB195: 16.4 | AC195: 1.94 | AD195: 0 | AE195: 16.2 | AF195: 11.8 | AG195: 87.17 | AH195: =SUM(AB195:AG195) -> 133.51
A196: 0000000036909 | B196: ㈱ﾌｧｰｽﾄﾌﾟﾗｲｽﾞ | C196: 0904 | D196: 足立(直) | F196: =IF($E196="","",IFERROR(INDEX(担当者マスタ!$B$2:$B$101,MATCH($E196,担当者マスタ!$A$2:$A$101,0)),"※マスタ未登録")) | G196: 1009.26 | H196: 2388.582 | I196: 1198.474 | J196: 1163.764 | K196: 1170.35 | L196: 1198.296 | M196: =SUM(G196:L196) -> 8128.726 | N196: 158.76 | O196: 375.732 | P196: 188.524 | Q196: 183.064 | R196: 184.1 | S196: 188.496 | T196: =SUM(N196:S196) -> 1278.676 | U196: 2377.012 | V196: 1182.276 | W196: 1224.106 | X196: 1181.92 | Y196: 1198.474 | Z196: 1197.584 | AA196: =SUM(U196:Z196) -> 8361.372 | AB196: 373.912 | AC196: 185.976 | AD196: 192.556 | AE196: 185.92 | AF196: 188.524 | AG196: 188.384 | AH196: =SUM(AB196:AG196) -> 1315.272
... A204: 0000000091709 | B204: ㈱上代 | C204: 0904 | D204: 足立(直) | F204: =IF($E204="","",IFERROR(INDEX(担当者マスタ!$B$2:$B$101,MATCH($E204,担当者マスタ!$A$2:$A$101,0)),"※マスタ未登録")) | G204: 9.3 | H204: 56 | I204: 26.2 | J204: 0 | K204: 0 | L204: 27.9 | M204: =SUM(G204:L204) -> 119.4 | N204: 3.15 | O204: 8.48 | P204: 2.8 | Q204: 0 | R204: 0 | S204: 9.45 | T204: =SUM(N204:S204) -> 23.88 | U204: 0 | V204: 0 | W204: 37.12 | X204: 0 | Y204: 0 | Z204: 0 | AA204: =SUM(U204:Z204) -> 37.12 | AB204: 0 | AC204: 0 | AD204: 4.48 | AE204: 0 | AF204: 0 | AG204: 0 | AH204: =SUM(AB204:AG204) -> 4.48
C205: 0904 集計 | D205: 足立(直) | G205: =SUBTOTAL(9,G185:G204) -> 9521.178 | H205: =SUBTOTAL(9,H185:H204) -> 13735.246 | I205: =SUBTOTAL(9,I185:I204) -> 11782.985 | J205: =SUBTOTAL(9,J185:J204) -> 9025.699 | K205: =SUBTOTAL(9,K185:K204) -> 9427.026 | L205: =SUBTOTAL(9,L185:L204) -> 10697.682 | M205: =SUBTOTAL(9,M185:M204) -> 64189.816 | N205: =SUBTOTAL(9,N185:N204) -> 2012.548 | ... AH205: =SUBTOTAL(9,AH185:AH204) -> 15795.381
A206: 0000000012909 | B206: (有)小倉水産食品 | C206: 0909 | D206: 藤波 | F206: =IF($E206="","",IFERROR(INDEX(担当者マスタ!$B$2:$B$101,MATCH($E206,担当者マスタ!$A$2:$A$101,0)),"※マスタ未登録")) | G206: 1099.368 | H206: 784.591 | I206: 1005.662 | J206: 683.833 | K206: 413.609 | L206: 341.676 | M206: =SUM(G206:L206) -> 4328.739 | N206: 213.265 | O206: 129.097 | P206: 179.02 | Q206: 127.17 | R206: 67.921 | S206: 63.663 | T206: =SUM(N206:S206) -> 780.136 | U206: 413.512 | V206: 366.304 | W206: 816.724 | X206: 319.316 | Y206: 461.614 | Z206: 577.646 | AA206: =SUM(U206:Z206) -> 2955.116 | AB206: 83.322 | AC206: 67.855 | AD206: 140.527 | AE206: 50.823 | AF206: 85.819 | AG206: 93.723 | AH206: =SUM(AB206:AG206) -> 522.069
A207: 0000000017709 | B207: ㈱さんれいﾌｰｽﾞ境港 | C207: 0909 | D207: 藤波 | F207: =IF($E207="","",IFERROR(INDEX(担当者マスタ!$B$2:$B$101,MATCH($E207,担当者マスタ!$A$2:$A$101,0)),"※マスタ未登録")) | G207: 1418.165 | H207: 1818.729 | I207: 2243.96 | J207: 819.811 | K207: 1358.77 | L207: 2499.902 | M207: =SUM(G207:L207) -> 10159.337 | N207: 278.991 | O207: 375.666 | P207: 402.503 | Q207: 136.251 | R207: 232.871 | S207: 449.678 | T207: =SUM(N207:S207) -> 1875.96 | U207: 1684.665 | V207: 1536.231 | W207: 1292.115 | X207: 857.49 | Y207: 851.29 | Z207: 852.88 | AA207: =SUM(U207:Z207) -> 7074.671 | AB207: 353.817 | AC207: 313.369 | AD207: 228.189 | AE207: 171.678 | AF207: 166.122 | AG207: 142.508 | AH207: =SUM(AB207:AG207) -> 1375.683
A208: 0000000017919 | B208: さんれいﾌｰｽﾞ境港機械 | C208: 0909 | D208: 藤波 | F208: =IF($E208="","",IFERROR(INDEX(担当者マスタ!$B$2:$B$101,MATCH($E208,担当者マスタ!$A$2:$A$101,0)),"※マスタ未登録")) | G208: 0 | H208: 0 | I208: 0 | J208: 0 | K208: 4620 | L208: 0 | M208: =SUM(G208:L208) -> 4620 | N208: 0 | O208: 0 | P208: 0 | Q208: 0 | R208: 750 | S208: 0 | T208: =SUM(N208:S208) -> 750 | U208: 0 | V208: 0 | W208: 0 | X208: 0 | Y208: 0 | Z208: 0 | AA208: =SUM(U208:Z208) -> 0 | AB208: 0 | AC208: 0 | AD208: 0 | AE208: 0 | AF208: 0 | AG208: 0 | AH208: =SUM(AB208:AG208) -> 0
A209: 0000000018109 | B209: ㈱さんれいﾌｰｽﾞ安来 | C209: 0909 | D209: 藤波 | F209: =IF($E209="","",IFERROR(INDEX(担当者マスタ!$B$2:$B$101,MATCH($E209,担当者マスタ!$A$2:$A$101,0)),"※マスタ未登録")) | G209: 4353.224 | H209: 4232.036 | I209: 5620.353 | J209: 3336.771 | K209: 7383.901 | L209: 4785.934 | M209: =SUM(G209:L209) -> 29712.219 | N209: 593.187 | O209: 629.177 | P209: 1046.888 | Q209: 425.037 | R209: 1339.34 | S209: 1011.313 | T209: =SUM(N209:S209) -> 5044.942 | U209: 11197.808 | V209: 4654.306 | W209: 3065.56 | X209: 3331.577 | Y209: 3632.858 | Z209: 13248.277 | AA209: =SUM(U209:Z209) -> 39130.386 | AB209: 2657.424 | AC209: 748.761 | AD209: 415.854 | AE209: 450.889 | AF209: 586.206 | AG209: 2423.874 | AH209: =SUM(AB209:AG209) -> 7283.008
A210: 0000000018139 | B210: ㈱さんれいﾌｰｽﾞ管理 | C210: 0909 | D210: 藤波 | F210: =IF($E210="","",IFERROR(INDEX(担当者マスタ!$B$2:$B$101,MATCH($E210,担当者マスタ!$A$2:$A$101,0)),"※マスタ未登録")) | G210: 0 | H210: 0 | I210: 0 | J210: 0 | K210: 0 | L210: 0 | M210: =SUM(G210:L210) -> 0 | N210: 0 | O210: 0 | P210: 0 | Q210: 0 | R210: 0 | S210: 0 | T210: =SUM(N210:S210) -> 0 | U210: 120.72 | V210: 0 | W210: 0 | X210: 0 | Y210: 0 | Z210: 0 | AA210: =SUM(U210:Z210) -> 120.72 | AB210: 20.64 | AC210: 0 | AD210: 0 | AE210: 0 | AF210: 0 | AG210: 0 | AH210: =SUM(AB210:AG210) -> 20.64
A211: 0000000018149 | B211: さんれい安来保守点検 | C211: 0909 | D211: 藤波 | F211: =IF($E211="","",IFERROR(INDEX(担当者マスタ!$B$2:$B$101,MATCH($E211,担当者マスタ!$A$2:$A$101,0)),"※マスタ未登録")) | G211: 52 | H211: 60 | I211: 84 | J211: 92 | K211: 124 | L211: 104 | M211: =SUM(G211:L211) -> 516 | N211: 52 | O211: 60 | P211: 84 | Q211: 92 | R211: 124 | S211: 104 | T211: =SUM(N211:S211) -> 516 | U211: 248 | V211: 128 | W211: 96 | X211: 52 | Y211: 92 | Z211: 84 | AA211: =SUM(U211:Z211) -> 700 | AB211: 248 | AC211: 128 | AD211: 96 | AE211: 52 | AF211: 92 | AG211: 84 | AH211: =SUM(AB211:AG211) -> 700
A212: 0000000018509 | B212: ㈱さんれいﾌｰｽﾞ | C212: 0909 | D212: 藤波 | F212: =IF($E212="","",IFERROR(INDEX(担当者マスタ!$B$2:$B$101,MATCH($E212,担当者マスタ!$A$2:$A$101,0)),"※マスタ未登録")) | G212: 10.2 | H212: 48.475 | I212: 0 | J212: 0 | K212: 0 | L212: 34.956 | M212: =SUM(G212:L212) -> 93.631 | N212: 1.4 | O212: 2.422 | P212: 4.77 | Q212: 0 | R212: 0 | S212: 6.872 | T212: =SUM(N212:S212) -> 15.464 | U212: 37.315 | V212: 17.819 | W212: 0 | X212: 31.825 | Y212: 26.256 | Z212: 5.49 | AA212: =SUM(U212:Z212) -> 118.705 | AB212: 5.015 | AC212: 3.399 | AD212: 0 | AE212: 4.025 | AF212: 4.576 | AG212: 0.99 | AH212: =SUM(AB212:AG212) -> 18.005
A213: 0000000018909 | B213: ㈱さんれいﾌｰｽﾞ第2営 | C213: 0909 | D213: 藤波 | F213: =IF($E213="","",IFERROR(INDEX(担当者マスタ!$B$2:$B$101,MATCH($E213,担当者マスタ!$A$2:$A$101,0)),"※マスタ未登録")) | G213: 0 | H213: 0 | I213: 1.162 | J213: 0 | K213: 0 | L213: 0 | M213: =SUM(G213:L213) -> 1.162 | N213: 0 | O213: 0 | P213: 0.063 | Q213: 0 | R213: 0 | S213: 0 | T213: =SUM(N213:S213) -> 0.063 | U213: 0 | V213: 0 | W213: 0 | X213: 0 | Y213: 0 | Z213: 0 | AA213: =SUM(U213:Z213) -> 0 | AB213: 0 | AC213: 0 | AD213: 0 | AE213: 0 | AF213: 0 | AG213: 0 | AH213: =SUM(AB213:AG213) -> 0
A214: 0000000019009 | B214: ㈱さんれいﾌｰｽﾞ津山 | C214: 0909 | D214: 藤波 | F214: =IF($E214="","",IFERROR(INDEX(担当者マスタ!$B$2:$B$101,MATCH($E214,担当者マスタ!$A$2:$A$101,0)),"※マスタ未登録")) | G214: 0 | H214: 0 | I214: 0 | J214: 0 | K214: 0 | L214: 52.8 | M214: =SUM(G214:L214) -> 52.8 | N214: 0 | O214: 0 | P214: 0 | Q214: 0 | R214: 0 | S214: 9.9 | T214: =SUM(N214:S214) -> 9.9 | U214: 0 | V214: 0 | W214: 0 | X214: 0 | Y214: 52.8 | Z214: 0 | AA214: =SUM(U214:Z214) -> 52.8 | AB214: 0 | AC214: 0 | AD214: 0 | AE214: 0 | AF214: 9.9 | AG214: 0 | AH214: =SUM(AB214:AG214) -> 9.9
A215: 0000000035009 | B215: 日本食品工業㈱ | C215: 0909 | D215: 藤波 | F215: =IF($E215="","",IFERROR(INDEX(担当者マスタ!$B$2:$B$101,MATCH($E215,担当者マスタ!$A$2:$A$101,0)),"※マスタ未登録")) | G215: 39.6 | H215: 66.1 | I215: 26.6 | J215: 39.9 | K215: 5.3 | L215: 0 | M215: =SUM(G215:L215) -> 177.5 | N215: 8.8 | O215: 12.9 | P215: 4.26 | Q215: 12.3 | R215: 0.5 | S215: 0 | T215: =SUM(N215:S215) -> 38.76 | U215: 42.6 | V215: 0 | W215: 21.6 | X215: 0 | Y215: 0 | Z215: 0 | AA215: =SUM(U215:Z215) -> 64.2 | AB215: 8.5 | AC215: 0 | AD215: 3.9 | AE215: 0 | AF215: 0 | AG215: 0 | AH215: =SUM(AB215:AG215) -> 12.4
A216: 0000000035059 | B216: (有)大味研 | C216: 0909 | D216: 藤波 | F216: =IF($E216="","",IFERROR(INDEX(担当者マスタ!$B$2:$B$101,MATCH($E216,担当者マスタ!$A$2:$A$101,0)),"※マスタ未登録")) | G216: 512.24 | H216: 1302.48 | I216: 657.72 | J216: 0 | K216: 658.44 | L216: 644.76 | M216: =SUM(G216:L216) -> 3775.64 | N216: 115.216 | O216: 265.68 | P216: 132.84 | Q216: 0 | R216: 133.06 | S216: 132.84 | T216: =SUM(N216:S216) -> 779.636 | U216: 391.99 | V216: 1315.44 | W216: 569.976 | X216: 1971.555 | Y216: 0 | Z216: 0 | AA216: =SUM(U216:Z216) -> 4248.961 | AB216: 80.77 | AC216: 265.68 | AD216: 140.208 | AE216: 324.72 | AF216: 0 | AG216: 0 | AH216: =SUM(AB216:AG216) -> 811.378
A217: 0000000036009 | B217: 鳥取はまみ屋 | C217: 0909 | D217: 藤波 | F217: =IF($E217="","",IFERROR(INDEX(担当者マスタ!$B$2:$B$101,MATCH($E217,担当者マスタ!$A$2:$A$101,0)),"※マスタ未登録")) | G217: 0 | H217: 12.5 | I217: 0 | J217: 0 | K217: 0 | L217: 0 | M217: =SUM(G217:L217) -> 12.5 | N217: 0 | O217: 2.5 | P217: 0 | Q217: 0 | R217: 0 | S217: 0 | T217: =SUM(N217:S217) -> 2.5 | U217: 0 | V217: 0 | W217: 0 | X217: 0 | Y217: 0 | Z217: 0 | AA217: =SUM(U217:Z217) -> 0 | AB217: 0 | AC217: 0 | AD217: 0 | AE217: 0 | AF217: 0 | AG217: 0 | AH217: =SUM(AB217:AG217) -> 0
... A234: 0000000091909 | B234: ㈱澤井珈琲ｳｴﾙﾈｽ | C234: 0909 | D234: 藤波 | F234: =IF($E234="","",IFERROR(INDEX(担当者マスタ!$B$2:$B$101,MATCH($E234,担当者マスタ!$A$2:$A$101,0)),"※マスタ未登録")) | G234: 39 | H234: 0 | I234: 0 | J234: 0 | K234: 649.98 | L234: 0 | M234: =SUM(G234:L234) -> 688.98 | N234: 4.23 | O234: 0 | P234: 0 | Q234: 0 | R234: 188.4 | S234: 0 | T234: =SUM(N234:S234) -> 192.63 | U234: 0 | V234: 0 | W234: 0 | X234: 0 | Y234: 0 | Z234: 0 | AA234: =SUM(U234:Z234) -> 0 | AB234: 0 | AC234: 0 | AD234: 0 | AE234: 0 | AF234: 0 | AG234: 0 | AH234: =SUM(AB234:AG234) -> 0
C235: 0909 集計 | D235: 藤波 | G235: =SUBTOTAL(9,G206:G234) -> 9726.812 | H235: =SUBTOTAL(9,H206:H234) -> 11304.049 | I235: =SUBTOTAL(9,I206:I234) -> 13402.157 | J235: =SUBTOTAL(9,J206:J234) -> 6316.522 | K235: =SUBTOTAL(9,K206:K234) -> 17731.106 | L235: =SUBTOTAL(9,L206:L234) -> 10896.336 | M235: =SUBTOTAL(9,M206:M234) -> 69376.982 | N235: =SUBTOTAL(9,N206:N234) -> 1669.92 | ... AH235: =SUBTOTAL(9,AH206:AH234) -> 14385.56
A236: 0000000000309 | B236: (有)赤石商店 | C236: 0911 | D236: 川邊 | F236: =IF($E236="","",IFERROR(INDEX(担当者マスタ!$B$2:$B$101,MATCH($E236,担当者マスタ!$A$2:$A$101,0)),"※マスタ未登録")) | G236: 0 | H236: 28.8 | I236: 46.125 | J236: 0 | K236: 0 | L236: 0 | M236: =SUM(G236:L236) -> 74.925 | N236: 0 | O236: 4.6 | P236: 11.625 | Q236: 0 | R236: 0 | S236: 0 | T236: =SUM(N236:S236) -> 16.225 | U236: 0 | V236: 0 | W236: 0 | X236: 153 | Y236: 0 | Z236: 0 | AA236: =SUM(U236:Z236) -> 153 | AB236: 0 | AC236: 0 | AD236: 0 | AE236: 24.48 | AF236: 0 | AG236: 0 | AH236: =SUM(AB236:AG236) -> 24.48
A237: 0000000001809 | B237: (有)石鹿商店 | C237: 0911 | D237: 川邊 | F237: =IF($E237="","",IFERROR(INDEX(担当者マスタ!$B$2:$B$101,MATCH($E237,担当者マスタ!$A$2:$A$101,0)),"※マスタ未登録")) | G237: 0 | H237: 0 | I237: 0 | J237: 0 | K237: 0 | L237: 19.3 | M237: =SUM(G237:L237) -> 19.3 | N237: 0 | O237: 0 | P237: 0 | Q237: 0 | R237: 0 | S237: 5.1 | T237: =SUM(N237:S237) -> 5.1 | U237: 0 | V237: 0 | W237: 0 | X237: 0 | Y237: 0 | Z237: 0 | AA237: =SUM(U237:Z237) -> 0 | AB237: 0 | AC237: 0 | AD237: 0 | AE237: 0 | AF237: 0 | AG237: 0 | AH237: =SUM(AB237:AG237) -> 0
...

Sheet 下関
A1: 得意先コード | B1: 得意先略称 | C1: 担当者コード | D1: 担当者名 | E1: 新担当者コード | F1: 新担当者 | G1: 2024/10売上 | H1: 2024/11売上 | I1: 2024/12売上 | J1: 2025/01売上 | K1: 2025/02売上 | L1: 2025/03売上 | M1: 前年度売上合計 | N1: 2024/10粗利益 | O1: 2024/11粗利益 | P1: 2024/12粗利益 | Q1: 2025/01粗利益 | R1: 2025/02粗利益 | S1: 2025/03粗利益 | T1: 前年度粗利益合計 | U1: 2025/10売上 | V1: 2025/11売上 | W1: 2025/12売上 | X1: 2026/01売上 | Y1: 2026/02売上 | Z1: 2026/03売上 | AA1: 今年度売上合計 | AB1: 2025/10粗利益 | AC1: 2025/11粗利益 | AD1: 2025/12粗利益 | AE1: 2026/01粗利益 | AF1: 2026/02粗利益 | AG1: 2026/03粗利益 | AH1: 今年度粗利益合計
A2: 0000000100682 | B2: 深川養鶏田屋 | C2: 0021 | D2: 高橋所長 | F2: =IF($E2="","",IFERROR(INDEX(担当者マスタ!$B$2:$B$101,MATCH($E2,担当者マスタ!$A$2:$A$101,0)),"※マスタ未登録")) | G2: 627.274 | H2: 586.766 | I2: 636.98 | J2: 439.889 | K2: 558.988 | L2: 479.596 | M2: =SUM(G2:L2) -> 3329.493 | N2: 111.011 | O2: 102.985 | P2: 118.218 | Q2: 88.206 | R2: 105.834 | S2: 80.049 | T2: =SUM(N2:S2) -> 606.303 | U2: 666.94 | V2: 555.38 | W2: 750.908 | X2: 556.719 | Y2: 500.888 | Z2: 588.448 | AA2: =SUM(U2:Z2) -> 3619.283 | AB2: 128.876 | AC2: 107.97 | AD2: 148.097 | AE2: 110.398 | AF2: 91.165 | AG2: 105.138 | AH2: =SUM(AB2:AG2) -> 691.644
A3: 0000000101112 | B3: ﾌｼﾞﾐﾂ㈱ | C3: 0021 | D3: 高橋所長 | F3: =IF($E3="","",IFERROR(INDEX(担当者マスタ!$B$2:$B$101,MATCH($E3,担当者マスタ!$A$2:$A$101,0)),"※マスタ未登録")) | G3: 0 | H3: 7.5 | I3: 0 | J3: 0 | K3: 0 | L3: 0 | M3: =SUM(G3:L3) -> 7.5 | N3: 0 | O3: 1.522 | P3: 0 | Q3: 0 | R3: 0 | S3: 0 | T3: =SUM(N3:S3) -> 1.522 | U3: 0 | V3: 0 | W3: 0 | X3: 0 | Y3: 0 | Z3: 0 | AA3: =SUM(U3:Z3) -> 0 | AB3: 0 | AC3: 0 | AD3: 0 | AE3: 0 | AF3: 0 | AG3: 0 | AH3: =SUM(AB3:AG3) -> 0
A4: 0000000101202 | B4: ㈱ﾔﾏﾓ水産 | C4: 0021 | D4: 高橋所長 | F4: =IF($E4="","",IFERROR(INDEX(担当者マスタ!$B$2:$B$101,MATCH($E4,担当者マスタ!$A$2:$A$101,0)),"※マスタ未登録")) | G4: 2583.956 | H4: 4914.968 | I4: 5317.348 | J4: 1981.78 | K4: 1361.999 | L4: 1233.177 | M4: =SUM(G4:L4) -> 17393.228 | N4: 616.553 | O4: 1111.27 | P4: 1271.882 | Q4: 479.304 | R4: 275.037 | S4: 246.329 | T4: =SUM(N4:S4) -> 4000.375 | U4: 3265.723 | V4: 5615.846 | W4: 7145.665 | X4: 1999.467 | Y4: 1450.982 | Z4: 904.831 | AA4: =SUM(U4:Z4) -> 20382.514 | AB4: 763.622 | AC4: 1293.181 | AD4: 1656.737 | AE4: 424.358 | AF4: 305.558 | AG4: 181.14 | AH4: =SUM(AB4:AG4) -> 4624.596
A5: 0000000101232 | B5: (有)森本商店 | C5: 0021 | D5: 高橋所長 | F5: =IF($E5="","",IFERROR(INDEX(担当者マスタ!$B$2:$B$101,MATCH($E5,担当者マスタ!$A$2:$A$101,0)),"※マスタ未登録")) | G5: 42.24 | H5: 131.38 | I5: 148.94 | J5: 10.56 | K5: 120.92 | L5: 31.68 | M5: =SUM(G5:L5) -> 485.72 | N5: 7.04 | O5: 28.592 | P5: 39.94 | Q5: 1.76 | R5: 33.24 | S5: 5.28 | T5: =SUM(N5:S5) -> 115.852 | U5: 35.312 | V5: 158.49 | W5: 432.92 | X5: 86.16 | Y5: 28.49 | Z5: 99.14 | AA5: =SUM(U5:Z5) -> 840.512 | AB5: 7.072 | AC5: 40.9 | AD5: 115.4 | AE5: 23.18 | AF5: 5.71 | AG5: 27.09 | AH5: =SUM(AB5:AG5) -> 219.352
A6: 0000000101242 | B6: (有)海人 門司港本店 | C6: 0021 | D6: 高橋所長 | F6: =IF($E6="","",IFERROR(INDEX(担当者マスタ!$B$2:$B$101,MATCH($E6,担当者マスタ!$A$2:$A$101,0)),"※マスタ未登録")) | G6: 21.6 | H6: 0 | I6: 62.7 | J6: 24.98 | K6: 21.6 | L6: 0 | M6: =SUM(G6:L6) -> 130.88 | N6: 6.99 | O6: 0 | P6: 7.224 | Q6: 7.2 | R6: 6.99 | S6: 0 | T6: =SUM(N6:S6) -> 28.404 | U6: 0 | V6: 0 | W6: 42.78 | X6: 46.88 | Y6: 0 | Z6: 0 | AA6: =SUM(U6:Z6) -> 89.66 | AB6: 0 | AC6: 0 | AD6: 7.609 | AE6: 14.19 | AF6: 0 | AG6: 0 | AH6: =SUM(AB6:AG6) -> 21.799
A7: 0000000101272 | B7: 海転からと市場寿司 | C7: 0021 | D7: 高橋所長 | F7: =IF($E7="","",IFERROR(INDEX(担当者マスタ!$B$2:$B$101,MATCH($E7,担当者マスタ!$A$2:$A$101,0)),"※マスタ未登録")) | G7: 0 | H7: 0 | I7: 0 | J7: 0 | K7: 0 | L7: 0 | M7: =SUM(G7:L7) -> 0 | N7: 0 | O7: 0 | P7: 0 | Q7: 0 | R7: 0 | S7: 0 | T7: =SUM(N7:S7) -> 0 | U7: 13.62 | V7: 0 | W7: 0 | X7: 0 | Y7: 0 | Z7: 0 | AA7: =SUM(U7:Z7) -> 13.62 | AB7: 4.32 | AC7: 0 | AD7: 0 | AE7: 0 | AF7: 0 | AG7: 0 | AH7: =SUM(AB7:AG7) -> 4.32
A8: 0000000101752 | B8: (有)萩陶苑 | C8: 0021 | D8: 高橋所長 | F8: =IF($E8="","",IFERROR(INDEX(担当者マスタ!$B$2:$B$101,MATCH($E8,担当者マスタ!$A$2:$A$101,0)),"※マスタ未登録")) | G8: 86.409 | H8: 50.322 | I8: 244.57 | J8: 0 | K8: 109.831 | L8: 276.201 | M8: =SUM(G8:L8) -> 767.333 | N8: 23.722 | O8: 13.597 | P8: 66.994 | Q8: 0 | R8: 30.847 | S8: 76.645 | T8: =SUM(N8:S8) -> 211.805 | U8: 83.827 | V8: 51.25 | W8: 206.802 | X8: 109.442 | Y8: 159.463 | Z8: 126.015 | AA8: =SUM(U8:Z8) -> 736.799 | AB8: 24.306 | AC8: 13.41 | AD8: 58.163 | AE8: 30.106 | AF8: 44.727 | AG8: 36.636 | AH8: =SUM(AB8:AG8) -> 207.348
A9: 0000000101762 | B9: ㈱ﾅｶｵ | C9: 0021 | D9: 高橋所長 | F9: =IF($E9="","",IFERROR(INDEX(担当者マスタ!$B$2:$B$101,MATCH($E9,担当者マスタ!$A$2:$A$101,0)),"※マスタ未登録")) | G9: 90.048 | H9: 346.4 | I9: 30 | J9: 187 | K9: 159 | L9: 136.526 | M9: =SUM(G9:L9) -> 948.974 | N9: 20.824 | O9: 68.72 | P9: 7 | Q9: 34.5 | R9: 30.2 | S9: 30.896 | T9: =SUM(N9:S9) -> 192.14 | U9: 225.584 | V9: 51 | W9: 136.2 | X9: 244.47 | Y9: 166.2 | Z9: 473.95 | AA9: =SUM(U9:Z9) -> 1297.404 | AB9: 47.204 | AC9: 8 | AD9: 30.2 | AE9: 53.82 | AF9: 36.3 | AG9: 104.63 | AH9: =SUM(AB9:AG9) -> 280.154
A10: 0000000101972 | B10: 山陽食品工業㈱ | C10: 0021 | D10: 高橋所長 | F10: =IF($E10="","",IFERROR(INDEX(担当者マスタ!$B$2:$B$101,MATCH($E10,担当者マスタ!$A$2:$A$101,0)),"※マスタ未登録")) | G10: 2243.321 | H10: 1971.139 | I10: 1782.016 | J10: 1355.819 | K10: 1429.735 | L10: 2072.647 | M10: =SUM(G10:L10) -> 10854.677 | N10: 506.575 | O10: 458.214 | P10: 415.525 | Q10: 297.15 | R10: 312.246 | S10: 452.533 | T10: =SUM(N10:S10) -> 2442.243 | U10: 1897.326 | V10: 1752.698 | W10: 2138.748 | X10: 1387.22 | Y10: 1521.007 | Z10: 1888.689 | AA10: =SUM(U10:Z10) -> 10585.688 | AB10: 448.308 | AC10: 415.46 | AD10: 484.266 | AE10: 302.932 | AF10: 319.391 | AG10: 390.061 | AH10: =SUM(AB10:AG10) -> 2360.418
A11: 0000000102102 | B11: ㈱土晃 | C11: 0021 | D11: 高橋所長 | F11: =IF($E11="","",IFERROR(INDEX(担当者マスタ!$B$2:$B$101,MATCH($E11,担当者マスタ!$A$2:$A$101,0)),"※マスタ未登録")) | G11: 0 | H11: 0 | I11: 0 | J11: 0 | K11: 0 | L11: 118.65 | M11: =SUM(G11:L11) -> 118.65 | N11: 0 | O11: 0 | P11: 0 | Q11: 0 | R11: 0 | S11: 30.45 | T11: =SUM(N11:S11) -> 30.45 | U11: 0 | V11: 0 | W11: 0 | X11: 0 | Y11: 0 | Z11: 0 | AA11: =SUM(U11:Z11) -> 0 | AB11: 0 | AC11: 0 | AD11: 0 | AE11: 0 | AF11: 0 | AG11: 0 | AH11: =SUM(AB11:AG11) -> 0
A12: 0000000102302 | B12: ㈱山京 | C12: 0021 | D12: 高橋所長 | F12: =IF($E12="","",IFERROR(INDEX(担当者マスタ!$B$2:$B$101,MATCH($E12,担当者マスタ!$A$2:$A$101,0)),"※マスタ未登録")) | G12: 0 | H12: 0 | I12: 22.2 | J12: 0 | K12: 0 | L12: 0 | M12: =SUM(G12:L12) -> 22.2 | N12: 0 | O12: 0 | P12: 4.695 | Q12: 0 | R12: 0 | S12: 0 | T12: =SUM(N12:S12) -> 4.695 | U12: 0 | V12: 23.975 | W12: 0 | X12: 0 | Y12: 0 | Z12: 23.975 | AA12: =SUM(U12:Z12) -> 47.95 | AB12: 0 | AC12: 5.594 | AD12: 0 | AE12: 0 | AF12: 0 | AG12: 5.594 | AH12: =SUM(AB12:AG12) -> 11.188
A13: 0000000102492 | B13: (協)萩大井浦加工場 | C13: 0021 | D13: 高橋所長 | F13: =IF($E13="","",IFERROR(INDEX(担当者マスタ!$B$2:$B$101,MATCH($E13,担当者マスタ!$A$2:$A$101,0)),"※マスタ未登録")) | G13: 1724.145 | H13: 1335.487 | I13: 1915.001 | J13: 1205.26 | K13: 1177.54 | L13: 1422.668 | M13: =SUM(G13:L13) -> 8780.101 | N13: 470.723 | O13: 370.242 | P13: 463.538 | Q13: 276.744 | R13: 281.906 | S13: 371.531 | T13: =SUM(N13:S13) -> 2234.684 | U13: 1149.225 | V13: 729.05 | W13: 999.905 | X13: 479.54 | Y13: 387.624 | Z13: 650.449 | AA13: =SUM(U13:Z13) -> 4395.793 | AB13: 279.047 | AC13: 155.947 | AD13: 217.056 | AE13: 133.83 | AF13: 91.77 | AG13: 113.81 | AH13: =SUM(AB13:AG13) -> 991.46
... A36: 0000000104612 | B36: ㈱清てん | C36: 0021 | D36: 高橋所長 | F36: =IF($E36="","",IFERROR(INDEX(担当者マスタ!$B$2:$B$101,MATCH($E36,担当者マスタ!$A$2:$A$101,0)),"※マスタ未登録")) | G36: 0 | H36: 0 | I36: 0 | J36: 0 | K36: 0 | L36: 0 | M36: =SUM(G36:L36) -> 0 | N36: 0 | O36: 0 | P36: 0 | Q36: 0 | R36: 0 | S36: 0 | T36: =SUM(N36:S36) -> 0 | U36: 7.6 | V36: 26.25 | W36: 15.2 | X36: 0 | Y36: 15.2 | Z36: 15.2 | AA36: =SUM(U36:Z36) -> 79.45 | AB36: 1.4 | AC36: 4.9 | AD36: 2.8 | AE36: 0 | AF36: 2.8 | AG36: 2.8 | AH36: =SUM(AB36:AG36) -> 14.7
C37: 0021 集計 | D37: 高橋所長 | G37: =SUBTOTAL(9,G2:G36) -> 11469.691 | H37: =SUBTOTAL(9,H2:H36) -> 13802.627 | I37: =SUBTOTAL(9,I2:I36) -> 15126.027 | J37: =SUBTOTAL(9,J2:J36) -> 8579.558 | K37: =SUBTOTAL(9,K2:K36) -> 8277.33 | L37: =SUBTOTAL(9,L2:L36) -> 9824.641 | M37: =SUBTOTAL(9,M2:M36) -> 67079.874 | N37: =SUBTOTAL(9,N2:N36) -> 2700.195 | ... AH37: =SUBTOTAL(9,AH2:AH36) -> 15194.882
A38: 0000000101182 | B38: ㈱山賀 | C38: 0024 | D38: 東野 | F38: =IF($E38="","",IFERROR(INDEX(担当者マスタ!$B$2:$B$101,MATCH($E38,担当者マスタ!$A$2:$A$101,0)),"※マスタ未登録")) | G38: 1762.784 | H38: 2011.437 | I38: 2030.469 | J38: 389.063 | K38: 644.198 | L38: 357.816 | M38: =SUM(G38:L38) -> 7195.767 | N38: 380.734 | O38: 416.234 | P38: 449.041 | Q38: 80.852 | R38: 139.69 | S38: 78.898 | T38: =SUM(N38:S38) -> 1545.449 | U38: 2038.455 | V38: 2042.949 | W38: 3446.565 | X38: 498.12 | Y38: 517.755 | Z38: 415.208 | AA38: =SUM(U38:Z38) -> 8959.052 | AB38: 485.763 | AC38: 481.774 | AD38: 756.734 | AE38: 129.237 | AF38: 98.946 | AG38: 108.582 | AH38: =SUM(AB38:AG38) -> 2061.036
A39: 0000000101562 | B39: (有)伊東繁商店 | C39: 0024 | D39: 東野 | F39: =IF($E39="","",IFERROR(INDEX(担当者マスタ!$B$2:$B$101,MATCH($E39,担当者マスタ!$A$2:$A$101,0)),"※マスタ未登録")) | G39: 0 | H39: 273.724 | I39: 900.84 | J39: 84.6 | K39: 84.6 | L39: 102.54 | M39: =SUM(G39:L39) -> 1446.304 | N39: 0 | O39: 39.686 | P39: 128.655 | Q39: 16.38 | R39: 16.38 | S39: 19.98 | T39: =SUM(N39:S39) -> 221.081 | U39: 155.1 | V39: 328.8 | W39: 436.8 | X39: 238.74 | Y39: 98.7 | Z39: 84.6 | AA39: =SUM(U39:Z39) -> 1342.74 | AB39: 30.03 | AC39: 50.55 | AD39: 64.905 | AE39: 39.795 | AF39: 19.11 | AG39: 16.38 | AH39: =SUM(AB39:AG39) -> 220.77
A40: 0000000101612 | B40: 瓜生美和商店 | C40: 0024 | D40: 東野 | F40: =IF($E40="","",IFERROR(INDEX(担当者マスタ!$B$2:$B$101,MATCH($E40,担当者マスタ!$A$2:$A$101,0)),"※マスタ未登録")) | G40: 20.58 | H40: 3.54 | I40: 0 | J40: 0 | K40: 0 | L40: 0 | M40: =SUM(G40:L40) -> 24.12 | N40: 1.512 | O40: 0.216 | P40: 0 | Q40: 0 | R40: 0 | S40: 0 | T40: =SUM(N40:S40) -> 1.728 | U40: 0 | V40: 0 | W40: 0 | X40: 0 | Y40: 0 | Z40: 0 | AA40: =SUM(U40:Z40) -> 0 | AB40: 0 | AC40: 0 | AD40: 0 | AE40: 0 | AF40: 0 | AG40: 0 | AH40: =SUM(AB40:AG40) -> 0
