Workbook

Sheet 包装資材
C1: 境港営業所包装資材
C2: 1．2024年
E3: 売上 | L3: 粗利益 | S3: 粗利益率
E4: 45383 | F4: 45413 | G4: 45444 | H4: 45474 | I4: 45505 | J4: 45536 | K4: 合計 | L4: 45383 | M4: 45413 | N4: 45444 | O4: 45474 | P4: 45505 | Q4: 45536 | R4: 合計 | S4: 45383 | T4: 45413 | U4: 45444 | V4: 45474 | W4: 45505 | X4: 45536 | Y4: 合計
C5: 0903 集計 | D5: 西岡 | E5: =全体!E5-機械!E5 | F5: =全体!F5-機械!F5 | G5: =全体!G5-機械!G5 | H5: =全体!H5-機械!H5 | I5: =全体!I5-機械!I5 | J5: =全体!J5-機械!J5 | K5: =SUM(E5:J5) | L5: =全体!L5-機械!L5 | M5: =全体!M5-機械!M5 | N5: =全体!N5-機械!N5 | O5: =全体!O5-機械!O5 | P5: =全体!P5-機械!P5 | Q5: =全体!Q5-機械!Q5 | R5: =SUM(L5:Q5) | S5: =IF(E5=0,"***",L5/E5) | T5: =IF(F5=0,"***",M5/F5) | U5: =IF(G5=0,"***",N5/G5) | V5: =IF(H5=0,"***",O5/H5) | W5: =IF(I5=0,"***",P5/I5) | X5: =IF(J5=0,"***",Q5/J5) | Y5: =IF(K5=0,"***",R5/K5)
C6: 0904 集計 | D6: 足立次長 | E6: =全体!E6-機械!E6 | F6: =全体!F6-機械!F6 | G6: =全体!G6-機械!G6 | H6: =全体!H6-機械!H6 | I6: =全体!I6-機械!I6 | J6: =全体!J6-機械!J6 | K6: =SUM(E6:J6) | L6: =全体!L6-機械!L6 | M6: =全体!M6-機械!M6 | N6: =全体!N6-機械!N6 | O6: =全体!O6-機械!O6 | P6: =全体!P6-機械!P6 | Q6: =全体!Q6-機械!Q6 | R6: =SUM(L6:Q6) | S6: =IF(E6=0,"***",L6/E6) | T6: =IF(F6=0,"***",M6/F6) | U6: =IF(G6=0,"***",N6/G6) | V6: =IF(H6=0,"***",O6/H6) | W6: =IF(I6=0,"***",P6/I6) | X6: =IF(J6=0,"***",Q6/J6) | Y6: =IF(K6=0,"***",R6/K6)
C7: 0909 集計 | D7: 藤波課長 | E7: =全体!E7-機械!E7 | F7: =全体!F7-機械!F7 | G7: =全体!G7-機械!G7 | H7: =全体!H7-機械!H7 | I7: =全体!I7-機械!I7 | J7: =全体!J7-機械!J7 | K7: =SUM(E7:J7) | L7: =全体!L7-機械!L7 | M7: =全体!M7-機械!M7 | N7: =全体!N7-機械!N7 | O7: =全体!O7-機械!O7 | P7: =全体!P7-機械!P7 | Q7: =全体!Q7-機械!Q7 | R7: =SUM(L7:Q7) | S7: =IF(E7=0,"***",L7/E7) | T7: =IF(F7=0,"***",M7/F7) | U7: =IF(G7=0,"***",N7/G7) | V7: =IF(H7=0,"***",O7/H7) | W7: =IF(I7=0,"***",P7/I7) | X7: =IF(J7=0,"***",Q7/J7) | Y7: =IF(K7=0,"***",R7/K7)
C8: 0910 集計 | D8: 足立課長 | E8: =全体!E8-機械!E8 | F8: =全体!F8-機械!F8 | G8: =全体!G8-機械!G8 | H8: =全体!H8-機械!H8 | I8: =全体!I8-機械!I8 | J8: =全体!J8-機械!J8 | K8: =SUM(E8:J8) | L8: =全体!L8-機械!L8 | M8: =全体!M8-機械!M8 | N8: =全体!N8-機械!N8 | O8: =全体!O8-機械!O8 | P8: =全体!P8-機械!P8 | Q8: =全体!Q8-機械!Q8 | R8: =SUM(L8:Q8) | S8: =IF(E8=0,"***",L8/E8) | T8: =IF(F8=0,"***",M8/F8) | U8: =IF(G8=0,"***",N8/G8) | V8: =IF(H8=0,"***",O8/H8) | W8: =IF(I8=0,"***",P8/I8) | X8: =IF(J8=0,"***",Q8/J8) | Y8: =IF(K8=0,"***",R8/K8)
C9: 0911 集計 | D9: 川邊主任 | E9: =全体!E9-機械!E9 | F9: =全体!F9-機械!F9 | G9: =全体!G9-機械!G9 | H9: =全体!H9-機械!H9 | I9: =全体!I9-機械!I9 | J9: =全体!J9-機械!J9 | K9: =SUM(E9:J9) | L9: =全体!L9-機械!L9 | M9: =全体!M9-機械!M9 | N9: =全体!N9-機械!N9 | O9: =全体!O9-機械!O9 | P9: =全体!P9-機械!P9 | Q9: =全体!Q9-機械!Q9 | R9: =SUM(L9:Q9) | S9: =IF(E9=0,"***",L9/E9) | T9: =IF(F9=0,"***",M9/F9) | U9: =IF(G9=0,"***",N9/G9) | V9: =IF(H9=0,"***",O9/H9) | W9: =IF(I9=0,"***",P9/I9) | X9: =IF(J9=0,"***",Q9/J9) | Y9: =IF(K9=0,"***",R9/K9)
C10: 0914 集計 | D10: 白根主任 | E10: =全体!E10-機械!E10 | F10: =全体!F10-機械!F10 | G10: =全体!G10-機械!G10 | H10: =全体!H10-機械!H10 | I10: =全体!I10-機械!I10 | J10: =全体!J10-機械!J10 | K10: =SUM(E10:J10) | L10: =全体!L10-機械!L10 | M10: =全体!M10-機械!M10 | N10: =全体!N10-機械!N10 | O10: =全体!O10-機械!O10 | P10: =全体!P10-機械!P10 | Q10: =全体!Q10-機械!Q10 | R10: =SUM(L10:Q10) | S10: =IF(E10=0,"***",L10/E10) | T10: =IF(F10=0,"***",M10/F10) | U10: =IF(G10=0,"***",N10/G10) | V10: =IF(H10=0,"***",O10/H10) | W10: =IF(I10=0,"***",P10/I10) | X10: =IF(J10=0,"***",Q10/J10) | Y10: =IF(K10=0,"***",R10/K10)
C11: 0918 集計 | D11: 海外 | E11: =全体!E11-機械!E11 | F11: =全体!F11-機械!F11 | G11: =全体!G11-機械!G11 | H11: =全体!H11-機械!H11 | I11: =全体!I11-機械!I11 | J11: =全体!J11-機械!J11 | K11: =SUM(E11:J11) | L11: =全体!L11-機械!L11 | M11: =全体!M11-機械!M11 | N11: =全体!N11-機械!N11 | O11: =全体!O11-機械!O11 | P11: =全体!P11-機械!P11 | Q11: =全体!Q11-機械!Q11 | R11: =SUM(L11:Q11) | S11: =IF(E11=0,"***",L11/E11) | T11: =IF(F11=0,"***",M11/F11) | U11: =IF(G11=0,"***",N11/G11) | V11: =IF(H11=0,"***",O11/H11) | W11: =IF(I11=0,"***",P11/I11) | X11: =IF(J11=0,"***",Q11/J11) | Y11: =IF(K11=0,"***",R11/K11)
C12: 0919 集計 | D12: その他 | E12: =全体!E12-機械!E12 | F12: =全体!F12-機械!F12 | G12: =全体!G12-機械!G12 | H12: =全体!H12-機械!H12 | I12: =全体!I12-機械!I12 | J12: =全体!J12-機械!J12 | K12: =SUM(E12:J12) | L12: =全体!L12-機械!L12 | M12: =全体!M12-機械!M12 | N12: =全体!N12-機械!N12 | O12: =全体!O12-機械!O12 | P12: =全体!P12-機械!P12 | Q12: =全体!Q12-機械!Q12 | R12: =SUM(L12:Q12) | S12: =IF(E12=0,"***",L12/E12) | T12: =IF(F12=0,"***",M12/F12) | U12: =IF(G12=0,"***",N12/G12) | V12: =IF(H12=0,"***",O12/H12) | W12: =IF(I12=0,"***",P12/I12) | X12: =IF(J12=0,"***",Q12/J12) | Y12: =IF(K12=0,"***",R12/K12)
C13: 0930 集計 | D13: 自治体 | E13: =全体!E13-機械!E13 | F13: =全体!F13-機械!F13 | G13: =全体!G13-機械!G13 | H13: =全体!H13-機械!H13 | I13: =全体!I13-機械!I13 | J13: =全体!J13-機械!J13 | K13: =SUM(E13:J13) | L13: =全体!L13-機械!L13 | M13: =全体!M13-機械!M13 | N13: =全体!N13-機械!N13 | O13: =全体!O13-機械!O13 | P13: =全体!P13-機械!P13 | Q13: =全体!Q13-機械!Q13 | R13: =SUM(L13:Q13) | S13: =IF(E13=0,"***",L13/E13) | T13: =IF(F13=0,"***",M13/F13) | U13: =IF(G13=0,"***",N13/G13) | V13: =IF(H13=0,"***",O13/H13) | W13: =IF(I13=0,"***",P13/I13) | X13: =IF(J13=0,"***",Q13/J13) | Y13: =IF(K13=0,"***",R13/K13)
C14: 合計 | E14: =SUM(E5:E13) | F14: =SUM(F5:F13) | G14: =SUM(G5:G13) | H14: =SUM(H5:H13) | I14: =SUM(I5:I13) | J14: =SUM(J5:J13) | K14: =SUM(K5:K13) | L14: =SUM(L5:L13) | ... R14: =SUM(R5:R13) | S14: =IF(E14=0,"***",L14/E14) | T14: =IF(F14=0,"***",M14/F14) | U14: =IF(G14=0,"***",N14/G14) | V14: =IF(H14=0,"***",O14/H14) | W14: =IF(I14=0,"***",P14/I14) | X14: =IF(J14=0,"***",Q14/J14) | Y14: =IF(K14=0,"***",R14/K14)
C16: 2．2025年
E17: 売上 | L17: 粗利益 | S17: 粗利益率
E18: 45748 | F18: 45778 | G18: 45809 | H18: 45839 | I18: 45870 | J18: 45901 | K18: 合計 | L18: 45748 | M18: 45778 | N18: 45809 | O18: 45839 | P18: 45870 | Q18: 45901 | R18: 合計 | S18: 45748 | T18: 45778 | U18: 45809 | V18: 45839 | W18: 45870 | X18: 45901 | Y18: 合計
C19: 0903 集計 | D19: 西岡 | E19: =全体!E19-機械!E19 | F19: =全体!F19-機械!F19 | G19: =全体!G19-機械!G19 | H19: =全体!H19-機械!H19 | I19: =全体!I19-機械!I19 | J19: =全体!J19-機械!J19 | K19: =SUM(E19:J19) | L19: =全体!L19-機械!L19 | M19: =全体!M19-機械!M19 | N19: =全体!N19-機械!N19 | O19: =全体!O19-機械!O19 | P19: =全体!P19-機械!P19 | Q19: =全体!Q19-機械!Q19 | R19: =SUM(L19:Q19) | S19: =IF(E19=0,"***",L19/E19) | T19: =IF(F19=0,"***",M19/F19) | U19: =IF(G19=0,"***",N19/G19) | V19: =IF(H19=0,"***",O19/H19) | W19: =IF(I19=0,"***",P19/I19) | X19: =IF(J19=0,"***",Q19/J19) | Y19: =IF(K19=0,"***",R19/K19)
C20: 0904 集計 | D20: 足立次長 | E20: =全体!E20-機械!E20 | F20: =全体!F20-機械!F20 | G20: =全体!G20-機械!G20 | H20: =全体!H20-機械!H20 | I20: =全体!I20-機械!I20 | J20: =全体!J20-機械!J20 | K20: =SUM(E20:J20) | L20: =全体!L20-機械!L20 | M20: =全体!M20-機械!M20 | N20: =全体!N20-機械!N20 | O20: =全体!O20-機械!O20 | P20: =全体!P20-機械!P20 | Q20: =全体!Q20-機械!Q20 | R20: =SUM(L20:Q20) | S20: =IF(E20=0,"***",L20/E20) | T20: =IF(F20=0,"***",M20/F20) | U20: =IF(G20=0,"***",N20/G20) | V20: =IF(H20=0,"***",O20/H20) | W20: =IF(I20=0,"***",P20/I20) | X20: =IF(J20=0,"***",Q20/J20) | Y20: =IF(K20=0,"***",R20/K20)
C21: 0909 集計 | D21: 藤波課長 | E21: =全体!E21-機械!E21 | F21: =全体!F21-機械!F21 | G21: =全体!G21-機械!G21 | H21: =全体!H21-機械!H21 | I21: =全体!I21-機械!I21 | J21: =全体!J21-機械!J21 | K21: =SUM(E21:J21) | L21: =全体!L21-機械!L21 | M21: =全体!M21-機械!M21 | N21: =全体!N21-機械!N21 | O21: =全体!O21-機械!O21 | P21: =全体!P21-機械!P21 | Q21: =全体!Q21-機械!Q21 | R21: =SUM(L21:Q21) | S21: =IF(E21=0,"***",L21/E21) | T21: =IF(F21=0,"***",M21/F21) | U21: =IF(G21=0,"***",N21/G21) | V21: =IF(H21=0,"***",O21/H21) | W21: =IF(I21=0,"***",P21/I21) | X21: =IF(J21=0,"***",Q21/J21) | Y21: =IF(K21=0,"***",R21/K21)
C22: 0910 集計 | D22: 足立課長 | E22: =全体!E22-機械!E22 | F22: =全体!F22-機械!F22 | G22: =全体!G22-機械!G22 | H22: =全体!H22-機械!H22 | I22: =全体!I22-機械!I22 | J22: =全体!J22-機械!J22 | K22: =SUM(E22:J22) | L22: =全体!L22-機械!L22 | M22: =全体!M22-機械!M22 | N22: =全体!N22-機械!N22 | O22: =全体!O22-機械!O22 | P22: =全体!P22-機械!P22 | Q22: =全体!Q22-機械!Q22 | R22: =SUM(L22:Q22) | S22: =IF(E22=0,"***",L22/E22) | T22: =IF(F22=0,"***",M22/F22) | U22: =IF(G22=0,"***",N22/G22) | V22: =IF(H22=0,"***",O22/H22) | W22: =IF(I22=0,"***",P22/I22) | X22: =IF(J22=0,"***",Q22/J22) | Y22: =IF(K22=0,"***",R22/K22)
C23: 0911 集計 | D23: 川邊主任 | E23: =全体!E23-機械!E23 | F23: =全体!F23-機械!F23 | G23: =全体!G23-機械!G23 | H23: =全体!H23-機械!H23 | I23: =全体!I23-機械!I23 | J23: =全体!J23-機械!J23 | K23: =SUM(E23:J23) | L23: =全体!L23-機械!L23 | M23: =全体!M23-機械!M23 | N23: =全体!N23-機械!N23 | O23: =全体!O23-機械!O23 | P23: =全体!P23-機械!P23 | Q23: =全体!Q23-機械!Q23 | R23: =SUM(L23:Q23) | S23: =IF(E23=0,"***",L23/E23) | T23: =IF(F23=0,"***",M23/F23) | U23: =IF(G23=0,"***",N23/G23) | V23: =IF(H23=0,"***",O23/H23) | W23: =IF(I23=0,"***",P23/I23) | X23: =IF(J23=0,"***",Q23/J23) | Y23: =IF(K23=0,"***",R23/K23)
C24: 0914 集計 | D24: 白根主任 | E24: =全体!E24-機械!E24 | F24: =全体!F24-機械!F24 | G24: =全体!G24-機械!G24 | H24: =全体!H24-機械!H24 | I24: =全体!I24-機械!I24 | J24: =全体!J24-機械!J24 | K24: =SUM(E24:J24) | L24: =全体!L24-機械!L24 | M24: =全体!M24-機械!M24 | N24: =全体!N24-機械!N24 | O24: =全体!O24-機械!O24 | P24: =全体!P24-機械!P24 | Q24: =全体!Q24-機械!Q24 | R24: =SUM(L24:Q24) | S24: =IF(E24=0,"***",L24/E24) | T24: =IF(F24=0,"***",M24/F24) | U24: =IF(G24=0,"***",N24/G24) | V24: =IF(H24=0,"***",O24/H24) | W24: =IF(I24=0,"***",P24/I24) | X24: =IF(J24=0,"***",Q24/J24) | Y24: =IF(K24=0,"***",R24/K24)
C25: 0918 集計 | D25: 海外 | E25: =全体!E25-機械!E25 | F25: =全体!F25-機械!F25 | G25: =全体!G25-機械!G25 | H25: =全体!H25-機械!H25 | I25: =全体!I25-機械!I25 | J25: =全体!J25-機械!J25 | K25: =SUM(E25:J25) | L25: =全体!L25-機械!L25 | M25: =全体!M25-機械!M25 | N25: =全体!N25-機械!N25 | O25: =全体!O25-機械!O25 | P25: =全体!P25-機械!P25 | Q25: =全体!Q25-機械!Q25 | R25: =SUM(L25:Q25) | S25: =IF(E25=0,"***",L25/E25) | T25: =IF(F25=0,"***",M25/F25) | U25: =IF(G25=0,"***",N25/G25) | V25: =IF(H25=0,"***",O25/H25) | W25: =IF(I25=0,"***",P25/I25) | X25: =IF(J25=0,"***",Q25/J25) | Y25: =IF(K25=0,"***",R25/K25)
C26: 0919 集計 | D26: その他 | E26: =全体!E26-機械!E26 | F26: =全体!F26-機械!F26 | G26: =全体!G26-機械!G26 | H26: =全体!H26-機械!H26 | I26: =全体!I26-機械!I26 | J26: =全体!J26-機械!J26 | K26: =SUM(E26:J26) | L26: =全体!L26-機械!L26 | M26: =全体!M26-機械!M26 | N26: =全体!N26-機械!N26 | O26: =全体!O26-機械!O26 | P26: =全体!P26-機械!P26 | Q26: =全体!Q26-機械!Q26 | R26: =SUM(L26:Q26) | S26: =IF(E26=0,"***",L26/E26) | T26: =IF(F26=0,"***",M26/F26) | U26: =IF(G26=0,"***",N26/G26) | V26: =IF(H26=0,"***",O26/H26) | W26: =IF(I26=0,"***",P26/I26) | X26: =IF(J26=0,"***",Q26/J26) | Y26: =IF(K26=0,"***",R26/K26)
C27: 0930 集計 | D27: 自治体 | E27: =全体!E27-機械!E27 | F27: =全体!F27-機械!F27 | G27: =全体!G27-機械!G27 | H27: =全体!H27-機械!H27 | I27: =全体!I27-機械!I27 | J27: =全体!J27-機械!J27 | K27: =SUM(E27:J27) | L27: =全体!L27-機械!L27 | M27: =全体!M27-機械!M27 | N27: =全体!N27-機械!N27 | O27: =全体!O27-機械!O27 | P27: =全体!P27-機械!P27 | Q27: =全体!Q27-機械!Q27 | R27: =SUM(L27:Q27) | S27: =IF(E27=0,"***",L27/E27) | T27: =IF(F27=0,"***",M27/F27) | U27: =IF(G27=0,"***",N27/G27) | V27: =IF(H27=0,"***",O27/H27) | W27: =IF(I27=0,"***",P27/I27) | X27: =IF(J27=0,"***",Q27/J27) | Y27: =IF(K27=0,"***",R27/K27)
C28: 合計 | E28: =SUM(E19:E27) | F28: =SUM(F19:F27) | G28: =SUM(G19:G27) | H28: =SUM(H19:H27) | I28: =SUM(I19:I27) | J28: =SUM(J19:J27) | K28: =SUM(K19:K27) | L28: =SUM(L19:L27) | ... R28: =SUM(R19:R27) | S28: =IF(E28=0,"***",L28/E28) | T28: =IF(F28=0,"***",M28/F28) | U28: =IF(G28=0,"***",N28/G28) | V28: =IF(H28=0,"***",O28/H28) | W28: =IF(I28=0,"***",P28/I28) | X28: =IF(J28=0,"***",Q28/J28) | Y28: =IF(K28=0,"***",R28/K28)
C30: 3．過年度平均
E31: 売上 | L31: 粗利益 | S31: 粗利益率
E32: 45748 | F32: 45778 | G32: 45809 | H32: 45839 | I32: 45870 | J32: 45901 | K32: 合計 | L32: 45748 | M32: 45778 | N32: 45809 | O32: 45839 | P32: 45870 | Q32: 45901 | R32: 合計 | S32: 45748 | T32: 45778 | U32: 45809 | V32: 45839 | W32: 45870 | X32: 45901 | Y32: 合計
C33: 0903 集計 | D33: 西岡 | E33: =(E19+E5)/2 | F33: =(F19+F5)/2 | G33: =(G19+G5)/2 | H33: =(H19+H5)/2 | I33: =(I19+I5)/2 | J33: =(J19+J5)/2 | K33: =SUM(E33:J33) | L33: =(L19+L5)/2 | M33: =(M19+M5)/2 | N33: =(N19+N5)/2 | O33: =(O19+O5)/2 | P33: =(P19+P5)/2 | Q33: =(Q19+Q5)/2 | R33: =SUM(L33:Q33) | S33: =IF(E33=0,"***",L33/E33) | T33: =IF(F33=0,"***",M33/F33) | U33: =IF(G33=0,"***",N33/G33) | V33: =IF(H33=0,"***",O33/H33) | W33: =IF(I33=0,"***",P33/I33) | X33: =IF(J33=0,"***",Q33/J33) | Y33: =IF(K33=0,"***",R33/K33)
C34: 0904 集計 | D34: 足立次長 | E34: =(E20+E6)/2 | F34: =(F20+F6)/2 | G34: =(G20+G6)/2 | H34: =(H20+H6)/2 | I34: =(I20+I6)/2 | J34: =(J20+J6)/2 | K34: =SUM(E34:J34) | L34: =(L20+L6)/2 | M34: =(M20+M6)/2 | N34: =(N20+N6)/2 | O34: =(O20+O6)/2 | P34: =(P20+P6)/2 | Q34: =(Q20+Q6)/2 | R34: =SUM(L34:Q34) | S34: =IF(E34=0,"***",L34/E34) | T34: =IF(F34=0,"***",M34/F34) | U34: =IF(G34=0,"***",N34/G34) | V34: =IF(H34=0,"***",O34/H34) | W34: =IF(I34=0,"***",P34/I34) | X34: =IF(J34=0,"***",Q34/J34) | Y34: =IF(K34=0,"***",R34/K34)
C35: 0909 集計 | D35: 藤波課長 | E35: =(E21+E7)/2 | F35: =(F21+F7)/2 | G35: =(G21+G7)/2 | H35: =(H21+H7)/2 | I35: =(I21+I7)/2 | J35: =(J21+J7)/2 | K35: =SUM(E35:J35) | L35: =(L21+L7)/2 | M35: =(M21+M7)/2 | N35: =(N21+N7)/2 | O35: =(O21+O7)/2 | P35: =(P21+P7)/2 | Q35: =(Q21+Q7)/2 | R35: =SUM(L35:Q35) | S35: =IF(E35=0,"***",L35/E35) | T35: =IF(F35=0,"***",M35/F35) | U35: =IF(G35=0,"***",N35/G35) | V35: =IF(H35=0,"***",O35/H35) | W35: =IF(I35=0,"***",P35/I35) | X35: =IF(J35=0,"***",Q35/J35) | Y35: =IF(K35=0,"***",R35/K35)
C36: 0910 集計 | D36: 足立課長 | E36: =(E22+E8)/2 | F36: =(F22+F8)/2 | G36: =(G22+G8)/2 | H36: =(H22+H8)/2 | I36: =(I22+I8)/2 | J36: =(J22+J8)/2 | K36: =SUM(E36:J36) | L36: =(L22+L8)/2 | M36: =(M22+M8)/2 | N36: =(N22+N8)/2 | O36: =(O22+O8)/2 | P36: =(P22+P8)/2 | Q36: =(Q22+Q8)/2 | R36: =SUM(L36:Q36) | S36: =IF(E36=0,"***",L36/E36) | T36: =IF(F36=0,"***",M36/F36) | U36: =IF(G36=0,"***",N36/G36) | V36: =IF(H36=0,"***",O36/H36) | W36: =IF(I36=0,"***",P36/I36) | X36: =IF(J36=0,"***",Q36/J36) | Y36: =IF(K36=0,"***",R36/K36)
C37: 0911 集計 | D37: 川邊主任 | E37: =(E23+E9)/2 | F37: =(F23+F9)/2 | G37: =(G23+G9)/2 | H37: =(H23+H9)/2 | I37: =(I23+I9)/2 | J37: =(J23+J9)/2 | K37: =SUM(E37:J37) | L37: =(L23+L9)/2 | M37: =(M23+M9)/2 | N37: =(N23+N9)/2 | O37: =(O23+O9)/2 | P37: =(P23+P9)/2 | Q37: =(Q23+Q9)/2 | R37: =SUM(L37:Q37) | S37: =IF(E37=0,"***",L37/E37) | T37: =IF(F37=0,"***",M37/F37) | U37: =IF(G37=0,"***",N37/G37) | V37: =IF(H37=0,"***",O37/H37) | W37: =IF(I37=0,"***",P37/I37) | X37: =IF(J37=0,"***",Q37/J37) | Y37: =IF(K37=0,"***",R37/K37)
C38: 0914 集計 | D38: 白根主任 | E38: =(E24+E10)/2 | F38: =(F24+F10)/2 | G38: =(G24+G10)/2 | H38: =(H24+H10)/2 | I38: =(I24+I10)/2 | J38: =(J24+J10)/2 | K38: =SUM(E38:J38) | L38: =(L24+L10)/2 | M38: =(M24+M10)/2 | N38: =(N24+N10)/2 | O38: =(O24+O10)/2 | P38: =(P24+P10)/2 | Q38: =(Q24+Q10)/2 | R38: =SUM(L38:Q38) | S38: =IF(E38=0,"***",L38/E38) | T38: =IF(F38=0,"***",M38/F38) | U38: =IF(G38=0,"***",N38/G38) | V38: =IF(H38=0,"***",O38/H38) | W38: =IF(I38=0,"***",P38/I38) | X38: =IF(J38=0,"***",Q38/J38) | Y38: =IF(K38=0,"***",R38/K38)
C39: 0918 集計 | D39: 海外 | E39: =(E25+E11)/2 | F39: =(F25+F11)/2 | G39: =(G25+G11)/2 | H39: =(H25+H11)/2 | I39: =(I25+I11)/2 | J39: =(J25+J11)/2 | K39: =SUM(E39:J39) | L39: =(L25+L11)/2 | M39: =(M25+M11)/2 | N39: =(N25+N11)/2 | O39: =(O25+O11)/2 | P39: =(P25+P11)/2 | Q39: =(Q25+Q11)/2 | R39: =SUM(L39:Q39) | S39: =IF(E39=0,"***",L39/E39) | T39: =IF(F39=0,"***",M39/F39) | U39: =IF(G39=0,"***",N39/G39) | V39: =IF(H39=0,"***",O39/H39) | W39: =IF(I39=0,"***",P39/I39) | X39: =IF(J39=0,"***",Q39/J39) | Y39: =IF(K39=0,"***",R39/K39)
C40: 0919 集計 | D40: その他 | E40: =(E26+E12)/2 | F40: =(F26+F12)/2 | G40: =(G26+G12)/2 | H40: =(H26+H12)/2 | I40: =(I26+I12)/2 | J40: =(J26+J12)/2 | K40: =SUM(E40:J40) | L40: =(L26+L12)/2 | M40: =(M26+M12)/2 | N40: =(N26+N12)/2 | O40: =(O26+O12)/2 | P40: =(P26+P12)/2 | Q40: =(Q26+Q12)/2 | R40: =SUM(L40:Q40) | S40: =IF(E40=0,"***",L40/E40) | T40: =IF(F40=0,"***",M40/F40) | U40: =IF(G40=0,"***",N40/G40) | V40: =IF(H40=0,"***",O40/H40) | W40: =IF(I40=0,"***",P40/I40) | X40: =IF(J40=0,"***",Q40/J40) | Y40: =IF(K40=0,"***",R40/K40)
C41: 0930 集計 | D41: 自治体 | E41: =(E27+E13)/2 | F41: =(F27+F13)/2 | G41: =(G27+G13)/2 | H41: =(H27+H13)/2 | I41: =(I27+I13)/2 | J41: =(J27+J13)/2 | K41: =SUM(E41:J41) | L41: =(L27+L13)/2 | M41: =(M27+M13)/2 | N41: =(N27+N13)/2 | O41: =(O27+O13)/2 | P41: =(P27+P13)/2 | Q41: =(Q27+Q13)/2 | R41: =SUM(L41:Q41) | S41: =IF(E41=0,"***",L41/E41) | T41: =IF(F41=0,"***",M41/F41) | U41: =IF(G41=0,"***",N41/G41) | V41: =IF(H41=0,"***",O41/H41) | W41: =IF(I41=0,"***",P41/I41) | X41: =IF(J41=0,"***",Q41/J41) | Y41: =IF(K41=0,"***",R41/K41)
C42: 合計 | E42: =SUM(E33:E41) | F42: =SUM(F33:F41) | G42: =SUM(G33:G41) | H42: =SUM(H33:H41) | I42: =SUM(I33:I41) | J42: =SUM(J33:J41) | K42: =SUM(K33:K41) | L42: =SUM(L33:L41) | ... R42: =SUM(R33:R41) | S42: =IF(E42=0,"***",L42/E42) | T42: =IF(F42=0,"***",M42/F42) | U42: =IF(G42=0,"***",N42/G42) | V42: =IF(H42=0,"***",O42/H42) | W42: =IF(I42=0,"***",P42/I42) | X42: =IF(J42=0,"***",Q42/J42) | Y42: =IF(K42=0,"***",R42/K42)
C44: 4．計画
E45: 売上 | L45: 粗利益 | S45: 粗利益率
E46: 46113 | F46: 46143 | G46: 46174 | H46: 46204 | I46: 46235 | J46: 46266 | K46: 合計 | L46: 46113 | M46: 46143 | N46: 46174 | O46: 46204 | P46: 46235 | Q46: 46266 | R46: 合計 | S46: 46113 | T46: 46143 | U46: 46174 | V46: 46204 | W46: 46235 | X46: 46266 | Y46: 合計
C47: 0903 集計 | D47: 西岡 | E47: 2500 | F47: 1900 | G47: 2500 | H47: =1400+ROUND([1]包装資材6月まで計画!H47,-1) | I47: =1200+ROUND([1]包装資材6月まで計画!I47,-1) | J47: =2600+ROUND([1]包装資材6月まで計画!J47,-1) | K47: =SUM(E47:J47) | L47: 550 | M47: 410 | N47: 480 | O47: =320++ROUND([1]包装資材6月まで計画!O47,-1) | P47: =260+ROUND([1]包装資材6月まで計画!P47,-1) | Q47: =520++ROUND([1]包装資材6月まで計画!Q47,-1) | R47: =SUM(L47:Q47) | S47: =IF(E47=0,"***",L47/E47) | T47: =IF(F47=0,"***",M47/F47) | U47: =IF(G47=0,"***",N47/G47) | V47: =IF(H47=0,"***",O47/H47) | W47: =IF(I47=0,"***",P47/I47) | X47: =IF(J47=0,"***",Q47/J47) | Y47: =IF(K47=0,"***",R47/K47)
C48: 0904 集計 | D48: 足立次長 | E48: 12500 | F48: 12500 | G48: 8250 | H48: 13000 | I48: 13000 | J48: 11300 | K48: =SUM(E48:J48) | L48: 2720 | M48: 2740 | N48: 1880 | O48: 2520 | P48: 2480 | Q48: 2200 | R48: =SUM(L48:Q48) | S48: =IF(E48=0,"***",L48/E48) | T48: =IF(F48=0,"***",M48/F48) | U48: =IF(G48=0,"***",N48/G48) | V48: =IF(H48=0,"***",O48/H48) | W48: =IF(I48=0,"***",P48/I48) | X48: =IF(J48=0,"***",Q48/J48) | Y48: =IF(K48=0,"***",R48/K48)
C49: 0909 集計 | D49: 藤波課長 | E49: 8400 | F49: 5540 | G49: 6330 | H49: =8400+ROUND([1]包装資材6月まで計画!H49,-1) | I49: =6980+ROUND([1]包装資材6月まで計画!I49,-1) | J49: =10850+ROUND([1]包装資材6月まで計画!J49,-1) | K49: =SUM(E49:J49) | L49: 1450 | M49: 1150 | N49: 1200 | O49: =1510+ROUND([1]包装資材6月まで計画!O49,-1) | P49: =1260+ROUND([1]包装資材6月まで計画!P49,-1) | Q49: =1980+ROUND([1]包装資材6月まで計画!Q49,-1) | R49: =SUM(L49:Q49) | S49: =IF(E49=0,"***",L49/E49) | T49: =IF(F49=0,"***",M49/F49) | U49: =IF(G49=0,"***",N49/G49) | V49: =IF(H49=0,"***",O49/H49) | W49: =IF(I49=0,"***",P49/I49) | X49: =IF(J49=0,"***",Q49/J49) | Y49: =IF(K49=0,"***",R49/K49)
C50: 0910 集計 | D50: 足立課長 | E50: 4000 | F50: 3480 | G50: 3320 | K50: =SUM(E50:J50) | L50: 580 | M50: 480 | N50: 470 | R50: =SUM(L50:Q50) | S50: =IF(E50=0,"***",L50/E50) | T50: =IF(F50=0,"***",M50/F50) | U50: =IF(G50=0,"***",N50/G50) | V50: =IF(H50=0,"***",O50/H50) | W50: =IF(I50=0,"***",P50/I50) | X50: =IF(J50=0,"***",Q50/J50) | Y50: =IF(K50=0,"***",R50/K50)
C51: 0911 集計 | D51: 川邊主任 | E51: 11000 | F51: 10000 | G51: 7760 | H51: 10000 | I51: 7300 | J51: 10000 | K51: =SUM(E51:J51) | L51: 1900 | M51: 1730 | N51: 1380 | O51: 1800 | P51: 1300 | Q51: 1700 | R51: =SUM(L51:Q51) | S51: =IF(E51=0,"***",L51/E51) | T51: =IF(F51=0,"***",M51/F51) | U51: =IF(G51=0,"***",N51/G51) | V51: =IF(H51=0,"***",O51/H51) | W51: =IF(I51=0,"***",P51/I51) | X51: =IF(J51=0,"***",Q51/J51) | Y51: =IF(K51=0,"***",R51/K51)
C52: 0914 集計 | D52: 白根主任 | E52: 8700 | F52: 9500 | G52: 7500 | H52: 12000 | I52: 8500 | J52: 24500 | K52: =SUM(E52:J52) | L52: 1600 | M52: 1850 | N52: 1480 | O52: 2880 | P52: 1730 | Q52: 6000 | R52: =SUM(L52:Q52) | S52: =IF(E52=0,"***",L52/E52) | T52: =IF(F52=0,"***",M52/F52) | U52: =IF(G52=0,"***",N52/G52) | V52: =IF(H52=0,"***",O52/H52) | W52: =IF(I52=0,"***",P52/I52) | X52: =IF(J52=0,"***",Q52/J52) | Y52: =IF(K52=0,"***",R52/K52)
C53: 0918 集計 | D53: 海外 | E53: 830 | F53: 1600 | G53: 460 | H53: 990 | I53: 130 | J53: 2200 | K53: =SUM(E53:J53) | L53: 180 | M53: 350 | N53: 110 | O53: 150 | P53: 20 | Q53: 350 | R53: =SUM(L53:Q53) | S53: =IF(E53=0,"***",L53/E53) | T53: =IF(F53=0,"***",M53/F53) | U53: =IF(G53=0,"***",N53/G53) | V53: =IF(H53=0,"***",O53/H53) | W53: =IF(I53=0,"***",P53/I53) | X53: =IF(J53=0,"***",Q53/J53) | Y53: =IF(K53=0,"***",R53/K53)
C54: 0919 集計 | D54: その他 | E54: 30 | F54: 30 | G54: 30 | H54: 30 | I54: 30 | J54: 30 | K54: =SUM(E54:J54) | L54: 10 | M54: 10 | N54: 10 | O54: 10 | P54: 10 | Q54: 10 | R54: =SUM(L54:Q54) | S54: =IF(E54=0,"***",L54/E54) | T54: =IF(F54=0,"***",M54/F54) | U54: =IF(G54=0,"***",N54/G54) | V54: =IF(H54=0,"***",O54/H54) | W54: =IF(I54=0,"***",P54/I54) | X54: =IF(J54=0,"***",Q54/J54) | Y54: =IF(K54=0,"***",R54/K54)
C55: 0930 集計 | D55: 自治体 | E55: 0 | F55: 0 | G55: 0 | H55: 0 | I55: 0 | J55: 0 | K55: =SUM(E55:J55) | L55: 0 | M55: 0 | N55: 0 | O55: 0 | P55: 0 | Q55: 0 | R55: =SUM(L55:Q55)
C56: 合計 | E56: =SUM(E47:E55) | F56: =SUM(F47:F55) | G56: =SUM(G47:G55) | H56: =SUM(H47:H55) | I56: =SUM(I47:I55) | J56: =SUM(J47:J55) | K56: =SUM(K47:K55) | L56: =SUM(L47:L55) | ... R56: =SUM(R47:R55) | S56: =IF(E56=0,"***",L56/E56) | T56: =IF(F56=0,"***",M56/F56) | U56: =IF(G56=0,"***",N56/G56) | V56: =IF(H56=0,"***",O56/H56) | W56: =IF(I56=0,"***",P56/I56) | X56: =IF(J56=0,"***",Q56/J56) | Y56: =IF(K56=0,"***",R56/K56)
C58: ５．前期比
E59: 売上 | L59: 粗利益 | S59: 粗利益率
E60: 46113 | F60: 46143 | G60: 46174 | H60: 46204 | I60: 46235 | J60: 46266 | K60: 合計 | L60: 46113 | M60: 46143 | N60: 46174 | O60: 46204 | P60: 46235 | Q60: 46266 | R60: 合計 | S60: 46113 | T60: 46143 | U60: 46174 | V60: 46204 | W60: 46235 | X60: 46266 | Y60: 合計
C61: 0903 集計 | D61: 西岡 | E61: =E47-E19 | F61: =F47-F19 | G61: =G47-G19 | H61: =H47-H19 | I61: =I47-I19 | J61: =J47-J19 | K61: =SUM(E61:J61) | L61: =L47-L19 | M61: =M47-M19 | N61: =N47-N19 | O61: =O47-O19 | P61: =P47-P19 | Q61: =Q47-Q19 | R61: =SUM(L61:Q61) | S61: =S47-S19 | T61: =T47-T19 | U61: =U47-U19 | V61: =V47-V19 | W61: =W47-W19 | X61: =X47-X19 | Y61: =Y47-Y19
C62: 0904 集計 | D62: 足立次長 | E62: =E48-E20 | F62: =F48-F20 | G62: =G48-G20 | H62: =H48-H20 | I62: =I48-I20 | J62: =J48-J20 | K62: =SUM(E62:J62) | L62: =L48-L20 | M62: =M48-M20 | N62: =N48-N20 | O62: =O48-O20 | P62: =P48-P20 | Q62: =Q48-Q20 | R62: =SUM(L62:Q62) | S62: =S48-S20 | T62: =T48-T20 | U62: =U48-U20 | V62: =V48-V20 | W62: =W48-W20 | X62: =X48-X20 | Y62: =Y48-Y20
C63: 0909 集計 | D63: 藤波課長 | E63: =E49-E21 | F63: =F49-F21 | G63: =G49-G21 | H63: =H49-H21 | I63: =I49-I21 | J63: =J49-J21 | K63: =SUM(E63:J63) | L63: =L49-L21 | M63: =M49-M21 | N63: =N49-N21 | O63: =O49-O21 | P63: =P49-P21 | Q63: =Q49-Q21 | R63: =SUM(L63:Q63) | S63: =S49-S21 | T63: =T49-T21 | U63: =U49-U21 | V63: =V49-V21 | W63: =W49-W21 | X63: =X49-X21 | Y63: =Y49-Y21
C64: 0910 集計 | D64: 足立課長 | E64: =E50-E22 | F64: =F50-F22 | G64: =G50-G22 | H64: =H50-H22 | I64: =I50-I22 | J64: =J50-J22 | K64: =SUM(E64:J64) | L64: =L50-L22 | M64: =M50-M22 | N64: =N50-N22 | O64: =O50-O22 | P64: =P50-P22 | Q64: =Q50-Q22 | R64: =SUM(L64:Q64) | S64: =S50-S22 | T64: =T50-T22 | U64: =U50-U22 | V64: =V50-V22 | W64: =W50-W22 | X64: =X50-X22 | Y64: =Y50-Y22
C65: 0911 集計 | D65: 川邊主任 | E65: =E51-E23 | F65: =F51-F23 | G65: =G51-G23 | H65: =H51-H23 | I65: =I51-I23 | J65: =J51-J23 | K65: =SUM(E65:J65) | L65: =L51-L23 | M65: =M51-M23 | N65: =N51-N23 | O65: =O51-O23 | P65: =P51-P23 | Q65: =Q51-Q23 | R65: =SUM(L65:Q65) | S65: =S51-S23 | T65: =T51-T23 | U65: =U51-U23 | V65: =V51-V23 | W65: =W51-W23 | X65: =X51-X23 | Y65: =Y51-Y23
C66: 0914 集計 | D66: 白根主任 | E66: =E52-E24 | F66: =F52-F24 | G66: =G52-G24 | H66: =H52-H24 | I66: =I52-I24 | J66: =J52-J24 | K66: =SUM(E66:J66) | L66: =L52-L24 | M66: =M52-M24 | N66: =N52-N24 | O66: =O52-O24 | P66: =P52-P24 | Q66: =Q52-Q24 | R66: =SUM(L66:Q66) | S66: =S52-S24 | T66: =T52-T24 | U66: =U52-U24 | V66: =V52-V24 | W66: =W52-W24 | X66: =X52-X24 | Y66: =Y52-Y24
C67: 0918 集計 | D67: 海外 | E67: =E53-E25 | F67: =F53-F25 | G67: =G53-G25 | H67: =H53-H25 | I67: =I53-I25 | J67: =J53-J25 | K67: =SUM(E67:J67) | L67: =L53-L25 | M67: =M53-M25 | N67: =N53-N25 | O67: =O53-O25 | P67: =P53-P25 | Q67: =Q53-Q25 | R67: =SUM(L67:Q67) | S67: =S53-S25 | T67: =T53-T25 | U67: =U53-U25 | V67: =V53-V25 | W67: =W53-W25 | X67: =X53-X25 | Y67: =Y53-Y25
C68: 0919 集計 | D68: その他 | E68: =E54-E26 | F68: =F54-F26 | G68: =G54-G26 | H68: =H54-H26 | I68: =I54-I26 | J68: =J54-J26 | K68: =SUM(E68:J68) | L68: =L54-L26 | M68: =M54-M26 | N68: =N54-N26 | O68: =O54-O26 | P68: =P54-P26 | Q68: =Q54-Q26 | R68: =SUM(L68:Q68) | S68: =S54-S26 | T68: =T54-T26 | U68: =U54-U26 | V68: =V54-V26 | W68: =W54-W26 | X68: =X54-X26 | Y68: =Y54-Y26
C69: 0930 集計 | D69: 自治体 | E69: =E55-E27 | F69: =F55-F27 | G69: =G55-G27 | H69: =H55-H27 | I69: =I55-I27 | J69: =J55-J27 | K69: =SUM(E69:J69) | L69: =L55-L27 | M69: =M55-M27 | N69: =N55-N27 | O69: =O55-O27 | P69: =P55-P27 | Q69: =Q55-Q27 | R69: =SUM(L69:Q69) | S69: =S55-S27 | T69: =T55-T27 | U69: =U55-U27 | V69: =V55-V27 | W69: =W55-W27 | X69: =X55-X27 | Y69: =Y55-Y27
C70: 合計 | E70: =SUM(E61:E69) | F70: =SUM(F61:F69) | G70: =SUM(G61:G69) | H70: =SUM(H61:H69) | I70: =SUM(I61:I69) | J70: =SUM(J61:J69) | K70: =SUM(K61:K69) | L70: =SUM(L61:L69) | ... R70: =SUM(R61:R69) | S70: =S56-S28 | T70: =T56-T28 | U70: =U56-U28 | V70: =V56-V28 | W70: =W56-W28 | X70: =X56-X28 | Y70: =Y56-Y28
C72: 6．過年度平均比
E73: 売上 | L73: 粗利益 | S73: 粗利益率
E74: 46113 | F74: 46143 | G74: 46174 | H74: 46204 | I74: 46235 | J74: 46266 | K74: 合計 | L74: 46113 | M74: 46143 | N74: 46174 | O74: 46204 | P74: 46235 | Q74: 46266 | R74: 合計 | S74: 46113 | T74: 46143 | U74: 46174 | V74: 46204 | W74: 46235 | X74: 46266 | Y74: 合計
C75: 0903 集計 | D75: 西岡 | E75: =E47-E33 | F75: =F47-F33 | G75: =G47-G33 | H75: =H47-H33 | I75: =I47-I33 | J75: =J47-J33 | K75: =SUM(E75:J75) | L75: =L47-L33 | M75: =M47-M33 | N75: =N47-N33 | O75: =O47-O33 | P75: =P47-P33 | Q75: =Q47-Q33 | R75: =SUM(L75:Q75) | S75: =IF(E75=0,"***",L75/E75) | T75: =IF(F75=0,"***",M75/F75) | U75: =IF(G75=0,"***",N75/G75) | V75: =IF(H75=0,"***",O75/H75) | W75: =IF(I75=0,"***",P75/I75) | X75: =IF(J75=0,"***",Q75/J75) | Y75: =IF(K75=0,"***",R75/K75)
C76: 0904 集計 | D76: 足立次長 | E76: =E48-E34 | F76: =F48-F34 | G76: =G48-G34 | H76: =H48-H34 | I76: =I48-I34 | J76: =J48-J34 | K76: =SUM(E76:J76) | L76: =L48-L34 | M76: =M48-M34 | N76: =N48-N34 | O76: =O48-O34 | P76: =P48-P34 | Q76: =Q48-Q34 | R76: =SUM(L76:Q76) | S76: =IF(E76=0,"***",L76/E76) | T76: =IF(F76=0,"***",M76/F76) | U76: =IF(G76=0,"***",N76/G76) | V76: =IF(H76=0,"***",O76/H76) | W76: =IF(I76=0,"***",P76/I76) | X76: =IF(J76=0,"***",Q76/J76) | Y76: =IF(K76=0,"***",R76/K76)
C77: 0909 集計 | D77: 藤波課長 | E77: =E49-E35 | F77: =F49-F35 | G77: =G49-G35 | H77: =H49-H35 | I77: =I49-I35 | J77: =J49-J35 | K77: =SUM(E77:J77) | L77: =L49-L35 | M77: =M49-M35 | N77: =N49-N35 | O77: =O49-O35 | P77: =P49-P35 | Q77: =Q49-Q35 | R77: =SUM(L77:Q77) | S77: =IF(E77=0,"***",L77/E77) | T77: =IF(F77=0,"***",M77/F77) | U77: =IF(G77=0,"***",N77/G77) | V77: =IF(H77=0,"***",O77/H77) | W77: =IF(I77=0,"***",P77/I77) | X77: =IF(J77=0,"***",Q77/J77) | Y77: =IF(K77=0,"***",R77/K77)
C78: 0910 集計 | D78: 足立課長 | E78: =E50-E36 | F78: =F50-F36 | G78: =G50-G36 | H78: =H50-H36 | I78: =I50-I36 | J78: =J50-J36 | K78: =SUM(E78:J78) | L78: =L50-L36 | M78: =M50-M36 | N78: =N50-N36 | O78: =O50-O36 | P78: =P50-P36 | Q78: =Q50-Q36 | R78: =SUM(L78:Q78) | S78: =IF(E78=0,"***",L78/E78) | T78: =IF(F78=0,"***",M78/F78) | U78: =IF(G78=0,"***",N78/G78) | V78: =IF(H78=0,"***",O78/H78) | W78: =IF(I78=0,"***",P78/I78) | X78: =IF(J78=0,"***",Q78/J78) | Y78: =IF(K78=0,"***",R78/K78)
C79: 0911 集計 | D79: 川邊主任 | E79: =E51-E37 | F79: =F51-F37 | G79: =G51-G37 | H79: =H51-H37 | I79: =I51-I37 | J79: =J51-J37 | K79: =SUM(E79:J79) | L79: =L51-L37 | M79: =M51-M37 | N79: =N51-N37 | O79: =O51-O37 | P79: =P51-P37 | Q79: =Q51-Q37 | R79: =SUM(L79:Q79) | S79: =IF(E79=0,"***",L79/E79) | T79: =IF(F79=0,"***",M79/F79) | U79: =IF(G79=0,"***",N79/G79) | V79: =IF(H79=0,"***",O79/H79) | W79: =IF(I79=0,"***",P79/I79) | X79: =IF(J79=0,"***",Q79/J79) | Y79: =IF(K79=0,"***",R79/K79)
C80: 0914 集計 | D80: 白根主任 | E80: =E52-E38 | F80: =F52-F38 | G80: =G52-G38 | H80: =H52-H38 | I80: =I52-I38 | J80: =J52-J38 | K80: =SUM(E80:J80) | L80: =L52-L38 | M80: =M52-M38 | N80: =N52-N38 | O80: =O52-O38 | P80: =P52-P38 | Q80: =Q52-Q38 | R80: =SUM(L80:Q80) | S80: =IF(E80=0,"***",L80/E80) | T80: =IF(F80=0,"***",M80/F80) | U80: =IF(G80=0,"***",N80/G80) | V80: =IF(H80=0,"***",O80/H80) | W80: =IF(I80=0,"***",P80/I80) | X80: =IF(J80=0,"***",Q80/J80) | Y80: =IF(K80=0,"***",R80/K80)
C81: 0918 集計 | D81: 海外 | E81: =E53-E39 | F81: =F53-F39 | G81: =G53-G39 | H81: =H53-H39 | I81: =I53-I39 | J81: =J53-J39 | K81: =SUM(E81:J81) | L81: =L53-L39 | M81: =M53-M39 | N81: =N53-N39 | O81: =O53-O39 | P81: =P53-P39 | Q81: =Q53-Q39 | R81: =SUM(L81:Q81) | S81: =IF(E81=0,"***",L81/E81) | T81: =IF(F81=0,"***",M81/F81) | U81: =IF(G81=0,"***",N81/G81) | V81: =IF(H81=0,"***",O81/H81) | W81: =IF(I81=0,"***",P81/I81) | X81: =IF(J81=0,"***",Q81/J81) | Y81: =IF(K81=0,"***",R81/K81)
C82: 0919 集計 | D82: その他 | E82: =E54-E40 | F82: =F54-F40 | G82: =G54-G40 | H82: =H54-H40 | I82: =I54-I40 | J82: =J54-J40 | K82: =SUM(E82:J82) | L82: =L54-L40 | M82: =M54-M40 | N82: =N54-N40 | O82: =O54-O40 | P82: =P54-P40 | Q82: =Q54-Q40 | R82: =SUM(L82:Q82) | S82: =IF(E82=0,"***",L82/E82) | T82: =IF(F82=0,"***",M82/F82) | U82: =IF(G82=0,"***",N82/G82) | V82: =IF(H82=0,"***",O82/H82) | W82: =IF(I82=0,"***",P82/I82) | X82: =IF(J82=0,"***",Q82/J82) | Y82: =IF(K82=0,"***",R82/K82)
C83: 0930 集計 | D83: 自治体 | E83: =E55-E41 | F83: =F55-F41 | G83: =G55-G41 | H83: =H55-H41 | I83: =I55-I41 | J83: =J55-J41 | K83: =SUM(E83:J83) | L83: =L55-L41 | M83: =M55-M41 | N83: =N55-N41 | O83: =O55-O41 | P83: =P55-P41 | Q83: =Q55-Q41 | R83: =SUM(L83:Q83) | S83: =IF(E83=0,"***",L83/E83) | T83: =IF(F83=0,"***",M83/F83) | U83: =IF(G83=0,"***",N83/G83) | V83: =IF(H83=0,"***",O83/H83) | W83: =IF(I83=0,"***",P83/I83) | X83: =IF(J83=0,"***",Q83/J83) | Y83: =IF(K83=0,"***",R83/K83)
C84: 合計 | E84: =SUM(E75:E83) | F84: =SUM(F75:F83) | G84: =SUM(G75:G83) | H84: =SUM(H75:H83) | I84: =SUM(I75:I83) | J84: =SUM(J75:J83) | K84: =SUM(K75:K83) | L84: =SUM(L75:L83) | ... R84: =SUM(R75:R83) | S84: =IF(E84=0,"***",L84/E84) | T84: =IF(F84=0,"***",M84/F84) | U84: =IF(G84=0,"***",N84/G84) | V84: =IF(H84=0,"***",O84/H84) | W84: =IF(I84=0,"***",P84/I84) | X84: =IF(J84=0,"***",Q84/J84) | Y84: =IF(K84=0,"***",R84/K84)
C86: 7．実績
E87: 売上 | L87: 粗利益 | S87: 粗利益率
E88: 46113 | F88: 46143 | G88: 46174 | H88: 46204 | I88: 46235 | J88: 46266 | K88: 合計 | L88: 46113 | M88: 46143 | N88: 46174 | O88: 46204 | P88: 46235 | Q88: 46266 | R88: 合計 | S88: 46113 | T88: 46143 | U88: 46174 | V88: 46204 | W88: 46235 | X88: 46266 | Y88: 合計
C89: 0903 集計 | D89: 西岡 | E89: =全体!E89-機械!E89 | F89: =全体!F89-機械!F89 | G89: =全体!G89-機械!G89 | H89: =全体!H89-機械!H89 | I89: =全体!I89-機械!I89 | J89: =全体!J89-機械!J89 | K89: =SUM(E89:J89) | L89: =全体!L89-機械!L89 | M89: =全体!M89-機械!M89 | N89: =全体!N89-機械!N89 | O89: =全体!O89-機械!O89 | P89: =全体!P89-機械!P89 | Q89: =全体!Q89-機械!Q89 | R89: =SUM(L89:Q89) | S89: =IF(E89=0,"***",L89/E89) | T89: =IF(F89=0,"***",M89/F89) | U89: =IF(G89=0,"***",N89/G89) | V89: =IF(H89=0,"***",O89/H89) | W89: =IF(I89=0,"***",P89/I89) | X89: =IF(J89=0,"***",Q89/J89) | Y89: =IF(K89=0,"***",R89/K89)
C90: 0904 集計 | D90: 足立次長 | E90: =全体!E90-機械!E90 | F90: =全体!F90-機械!F90 | G90: =全体!G90-機械!G90 | H90: =全体!H90-機械!H90 | I90: =全体!I90-機械!I90 | J90: =全体!J90-機械!J90 | K90: =SUM(E90:J90) | L90: =全体!L90-機械!L90 | M90: =全体!M90-機械!M90 | N90: =全体!N90-機械!N90 | O90: =全体!O90-機械!O90 | P90: =全体!P90-機械!P90 | Q90: =全体!Q90-機械!Q90 | R90: =SUM(L90:Q90) | S90: =IF(E90=0,"***",L90/E90) | T90: =IF(F90=0,"***",M90/F90) | U90: =IF(G90=0,"***",N90/G90) | V90: =IF(H90=0,"***",O90/H90) | W90: =IF(I90=0,"***",P90/I90) | X90: =IF(J90=0,"***",Q90/J90) | Y90: =IF(K90=0,"***",R90/K90)
C91: 0909 集計 | D91: 藤波課長 | E91: =全体!E91-機械!E91 | F91: =全体!F91-機械!F91 | G91: =全体!G91-機械!G91 | H91: =全体!H91-機械!H91 | I91: =全体!I91-機械!I91 | J91: =全体!J91-機械!J91 | K91: =SUM(E91:J91) | L91: =全体!L91-機械!L91 | M91: =全体!M91-機械!M91 | N91: =全体!N91-機械!N91 | O91: =全体!O91-機械!O91 | P91: =全体!P91-機械!P91 | Q91: =全体!Q91-機械!Q91 | R91: =SUM(L91:Q91) | S91: =IF(E91=0,"***",L91/E91) | T91: =IF(F91=0,"***",M91/F91) | U91: =IF(G91=0,"***",N91/G91) | V91: =IF(H91=0,"***",O91/H91) | W91: =IF(I91=0,"***",P91/I91) | X91: =IF(J91=0,"***",Q91/J91) | Y91: =IF(K91=0,"***",R91/K91)
C92: 0910 集計 | D92: 足立課長 | E92: =全体!E92-機械!E92 | F92: =全体!F92-機械!F92 | G92: =全体!G92-機械!G92 | H92: =全体!H92-機械!H92 | I92: =全体!I92-機械!I92 | J92: =全体!J92-機械!J92 | K92: =SUM(E92:J92) | L92: =全体!L92-機械!L92 | M92: =全体!M92-機械!M92 | N92: =全体!N92-機械!N92 | O92: =全体!O92-機械!O92 | P92: =全体!P92-機械!P92 | Q92: =全体!Q92-機械!Q92 | R92: =SUM(L92:Q92) | S92: =IF(E92=0,"***",L92/E92) | T92: =IF(F92=0,"***",M92/F92) | U92: =IF(G92=0,"***",N92/G92) | V92: =IF(H92=0,"***",O92/H92) | W92: =IF(I92=0,"***",P92/I92) | X92: =IF(J92=0,"***",Q92/J92) | Y92: =IF(K92=0,"***",R92/K92)
C93: 0911 集計 | D93: 川邊主任 | E93: =全体!E93-機械!E93 | F93: =全体!F93-機械!F93 | G93: =全体!G93-機械!G93 | H93: =全体!H93-機械!H93 | I93: =全体!I93-機械!I93 | J93: =全体!J93-機械!J93 | K93: =SUM(E93:J93) | L93: =全体!L93-機械!L93 | M93: =全体!M93-機械!M93 | N93: =全体!N93-機械!N93 | O93: =全体!O93-機械!O93 | P93: =全体!P93-機械!P93 | Q93: =全体!Q93-機械!Q93 | R93: =SUM(L93:Q93) | S93: =IF(E93=0,"***",L93/E93) | T93: =IF(F93=0,"***",M93/F93) | U93: =IF(G93=0,"***",N93/G93) | V93: =IF(H93=0,"***",O93/H93) | W93: =IF(I93=0,"***",P93/I93) | X93: =IF(J93=0,"***",Q93/J93) | Y93: =IF(K93=0,"***",R93/K93)
C94: 0914 集計 | D94: 白根主任 | E94: =全体!E94-機械!E94 | F94: =全体!F94-機械!F94 | G94: =全体!G94-機械!G94 | H94: =全体!H94-機械!H94 | I94: =全体!I94-機械!I94 | J94: =全体!J94-機械!J94 | K94: =SUM(E94:J94) | L94: =全体!L94-機械!L94 | M94: =全体!M94-機械!M94 | N94: =全体!N94-機械!N94 | O94: =全体!O94-機械!O94 | P94: =全体!P94-機械!P94 | Q94: =全体!Q94-機械!Q94 | R94: =SUM(L94:Q94) | S94: =IF(E94=0,"***",L94/E94) | T94: =IF(F94=0,"***",M94/F94) | U94: =IF(G94=0,"***",N94/G94) | V94: =IF(H94=0,"***",O94/H94) | W94: =IF(I94=0,"***",P94/I94) | X94: =IF(J94=0,"***",Q94/J94) | Y94: =IF(K94=0,"***",R94/K94)
C95: 0918 集計 | D95: 海外 | E95: =全体!E95-機械!E95 | F95: =全体!F95-機械!F95 | G95: =全体!G95-機械!G95 | H95: =全体!H95-機械!H95 | I95: =全体!I95-機械!I95 | J95: =全体!J95-機械!J95 | K95: =SUM(E95:J95) | L95: =全体!L95-機械!L95 | M95: =全体!M95-機械!M95 | N95: =全体!N95-機械!N95 | O95: =全体!O95-機械!O95 | P95: =全体!P95-機械!P95 | Q95: =全体!Q95-機械!Q95 | R95: =SUM(L95:Q95) | S95: =IF(E95=0,"***",L95/E95) | T95: =IF(F95=0,"***",M95/F95) | U95: =IF(G95=0,"***",N95/G95) | V95: =IF(H95=0,"***",O95/H95) | W95: =IF(I95=0,"***",P95/I95) | X95: =IF(J95=0,"***",Q95/J95) | Y95: =IF(K95=0,"***",R95/K95)
C96: 0919 集計 | D96: その他 | E96: =全体!E96-機械!E96 | F96: =全体!F96-機械!F96 | G96: =全体!G96-機械!G96 | H96: =全体!H96-機械!H96 | I96: =全体!I96-機械!I96 | J96: =全体!J96-機械!J96 | K96: =SUM(E96:J96) | L96: =全体!L96-機械!L96 | M96: =全体!M96-機械!M96 | N96: =全体!N96-機械!N96 | O96: =全体!O96-機械!O96 | P96: =全体!P96-機械!P96 | Q96: =全体!Q96-機械!Q96 | R96: =SUM(L96:Q96) | S96: =IF(E96=0,"***",L96/E96) | T96: =IF(F96=0,"***",M96/F96) | U96: =IF(G96=0,"***",N96/G96) | V96: =IF(H96=0,"***",O96/H96) | W96: =IF(I96=0,"***",P96/I96) | X96: =IF(J96=0,"***",Q96/J96) | Y96: =IF(K96=0,"***",R96/K96)
C97: 0930 集計 | D97: 自治体 | E97: =全体!E97-機械!E97 | G97: =全体!G97-機械!G97 | H97: =全体!H97-機械!H97 | I97: =全体!I97-機械!I97 | J97: =全体!J97-機械!J97 | K97: =SUM(E97:J97) | L97: =全体!L97-機械!L97 | N97: =全体!N97-機械!N97 | O97: =全体!O97-機械!O97 | P97: =全体!P97-機械!P97 | Q97: =全体!Q97-機械!Q97 | R97: =SUM(L97:Q97) | S97: =IF(E97=0,"***",L97/E97) | T97: =IF(F97=0,"***",M97/F97) | U97: =IF(G97=0,"***",N97/G97) | V97: =IF(H97=0,"***",O97/H97) | W97: =IF(I97=0,"***",P97/I97) | X97: =IF(J97=0,"***",Q97/J97) | Y97: =IF(K97=0,"***",R97/K97)
C98: 合計 | E98: =SUM(E89:E97) | F98: =SUM(F89:F97) | G98: =SUM(G89:G97) | H98: =SUM(H89:H97) | I98: =SUM(I89:I97) | J98: =SUM(J89:J97) | K98: =SUM(K89:K97) | L98: =SUM(L89:L97) | ... R98: =SUM(R89:R97) | S98: =IF(E98=0,"***",L98/E98) | T98: =IF(F98=0,"***",M98/F98) | U98: =IF(G98=0,"***",N98/G98) | V98: =IF(H98=0,"***",O98/H98) | W98: =IF(I98=0,"***",P98/I98) | X98: =IF(J98=0,"***",Q98/J98) | Y98: =IF(K98=0,"***",R98/K98)
C100: 8．計画比
E101: 売上 | L101: 粗利益 | S101: 粗利益率
E102: 46113 | F102: 46143 | G102: 46174 | H102: 46204 | I102: 46235 | J102: 46266 | K102: 合計 | L102: 46113 | M102: 46143 | N102: 46174 | O102: 46204 | P102: 46235 | Q102: 46266 | R102: 合計 | S102: 46113 | T102: 46143 | U102: 46174 | V102: 46204 | W102: 46235 | X102: 46266 | Y102: 合計
C103: 0903 集計 | D103: 西岡 | E103: =E89-E47 | F103: =F89-F47 | G103: =G89-G47 | H103: =H89-H47 | I103: =I89-I47 | J103: =J89-J47 | K103: =SUM(E103:J103) | L103: =L89-L47 | M103: =M89-M47 | N103: =N89-N47 | O103: =O89-O47 | P103: =P89-P47 | Q103: =Q89-Q47 | R103: =SUM(L103:Q103) | S103: =S89-S47 | T103: =T89-T47 | U103: =U89-U47 | V103: =V89-V47 | W103: =W89-W47 | X103: =X89-X47 | Y103: =Y89-Y47
C104: 0904 集計 | D104: 足立次長 | E104: =E90-E48 | F104: =F90-F48 | G104: =G90-G48 | H104: =H90-H48 | I104: =I90-I48 | J104: =J90-J48 | K104: =SUM(E104:J104) | L104: =L90-L48 | M104: =M90-M48 | N104: =N90-N48 | O104: =O90-O48 | P104: =P90-P48 | Q104: =Q90-Q48 | R104: =SUM(L104:Q104) | S104: =S90-S48 | T104: =T90-T48 | U104: =U90-U48 | V104: =V90-V48 | W104: =W90-W48 | X104: =X90-X48 | Y104: =Y90-Y48
C105: 0909 集計 | D105: 藤波課長 | E105: =E91-E49 | F105: =F91-F49 | G105: =G91-G49 | H105: =H91-H49 | I105: =I91-I49 | J105: =J91-J49 | K105: =SUM(E105:J105) | L105: =L91-L49 | M105: =M91-M49 | N105: =N91-N49 | O105: =O91-O49 | P105: =P91-P49 | Q105: =Q91-Q49 | R105: =SUM(L105:Q105) | S105: =S91-S49 | T105: =T91-T49 | U105: =U91-U49 | V105: =V91-V49 | W105: =W91-W49 | X105: =X91-X49 | Y105: =Y91-Y49
C106: 0910 集計 | D106: 足立課長 | E106: =E92-E50 | F106: =F92-F50 | G106: =G92-G50 | H106: =H92-H50 | I106: =I92-I50 | J106: =J92-J50 | K106: =SUM(E106:J106) | L106: =L92-L50 | M106: =M92-M50 | N106: =N92-N50 | O106: =O92-O50 | P106: =P92-P50 | Q106: =Q92-Q50 | R106: =SUM(L106:Q106) | S106: =S92-S50 | T106: =T92-T50 | U106: =U92-U50 | V106: =V92-V50 | W106: =W92-W50 | X106: =X92-X50 | Y106: =Y92-Y50
C107: 0911 集計 | D107: 川邊主任 | E107: =E93-E51 | F107: =F93-F51 | G107: =G93-G51 | H107: =H93-H51 | I107: =I93-I51 | J107: =J93-J51 | K107: =SUM(E107:J107) | L107: =L93-L51 | M107: =M93-M51 | N107: =N93-N51 | O107: =O93-O51 | P107: =P93-P51 | Q107: =Q93-Q51 | R107: =SUM(L107:Q107) | S107: =S93-S51 | T107: =T93-T51 | U107: =U93-U51 | V107: =V93-V51 | W107: =W93-W51 | X107: =X93-X51 | Y107: =Y93-Y51
...

Sheet 機械
C1: 境港営業所機械
C2: 1．2024年
E3: 売上 | L3: 粗利益 | S3: 粗利益率
E4: 45383 | F4: 45413 | G4: 45444 | H4: 45474 | I4: 45505 | J4: 45536 | K4: 合計 | L4: 45383 | M4: 45413 | N4: 45444 | O4: 45474 | P4: 45505 | Q4: 45536 | R4: 合計 | S4: 45383 | T4: 45413 | U4: 45444 | V4: 45474 | W4: 45505 | X4: 45536 | Y4: 合計
C5: 0903 集計 | D5: 西岡 | E5: 1 | F5: 72 | G5: 56 | H5: =168+76 | I5: =217+11 | J5: 268 | K5: =SUM(E5:J5) | L5: 0 | M5: 13 | N5: 14 | O5: =56+24 | P5: =62+3 | Q5: 98 | R5: =SUM(L5:Q5) | S5: =IF(E5=0,"***",L5/E5) | T5: =IF(F5=0,"***",M5/F5) | U5: =IF(G5=0,"***",N5/G5) | V5: =IF(H5=0,"***",O5/H5) | W5: =IF(I5=0,"***",P5/I5) | X5: =IF(J5=0,"***",Q5/J5) | Y5: =IF(K5=0,"***",R5/K5)
C6: 0904 集計 | D6: 足立次長 | E6: 643 | F6: 26318 | G6: 397 | H6: 472 | I6: 265 | J6: 444 | K6: =SUM(E6:J6) | L6: 105 | M6: 5374 | N6: 81 | O6: 124 | P6: 47 | Q6: 71 | R6: =SUM(L6:Q6) | S6: =IF(E6=0,"***",L6/E6) | T6: =IF(F6=0,"***",M6/F6) | U6: =IF(G6=0,"***",N6/G6) | V6: =IF(H6=0,"***",O6/H6) | W6: =IF(I6=0,"***",P6/I6) | X6: =IF(J6=0,"***",Q6/J6) | Y6: =IF(K6=0,"***",R6/K6)
C7: 0909 集計 | D7: 藤波課長 | E7: 575 | F7: 675 | G7: 193 | H7: =414+70 | I7: =169+58 | J7: 814 | K7: =SUM(E7:J7) | L7: 209 | M7: 193 | N7: 89 | O7: =201+23 | P7: =91+18 | Q7: 223 | R7: =SUM(L7:Q7) | S7: =IF(E7=0,"***",L7/E7) | T7: =IF(F7=0,"***",M7/F7) | U7: =IF(G7=0,"***",N7/G7) | V7: =IF(H7=0,"***",O7/H7) | W7: =IF(I7=0,"***",P7/I7) | X7: =IF(J7=0,"***",Q7/J7) | Y7: =IF(K7=0,"***",R7/K7)
C8: 0910 集計 | D8: 足立課長 | E8: 6691 | F8: 59 | G8: 60 | K8: =SUM(E8:J8) | L8: 1276 | M8: 14 | N8: 16 | R8: =SUM(L8:Q8) | S8: =IF(E8=0,"***",L8/E8) | T8: =IF(F8=0,"***",M8/F8) | U8: =IF(G8=0,"***",N8/G8) | V8: =IF(H8=0,"***",O8/H8) | W8: =IF(I8=0,"***",P8/I8) | X8: =IF(J8=0,"***",Q8/J8) | Y8: =IF(K8=0,"***",R8/K8)
C9: 0911 集計 | D9: 川邊主任 | E9: 393 | F9: 1326 | G9: 753 | H9: 511 | I9: 237 | J9: 389 | K9: =SUM(E9:J9) | L9: 101 | M9: 298 | N9: 166 | O9: 124 | P9: 52 | Q9: 87 | R9: =SUM(L9:Q9) | S9: =IF(E9=0,"***",L9/E9) | T9: =IF(F9=0,"***",M9/F9) | U9: =IF(G9=0,"***",N9/G9) | V9: =IF(H9=0,"***",O9/H9) | W9: =IF(I9=0,"***",P9/I9) | X9: =IF(J9=0,"***",Q9/J9) | Y9: =IF(K9=0,"***",R9/K9)
C10: 0914 集計 | D10: 白根主任 | E10: 978 | F10: 3707 | G10: 2099 | H10: 711 | I10: 326 | J10: 956 | K10: =SUM(E10:J10) | L10: 278 | M10: 384 | N10: 539 | O10: 197 | P10: 89 | Q10: 260 | R10: =SUM(L10:Q10) | S10: =IF(E10=0,"***",L10/E10) | T10: =IF(F10=0,"***",M10/F10) | U10: =IF(G10=0,"***",N10/G10) | V10: =IF(H10=0,"***",O10/H10) | W10: =IF(I10=0,"***",P10/I10) | X10: =IF(J10=0,"***",Q10/J10) | Y10: =IF(K10=0,"***",R10/K10)
C11: 0918 集計 | D11: 海外 | E11: 199 | F11: 2039 | G11: 379 | H11: 108 | I11: 35 | J11: 0 | K11: =SUM(E11:J11) | L11: 56 | M11: 381 | N11: 90 | O11: 27 | P11: 29 | Q11: 0 | R11: =SUM(L11:Q11) | S11: =IF(E11=0,"***",L11/E11) | T11: =IF(F11=0,"***",M11/F11) | U11: =IF(G11=0,"***",N11/G11) | V11: =IF(H11=0,"***",O11/H11) | W11: =IF(I11=0,"***",P11/I11) | X11: =IF(J11=0,"***",Q11/J11) | Y11: =IF(K11=0,"***",R11/K11)
C12: 0919 集計 | D12: その他 | E12: 0 | F12: 0 | G12: 0 | H12: 0 | I12: 0 | J12: 4 | K12: =SUM(E12:J12) | L12: 0 | M12: 0 | N12: 0 | O12: 0 | P12: 0 | Q12: 1 | R12: =SUM(L12:Q12) | S12: =IF(E12=0,"***",L12/E12) | T12: =IF(F12=0,"***",M12/F12) | U12: =IF(G12=0,"***",N12/G12) | V12: =IF(H12=0,"***",O12/H12) | W12: =IF(I12=0,"***",P12/I12) | X12: =IF(J12=0,"***",Q12/J12) | Y12: =IF(K12=0,"***",R12/K12)
C13: 0930 集計 | D13: 自治体 | K13: =SUM(E13:J13) | R13: =SUM(L13:Q13) | S13: =IF(E13=0,"***",L13/E13) | T13: =IF(F13=0,"***",M13/F13) | U13: =IF(G13=0,"***",N13/G13) | V13: =IF(H13=0,"***",O13/H13) | W13: =IF(I13=0,"***",P13/I13) | X13: =IF(J13=0,"***",Q13/J13) | Y13: =IF(K13=0,"***",R13/K13)
C14: 合計 | E14: =SUM(E5:E13) | F14: =SUM(F5:F13) | G14: =SUM(G5:G13) | H14: =SUM(H5:H13) | I14: =SUM(I5:I13) | J14: =SUM(J5:J13) | K14: =SUM(K5:K13) | L14: =SUM(L5:L13) | ... R14: =SUM(R5:R13) | S14: =IF(E14=0,"***",L14/E14) | T14: =IF(F14=0,"***",M14/F14) | U14: =IF(G14=0,"***",N14/G14) | V14: =IF(H14=0,"***",O14/H14) | W14: =IF(I14=0,"***",P14/I14) | X14: =IF(J14=0,"***",Q14/J14) | Y14: =IF(K14=0,"***",R14/K14)
C16: 2．2025年
E17: 売上 | L17: 粗利益 | S17: 粗利益率
E18: 45748 | F18: 45778 | G18: 45809 | H18: 45839 | I18: 45870 | J18: 45901 | K18: 合計 | L18: 45748 | M18: 45778 | N18: 45809 | O18: 45839 | P18: 45870 | Q18: 45901 | R18: 合計 | S18: 45748 | T18: 45778 | U18: 45809 | V18: 45839 | W18: 45870 | X18: 45901 | Y18: 合計
C19: 0903 集計 | D19: 西岡 | E19: 145 | F19: 22 | G19: 250 | H19: =57+130 | I19: =60+8 | J19: =130+5 | K19: =SUM(E19:J19) | L19: 35 | M19: 3 | N19: 127 | O19: =23+27 | P19: =14+0 | Q19: =32+1 | R19: =SUM(L19:Q19) | S19: =IF(E19=0,"***",L19/E19) | T19: =IF(F19=0,"***",M19/F19) | U19: =IF(G19=0,"***",N19/G19) | V19: =IF(H19=0,"***",O19/H19) | W19: =IF(I19=0,"***",P19/I19) | X19: =IF(J19=0,"***",Q19/J19) | Y19: =IF(K19=0,"***",R19/K19)
C20: 0904 集計 | D20: 足立次長 | E20: 625 | F20: 200 | G20: 207 | H20: 1557 | I20: 82542 | J20: 30771 | K20: =SUM(E20:J20) | L20: 106 | M20: 40 | N20: 37 | O20: 296 | P20: 13969 | Q20: 7512 | R20: =SUM(L20:Q20) | S20: =IF(E20=0,"***",L20/E20) | T20: =IF(F20=0,"***",M20/F20) | U20: =IF(G20=0,"***",N20/G20) | V20: =IF(H20=0,"***",O20/H20) | W20: =IF(I20=0,"***",P20/I20) | X20: =IF(J20=0,"***",Q20/J20) | Y20: =IF(K20=0,"***",R20/K20)
C21: 0909 集計 | D21: 藤波課長 | E21: 419 | F21: 740 | G21: 708 | H21: =3107+1124-130 | I21: =434+1804 | J21: =244+132-5 | K21: =SUM(E21:J21) | L21: 172 | M21: 261 | N21: 302 | O21: =945+376-27 | P21: =190+491-0 | Q21: =141+33-1 | R21: =SUM(L21:Q21) | S21: =IF(E21=0,"***",L21/E21) | T21: =IF(F21=0,"***",M21/F21) | U21: =IF(G21=0,"***",N21/G21) | V21: =IF(H21=0,"***",O21/H21) | W21: =IF(I21=0,"***",P21/I21) | X21: =IF(J21=0,"***",Q21/J21) | Y21: =IF(K21=0,"***",R21/K21)
C22: 0910 集計 | D22: 足立課長 | E22: 114 | F22: 87 | G22: 124 | K22: =SUM(E22:J22) | L22: 31 | M22: 31 | N22: 34 | R22: =SUM(L22:Q22) | S22: =IF(E22=0,"***",L22/E22) | T22: =IF(F22=0,"***",M22/F22) | U22: =IF(G22=0,"***",N22/G22) | V22: =IF(H22=0,"***",O22/H22) | W22: =IF(I22=0,"***",P22/I22) | X22: =IF(J22=0,"***",Q22/J22) | Y22: =IF(K22=0,"***",R22/K22)
C23: 0911 集計 | D23: 川邊主任 | E23: 319 | F23: 1653 | G23: 400 | H23: 906 | I23: 402 | J23: 243 | K23: =SUM(E23:J23) | L23: 101 | M23: 284 | N23: 90 | O23: 184 | P23: 77 | Q23: 39 | R23: =SUM(L23:Q23) | S23: =IF(E23=0,"***",L23/E23) | T23: =IF(F23=0,"***",M23/F23) | U23: =IF(G23=0,"***",N23/G23) | V23: =IF(H23=0,"***",O23/H23) | W23: =IF(I23=0,"***",P23/I23) | X23: =IF(J23=0,"***",Q23/J23) | Y23: =IF(K23=0,"***",R23/K23)
C24: 0914 集計 | D24: 白根主任 | E24: 1021 | F24: 176 | G24: 6504 | H24: 738 | I24: 427 | J24: 394 | K24: =SUM(E24:J24) | L24: 346 | M24: 55 | N24: 1639 | O24: 217 | P24: 158 | Q24: 101 | R24: =SUM(L24:Q24) | S24: =IF(E24=0,"***",L24/E24) | T24: =IF(F24=0,"***",M24/F24) | U24: =IF(G24=0,"***",N24/G24) | V24: =IF(H24=0,"***",O24/H24) | W24: =IF(I24=0,"***",P24/I24) | X24: =IF(J24=0,"***",Q24/J24) | Y24: =IF(K24=0,"***",R24/K24)
C25: 0918 集計 | D25: 海外 | E25: 643 | F25: 95 | G25: 576 | H25: 219 | I25: 2 | J25: 176 | K25: =SUM(E25:J25) | L25: 130 | M25: 19 | N25: 130 | O25: 47 | P25: 0 | Q25: 48 | R25: =SUM(L25:Q25) | S25: =IF(E25=0,"***",L25/E25) | T25: =IF(F25=0,"***",M25/F25) | U25: =IF(G25=0,"***",N25/G25) | V25: =IF(H25=0,"***",O25/H25) | W25: =IF(I25=0,"***",P25/I25) | X25: =IF(J25=0,"***",Q25/J25) | Y25: =IF(K25=0,"***",R25/K25)
C26: 0919 集計 | D26: その他 | E26: 0 | F26: 0 | G26: 0 | H26: 0 | I26: 0 | J26: 0 | K26: =SUM(E26:J26) | L26: 0 | M26: 0 | N26: 0 | O26: 0 | P26: 0 | Q26: 0 | R26: =SUM(L26:Q26) | S26: =IF(E26=0,"***",L26/E26) | T26: =IF(F26=0,"***",M26/F26) | U26: =IF(G26=0,"***",N26/G26) | V26: =IF(H26=0,"***",O26/H26) | W26: =IF(I26=0,"***",P26/I26) | X26: =IF(J26=0,"***",Q26/J26) | Y26: =IF(K26=0,"***",R26/K26)
C27: 0930 集計 | D27: 自治体
C28: 合計 | E28: =SUM(E19:E27) | F28: =SUM(F19:F27) | G28: =SUM(G19:G27) | H28: =SUM(H19:H27) | I28: =SUM(I19:I27) | J28: =SUM(J19:J27) | K28: =SUM(K19:K27) | L28: =SUM(L19:L27) | ... R28: =SUM(R19:R27) | S28: =IF(E28=0,"***",L28/E28) | T28: =IF(F28=0,"***",M28/F28) | U28: =IF(G28=0,"***",N28/G28) | V28: =IF(H28=0,"***",O28/H28) | W28: =IF(I28=0,"***",P28/I28) | X28: =IF(J28=0,"***",Q28/J28) | Y28: =IF(K28=0,"***",R28/K28)
C30: 3．過年度平均
E31: 売上 | L31: 粗利益 | S31: 粗利益率
E32: 45748 | F32: 45778 | G32: 45809 | H32: 45839 | I32: 45870 | J32: 45901 | K32: 合計 | L32: 45748 | M32: 45778 | N32: 45809 | O32: 45839 | P32: 45870 | Q32: 45901 | R32: 合計 | S32: 45748 | T32: 45778 | U32: 45809 | V32: 45839 | W32: 45870 | X32: 45901 | Y32: 合計
C33: 0903 集計 | D33: 西岡 | E33: =(E19+E5)/2 | F33: =(F19+F5)/2 | G33: =(G19+G5)/2 | H33: =(H19+H5)/2 | I33: =(I19+I5)/2 | J33: =(J19+J5)/2 | K33: =SUM(E33:J33) | L33: =(L19+L5)/2 | M33: =(M19+M5)/2 | N33: =(N19+N5)/2 | O33: =(O19+O5)/2 | P33: =(P19+P5)/2 | Q33: =(Q19+Q5)/2 | R33: =SUM(L33:Q33) | S33: =IF(E33=0,"***",L33/E33) | T33: =IF(F33=0,"***",M33/F33) | U33: =IF(G33=0,"***",N33/G33) | V33: =IF(H33=0,"***",O33/H33) | W33: =IF(I33=0,"***",P33/I33) | X33: =IF(J33=0,"***",Q33/J33) | Y33: =IF(K33=0,"***",R33/K33)
C34: 0904 集計 | D34: 足立次長 | E34: =(E20+E6)/2 | F34: =(F20+F6)/2 | G34: =(G20+G6)/2 | H34: =(H20+H6)/2 | I34: =(I20+I6)/2 | J34: =(J20+J6)/2 | K34: =SUM(E34:J34) | L34: =(L20+L6)/2 | M34: =(M20+M6)/2 | N34: =(N20+N6)/2 | O34: =(O20+O6)/2 | P34: =(P20+P6)/2 | Q34: =(Q20+Q6)/2 | R34: =SUM(L34:Q34) | S34: =IF(E34=0,"***",L34/E34) | T34: =IF(F34=0,"***",M34/F34) | U34: =IF(G34=0,"***",N34/G34) | V34: =IF(H34=0,"***",O34/H34) | W34: =IF(I34=0,"***",P34/I34) | X34: =IF(J34=0,"***",Q34/J34) | Y34: =IF(K34=0,"***",R34/K34)
C35: 0909 集計 | D35: 藤波課長 | E35: =(E21+E7)/2 | F35: =(F21+F7)/2 | G35: =(G21+G7)/2 | H35: =(H21+H7)/2 | I35: =(I21+I7)/2 | J35: =(J21+J7)/2 | K35: =SUM(E35:J35) | L35: =(L21+L7)/2 | M35: =(M21+M7)/2 | N35: =(N21+N7)/2 | O35: =(O21+O7)/2 | P35: =(P21+P7)/2 | Q35: =(Q21+Q7)/2 | R35: =SUM(L35:Q35) | S35: =IF(E35=0,"***",L35/E35) | T35: =IF(F35=0,"***",M35/F35) | U35: =IF(G35=0,"***",N35/G35) | V35: =IF(H35=0,"***",O35/H35) | W35: =IF(I35=0,"***",P35/I35) | X35: =IF(J35=0,"***",Q35/J35) | Y35: =IF(K35=0,"***",R35/K35)
C36: 0910 集計 | D36: 足立課長 | E36: =(E22+E8)/2 | F36: =(F22+F8)/2 | G36: =(G22+G8)/2 | H36: =(H22+H8)/2 | I36: =(I22+I8)/2 | J36: =(J22+J8)/2 | K36: =SUM(E36:J36) | L36: =(L22+L8)/2 | M36: =(M22+M8)/2 | N36: =(N22+N8)/2 | O36: =(O22+O8)/2 | P36: =(P22+P8)/2 | Q36: =(Q22+Q8)/2 | R36: =SUM(L36:Q36) | S36: =IF(E36=0,"***",L36/E36) | T36: =IF(F36=0,"***",M36/F36) | U36: =IF(G36=0,"***",N36/G36) | V36: =IF(H36=0,"***",O36/H36) | W36: =IF(I36=0,"***",P36/I36) | X36: =IF(J36=0,"***",Q36/J36) | Y36: =IF(K36=0,"***",R36/K36)
C37: 0911 集計 | D37: 川邊主任 | E37: =(E23+E9)/2 | F37: =(F23+F9)/2 | G37: =(G23+G9)/2 | H37: =(H23+H9)/2 | I37: =(I23+I9)/2 | J37: =(J23+J9)/2 | K37: =SUM(E37:J37) | L37: =(L23+L9)/2 | M37: =(M23+M9)/2 | N37: =(N23+N9)/2 | O37: =(O23+O9)/2 | P37: =(P23+P9)/2 | Q37: =(Q23+Q9)/2 | R37: =SUM(L37:Q37) | S37: =IF(E37=0,"***",L37/E37) | T37: =IF(F37=0,"***",M37/F37) | U37: =IF(G37=0,"***",N37/G37) | V37: =IF(H37=0,"***",O37/H37) | W37: =IF(I37=0,"***",P37/I37) | X37: =IF(J37=0,"***",Q37/J37) | Y37: =IF(K37=0,"***",R37/K37)
C38: 0914 集計 | D38: 白根主任 | E38: =(E24+E10)/2 | F38: =(F24+F10)/2 | G38: =(G24+G10)/2 | H38: =(H24+H10)/2 | I38: =(I24+I10)/2 | J38: =(J24+J10)/2 | K38: =SUM(E38:J38) | L38: =(L24+L10)/2 | M38: =(M24+M10)/2 | N38: =(N24+N10)/2 | O38: =(O24+O10)/2 | P38: =(P24+P10)/2 | Q38: =(Q24+Q10)/2 | R38: =SUM(L38:Q38) | S38: =IF(E38=0,"***",L38/E38) | T38: =IF(F38=0,"***",M38/F38) | U38: =IF(G38=0,"***",N38/G38) | V38: =IF(H38=0,"***",O38/H38) | W38: =IF(I38=0,"***",P38/I38) | X38: =IF(J38=0,"***",Q38/J38) | Y38: =IF(K38=0,"***",R38/K38)
C39: 0918 集計 | D39: 海外 | E39: =(E25+E11)/2 | F39: =(F25+F11)/2 | G39: =(G25+G11)/2 | H39: =(H25+H11)/2 | I39: =(I25+I11)/2 | J39: =(J25+J11)/2 | K39: =SUM(E39:J39) | L39: =(L25+L11)/2 | M39: =(M25+M11)/2 | N39: =(N25+N11)/2 | O39: =(O25+O11)/2 | P39: =(P25+P11)/2 | Q39: =(Q25+Q11)/2 | R39: =SUM(L39:Q39) | S39: =IF(E39=0,"***",L39/E39) | T39: =IF(F39=0,"***",M39/F39) | U39: =IF(G39=0,"***",N39/G39) | V39: =IF(H39=0,"***",O39/H39) | W39: =IF(I39=0,"***",P39/I39) | X39: =IF(J39=0,"***",Q39/J39) | Y39: =IF(K39=0,"***",R39/K39)
C40: 0919 集計 | D40: その他 | E40: =(E26+E12)/2 | F40: =(F26+F12)/2 | G40: =(G26+G12)/2 | H40: =(H26+H12)/2 | I40: =(I26+I12)/2 | J40: =(J26+J12)/2 | K40: =SUM(E40:J40) | L40: =(L26+L12)/2 | M40: =(M26+M12)/2 | N40: =(N26+N12)/2 | O40: =(O26+O12)/2 | P40: =(P26+P12)/2 | Q40: =(Q26+Q12)/2 | R40: =SUM(L40:Q40) | S40: =IF(E40=0,"***",L40/E40) | T40: =IF(F40=0,"***",M40/F40) | U40: =IF(G40=0,"***",N40/G40) | V40: =IF(H40=0,"***",O40/H40) | W40: =IF(I40=0,"***",P40/I40) | X40: =IF(J40=0,"***",Q40/J40) | Y40: =IF(K40=0,"***",R40/K40)
C41: 0930 集計 | D41: 自治体 | E41: =(E27+E13)/2 | F41: =(F27+F13)/2 | G41: =(G27+G13)/2 | H41: =(H27+H13)/2 | I41: =(I27+I13)/2 | J41: =(J27+J13)/2 | K41: =SUM(E41:J41) | L41: =(L27+L13)/2 | M41: =(M27+M13)/2 | N41: =(N27+N13)/2 | O41: =(O27+O13)/2 | P41: =(P27+P13)/2 | Q41: =(Q27+Q13)/2 | R41: =SUM(L41:Q41) | S41: =IF(E41=0,"***",L41/E41) | T41: =IF(F41=0,"***",M41/F41) | U41: =IF(G41=0,"***",N41/G41) | V41: =IF(H41=0,"***",O41/H41) | W41: =IF(I41=0,"***",P41/I41) | X41: =IF(J41=0,"***",Q41/J41) | Y41: =IF(K41=0,"***",R41/K41)
C42: 合計 | E42: =SUM(E33:E41) | F42: =SUM(F33:F41) | G42: =SUM(G33:G41) | H42: =SUM(H33:H41) | I42: =SUM(I33:I41) | J42: =SUM(J33:J41) | K42: =SUM(K33:K41) | L42: =SUM(L33:L41) | ... R42: =SUM(R33:R41) | S42: =IF(E42=0,"***",L42/E42) | T42: =IF(F42=0,"***",M42/F42) | U42: =IF(G42=0,"***",N42/G42) | V42: =IF(H42=0,"***",O42/H42) | W42: =IF(I42=0,"***",P42/I42) | X42: =IF(J42=0,"***",Q42/J42) | Y42: =IF(K42=0,"***",R42/K42)
C44: 4．計画
E45: 売上 | L45: 粗利益 | S45: 粗利益率
E46: 46113 | F46: 46143 | G46: 46174 | H46: 46204 | I46: 46235 | J46: 46266 | K46: 合計 | L46: 46113 | M46: 46143 | N46: 46174 | O46: 46204 | P46: 46235 | Q46: 46266 | R46: 合計 | S46: 46113 | T46: 46143 | U46: 46174 | V46: 46204 | W46: 46235 | X46: 46266 | Y46: 合計
C47: 0903 集計 | D47: 西岡 | E47: 200 | F47: 200 | G47: 200 | H47: 200 | I47: 200 | J47: 200 | K47: =SUM(E47:J47) | L47: 40 | M47: 70 | N47: 70 | O47: 70 | P47: 70 | Q47: 70 | R47: =SUM(L47:Q47) | S47: =IF(E47=0,"***",L47/E47) | T47: =IF(F47=0,"***",M47/F47) | U47: =IF(G47=0,"***",N47/G47) | V47: =IF(H47=0,"***",O47/H47) | W47: =IF(I47=0,"***",P47/I47) | X47: =IF(J47=0,"***",Q47/J47) | Y47: =IF(K47=0,"***",R47/K47)
C48: 0904 集計 | D48: 足立次長 | E48: 5000 | F48: 5000 | G48: 5000 | H48: 5000 | I48: 5000 | J48: 5000 | K48: =SUM(E48:J48) | L48: 1000 | M48: 1000 | N48: 1000 | O48: 1000 | P48: 1000 | Q48: 1000 | R48: =SUM(L48:Q48) | S48: =IF(E48=0,"***",L48/E48) | T48: =IF(F48=0,"***",M48/F48) | U48: =IF(G48=0,"***",N48/G48) | V48: =IF(H48=0,"***",O48/H48) | W48: =IF(I48=0,"***",P48/I48) | X48: =IF(J48=0,"***",Q48/J48) | Y48: =IF(K48=0,"***",R48/K48)
C49: 0909 集計 | D49: 藤波課長 | E49: 700 | F49: 700 | G49: 18700 | H49: 700 | I49: 700 | J49: 700 | K49: =SUM(E49:J49) | L49: 250 | M49: 250 | N49: 5410 | O49: 250 | P49: 250 | Q49: 250 | R49: =SUM(L49:Q49) | S49: =IF(E49=0,"***",L49/E49) | T49: =IF(F49=0,"***",M49/F49) | U49: =IF(G49=0,"***",N49/G49) | V49: =IF(H49=0,"***",O49/H49) | W49: =IF(I49=0,"***",P49/I49) | X49: =IF(J49=0,"***",Q49/J49) | Y49: =IF(K49=0,"***",R49/K49)
C50: 0910 集計 | D50: 足立課長 | E50: 1000 | F50: 1000 | G50: 1000 | K50: =SUM(E50:J50) | L50: 250 | M50: 250 | N50: 250 | R50: =SUM(L50:Q50) | S50: =IF(E50=0,"***",L50/E50) | T50: =IF(F50=0,"***",M50/F50) | U50: =IF(G50=0,"***",N50/G50) | V50: =IF(H50=0,"***",O50/H50) | W50: =IF(I50=0,"***",P50/I50) | X50: =IF(J50=0,"***",Q50/J50) | Y50: =IF(K50=0,"***",R50/K50)
C51: 0911 集計 | D51: 川邊主任 | E51: 700 | F51: 700 | G51: 700 | H51: 700 | I51: 700 | J51: 700 | K51: =SUM(E51:J51) | L51: 180 | M51: 180 | N51: 180 | O51: 180 | P51: 180 | Q51: 180 | R51: =SUM(L51:Q51) | S51: =IF(E51=0,"***",L51/E51) | T51: =IF(F51=0,"***",M51/F51) | U51: =IF(G51=0,"***",N51/G51) | V51: =IF(H51=0,"***",O51/H51) | W51: =IF(I51=0,"***",P51/I51) | X51: =IF(J51=0,"***",Q51/J51) | Y51: =IF(K51=0,"***",R51/K51)
C52: 0914 集計 | D52: 白根主任 | E52: 20500 | F52: 1500 | G52: 1500 | H52: 1500 | I52: 1500 | J52: 1500 | K52: =SUM(E52:J52) | L52: 2600 | M52: 300 | N52: 300 | O52: 300 | P52: 300 | Q52: 300 | R52: =SUM(L52:Q52) | S52: =IF(E52=0,"***",L52/E52) | T52: =IF(F52=0,"***",M52/F52) | U52: =IF(G52=0,"***",N52/G52) | V52: =IF(H52=0,"***",O52/H52) | W52: =IF(I52=0,"***",P52/I52) | X52: =IF(J52=0,"***",Q52/J52) | Y52: =IF(K52=0,"***",R52/K52)
C53: 0918 集計 | D53: 海外 | E53: 400 | F53: 400 | G53: 400 | H53: 400 | I53: 400 | J53: 400 | K53: =SUM(E53:J53) | L53: 80 | M53: 80 | N53: 80 | O53: 80 | P53: 80 | Q53: 80 | R53: =SUM(L53:Q53) | S53: =IF(E53=0,"***",L53/E53) | T53: =IF(F53=0,"***",M53/F53) | U53: =IF(G53=0,"***",N53/G53) | V53: =IF(H53=0,"***",O53/H53) | W53: =IF(I53=0,"***",P53/I53) | X53: =IF(J53=0,"***",Q53/J53) | Y53: =IF(K53=0,"***",R53/K53)
C54: 0919 集計 | D54: その他 | E54: 0 | F54: 0 | G54: 0 | H54: 0 | I54: 0 | J54: 0 | K54: =SUM(E54:J54) | L54: 0 | M54: 0 | N54: 0 | O54: 0 | P54: 0 | Q54: 0 | R54: =SUM(L54:Q54) | S54: =IF(E54=0,"***",L54/E54) | T54: =IF(F54=0,"***",M54/F54) | U54: =IF(G54=0,"***",N54/G54) | V54: =IF(H54=0,"***",O54/H54) | W54: =IF(I54=0,"***",P54/I54) | X54: =IF(J54=0,"***",Q54/J54) | Y54: =IF(K54=0,"***",R54/K54)
C55: 0930 集計 | D55: 自治体 | E55: 0 | F55: 0 | G55: 0 | H55: 0 | I55: 0 | J55: 0 | K55: =SUM(E55:J55) | L55: 0 | M55: 0 | N55: 0 | O55: 0 | P55: 0 | Q55: 0 | R55: =SUM(L55:Q55) | S55: =IF(E55=0,"***",L55/E55) | T55: =IF(F55=0,"***",M55/F55) | U55: =IF(G55=0,"***",N55/G55) | V55: =IF(H55=0,"***",O55/H55) | W55: =IF(I55=0,"***",P55/I55) | X55: =IF(J55=0,"***",Q55/J55) | Y55: =IF(K55=0,"***",R55/K55)
C56: 合計 | E56: =SUM(E47:E55) | F56: =SUM(F47:F55) | G56: =SUM(G47:G55) | H56: =SUM(H47:H55) | I56: =SUM(I47:I55) | J56: =SUM(J47:J55) | K56: =SUM(K47:K55) | L56: =SUM(L47:L55) | ... R56: =SUM(R47:R55) | S56: =IF(E56=0,"***",L56/E56) | T56: =IF(F56=0,"***",M56/F56) | U56: =IF(G56=0,"***",N56/G56) | V56: =IF(H56=0,"***",O56/H56) | W56: =IF(I56=0,"***",P56/I56) | X56: =IF(J56=0,"***",Q56/J56) | Y56: =IF(K56=0,"***",R56/K56)
C58: ５．前期比
E59: 売上 | L59: 粗利益 | S59: 粗利益率
E60: 46113 | F60: 46143 | G60: 46174 | H60: 46204 | I60: 46235 | J60: 46266 | K60: 合計 | L60: 46113 | M60: 46143 | N60: 46174 | O60: 46204 | P60: 46235 | Q60: 46266 | R60: 合計 | S60: 46113 | T60: 46143 | U60: 46174 | V60: 46204 | W60: 46235 | X60: 46266 | Y60: 合計
C61: 0903 集計 | D61: 西岡 | E61: =E47-E19 | F61: =F47-F19 | G61: =G47-G19 | H61: =H47-H19 | I61: =I47-I19 | J61: =J47-J19 | K61: =SUM(E61:J61) | L61: =L47-L19 | M61: =M47-M19 | N61: =N47-N19 | O61: =O47-O19 | P61: =P47-P19 | Q61: =Q47-Q19 | R61: =SUM(L61:Q61) | S61: =S47-S19 | T61: =T47-T19 | U61: =U47-U19 | V61: =V47-V19 | W61: =W47-W19 | X61: =X47-X19 | Y61: =Y47-Y19
C62: 0904 集計 | D62: 足立次長 | E62: =E48-E20 | F62: =F48-F20 | G62: =G48-G20 | H62: =H48-H20 | I62: =I48-I20 | J62: =J48-J20 | K62: =SUM(E62:J62) | L62: =L48-L20 | M62: =M48-M20 | N62: =N48-N20 | O62: =O48-O20 | P62: =P48-P20 | Q62: =Q48-Q20 | R62: =SUM(L62:Q62) | S62: =S48-S20 | T62: =T48-T20 | U62: =U48-U20 | V62: =V48-V20 | W62: =W48-W20 | X62: =X48-X20 | Y62: =Y48-Y20
C63: 0909 集計 | D63: 藤波課長 | E63: =E49-E21 | F63: =F49-F21 | G63: =G49-G21 | H63: =H49-H21 | I63: =I49-I21 | J63: =J49-J21 | K63: =SUM(E63:J63) | L63: =L49-L21 | M63: =M49-M21 | N63: =N49-N21 | O63: =O49-O21 | P63: =P49-P21 | Q63: =Q49-Q21 | R63: =SUM(L63:Q63) | S63: =S49-S21 | T63: =T49-T21 | U63: =U49-U21 | V63: =V49-V21 | W63: =W49-W21 | X63: =X49-X21 | Y63: =Y49-Y21
C64: 0910 集計 | D64: 足立課長 | E64: =E50-E22 | F64: =F50-F22 | G64: =G50-G22 | H64: =H50-H22 | I64: =I50-I22 | J64: =J50-J22 | K64: =SUM(E64:J64) | L64: =L50-L22 | M64: =M50-M22 | N64: =N50-N22 | O64: =O50-O22 | P64: =P50-P22 | Q64: =Q50-Q22 | R64: =SUM(L64:Q64) | S64: =S50-S22 | T64: =T50-T22 | U64: =U50-U22 | V64: =V50-V22 | W64: =W50-W22 | X64: =X50-X22 | Y64: =Y50-Y22
C65: 0911 集計 | D65: 川邊主任 | E65: =E51-E23 | F65: =F51-F23 | G65: =G51-G23 | H65: =H51-H23 | I65: =I51-I23 | J65: =J51-J23 | K65: =SUM(E65:J65) | L65: =L51-L23 | M65: =M51-M23 | N65: =N51-N23 | O65: =O51-O23 | P65: =P51-P23 | Q65: =Q51-Q23 | R65: =SUM(L65:Q65) | S65: =S51-S23 | T65: =T51-T23 | U65: =U51-U23 | V65: =V51-V23 | W65: =W51-W23 | X65: =X51-X23 | Y65: =Y51-Y23
C66: 0914 集計 | D66: 白根主任 | E66: =E52-E24 | F66: =F52-F24 | G66: =G52-G24 | H66: =H52-H24 | I66: =I52-I24 | J66: =J52-J24 | K66: =SUM(E66:J66) | L66: =L52-L24 | M66: =M52-M24 | N66: =N52-N24 | O66: =O52-O24 | P66: =P52-P24 | Q66: =Q52-Q24 | R66: =SUM(L66:Q66) | S66: =S52-S24 | T66: =T52-T24 | U66: =U52-U24 | V66: =V52-V24 | W66: =W52-W24 | X66: =X52-X24 | Y66: =Y52-Y24
C67: 0918 集計 | D67: 海外 | E67: =E53-E25 | F67: =F53-F25 | G67: =G53-G25 | H67: =H53-H25 | I67: =I53-I25 | J67: =J53-J25 | K67: =SUM(E67:J67) | L67: =L53-L25 | M67: =M53-M25 | N67: =N53-N25 | O67: =O53-O25 | P67: =P53-P25 | Q67: =Q53-Q25 | R67: =SUM(L67:Q67) | S67: =S53-S25 | T67: =T53-T25 | U67: =U53-U25 | V67: =V53-V25 | W67: =W53-W25 | X67: =X53-X25 | Y67: =Y53-Y25
C68: 0919 集計 | D68: その他 | E68: =E54-E26 | F68: =F54-F26 | G68: =G54-G26 | H68: =H54-H26 | I68: =I54-I26 | J68: =J54-J26 | K68: =SUM(E68:J68) | L68: =L54-L26 | M68: =M54-M26 | N68: =N54-N26 | O68: =O54-O26 | P68: =P54-P26 | Q68: =Q54-Q26 | R68: =SUM(L68:Q68) | S68: =S54-S26 | T68: =T54-T26 | U68: =U54-U26 | V68: =V54-V26 | W68: =W54-W26 | X68: =X54-X26 | Y68: =Y54-Y26
C69: 0930 集計 | D69: 自治体 | E69: =E55-E27 | F69: =F55-F27 | G69: =G55-G27 | H69: =H55-H27 | I69: =I55-I27 | J69: =J55-J27 | K69: =SUM(E69:J69) | L69: =L55-L27 | M69: =M55-M27 | N69: =N55-N27 | O69: =O55-O27 | P69: =P55-P27 | Q69: =Q55-Q27 | R69: =SUM(L69:Q69) | S69: =S55-S27 | T69: =T55-T27 | U69: =U55-U27 | V69: =V55-V27 | W69: =W55-W27 | X69: =X55-X27 | Y69: =Y55-Y27
C70: 合計 | E70: =SUM(E61:E69) | F70: =SUM(F61:F69) | G70: =SUM(G61:G69) | H70: =SUM(H61:H69) | I70: =SUM(I61:I69) | J70: =SUM(J61:J69) | K70: =SUM(K61:K69) | L70: =SUM(L61:L69) | ... R70: =SUM(R61:R69) | S70: =S56-S28 | T70: =T56-T28 | U70: =U56-U28 | V70: =V56-V28 | W70: =W56-W28 | X70: =X56-X28 | Y70: =Y56-Y28
C72: 6．過年度平均比
E73: 売上 | L73: 粗利益 | S73: 粗利益率
E74: 46113 | F74: 46143 | G74: 46174 | H74: 46204 | I74: 46235 | J74: 46266 | K74: 合計 | L74: 46113 | M74: 46143 | N74: 46174 | O74: 46204 | P74: 46235 | Q74: 46266 | R74: 合計 | S74: 46113 | T74: 46143 | U74: 46174 | V74: 46204 | W74: 46235 | X74: 46266 | Y74: 合計
C75: 0903 集計 | D75: 西岡 | E75: =E47-E33 | F75: =F47-F33 | G75: =G47-G33 | H75: =H47-H33 | I75: =I47-I33 | J75: =J47-J33 | K75: =SUM(E75:J75) | L75: =L47-L33 | M75: =M47-M33 | N75: =N47-N33 | O75: =O47-O33 | P75: =P47-P33 | Q75: =Q47-Q33 | R75: =SUM(L75:Q75) | S75: =IF(E75=0,"***",L75/E75) | T75: =IF(F75=0,"***",M75/F75) | U75: =IF(G75=0,"***",N75/G75) | V75: =IF(H75=0,"***",O75/H75) | W75: =IF(I75=0,"***",P75/I75) | X75: =IF(J75=0,"***",Q75/J75) | Y75: =IF(K75=0,"***",R75/K75)
C76: 0904 集計 | D76: 足立次長 | E76: =E48-E34 | F76: =F48-F34 | G76: =G48-G34 | H76: =H48-H34 | I76: =I48-I34 | J76: =J48-J34 | K76: =SUM(E76:J76) | L76: =L48-L34 | M76: =M48-M34 | N76: =N48-N34 | O76: =O48-O34 | P76: =P48-P34 | Q76: =Q48-Q34 | R76: =SUM(L76:Q76) | S76: =IF(E76=0,"***",L76/E76) | T76: =IF(F76=0,"***",M76/F76) | U76: =IF(G76=0,"***",N76/G76) | V76: =IF(H76=0,"***",O76/H76) | W76: =IF(I76=0,"***",P76/I76) | X76: =IF(J76=0,"***",Q76/J76) | Y76: =IF(K76=0,"***",R76/K76)
C77: 0909 集計 | D77: 藤波課長 | E77: =E49-E35 | F77: =F49-F35 | G77: =G49-G35 | H77: =H49-H35 | I77: =I49-I35 | J77: =J49-J35 | K77: =SUM(E77:J77) | L77: =L49-L35 | M77: =M49-M35 | N77: =N49-N35 | O77: =O49-O35 | P77: =P49-P35 | Q77: =Q49-Q35 | R77: =SUM(L77:Q77) | S77: =IF(E77=0,"***",L77/E77) | T77: =IF(F77=0,"***",M77/F77) | U77: =IF(G77=0,"***",N77/G77) | V77: =IF(H77=0,"***",O77/H77) | W77: =IF(I77=0,"***",P77/I77) | X77: =IF(J77=0,"***",Q77/J77) | Y77: =IF(K77=0,"***",R77/K77)
C78: 0910 集計 | D78: 足立課長 | E78: =E50-E36 | F78: =F50-F36 | G78: =G50-G36 | H78: =H50-H36 | I78: =I50-I36 | J78: =J50-J36 | K78: =SUM(E78:J78) | L78: =L50-L36 | M78: =M50-M36 | N78: =N50-N36 | O78: =O50-O36 | P78: =P50-P36 | Q78: =Q50-Q36 | R78: =SUM(L78:Q78) | S78: =IF(E78=0,"***",L78/E78) | T78: =IF(F78=0,"***",M78/F78) | U78: =IF(G78=0,"***",N78/G78) | V78: =IF(H78=0,"***",O78/H78) | W78: =IF(I78=0,"***",P78/I78) | X78: =IF(J78=0,"***",Q78/J78) | Y78: =IF(K78=0,"***",R78/K78)
C79: 0911 集計 | D79: 川邊主任 | E79: =E51-E37 | F79: =F51-F37 | G79: =G51-G37 | H79: =H51-H37 | I79: =I51-I37 | J79: =J51-J37 | K79: =SUM(E79:J79) | L79: =L51-L37 | M79: =M51-M37 | N79: =N51-N37 | O79: =O51-O37 | P79: =P51-P37 | Q79: =Q51-Q37 | R79: =SUM(L79:Q79) | S79: =IF(E79=0,"***",L79/E79) | T79: =IF(F79=0,"***",M79/F79) | U79: =IF(G79=0,"***",N79/G79) | V79: =IF(H79=0,"***",O79/H79) | W79: =IF(I79=0,"***",P79/I79) | X79: =IF(J79=0,"***",Q79/J79) | Y79: =IF(K79=0,"***",R79/K79)
C80: 0914 集計 | D80: 白根主任 | E80: =E52-E38 | F80: =F52-F38 | G80: =G52-G38 | H80: =H52-H38 | I80: =I52-I38 | J80: =J52-J38 | K80: =SUM(E80:J80) | L80: =L52-L38 | M80: =M52-M38 | N80: =N52-N38 | O80: =O52-O38 | P80: =P52-P38 | Q80: =Q52-Q38 | R80: =SUM(L80:Q80) | S80: =IF(E80=0,"***",L80/E80) | T80: =IF(F80=0,"***",M80/F80) | U80: =IF(G80=0,"***",N80/G80) | V80: =IF(H80=0,"***",O80/H80) | W80: =IF(I80=0,"***",P80/I80) | X80: =IF(J80=0,"***",Q80/J80) | Y80: =IF(K80=0,"***",R80/K80)
C81: 0918 集計 | D81: 海外 | E81: =E53-E39 | F81: =F53-F39 | G81: =G53-G39 | H81: =H53-H39 | I81: =I53-I39 | J81: =J53-J39 | K81: =SUM(E81:J81) | L81: =L53-L39 | M81: =M53-M39 | N81: =N53-N39 | O81: =O53-O39 | P81: =P53-P39 | Q81: =Q53-Q39 | R81: =SUM(L81:Q81) | S81: =IF(E81=0,"***",L81/E81) | T81: =IF(F81=0,"***",M81/F81) | U81: =IF(G81=0,"***",N81/G81) | V81: =IF(H81=0,"***",O81/H81) | W81: =IF(I81=0,"***",P81/I81) | X81: =IF(J81=0,"***",Q81/J81) | Y81: =IF(K81=0,"***",R81/K81)
C82: 0919 集計 | D82: その他 | E82: =E54-E40 | F82: =F54-F40 | G82: =G54-G40 | H82: =H54-H40 | I82: =I54-I40 | J82: =J54-J40 | K82: =SUM(E82:J82) | L82: =L54-L40 | M82: =M54-M40 | N82: =N54-N40 | O82: =O54-O40 | P82: =P54-P40 | Q82: =Q54-Q40 | R82: =SUM(L82:Q82) | S82: =IF(E82=0,"***",L82/E82) | T82: =IF(F82=0,"***",M82/F82) | U82: =IF(G82=0,"***",N82/G82) | V82: =IF(H82=0,"***",O82/H82) | W82: =IF(I82=0,"***",P82/I82) | X82: =IF(J82=0,"***",Q82/J82) | Y82: =IF(K82=0,"***",R82/K82)
C83: 0930 集計 | D83: 自治体 | G83: =G55-G41 | H83: =H55-H41 | I83: =I55-I41 | J83: =J55-J41 | K83: =SUM(E83:J83) | L83: =L55-L41 | M83: =M55-M41 | N83: =N55-N41 | O83: =O55-O41 | P83: =P55-P41 | Q83: =Q55-Q41 | R83: =SUM(L83:Q83) | S83: =IF(E83=0,"***",L83/E83) | T83: =IF(F83=0,"***",M83/F83) | U83: =IF(G83=0,"***",N83/G83) | V83: =IF(H83=0,"***",O83/H83) | W83: =IF(I83=0,"***",P83/I83) | X83: =IF(J83=0,"***",Q83/J83) | Y83: =IF(K83=0,"***",R83/K83)
C84: 合計 | E84: =SUM(E75:E83) | F84: =SUM(F75:F83) | G84: =SUM(G75:G83) | H84: =SUM(H75:H83) | I84: =SUM(I75:I83) | J84: =SUM(J75:J83) | K84: =SUM(K75:K83) | L84: =SUM(L75:L83) | ... R84: =SUM(R75:R83) | S84: =IF(E84=0,"***",L84/E84) | T84: =IF(F84=0,"***",M84/F84) | U84: =IF(G84=0,"***",N84/G84) | V84: =IF(H84=0,"***",O84/H84) | W84: =IF(I84=0,"***",P84/I84) | X84: =IF(J84=0,"***",Q84/J84) | Y84: =IF(K84=0,"***",R84/K84)
C86: 7．実績
E87: 売上 | L87: 粗利益 | S87: 粗利益率
E88: 46113 | F88: 46143 | G88: 46174 | H88: 46204 | I88: 46235 | J88: 46266 | K88: 合計 | L88: 46113 | M88: 46143 | N88: 46174 | O88: 46204 | P88: 46235 | Q88: 46266 | R88: 合計 | S88: 46113 | T88: 46143 | U88: 46174 | V88: 46204 | W88: 46235 | X88: 46266 | Y88: 合計
C89: 0903 集計 | D89: 西岡 | E89: 148.1 | F89: 2136.89 | G89: 64.5 | H89: 102.82 | I89: 95.95 | J89: 360.83 | K89: =SUM(E89:J89) | L89: 33.93 | M89: 359.932 | N89: 25.568 | O89: 31.785 | P89: 31.3 | Q89: 103.33 | R89: =SUM(L89:Q89) | S89: =IF(E89=0,"***",L89/E89) | T89: =IF(F89=0,"***",M89/F89) | U89: =IF(G89=0,"***",N89/G89) | V89: =IF(H89=0,"***",O89/H89) | W89: =IF(I89=0,"***",P89/I89) | X89: =IF(J89=0,"***",Q89/J89) | Y89: =IF(K89=0,"***",R89/K89)
C90: 0904 集計 | D90: 足立次長 | E90: 956.98 | F90: 787.45 | G90: 481.84 | H90: 507.605 | I90: 2776.22 | J90: 323.5 | K90: =SUM(E90:J90) | L90: 152.797 | M90: 133.891 | N90: 101.712 | O90: 95.715 | P90: 427.306 | Q90: 51.723 | R90: =SUM(L90:Q90) | S90: =IF(E90=0,"***",L90/E90) | T90: =IF(F90=0,"***",M90/F90) | U90: =IF(G90=0,"***",N90/G90) | V90: =IF(H90=0,"***",O90/H90) | W90: =IF(I90=0,"***",P90/I90) | X90: =IF(J90=0,"***",Q90/J90) | Y90: =IF(K90=0,"***",R90/K90)
C91: 0909 集計 | D91: 藤波課長 | E91: 391.27 | F91: 6526.66 | G91: 19790.8 | H91: 541.19 | I91: 430.34 | J91: 5195.98 | K91: =SUM(E91:J91) | L91: 166.92 | M91: 1728.25 | N91: 5372.184 | O91: 236.875 | P91: 181.44 | Q91: 1185.271 | R91: =SUM(L91:Q91) | S91: =IF(E91=0,"***",L91/E91) | T91: =IF(F91=0,"***",M91/F91) | U91: =IF(G91=0,"***",N91/G91) | V91: =IF(H91=0,"***",O91/H91) | W91: =IF(I91=0,"***",P91/I91) | X91: =IF(J91=0,"***",Q91/J91) | Y91: =IF(K91=0,"***",R91/K91)
C92: 0910 集計 | D92: 足立課長 | E92: 941.3 | F92: 124.3 | G92: 306.39 | H92: 0 | I92: 0 | J92: 0 | K92: =SUM(E92:J92) | L92: 196.6 | M92: 44.381 | N92: 106.07 | O92: 0 | P92: 0 | Q92: 0 | R92: =SUM(L92:Q92) | S92: =IF(E92=0,"***",L92/E92) | T92: =IF(F92=0,"***",M92/F92) | U92: =IF(G92=0,"***",N92/G92) | V92: =IF(H92=0,"***",O92/H92) | W92: =IF(I92=0,"***",P92/I92) | X92: =IF(J92=0,"***",Q92/J92) | Y92: =IF(K92=0,"***",R92/K92)
C93: 0911 集計 | D93: 川邊主任 | E93: 435.39 | F93: 534.19 | G93: 1385.69 | H93: 2617.59 | I93: 248.8 | J93: 182.29 | K93: =SUM(E93:J93) | L93: 100.958 | M93: 151.095 | N93: 255.975 | O93: 345.805 | P93: 59.55 | Q93: 83.8 | R93: =SUM(L93:Q93) | S93: =IF(E93=0,"***",L93/E93) | T93: =IF(F93=0,"***",M93/F93) | U93: =IF(G93=0,"***",N93/G93) | V93: =IF(H93=0,"***",O93/H93) | W93: =IF(I93=0,"***",P93/I93) | X93: =IF(J93=0,"***",Q93/J93) | Y93: =IF(K93=0,"***",R93/K93)
C94: 0914 集計 | D94: 白根主任 | E94: 19431.76 | F94: 503.53 | G94: 260.09 | H94: 219.45 | I94: 783.25 | J94: 2104.76 | K94: =SUM(E94:J94) | L94: 2446.647 | M94: 250.198 | N94: 142.992 | O94: 68.92 | P94: 242.149 | Q94: 516.139 | R94: =SUM(L94:Q94) | S94: =IF(E94=0,"***",L94/E94) | T94: =IF(F94=0,"***",M94/F94) | U94: =IF(G94=0,"***",N94/G94) | V94: =IF(H94=0,"***",O94/H94) | W94: =IF(I94=0,"***",P94/I94) | X94: =IF(J94=0,"***",Q94/J94) | Y94: =IF(K94=0,"***",R94/K94)
C95: 0918 集計 | D95: 海外 | E95: 706.9 | F95: 53.05 | G95: 1833.65 | H95: 6.36 | I95: 314.45 | J95: 0 | K95: =SUM(E95:J95) | L95: 171.7 | M95: 10.7 | N95: 536.9 | O95: 0.56 | P95: 59.63 | Q95: 0 | R95: =SUM(L95:Q95) | S95: =IF(E95=0,"***",L95/E95) | T95: =IF(F95=0,"***",M95/F95) | U95: =IF(G95=0,"***",N95/G95) | V95: =IF(H95=0,"***",O95/H95) | W95: =IF(I95=0,"***",P95/I95) | X95: =IF(J95=0,"***",Q95/J95) | Y95: =IF(K95=0,"***",R95/K95)
C96: 0919 集計 | D96: その他 | I96: 0 | J96: 0 | K96: =SUM(E96:J96) | P96: 0 | Q96: 0 | R96: =SUM(L96:Q96) | S96: =IF(E96=0,"***",L96/E96) | T96: =IF(F96=0,"***",M96/F96) | U96: =IF(G96=0,"***",N96/G96) | V96: =IF(H96=0,"***",O96/H96) | W96: =IF(I96=0,"***",P96/I96) | X96: =IF(J96=0,"***",Q96/J96) | Y96: =IF(K96=0,"***",R96/K96)
C97: 0930 集計 | D97: 自治体 | I97: 0 | J97: 0 | K97: =SUM(E97:J97) | P97: 0 | Q97: 0 | R97: =SUM(L97:Q97) | S97: =IF(E97=0,"***",L97/E97) | T97: =IF(F97=0,"***",M97/F97) | U97: =IF(G97=0,"***",N97/G97) | V97: =IF(H97=0,"***",O97/H97) | W97: =IF(I97=0,"***",P97/I97) | X97: =IF(J97=0,"***",Q97/J97) | Y97: =IF(K97=0,"***",R97/K97)
C98: 合計 | E98: =SUM(E89:E97) | F98: =SUM(F89:F97) | G98: =SUM(G89:G97) | H98: =SUM(H89:H97) | I98: =SUM(I89:I97) | J98: =SUM(J89:J97) | K98: =SUM(K89:K97) | L98: =SUM(L89:L97) | ... R98: =SUM(R89:R97) | S98: =IF(E98=0,"***",L98/E98) | T98: =IF(F98=0,"***",M98/F98) | U98: =IF(G98=0,"***",N98/G98) | V98: =IF(H98=0,"***",O98/H98) | W98: =IF(I98=0,"***",P98/I98) | X98: =IF(J98=0,"***",Q98/J98) | Y98: =IF(K98=0,"***",R98/K98)
C100: 8．計画比
E101: 売上 | L101: 粗利益 | S101: 粗利益率
E102: 46113 | F102: 46143 | G102: 46174 | H102: 46204 | I102: 46235 | J102: 46266 | K102: 合計 | L102: 46113 | M102: 46143 | N102: 46174 | O102: 46204 | P102: 46235 | Q102: 46266 | R102: 合計 | S102: 46113 | T102: 46143 | U102: 46174 | V102: 46204 | W102: 46235 | X102: 46266 | Y102: 合計
C103: 0903 集計 | D103: 西岡 | E103: =E89-E47 | F103: =F89-F47 | G103: =G89-G47 | H103: =H89-H47 | I103: =I89-I47 | J103: =J89-J47 | K103: =SUM(E103:J103) | L103: =L89-L47 | M103: =M89-M47 | N103: =N89-N47 | O103: =O89-O47 | P103: =P89-P47 | Q103: =Q89-Q47 | R103: =SUM(L103:Q103) | S103: =S89-S47 | T103: =T89-T47 | U103: =U89-U47 | V103: =V89-V47 | W103: =W89-W47 | X103: =X89-X47 | Y103: =Y89-Y47
C104: 0904 集計 | D104: 足立次長 | E104: =E90-E48 | F104: =F90-F48 | G104: =G90-G48 | H104: =H90-H48 | I104: =I90-I48 | J104: =J90-J48 | K104: =SUM(E104:J104) | L104: =L90-L48 | M104: =M90-M48 | N104: =N90-N48 | O104: =O90-O48 | P104: =P90-P48 | Q104: =Q90-Q48 | R104: =SUM(L104:Q104) | S104: =S90-S48 | T104: =T90-T48 | U104: =U90-U48 | V104: =V90-V48 | W104: =W90-W48 | X104: =X90-X48 | Y104: =Y90-Y48
C105: 0909 集計 | D105: 藤波課長 | E105: =E91-E49 | F105: =F91-F49 | G105: =G91-G49 | H105: =H91-H49 | I105: =I91-I49 | J105: =J91-J49 | K105: =SUM(E105:J105) | L105: =L91-L49 | M105: =M91-M49 | N105: =N91-N49 | O105: =O91-O49 | P105: =P91-P49 | Q105: =Q91-Q49 | R105: =SUM(L105:Q105) | S105: =S91-S49 | T105: =T91-T49 | U105: =U91-U49 | V105: =V91-V49 | W105: =W91-W49 | X105: =X91-X49 | Y105: =Y91-Y49
C106: 0910 集計 | D106: 足立課長 | E106: =E92-E50 | F106: =F92-F50 | G106: =G92-G50 | H106: =H92-H50 | I106: =I92-I50 | J106: =J92-J50 | K106: =SUM(E106:J106) | L106: =L92-L50 | M106: =M92-M50 | N106: =N92-N50 | O106: =O92-O50 | P106: =P92-P50 | Q106: =Q92-Q50 | R106: =SUM(L106:Q106) | S106: =S92-S50 | T106: =T92-T50 | U106: =U92-U50 | V106: =V92-V50 | W106: =W92-W50 | X106: =X92-X50 | Y106: =Y92-Y50
C107: 0911 集計 | D107: 川邊主任 | E107: =E93-E51 | F107: =F93-F51 | G107: =G93-G51 | H107: =H93-H51 | I107: =I93-I51 | J107: =J93-J51 | K107: =SUM(E107:J107) | L107: =L93-L51 | M107: =M93-M51 | N107: =N93-N51 | O107: =O93-O51 | P107: =P93-P51 | Q107: =Q93-Q51 | R107: =SUM(L107:Q107) | S107: =S93-S51 | T107: =T93-T51 | U107: =U93-U51 | V107: =V93-V51 | W107: =W93-W51 | X107: =X93-X51 | Y107: =Y93-Y51
...

Sheet 全体
C1: 境港営業所全体
C2: 1．2024年
E3: 売上 | L3: 粗利益 | S3: 粗利益率
E4: 45383 | F4: 45413 | G4: 45444 | H4: 45474 | I4: 45505 | J4: 45536 | K4: 合計 | L4: 45383 | M4: 45413 | N4: 45444 | O4: 45474 | P4: 45505 | Q4: 45536 | R4: 合計 | S4: 45383 | T4: 45413 | U4: 45444 | V4: 45474 | W4: 45505 | X4: 45536 | Y4: 合計
C5: 0903 集計 | D5: 西岡 | E5: 2992.321 | F5: 1870.416 | G5: 2624.67 | H5: 2506.235 | I5: 2707.683 | J5: 4067.607 | K5: =SUM(E5:J5) | L5: 548.984 | M5: 363.353 | N5: 510.638 | O5: 513.458 | P5: 563.279 | Q5: 811.5544 | R5: =SUM(L5:Q5) | S5: =IF(E5=0,"***",L5/E5) | T5: =IF(F5=0,"***",M5/F5) | U5: =IF(G5=0,"***",N5/G5) | V5: =IF(H5=0,"***",O5/H5) | W5: =IF(I5=0,"***",P5/I5) | X5: =IF(J5=0,"***",Q5/J5) | Y5: =IF(K5=0,"***",R5/K5)
C6: 0904 集計 | D6: 足立次長 | E6: 9457.609 | F6: 33342.444 | G6: 9536.075 | H6: 12322.971 | I6: 8433.195 | J6: 12377.608 | K6: =SUM(E6:J6) | L6: 2013.302 | M6: 6923.814 | N6: 1850.747 | O6: 2403.043 | P6: 1946.27 | Q6: 2430.328 | R6: =SUM(L6:Q6) | S6: =IF(E6=0,"***",L6/E6) | T6: =IF(F6=0,"***",M6/F6) | U6: =IF(G6=0,"***",N6/G6) | V6: =IF(H6=0,"***",O6/H6) | W6: =IF(I6=0,"***",P6/I6) | X6: =IF(J6=0,"***",Q6/J6) | Y6: =IF(K6=0,"***",R6/K6)
C7: 0909 集計 | D7: 藤波課長 | E7: 7831.518 | F7: 7149.748 | G7: 5762.823 | H7: 8011.724 | I7: 6436.908 | J7: 8821.121 | K7: =SUM(E7:J7) | L7: 1249.792 | M7: 1193.97 | N7: 1008.843 | O7: 1465.948 | P7: 1134.483 | Q7: 1613.746 | R7: =SUM(L7:Q7) | S7: =IF(E7=0,"***",L7/E7) | T7: =IF(F7=0,"***",M7/F7) | U7: =IF(G7=0,"***",N7/G7) | V7: =IF(H7=0,"***",O7/H7) | W7: =IF(I7=0,"***",P7/I7) | X7: =IF(J7=0,"***",Q7/J7) | Y7: =IF(K7=0,"***",R7/K7)
C8: 0910 集計 | D8: 足立課長 | E8: 8439.824 | F8: 1787.369 | G8: 1386.514 | K8: =SUM(E8:J8) | L8: 1598.596 | M8: 276.611 | N8: 246.168 | R8: =SUM(L8:Q8) | S8: =IF(E8=0,"***",L8/E8) | T8: =IF(F8=0,"***",M8/F8) | U8: =IF(G8=0,"***",N8/G8) | V8: =IF(H8=0,"***",O8/H8) | W8: =IF(I8=0,"***",P8/I8) | X8: =IF(J8=0,"***",Q8/J8) | Y8: =IF(K8=0,"***",R8/K8)
C9: 0911 集計 | D9: 川邊主任 | E9: 9628.221 | F9: 8898.137 | G9: 8938.893 | H9: 8453.326 | I9: 8467.791 | J9: 9049.48 | K9: =SUM(E9:J9) | L9: 1562.079 | M9: 1570.745 | N9: 1489.311 | O9: 1463.971 | P9: 1504.084 | Q9: 1448.511 | R9: =SUM(L9:Q9) | S9: =IF(E9=0,"***",L9/E9) | T9: =IF(F9=0,"***",M9/F9) | U9: =IF(G9=0,"***",N9/G9) | V9: =IF(H9=0,"***",O9/H9) | W9: =IF(I9=0,"***",P9/I9) | X9: =IF(J9=0,"***",Q9/J9) | Y9: =IF(K9=0,"***",R9/K9)
C10: 0914 集計 | D10: 白根主任 | E10: 8795.503 | F10: 11637.292 | G10: 9494.164 | H10: 10083.54 | I10: 18835.421 | J10: 25101.073 | K10: =SUM(E10:J10) | L10: 1505.568 | M10: 1605.192 | N10: 1706.263 | O10: 1787.849 | P10: 4384.14 | Q10: 5731.302 | R10: =SUM(L10:Q10) | S10: =IF(E10=0,"***",L10/E10) | T10: =IF(F10=0,"***",M10/F10) | U10: =IF(G10=0,"***",N10/G10) | V10: =IF(H10=0,"***",O10/H10) | W10: =IF(I10=0,"***",P10/I10) | X10: =IF(J10=0,"***",Q10/J10) | Y10: =IF(K10=0,"***",R10/K10)
C11: 0918 集計 | D11: 海外 | E11: 462.725 | F11: 2599.656 | G11: 378.6 | H11: 1452.4 | I11: 232.15 | J11: 3240.614 | K11: =SUM(E11:J11) | L11: 127.104 | M11: 474.93 | N11: 89.88 | O11: 218.502 | P11: 73.45 | Q11: 653.405 | R11: =SUM(L11:Q11) | S11: =IF(E11=0,"***",L11/E11) | T11: =IF(F11=0,"***",M11/F11) | U11: =IF(G11=0,"***",N11/G11) | V11: =IF(H11=0,"***",O11/H11) | W11: =IF(I11=0,"***",P11/I11) | X11: =IF(J11=0,"***",Q11/J11) | Y11: =IF(K11=0,"***",R11/K11)
C12: 0919 集計 | D12: その他 | E12: 25.21 | F12: 37.986 | G12: 27.305 | H12: 17.22 | I12: 39.025 | J12: 44.165 | K12: =SUM(E12:J12) | L12: 5.949 | M12: 8.269 | N12: 6.925 | O12: 2.97 | P12: 6.325 | Q12: 12.399 | R12: =SUM(L12:Q12) | S12: =IF(E12=0,"***",L12/E12) | T12: =IF(F12=0,"***",M12/F12) | U12: =IF(G12=0,"***",N12/G12) | V12: =IF(H12=0,"***",O12/H12) | W12: =IF(I12=0,"***",P12/I12) | X12: =IF(J12=0,"***",Q12/J12) | Y12: =IF(K12=0,"***",R12/K12)
C13: 0930 集計 | D13: 自治体 | E13: 0 | F13: 0 | G13: 56.54 | H13: 0 | I13: 0 | J13: 0 | K13: =SUM(E13:J13) | L13: 0 | M13: 0 | N13: 1.751 | O13: 0 | P13: 0 | Q13: 0 | R13: =SUM(L13:Q13) | S13: =IF(E13=0,"***",L13/E13) | T13: =IF(F13=0,"***",M13/F13) | U13: =IF(G13=0,"***",N13/G13) | V13: =IF(H13=0,"***",O13/H13) | W13: =IF(I13=0,"***",P13/I13) | X13: =IF(J13=0,"***",Q13/J13) | Y13: =IF(K13=0,"***",R13/K13)
C14: 合計 | E14: =SUM(E5:E13) | F14: =SUM(F5:F13) | G14: =SUM(G5:G13) | H14: =SUM(H5:H13) | I14: =SUM(I5:I13) | J14: =SUM(J5:J13) | K14: =SUM(K5:K13) | L14: =SUM(L5:L13) | ... R14: =SUM(R5:R13) | S14: =IF(E14=0,"***",L14/E14) | T14: =IF(F14=0,"***",M14/F14) | U14: =IF(G14=0,"***",N14/G14) | V14: =IF(H14=0,"***",O14/H14) | W14: =IF(I14=0,"***",P14/I14) | X14: =IF(J14=0,"***",Q14/J14) | Y14: =IF(K14=0,"***",R14/K14)
C16: 2．2025年
E17: 売上 | L17: 粗利益 | S17: 粗利益率
E18: 45748 | F18: 45778 | G18: 45809 | H18: 45839 | I18: 45870 | J18: 45901 | K18: 合計 | L18: 45748 | M18: 45778 | N18: 45809 | O18: 45839 | P18: 45870 | Q18: 45901 | R18: 合計 | S18: 45748 | T18: 45778 | U18: 45809 | V18: 45839 | W18: 45870 | X18: 45901 | Y18: 合計
C19: 0903 集計 | D19: 西岡 | E19: 2842.845 | F19: 1782.782 | G19: 2650.612 | H19: 2128.284 | I19: 1678.593 | J19: 3222.317 | K19: =SUM(E19:J19) | L19: 549.261 | M19: 400.415 | N19: 592.779 | O19: 470.908 | P19: 329.85 | Q19: 643.129 | R19: =SUM(L19:Q19) | S19: =IF(E19=0,"***",L19/E19) | T19: =IF(F19=0,"***",M19/F19) | U19: =IF(G19=0,"***",N19/G19) | V19: =IF(H19=0,"***",O19/H19) | W19: =IF(I19=0,"***",P19/I19) | X19: =IF(J19=0,"***",Q19/J19) | Y19: =IF(K19=0,"***",R19/K19)
C20: 0904 集計 | D20: 足立次長 | E20: 11862.965 | F20: 11689.497 | G20: 7550.568 | H20: 13687.464 | I20: 94774.135 | J20: 40900.174 | K20: =SUM(E20:J20) | L20: 2574.856 | M20: 2531.644 | N20: 1747.441 | O20: 2580.203 | P20: 16143.789 | Q20: 9365.84 | R20: =SUM(L20:Q20) | S20: =IF(E20=0,"***",L20/E20) | T20: =IF(F20=0,"***",M20/F20) | U20: =IF(G20=0,"***",N20/G20) | V20: =IF(H20=0,"***",O20/H20) | W20: =IF(I20=0,"***",P20/I20) | X20: =IF(J20=0,"***",Q20/J20) | Y20: =IF(K20=0,"***",R20/K20)
C21: 0909 集計 | D21: 藤波課長 | E21: 7842.768 | F21: 5683.808 | G21: 6360.448 | H21: 12802.674 | I21: 10570.955 | J21: 12015.35 | K21: =SUM(E21:J21) | L21: 1363.778 | M21: 1061.963 | N21: 1284.442 | O21: 2847.084 | P21: 2207.566 | Q21: 2274.845 | R21: =SUM(L21:Q21) | S21: =IF(E21=0,"***",L21/E21) | T21: =IF(F21=0,"***",M21/F21) | U21: =IF(G21=0,"***",N21/G21) | V21: =IF(H21=0,"***",O21/H21) | W21: =IF(I21=0,"***",P21/I21) | X21: =IF(J21=0,"***",Q21/J21) | Y21: =IF(K21=0,"***",R21/K21)
C22: 0910 集計 | D22: 足立課長 | E22: 2264.573 | F22: 1770.147 | G22: 1664.316 | K22: =SUM(E22:J22) | L22: 450.801 | M22: 345.224 | N22: 314.771 | R22: =SUM(L22:Q22) | S22: =IF(E22=0,"***",L22/E22) | T22: =IF(F22=0,"***",M22/F22) | U22: =IF(G22=0,"***",N22/G22) | V22: =IF(H22=0,"***",O22/H22) | W22: =IF(I22=0,"***",P22/I22) | X22: =IF(J22=0,"***",Q22/J22) | Y22: =IF(K22=0,"***",R22/K22)
C23: 0911 集計 | D23: 川邊主任 | E23: 10963.509 | F23: 10807.006 | G23: 7331.919 | H23: 10739.124 | I23: 6927.711 | J23: 9685.745 | K23: =SUM(E23:J23) | L23: 1855.471 | M23: 1855.43 | N23: 1341.294 | O23: 1734.601 | P23: 1138.342 | Q23: 1483.015 | R23: =SUM(L23:Q23) | S23: =IF(E23=0,"***",L23/E23) | T23: =IF(F23=0,"***",M23/F23) | U23: =IF(G23=0,"***",N23/G23) | V23: =IF(H23=0,"***",O23/H23) | W23: =IF(I23=0,"***",P23/I23) | X23: =IF(J23=0,"***",Q23/J23) | Y23: =IF(K23=0,"***",R23/K23)
C24: 0914 集計 | D24: 白根主任 | E24: 8829.619 | F24: 8702.497 | G24: 13277.306 | H24: 11551.865 | I24: 8043.705 | J24: 22830.648 | K24: =SUM(E24:J24) | L24: 1721.514 | M24: 1717.424 | N24: 2915.928 | O24: 2832.065 | P24: 1698.655 | Q24: 5392.991 | R24: =SUM(L24:Q24) | S24: =IF(E24=0,"***",L24/E24) | T24: =IF(F24=0,"***",M24/F24) | U24: =IF(G24=0,"***",N24/G24) | V24: =IF(H24=0,"***",O24/H24) | W24: =IF(I24=0,"***",P24/I24) | X24: =IF(J24=0,"***",Q24/J24) | Y24: =IF(K24=0,"***",R24/K24)
C25: 0918 集計 | D25: 海外 | E25: 1833.894 | F25: 2423.2 | G25: 1376.87 | H25: 604.22 | I25: 21.15 | J25: 693.45 | K25: =SUM(E25:J25) | L25: 326.979 | M25: 339.583 | N25: 289.41 | O25: 117.704 | P25: 5.8 | Q25: 204.995 | R25: =SUM(L25:Q25) | S25: =IF(E25=0,"***",L25/E25) | T25: =IF(F25=0,"***",M25/F25) | U25: =IF(G25=0,"***",N25/G25) | V25: =IF(H25=0,"***",O25/H25) | W25: =IF(I25=0,"***",P25/I25) | X25: =IF(J25=0,"***",Q25/J25) | Y25: =IF(K25=0,"***",R25/K25)
C26: 0919 集計 | D26: その他 | E26: 33.365 | F26: 30.73 | G26: 37.726 | H26: 17.86 | I26: 32.296 | J26: 30.7 | K26: =SUM(E26:J26) | L26: 6.939 | M26: 6.67 | N26: 7.436 | O26: 3 | P26: 8.956 | Q26: 6.12 | R26: =SUM(L26:Q26) | S26: =IF(E26=0,"***",L26/E26) | T26: =IF(F26=0,"***",M26/F26) | U26: =IF(G26=0,"***",N26/G26) | V26: =IF(H26=0,"***",O26/H26) | W26: =IF(I26=0,"***",P26/I26) | X26: =IF(J26=0,"***",Q26/J26) | Y26: =IF(K26=0,"***",R26/K26)
C27: 0930 集計 | D27: 自治体 | E27: 0 | F27: 87.14 | G27: 0 | H27: 0 | I27: 0 | J27: 0 | K27: =SUM(E27:J27) | L27: 0 | M27: 4.893 | N27: 0 | O27: 0 | P27: 0 | Q27: 0 | R27: =SUM(L27:Q27) | S27: =IF(E27=0,"***",L27/E27) | T27: =IF(F27=0,"***",M27/F27) | U27: =IF(G27=0,"***",N27/G27) | V27: =IF(H27=0,"***",O27/H27) | W27: =IF(I27=0,"***",P27/I27) | X27: =IF(J27=0,"***",Q27/J27) | Y27: =IF(K27=0,"***",R27/K27)
C28: 合計 | E28: =SUM(E19:E27) | F28: =SUM(F19:F27) | G28: =SUM(G19:G27) | H28: =SUM(H19:H27) | I28: =SUM(I19:I27) | J28: =SUM(J19:J27) | K28: =SUM(K19:K27) | L28: =SUM(L19:L27) | ... R28: =SUM(R19:R27) | S28: =IF(E28=0,"***",L28/E28) | T28: =IF(F28=0,"***",M28/F28) | U28: =IF(G28=0,"***",N28/G28) | V28: =IF(H28=0,"***",O28/H28) | W28: =IF(I28=0,"***",P28/I28) | X28: =IF(J28=0,"***",Q28/J28) | Y28: =IF(K28=0,"***",R28/K28)
C30: 3．過年度平均
E31: 売上 | L31: 粗利益 | S31: 粗利益率
E32: 45748 | F32: 45778 | G32: 45809 | H32: 45839 | I32: 45870 | J32: 45901 | K32: 合計 | L32: 45748 | M32: 45778 | N32: 45809 | O32: 45839 | P32: 45870 | Q32: 45901 | R32: 合計 | S32: 45748 | T32: 45778 | U32: 45809 | V32: 45839 | W32: 45870 | X32: 45901 | Y32: 合計
C33: 0903 集計 | D33: 西岡 | E33: =(E19+E5)/2 | F33: =(F19+F5)/2 | G33: =(G19+G5)/2 | H33: =(H19+H5)/2 | I33: =(I19+I5)/2 | J33: =(J19+J5)/2 | K33: =SUM(E33:J33) | L33: =(L19+L5)/2 | M33: =(M19+M5)/2 | N33: =(N19+N5)/2 | O33: =(O19+O5)/2 | P33: =(P19+P5)/2 | Q33: =(Q19+Q5)/2 | R33: =SUM(L33:Q33) | S33: =IF(E33=0,"***",L33/E33) | T33: =IF(F33=0,"***",M33/F33) | U33: =IF(G33=0,"***",N33/G33) | V33: =IF(H33=0,"***",O33/H33) | W33: =IF(I33=0,"***",P33/I33) | X33: =IF(J33=0,"***",Q33/J33) | Y33: =IF(K33=0,"***",R33/K33)
C34: 0904 集計 | D34: 足立次長 | E34: =(E20+E6)/2 | F34: =(F20+F6)/2 | G34: =(G20+G6)/2 | H34: =(H20+H6)/2 | I34: =(I20+I6)/2 | J34: =(J20+J6)/2 | K34: =SUM(E34:J34) | L34: =(L20+L6)/2 | M34: =(M20+M6)/2 | N34: =(N20+N6)/2 | O34: =(O20+O6)/2 | P34: =(P20+P6)/2 | Q34: =(Q20+Q6)/2 | R34: =SUM(L34:Q34) | S34: =IF(E34=0,"***",L34/E34) | T34: =IF(F34=0,"***",M34/F34) | U34: =IF(G34=0,"***",N34/G34) | V34: =IF(H34=0,"***",O34/H34) | W34: =IF(I34=0,"***",P34/I34) | X34: =IF(J34=0,"***",Q34/J34) | Y34: =IF(K34=0,"***",R34/K34)
C35: 0909 集計 | D35: 藤波課長 | E35: =(E21+E7)/2 | F35: =(F21+F7)/2 | G35: =(G21+G7)/2 | H35: =(H21+H7)/2 | I35: =(I21+I7)/2 | J35: =(J21+J7)/2 | K35: =SUM(E35:J35) | L35: =(L21+L7)/2 | M35: =(M21+M7)/2 | N35: =(N21+N7)/2 | O35: =(O21+O7)/2 | P35: =(P21+P7)/2 | Q35: =(Q21+Q7)/2 | R35: =SUM(L35:Q35) | S35: =IF(E35=0,"***",L35/E35) | T35: =IF(F35=0,"***",M35/F35) | U35: =IF(G35=0,"***",N35/G35) | V35: =IF(H35=0,"***",O35/H35) | W35: =IF(I35=0,"***",P35/I35) | X35: =IF(J35=0,"***",Q35/J35) | Y35: =IF(K35=0,"***",R35/K35)
C36: 0910 集計 | D36: 足立課長 | E36: =(E22+E8)/2 | F36: =(F22+F8)/2 | G36: =(G22+G8)/2 | H36: =(H22+H8)/2 | I36: =(I22+I8)/2 | J36: =(J22+J8)/2 | K36: =SUM(E36:J36) | L36: =(L22+L8)/2 | M36: =(M22+M8)/2 | N36: =(N22+N8)/2 | O36: =(O22+O8)/2 | P36: =(P22+P8)/2 | Q36: =(Q22+Q8)/2 | R36: =SUM(L36:Q36) | S36: =IF(E36=0,"***",L36/E36) | T36: =IF(F36=0,"***",M36/F36) | U36: =IF(G36=0,"***",N36/G36) | V36: =IF(H36=0,"***",O36/H36) | W36: =IF(I36=0,"***",P36/I36) | X36: =IF(J36=0,"***",Q36/J36) | Y36: =IF(K36=0,"***",R36/K36)
C37: 0911 集計 | D37: 川邊主任 | E37: =(E23+E9)/2 | F37: =(F23+F9)/2 | G37: =(G23+G9)/2 | H37: =(H23+H9)/2 | I37: =(I23+I9)/2 | J37: =(J23+J9)/2 | K37: =SUM(E37:J37) | L37: =(L23+L9)/2 | M37: =(M23+M9)/2 | N37: =(N23+N9)/2 | O37: =(O23+O9)/2 | P37: =(P23+P9)/2 | Q37: =(Q23+Q9)/2 | R37: =SUM(L37:Q37) | S37: =IF(E37=0,"***",L37/E37) | T37: =IF(F37=0,"***",M37/F37) | U37: =IF(G37=0,"***",N37/G37) | V37: =IF(H37=0,"***",O37/H37) | W37: =IF(I37=0,"***",P37/I37) | X37: =IF(J37=0,"***",Q37/J37) | Y37: =IF(K37=0,"***",R37/K37)
C38: 0914 集計 | D38: 白根主任 | E38: =(E24+E10)/2 | F38: =(F24+F10)/2 | G38: =(G24+G10)/2 | H38: =(H24+H10)/2 | I38: =(I24+I10)/2 | J38: =(J24+J10)/2 | K38: =SUM(E38:J38) | L38: =(L24+L10)/2 | M38: =(M24+M10)/2 | N38: =(N24+N10)/2 | O38: =(O24+O10)/2 | P38: =(P24+P10)/2 | Q38: =(Q24+Q10)/2 | R38: =SUM(L38:Q38) | S38: =IF(E38=0,"***",L38/E38) | T38: =IF(F38=0,"***",M38/F38) | U38: =IF(G38=0,"***",N38/G38) | V38: =IF(H38=0,"***",O38/H38) | W38: =IF(I38=0,"***",P38/I38) | X38: =IF(J38=0,"***",Q38/J38) | Y38: =IF(K38=0,"***",R38/K38)
C39: 0918 集計 | D39: 海外 | E39: =(E25+E11)/2 | F39: =(F25+F11)/2 | G39: =(G25+G11)/2 | H39: =(H25+H11)/2 | I39: =(I25+I11)/2 | J39: =(J25+J11)/2 | K39: =SUM(E39:J39) | L39: =(L25+L11)/2 | M39: =(M25+M11)/2 | N39: =(N25+N11)/2 | O39: =(O25+O11)/2 | P39: =(P25+P11)/2 | Q39: =(Q25+Q11)/2 | R39: =SUM(L39:Q39) | S39: =IF(E39=0,"***",L39/E39) | T39: =IF(F39=0,"***",M39/F39) | U39: =IF(G39=0,"***",N39/G39) | V39: =IF(H39=0,"***",O39/H39) | W39: =IF(I39=0,"***",P39/I39) | X39: =IF(J39=0,"***",Q39/J39) | Y39: =IF(K39=0,"***",R39/K39)
C40: 0919 集計 | D40: その他 | E40: =(E26+E12)/2 | F40: =(F26+F12)/2 | G40: =(G26+G12)/2 | H40: =(H26+H12)/2 | I40: =(I26+I12)/2 | J40: =(J26+J12)/2 | K40: =SUM(E40:J40) | L40: =(L26+L12)/2 | M40: =(M26+M12)/2 | N40: =(N26+N12)/2 | O40: =(O26+O12)/2 | P40: =(P26+P12)/2 | Q40: =(Q26+Q12)/2 | R40: =SUM(L40:Q40) | S40: =IF(E40=0,"***",L40/E40) | T40: =IF(F40=0,"***",M40/F40) | U40: =IF(G40=0,"***",N40/G40) | V40: =IF(H40=0,"***",O40/H40) | W40: =IF(I40=0,"***",P40/I40) | X40: =IF(J40=0,"***",Q40/J40) | Y40: =IF(K40=0,"***",R40/K40)
C41: 0930 集計 | D41: 自治体 | E41: =(E27+E13)/2 | F41: =(F27+F13)/2 | G41: =(G27+G13)/2 | H41: =(H27+H13)/2 | I41: =(I27+I13)/2 | J41: =(J27+J13)/2 | K41: =SUM(E41:J41) | L41: =(L27+L13)/2 | M41: =(M27+M13)/2 | N41: =(N27+N13)/2 | O41: =(O27+O13)/2 | P41: =(P27+P13)/2 | Q41: =(Q27+Q13)/2 | R41: =SUM(L41:Q41) | S41: =IF(E41=0,"***",L41/E41) | T41: =IF(F41=0,"***",M41/F41) | U41: =IF(G41=0,"***",N41/G41) | V41: =IF(H41=0,"***",O41/H41) | W41: =IF(I41=0,"***",P41/I41) | X41: =IF(J41=0,"***",Q41/J41) | Y41: =IF(K41=0,"***",R41/K41)
C42: 合計 | E42: =SUM(E33:E41) | F42: =SUM(F33:F41) | G42: =SUM(G33:G41) | H42: =SUM(H33:H41) | I42: =SUM(I33:I41) | J42: =SUM(J33:J41) | K42: =SUM(K33:K41) | L42: =SUM(L33:L41) | ... R42: =SUM(R33:R41) | S42: =IF(E42=0,"***",L42/E42) | T42: =IF(F42=0,"***",M42/F42) | U42: =IF(G42=0,"***",N42/G42) | V42: =IF(H42=0,"***",O42/H42) | W42: =IF(I42=0,"***",P42/I42) | X42: =IF(J42=0,"***",Q42/J42) | Y42: =IF(K42=0,"***",R42/K42)
C44: 4．計画
E45: 売上 | L45: 粗利益 | S45: 粗利益率
E46: 46113 | F46: 46143 | G46: 46174 | H46: 46204 | I46: 46235 | J46: 46266 | K46: 合計 | L46: 46113 | M46: 46143 | N46: 46174 | O46: 46204 | P46: 46235 | Q46: 46266 | R46: 合計 | S46: 46113 | T46: 46143 | U46: 46174 | V46: 46204 | W46: 46235 | X46: 46266 | Y46: 合計
C47: 0903 集計 | D47: 西岡 | E47: =包装資材!E47+機械!E47 | F47: =包装資材!F47+機械!F47 | G47: =包装資材!G47+機械!G47 | H47: =包装資材!H47+機械!H47 | I47: =包装資材!I47+機械!I47 | J47: =包装資材!J47+機械!J47 | K47: =SUM(E47:J47) | L47: =包装資材!L47+機械!L47 | M47: =包装資材!M47+機械!M47 | N47: =包装資材!N47+機械!N47 | O47: =包装資材!O47+機械!O47 | P47: =包装資材!P47+機械!P47 | Q47: =包装資材!Q47+機械!Q47 | R47: =SUM(L47:Q47) | S47: =IF(E47=0,"***",L47/E47) | T47: =IF(F47=0,"***",M47/F47) | U47: =IF(G47=0,"***",N47/G47) | V47: =IF(H47=0,"***",O47/H47) | W47: =IF(I47=0,"***",P47/I47) | X47: =IF(J47=0,"***",Q47/J47) | Y47: =IF(K47=0,"***",R47/K47)
C48: 0904 集計 | D48: 足立次長 | E48: =包装資材!E48+機械!E48 | F48: =包装資材!F48+機械!F48 | G48: =包装資材!G48+機械!G48 | H48: =包装資材!H48+機械!H48 | I48: =包装資材!I48+機械!I48 | J48: =包装資材!J48+機械!J48 | K48: =SUM(E48:J48) | L48: =包装資材!L48+機械!L48 | M48: =包装資材!M48+機械!M48 | N48: =包装資材!N48+機械!N48 | O48: =包装資材!O48+機械!O48 | P48: =包装資材!P48+機械!P48 | Q48: =包装資材!Q48+機械!Q48 | R48: =SUM(L48:Q48) | S48: =IF(E48=0,"***",L48/E48) | T48: =IF(F48=0,"***",M48/F48) | U48: =IF(G48=0,"***",N48/G48) | V48: =IF(H48=0,"***",O48/H48) | W48: =IF(I48=0,"***",P48/I48) | X48: =IF(J48=0,"***",Q48/J48) | Y48: =IF(K48=0,"***",R48/K48)
C49: 0909 集計 | D49: 藤波課長 | E49: =包装資材!E49+機械!E49 | F49: =包装資材!F49+機械!F49 | G49: =包装資材!G49+機械!G49 | H49: =包装資材!H49+機械!H49 | I49: =包装資材!I49+機械!I49 | J49: =包装資材!J49+機械!J49 | K49: =SUM(E49:J49) | L49: =包装資材!L49+機械!L49 | M49: =包装資材!M49+機械!M49 | N49: =包装資材!N49+機械!N49 | O49: =包装資材!O49+機械!O49 | P49: =包装資材!P49+機械!P49 | Q49: =包装資材!Q49+機械!Q49 | R49: =SUM(L49:Q49) | S49: =IF(E49=0,"***",L49/E49) | T49: =IF(F49=0,"***",M49/F49) | U49: =IF(G49=0,"***",N49/G49) | V49: =IF(H49=0,"***",O49/H49) | W49: =IF(I49=0,"***",P49/I49) | X49: =IF(J49=0,"***",Q49/J49) | Y49: =IF(K49=0,"***",R49/K49)
C50: 0910 集計 | D50: 足立課長 | E50: =包装資材!E50+機械!E50 | F50: =包装資材!F50+機械!F50 | G50: =包装資材!G50+機械!G50 | H50: =包装資材!H50+機械!H50 | I50: =包装資材!I50+機械!I50 | J50: =包装資材!J50+機械!J50 | K50: =SUM(E50:J50) | L50: =包装資材!L50+機械!L50 | M50: =包装資材!M50+機械!M50 | N50: =包装資材!N50+機械!N50 | O50: =包装資材!O50+機械!O50 | P50: =包装資材!P50+機械!P50 | Q50: =包装資材!Q50+機械!Q50 | R50: =SUM(L50:Q50) | S50: =IF(E50=0,"***",L50/E50) | T50: =IF(F50=0,"***",M50/F50) | U50: =IF(G50=0,"***",N50/G50) | V50: =IF(H50=0,"***",O50/H50) | W50: =IF(I50=0,"***",P50/I50) | X50: =IF(J50=0,"***",Q50/J50) | Y50: =IF(K50=0,"***",R50/K50)
C51: 0911 集計 | D51: 川邊主任 | E51: =包装資材!E51+機械!E51 | F51: =包装資材!F51+機械!F51 | G51: =包装資材!G51+機械!G51 | H51: =包装資材!H51+機械!H51 | I51: =包装資材!I51+機械!I51 | J51: =包装資材!J51+機械!J51 | K51: =SUM(E51:J51) | L51: =包装資材!L51+機械!L51 | M51: =包装資材!M51+機械!M51 | N51: =包装資材!N51+機械!N51 | O51: =包装資材!O51+機械!O51 | P51: =包装資材!P51+機械!P51 | Q51: =包装資材!Q51+機械!Q51 | R51: =SUM(L51:Q51) | S51: =IF(E51=0,"***",L51/E51) | T51: =IF(F51=0,"***",M51/F51) | U51: =IF(G51=0,"***",N51/G51) | V51: =IF(H51=0,"***",O51/H51) | W51: =IF(I51=0,"***",P51/I51) | X51: =IF(J51=0,"***",Q51/J51) | Y51: =IF(K51=0,"***",R51/K51)
C52: 0914 集計 | D52: 白根主任 | E52: =包装資材!E52+機械!E52 | F52: =包装資材!F52+機械!F52 | G52: =包装資材!G52+機械!G52 | H52: =包装資材!H52+機械!H52 | I52: =包装資材!I52+機械!I52 | J52: =包装資材!J52+機械!J52 | K52: =SUM(E52:J52) | L52: =包装資材!L52+機械!L52 | M52: =包装資材!M52+機械!M52 | N52: =包装資材!N52+機械!N52 | O52: =包装資材!O52+機械!O52 | P52: =包装資材!P52+機械!P52 | Q52: =包装資材!Q52+機械!Q52 | R52: =SUM(L52:Q52) | S52: =IF(E52=0,"***",L52/E52) | T52: =IF(F52=0,"***",M52/F52) | U52: =IF(G52=0,"***",N52/G52) | V52: =IF(H52=0,"***",O52/H52) | W52: =IF(I52=0,"***",P52/I52) | X52: =IF(J52=0,"***",Q52/J52) | Y52: =IF(K52=0,"***",R52/K52)
C53: 0918 集計 | D53: 海外 | E53: =包装資材!E53+機械!E53 | F53: =包装資材!F53+機械!F53 | G53: =包装資材!G53+機械!G53 | H53: =包装資材!H53+機械!H53 | I53: =包装資材!I53+機械!I53 | J53: =包装資材!J53+機械!J53 | K53: =SUM(E53:J53) | L53: =包装資材!L53+機械!L53 | M53: =包装資材!M53+機械!M53 | N53: =包装資材!N53+機械!N53 | O53: =包装資材!O53+機械!O53 | P53: =包装資材!P53+機械!P53 | Q53: =包装資材!Q53+機械!Q53 | R53: =SUM(L53:Q53) | S53: =IF(E53=0,"***",L53/E53) | T53: =IF(F53=0,"***",M53/F53) | U53: =IF(G53=0,"***",N53/G53) | V53: =IF(H53=0,"***",O53/H53) | W53: =IF(I53=0,"***",P53/I53) | X53: =IF(J53=0,"***",Q53/J53) | Y53: =IF(K53=0,"***",R53/K53)
C54: 0919 集計 | D54: その他 | E54: =包装資材!E54+機械!E54 | F54: =包装資材!F54+機械!F54 | G54: =包装資材!G54+機械!G54 | H54: =包装資材!H54+機械!H54 | I54: =包装資材!I54+機械!I54 | J54: =包装資材!J54+機械!J54 | K54: =SUM(E54:J54) | L54: =包装資材!L54+機械!L54 | M54: =包装資材!M54+機械!M54 | N54: =包装資材!N54+機械!N54 | O54: =包装資材!O54+機械!O54 | P54: =包装資材!P54+機械!P54 | Q54: =包装資材!Q54+機械!Q54 | R54: =SUM(L54:Q54) | S54: =IF(E54=0,"***",L54/E54) | T54: =IF(F54=0,"***",M54/F54) | U54: =IF(G54=0,"***",N54/G54) | V54: =IF(H54=0,"***",O54/H54) | W54: =IF(I54=0,"***",P54/I54) | X54: =IF(J54=0,"***",Q54/J54) | Y54: =IF(K54=0,"***",R54/K54)
C55: 0930 集計 | D55: 自治体 | E55: =包装資材!E55+機械!E55 | F55: =包装資材!F55+機械!F55 | G55: =包装資材!G55+機械!G55 | H55: =包装資材!H55+機械!H55 | I55: =包装資材!I55+機械!I55 | J55: =包装資材!J55+機械!J55 | K55: =SUM(E55:J55) | L55: =包装資材!L55+機械!L55 | M55: =包装資材!M55+機械!M55 | N55: =包装資材!N55+機械!N55 | O55: =包装資材!O55+機械!O55 | P55: =包装資材!P55+機械!P55 | Q55: =包装資材!Q55+機械!Q55 | R55: =SUM(L55:Q55)
C56: 合計 | E56: =SUM(E47:E55) | F56: =SUM(F47:F55) | G56: =SUM(G47:G55) | H56: =SUM(H47:H55) | I56: =SUM(I47:I55) | J56: =SUM(J47:J55) | K56: =SUM(K47:K55) | L56: =SUM(L47:L55) | ... R56: =SUM(R47:R55) | S56: =IF(E56=0,"***",L56/E56) | T56: =IF(F56=0,"***",M56/F56) | U56: =IF(G56=0,"***",N56/G56) | V56: =IF(H56=0,"***",O56/H56) | W56: =IF(I56=0,"***",P56/I56) | X56: =IF(J56=0,"***",Q56/J56) | Y56: =IF(K56=0,"***",R56/K56)
C58: ５．前期比
E59: 売上 | L59: 粗利益 | S59: 粗利益率
E60: 46113 | F60: 46143 | G60: 46174 | H60: 46204 | I60: 46235 | J60: 46266 | K60: 合計 | L60: 46113 | M60: 46143 | N60: 46174 | O60: 46204 | P60: 46235 | Q60: 46266 | R60: 合計 | S60: 46113 | T60: 46143 | U60: 46174 | V60: 46204 | W60: 46235 | X60: 46266 | Y60: 合計
C61: 0903 集計 | D61: 西岡 | E61: =E47-E19 | F61: =F47-F19 | G61: =G47-G19 | H61: =H47-H19 | I61: =I47-I19 | J61: =J47-J19 | K61: =SUM(E61:J61) | L61: =L47-L19 | M61: =M47-M19 | N61: =N47-N19 | O61: =O47-O19 | P61: =P47-P19 | Q61: =Q47-Q19 | R61: =SUM(L61:Q61) | S61: =S47-S19 | T61: =T47-T19 | U61: =U47-U19 | V61: =V47-V19 | W61: =W47-W19 | X61: =X47-X19 | Y61: =Y47-Y19
C62: 0904 集計 | D62: 足立次長 | E62: =E48-E20 | F62: =F48-F20 | G62: =G48-G20 | H62: =H48-H20 | I62: =I48-I20 | J62: =J48-J20 | K62: =SUM(E62:J62) | L62: =L48-L20 | M62: =M48-M20 | N62: =N48-N20 | O62: =O48-O20 | P62: =P48-P20 | Q62: =Q48-Q20 | R62: =SUM(L62:Q62) | S62: =S48-S20 | T62: =T48-T20 | U62: =U48-U20 | V62: =V48-V20 | W62: =W48-W20 | X62: =X48-X20 | Y62: =Y48-Y20
C63: 0909 集計 | D63: 藤波課長 | E63: =E49-E21 | F63: =F49-F21 | G63: =G49-G21 | H63: =H49-H21 | I63: =I49-I21 | J63: =J49-J21 | K63: =SUM(E63:J63) | L63: =L49-L21 | M63: =M49-M21 | N63: =N49-N21 | O63: =O49-O21 | P63: =P49-P21 | Q63: =Q49-Q21 | R63: =SUM(L63:Q63) | S63: =S49-S21 | T63: =T49-T21 | U63: =U49-U21 | V63: =V49-V21 | W63: =W49-W21 | X63: =X49-X21 | Y63: =Y49-Y21
C64: 0910 集計 | D64: 足立課長 | E64: =E50-E22 | F64: =F50-F22 | G64: =G50-G22 | H64: =H50-H22 | I64: =I50-I22 | J64: =J50-J22 | K64: =SUM(E64:J64) | L64: =L50-L22 | M64: =M50-M22 | N64: =N50-N22 | O64: =O50-O22 | P64: =P50-P22 | Q64: =Q50-Q22 | R64: =SUM(L64:Q64) | S64: =S50-S22 | T64: =T50-T22 | U64: =U50-U22 | V64: =V50-V22 | W64: =W50-W22 | X64: =X50-X22 | Y64: =Y50-Y22
C65: 0911 集計 | D65: 川邊主任 | E65: =E51-E23 | F65: =F51-F23 | G65: =G51-G23 | H65: =H51-H23 | I65: =I51-I23 | J65: =J51-J23 | K65: =SUM(E65:J65) | L65: =L51-L23 | M65: =M51-M23 | N65: =N51-N23 | O65: =O51-O23 | P65: =P51-P23 | Q65: =Q51-Q23 | R65: =SUM(L65:Q65) | S65: =S51-S23 | T65: =T51-T23 | U65: =U51-U23 | V65: =V51-V23 | W65: =W51-W23 | X65: =X51-X23 | Y65: =Y51-Y23
C66: 0914 集計 | D66: 白根主任 | E66: =E52-E24 | F66: =F52-F24 | G66: =G52-G24 | H66: =H52-H24 | I66: =I52-I24 | J66: =J52-J24 | K66: =SUM(E66:J66) | L66: =L52-L24 | M66: =M52-M24 | N66: =N52-N24 | O66: =O52-O24 | P66: =P52-P24 | Q66: =Q52-Q24 | R66: =SUM(L66:Q66) | S66: =S52-S24 | T66: =T52-T24 | U66: =U52-U24 | V66: =V52-V24 | W66: =W52-W24 | X66: =X52-X24 | Y66: =Y52-Y24
C67: 0918 集計 | D67: 海外 | E67: =E53-E25 | F67: =F53-F25 | G67: =G53-G25 | H67: =H53-H25 | I67: =I53-I25 | J67: =J53-J25 | K67: =SUM(E67:J67) | L67: =L53-L25 | M67: =M53-M25 | N67: =N53-N25 | O67: =O53-O25 | P67: =P53-P25 | Q67: =Q53-Q25 | R67: =SUM(L67:Q67) | S67: =S53-S25 | T67: =T53-T25 | U67: =U53-U25 | V67: =V53-V25 | W67: =W53-W25 | X67: =X53-X25 | Y67: =Y53-Y25
C68: 0919 集計 | D68: その他 | E68: =E54-E26 | F68: =F54-F26 | G68: =G54-G26 | H68: =H54-H26 | I68: =I54-I26 | J68: =J54-J26 | K68: =SUM(E68:J68) | L68: =L54-L26 | M68: =M54-M26 | N68: =N54-N26 | O68: =O54-O26 | P68: =P54-P26 | Q68: =Q54-Q26 | R68: =SUM(L68:Q68) | S68: =S54-S26 | T68: =T54-T26 | U68: =U54-U26 | V68: =V54-V26 | W68: =W54-W26 | X68: =X54-X26 | Y68: =Y54-Y26
C69: 0930 集計 | D69: 自治体 | E69: =E55-E27 | F69: =F55-F27 | G69: =G55-G27 | H69: =H55-H27 | I69: =I55-I27 | J69: =J55-J27 | K69: =SUM(E69:J69) | L69: =L55-L27 | M69: =M55-M27 | N69: =N55-N27 | O69: =O55-O27 | P69: =P55-P27 | Q69: =Q55-Q27 | R69: =SUM(L69:Q69) | S69: =S55-S27 | T69: =T55-T27 | U69: =U55-U27 | V69: =V55-V27 | W69: =W55-W27 | X69: =X55-X27 | Y69: =Y55-Y27
C70: 合計 | E70: =SUM(E61:E69) | F70: =SUM(F61:F69) | G70: =SUM(G61:G69) | H70: =SUM(H61:H69) | I70: =SUM(I61:I69) | J70: =SUM(J61:J69) | K70: =SUM(K61:K69) | L70: =SUM(L61:L69) | ... R70: =SUM(R61:R69) | S70: =S56-S28 | T70: =T56-T28 | U70: =U56-U28 | V70: =V56-V28 | W70: =W56-W28 | X70: =X56-X28 | Y70: =Y56-Y28
C72: 6．過年度平均比
E73: 売上 | L73: 粗利益 | S73: 粗利益率
E74: 46113 | F74: 46143 | G74: 46174 | H74: 46204 | I74: 46235 | J74: 46266 | K74: 合計 | L74: 46113 | M74: 46143 | N74: 46174 | O74: 46204 | P74: 46235 | Q74: 46266 | R74: 合計 | S74: 46113 | T74: 46143 | U74: 46174 | V74: 46204 | W74: 46235 | X74: 46266 | Y74: 合計
C75: 0903 集計 | D75: 西岡 | E75: =E47-E33 | F75: =F47-F33 | G75: =G47-G33 | H75: =H47-H33 | I75: =I47-I33 | J75: =J47-J33 | K75: =SUM(E75:J75) | L75: =L47-L33 | M75: =M47-M33 | N75: =N47-N33 | O75: =O47-O33 | P75: =P47-P33 | Q75: =Q47-Q33 | R75: =SUM(L75:Q75) | S75: =IF(E75=0,"***",L75/E75) | T75: =IF(F75=0,"***",M75/F75) | U75: =IF(G75=0,"***",N75/G75) | V75: =IF(H75=0,"***",O75/H75) | W75: =IF(I75=0,"***",P75/I75) | X75: =IF(J75=0,"***",Q75/J75) | Y75: =IF(K75=0,"***",R75/K75)
C76: 0904 集計 | D76: 足立次長 | E76: =E48-E34 | F76: =F48-F34 | G76: =G48-G34 | H76: =H48-H34 | I76: =I48-I34 | J76: =J48-J34 | K76: =SUM(E76:J76) | L76: =L48-L34 | M76: =M48-M34 | N76: =N48-N34 | O76: =O48-O34 | P76: =P48-P34 | Q76: =Q48-Q34 | R76: =SUM(L76:Q76) | S76: =IF(E76=0,"***",L76/E76) | T76: =IF(F76=0,"***",M76/F76) | U76: =IF(G76=0,"***",N76/G76) | V76: =IF(H76=0,"***",O76/H76) | W76: =IF(I76=0,"***",P76/I76) | X76: =IF(J76=0,"***",Q76/J76) | Y76: =IF(K76=0,"***",R76/K76)
C77: 0909 集計 | D77: 藤波課長 | E77: =E49-E35 | F77: =F49-F35 | G77: =G49-G35 | H77: =H49-H35 | I77: =I49-I35 | J77: =J49-J35 | K77: =SUM(E77:J77) | L77: =L49-L35 | M77: =M49-M35 | N77: =N49-N35 | O77: =O49-O35 | P77: =P49-P35 | Q77: =Q49-Q35 | R77: =SUM(L77:Q77) | S77: =IF(E77=0,"***",L77/E77) | T77: =IF(F77=0,"***",M77/F77) | U77: =IF(G77=0,"***",N77/G77) | V77: =IF(H77=0,"***",O77/H77) | W77: =IF(I77=0,"***",P77/I77) | X77: =IF(J77=0,"***",Q77/J77) | Y77: =IF(K77=0,"***",R77/K77)
C78: 0910 集計 | D78: 足立課長 | E78: =E50-E36 | F78: =F50-F36 | G78: =G50-G36 | H78: =H50-H36 | I78: =I50-I36 | J78: =J50-J36 | K78: =SUM(E78:J78) | L78: =L50-L36 | M78: =M50-M36 | N78: =N50-N36 | O78: =O50-O36 | P78: =P50-P36 | Q78: =Q50-Q36 | R78: =SUM(L78:Q78) | S78: =IF(E78=0,"***",L78/E78) | T78: =IF(F78=0,"***",M78/F78) | U78: =IF(G78=0,"***",N78/G78) | V78: =IF(H78=0,"***",O78/H78) | W78: =IF(I78=0,"***",P78/I78) | X78: =IF(J78=0,"***",Q78/J78) | Y78: =IF(K78=0,"***",R78/K78)
C79: 0911 集計 | D79: 川邊主任 | E79: =E51-E37 | F79: =F51-F37 | G79: =G51-G37 | H79: =H51-H37 | I79: =I51-I37 | J79: =J51-J37 | K79: =SUM(E79:J79) | L79: =L51-L37 | M79: =M51-M37 | N79: =N51-N37 | O79: =O51-O37 | P79: =P51-P37 | Q79: =Q51-Q37 | R79: =SUM(L79:Q79) | S79: =IF(E79=0,"***",L79/E79) | T79: =IF(F79=0,"***",M79/F79) | U79: =IF(G79=0,"***",N79/G79) | V79: =IF(H79=0,"***",O79/H79) | W79: =IF(I79=0,"***",P79/I79) | X79: =IF(J79=0,"***",Q79/J79) | Y79: =IF(K79=0,"***",R79/K79)
C80: 0914 集計 | D80: 白根主任 | E80: =E52-E38 | F80: =F52-F38 | G80: =G52-G38 | H80: =H52-H38 | I80: =I52-I38 | J80: =J52-J38 | K80: =SUM(E80:J80) | L80: =L52-L38 | M80: =M52-M38 | N80: =N52-N38 | O80: =O52-O38 | P80: =P52-P38 | Q80: =Q52-Q38 | R80: =SUM(L80:Q80) | S80: =IF(E80=0,"***",L80/E80) | T80: =IF(F80=0,"***",M80/F80) | U80: =IF(G80=0,"***",N80/G80) | V80: =IF(H80=0,"***",O80/H80) | W80: =IF(I80=0,"***",P80/I80) | X80: =IF(J80=0,"***",Q80/J80) | Y80: =IF(K80=0,"***",R80/K80)
C81: 0918 集計 | D81: 海外 | E81: =E53-E39 | F81: =F53-F39 | G81: =G53-G39 | H81: =H53-H39 | I81: =I53-I39 | J81: =J53-J39 | K81: =SUM(E81:J81) | L81: =L53-L39 | M81: =M53-M39 | N81: =N53-N39 | O81: =O53-O39 | P81: =P53-P39 | Q81: =Q53-Q39 | R81: =SUM(L81:Q81) | S81: =IF(E81=0,"***",L81/E81) | T81: =IF(F81=0,"***",M81/F81) | U81: =IF(G81=0,"***",N81/G81) | V81: =IF(H81=0,"***",O81/H81) | W81: =IF(I81=0,"***",P81/I81) | X81: =IF(J81=0,"***",Q81/J81) | Y81: =IF(K81=0,"***",R81/K81)
C82: 0919 集計 | D82: その他 | E82: =E54-E40 | F82: =F54-F40 | G82: =G54-G40 | H82: =H54-H40 | I82: =I54-I40 | J82: =J54-J40 | K82: =SUM(E82:J82) | L82: =L54-L40 | M82: =M54-M40 | N82: =N54-N40 | O82: =O54-O40 | P82: =P54-P40 | Q82: =Q54-Q40 | R82: =SUM(L82:Q82) | S82: =IF(E82=0,"***",L82/E82) | T82: =IF(F82=0,"***",M82/F82) | U82: =IF(G82=0,"***",N82/G82) | V82: =IF(H82=0,"***",O82/H82) | W82: =IF(I82=0,"***",P82/I82) | X82: =IF(J82=0,"***",Q82/J82) | Y82: =IF(K82=0,"***",R82/K82)
C83: 0930 集計 | D83: 自治体 | F83: =F55-F41 | G83: =G55-G41 | H83: =H55-H41 | I83: =I55-I41 | J83: =J55-J41 | K83: =SUM(E83:J83) | L83: =L55-L41 | M83: =M55-M41 | N83: =N55-N41 | O83: =O55-O41 | P83: =P55-P41 | Q83: =Q55-Q41 | R83: =SUM(L83:Q83) | S83: =IF(E83=0,"***",L83/E83) | T83: =IF(F83=0,"***",M83/F83) | U83: =IF(G83=0,"***",N83/G83) | V83: =IF(H83=0,"***",O83/H83) | W83: =IF(I83=0,"***",P83/I83) | X83: =IF(J83=0,"***",Q83/J83) | Y83: =IF(K83=0,"***",R83/K83)
C84: 合計 | E84: =SUM(E75:E83) | F84: =SUM(F75:F83) | G84: =SUM(G75:G83) | H84: =SUM(H75:H83) | I84: =SUM(I75:I83) | J84: =SUM(J75:J83) | K84: =SUM(K75:K83) | L84: =SUM(L75:L83) | ... R84: =SUM(R75:R83) | S84: =IF(E84=0,"***",L84/E84) | T84: =IF(F84=0,"***",M84/F84) | U84: =IF(G84=0,"***",N84/G84) | V84: =IF(H84=0,"***",O84/H84) | W84: =IF(I84=0,"***",P84/I84) | X84: =IF(J84=0,"***",Q84/J84) | Y84: =IF(K84=0,"***",R84/K84)
C86: 7．実績
E87: 売上 | L87: 粗利益 | S87: 粗利益率
E88: 46113 | F88: 46143 | G88: 46174 | H88: 46204 | I88: 46235 | J88: 46266 | K88: 合計 | L88: 46113 | M88: 46143 | N88: 46174 | O88: 46204 | P88: 46235 | Q88: 46266 | R88: 合計 | S88: 46113 | T88: 46143 | U88: 46174 | V88: 46204 | W88: 46235 | X88: 46266 | Y88: 合計
C89: 0903 集計 | D89: 西岡 | E89: 2546.443 | F89: 3731.251 | G89: 2209.745 | H89: 4001.158 | I89: 1726.807 | J89: 3718.586 | K89: =SUM(E89:J89) | L89: 520.126 | M89: 686.299 | N89: 427.57 | O89: 843.943 | P89: 465.365 | Q89: 883.3496 | R89: =SUM(L89:Q89) | S89: =IF(E89=0,"***",L89/E89) | T89: =IF(F89=0,"***",M89/F89) | U89: =IF(G89=0,"***",N89/G89) | V89: =IF(H89=0,"***",O89/H89) | W89: =IF(I89=0,"***",P89/I89) | X89: =IF(J89=0,"***",Q89/J89) | Y89: =IF(K89=0,"***",R89/K89)
C90: 0904 集計 | D90: 足立次長 | E90: 11819.231 | F90: 11379.324 | G90: 11256.487 | H90: 16574.086 | I90: 13005.837 | J90: 11997.104 | K90: =SUM(E90:J90) | L90: 2340.125 | M90: 2453.784 | N90: 2520.689 | O90: 3142.911 | P90: 2594.545 | Q90: 2485.751 | R90: =SUM(L90:Q90) | S90: =IF(E90=0,"***",L90/E90) | T90: =IF(F90=0,"***",M90/F90) | U90: =IF(G90=0,"***",N90/G90) | V90: =IF(H90=0,"***",O90/H90) | W90: =IF(I90=0,"***",P90/I90) | X90: =IF(J90=0,"***",Q90/J90) | Y90: =IF(K90=0,"***",R90/K90)
C91: 0909 集計 | D91: 藤波課長 | E91: 6431.527 | F91: 11141 | G91: 28205.688 | H91: 9716.294 | I91: 8694.421 | J91: 14951.556 | K91: =SUM(E91:J91) | L91: 1088.606 | M91: 2462 | N91: 6703.305 | O91: 1815.052 | P91: 1564.721 | Q91: 2864.973 | R91: =SUM(L91:Q91) | S91: =IF(E91=0,"***",L91/E91) | T91: =IF(F91=0,"***",M91/F91) | U91: =IF(G91=0,"***",N91/G91) | V91: =IF(H91=0,"***",O91/H91) | W91: =IF(I91=0,"***",P91/I91) | X91: =IF(J91=0,"***",Q91/J91) | Y91: =IF(K91=0,"***",R91/K91)
C92: 0910 集計 | D92: 足立課長 | E92: 4172.414 | F92: 2185.112 | G92: 2680.001 | H92: 0 | I92: 0 | J92: 0 | K92: =SUM(E92:J92) | L92: 817.802 | M92: 516.576 | N92: 508.359 | O92: 0 | P92: 0 | Q92: 0 | R92: =SUM(L92:Q92) | S92: =IF(E92=0,"***",L92/E92) | T92: =IF(F92=0,"***",M92/F92) | U92: =IF(G92=0,"***",N92/G92) | V92: =IF(H92=0,"***",O92/H92) | W92: =IF(I92=0,"***",P92/I92) | X92: =IF(J92=0,"***",Q92/J92) | Y92: =IF(K92=0,"***",R92/K92)
C93: 0911 集計 | D93: 川邊主任 | E93: 12178.474 | F93: 10681.174 | G93: 11717.856 | H93: 14845.393 | I93: 9474.612 | J93: 12056.125 | K93: =SUM(E93:J93) | L93: 1958.402 | M93: 1759.2 | N93: 1889.211 | O93: 2334.2 | P93: 1573.26 | Q93: 1928.239 | R93: =SUM(L93:Q93) | S93: =IF(E93=0,"***",L93/E93) | T93: =IF(F93=0,"***",M93/F93) | U93: =IF(G93=0,"***",N93/G93) | V93: =IF(H93=0,"***",O93/H93) | W93: =IF(I93=0,"***",P93/I93) | X93: =IF(J93=0,"***",Q93/J93) | Y93: =IF(K93=0,"***",R93/K93)
C94: 0914 集計 | D94: 白根主任 | E94: 27251.289 | F94: 10272.05 | G94: 9860.912 | H94: 12006.348 | I94: 8513.204 | J94: 19692.826 | K94: =SUM(E94:J94) | L94: 3929.53 | M94: 2665.577 | N94: 2196.369 | O94: 2961.116 | P94: 2123.723 | Q94: 5098.518 | R94: =SUM(L94:Q94) | S94: =IF(E94=0,"***",L94/E94) | T94: =IF(F94=0,"***",M94/F94) | U94: =IF(G94=0,"***",N94/G94) | V94: =IF(H94=0,"***",O94/H94) | W94: =IF(I94=0,"***",P94/I94) | X94: =IF(J94=0,"***",Q94/J94) | Y94: =IF(K94=0,"***",R94/K94)
C95: 0918 集計 | D95: 海外 | E95: 2165.5 | F95: 5289.97 | G95: 2659.97 | H95: 130.06 | I95: 314.45 | J95: 0 | K95: =SUM(E95:J95) | L95: 413.203 | M95: 806.536 | N95: 713.36 | O95: 29.11 | P95: 59.63 | Q95: 0 | R95: =SUM(L95:Q95) | S95: =IF(E95=0,"***",L95/E95) | T95: =IF(F95=0,"***",M95/F95) | U95: =IF(G95=0,"***",N95/G95) | V95: =IF(H95=0,"***",O95/H95) | W95: =IF(I95=0,"***",P95/I95) | X95: =IF(J95=0,"***",Q95/J95) | Y95: =IF(K95=0,"***",R95/K95)
C96: 0919 集計 | D96: その他 | E96: 74.8 | F96: 30 | G96: 37.578 | H96: 14.91 | I96: 0 | J96: 461.2 | K96: =SUM(E96:J96) | L96: 13.625 | M96: 6 | N96: 12.358 | O96: 3.7 | P96: 0 | Q96: 21.04 | R96: =SUM(L96:Q96) | S96: =IF(E96=0,"***",L96/E96) | T96: =IF(F96=0,"***",M96/F96) | U96: =IF(G96=0,"***",N96/G96) | V96: =IF(H96=0,"***",O96/H96) | W96: =IF(I96=0,"***",P96/I96) | X96: =IF(J96=0,"***",Q96/J96) | Y96: =IF(K96=0,"***",R96/K96)
C97: 0930 集計 | D97: 自治体 | G97: 82.104 | H97: 0 | I97: 156 | J97: 0 | K97: =SUM(E97:J97) | N97: 2.476 | O97: 0 | P97: 4.8 | Q97: 0 | R97: =SUM(L97:Q97) | S97: =IF(E97=0,"***",L97/E97) | T97: =IF(F97=0,"***",M97/F97) | U97: =IF(G97=0,"***",N97/G97) | V97: =IF(H97=0,"***",O97/H97) | W97: =IF(I97=0,"***",P97/I97) | X97: =IF(J97=0,"***",Q97/J97) | Y97: =IF(K97=0,"***",R97/K97)
C98: 合計 | E98: =SUM(E89:E97) | F98: =SUM(F89:F97) | G98: =SUM(G89:G97) | H98: =SUM(H89:H97) | I98: =SUM(I89:I97) | J98: =SUM(J89:J97) | K98: =SUM(K89:K97) | L98: =SUM(L89:L97) | ... R98: =SUM(R89:R97) | S98: =IF(E98=0,"***",L98/E98) | T98: =IF(F98=0,"***",M98/F98) | U98: =IF(G98=0,"***",N98/G98) | V98: =IF(H98=0,"***",O98/H98) | W98: =IF(I98=0,"***",P98/I98) | X98: =IF(J98=0,"***",Q98/J98) | Y98: =IF(K98=0,"***",R98/K98)
C100: 8．計画比
E101: 売上 | L101: 粗利益 | S101: 粗利益率
E102: 46113 | F102: 46143 | G102: 46174 | H102: 46204 | I102: 46235 | J102: 46266 | K102: 合計 | L102: 46113 | M102: 46143 | N102: 46174 | O102: 46204 | P102: 46235 | Q102: 46266 | R102: 合計 | S102: 46113 | T102: 46143 | U102: 46174 | V102: 46204 | W102: 46235 | X102: 46266 | Y102: 合計
C103: 0903 集計 | D103: 西岡 | E103: =E89-E47 | F103: =F89-F47 | G103: =G89-G47 | H103: =H89-H47 | I103: =I89-I47 | J103: =J89-J47 | K103: =SUM(E103:J103) | L103: =L89-L47 | M103: =M89-M47 | N103: =N89-N47 | O103: =O89-O47 | P103: =P89-P47 | Q103: =Q89-Q47 | R103: =SUM(L103:Q103) | S103: =S89-S47 | T103: =T89-T47 | U103: =U89-U47 | V103: =V89-V47 | W103: =W89-W47 | X103: =X89-X47 | Y103: =Y89-Y47
C104: 0904 集計 | D104: 足立次長 | E104: =E90-E48 | F104: =F90-F48 | G104: =G90-G48 | H104: =H90-H48 | I104: =I90-I48 | J104: =J90-J48 | K104: =SUM(E104:J104) | L104: =L90-L48 | M104: =M90-M48 | N104: =N90-N48 | O104: =O90-O48 | P104: =P90-P48 | Q104: =Q90-Q48 | R104: =SUM(L104:Q104) | S104: =S90-S48 | T104: =T90-T48 | U104: =U90-U48 | V104: =V90-V48 | W104: =W90-W48 | X104: =X90-X48 | Y104: =Y90-Y48
C105: 0909 集計 | D105: 藤波課長 | E105: =E91-E49 | F105: =F91-F49 | G105: =G91-G49 | H105: =H91-H49 | I105: =I91-I49 | J105: =J91-J49 | K105: =SUM(E105:J105) | L105: =L91-L49 | M105: =M91-M49 | N105: =N91-N49 | O105: =O91-O49 | P105: =P91-P49 | Q105: =Q91-Q49 | R105: =SUM(L105:Q105) | S105: =S91-S49 | T105: =T91-T49 | U105: =U91-U49 | V105: =V91-V49 | W105: =W91-W49 | X105: =X91-X49 | Y105: =Y91-Y49
C106: 0910 集計 | D106: 足立課長 | E106: =E92-E50 | F106: =F92-F50 | G106: =G92-G50 | H106: =H92-H50 | I106: =I92-I50 | J106: =J92-J50 | K106: =SUM(E106:J106) | L106: =L92-L50 | M106: =M92-M50 | N106: =N92-N50 | O106: =O92-O50 | P106: =P92-P50 | Q106: =Q92-Q50 | R106: =SUM(L106:Q106) | S106: =S92-S50 | T106: =T92-T50 | U106: =U92-U50 | V106: =V92-V50 | W106: =W92-W50 | X106: =X92-X50 | Y106: =Y92-Y50
C107: 0911 集計 | D107: 川邊主任 | E107: =E93-E51 | F107: =F93-F51 | G107: =G93-G51 | H107: =H93-H51 | I107: =I93-I51 | J107: =J93-J51 | K107: =SUM(E107:J107) | L107: =L93-L51 | M107: =M93-M51 | N107: =N93-N51 | O107: =O93-O51 | P107: =P93-P51 | Q107: =Q93-Q51 | R107: =SUM(L107:Q107) | S107: =S93-S51 | T107: =T93-T51 | U107: =U93-U51 | V107: =V93-V51 | W107: =W93-W51 | X107: =X93-X51 | Y107: =Y93-Y51
...

Sheet 総括
D1: 境港営業所第51期下期予算について
G7: 2024年4～9月 | J7: 2025年4～9月 | M7: 過年度平均 | P7: 計画 | U7: 根拠
G8: 売上 | H8: 粗利益 | I8: 粗利益率 | J8: 売上 | K8: 粗利益 | L8: 粗利益率 | M8: 売上 | N8: 粗利益 | O8: 粗利益率 | P8: 売上 | Q8: 粗利益 | R8: 粗利益率 | S8: 売上年率 | T8: 粗利益年率
D9: 境港営業所 | G9: 303863 | H9: 58108 | I9: =H9/G9 | J9: 392659 | K9: 77096 | L9: =K9/J9 | M9: =(G9+J9)/2 | N9: =(H9+K9)/2 | O9: =N9/M9 | P9: =P10+P13+P14 | Q9: =Q10+Q13+Q14 | R9: =Q9/P9 | S9: =P9/J9-1 | T9: =Q9/K9-1
E10: 営業 | G10: =G9-G14-G13 | H10: =H9-H14-H13 | I10: =H10/G10 | J10: =J9-J14-J13 | K10: =K9-K14-K13 | L10: =K10/J10 | M10: =(G10+J10)/2 | N10: =(H10+K10)/2 | O10: =N10/M10 | P10: =P11+P12 | Q10: =Q11+Q12 | R10: =Q10/P10 | S10: =P10/J10-1 | T10: =Q10/K10-1
F11: 包装資材 | G11: =G10-G12 | H11: =H10-H12 | I11: =H11/G11 | J11: =J10-J12 | K11: =K10-K12 | L11: =K11/J11 | M11: =(G11+J11)/2 | N11: =(H11+K11)/2 | O11: =N11/M11 | P11: 279390 | Q11: 54430 | R11: =Q11/P11 | S11: =P11/J11-1 | T11: =Q11/K11-1
F12: 機械 | G12: 51572 | H12: 11000 | I12: =H12/G12 | J12: 138794 | K12: 28492 | L12: =K12/J12 | M12: =(G12+J12)/2 | N12: =(H12+K12)/2 | O12: =N12/M12 | P12: =H26 | Q12: 19730 | R12: =Q12/P12 | S12: =P12/J12-1 | T12: =Q12/K12-1
E13: 自治体 | G13: 57 | H13: 2 | I13: =H13/G13 | J13: 87 | K13: 5 | L13: =K13/J13 | M13: =(G13+J13)/2 | N13: =(H13+K13)/2 | O13: =N13/M13 | P13: 0 | Q13: 0 | R13: =Q13/P13 | S13: =P13/J13-1 | T13: =Q13/K13-1
E14: 海外 | G14: 8366 | H14: 1637 | I14: =H14/G14 | J14: 6953 | K14: 1284 | L14: =K14/J14 | M14: =(G14+J14)/2 | N14: =(H14+K14)/2 | O14: =N14/M14 | P14: 8610 | Q14: 1640 | R14: =Q14/P14 | S14: =P14/J14-1 | T14: =Q14/K14-1
F17: 包材：期初計画 年率11.5％ 粗利率：段ボールも含め値上げで苦戦するので約1％程度改善で計画。
F18: 上期2月末実績では前年比+3,800（年率1.6％）で特定の顧客の増加があり売上が増えているので難しいが＋5％で計画。
F19: 機械：受注案件金額と個人別過年度平均にて個別に計画策定
G20: 秋田さん | H20: 1200 | I20: 過年度平均は723千円/6か月 200千円/月で1,200千円/6ヶ月で計画。浅井SAと一緒に大新、環境プラントの機械案件に取り組む
G21: 足立次長 | H21: 30000 | I21: 昨年実績は特殊（弓ヶ浜、岡野農場）だったので前々年実績（28,600千円）を参照し約5％UPの30,000千円で計画
G22: 藤波課長 | H22: 22200 | I22: 過年度平均4,200千円にモリイ食品の包装機18,000千円（6月）を足して22,200千円で計画
G23: 足立課長 | H23: 6000 | I23: 過年度平均が5,000千円で、大型機械案件がないので過年度平均並みで計画。澤井珈琲の資材と食品輸出にウェイトを増やす。
G24: 川邊主任 | H24: 4200 | I24: 期内にて大きな機械案件がないので過年度平均に約5％UPで計画。粗利は有償メンテを推進して2％前後改善する。
G25: 白根主任 | H25: 28000 | I25: 過年度＋白雪食品の包装機が19,000千円（4月納品）で計画
G26: 合計 | H26: =SUM(H20:H25) | I26: 前々期（2024年4月～9月）と比較すると約40,000千円の増加にて計画。粗利は機械メンテ有償化推進にて2％UPを計画
F27: 海外：過年度平均に食品輸出を約15％盛り込み計画。機械については案件がないので400千円/月で計算。
