Workbook

Sheet キョウワ
C1: キョウワ
C3: 売上を増やす営業活動はタカハシ包装が主体になると思いますので、一旦計画は過年度平均比スライドで設定しております。
C5: （参考）2019年
E7: 43556 | F7: 43586 | G7: 43617 | H7: 43647 | I7: 43678 | J7: 43709 | K7: 合計 | L7: 43556 | M7: 43586 | N7: 43617 | O7: 43647 | P7: 43678 | Q7: 43709 | R7: 合計 | S7: 43556 | T7: 43586 | U7: 43617 | V7: 43647 | W7: 43678 | X7: 43709 | Y7: 合計
C8: 合計 | E8: 2493 | F8: 2802 | G8: 1732 | H8: 3012 | I8: 2306 | J8: 1835 | K8: =SUM(E8:J8) | L8: 1774 | M8: 1783 | N8: 965 | O8: 2273 | P8: 1854 | Q8: 1134 | R8: =SUM(L8:Q8) | S8: =IF(E8=0,"***",L8/E8) | T8: =IF(F8=0,"***",M8/F8) | U8: =IF(G8=0,"***",N8/G8) | V8: =IF(H8=0,"***",O8/H8) | W8: =IF(I8=0,"***",P8/I8) | X8: =IF(J8=0,"***",Q8/J8) | Y8: =IF(K8=0,"***",R8/K8)
C10: （参考）2020年 | H10: →子会社化 | K10: コロナは5月から
E12: 43922 | F12: 43952 | G12: 43983 | H12: 44013 | I12: 44044 | J12: 44075 | K12: 合計 | L12: 43922 | M12: 43952 | N12: 43983 | O12: 44013 | P12: 44044 | Q12: 44075 | R12: 合計 | S12: 43922 | T12: 43952 | U12: 43983 | V12: 44013 | W12: 44044 | X12: 44075 | Y12: 合計
C13: 合計 | E13: 2493 | F13: 764 | G13: 996 | H13: 1776 | I13: 1746 | J13: 1050 | K13: =SUM(E13:J13) | L13: 592 | M13: 551 | N13: 790 | O13: 1364 | P13: 720 | Q13: 725 | R13: =SUM(L13:Q13) | S13: =IF(E13=0,"***",L13/E13) | T13: =IF(F13=0,"***",M13/F13) | U13: =IF(G13=0,"***",N13/G13) | V13: =IF(H13=0,"***",O13/H13) | W13: =IF(I13=0,"***",P13/I13) | X13: =IF(J13=0,"***",Q13/J13) | Y13: =IF(K13=0,"***",R13/K13)
C15: （参考）2021年
E17: 44287 | F17: 44317 | G17: 44348 | H17: 44378 | I17: 44409 | J17: 44440 | K17: 合計 | L17: 44287 | M17: 44317 | N17: 44348 | O17: 44378 | P17: 44409 | Q17: 44440 | R17: 合計 | S17: 44287 | T17: 44317 | U17: 44348 | V17: 44378 | W17: 44409 | X17: 44440 | Y17: 合計
C18: 合計 | E18: 2530 | F18: 1033 | G18: 1277 | H18: 2805 | I18: 2044 | J18: 1149 | K18: =SUM(E18:J18) | L18: 1904 | M18: -377 | N18: 966 | O18: 923 | P18: 860 | Q18: 496 | R18: =SUM(L18:Q18) | S18: =IF(E18=0,"***",L18/E18) | T18: =IF(F18=0,"***",M18/F18) | U18: =IF(G18=0,"***",N18/G18) | V18: =IF(H18=0,"***",O18/H18) | W18: =IF(I18=0,"***",P18/I18) | X18: =IF(J18=0,"***",Q18/J18) | Y18: =IF(K18=0,"***",R18/K18)
C20: （参考）2022年
E22: 44652 | F22: 44682 | G22: 44713 | H22: 44743 | I22: 44774 | J22: 44805 | K22: 合計 | L22: 44652 | M22: 44682 | N22: 44713 | O22: 44743 | P22: 44774 | Q22: 44805 | R22: 合計 | S22: 44652 | T22: 44682 | U22: 44713 | V22: 44743 | W22: 44774 | X22: 44805 | Y22: 合計
C23: 合計 | E23: 1414 | F23: 2156 | G23: 3338 | H23: 2255 | I23: 1581 | J23: 2089 | K23: =SUM(E23:J23) | L23: 797 | M23: 896 | N23: 797 | O23: 1624 | P23: 916 | Q23: 845 | R23: =SUM(L23:Q23) | S23: =IF(E23=0,"***",L23/E23) | T23: =IF(F23=0,"***",M23/F23) | U23: =IF(G23=0,"***",N23/G23) | V23: =IF(H23=0,"***",O23/H23) | W23: =IF(I23=0,"***",P23/I23) | X23: =IF(J23=0,"***",Q23/J23) | Y23: =IF(K23=0,"***",R23/K23)
C25: 1．2024年
E26: 売上 | L26: 粗利益 | S26: 粗利益率
E27: 45383 | F27: 45413 | G27: 45444 | H27: 45474 | I27: 45505 | J27: 45536 | K27: 合計 | L27: 45383 | M27: 45413 | N27: 45444 | O27: 45474 | P27: 45505 | Q27: 45536 | R27: 合計 | S27: 45383 | T27: 45413 | U27: 45444 | V27: 45474 | W27: 45505 | X27: 45536 | Y27: 合計
C28: 合計 | E28: 1956 | F28: 2537 | G28: 3086.5 | H28: 2625 | I28: 1730 | J28: 1896 | K28: =SUM(E28:J28) | L28: 1049.5 | M28: 1242.5 | N28: 1137.5 | O28: 1188 | P28: 1147 | Q28: 980 | R28: =SUM(L28:Q28) | S28: =IF(E28=0,"***",L28/E28) | T28: =IF(F28=0,"***",M28/F28) | U28: =IF(G28=0,"***",N28/G28) | V28: =IF(H28=0,"***",O28/H28) | W28: =IF(I28=0,"***",P28/I28) | X28: =IF(J28=0,"***",Q28/J28) | Y28: =IF(K28=0,"***",R28/K28)
C29: 合計(税抜） | E29: =ROUND(E28/1.1,-1) | F29: =ROUND(F28/1.1,-1) | G29: =ROUND(G28/1.1,-1) | H29: =ROUND(H28/1.1,-1) | I29: =ROUND(I28/1.1,-1) | J29: =ROUND(J28/1.1,-1) | K29: =SUM(E29:J29) | L29: =ROUND(L28/1.1,-1) | M29: =ROUND(M28/1.1,-1) | N29: =ROUND(N28/1.1,-1) | O29: =ROUND(O28/1.1,-1) | P29: =ROUND(P28/1.1,-1) | Q29: =ROUND(Q28/1.1,-1) | R29: =SUM(L29:Q29) | S29: =IF(E29=0,"***",L29/E29) | T29: =IF(F29=0,"***",M29/F29) | U29: =IF(G29=0,"***",N29/G29) | V29: =IF(H29=0,"***",O29/H29) | W29: =IF(I29=0,"***",P29/I29) | X29: =IF(J29=0,"***",Q29/J29) | Y29: =IF(K29=0,"***",R29/K29)
C31: 2．2025年
E32: 売上 | L32: 粗利益 | S32: 粗利益率
E33: 45748 | F33: 45778 | G33: 45809 | H33: 45839 | I33: 45870 | J33: 45901 | K33: 合計 | L33: 45748 | M33: 45778 | N33: 45809 | O33: 45839 | P33: 45870 | Q33: 45901 | R33: 合計 | S33: 45748 | T33: 45778 | U33: 45809 | V33: 45839 | W33: 45870 | X33: 45901 | Y33: 合計
C34: 合計 | E34: 2671 | F34: 1888 | G34: 4052 | H34: 2201 | I34: 1251 | J34: 1422 | K34: =SUM(E34:J34) | L34: 1634 | M34: 1214 | N34: 2753 | O34: 1206 | P34: 783 | Q34: 993 | R34: =SUM(L34:Q34) | S34: =IF(E34=0,"***",L34/E34) | T34: =IF(F34=0,"***",M34/F34) | U34: =IF(G34=0,"***",N34/G34) | V34: =IF(H34=0,"***",O34/H34) | W34: =IF(I34=0,"***",P34/I34) | X34: =IF(J34=0,"***",Q34/J34) | Y34: =IF(K34=0,"***",R34/K34)
C35: 合計(税抜） | E35: =ROUND(E34/1.05,-1) | F35: =ROUND(F34/1.05,-1) | G35: =ROUND(G34/1.05,-1) | H35: =ROUND(H34/1.05,-1) | I35: =ROUND(I34/1.05,-1) | J35: =ROUND(J34/1.05,-1) | K35: =SUM(E35:J35) | L35: =ROUND(L34/1.05,-1) | M35: =ROUND(M34/1.05,-1) | N35: =ROUND(N34/1.05,-1) | O35: =ROUND(O34/1.05,-1) | P35: =ROUND(P34/1.05,-1) | Q35: =ROUND(Q34/1.05,-1) | R35: =SUM(L35:Q35) | S35: =IF(E35=0,"***",L35/E35) | T35: =IF(F35=0,"***",M35/F35) | U35: =IF(G35=0,"***",N35/G35) | V35: =IF(H35=0,"***",O35/H35) | W35: =IF(I35=0,"***",P35/I35) | X35: =IF(J35=0,"***",Q35/J35) | Y35: =IF(K35=0,"***",R35/K35)
C37: 3．過年度平均
E38: 売上 | L38: 粗利益 | S38: 粗利益率
E39: 45748 | F39: 45778 | G39: 45809 | H39: 45839 | I39: 45870 | J39: 45901 | K39: 合計 | L39: 45748 | M39: 45778 | N39: 45809 | O39: 45839 | P39: 45870 | Q39: 45901 | R39: 合計 | S39: 45748 | T39: 45778 | U39: 45809 | V39: 45839 | W39: 45870 | X39: 45901 | Y39: 合計
C40: 合計 | E40: =ROUND((E28+E34)/2/1.1,0) | F40: =ROUND((F28+F34)/2/1.1,0) | G40: =ROUND((G28+G34)/2/1.1,0) | H40: =ROUND((H28+H34)/2/1.1,0) | I40: =ROUND((I28+I34)/2/1.1,0) | J40: =ROUND((J28+J34)/2/1.1,0) | K40: =SUM(E40:J40) | L40: =ROUND((L28+L34)/2/1.1,0) | M40: =ROUND((M28+M34)/2/1.1,0) | N40: =ROUND((N28+N34)/2/1.1,0) | O40: =ROUND((O28+O34)/2/1.1,0) | P40: =ROUND((P28+P34)/2/1.1,0) | Q40: =ROUND((Q28+Q34)/2/1.1,0) | R40: =SUM(L40:Q40) | S40: =IF(E40=0,"***",L40/E40) | T40: =IF(F40=0,"***",M40/F40) | U40: =IF(G40=0,"***",N40/G40) | V40: =IF(H40=0,"***",O40/H40) | W40: =IF(I40=0,"***",P40/I40) | X40: =IF(J40=0,"***",Q40/J40) | Y40: =IF(K40=0,"***",R40/K40)
C42: 4．計画
E43: 売上 | L43: 粗利益 | S43: 粗利益率
E44: 46113 | F44: 46143 | G44: 46174 | H44: 46204 | I44: 46235 | J44: 46266 | K44: 合計 | L44: 46113 | M44: 46143 | N44: 46174 | O44: 46204 | P44: 46235 | Q44: 46266 | R44: 合計 | S44: 46113 | T44: 46143 | U44: 46174 | V44: 46204 | W44: 46235 | X44: 46266 | Y44: 合計
C45: 合計(税抜） | E45: =ROUND(E40,-1) | F45: =ROUND(F40,-1) | G45: =ROUND(G40,-1) | H45: =ROUND(H40,-1) | I45: =ROUND(I40,-1) | J45: =ROUND(J40,-1) | K45: =SUM(E45:J45) | L45: =ROUND(L40,-1) | M45: =ROUND(M40,-1) | N45: =ROUND(N40,-1) | O45: =ROUND(O40,-1) | P45: =ROUND(P40,-1) | Q45: =ROUND(Q40,-1) | R45: =SUM(L45:Q45) | S45: =IF(E45=0,"***",L45/E45) | T45: =IF(F45=0,"***",M45/F45) | U45: =IF(G45=0,"***",N45/G45) | V45: =IF(H45=0,"***",O45/H45) | W45: =IF(I45=0,"***",P45/I45) | X45: =IF(J45=0,"***",Q45/J45) | Y45: =IF(K45=0,"***",R45/K45)
C47: ５．前期比
E48: 売上 | L48: 粗利益 | S48: 粗利益率
E49: 46113 | F49: 46143 | G49: 46174 | H49: 46204 | I49: 46235 | J49: 46266 | K49: 合計 | L49: 46113 | M49: 46143 | N49: 46174 | O49: 46204 | P49: 46235 | Q49: 46266 | R49: 合計 | S49: 46113 | T49: 46143 | U49: 46174 | V49: 46204 | W49: 46235 | X49: 46266 | Y49: 合計
C50: 合計(税抜） | E50: =E45-E35 | F50: =F45-F35 | G50: =G45-G35 | H50: =H45-H35 | I50: =I45-I35 | J50: =J45-J35 | K50: =SUM(E50:J50) | L50: =L45-L35 | M50: =M45-M35 | N50: =N45-N35 | O50: =O45-O35 | P50: =P45-P35 | Q50: =Q45-Q35 | R50: =SUM(L50:Q50) | S50: =S45-S35 | T50: =T45-T35 | U50: =U45-U35 | V50: =V45-V35 | W50: =W45-W35 | X50: =X45-X35 | Y50: =Y45-Y35
C52: ６．過年度平均比
E53: 売上 | L53: 粗利益 | S53: 粗利益率
E54: 46113 | F54: 46143 | G54: 46174 | H54: 46204 | I54: 46235 | J54: 46266 | K54: 合計 | L54: 46113 | M54: 46143 | N54: 46174 | O54: 46204 | P54: 46235 | Q54: 46266 | R54: 合計 | S54: 46113 | T54: 46143 | U54: 46174 | V54: 46204 | W54: 46235 | X54: 46266 | Y54: 合計
C55: 合計(税抜） | E55: =E45-E40 | F55: =F45-F40 | G55: =G45-G40 | H55: =H45-H40 | I55: =I45-I40 | J55: =J45-J40 | K55: =SUM(E55:J55) | L55: =L45-L40 | M55: =M45-M40 | N55: =N45-N40 | O55: =O45-O40 | P55: =P45-P40 | Q55: =Q45-Q40 | R55: =SUM(L55:Q55) | S55: =S45-S40 | T55: =T45-T40 | U55: =U45-U40 | V55: =V45-V40 | W55: =W45-W40 | X55: =X45-X40
C57: 7．実績
E58: 売上 | L58: 粗利益 | S58: 粗利益率
E59: 46113 | F59: 46143 | G59: 46174 | H59: 46204 | I59: 46235 | J59: 46266 | K59: 合計 | L59: 46113 | M59: 46143 | N59: 46174 | O59: 46204 | P59: 46235 | Q59: 46266 | R59: 合計 | S59: 46113 | T59: 46143 | U59: 46174 | V59: 46204 | W59: 46235 | X59: 46266 | Y59: 合計
C60: 合計(税抜） | E60: 1899 | F60: 1869 | G60: 2382 | H60: 2329 | I60: 3950 | J60: 1734 | K60: =SUM(E60:J60) | L60: 1242 | M60: 1317 | N60: 1466 | O60: 1227 | P60: 1723 | Q60: 1025 | R60: =SUM(L60:Q60) | S60: =IF(E60=0,"***",L60/E60) | T60: =IF(F60=0,"***",M60/F60) | U60: =IF(G60=0,"***",N60/G60) | V60: =IF(H60=0,"***",O60/H60) | W60: =IF(I60=0,"***",P60/I60) | X60: =IF(J60=0,"***",Q60/J60) | Y60: =IF(K60=0,"***",R60/K60)
C62: 8．計画比
E63: 売上 | L63: 粗利益 | S63: 粗利益率
E64: 46113 | F64: 46143 | G64: 46174 | H64: 46204 | I64: 46235 | J64: 46266 | K64: 合計 | L64: 46113 | M64: 46143 | N64: 46174 | O64: 46204 | P64: 46235 | Q64: 46266 | R64: 合計 | S64: 46113 | T64: 46143 | U64: 46174 | V64: 46204 | W64: 46235 | X64: 46266 | Y64: 合計
C65: 合計(税抜） | E65: =E60-E45 | F65: =F60-F45 | G65: =G60-G45 | H65: =H60-H45 | I65: =I60-I45 | J65: =J60-J45 | K65: =SUM(E65:J65) | L65: =L60-L45 | M65: =M60-M45 | N65: =N60-N45 | O65: =O60-O45 | P65: =P60-P45 | Q65: =Q60-Q45 | R65: =SUM(L65:Q65) | Y65: =Y60-Y45
C67: 9,前期比
E68: 売上 | L68: 粗利益 | S68: 粗利益率
E69: 45748 | F69: 45778 | G69: 45809 | H69: 45839 | I69: 45870 | J69: 45901 | K69: 合計 | L69: 45748 | M69: 45778 | N69: 45809 | O69: 45839 | P69: 45870 | Q69: 45901 | R69: 合計 | S69: 45748 | T69: 45778 | U69: 45809 | V69: 45839 | W69: 45870 | X69: 45901 | Y69: 合計
C70: 合計(税抜） | E70: =E60-E35 | F70: =F60-F35 | G70: =G60-G35 | H70: =H60-H35 | I70: =I60-I35 | J70: =J60-J35 | K70: =SUM(E70:J70) | L70: =L60-L35 | M70: =M60-M35 | N70: =N60-N35 | O70: =O60-O35 | P70: =P60-P35 | Q70: =Q60-Q35 | R70: =SUM(L70:Q70) | S70: =S60-S35 | T70: =T65-T50 | U70: =U65-U50 | V70: =V65-V50 | W70: =W65-W50 | X70: =X65-X50 | Y70: =Y60-Y35

Sheet 包装資材
C1: 広域営業部包装資材
C2: 1．2024年
E3: 売上 | L3: 粗利益 | S3: 粗利益率
E4: 45383 | F4: 45413 | G4: 45444 | H4: 45474 | I4: 45505 | J4: 45536 | K4: 合計 | L4: 45383 | M4: 45413 | N4: 45444 | O4: 45474 | P4: 45505 | Q4: 45536 | R4: 合計 | S4: 45383 | T4: 45413 | U4: 45444 | V4: 45474 | W4: 45505 | X4: 45536 | Y4: 合計
C5: 0042 集計 | D5: 馬場部長（鳥栖） | E5: =全体!E5-機械!E5 | F5: =全体!F5-機械!F5 | G5: =全体!G5-機械!G5 | H5: =全体!H5-機械!H5 | I5: =全体!I5-機械!I5 | J5: =全体!J5-機械!J5 | K5: =SUM(E5:J5) | L5: =全体!L5-機械!L5 | M5: =全体!M5-機械!M5 | N5: =全体!N5-機械!N5 | O5: =全体!O5-機械!O5 | P5: =全体!P5-機械!P5 | Q5: =全体!Q5-機械!Q5 | R5: =SUM(L5:Q5) | S5: =IF(E5=0,"***",L5/E5) | T5: =IF(F5=0,"***",M5/F5) | U5: =IF(G5=0,"***",N5/G5) | V5: =IF(H5=0,"***",O5/H5) | W5: =IF(I5=0,"***",P5/I5) | X5: =IF(J5=0,"***",Q5/J5) | Y5: =IF(K5=0,"***",R5/K5)
C6: 0045 集計 | D6: ペーパーハグ | E6: =全体!E6-機械!E6 | F6: =全体!F6-機械!F6 | G6: =全体!G6-機械!G6 | H6: =全体!H6-機械!H6 | I6: =全体!I6-機械!I6 | J6: =全体!J6-機械!J6 | K6: =SUM(E6:J6) | L6: =全体!L6-機械!L6 | M6: =全体!M6-機械!M6 | N6: =全体!N6-機械!N6 | O6: =全体!O6-機械!O6 | P6: =全体!P6-機械!P6 | Q6: =全体!Q6-機械!Q6
C7: 0046 集計 | D7: 角田 | E7: =全体!E7-機械!E7 | F7: =全体!F7-機械!F7 | G7: =全体!G7-機械!G7 | H7: =全体!H7-機械!H7 | I7: =全体!I7-機械!I7 | J7: =全体!J7-機械!J7 | K7: =SUM(E7:J7) | L7: =全体!L7-機械!L7 | M7: =全体!M7-機械!M7 | N7: =全体!N7-機械!N7 | O7: =全体!O7-機械!O7 | P7: =全体!P7-機械!P7 | Q7: =全体!Q7-機械!Q7 | R7: =SUM(L7:Q7) | S7: =IF(E7=0,"***",L7/E7) | T7: =IF(F7=0,"***",M7/F7) | U7: =IF(G7=0,"***",N7/G7) | V7: =IF(H7=0,"***",O7/H7) | W7: =IF(I7=0,"***",P7/I7) | X7: =IF(J7=0,"***",Q7/J7) | Y7: =IF(K7=0,"***",R7/K7)
C8: 0047 集計 | D8: 馬場部長（静岡） | E8: =全体!E8-機械!E8 | F8: =全体!F8-機械!F8 | G8: =全体!G8-機械!G8 | H8: =全体!H8-機械!H8 | I8: =全体!I8-機械!I8 | J8: =全体!J8-機械!J8 | K8: =SUM(E8:J8) | L8: =全体!L8-機械!L8 | M8: =全体!M8-機械!M8 | N8: =全体!N8-機械!N8 | O8: =全体!O8-機械!O8 | P8: =全体!P8-機械!P8 | Q8: =全体!Q8-機械!Q8
C9: 0550 集計 | D9: 馬場所長（東京） | E9: =全体!E9-機械!E9 | F9: =全体!F9-機械!F9 | G9: =全体!G9-機械!G9 | H9: =全体!H9-機械!H9 | I9: =全体!I9-機械!I9 | J9: =全体!J9-機械!J9 | K9: =SUM(E9:J9) | L9: =全体!L9-機械!L9 | M9: =全体!M9-機械!M9 | N9: =全体!N9-機械!N9 | O9: =全体!O9-機械!O9 | P9: =全体!P9-機械!P9 | Q9: =全体!Q9-機械!Q9 | R9: =SUM(L9:Q9) | S9: =IF(E9=0,"***",L9/E9) | T9: =IF(F9=0,"***",M9/F9) | U9: =IF(G9=0,"***",N9/G9) | V9: =IF(H9=0,"***",O9/H9) | W9: =IF(I9=0,"***",P9/I9) | X9: =IF(J9=0,"***",Q9/J9) | Y9: =IF(K9=0,"***",R9/K9)
C10: 0552 集計 | D10: 馬場部長（東京） | E10: =全体!E10-機械!E10 | F10: =全体!F10-機械!F10 | G10: =全体!G10-機械!G10 | H10: =全体!H10-機械!H10 | I10: =全体!I10-機械!I10 | J10: =全体!J10-機械!J10 | K10: =SUM(E10:J10) | L10: =全体!L10-機械!L10 | M10: =全体!M10-機械!M10 | N10: =全体!N10-機械!N10 | O10: =全体!O10-機械!O10 | P10: =全体!P10-機械!P10 | Q10: =全体!Q10-機械!Q10 | R10: =SUM(L10:Q10) | S10: =IF(E10=0,"***",L10/E10) | T10: =IF(F10=0,"***",M10/F10) | U10: =IF(G10=0,"***",N10/G10) | V10: =IF(H10=0,"***",O10/H10) | W10: =IF(I10=0,"***",P10/I10) | X10: =IF(J10=0,"***",Q10/J10) | Y10: =IF(K10=0,"***",R10/K10)
C11: 合計 | E11: =SUM(E5:E10) | F11: =SUM(F5:F10) | G11: =SUM(G5:G10) | H11: =SUM(H5:H10) | I11: =SUM(I5:I10) | J11: =SUM(J5:J10) | K11: =SUM(K5:K10) | L11: =SUM(L5:L10) | ... Y11: =SUM(Y5:Y10)
C12: リンガーハット | E12: =全体!E12-機械!E12 | F12: =全体!F12-機械!F12 | G12: =全体!G12-機械!G12 | H12: =全体!H12-機械!H12 | I12: =全体!I12-機械!I12 | J12: =全体!J12-機械!J12 | K12: =SUM(E12:J12) | L12: =全体!L12-機械!L12 | M12: =全体!M12-機械!M12 | N12: =全体!N12-機械!N12 | O12: =全体!O12-機械!O12 | P12: =全体!P12-機械!P12 | Q12: =全体!Q12-機械!Q12 | R12: =SUM(L12:Q12) | S12: =IF(E12=0,"***",L12/E12) | T12: =IF(F12=0,"***",M12/F12) | U12: =IF(G12=0,"***",N12/G12) | V12: =IF(H12=0,"***",O12/H12) | W12: =IF(I12=0,"***",P12/I12) | X12: =IF(J12=0,"***",Q12/J12) | Y12: =IF(K12=0,"***",R12/K12) | Z12: 0042と0550からカネゲン引く
C13: リンガーハット以外 | E13: =E11-E12 | F13: =F11-F12 | G13: =G11-G12 | H13: =H11-H12 | I13: =I11-I12 | J13: =J11-J12 | K13: =SUM(E13:J13) | L13: =L11-L12 | M13: =M11-M12 | N13: =N11-N12 | O13: =O11-O12 | P13: =P11-P12 | Q13: =Q11-Q12 | R13: =SUM(L13:Q13) | S13: =IF(E13=0,"***",L13/E13) | T13: =IF(F13=0,"***",M13/F13) | U13: =IF(G13=0,"***",N13/G13) | V13: =IF(H13=0,"***",O13/H13) | W13: =IF(I13=0,"***",P13/I13) | X13: =IF(J13=0,"***",Q13/J13) | Y13: =IF(K13=0,"***",R13/K13) | Z13: 0042と0550からカネゲン引く
C15: 2．2025年
E16: 売上 | L16: 粗利益 | S16: 粗利益率
E17: 45748 | F17: 45778 | G17: 45809 | H17: 45839 | I17: 45870 | J17: 45901 | K17: 合計 | L17: 45748 | M17: 45778 | N17: 45809 | O17: 45839 | P17: 45870 | Q17: 45901 | R17: 合計 | S17: 45748 | T17: 45778 | U17: 45809 | V17: 45839 | W17: 45870 | X17: 45901 | Y17: 合計
C18: 0042 集計 | D18: 馬場部長（鳥栖） | E18: =全体!E18-機械!E18 | F18: =全体!F18-機械!F18 | G18: =全体!G18-機械!G18 | H18: =全体!H18-機械!H18 | I18: =全体!I18-機械!I18 | J18: =全体!J18-機械!J18 | K18: =SUM(E18:J18) | L18: =全体!L18-機械!L18 | M18: =全体!M18-機械!M18 | N18: =全体!N18-機械!N18 | O18: =全体!O18-機械!O18 | P18: =全体!P18-機械!P18 | Q18: =全体!Q18-機械!Q18 | R18: =SUM(L18:Q18) | S18: =IF(E18=0,"***",L18/E18) | T18: =IF(F18=0,"***",M18/F18) | U18: =IF(G18=0,"***",N18/G18) | V18: =IF(H18=0,"***",O18/H18) | W18: =IF(I18=0,"***",P18/I18) | X18: =IF(J18=0,"***",Q18/J18) | Y18: =IF(K18=0,"***",R18/K18)
C19: 0045 集計 | D19: ペーパーハグ | E19: =全体!E19-機械!E19 | F19: =全体!F19-機械!F19 | G19: =全体!G19-機械!G19 | H19: =全体!H19-機械!H19 | I19: =全体!I19-機械!I19 | J19: =全体!J19-機械!J19 | K19: =SUM(E19:J19) | L19: =全体!L19-機械!L19 | M19: =全体!M19-機械!M19 | N19: =全体!N19-機械!N19 | O19: =全体!O19-機械!O19 | P19: =全体!P19-機械!P19 | Q19: =全体!Q19-機械!Q19 | R19: =SUM(L19:Q19) | S19: =IF(E19=0,"***",L19/E19) | T19: =IF(F19=0,"***",M19/F19) | U19: =IF(G19=0,"***",N19/G19) | V19: =IF(H19=0,"***",O19/H19) | W19: =IF(I19=0,"***",P19/I19) | X19: =IF(J19=0,"***",Q19/J19) | Y19: =IF(K19=0,"***",R19/K19)
C20: 0046 集計 | D20: 角田 | E20: =全体!E20-機械!E20 | F20: =全体!F20-機械!F20 | G20: =全体!G20-機械!G20 | H20: =全体!H20-機械!H20 | I20: =全体!I20-機械!I20 | J20: =全体!J20-機械!J20 | K20: =SUM(E20:J20) | L20: =全体!L20-機械!L20 | M20: =全体!M20-機械!M20 | N20: =全体!N20-機械!N20 | O20: =全体!O20-機械!O20 | P20: =全体!P20-機械!P20 | Q20: =全体!Q20-機械!Q20 | R20: =SUM(L20:Q20) | S20: =IF(E20=0,"***",L20/E20) | T20: =IF(F20=0,"***",M20/F20) | U20: =IF(G20=0,"***",N20/G20) | V20: =IF(H20=0,"***",O20/H20) | W20: =IF(I20=0,"***",P20/I20) | X20: =IF(J20=0,"***",Q20/J20) | Y20: =IF(K20=0,"***",R20/K20)
C21: 0047 集計 | D21: 馬場部長（静岡） | E21: =全体!E21-機械!E21 | F21: =全体!F21-機械!F21 | G21: =全体!G21-機械!G21 | H21: =全体!H21-機械!H21 | I21: =全体!I21-機械!I21 | J21: =全体!J21-機械!J21 | L21: =全体!L21-機械!L21 | M21: =全体!M21-機械!M21 | N21: =全体!N21-機械!N21 | O21: =全体!O21-機械!O21 | P21: =全体!P21-機械!P21 | Q21: =全体!Q21-機械!Q21
C22: 0550 集計 | D22: 馬場所長（東京） | E22: =全体!E22-機械!E22 | F22: =全体!F22-機械!F22 | G22: =全体!G22-機械!G22 | H22: =全体!H22-機械!H22 | I22: =全体!I22-機械!I22 | J22: =全体!J22-機械!J22 | K22: =SUM(E22:J22) | L22: =全体!L22-機械!L22 | M22: =全体!M22-機械!M22 | N22: =全体!N22-機械!N22 | O22: =全体!O22-機械!O22 | P22: =全体!P22-機械!P22 | Q22: =全体!Q22-機械!Q22 | R22: =SUM(L22:Q22) | S22: =IF(E22=0,"***",L22/E22) | T22: =IF(F22=0,"***",M22/F22) | U22: =IF(G22=0,"***",N22/G22) | V22: =IF(H22=0,"***",O22/H22) | W22: =IF(I22=0,"***",P22/I22) | X22: =IF(J22=0,"***",Q22/J22) | Y22: =IF(K22=0,"***",R22/K22)
C23: 0552 集計 | D23: 馬場部長（東京） | E23: =全体!E23-機械!E23 | F23: =全体!F23-機械!F23 | G23: =全体!G23-機械!G23 | H23: =全体!H23-機械!H23 | I23: =全体!I23-機械!I23 | J23: =全体!J23-機械!J23 | K23: =SUM(E23:J23) | L23: =全体!L23-機械!L23 | M23: =全体!M23-機械!M23 | N23: =全体!N23-機械!N23 | O23: =全体!O23-機械!O23 | P23: =全体!P23-機械!P23 | Q23: =全体!Q23-機械!Q23 | R23: =SUM(L23:Q23) | S23: =IF(E23=0,"***",L23/E23) | T23: =IF(F23=0,"***",M23/F23) | U23: =IF(G23=0,"***",N23/G23) | V23: =IF(H23=0,"***",O23/H23) | W23: =IF(I23=0,"***",P23/I23) | X23: =IF(J23=0,"***",Q23/J23) | Y23: =IF(K23=0,"***",R23/K23)
C24: 合計 | E24: =SUM(E18:E23) | F24: =SUM(F18:F23) | G24: =SUM(G18:G23) | H24: =SUM(H18:H23) | I24: =SUM(I18:I23) | J24: =SUM(J18:J23) | K24: =SUM(K18:K23) | L24: =SUM(L18:L23) | ... R24: =SUM(R18:R23) | S24: =IF(E24=0,"***",L24/E24) | T24: =IF(F24=0,"***",M24/F24) | U24: =IF(G24=0,"***",N24/G24) | V24: =IF(H24=0,"***",O24/H24) | W24: =IF(I24=0,"***",P24/I24) | X24: =IF(J24=0,"***",Q24/J24) | Y24: =IF(K24=0,"***",R24/K24)
C25: 内リンガーハット | E25: =全体!E25-機械!E25 | F25: =全体!F25-機械!F25 | G25: =全体!G25-機械!G25 | H25: =全体!H25-機械!H25 | I25: =全体!I25-機械!I25 | J25: =全体!J25-機械!J25 | K25: =SUM(E25:J25) | L25: =全体!L25-機械!L25 | M25: =全体!M25-機械!M25 | N25: =全体!N25-機械!N25 | O25: =全体!O25-機械!O25 | P25: =全体!P25-機械!P25 | Q25: =全体!Q25-機械!Q25 | R25: =SUM(L25:Q25) | S25: =IF(E25=0,"***",L25/E25) | T25: =IF(F25=0,"***",M25/F25) | U25: =IF(G25=0,"***",N25/G25) | V25: =IF(H25=0,"***",O25/H25) | W25: =IF(I25=0,"***",P25/I25) | X25: =IF(J25=0,"***",Q25/J25) | Y25: =IF(K25=0,"***",R25/K25) | Z25: 0042と0550からカネゲン引く
C26: リンガーハット以外 | E26: =E24-E25 | F26: =F24-F25 | G26: =G24-G25 | H26: =H24-H25 | I26: =I24-I25 | J26: =J24-J25 | K26: =SUM(E26:J26) | L26: =L24-L25 | M26: =M24-M25 | N26: =N24-N25 | O26: =O24-O25 | P26: =P24-P25 | Q26: =Q24-Q25 | R26: =SUM(L26:Q26) | S26: =IF(E26=0,"***",L26/E26) | T26: =IF(F26=0,"***",M26/F26) | U26: =IF(G26=0,"***",N26/G26) | V26: =IF(H26=0,"***",O26/H26) | W26: =IF(I26=0,"***",P26/I26) | X26: =IF(J26=0,"***",Q26/J26) | Y26: =IF(K26=0,"***",R26/K26) | Z26: 0042と0550からカネゲン引く
C28: 3．過年度平均
E29: 売上 | L29: 粗利益 | S29: 粗利益率
E30: 45748 | F30: 45778 | G30: 45809 | H30: 45839 | I30: 45870 | J30: 45901 | K30: 合計 | L30: 45748 | M30: 45778 | N30: 45809 | O30: 45839 | P30: 45870 | Q30: 45901 | R30: 合計 | S30: 45748 | T30: 45778 | U30: 45809 | V30: 45839 | W30: 45870 | X30: 45901 | Y30: 合計
C31: 0042 集計 | D31: 馬場部長（鳥栖） | E31: =(E18+E5)/2 | F31: =(F18+F5)/2 | G31: =(G18+G5)/2 | H31: =(H18+H5)/2 | I31: =(I18+I5)/2 | J31: =(J18+J5)/2 | K31: =SUM(E31:J31) | L31: =(L18+L5)/2 | M31: =(M18+M5)/2 | N31: =(N18+N5)/2 | O31: =(O18+O5)/2 | P31: =(P18+P5)/2 | Q31: =(Q18+Q5)/2 | R31: =SUM(L31:Q31) | S31: =IF(E31=0,"***",L31/E31) | T31: =IF(F31=0,"***",M31/F31) | U31: =IF(G31=0,"***",N31/G31) | V31: =IF(H31=0,"***",O31/H31) | W31: =IF(I31=0,"***",P31/I31) | X31: =IF(J31=0,"***",Q31/J31) | Y31: =IF(K31=0,"***",R31/K31)
C32: 0045 集計 | D32: ペーパーハグ | E32: =(E19+E6)/2 | F32: =(F19+F6)/2 | G32: =(G19+G6)/2 | H32: =(H19+H6)/2 | I32: =(I19+I6)/2 | J32: =(J19+J6)/2 | K32: =SUM(E32:J32) | L32: =(L19+L6)/2 | M32: =(M19+M6)/2 | N32: =(N19+N6)/2 | O32: =(O19+O6)/2 | P32: =(P19+P6)/2 | Q32: =(Q19+Q6)/2 | R32: =SUM(L32:Q32) | S32: =IF(E32=0,"***",L32/E32) | T32: =IF(F32=0,"***",M32/F32) | U32: =IF(G32=0,"***",N32/G32) | V32: =IF(H32=0,"***",O32/H32) | W32: =IF(I32=0,"***",P32/I32) | X32: =IF(J32=0,"***",Q32/J32) | Y32: =IF(K32=0,"***",R32/K32)
C33: 0046 集計 | D33: 角田 | E33: =(E20+E7)/2 | F33: =(F20+F7)/2 | G33: =(G20+G7)/2 | H33: =(H20+H7)/2 | I33: =(I20+I7)/2 | J33: =(J20+J7)/2 | K33: =SUM(E33:J33) | L33: =(L20+L7)/2 | M33: =(M20+M7)/2 | N33: =(N20+N7)/2 | O33: =(O20+O7)/2 | P33: =(P20+P7)/2 | Q33: =(Q20+Q7)/2 | R33: =SUM(L33:Q33) | S33: =IF(E33=0,"***",L33/E33) | T33: =IF(F33=0,"***",M33/F33) | U33: =IF(G33=0,"***",N33/G33) | V33: =IF(H33=0,"***",O33/H33) | W33: =IF(I33=0,"***",P33/I33) | X33: =IF(J33=0,"***",Q33/J33) | Y33: =IF(K33=0,"***",R33/K33)
C34: 0047 集計 | D34: 馬場部長（静岡） | E34: =(E21+E8)/2 | F34: =(F21+F8)/2 | G34: =(G21+G8)/2 | H34: =(H21+H8)/2 | I34: =(I21+I8)/2 | J34: =(J21+J8)/2 | L34: =(L21+L8)/2 | M34: =(M21+M8)/2 | N34: =(N21+N8)/2 | O34: =(O21+O8)/2 | P34: =(P21+P8)/2 | Q34: =(Q21+Q8)/2
C35: 0550 集計 | D35: 馬場所長（東京） | E35: =(E22+E9)/2 | F35: =(F22+F9)/2 | G35: =(G22+G9)/2 | H35: =(H22+H9)/2 | I35: =(I22+I9)/2 | J35: =(J22+J9)/2 | K35: =SUM(E35:J35) | L35: =(L22+L9)/2 | M35: =(M22+M9)/2 | N35: =(N22+N9)/2 | O35: =(O22+O9)/2 | P35: =(P22+P9)/2 | Q35: =(Q22+Q9)/2 | R35: =SUM(L35:Q35) | S35: =IF(E35=0,"***",L35/E35) | T35: =IF(F35=0,"***",M35/F35) | U35: =IF(G35=0,"***",N35/G35) | V35: =IF(H35=0,"***",O35/H35) | W35: =IF(I35=0,"***",P35/I35) | X35: =IF(J35=0,"***",Q35/J35) | Y35: =IF(K35=0,"***",R35/K35)
C36: 0552 集計 | D36: 馬場部長（東京） | E36: =(E23+E10)/2 | F36: =(F23+F10)/2 | G36: =(G23+G10)/2 | H36: =(H23+H10)/2 | I36: =(I23+I10)/2 | J36: =(J23+J10)/2 | K36: =SUM(E36:J36) | L36: =(L23+L10)/2 | M36: =(M23+M10)/2 | N36: =(N23+N10)/2 | O36: =(O23+O10)/2 | P36: =(P23+P10)/2 | Q36: =(Q23+Q10)/2 | R36: =SUM(L36:Q36) | S36: =IF(E36=0,"***",L36/E36) | T36: =IF(F36=0,"***",M36/F36) | U36: =IF(G36=0,"***",N36/G36) | V36: =IF(H36=0,"***",O36/H36) | W36: =IF(I36=0,"***",P36/I36) | X36: =IF(J36=0,"***",Q36/J36) | Y36: =IF(K36=0,"***",R36/K36)
C37: 合計 | E37: =SUM(E31:E36) | F37: =SUM(F31:F36) | G37: =SUM(G31:G36) | H37: =SUM(H31:H36) | I37: =SUM(I31:I36) | J37: =SUM(J31:J36) | K37: =SUM(K31:K36) | L37: =SUM(L31:L36) | ... R37: =SUM(R31:R36) | S37: =IF(E37=0,"***",L37/E37) | T37: =IF(F37=0,"***",M37/F37) | U37: =IF(G37=0,"***",N37/G37) | V37: =IF(H37=0,"***",O37/H37) | W37: =IF(I37=0,"***",P37/I37) | X37: =IF(J37=0,"***",Q37/J37) | Y37: =IF(K37=0,"***",R37/K37)
C38: 内リンガーハット | E38: =(E25+E12)/2 | F38: =(F25+F12)/2 | G38: =(G25+G12)/2 | H38: =(H25+H12)/2 | I38: =(I25+I12)/2 | J38: =(J25+J12)/2 | K38: =SUM(E38:J38) | L38: =(L25+L12)/2 | M38: =(M25+M12)/2 | N38: =(N25+N12)/2 | O38: =(O25+O12)/2 | P38: =(P25+P12)/2 | Q38: =(Q25+Q12)/2 | R38: =SUM(L38:Q38) | S38: =IF(E38=0,"***",L38/E38) | T38: =IF(F38=0,"***",M38/F38) | U38: =IF(G38=0,"***",N38/G38) | V38: =IF(H38=0,"***",O38/H38) | W38: =IF(I38=0,"***",P38/I38) | X38: =IF(J38=0,"***",Q38/J38) | Y38: =IF(K38=0,"***",R38/K38) | Z38: 0042と0550からカネゲン引く
C39: リンガーハット以外 | E39: =E37-E38 | F39: =F37-F38 | G39: =G37-G38 | H39: =H37-H38 | I39: =I37-I38 | J39: =J37-J38 | K39: =SUM(E39:J39) | L39: =L37-L38 | M39: =M37-M38 | N39: =N37-N38 | O39: =O37-O38 | P39: =P37-P38 | Q39: =Q37-Q38 | R39: =SUM(L39:Q39) | S39: =IF(E39=0,"***",L39/E39) | T39: =IF(F39=0,"***",M39/F39) | U39: =IF(G39=0,"***",N39/G39) | V39: =IF(H39=0,"***",O39/H39) | W39: =IF(I39=0,"***",P39/I39) | X39: =IF(J39=0,"***",Q39/J39) | Y39: =IF(K39=0,"***",R39/K39) | Z39: 0042と0550からカネゲン引く
C41: 4．計画 | E41: 実績は0042と0047が分かれて出るため実績を2行にしています
E42: 売上 | L42: 粗利益 | S42: 粗利益率
E43: 46113 | F43: 46143 | G43: 46174 | H43: 46204 | I43: 46235 | J43: 46266 | K43: 合計 | L43: 46113 | M43: 46143 | N43: 46174 | O43: 46204 | P43: 46235 | Q43: 46266 | R43: 合計 | S43: 46113 | T43: 46143 | U43: 46174 | V43: 46204 | W43: 46235 | X43: 46266 | Y43: 合計
C44: 0042 集計 | D44: 馬場部長（鳥栖） | E44: 31000 | F44: 28000 | G44: 29000 | H44: 33500 | I44: 33800 | J44: 33600 | K44: =SUM(E44:J44) | L44: 4500 | M44: 4100 | N44: 4200 | O44: 4860 | P44: 4900 | Q44: 4800 | R44: =SUM(L44:Q44) | S44: =IF(E44=0,"***",L44/E44) | T44: =IF(F44=0,"***",M44/F44) | U44: =IF(G44=0,"***",N44/G44) | V44: =IF(H44=0,"***",O44/H44) | W44: =IF(I44=0,"***",P44/I44) | X44: =IF(J44=0,"***",Q44/J44) | Y44: =IF(K44=0,"***",R44/K44)
C45: 0045 集計 | D45: ペーパーハグ | K45: =SUM(E45:J45) | R45: =SUM(L45:Q45) | S45: =IF(E45=0,"***",L45/E45) | T45: =IF(F45=0,"***",M45/F45) | U45: =IF(G45=0,"***",N45/G45) | V45: =IF(H45=0,"***",O45/H45) | W45: =IF(I45=0,"***",P45/I45) | X45: =IF(J45=0,"***",Q45/J45) | Y45: =IF(K45=0,"***",R45/K45)
C46: 0046 集計 | D46: 角田 | E46: 7000 | F46: 4500 | G46: 5600 | H46: 7180 | I46: 6300 | J46: 5000 | K46: =SUM(E46:J46) | L46: 1365 | M46: 900 | N46: 1100 | O46: 1500 | P46: 1300 | Q46: 1000 | R46: =SUM(L46:Q46) | S46: =IF(E46=0,"***",L46/E46) | T46: =IF(F46=0,"***",M46/F46) | U46: =IF(G46=0,"***",N46/G46) | V46: =IF(H46=0,"***",O46/H46) | W46: =IF(I46=0,"***",P46/I46) | X46: =IF(J46=0,"***",Q46/J46) | Y46: =IF(K46=0,"***",R46/K46)
C47: 0047 集計 | D47: 馬場部長（静岡） | K47: =SUM(E47:J47) | R47: =SUM(L47:Q47)
C48: 0550 集計 | D48: 馬場所長（東京） | K48: =SUM(E48:J48) | L48: =ROUND(E48*S48,-1) | M48: =ROUND(F48*T48,-1) | N48: =ROUND(G48*U48,-1) | O48: =ROUND(H48*V48,-1) | P48: =ROUND(I48*W48,-1) | Q48: =ROUND(J48*X48,-1) | R48: =SUM(L48:Q48) | S48: 0.12 | T48: 0.12 | U48: 0.11666667 | V48: 0.1 | W48: 0.12 | X48: 0.12 | Y48: =IF(K48=0,"***",R48/K48)
C49: 0552 集計 | D49: 馬場部長（東京） | E49: 8900 | F49: 6500 | G49: 6600 | H49: 4250 | I49: 3890 | J49: 6100 | K49: =SUM(E49:J49) | L49: 1150 | M49: 715 | N49: 860 | O49: 550 | P49: 500 | Q49: 800 | R49: =SUM(L49:Q49) | S49: =IF(E49=0,"***",L49/E49) | T49: =IF(F49=0,"***",M49/F49) | U49: =IF(G49=0,"***",N49/G49) | V49: =IF(H49=0,"***",O49/H49) | W49: =IF(I49=0,"***",P49/I49) | X49: =IF(J49=0,"***",Q49/J49) | Y49: =IF(K49=0,"***",R49/K49)
C50: 合計 | E50: =SUM(E44:E49) | F50: =SUM(F44:F49) | G50: =SUM(G44:G49) | H50: =SUM(H44:H49) | I50: =SUM(I44:I49) | J50: =SUM(J44:J49) | K50: =SUM(K44:K49) | L50: =SUM(L44:L49) | ... R50: =SUM(R44:R49) | S50: =IF(E50=0,"***",L50/E50) | T50: =IF(F50=0,"***",M50/F50) | U50: =IF(G50=0,"***",N50/G50) | V50: =IF(H50=0,"***",O50/H50) | W50: =IF(I50=0,"***",P50/I50) | X50: =IF(J50=0,"***",Q50/J50) | Y50: =IF(K50=0,"***",R50/K50)
C51: 内リンガーハット | E51: =(E38+E25)/2 | F51: =(F38+F25)/2 | G51: =(G38+G25)/2 | H51: =(H38+H25)/2 | I51: =(I38+I25)/2 | J51: =(J38+J25)/2 | K51: =SUM(E51:J51) | L51: =(L38+L25)/2 | M51: =(M38+M25)/2 | N51: =(N38+N25)/2 | O51: =(O38+O25)/2 | P51: =(P38+P25)/2 | Q51: =(Q38+Q25)/2 | R51: =SUM(L51:Q51) | S51: =IF(E51=0,"***",L51/E51) | T51: =IF(F51=0,"***",M51/F51) | U51: =IF(G51=0,"***",N51/G51) | V51: =IF(H51=0,"***",O51/H51) | W51: =IF(I51=0,"***",P51/I51) | X51: =IF(J51=0,"***",Q51/J51) | Y51: =IF(K51=0,"***",R51/K51) | Z51: 0042と0550からカネゲン引く
C52: リンガーハット以外 | E52: =E50-E51 | F52: =F50-F51 | G52: =G50-G51 | H52: =H50-H51 | I52: =I50-I51 | J52: =J50-J51 | K52: =SUM(E52:J52) | L52: =L50-L51 | M52: =M50-M51 | N52: =N50-N51 | O52: =O50-O51 | P52: =P50-P51 | Q52: =Q50-Q51 | R52: =SUM(L52:Q52) | S52: =IF(E52=0,"***",L52/E52) | T52: =IF(F52=0,"***",M52/F52) | U52: =IF(G52=0,"***",N52/G52) | V52: =IF(H52=0,"***",O52/H52) | W52: =IF(I52=0,"***",P52/I52) | X52: =IF(J52=0,"***",Q52/J52) | Y52: =IF(K52=0,"***",R52/K52) | Z52: 0042と0550からカネゲン引く
C54: 5．前期比
E55: 売上 | L55: 粗利益 | S55: 粗利益率
E56: 46113 | F56: 46143 | G56: 46174 | H56: 46204 | I56: 46235 | J56: 46266 | K56: 合計 | L56: 46113 | M56: 46143 | N56: 46174 | O56: 46204 | P56: 46235 | Q56: 46266 | R56: 合計 | S56: 46113 | T56: 46143 | U56: 46174 | V56: 46204 | W56: 46235 | X56: 46266 | Y56: 合計
C57: 0042 集計 | D57: 馬場部長（鳥栖） | E57: =E44-E18 | F57: =F44-F18 | G57: =G44-G18 | H57: =H44-H18 | I57: =I44-I18 | J57: =J44-J18 | K57: =SUM(E57:J57) | L57: =L44-L18 | M57: =M44-M18 | N57: =N44-N18 | O57: =O44-O18 | P57: =P44-P18 | Q57: =Q44-Q18 | R57: =SUM(L57:Q57) | S57: =S44-S18 | T57: =T44-T18 | U57: =U44-U18 | V57: =V44-V18 | W57: =W44-W18 | X57: =X44-X18 | Y57: =Y44-Y18
C58: 0045 集計 | D58: ペーパーハグ | E58: =E45-E19 | F58: =F45-F19 | G58: =G45-G19 | H58: =H45-H19 | I58: =I45-I19 | J58: =J45-J19 | K58: =SUM(E58:J58) | L58: =L45-L19 | M58: =M45-M19 | N58: =N45-N19 | O58: =O45-O19 | P58: =P45-P19 | Q58: =Q45-Q19 | R58: =SUM(L58:Q58)
C59: 0046 集計 | D59: 角田 | E59: =E46-E20 | F59: =F46-F20 | G59: =G46-G20 | H59: =H46-H20 | I59: =I46-I20 | J59: =J46-J20 | K59: =SUM(E59:J59) | L59: =L46-L20 | M59: =M46-M20 | N59: =N46-N20 | O59: =O46-O20 | P59: =P46-P20 | Q59: =Q46-Q20 | R59: =SUM(L59:Q59) | S59: =S46-S20 | T59: =T46-T20 | U59: =U46-U20 | V59: =V46-V20 | W59: =W46-W20 | X59: =X46-X20 | Y59: =Y46-Y20
C60: 0047 集計 | D60: 馬場部長（静岡） | E60: =E47-E21 | F60: =F47-F21 | G60: =G47-G21 | H60: =H47-H21 | I60: =I47-I21 | J60: =J47-J21 | K60: =SUM(E60:J60) | L60: =L47-L21 | M60: =M47-M21 | N60: =N47-N21 | O60: =O47-O21 | P60: =P47-P21 | Q60: =Q47-Q21 | R60: =SUM(L60:Q60) | S60: =S47-S21 | T60: =T47-T21 | U60: =U47-U21 | V60: =V47-V21 | W60: =W47-W21 | X60: =X47-X21 | Y60: =Y47-Y21
C61: 0550 集計 | D61: 馬場所長（東京） | E61: =E48-E22 | F61: =F48-F22 | G61: =G48-G22 | H61: =H48-H22 | I61: =I48-I22 | J61: =J48-J22 | K61: =SUM(E61:J61) | L61: =L48-L22 | M61: =M48-M22 | N61: =N48-N22 | O61: =O48-O22 | P61: =P48-P22 | Q61: =Q48-Q22 | R61: =SUM(L61:Q61) | S61: =S48-S22 | T61: =T48-T22 | U61: =U48-U22 | V61: =V48-V22 | W61: =W48-W22 | X61: =X48-X22 | Y61: =Y48-Y22
C62: 0552 集計 | D62: 馬場部長（東京） | E62: =E49-E23 | F62: =F49-F23 | G62: =G49-G23 | H62: =H49-H23 | I62: =I49-I23 | J62: =J49-J23 | K62: =SUM(E62:J62) | L62: =L49-L23 | M62: =M49-M23 | N62: =N49-N23 | O62: =O49-O23 | P62: =P49-P23 | Q62: =Q49-Q23 | R62: =SUM(L62:Q62) | S62: =S49-S23 | T62: =T49-T23 | U62: =U49-U23 | V62: =V49-V23 | W62: =W49-W23 | X62: =X49-X23 | Y62: =Y49-Y23
C63: 合計 | E63: =SUM(E57:E62) | F63: =SUM(F57:F62) | G63: =SUM(G57:G62) | H63: =SUM(H57:H62) | I63: =SUM(I57:I62) | J63: =SUM(J57:J62) | K63: =SUM(K57:K62) | L63: =SUM(L57:L62) | ... R63: =SUM(R57:R62) | S63: =S50-S24 | T63: =T50-T24 | U63: =U50-U24 | V63: =V50-V24 | W63: =W50-W24 | X63: =X50-X24 | Y63: =Y50-Y24
C64: 内リンガーハット | E64: =E51-E25 | F64: =F51-F25 | G64: =G51-G25 | H64: =H51-H25 | I64: =I51-I25 | J64: =J51-J25 | K64: =SUM(E64:J64) | L64: =L51-L25 | M64: =M51-M25 | N64: =N51-N25 | O64: =O51-O25 | P64: =P51-P25 | Q64: =Q51-Q25 | R64: =SUM(L64:Q64) | S64: =S51-S25 | T64: =T51-T25 | U64: =U51-U25 | V64: =V51-V25 | W64: =W51-W25 | X64: =X51-X25 | Y64: =Y51-Y25
C65: リンガーハット以外 | E65: =E63-E64 | F65: =F63-F64 | G65: =G63-G64 | H65: =H63-H64 | I65: =I63-I64 | J65: =J63-J64 | K65: =SUM(E65:J65) | L65: =L63-L64 | M65: =M63-M64 | N65: =N63-N64 | O65: =O63-O64 | P65: =P63-P64 | Q65: =Q63-Q64 | R65: =SUM(L65:Q65) | S65: =IF(E65=0,"***",L65/E65) | T65: =IF(F65=0,"***",M65/F65) | U65: =IF(G65=0,"***",N65/G65) | V65: =IF(H65=0,"***",O65/H65) | W65: =IF(I65=0,"***",P65/I65) | X65: =IF(J65=0,"***",Q65/J65) | Y65: =IF(K65=0,"***",R65/K65) | Z65: 0042と0550からカネゲン引く
C67: 6．過年度平均比
E68: 売上 | L68: 粗利益 | S68: 粗利益率
E69: 46113 | F69: 46143 | G69: 46174 | H69: 46204 | I69: 46235 | J69: 46266 | K69: 合計 | L69: 46113 | M69: 46143 | N69: 46174 | O69: 46204 | P69: 46235 | Q69: 46266 | R69: 合計 | S69: 46113 | T69: 46143 | U69: 46174 | V69: 46204 | W69: 46235 | X69: 46266 | Y69: 合計
C70: 0042 集計 | D70: 馬場部長（鳥栖） | E70: =E44-E31 | F70: =F44-F31 | G70: =G44-G31 | H70: =H44-H31 | I70: =I44-I31 | J70: =J44-J31 | K70: =SUM(E70:J70) | L70: =L44-L31 | M70: =M44-M31 | N70: =N44-N31 | O70: =O44-O31 | P70: =P44-P31 | Q70: =Q44-Q31 | R70: =SUM(L70:Q70) | S70: =S44-S31 | T70: =T44-T31 | U70: =U44-U31 | V70: =V44-V31 | W70: =W44-W31 | X70: =X44-X31 | Y70: =Y44-Y31
C71: 0045 集計 | D71: ペーパーハグ | E71: =E45-E32 | F71: =F45-F32 | G71: =G45-G32 | H71: =H45-H32 | I71: =I45-I32 | J71: =J45-J32 | K71: =SUM(E71:J71) | L71: =L45-L32 | M71: =M45-M32 | N71: =N45-N32 | O71: =O45-O32 | P71: =P45-P32 | Q71: =Q45-Q32 | R71: =SUM(L71:Q71) | S71: =S45-S32 | T71: =T45-T32 | U71: =U45-U32 | V71: =V45-V32 | W71: =W45-W32 | X71: =X45-X32 | Y71: =Y45-Y32
C72: 0046 集計 | D72: 角田 | E72: =E46-E33 | F72: =F46-F33 | G72: =G46-G33 | H72: =H46-H33 | I72: =I46-I33 | J72: =J46-J33 | K72: =SUM(E72:J72) | L72: =L46-L33 | M72: =M46-M33 | N72: =N46-N33 | O72: =O46-O33 | P72: =P46-P33 | Q72: =Q46-Q33 | R72: =SUM(L72:Q72) | S72: =S46-S33 | T72: =T46-T33 | U72: =U46-U33 | V72: =V46-V33 | W72: =W46-W33 | X72: =X46-X33 | Y72: =Y46-Y33
C73: 0047 集計 | D73: 馬場部長（静岡） | E73: =E47-E34 | F73: =F47-F34 | G73: =G47-G34 | H73: =H47-H34 | I73: =I47-I34 | J73: =J47-J34 | K73: =SUM(E73:J73) | L73: =L47-L34 | M73: =M47-M34 | N73: =N47-N34 | O73: =O47-O34 | P73: =P47-P34 | Q73: =Q47-Q34 | R73: =SUM(L73:Q73) | S73: =S47-S34 | T73: =T47-T34 | U73: =U47-U34 | V73: =V47-V34 | W73: =W47-W34 | X73: =X47-X34 | Y73: =Y47-Y34
C74: 0550 集計 | D74: 馬場所長（東京） | E74: =E48-E35 | F74: =F48-F35 | G74: =G48-G35 | H74: =H48-H35 | I74: =I48-I35 | J74: =J48-J35 | K74: =SUM(E74:J74) | L74: =L48-L35 | M74: =M48-M35 | N74: =N48-N35 | O74: =O48-O35 | P74: =P48-P35 | Q74: =Q48-Q35 | R74: =SUM(L74:Q74) | S74: =S48-S35 | T74: =T48-T35 | U74: =U48-U35 | V74: =V48-V35 | W74: =W48-W35 | X74: =X48-X35 | Y74: =Y48-Y35
C75: 0552 集計 | D75: 馬場部長（東京） | E75: =E49-E36 | F75: =F49-F36 | G75: =G49-G36 | H75: =H49-H36 | I75: =I49-I36 | J75: =J49-J36 | K75: =SUM(E75:J75) | L75: =L49-L36 | M75: =M49-M36 | N75: =N49-N36 | O75: =O49-O36 | P75: =P49-P36 | Q75: =Q49-Q36 | R75: =SUM(L75:Q75) | S75: =S49-S36 | T75: =T49-T36 | U75: =U49-U36 | V75: =V49-V36 | W75: =W49-W36 | X75: =X49-X36 | Y75: =Y49-Y36
C76: 合計 | E76: =SUM(E70:E75) | F76: =SUM(F70:F75) | G76: =SUM(G70:G75) | H76: =SUM(H70:H75) | I76: =SUM(I70:I75) | J76: =SUM(J70:J75) | K76: =SUM(K70:K75) | L76: =SUM(L70:L75) | ... R76: =SUM(R70:R75) | S76: =S50-S37 | T76: =T50-T37 | U76: =U50-U37 | V76: =V50-V37 | W76: =W50-W37 | X76: =X50-X37 | Y76: =Y50-Y37
C77: 内リンガーハット | E77: =E51-E38 | F77: =F51-F38 | G77: =G51-G38 | H77: =H51-H38 | I77: =I51-I38 | J77: =J51-J38 | K77: =SUM(E77:J77) | L77: =L51-L38 | M77: =M51-M38 | N77: =N51-N38 | O77: =O51-O38 | P77: =P51-P38 | Q77: =Q51-Q38 | R77: =SUM(L77:Q77) | S77: =IF(E77=0,"***",L77/E77) | T77: =IF(F77=0,"***",M77/F77) | U77: =IF(G77=0,"***",N77/G77) | V77: =IF(H77=0,"***",O77/H77) | W77: =IF(I77=0,"***",P77/I77) | X77: =IF(J77=0,"***",Q77/J77) | Y77: =IF(K77=0,"***",R77/K77) | Z77: 0042と0550からカネゲン引く
C78: リンガーハット以外 | E78: =E76-E77 | F78: =F76-F77 | G78: =G76-G77 | H78: =H76-H77 | I78: =I76-I77 | J78: =J76-J77 | K78: =SUM(E78:J78) | L78: =L76-L77 | M78: =M76-M77 | N78: =N76-N77 | O78: =O76-O77 | P78: =P76-P77 | Q78: =Q76-Q77 | R78: =SUM(L78:Q78) | S78: =IF(E78=0,"***",L78/E78) | T78: =IF(F78=0,"***",M78/F78) | U78: =IF(G78=0,"***",N78/G78) | V78: =IF(H78=0,"***",O78/H78) | W78: =IF(I78=0,"***",P78/I78) | X78: =IF(J78=0,"***",Q78/J78) | Y78: =IF(K78=0,"***",R78/K78) | Z78: 0042と0550からカネゲン引く
C80: 7．実績 | E80: 実績は0042と0047が分かれて出るため実績を2行にしています
E81: 売上 | L81: 粗利益 | S81: 粗利益率
E82: 46113 | F82: 46143 | G82: 46174 | H82: 46204 | I82: 46235 | J82: 46266 | K82: 合計 | L82: 46113 | M82: 46143 | N82: 46174 | O82: 46204 | P82: 46235 | Q82: 46266 | R82: 合計 | S82: 46113 | T82: 46143 | U82: 46174 | V82: 46204 | W82: 46235 | X82: 46266 | Y82: 合計
C83: 0042 集計 | D83: 馬場部長（鳥栖） | E83: =全体!E83-機械!E83 | F83: =全体!F83-機械!F83 | G83: =全体!G83-機械!G83 | H83: =全体!H83-機械!H83 | I83: =全体!I83-機械!I83 | J83: =全体!J83-機械!J83 | K83: =SUM(E83:J83) | L83: =全体!L83-機械!L83 | M83: =全体!M83-機械!M83 | N83: =全体!N83-機械!N83 | O83: =全体!O83-機械!O83 | P83: =全体!P83-機械!P83 | Q83: =全体!Q83-機械!Q83 | R83: =SUM(L83:Q83) | S83: =IF(E83=0,"***",L83/E83) | T83: =IF(F83=0,"***",M83/F83) | U83: =IF(G83=0,"***",N83/G83) | V83: =IF(H83=0,"***",O83/H83) | W83: =IF(I83=0,"***",P83/I83) | X83: =IF(J83=0,"***",Q83/J83) | Y83: =IF(K83=0,"***",R83/K83)
C84: 0045 集計 | D84: ペーパーハグ | E84: =全体!E84-機械!E84 | G84: =全体!G84-機械!G84 | H84: =全体!H84-機械!H84 | I84: =全体!I84-機械!I84 | J84: =全体!J84-機械!J84 | K84: =SUM(E84:J84) | L84: =全体!L84-機械!L84 | N84: =全体!N84-機械!N84 | O84: =全体!O84-機械!O84 | P84: =全体!P84-機械!P84 | Q84: =全体!Q84-機械!Q84 | R84: =SUM(L84:Q84) | S84: =IF(E84=0,"***",L84/E84) | T84: =IF(F84=0,"***",M84/F84) | U84: =IF(G84=0,"***",N84/G84) | V84: =IF(H84=0,"***",O84/H84) | W84: =IF(I84=0,"***",P84/I84) | X84: =IF(J84=0,"***",Q84/J84) | Y84: =IF(K84=0,"***",R84/K84)
C85: 0046 集計 | D85: 角田 | E85: =全体!E85-機械!E85 | F85: =全体!F85-機械!F85 | G85: =全体!G85-機械!G85 | H85: =全体!H85-機械!H85 | I85: =全体!I85-機械!I85 | J85: =全体!J85-機械!J85 | K85: =SUM(E85:J85) | L85: =全体!L85-機械!L85 | M85: =全体!M85-機械!M85 | N85: =全体!N85-機械!N85 | O85: =全体!O85-機械!O85 | P85: =全体!P85-機械!P85 | Q85: =全体!Q85-機械!Q85 | R85: =SUM(L85:Q85) | S85: =IF(E85=0,"***",L85/E85) | T85: =IF(F85=0,"***",M85/F85) | U85: =IF(G85=0,"***",N85/G85) | V85: =IF(H85=0,"***",O85/H85) | W85: =IF(I85=0,"***",P85/I85) | X85: =IF(J85=0,"***",Q85/J85) | Y85: =IF(K85=0,"***",R85/K85)
C86: 0047 集計 | D86: 馬場部長（静岡） | E86: =全体!E86-機械!E86 | F86: =全体!F86-機械!F86 | G86: =全体!G86-機械!G86 | H86: =全体!H86-機械!H86 | I86: =全体!I86-機械!I86 | J86: =全体!J86-機械!J86 | K86: =SUM(E86:J86) | L86: =全体!L86-機械!L86 | M86: =全体!M86-機械!M86 | N86: =全体!N86-機械!N86 | O86: =全体!O86-機械!O86 | P86: =全体!P86-機械!P86 | Q86: =全体!Q86-機械!Q86 | R86: =SUM(L86:Q86) | S86: =IF(E86=0,"***",L86/E86) | T86: =IF(F86=0,"***",M86/F86) | U86: =IF(G86=0,"***",N86/G86) | V86: =IF(H86=0,"***",O86/H86) | W86: =IF(I86=0,"***",P86/I86) | X86: =IF(J86=0,"***",Q86/J86) | Y86: =IF(K86=0,"***",R86/K86)
C87: 0550 集計 | D87: 馬場所長（東京） | E87: =全体!E87-機械!E87 | F87: =全体!F87-機械!F87 | G87: =全体!G87-機械!G87 | H87: =全体!H87-機械!H87 | I87: =全体!I87-機械!I87 | J87: =全体!J87-機械!J87 | K87: =SUM(E87:J87) | L87: =全体!L87-機械!L87 | M87: =全体!M87-機械!M87 | N87: =全体!N87-機械!N87 | O87: =全体!O87-機械!O87 | P87: =全体!P87-機械!P87 | Q87: =全体!Q87-機械!Q87 | R87: =SUM(L87:Q87) | S87: =IF(E87=0,"***",L87/E87) | T87: =IF(F87=0,"***",M87/F87) | U87: =IF(G87=0,"***",N87/G87) | V87: =IF(H87=0,"***",O87/H87) | W87: =IF(I87=0,"***",P87/I87) | X87: =IF(J87=0,"***",Q87/J87) | Y87: =IF(K87=0,"***",R87/K87)
C88: 0552 集計 | D88: 馬場部長（東京） | E88: =全体!E88-機械!E88 | F88: =全体!F88-機械!F88 | G88: =全体!G88-機械!G88 | H88: =全体!H88-機械!H88 | I88: =全体!I88-機械!I88 | J88: =全体!J88-機械!J88 | K88: =SUM(E88:J88) | L88: =全体!L88-機械!L88 | M88: =全体!M88-機械!M88 | N88: =全体!N88-機械!N88 | O88: =全体!O88-機械!O88 | P88: =全体!P88-機械!P88 | Q88: =全体!Q88-機械!Q88 | R88: =SUM(L88:Q88) | S88: =IF(E88=0,"***",L88/E88) | T88: =IF(F88=0,"***",M88/F88) | U88: =IF(G88=0,"***",N88/G88) | V88: =IF(H88=0,"***",O88/H88) | W88: =IF(I88=0,"***",P88/I88) | X88: =IF(J88=0,"***",Q88/J88) | Y88: =IF(K88=0,"***",R88/K88)
C89: 合計 | E89: =SUM(E83:E88) | F89: =SUM(F83:F88) | G89: =SUM(G83:G88) | H89: =SUM(H83:H88) | I89: =SUM(I83:I88) | J89: =SUM(J83:J88) | K89: =SUM(K83:K88) | L89: =SUM(L83:L88) | ... R89: =SUM(R83:R88) | S89: =IF(E89=0,"***",L89/E89) | T89: =IF(F89=0,"***",M89/F89) | U89: =IF(G89=0,"***",N89/G89) | V89: =IF(H89=0,"***",O89/H89) | W89: =IF(I89=0,"***",P89/I89) | X89: =IF(J89=0,"***",Q89/J89) | Y89: =IF(K89=0,"***",R89/K89)
C90: 内リンガーハット | E90: 29277.996 | F90: 31673.622 | G90: =全体!G90-機械!G90 | H90: =全体!H90-機械!H90 | I90: =全体!I90-機械!I90 | J90: =全体!J90-機械!J90 | K90: =SUM(E90:J90) | L90: 4709.931 | M90: 7747.61 | N90: =全体!N90-機械!N90 | O90: =全体!O90-機械!O90 | P90: =全体!P90-機械!P90 | Q90: =全体!Q90-機械!Q90 | R90: =SUM(L90:Q90) | S90: =IF(E90=0,"***",L90/E90) | T90: =IF(F90=0,"***",M90/F90) | U90: =IF(G90=0,"***",N90/G90) | V90: =IF(H90=0,"***",O90/H90) | W90: =IF(I90=0,"***",P90/I90) | X90: =IF(J90=0,"***",Q90/J90) | Y90: =IF(K90=0,"***",R90/K90) | Z90: 0042と0550からカネゲン引く
C91: リンガーハット以外 | E91: =E89-E90 | F91: =F89-F90 | G91: =G89-G90 | H91: =H89-H90 | I91: =I89-I90 | J91: =J89-J90 | K91: =SUM(E91:J91) | L91: =L89-L90 | M91: =M89-M90 | N91: =N89-N90 | O91: =O89-O90 | P91: =P89-P90 | Q91: =Q89-Q90 | R91: =SUM(L91:Q91) | S91: =IF(E91=0,"***",L91/E91) | T91: =IF(F91=0,"***",M91/F91) | U91: =IF(G91=0,"***",N91/G91) | V91: =IF(H91=0,"***",O91/H91) | W91: =IF(I91=0,"***",P91/I91) | X91: =IF(J91=0,"***",Q91/J91) | Y91: =IF(K91=0,"***",R91/K91) | Z91: 0042と0550からカネゲン引く
N92: =全体!N92-機械!N92
C93: 8．計画比
E94: 売上 | L94: 粗利益 | S94: 粗利益率
E95: 46113 | F95: 46143 | G95: 46174 | H95: 46204 | I95: 46235 | J95: 46266 | K95: 合計 | L95: 46113 | M95: 46143 | N95: 46174 | O95: 46204 | P95: 46235 | Q95: 46266 | R95: 合計 | S95: 46113 | T95: 46143 | U95: 46174 | V95: 46204 | W95: 46235 | X95: 46266 | Y95: 合計
C96: 0042 集計 | D96: 馬場部長（鳥栖） | E96: =E83-E44 | F96: =F83-F44 | G96: =G83-G44 | H96: =H83-H44 | I96: =I83-I44 | J96: =J83-J44 | K96: =SUM(E96:J96) | L96: =L83-L44 | M96: =M83-M44 | N96: =N83-N44 | O96: =O83-O44 | P96: =P83-P44 | Q96: =Q83-Q44 | R96: =SUM(L96:Q96) | S96: =S83-S44 | T96: =T83-T44 | U96: =U83-U44 | V96: =V83-V44 | W96: =W83-W44 | X96: =X83-X44 | Y96: =Y83-Y44
C97: 0045 集計 | D97: ペーパーハグ | E97: =E84-E45 | F97: =F84-F45 | G97: =G84-G45 | H97: =H84-H45 | I97: =I84-I45 | J97: =J84-J45 | K97: =SUM(E97:J97) | L97: =L84-L45 | M97: =M84-M45 | N97: =N84-N45 | O97: =O84-O45 | P97: =P84-P45 | Q97: =Q84-Q45 | R97: =SUM(L97:Q97) | S97: =S84-S45 | T97: =T84-T45 | U97: =U84-U45 | V97: =V84-V45 | W97: =W84-W45 | X97: =X84-X45 | Y97: =Y84-Y45
C98: 0046 集計 | D98: 角田 | E98: =E85-E46 | F98: =F85-F46 | G98: =G85-G46 | H98: =H85-H46 | I98: =I85-I46 | J98: =J85-J46 | K98: =SUM(E98:J98) | L98: =L85-L46 | M98: =M85-M46 | N98: =N85-N46 | O98: =O85-O46 | P98: =P85-P46 | Q98: =Q85-Q46 | R98: =SUM(L98:Q98) | S98: =S85-S46 | T98: =T85-T46 | U98: =U85-U46 | V98: =V85-V46 | W98: =W85-W46 | X98: =X85-X46 | Y98: =Y85-Y46
C99: 0047 集計 | D99: 馬場部長（静岡） | E99: =E86-E47 | F99: =F86-F47 | G99: =G86-G47 | H99: =H86-H47 | I99: =I86-I47 | J99: =J86-J47 | K99: =SUM(E99:J99) | L99: =L86-L47 | M99: =M86-M47 | N99: =N86-N47 | O99: =O86-O47 | P99: =P86-P47 | Q99: =Q86-Q47 | R99: =SUM(L99:Q99) | S99: =S86-S47 | T99: =T86-T47 | U99: =U86-U47 | V99: =V86-V47 | W99: =W86-W47 | X99: =X86-X47 | Y99: =Y86-Y47
C100: 0550 集計 | D100: 馬場所長（東京） | E100: =E87-E48 | F100: =F87-F48 | G100: =G87-G48 | H100: =H87-H48 | I100: =I87-I48 | J100: =J87-J48 | K100: =SUM(E100:J100) | L100: =L87-L48 | M100: =M87-M48 | N100: =N87-N48 | O100: =O87-O48 | P100: =P87-P48 | Q100: =Q87-Q48 | R100: =SUM(L100:Q100) | S100: =S87-S48 | T100: =T87-T48 | U100: =U87-U48 | V100: =V87-V48 | W100: =W87-W48 | X100: =X87-X48 | Y100: =Y87-Y48
C101: 0552 集計 | D101: 馬場部長（東京） | E101: =E88-E49 | F101: =F88-F49 | G101: =G88-G49 | H101: =H88-H49 | I101: =I88-I49 | J101: =J88-J49 | K101: =SUM(E101:J101) | L101: =L88-L49 | M101: =M88-M49 | N101: =N88-N49 | O101: =O88-O49 | P101: =P88-P49 | Q101: =Q88-Q49 | R101: =SUM(L101:Q101) | S101: =S88-S49 | T101: =T88-T49 | U101: =U88-U49 | V101: =V88-V49 | W101: =W88-W49 | X101: =X88-X49 | Y101: =Y88-Y49
C102: 合計 | E102: =SUM(E96:E101) | F102: =SUM(F96:F101) | G102: =SUM(G96:G101) | H102: =SUM(H96:H101) | I102: =SUM(I96:I101) | J102: =SUM(J96:J101) | K102: =SUM(K96:K101) | L102: =SUM(L96:L101) | ... R102: =SUM(R96:R101) | S102: =S89-S50 | T102: =T89-T50 | U102: =U89-U50 | V102: =V89-V50 | W102: =W89-W50 | X102: =X89-X50 | Y102: =Y89-Y50
C103: 内リンガーハット | E103: =E90-E51 | F103: =F90-F51 | G103: =G90-G51 | H103: =H90-H51 | I103: =I90-I51 | J103: =J90-J51 | K103: =SUM(E103:J103) | L103: =L90-L51 | M103: =M90-M51 | N103: =N90-N51 | O103: =O90-O51 | P103: =P90-P51 | Q103: =Q90-Q51 | R103: =SUM(L103:Q103) | S103: =S90-S51 | T103: =T90-T51 | U103: =U90-U51 | V103: =V90-V51 | W103: =W90-W51 | X103: =X90-X51 | Y103: =Y90-Y51 | Z103: 0042と0550からカネゲン引く
C104: リンガーハット以外 | E104: =E102-E103 | F104: =F102-F103 | G104: =G102-G103 | H104: =H102-H103 | I104: =I102-I103 | J104: =J102-J103 | K104: =SUM(E104:J104) | L104: =L102-L103 | M104: =M102-M103 | N104: =N102-N103 | O104: =O102-O103 | P104: =P102-P103 | Q104: =Q102-Q103 | R104: =SUM(L104:Q104) | S104: =S91-S52 | T104: =T91-T52 | U104: =U91-U52 | V104: =V91-V52 | W104: =W91-W52 | X104: =X91-X52 | Y104: =Y91-Y52 | Z104: 0042と0550からカネゲン引く
C106: 9．前期比
E107: 売上 | L107: 粗利益 | S107: 粗利益率
...

Sheet 機械
C1: 広域営業部機械
C2: 1．2024年
E3: 売上 | L3: 粗利益 | S3: 粗利益率
E4: 45383 | F4: 45413 | G4: 45444 | H4: 45474 | I4: 45505 | J4: 45536 | K4: 合計 | L4: 45383 | M4: 45413 | N4: 45444 | O4: 45474 | P4: 45505 | Q4: 45536 | R4: 合計 | S4: 45383 | T4: 45413 | U4: 45444 | V4: 45474 | W4: 45505 | X4: 45536 | Y4: 合計
C5: 0042 集計 | D5: 馬場部長（鳥栖） | E5: 22 | F5: 148 | G5: 27 | H5: 46 | I5: 83 | J5: 27 | K5: =SUM(E5:J5) | L5: 1 | M5: 4 | N5: -1 | O5: 5 | P5: 1 | Q5: -1 | R5: =SUM(L5:Q5) | S5: =IF(E5=0,"***",L5/E5) | T5: =IF(F5=0,"***",M5/F5) | U5: =IF(G5=0,"***",N5/G5) | V5: =IF(H5=0,"***",O5/H5) | W5: =IF(I5=0,"***",P5/I5) | X5: =IF(J5=0,"***",Q5/J5) | Y5: =IF(K5=0,"***",R5/K5)
C6: 0045 集計 | D6: ペーパーハグ
C7: 0046 集計 | D7: 角田 | E7: 15 | F7: 80 | G7: 91 | H7: 10 | I7: 70 | J7: 0 | K7: =SUM(E7:J7) | L7: 2 | M7: 5 | N7: 11 | O7: 1 | P7: 7 | Q7: 0 | R7: =SUM(L7:Q7) | S7: =IF(E7=0,"***",L7/E7) | T7: =IF(F7=0,"***",M7/F7) | U7: =IF(G7=0,"***",N7/G7) | V7: =IF(H7=0,"***",O7/H7) | W7: =IF(I7=0,"***",P7/I7) | X7: =IF(J7=0,"***",Q7/J7) | Y7: =IF(K7=0,"***",R7/K7)
C8: 0047 集計 | D8: 馬場部長（静岡）
C9: 0550 集計 | D9: 馬場所長（東京） | G9: 3 | H9: 1 | K9: =SUM(E9:J9) | M9: 0 | R9: =SUM(L9:Q9) | S9: =IF(E9=0,"***",L9/E9) | T9: =IF(F9=0,"***",M9/F9) | U9: =IF(G9=0,"***",N9/G9) | V9: =IF(H9=0,"***",O9/H9) | W9: =IF(I9=0,"***",P9/I9) | X9: =IF(J9=0,"***",Q9/J9) | Y9: =IF(K9=0,"***",R9/K9)
C10: 0552 集計 | D10: 馬場部長（東京） | E10: 18 | F10: 18 | G10: 18 | H10: 35 | I10: 54 | J10: 18 | K10: =SUM(E10:J10) | L10: 3 | M10: 3 | N10: 3 | O10: 6 | P10: 14 | Q10: 3 | R10: =SUM(L10:Q10) | S10: =IF(E10=0,"***",L10/E10) | T10: =IF(F10=0,"***",M10/F10) | U10: =IF(G10=0,"***",N10/G10) | V10: =IF(H10=0,"***",O10/H10) | W10: =IF(I10=0,"***",P10/I10) | X10: =IF(J10=0,"***",Q10/J10) | Y10: =IF(K10=0,"***",R10/K10)
C11: 合計 | E11: =SUM(E5:E10) | F11: =SUM(F5:F10) | G11: =SUM(G5:G10) | H11: =SUM(H5:H10) | I11: =SUM(I5:I10) | J11: =SUM(J5:J10) | K11: =SUM(K5:K10) | L11: =SUM(L5:L10) | ... Y11: =SUM(Y5:Y10)
C12: リンガーハット | E12: 22 | F12: 148 | G12: 27 | H12: 46 | I12: 83 | J12: 27 | K12: =SUM(E12:J12) | L12: 1 | M12: 4 | N12: -1 | O12: 5 | P12: 1 | Q12: -1 | R12: =SUM(L12:Q12) | S12: =IF(E12=0,"***",L12/E12) | T12: =IF(F12=0,"***",M12/F12) | U12: =IF(G12=0,"***",N12/G12) | V12: =IF(H12=0,"***",O12/H12) | W12: =IF(I12=0,"***",P12/I12) | X12: =IF(J12=0,"***",Q12/J12) | Y12: =IF(K12=0,"***",R12/K12) | Z12: 0042と0550からカネゲン引く
C13: リンガーハット以外 | E13: =E11-E12 | F13: =F11-F12 | G13: =G11-G12 | H13: =H11-H12 | I13: =I11-I12 | J13: =J11-J12 | K13: =SUM(E13:J13) | L13: =L11-L12 | M13: =M11-M12 | N13: =N11-N12 | O13: =O11-O12 | P13: =P11-P12 | Q13: =Q11-Q12 | R13: =SUM(L13:Q13) | S13: =IF(E13=0,"***",L13/E13) | T13: =IF(F13=0,"***",M13/F13) | U13: =IF(G13=0,"***",N13/G13) | V13: =IF(H13=0,"***",O13/H13) | W13: =IF(I13=0,"***",P13/I13) | X13: =IF(J13=0,"***",Q13/J13) | Y13: =IF(K13=0,"***",R13/K13) | Z13: 0042と0550からカネゲン引く
C15: 2．2025年
E16: 売上 | L16: 粗利益 | S16: 粗利益率
E17: 45748 | F17: 45778 | G17: 45809 | H17: 45839 | I17: 45870 | J17: 45901 | K17: 合計 | L17: 45748 | M17: 45778 | N17: 45809 | O17: 45839 | P17: 45870 | Q17: 45901 | R17: 合計 | S17: 45748 | T17: 45778 | U17: 45809 | V17: 45839 | W17: 45870 | X17: 45901 | Y17: 合計
C18: 0042 集計 | D18: 馬場部長（鳥栖） | E18: 49 | F18: 62 | G18: 155 | H18: 77 | I18: 23 | J18: 78 | K18: =SUM(E18:J18) | L18: 1 | M18: 4 | N18: -1 | O18: 7 | P18: 1 | Q18: -1 | R18: =SUM(L18:Q18) | S18: =IF(E18=0,"***",L18/E18) | T18: =IF(F18=0,"***",M18/F18) | U18: =IF(G18=0,"***",N18/G18) | V18: =IF(H18=0,"***",O18/H18) | W18: =IF(I18=0,"***",P18/I18) | X18: =IF(J18=0,"***",Q18/J18) | Y18: =IF(K18=0,"***",R18/K18)
C19: 0045 集計 | D19: ペーパーハグ | E19: 0 | F19: 0 | G19: 0 | H19: 0 | I19: 0 | J19: 0 | K19: =SUM(E19:J19) | R19: =SUM(L19:Q19) | S19: =IF(E19=0,"***",L19/E19) | T19: =IF(F19=0,"***",M19/F19) | U19: =IF(G19=0,"***",N19/G19) | V19: =IF(H19=0,"***",O19/H19) | W19: =IF(I19=0,"***",P19/I19) | X19: =IF(J19=0,"***",Q19/J19) | Y19: =IF(K19=0,"***",R19/K19)
C20: 0046 集計 | D20: 角田 | E20: 26 | F20: 0 | G20: 0 | H20: 0 | I20: 18 | J20: 33 | K20: =SUM(E20:J20) | L20: =L18+L19 | M20: =M18+M19 | N20: =N18+N19 | O20: =O18+O19 | P20: =P18+P19 | Q20: =Q18+Q19 | R20: =SUM(L20:Q20) | S20: =IF(E20=0,"***",L20/E20) | T20: =IF(F20=0,"***",M20/F20) | U20: =IF(G20=0,"***",N20/G20) | V20: =IF(H20=0,"***",O20/H20) | W20: =IF(I20=0,"***",P20/I20) | X20: =IF(J20=0,"***",Q20/J20) | Y20: =IF(K20=0,"***",R20/K20)
C21: 0047 集計 | D21: 馬場部長（静岡）
C22: 0550 集計 | D22: 馬場所長（東京） | G22: 0 | H22: 0 | K22: =SUM(E22:J22) | N22: 0 | O22: 0 | R22: =SUM(L22:Q22) | S22: =IF(E22=0,"***",L22/E22) | T22: =IF(F22=0,"***",M22/F22) | U22: =IF(G22=0,"***",N22/G22) | V22: =IF(H22=0,"***",O22/H22) | W22: =IF(I22=0,"***",P22/I22) | X22: =IF(J22=0,"***",Q22/J22) | Y22: =IF(K22=0,"***",R22/K22)
C23: 0552 集計 | D23: 馬場部長（東京） | E23: 85 | F23: 18 | G23: 52 | H23: 18 | I23: 29 | J23: 22 | K23: =SUM(E23:J23) | L23: 39 | M23: 3 | N23: 36 | O23: 3 | P23: 4 | Q23: 7 | R23: =SUM(L23:Q23) | S23: =IF(E23=0,"***",L23/E23) | T23: =IF(F23=0,"***",M23/F23) | U23: =IF(G23=0,"***",N23/G23) | V23: =IF(H23=0,"***",O23/H23) | W23: =IF(I23=0,"***",P23/I23) | X23: =IF(J23=0,"***",Q23/J23) | Y23: =IF(K23=0,"***",R23/K23)
C24: 合計 | E24: =SUM(E18:E23) | F24: =SUM(F18:F23) | G24: =SUM(G18:G23) | H24: =SUM(H18:H23) | I24: =SUM(I18:I23) | J24: =SUM(J18:J23) | K24: =SUM(K18:K23) | L24: =SUM(L18:L23) | ... R24: =SUM(R18:R23) | S24: =IF(E24=0,"***",L24/E24) | T24: =IF(F24=0,"***",M24/F24) | U24: =IF(G24=0,"***",N24/G24) | V24: =IF(H24=0,"***",O24/H24) | W24: =IF(I24=0,"***",P24/I24) | X24: =IF(J24=0,"***",Q24/J24) | Y24: =IF(K24=0,"***",R24/K24)
C25: 内リンガーハット | E25: 49 | F25: 62 | G25: 155 | H25: 77 | I25: 23 | J25: 78 | K25: =SUM(E25:J25) | M25: 44 | O25: 45 | R25: =SUM(L25:Q25) | S25: =IF(E25=0,"***",L25/E25) | T25: =IF(F25=0,"***",M25/F25) | U25: =IF(G25=0,"***",N25/G25) | V25: =IF(H25=0,"***",O25/H25) | W25: =IF(I25=0,"***",P25/I25) | X25: =IF(J25=0,"***",Q25/J25) | Y25: =IF(K25=0,"***",R25/K25) | Z25: 0042と0550からカネゲン引く
C26: リンガーハット以外 | E26: =E24-E25 | F26: =F24-F25 | G26: =G24-G25 | H26: =H24-H25 | I26: =I24-I25 | J26: =J24-J25 | K26: =SUM(E26:J26) | L26: =L24-L25 | M26: =M24-M25 | N26: =N24-N25 | O26: =O24-O25 | P26: =P24-P25 | Q26: =Q24-Q25 | R26: =SUM(L26:Q26) | S26: =IF(E26=0,"***",L26/E26) | T26: =IF(F26=0,"***",M26/F26) | U26: =IF(G26=0,"***",N26/G26) | V26: =IF(H26=0,"***",O26/H26) | W26: =IF(I26=0,"***",P26/I26) | X26: =IF(J26=0,"***",Q26/J26) | Y26: =IF(K26=0,"***",R26/K26) | Z26: 0042と0550からカネゲン引く
C28: 3．過年度平均
E29: 売上 | L29: 粗利益 | S29: 粗利益率
E30: 45748 | F30: 45778 | G30: 45809 | H30: 45839 | I30: 45870 | J30: 45901 | K30: 合計 | L30: 45748 | M30: 45778 | N30: 45809 | O30: 45839 | P30: 45870 | Q30: 45901 | R30: 合計 | S30: 45748 | T30: 45778 | U30: 45809 | V30: 45839 | W30: 45870 | X30: 45901 | Y30: 合計
C31: 0042 集計 | D31: 馬場部長（鳥栖） | E31: =(E18+E5)/2 | F31: =(F18+F5)/2 | G31: =(G18+G5)/2 | H31: =(H18+H5)/2 | I31: =(I18+I5)/2 | J31: =(J18+J5)/2 | K31: =SUM(E31:J31) | L31: =(L18+L5)/2 | M31: =(M18+M5)/2 | N31: =(N18+N5)/2 | O31: =(O18+O5)/2 | P31: =(P18+P5)/2 | Q31: =(Q18+Q5)/2 | R31: =SUM(L31:Q31) | S31: =IF(E31=0,"***",L31/E31) | T31: =IF(F31=0,"***",M31/F31) | U31: =IF(G31=0,"***",N31/G31) | V31: =IF(H31=0,"***",O31/H31) | W31: =IF(I31=0,"***",P31/I31) | X31: =IF(J31=0,"***",Q31/J31) | Y31: =IF(K31=0,"***",R31/K31)
C32: 0045 集計 | D32: ペーパーハグ | E32: =(E19+E6)/2 | F32: =(F19+F6)/2 | G32: =(G19+G6)/2 | H32: =(H19+H6)/2 | I32: =(I19+I6)/2 | J32: =(J19+J6)/2 | K32: =SUM(E32:J32) | L32: =(L19+L6)/2 | M32: =(M19+M6)/2 | N32: =(N19+N6)/2 | O32: =(O19+O6)/2 | P32: =(P19+P6)/2 | Q32: =(Q19+Q6)/2 | R32: =SUM(L32:Q32) | S32: =IF(E32=0,"***",L32/E32) | T32: =IF(F32=0,"***",M32/F32) | U32: =IF(G32=0,"***",N32/G32) | V32: =IF(H32=0,"***",O32/H32) | W32: =IF(I32=0,"***",P32/I32) | X32: =IF(J32=0,"***",Q32/J32) | Y32: =IF(K32=0,"***",R32/K32)
C33: 0046 集計 | D33: 角田 | E33: =(E20+E7)/2 | F33: =(F20+F7)/2 | G33: =(G20+G7)/2 | H33: =(H20+H7)/2 | I33: =(I20+I7)/2 | J33: =(J20+J7)/2 | K33: =SUM(E33:J33) | L33: =(L20+L7)/2 | M33: =(M20+M7)/2 | N33: =(N20+N7)/2 | O33: =(O20+O7)/2 | P33: =(P20+P7)/2 | Q33: =(Q20+Q7)/2 | R33: =SUM(L33:Q33) | S33: =IF(E33=0,"***",L33/E33) | T33: =IF(F33=0,"***",M33/F33) | U33: =IF(G33=0,"***",N33/G33) | V33: =IF(H33=0,"***",O33/H33) | W33: =IF(I33=0,"***",P33/I33) | X33: =IF(J33=0,"***",Q33/J33) | Y33: =IF(K33=0,"***",R33/K33)
C34: 0047 集計 | D34: 馬場部長（静岡） | E34: =(E21+E8)/2 | F34: =(F21+F8)/2 | G34: =(G21+G8)/2 | H34: =(H21+H8)/2 | I34: =(I21+I8)/2 | J34: =(J21+J8)/2 | L34: =(L21+L8)/2 | M34: =(M21+M8)/2 | N34: =(N21+N8)/2 | O34: =(O21+O8)/2 | P34: =(P21+P8)/2 | Q34: =(Q21+Q8)/2 | R34: =SUM(L34:Q34)
C35: 0550 集計 | D35: 馬場所長（東京） | E35: =(E22+E9)/2 | F35: =(F22+F9)/2 | G35: =(G22+G9)/2 | H35: =(H22+H9)/2 | I35: =(I22+I9)/2 | J35: =(J22+J9)/2 | K35: =SUM(E35:J35) | L35: =(L22+L9)/2 | M35: =(M22+M9)/2 | N35: =(N22+N9)/2 | O35: =(O22+O9)/2 | P35: =(P22+P9)/2 | Q35: =(Q22+Q9)/2 | R35: =SUM(L35:Q35) | S35: =IF(E35=0,"***",L35/E35) | T35: =IF(F35=0,"***",M35/F35) | U35: =IF(G35=0,"***",N35/G35) | V35: =IF(H35=0,"***",O35/H35) | W35: =IF(I35=0,"***",P35/I35) | X35: =IF(J35=0,"***",Q35/J35) | Y35: =IF(K35=0,"***",R35/K35)
C36: 0552 集計 | D36: 馬場部長（東京） | E36: =(E23+E10)/2 | F36: =(F23+F10)/2 | G36: =(G23+G10)/2 | H36: =(H23+H10)/2 | I36: =(I23+I10)/2 | J36: =(J23+J10)/2 | K36: =SUM(E36:J36) | L36: =(L23+L10)/2 | M36: =(M23+M10)/2 | N36: =(N23+N10)/2 | O36: =(O23+O10)/2 | P36: =(P23+P10)/2 | Q36: =(Q23+Q10)/2 | R36: =SUM(L36:Q36) | S36: =IF(E36=0,"***",L36/E36) | T36: =IF(F36=0,"***",M36/F36) | U36: =IF(G36=0,"***",N36/G36) | V36: =IF(H36=0,"***",O36/H36) | W36: =IF(I36=0,"***",P36/I36) | X36: =IF(J36=0,"***",Q36/J36) | Y36: =IF(K36=0,"***",R36/K36)
C37: 合計 | E37: =SUM(E31:E36) | F37: =SUM(F31:F36) | G37: =SUM(G31:G36) | H37: =SUM(H31:H36) | I37: =SUM(I31:I36) | J37: =SUM(J31:J36) | K37: =SUM(K31:K36) | L37: =SUM(L31:L36) | ... R37: =SUM(R31:R36) | S37: =IF(E37=0,"***",L37/E37) | T37: =IF(F37=0,"***",M37/F37) | U37: =IF(G37=0,"***",N37/G37) | V37: =IF(H37=0,"***",O37/H37) | W37: =IF(I37=0,"***",P37/I37) | X37: =IF(J37=0,"***",Q37/J37) | Y37: =IF(K37=0,"***",R37/K37)
C38: 内リンガーハット | E38: =(E25+E12)/2 | F38: =(F25+F12)/2 | G38: =(G25+G12)/2 | H38: =(H25+H12)/2 | I38: =(I25+I12)/2 | J38: =(J25+J12)/2 | K38: =SUM(E38:J38) | L38: =(L25+L12)/2 | M38: =(M25+M12)/2 | N38: =(N25+N12)/2 | O38: =(O25+O12)/2 | P38: =(P25+P12)/2 | Q38: =(Q25+Q12)/2 | R38: =SUM(L38:Q38) | S38: =IF(E38=0,"***",L38/E38) | T38: =IF(F38=0,"***",M38/F38) | U38: =IF(G38=0,"***",N38/G38) | V38: =IF(H38=0,"***",O38/H38) | W38: =IF(I38=0,"***",P38/I38) | X38: =IF(J38=0,"***",Q38/J38) | Y38: =IF(K38=0,"***",R38/K38) | Z38: 0042と0550からカネゲン引く
C39: リンガーハット以外 | E39: =E37-E38 | F39: =F37-F38 | G39: =G37-G38 | H39: =H37-H38 | I39: =I37-I38 | J39: =J37-J38 | K39: =SUM(E39:J39) | L39: =L37-L38 | M39: =M37-M38 | N39: =N37-N38 | O39: =O37-O38 | P39: =P37-P38 | Q39: =Q37-Q38 | R39: =SUM(L39:Q39) | S39: =IF(E39=0,"***",L39/E39) | T39: =IF(F39=0,"***",M39/F39) | U39: =IF(G39=0,"***",N39/G39) | V39: =IF(H39=0,"***",O39/H39) | W39: =IF(I39=0,"***",P39/I39) | X39: =IF(J39=0,"***",Q39/J39) | Y39: =IF(K39=0,"***",R39/K39) | Z39: 0042と0550からカネゲン引く
C41: 4．計画 | E41: 実績は0042と0047が分かれて出るため実績を2行にしています
E42: 売上 | L42: 粗利益 | S42: 粗利益率
E43: 46113 | F43: 46143 | G43: 46174 | H43: 46204 | I43: 46235 | J43: 46266 | K43: 合計 | L43: 46113 | M43: 46143 | N43: 46174 | O43: 46204 | P43: 46235 | Q43: 46266 | R43: 合計 | S43: 46113 | T43: 46143 | U43: 46174 | V43: 46204 | W43: 46235 | X43: 46266 | Y43: 合計
C44: 0042 集計 | D44: 馬場部長（鳥栖） | E44: 500 | F44: 500 | G44: 500 | H44: 500 | I44: 500 | J44: 500 | K44: =SUM(E44:J44) | L44: 50 | M44: 50 | N44: 50 | O44: 50 | P44: 50 | Q44: 50 | R44: =SUM(L44:Q44) | S44: =IF(E44=0,"***",L44/E44) | T44: =IF(F44=0,"***",M44/F44) | U44: =IF(G44=0,"***",N44/G44) | V44: =IF(H44=0,"***",O44/H44) | W44: =IF(I44=0,"***",P44/I44) | X44: =IF(J44=0,"***",Q44/J44) | Y44: =IF(K44=0,"***",R44/K44)
C45: 0045 集計 | D45: ペーパーハグ | K45: =SUM(E45:J45) | R45: =SUM(L45:Q45) | S45: =IF(E45=0,"***",L45/E45) | T45: =IF(F45=0,"***",M45/F45) | U45: =IF(G45=0,"***",N45/G45) | V45: =IF(H45=0,"***",O45/H45) | W45: =IF(I45=0,"***",P45/I45) | X45: =IF(J45=0,"***",Q45/J45) | Y45: =IF(K45=0,"***",R45/K45)
C46: 0046 集計 | D46: 角田 | E46: 250 | F46: 250 | G46: 250 | H46: 250 | I46: 250 | J46: 250 | K46: =SUM(E46:J46) | L46: 30 | M46: 30 | N46: 30 | O46: 30 | P46: 30 | Q46: 30 | R46: =SUM(L46:Q46) | S46: =IF(E46=0,"***",L46/E46) | T46: =IF(F46=0,"***",M46/F46) | U46: =IF(G46=0,"***",N46/G46) | V46: =IF(H46=0,"***",O46/H46) | W46: =IF(I46=0,"***",P46/I46) | X46: =IF(J46=0,"***",Q46/J46) | Y46: =IF(K46=0,"***",R46/K46)
C47: 0047 集計 | D47: 馬場部長（静岡） | K47: =SUM(E47:J47) | R47: =SUM(L47:Q47)
C48: 0550 集計 | D48: 馬場所長（東京） | K48: =SUM(E48:J48) | R48: =SUM(L48:Q48) | S48: =IF(E48=0,"***",L48/E48) | T48: =IF(F48=0,"***",M48/F48) | U48: =IF(G48=0,"***",N48/G48) | V48: =IF(H48=0,"***",O48/H48) | W48: =IF(I48=0,"***",P48/I48) | X48: =IF(J48=0,"***",Q48/J48) | Y48: =IF(K48=0,"***",R48/K48)
C49: 0552 集計 | D49: 馬場部長（東京） | E49: 250 | F49: 250 | G49: 250 | H49: 250 | I49: 250 | J49: 250 | K49: =SUM(E49:J49) | L49: 30 | M49: 30 | N49: 30 | O49: 30 | P49: 30 | Q49: 30 | R49: =SUM(L49:Q49) | S49: =IF(E49=0,"***",L49/E49) | T49: =IF(F49=0,"***",M49/F49) | U49: =IF(G49=0,"***",N49/G49) | V49: =IF(H49=0,"***",O49/H49) | W49: =IF(I49=0,"***",P49/I49) | X49: =IF(J49=0,"***",Q49/J49) | Y49: =IF(K49=0,"***",R49/K49)
C50: 合計 | E50: =SUM(E44:E49) | F50: =SUM(F44:F49) | G50: =SUM(G44:G49) | H50: =SUM(H44:H49) | I50: =SUM(I44:I49) | J50: =SUM(J44:J49) | K50: =SUM(K44:K49) | L50: =SUM(L44:L49) | ... R50: =SUM(R44:R49) | S50: =IF(E50=0,"***",L50/E50) | T50: =IF(F50=0,"***",M50/F50) | U50: =IF(G50=0,"***",N50/G50) | V50: =IF(H50=0,"***",O50/H50) | W50: =IF(I50=0,"***",P50/I50) | X50: =IF(J50=0,"***",Q50/J50) | Y50: =IF(K50=0,"***",R50/K50)
C51: 内リンガーハット | E51: =(E38+E25)/2 | F51: =(F38+F25)/2 | G51: =(G38+G25)/2 | H51: =(H38+H25)/2 | I51: =(I38+I25)/2 | J51: =(J38+J25)/2 | K51: =SUM(E51:J51) | L51: =(L38+L25)/2 | M51: =(M38+M25)/2 | N51: =(N38+N25)/2 | O51: =(O38+O25)/2 | P51: =(P38+P25)/2 | Q51: =(Q38+Q25)/2 | R51: =SUM(L51:Q51) | S51: =IF(E51=0,"***",L51/E51) | T51: =IF(F51=0,"***",M51/F51) | U51: =IF(G51=0,"***",N51/G51) | V51: =IF(H51=0,"***",O51/H51) | W51: =IF(I51=0,"***",P51/I51) | X51: =IF(J51=0,"***",Q51/J51) | Y51: =IF(K51=0,"***",R51/K51) | Z51: 0042と0550からカネゲン引く
C52: リンガーハット以外 | E52: =E50-E51 | F52: =F50-F51 | G52: =G50-G51 | H52: =H50-H51 | I52: =I50-I51 | J52: =J50-J51 | K52: =SUM(E52:J52) | L52: =L50-L51 | M52: =M50-M51 | N52: =N50-N51 | O52: =O50-O51 | P52: =P50-P51 | Q52: =Q50-Q51 | R52: =SUM(L52:Q52) | S52: =IF(E52=0,"***",L52/E52) | T52: =IF(F52=0,"***",M52/F52) | U52: =IF(G52=0,"***",N52/G52) | V52: =IF(H52=0,"***",O52/H52) | W52: =IF(I52=0,"***",P52/I52) | X52: =IF(J52=0,"***",Q52/J52) | Y52: =IF(K52=0,"***",R52/K52) | Z52: 0042と0550からカネゲン引く
C54: 5．前期比
E55: 売上 | L55: 粗利益 | S55: 粗利益率
E56: 46113 | F56: 46143 | G56: 46174 | H56: 46204 | I56: 46235 | J56: 46266 | K56: 合計 | L56: 46113 | M56: 46143 | N56: 46174 | O56: 46204 | P56: 46235 | Q56: 46266 | R56: 合計 | S56: 46113 | T56: 46143 | U56: 46174 | V56: 46204 | W56: 46235 | X56: 46266 | Y56: 合計
C57: 0042 集計 | D57: 馬場部長（鳥栖） | E57: =E44-E18 | F57: =F44-F18 | G57: =G44-G18 | H57: =H44-H18 | I57: =I44-I18 | J57: =J44-J18 | K57: =SUM(E57:J57) | L57: =L44-L18 | M57: =M44-M18 | N57: =N44-N18 | O57: =O44-O18 | P57: =P44-P18 | Q57: =Q44-Q18 | R57: =SUM(L57:Q57) | S57: =S44-S18 | T57: =T44-T18 | U57: =U44-U18 | V57: =V44-V18 | W57: =W44-W18 | X57: =X44-X18 | Y57: =Y44-Y18
C58: 0045 集計 | D58: ペーパーハグ | E58: =E45-E19 | F58: =F45-F19 | G58: =G45-G19 | H58: =H45-H19 | I58: =I45-I19 | J58: =J45-J19 | K58: =SUM(E58:J58) | L58: =L45-L19 | M58: =M45-M19 | N58: =N45-N19 | O58: =O45-O19 | P58: =P45-P19 | Q58: =Q45-Q19 | R58: =SUM(L58:Q58) | S58: =S45-S19 | T58: =T45-T19 | U58: =U45-U19 | V58: =V45-V19 | W58: =W45-W19 | X58: =X45-X19 | Y58: =Y45-Y19
C59: 0046 集計 | D59: 角田 | E59: =E46-E20 | F59: =F46-F20 | G59: =G46-G20 | H59: =H46-H20 | I59: =I46-I20 | J59: =J46-J20 | K59: =SUM(E59:J59) | L59: =L46-L20 | M59: =M46-M20 | N59: =N46-N20 | O59: =O46-O20 | P59: =P46-P20 | Q59: =Q46-Q20 | R59: =SUM(L59:Q59) | S59: =S46-S20 | T59: =T46-T20 | U59: =U46-U20 | V59: =V46-V20 | W59: =W46-W20 | X59: =X46-X20 | Y59: =Y46-Y20
C60: 0047 集計 | D60: 馬場部長（静岡） | E60: =E47-E21 | F60: =F47-F21 | G60: =G47-G21 | H60: =H47-H21 | I60: =I47-I21 | J60: =J47-J21 | K60: =SUM(E60:J60) | L60: =L47-L21 | M60: =M47-M21 | N60: =N47-N21 | O60: =O47-O21 | P60: =P47-P21 | Q60: =Q47-Q21 | R60: =SUM(L60:Q60) | S60: =S47-S21 | T60: =T47-T21 | U60: =U47-U21 | V60: =V47-V21 | W60: =W47-W21 | X60: =X47-X21 | Y60: =Y47-Y21
C61: 0550 集計 | D61: 馬場所長（東京） | E61: =E48-E22 | F61: =F48-F22 | G61: =G48-G22 | H61: =H48-H22 | I61: =I48-I22 | J61: =J48-J22 | K61: =SUM(E61:J61) | L61: =L48-L22 | M61: =M48-M22 | N61: =N48-N22 | O61: =O48-O22 | P61: =P48-P22 | Q61: =Q48-Q22 | R61: =SUM(L61:Q61) | S61: =S48-S22 | T61: =T48-T22 | U61: =U48-U22 | V61: =V48-V22 | W61: =W48-W22 | X61: =X48-X22 | Y61: =Y48-Y22
C62: 0552 集計 | D62: 馬場部長（東京） | E62: =E49-E23 | F62: =F49-F23 | G62: =G49-G23 | H62: =H49-H23 | I62: =I49-I23 | J62: =J49-J23 | K62: =SUM(E62:J62) | L62: =L49-L23 | M62: =M49-M23 | N62: =N49-N23 | O62: =O49-O23 | P62: =P49-P23 | Q62: =Q49-Q23 | R62: =SUM(L62:Q62) | S62: =S49-S23 | T62: =T49-T23 | U62: =U49-U23 | V62: =V49-V23 | W62: =W49-W23 | X62: =X49-X23 | Y62: =Y49-Y23
C63: 合計 | E63: =SUM(E57:E62) | F63: =SUM(F57:F62) | G63: =SUM(G57:G62) | H63: =SUM(H57:H62) | I63: =SUM(I57:I62) | J63: =SUM(J57:J62) | K63: =SUM(K57:K62) | L63: =SUM(L57:L62) | ... R63: =SUM(R57:R62) | S63: =S50-S24 | T63: =T50-T24 | U63: =U50-U24 | V63: =V50-V24 | W63: =W50-W24 | X63: =X50-X24 | Y63: =Y50-Y24
C64: 内リンガーハット | E64: =E51-E25 | F64: =F51-F25 | G64: =G51-G25 | H64: =H51-H25 | I64: =I51-I25 | J64: =J51-J25 | K64: =SUM(E64:J64) | L64: =L51-L25 | M64: =M51-M25 | N64: =N51-N25 | O64: =O51-O25 | P64: =P51-P25 | Q64: =Q51-Q25 | R64: =SUM(L64:Q64) | S64: =S51-S25 | T64: =T51-T25 | U64: =U51-U25 | V64: =V51-V25 | W64: =W51-W25 | X64: =X51-X25 | Y64: =Y51-Y25
C65: リンガーハット以外 | E65: =E63-E64 | F65: =F63-F64 | G65: =G63-G64 | H65: =H63-H64 | I65: =I63-I64 | J65: =J63-J64 | K65: =SUM(E65:J65) | L65: =L63-L64 | M65: =M63-M64 | N65: =N63-N64 | O65: =O63-O64 | P65: =P63-P64 | Q65: =Q63-Q64 | R65: =SUM(L65:Q65) | S65: =IF(E65=0,"***",L65/E65) | T65: =IF(F65=0,"***",M65/F65) | U65: =IF(G65=0,"***",N65/G65) | V65: =IF(H65=0,"***",O65/H65) | W65: =IF(I65=0,"***",P65/I65) | X65: =IF(J65=0,"***",Q65/J65) | Y65: =IF(K65=0,"***",R65/K65) | Z65: 0042と0550からカネゲン引く
C67: 6．過年度平均比
E68: 売上 | L68: 粗利益 | S68: 粗利益率
E69: 46113 | F69: 46143 | G69: 46174 | H69: 46204 | I69: 46235 | J69: 46266 | K69: 合計 | L69: 46113 | M69: 46143 | N69: 46174 | O69: 46204 | P69: 46235 | Q69: 46266 | R69: 合計 | S69: 46113 | T69: 46143 | U69: 46174 | V69: 46204 | W69: 46235 | X69: 46266 | Y69: 合計
C70: 0042 集計 | D70: 馬場部長（鳥栖） | E70: =E44-E31 | F70: =F44-F31 | G70: =G44-G31 | H70: =H44-H31 | I70: =I44-I31 | J70: =J44-J31 | K70: =SUM(E70:J70) | L70: =L44-L31 | M70: =M44-M31 | N70: =N44-N31 | O70: =O44-O31 | P70: =P44-P31 | Q70: =Q44-Q31 | R70: =SUM(L70:Q70) | S70: =S44-S31 | T70: =T44-T31 | U70: =U44-U31 | V70: =V44-V31 | W70: =W44-W31 | X70: =X44-X31 | Y70: =Y44-Y31
C71: 0045 集計 | D71: ペーパーハグ | E71: =E45-E32 | F71: =F45-F32 | G71: =G45-G32 | H71: =H45-H32 | I71: =I45-I32 | J71: =J45-J32 | K71: =SUM(E71:J71) | L71: =L45-L32 | M71: =M45-M32 | N71: =N45-N32 | O71: =O45-O32 | P71: =P45-P32 | Q71: =Q45-Q32 | R71: =SUM(L71:Q71) | S71: =S45-S32 | T71: =T45-T32 | U71: =U45-U32 | V71: =V45-V32 | W71: =W45-W32 | X71: =X45-X32 | Y71: =Y45-Y32
C72: 0046 集計 | D72: 角田 | E72: =E46-E33 | F72: =F46-F33 | G72: =G46-G33 | H72: =H46-H33 | I72: =I46-I33 | J72: =J46-J33 | K72: =SUM(E72:J72) | L72: =L46-L33 | M72: =M46-M33 | N72: =N46-N33 | O72: =O46-O33 | P72: =P46-P33 | Q72: =Q46-Q33 | R72: =SUM(L72:Q72) | S72: =S46-S33 | T72: =T46-T33 | U72: =U46-U33 | V72: =V46-V33 | W72: =W46-W33 | X72: =X46-X33 | Y72: =Y46-Y33
C73: 0047 集計 | D73: 馬場部長（静岡） | E73: =E47-E34 | F73: =F47-F34 | G73: =G47-G34 | H73: =H47-H34 | I73: =I47-I34 | J73: =J47-J34 | K73: =SUM(E73:J73) | L73: =L47-L34 | M73: =M47-M34 | N73: =N47-N34 | O73: =O47-O34 | P73: =P47-P34 | Q73: =Q47-Q34 | R73: =SUM(L73:Q73) | S73: =S47-S34 | T73: =T47-T34 | U73: =U47-U34 | V73: =V47-V34 | W73: =W47-W34 | X73: =X47-X34 | Y73: =Y47-Y34
C74: 0550 集計 | D74: 馬場所長（東京） | E74: =E48-E35 | F74: =F48-F35 | G74: =G48-G35 | H74: =H48-H35 | I74: =I48-I35 | J74: =J48-J35 | K74: =SUM(E74:J74) | L74: =L48-L35 | M74: =M48-M35 | N74: =N48-N35 | O74: =O48-O35 | P74: =P48-P35 | Q74: =Q48-Q35 | R74: =SUM(L74:Q74) | S74: =S48-S35 | T74: =T48-T35 | U74: =U48-U35 | V74: =V48-V35 | W74: =W48-W35 | X74: =X48-X35 | Y74: =Y48-Y35
C75: 0552 集計 | D75: 馬場部長（東京） | E75: =E49-E36 | F75: =F49-F36 | G75: =G49-G36 | H75: =H49-H36 | I75: =I49-I36 | J75: =J49-J36 | K75: =SUM(E75:J75) | L75: =L49-L36 | M75: =M49-M36 | N75: =N49-N36 | O75: =O49-O36 | P75: =P49-P36 | Q75: =Q49-Q36 | R75: =SUM(L75:Q75) | S75: =S49-S36 | T75: =T49-T36 | U75: =U49-U36 | V75: =V49-V36 | W75: =W49-W36 | X75: =X49-X36 | Y75: =Y49-Y36
C76: 合計 | E76: =SUM(E70:E75) | F76: =SUM(F70:F75) | G76: =SUM(G70:G75) | H76: =SUM(H70:H75) | I76: =SUM(I70:I75) | J76: =SUM(J70:J75) | K76: =SUM(K70:K75) | L76: =SUM(L70:L75) | ... R76: =SUM(R70:R75) | S76: =S50-S37 | T76: =T50-T37 | U76: =U50-U37 | V76: =V50-V37 | W76: =W50-W37 | X76: =X50-X37 | Y76: =Y50-Y37
C77: 内リンガーハット | E77: =E51-E38 | F77: =F51-F38 | G77: =G51-G38 | H77: =H51-H38 | I77: =I51-I38 | J77: =J51-J38 | K77: =SUM(E77:J77) | L77: =L51-L38 | M77: =M51-M38 | N77: =N51-N38 | O77: =O51-O38 | P77: =P51-P38 | Q77: =Q51-Q38 | R77: =SUM(L77:Q77) | S77: =IF(E77=0,"***",L77/E77) | T77: =IF(F77=0,"***",M77/F77) | U77: =IF(G77=0,"***",N77/G77) | V77: =IF(H77=0,"***",O77/H77) | W77: =IF(I77=0,"***",P77/I77) | X77: =IF(J77=0,"***",Q77/J77) | Y77: =IF(K77=0,"***",R77/K77) | Z77: 0042と0550からカネゲン引く
C78: リンガーハット以外 | E78: =E76-E77 | F78: =F76-F77 | G78: =G76-G77 | H78: =H76-H77 | I78: =I76-I77 | J78: =J76-J77 | K78: =SUM(E78:J78) | L78: =L76-L77 | M78: =M76-M77 | N78: =N76-N77 | O78: =O76-O77 | P78: =P76-P77 | Q78: =Q76-Q77 | R78: =SUM(L78:Q78) | S78: =IF(E78=0,"***",L78/E78) | T78: =IF(F78=0,"***",M78/F78) | U78: =IF(G78=0,"***",N78/G78) | V78: =IF(H78=0,"***",O78/H78) | W78: =IF(I78=0,"***",P78/I78) | X78: =IF(J78=0,"***",Q78/J78) | Y78: =IF(K78=0,"***",R78/K78) | Z78: 0042と0550からカネゲン引く
C80: 7．実績 | E80: 実績は0042と0047が分かれて出るため実績を2行にしています
E81: 売上 | L81: 粗利益 | S81: 粗利益率
E82: 46113 | F82: 46143 | G82: 46174 | H82: 46204 | I82: 46235 | J82: 46266 | K82: 合計 | L82: 46113 | M82: 46143 | N82: 46174 | O82: 46204 | P82: 46235 | Q82: 46266 | R82: 合計 | S82: 46113 | T82: 46143 | U82: 46174 | V82: 46204 | W82: 46235 | X82: 46266 | Y82: 合計
C83: 0042 集計 | D83: 馬場部長（鳥栖） | E83: 22 | F83: 49.6 | G83: 29.42 | H83: 46.2 | I83: 286.455 | J83: 0 | K83: =SUM(E83:J83) | L83: 0.8 | M83: 4.94 | N83: 5.78 | O83: 5 | P83: 25.625 | Q83: 0 | R83: =SUM(L83:Q83) | S83: =IF(E83=0,"***",L83/E83) | T83: =IF(F83=0,"***",M83/F83) | U83: =IF(G83=0,"***",N83/G83) | V83: =IF(H83=0,"***",O83/H83) | W83: =IF(I83=0,"***",P83/I83) | X83: =IF(J83=0,"***",Q83/J83) | Y83: =IF(K83=0,"***",R83/K83)
C84: 0045 集計 | D84: ペーパーハグ | I84: 0 | J84: 0 | K84: =SUM(E84:J84) | P84: 0 | Q84: 0 | R84: =SUM(L84:Q84) | S84: =IF(E84=0,"***",L84/E84) | T84: =IF(F84=0,"***",M84/F84) | U84: =IF(G84=0,"***",N84/G84) | V84: =IF(H84=0,"***",O84/H84) | W84: =IF(I84=0,"***",P84/I84) | X84: =IF(J84=0,"***",Q84/J84) | Y84: =IF(K84=0,"***",R84/K84)
C85: 0046 集計 | D85: 角田 | E85: 57.745 | G85: 312.761 | H85: 0 | I85: 0 | J85: 0 | K85: =SUM(E85:J85) | L85: 5.785 | N85: 6.111 | O85: 0 | P85: 0 | Q85: 0 | R85: =SUM(L85:Q85) | S85: =IF(E85=0,"***",L85/E85) | T85: =IF(F85=0,"***",M85/F85) | U85: =IF(G85=0,"***",N85/G85) | V85: =IF(H85=0,"***",O85/H85) | W85: =IF(I85=0,"***",P85/I85) | X85: =IF(J85=0,"***",Q85/J85) | Y85: =IF(K85=0,"***",R85/K85)
C86: 0047 集計 | D86: 馬場部長（静岡） | E86: 22 | I86: 0 | J86: 0 | K86: =SUM(E86:J86) | L86: 2 | P86: 0 | Q86: 0 | R86: =SUM(L86:Q86) | S86: =IF(E86=0,"***",L86/E86) | T86: =IF(F86=0,"***",M86/F86) | U86: =IF(G86=0,"***",N86/G86) | V86: =IF(H86=0,"***",O86/H86) | W86: =IF(I86=0,"***",P86/I86) | X86: =IF(J86=0,"***",Q86/J86) | Y86: =IF(K86=0,"***",R86/K86)
C87: 0550 集計 | D87: 馬場所長（東京） | I87: 0 | J87: 0 | K87: =SUM(E87:J87) | P87: 0 | Q87: 0 | R87: =SUM(L87:Q87) | S87: =IF(E87=0,"***",L87/E87) | T87: =IF(F87=0,"***",M87/F87) | U87: =IF(G87=0,"***",N87/G87) | V87: =IF(H87=0,"***",O87/H87) | W87: =IF(I87=0,"***",P87/I87) | X87: =IF(J87=0,"***",Q87/J87) | Y87: =IF(K87=0,"***",R87/K87)
C88: 0552 集計 | D88: 馬場部長（東京） | E88: 21.24 | F88: 49.2 | G88: 18 | H88: 138.46 | I88: 76.6 | J88: 18 | K88: =SUM(E88:J88) | L88: 6.24 | M88: 14.7 | N88: 3 | O88: 22.21 | P88: 14.72 | Q88: 3 | R88: =SUM(L88:Q88) | S88: =IF(E88=0,"***",L88/E88) | T88: =IF(F88=0,"***",M88/F88) | U88: =IF(G88=0,"***",N88/G88) | V88: =IF(H88=0,"***",O88/H88) | W88: =IF(I88=0,"***",P88/I88) | X88: =IF(J88=0,"***",Q88/J88) | Y88: =IF(K88=0,"***",R88/K88)
C89: 合計 | E89: =SUM(E83:E88) | F89: =SUM(F83:F88) | G89: =SUM(G83:G88) | H89: =SUM(H83:H88) | I89: =SUM(I83:I88) | J89: =SUM(J83:J88) | K89: =SUM(K83:K88) | L89: =SUM(L83:L88) | ... R89: =SUM(R83:R88) | S89: =IF(E89=0,"***",L89/E89) | T89: =IF(F89=0,"***",M89/F89) | U89: =IF(G89=0,"***",N89/G89) | V89: =IF(H89=0,"***",O89/H89) | W89: =IF(I89=0,"***",P89/I89) | X89: =IF(J89=0,"***",Q89/J89) | Y89: =IF(K89=0,"***",R89/K89)
C90: 内リンガーハット | E90: 44 | F90: 49.6 | G90: 29.42 | H90: 46.2 | I90: 286.455 | J90: 0 | K90: =SUM(E90:J90) | L90: 2.8 | M90: 4.94 | N90: 5.78 | O90: 5 | P90: 25.625 | Q90: 0 | R90: =SUM(L90:Q90) | S90: =IF(E90=0,"***",L90/E90) | T90: =IF(F90=0,"***",M90/F90) | U90: =IF(G90=0,"***",N90/G90) | V90: =IF(H90=0,"***",O90/H90) | W90: =IF(I90=0,"***",P90/I90) | X90: =IF(J90=0,"***",Q90/J90) | Y90: =IF(K90=0,"***",R90/K90) | Z90: 0042と0550からカネゲン引く
C91: リンガーハット以外 | E91: =E89-E90 | F91: =F89-F90 | G91: =G89-G90 | H91: =H89-H90 | I91: =I89-I90 | J91: =J89-J90 | K91: =SUM(E91:J91) | L91: =L89-L90 | M91: =M89-M90 | N91: =N89-N90 | O91: =O89-O90 | P91: =P89-P90 | Q91: =Q89-Q90 | R91: =SUM(L91:Q91) | S91: =IF(E91=0,"***",L91/E91) | T91: =IF(F91=0,"***",M91/F91) | U91: =IF(G91=0,"***",N91/G91) | V91: =IF(H91=0,"***",O91/H91) | W91: =IF(I91=0,"***",P91/I91) | X91: =IF(J91=0,"***",Q91/J91) | Y91: =IF(K91=0,"***",R91/K91) | Z91: 0042と0550からカネゲン引く
C93: 8．計画比
E94: 売上 | L94: 粗利益 | S94: 粗利益率
E95: 46113 | F95: 46143 | G95: 46174 | H95: 46204 | I95: 46235 | J95: 46266 | K95: 合計 | L95: 46113 | M95: 46143 | N95: 46174 | O95: 46204 | P95: 46235 | Q95: 46266 | R95: 合計 | S95: 46113 | T95: 46143 | U95: 46174 | V95: 46204 | W95: 46235 | X95: 46266 | Y95: 合計
C96: 0042 集計 | D96: 馬場部長（鳥栖） | E96: =E83-E44 | F96: =F83-F44 | G96: =G83-G44 | H96: =H83-H44 | I96: =I83-I44 | J96: =J83-J44 | K96: =SUM(E96:J96) | L96: =L83-L44 | M96: =M83-M44 | N96: =N83-N44 | O96: =O83-O44 | P96: =P83-P44 | Q96: =Q83-Q44 | R96: =SUM(L96:Q96) | S96: =S83-S44 | T96: =T83-T44 | U96: =U83-U44 | V96: =V83-V44 | W96: =W83-W44 | X96: =X83-X44 | Y96: =Y83-Y44
C97: 0045 集計 | D97: ペーパーハグ | E97: =E84-E45 | F97: =F84-F45 | G97: =G84-G45 | H97: =H84-H45 | I97: =I84-I45 | J97: =J84-J45 | K97: =SUM(E97:J97) | L97: =L84-L45 | M97: =M84-M45 | N97: =N84-N45 | O97: =O84-O45 | P97: =P84-P45 | Q97: =Q84-Q45 | R97: =SUM(L97:Q97) | S97: =S84-S45 | T97: =T84-T45 | U97: =U84-U45 | V97: =V84-V45 | W97: =W84-W45 | X97: =X84-X45 | Y97: =Y84-Y45
C98: 0046 集計 | D98: 角田 | E98: =E85-E46 | F98: =F85-F46 | G98: =G85-G46 | H98: =H85-H46 | I98: =I85-I46 | J98: =J85-J46 | K98: =SUM(E98:J98) | L98: =L85-L46 | M98: =M85-M46 | N98: =N85-N46 | O98: =O85-O46 | P98: =P85-P46 | Q98: =Q85-Q46 | R98: =SUM(L98:Q98) | S98: =S85-S46 | T98: =T85-T46 | U98: =U85-U46 | V98: =V85-V46 | W98: =W85-W46 | X98: =X85-X46 | Y98: =Y85-Y46
C99: 0047 集計 | D99: 馬場部長（静岡） | E99: =E86-E47 | F99: =F86-F47 | G99: =G86-G47 | H99: =H86-H47 | I99: =I86-I47 | J99: =J86-J47 | K99: =SUM(E99:J99) | L99: =L86-L47 | M99: =M86-M47 | N99: =N86-N47 | O99: =O86-O47 | P99: =P86-P47 | Q99: =Q86-Q47 | R99: =SUM(L99:Q99) | S99: =S86-S47 | T99: =T86-T47 | U99: =U86-U47 | V99: =V86-V47 | W99: =W86-W47 | X99: =X86-X47 | Y99: =Y86-Y47
C100: 0550 集計 | D100: 馬場所長（東京） | E100: =E87-E48 | F100: =F87-F48 | G100: =G87-G48 | H100: =H87-H48 | I100: =I87-I48 | J100: =J87-J48 | K100: =SUM(E100:J100) | L100: =L87-L48 | M100: =M87-M48 | N100: =N87-N48 | O100: =O87-O48 | P100: =P87-P48 | Q100: =Q87-Q48 | R100: =SUM(L100:Q100) | S100: =S87-S48 | T100: =T87-T48 | U100: =U87-U48 | V100: =V87-V48 | W100: =W87-W48 | X100: =X87-X48 | Y100: =Y87-Y48
C101: 0552 集計 | D101: 馬場部長（東京） | E101: =E88-E49 | F101: =F88-F49 | G101: =G88-G49 | H101: =H88-H49 | I101: =I88-I49 | J101: =J88-J49 | K101: =SUM(E101:J101) | L101: =L88-L49 | M101: =M88-M49 | N101: =N88-N49 | O101: =O88-O49 | P101: =P88-P49 | Q101: =Q88-Q49 | R101: =SUM(L101:Q101) | S101: =S88-S49 | T101: =T88-T49 | U101: =U88-U49 | V101: =V88-V49 | W101: =W88-W49 | X101: =X88-X49 | Y101: =Y88-Y49
C102: 合計 | E102: =SUM(E96:E101) | F102: =SUM(F96:F101) | G102: =SUM(G96:G101) | H102: =SUM(H96:H101) | I102: =SUM(I96:I101) | J102: =SUM(J96:J101) | K102: =SUM(K96:K101) | L102: =SUM(L96:L101) | ... R102: =SUM(R96:R101) | S102: =S89-S50 | T102: =T89-T50 | U102: =U89-U50 | V102: =V89-V50 | W102: =W89-W50 | X102: =X89-X50 | Y102: =Y89-Y50
C103: 内リンガーハット | F103: 49.6 | K103: =SUM(E103:J103) | M103: 4.94 | R103: =SUM(L103:Q103) | S103: =S90-S51 | T103: =T90-T51 | U103: =U90-U51 | V103: =V90-V51 | W103: =W90-W51 | X103: =X90-X51 | Y103: =Y90-Y51 | Z103: 0042と0550からカネゲン引く
C104: リンガーハット以外 | E104: =E102-E103 | F104: =F102-F103 | G104: =G102-G103 | H104: =H102-H103 | I104: =I102-I103 | J104: =J102-J103 | K104: =SUM(E104:J104) | L104: =L102-L103 | M104: =M102-M103 | N104: =N102-N103 | O104: =O102-O103 | P104: =P102-P103 | Q104: =Q102-Q103 | R104: =SUM(L104:Q104) | S104: =S91-S52 | T104: =T91-T52 | U104: =U91-U52 | V104: =V91-V52 | W104: =W91-W52 | X104: =X91-X52 | Y104: =Y91-Y52 | Z104: 0042と0550からカネゲン引く
C106: 9．前期比
E107: 売上 | L107: 粗利益 | S107: 粗利益率
E108: 46113 | F108: 46143 | G108: 46174 | H108: 46204 | I108: 46235 | J108: 46266 | K108: 合計 | L108: 46113 | M108: 46143 | N108: 46174 | O108: 46204 | P108: 46235 | Q108: 46266 | R108: 合計 | S108: 46113 | T108: 46143 | U108: 46174 | V108: 46204 | W108: 46235 | X108: 46266 | Y108: 合計
...

Sheet 全体
C1: 広域営業部全体
C2: 1．2024年
E3: 売上 | L3: 粗利益 | S3: 粗利益率
E4: 45383 | F4: 45413 | G4: 45444 | H4: 45474 | I4: 45505 | J4: 45536 | K4: 合計 | L4: 45383 | M4: 45413 | N4: 45444 | O4: 45474 | P4: 45505 | Q4: 45536 | R4: 合計 | S4: 45383 | T4: 45413 | U4: 45444 | V4: 45474 | W4: 45505 | X4: 45536 | Y4: 合計
C5: 0042 集計 | D5: 馬場部長（鳥栖） | E5: 26386.247 | F5: 26971.12 | G5: 27114.709 | H5: 27167.311 | I5: 29803.714 | J5: 27213.514 | K5: =SUM(E5:J5) | L5: 3948.893 | M5: 3790.598 | N5: 3848.321 | O5: 3623.105 | P5: 3770.767 | Q5: 4090.452 | R5: =SUM(L5:Q5) | S5: =IF(E5=0,"***",L5/E5) | T5: =IF(F5=0,"***",M5/F5) | U5: =IF(G5=0,"***",N5/G5) | V5: =IF(H5=0,"***",O5/H5) | W5: =IF(I5=0,"***",P5/I5) | X5: =IF(J5=0,"***",Q5/J5) | Y5: =IF(K5=0,"***",R5/K5)
C6: 0045 集計 | D6: ペーパーハグ | E6: 0 | F6: 0 | G6: 3.3 | H6: 0 | I6: 0 | J6: 0 | K6: =SUM(E6:J6) | L6: 0 | M6: 0 | N6: 0.53 | O6: 0 | P6: 0 | Q6: 0
C7: 0046 集計 | D7: 角田 | E7: 5228.142 | F7: 4797.901 | G7: 5029.399 | H7: 5698.966 | I7: 5858.116 | J7: 4770.001 | K7: =SUM(E7:J7) | L7: 932.496 | M7: 815.263 | N7: 927.197 | O7: 1039.285 | P7: 1098.501 | Q7: 981.102 | R7: =SUM(L7:Q7) | S7: =IF(E7=0,"***",L7/E7) | T7: =IF(F7=0,"***",M7/F7) | U7: =IF(G7=0,"***",N7/G7) | V7: =IF(H7=0,"***",O7/H7) | W7: =IF(I7=0,"***",P7/I7) | X7: =IF(J7=0,"***",Q7/J7) | Y7: =IF(K7=0,"***",R7/K7)
C8: 0047 集計 | D8: 馬場部長（静岡） | E8: 0 | F8: 0 | G8: 0 | H8: 0 | I8: 0 | J8: 0 | K8: =SUM(E8:J8) | L8: 0 | M8: 0 | N8: 0 | O8: 0 | P8: 0 | Q8: 0
C9: 0550 集計 | D9: 馬場所長（東京） | E9: 119 | F9: -3482.785 | G9: 214.6 | H9: 3732.15 | I9: 195.075 | J9: 131.425 | K9: =SUM(E9:J9) | L9: 50 | M9: -368 | N9: 51.376 | O9: 482.149 | P9: 53.971 | Q9: 55.625 | R9: =SUM(L9:Q9) | S9: =IF(E9=0,"***",L9/E9) | T9: =IF(F9=0,"***",M9/F9) | U9: =IF(G9=0,"***",N9/G9) | V9: =IF(H9=0,"***",O9/H9) | W9: =IF(I9=0,"***",P9/I9) | X9: =IF(J9=0,"***",Q9/J9) | Y9: =IF(K9=0,"***",R9/K9)
C10: 0552 集計 | D10: 馬場部長（東京） | E10: 2089.362 | F10: 2216.486 | G10: 4958.206 | H10: 1725.873 | I10: 2241.943 | J10: 4914.884 | K10: =SUM(E10:J10) | L10: 227.091 | M10: 241.8505 | N10: 425.859 | O10: 195.984 | P10: 264.976 | Q10: 427.93 | R10: =SUM(L10:Q10) | S10: =IF(E10=0,"***",L10/E10) | T10: =IF(F10=0,"***",M10/F10) | U10: =IF(G10=0,"***",N10/G10) | V10: =IF(H10=0,"***",O10/H10) | W10: =IF(I10=0,"***",P10/I10) | X10: =IF(J10=0,"***",Q10/J10) | Y10: =IF(K10=0,"***",R10/K10)
C11: 合計 | E11: =SUM(E5:E10) | F11: =SUM(F5:F10) | G11: =SUM(G5:G10) | H11: =SUM(H5:H10) | I11: =SUM(I5:I10) | J11: =SUM(J5:J10) | K11: =SUM(K5:K10) | L11: =SUM(L5:L10) | ... Y11: =SUM(Y5:Y10)
C12: リンガーハット | E12: 24579.713 | F12: 21871.365 | G12: 26248.349 | H12: 29746.479 | I12: 28967.532 | J12: 26179.68 | K12: =SUM(E12:J12) | L12: 3729.805 | M12: 3148.576 | N12: 3729.589 | O12: 3940.045 | P12: 3790.54 | Q12: 3985.081 | R12: =SUM(L12:Q12) | S12: =IF(E12=0,"***",L12/E12) | T12: =IF(F12=0,"***",M12/F12) | U12: =IF(G12=0,"***",N12/G12) | V12: =IF(H12=0,"***",O12/H12) | W12: =IF(I12=0,"***",P12/I12) | X12: =IF(J12=0,"***",Q12/J12) | Y12: =SUM(S12:X12) | Z12: 0042と0550からカネゲン引く
C13: リンガーハット以外 | E13: =E11-E12 | F13: =F11-F12 | G13: =G11-G12 | H13: =H11-H12 | I13: =I11-I12 | J13: =J11-J12 | K13: =SUM(E13:J13) | L13: =L11-L12 | M13: =M11-M12 | N13: =N11-N12 | O13: =O11-O12 | P13: =P11-P12 | Q13: =Q11-Q12 | R13: =SUM(L13:Q13) | S13: =IF(E13=0,"***",L13/E13) | T13: =IF(F13=0,"***",M13/F13) | U13: =IF(G13=0,"***",N13/G13) | V13: =IF(H13=0,"***",O13/H13) | W13: =IF(I13=0,"***",P13/I13) | X13: =IF(J13=0,"***",Q13/J13) | Y13: =SUM(S13:X13) | Z13: 0042と0550からカネゲン引く
C15: 2．2025年
E16: 売上 | L16: 粗利益 | S16: 粗利益率
E17: 45748 | F17: 45778 | G17: 45809 | H17: 45839 | I17: 45870 | J17: 45901 | K17: 合計 | L17: 45748 | M17: 45778 | N17: 45809 | O17: 45839 | P17: 45870 | Q17: 45901 | R17: 合計 | S17: 45748 | T17: 45778 | U17: 45809 | V17: 45839 | W17: 45870 | X17: 45901 | Y17: 合計
C18: 0042 集計 | D18: 馬場部長（鳥栖） | E18: 30550.707 | F18: 26569.409 | G18: 27573.182 | H18: 31429.011 | I18: 30768.325 | J18: 30659.494 | K18: =SUM(E18:J18) | L18: 4866.252 | M18: 3636.631 | N18: 4122.204 | O18: 4576.347 | P18: 4390.406 | Q18: 4513.813 | R18: =SUM(L18:Q18) | S18: =IF(E18=0,"***",L18/E18) | T18: =IF(F18=0,"***",M18/F18) | U18: =IF(G18=0,"***",N18/G18) | V18: =IF(H18=0,"***",O18/H18) | W18: =IF(I18=0,"***",P18/I18) | X18: =IF(J18=0,"***",Q18/J18) | Y18: =IF(K18=0,"***",R18/K18)
C19: 0045 集計 | D19: ペーパーハグ | E19: 0 | F19: 0 | G19: 0 | H19: 0 | I19: 5.8 | J19: 0 | K19: =SUM(E19:J19) | L19: 0 | M19: 0 | N19: 0 | O19: 0 | P19: 0.79 | Q19: 0 | R19: =SUM(L19:Q19) | S19: =IF(E19=0,"***",L19/E19) | T19: =IF(F19=0,"***",M19/F19) | U19: =IF(G19=0,"***",N19/G19) | V19: =IF(H19=0,"***",O19/H19) | W19: =IF(I19=0,"***",P19/I19) | X19: =IF(J19=0,"***",Q19/J19) | Y19: =IF(K19=0,"***",R19/K19)
C20: 0046 集計 | D20: 角田 | E20: 7092.263 | F20: 4261.299 | G20: 5606.113 | H20: 6717.742 | I20: 5607.593 | J20: 4580.451 | K20: =SUM(E20:J20) | L20: 1325.635 | M20: 843.723 | N20: 1018.994 | O20: 1302.026 | P20: 1156.275 | Q20: 870.391 | R20: =SUM(L20:Q20) | S20: =IF(E20=0,"***",L20/E20) | T20: =IF(F20=0,"***",M20/F20) | U20: =IF(G20=0,"***",N20/G20) | V20: =IF(H20=0,"***",O20/H20) | W20: =IF(I20=0,"***",P20/I20) | X20: =IF(J20=0,"***",Q20/J20) | Y20: =IF(K20=0,"***",R20/K20)
C21: 0047 集計 | D21: 馬場部長（静岡） | E21: 0 | F21: 0 | G21: 0 | H21: 0 | I21: 0 | J21: 0 | L21: 0 | M21: 0 | N21: 0 | O21: 0 | P21: 0 | Q21: 0
C22: 0550 集計 | D22: 馬場所長（東京） | E22: 360.673 | F22: 658.225 | G22: 545.225 | H22: 206 | I22: 395.325 | J22: 860.024 | K22: =SUM(E22:J22) | L22: 128.768 | M22: 147.685 | N22: 247.17 | O22: 100 | P22: 121.105 | Q22: 214.677 | R22: =SUM(L22:Q22) | S22: =IF(E22=0,"***",L22/E22) | T22: =IF(F22=0,"***",M22/F22) | U22: =IF(G22=0,"***",N22/G22) | V22: =IF(H22=0,"***",O22/H22) | W22: =IF(I22=0,"***",P22/I22) | X22: =IF(J22=0,"***",Q22/J22) | Y22: =IF(K22=0,"***",R22/K22)
C23: 0552 集計 | D23: 馬場部長（東京） | E23: 8777.215 | F23: 6581.314 | G23: 7833.661 | H23: 3951.749 | I23: 3566.672 | J23: 5578.054 | K23: =SUM(E23:J23) | L23: 1132.509 | M23: 632.228 | N23: 975.502 | O23: 665.771 | P23: 421.772 | Q23: 522.108 | R23: =SUM(L23:Q23) | S23: =IF(E23=0,"***",L23/E23) | T23: =IF(F23=0,"***",M23/F23) | U23: =IF(G23=0,"***",N23/G23) | V23: =IF(H23=0,"***",O23/H23) | W23: =IF(I23=0,"***",P23/I23) | X23: =IF(J23=0,"***",Q23/J23) | Y23: =IF(K23=0,"***",R23/K23)
C24: 合計 | E24: =SUM(E18:E23) | F24: =SUM(F18:F23) | G24: =SUM(G18:G23) | H24: =SUM(H18:H23) | I24: =SUM(I18:I23) | J24: =SUM(J18:J23) | K24: =SUM(K18:K23) | L24: =SUM(L18:L23) | ... R24: =SUM(R18:R23) | S24: =IF(E24=0,"***",L24/E24) | T24: =IF(F24=0,"***",M24/F24) | U24: =IF(G24=0,"***",N24/G24) | V24: =IF(H24=0,"***",O24/H24) | W24: =IF(I24=0,"***",P24/I24) | X24: =IF(J24=0,"***",Q24/J24) | Y24: =IF(K24=0,"***",R24/K24)
C25: 内リンガーハット | E25: 29836.46 | F25: 25889.141 | G25: 27401.864 | H25: 30161.422 | I25: 29499.674 | J25: 30553.051 | K25: =SUM(E25:J25) | L25: 4812.843 | M25: 3628.179 | N25: 4290.655 | O25: 4536.108 | P25: 4379.268 | Q25: 4616.129 | R25: =SUM(L25:Q25) | S25: =IF(E25=0,"***",L25/E25) | T25: =IF(F25=0,"***",M25/F25) | U25: =IF(G25=0,"***",N25/G25) | V25: =IF(H25=0,"***",O25/H25) | W25: =IF(I25=0,"***",P25/I25) | X25: =IF(J25=0,"***",Q25/J25) | Y25: =IF(K25=0,"***",R25/K25) | Z25: 0042と0550からカネゲン引く
C26: リンガーハット以外 | E26: =E24-E25 | F26: =F24-F25 | G26: =G24-G25 | H26: =H24-H25 | I26: =I24-I25 | J26: =J24-J25 | K26: =SUM(E26:J26) | L26: =L24-L25 | M26: =M24-M25 | N26: =N24-N25 | O26: =O24-O25 | P26: =P24-P25 | Q26: =Q24-Q25 | R26: =SUM(L26:Q26) | S26: =IF(E26=0,"***",L26/E26) | T26: =IF(F26=0,"***",M26/F26) | U26: =IF(G26=0,"***",N26/G26) | V26: =IF(H26=0,"***",O26/H26) | W26: =IF(I26=0,"***",P26/I26) | X26: =IF(J26=0,"***",Q26/J26) | Y26: =SUM(S26:X26) | Z26: 0042と0550からカネゲン引く
C28: 3．過年度平均
E29: 売上 | L29: 粗利益 | S29: 粗利益率
E30: 45748 | F30: 45778 | G30: 45809 | H30: 45839 | I30: 45870 | J30: 45901 | K30: 合計 | L30: 45748 | M30: 45778 | N30: 45809 | O30: 45839 | P30: 45870 | Q30: 45901 | R30: 合計 | S30: 45748 | T30: 45778 | U30: 45809 | V30: 45839 | W30: 45870 | X30: 45901 | Y30: 合計
C31: 0042 集計 | D31: 馬場部長（鳥栖） | E31: =(E18+E5)/2 | F31: =(F18+F5)/2 | G31: =(G18+G5)/2 | H31: =(H18+H5)/2 | I31: =(I18+I5)/2 | J31: =(J18+J5)/2 | K31: =SUM(E31:J31) | L31: =(L18+L5)/2 | M31: =(M18+M5)/2 | N31: =(N18+N5)/2 | O31: =(O18+O5)/2 | P31: =(P18+P5)/2 | Q31: =(Q18+Q5)/2 | R31: =SUM(L31:Q31) | S31: =IF(E31=0,"***",L31/E31) | T31: =IF(F31=0,"***",M31/F31) | U31: =IF(G31=0,"***",N31/G31) | V31: =IF(H31=0,"***",O31/H31) | W31: =IF(I31=0,"***",P31/I31) | X31: =IF(J31=0,"***",Q31/J31) | Y31: =IF(K31=0,"***",R31/K31)
C32: 0045 集計 | D32: ペーパーハグ | E32: =(E19+E6)/2 | F32: =(F19+F6)/2 | G32: =(G19+G6)/2 | H32: =(H19+H6)/2 | I32: =(I19+I6)/2 | J32: =(J19+J6)/2 | K32: =SUM(E32:J32) | L32: =(L19+L6)/2 | M32: =(M19+M6)/2 | N32: =(N19+N6)/2 | O32: =(O19+O6)/2 | P32: =(P19+P6)/2 | Q32: =(Q19+Q6)/2 | R32: =SUM(L32:Q32) | S32: =IF(E32=0,"***",L32/E32) | T32: =IF(F32=0,"***",M32/F32) | U32: =IF(G32=0,"***",N32/G32) | V32: =IF(H32=0,"***",O32/H32) | W32: =IF(I32=0,"***",P32/I32) | X32: =IF(J32=0,"***",Q32/J32) | Y32: =IF(K32=0,"***",R32/K32)
C33: 0046 集計 | D33: 角田 | E33: =(E20+E7)/2 | F33: =(F20+F7)/2 | G33: =(G20+G7)/2 | H33: =(H20+H7)/2 | I33: =(I20+I7)/2 | J33: =(J20+J7)/2 | K33: =SUM(E33:J33) | L33: =(L20+L7)/2 | M33: =(M20+M7)/2 | N33: =(N20+N7)/2 | O33: =(O20+O7)/2 | P33: =(P20+P7)/2 | Q33: =(Q20+Q7)/2 | R33: =SUM(L33:Q33) | S33: =IF(E33=0,"***",L33/E33) | T33: =IF(F33=0,"***",M33/F33) | U33: =IF(G33=0,"***",N33/G33) | V33: =IF(H33=0,"***",O33/H33) | W33: =IF(I33=0,"***",P33/I33) | X33: =IF(J33=0,"***",Q33/J33) | Y33: =IF(K33=0,"***",R33/K33)
C34: 0047 集計 | D34: 馬場部長（静岡） | E34: =(E21+E8)/2 | F34: =(F21+F8)/2 | G34: =(G21+G8)/2 | H34: =(H21+H8)/2 | I34: =(I21+I8)/2 | J34: =(J21+J8)/2 | K34: =SUM(E34:J34) | L34: =(L21+L8)/2 | M34: =(M21+M8)/2 | N34: =(N21+N8)/2 | O34: =(O21+O8)/2 | P34: =(P21+P8)/2 | Q34: =(Q21+Q8)/2
C35: 0550 集計 | D35: 馬場所長（東京） | E35: =(E22+E9)/2 | F35: =(F22+F9)/2 | G35: =(G22+G9)/2 | H35: =(H22+H9)/2 | I35: =(I22+I9)/2 | J35: =(J22+J9)/2 | K35: =SUM(E35:J35) | L35: =(L22+L9)/2 | M35: =(M22+M9)/2 | N35: =(N22+N9)/2 | O35: =(O22+O9)/2 | P35: =(P22+P9)/2 | Q35: =(Q22+Q9)/2 | R35: =SUM(L35:Q35) | S35: =IF(E35=0,"***",L35/E35) | T35: =IF(F35=0,"***",M35/F35) | U35: =IF(G35=0,"***",N35/G35) | V35: =IF(H35=0,"***",O35/H35) | W35: =IF(I35=0,"***",P35/I35) | X35: =IF(J35=0,"***",Q35/J35) | Y35: =IF(K35=0,"***",R35/K35)
C36: 0552 集計 | D36: 馬場部長（東京） | E36: =(E23+E10)/2 | F36: =(F23+F10)/2 | G36: =(G23+G10)/2 | H36: =(H23+H10)/2 | I36: =(I23+I10)/2 | J36: =(J23+J10)/2 | K36: =SUM(E36:J36) | L36: =(L23+L10)/2 | M36: =(M23+M10)/2 | N36: =(N23+N10)/2 | O36: =(O23+O10)/2 | P36: =(P23+P10)/2 | Q36: =(Q23+Q10)/2 | R36: =SUM(L36:Q36) | S36: =IF(E36=0,"***",L36/E36) | T36: =IF(F36=0,"***",M36/F36) | U36: =IF(G36=0,"***",N36/G36) | V36: =IF(H36=0,"***",O36/H36) | W36: =IF(I36=0,"***",P36/I36) | X36: =IF(J36=0,"***",Q36/J36) | Y36: =IF(K36=0,"***",R36/K36)
C37: 合計 | E37: =SUM(E31:E36) | F37: =SUM(F31:F36) | G37: =SUM(G31:G36) | H37: =SUM(H31:H36) | I37: =SUM(I31:I36) | J37: =SUM(J31:J36) | K37: =SUM(K31:K36) | L37: =SUM(L31:L36) | ... R37: =SUM(R31:R36) | S37: =IF(E37=0,"***",L37/E37) | T37: =IF(F37=0,"***",M37/F37) | U37: =IF(G37=0,"***",N37/G37) | V37: =IF(H37=0,"***",O37/H37) | W37: =IF(I37=0,"***",P37/I37) | X37: =IF(J37=0,"***",Q37/J37) | Y37: =IF(K37=0,"***",R37/K37)
C38: 内リンガーハット | E38: =(E25+E12)/2 | F38: =(F25+F12)/2 | G38: =(G25+G12)/2 | H38: =(H25+H12)/2 | I38: =(I25+I12)/2 | J38: =(J25+J12)/2 | K38: =SUM(E38:J38) | L38: =(L25+L12)/2 | M38: =(M25+M12)/2 | N38: =(N25+N12)/2 | O38: =(O25+O12)/2 | P38: =(P25+P12)/2 | Q38: =(Q25+Q12)/2 | R38: =SUM(L38:Q38) | S38: =IF(E38=0,"***",L38/E38) | T38: =IF(F38=0,"***",M38/F38) | U38: =IF(G38=0,"***",N38/G38) | V38: =IF(H38=0,"***",O38/H38) | W38: =IF(I38=0,"***",P38/I38) | X38: =IF(J38=0,"***",Q38/J38) | Y38: =IF(K38=0,"***",R38/K38) | Z38: 0042と0550からカネゲン引く
C39: リンガーハット以外 | E39: =E37-E38 | F39: =F37-F38 | G39: =G37-G38 | H39: =H37-H38 | I39: =I37-I38 | J39: =J37-J38 | K39: =SUM(E39:J39) | L39: =L37-L38 | M39: =M37-M38 | N39: =N37-N38 | O39: =O37-O38 | P39: =P37-P38 | Q39: =Q37-Q38 | R39: =SUM(L39:Q39) | S39: =IF(E39=0,"***",L39/E39) | T39: =IF(F39=0,"***",M39/F39) | U39: =IF(G39=0,"***",N39/G39) | V39: =IF(H39=0,"***",O39/H39) | W39: =IF(I39=0,"***",P39/I39) | X39: =IF(J39=0,"***",Q39/J39) | Y39: =SUM(S39:X39) | Z39: 0042と0550からカネゲン引く
C41: 4．計画 | E41: 実績は0042と0047が分かれて出るため実績を2行にしています
E42: 売上 | L42: 粗利益 | S42: 粗利益率
E43: 46113 | F43: 46143 | G43: 46174 | H43: 46204 | I43: 46235 | J43: 46266 | K43: 合計 | L43: 46113 | M43: 46143 | N43: 46174 | O43: 46204 | P43: 46235 | Q43: 46266 | R43: 合計 | S43: 46113 | T43: 46143 | U43: 46174 | V43: 46204 | W43: 46235 | X43: 46266 | Y43: 合計
A44: 売106.4％ | C44: 0042 集計 | D44: 馬場部長（鳥栖） | E44: =機械!E44+包装資材!E44 | F44: =機械!F44+包装資材!F44 | G44: =機械!G44+包装資材!G44 | H44: =機械!H44+包装資材!H44 | I44: =機械!I44+包装資材!I44 | J44: =機械!J44+包装資材!J44 | K44: =SUM(E44:J44) | L44: =機械!L44+包装資材!L44 | M44: =機械!M44+包装資材!M44 | N44: =機械!N44+包装資材!N44 | O44: =機械!O44+包装資材!O44 | P44: =機械!P44+包装資材!P44 | Q44: =機械!Q44+包装資材!Q44 | R44: =SUM(L44:Q44) | S44: =IF(E44=0,"***",L44/E44) | T44: =IF(F44=0,"***",M44/F44) | U44: =IF(G44=0,"***",N44/G44) | V44: =IF(H44=0,"***",O44/H44) | W44: =IF(I44=0,"***",P44/I44) | X44: =IF(J44=0,"***",Q44/J44) | Y44: =IF(K44=0,"***",R44/K44)
A45: 粗利額104.6％ | C45: 0045 集計 | D45: ペーパーハグ | E45: =機械!E45+包装資材!E45 | F45: =機械!F45+包装資材!F45 | G45: =機械!G45+包装資材!G45 | H45: =機械!H45+包装資材!H45 | I45: =機械!I45+包装資材!I45 | J45: =機械!J45+包装資材!J45 | K45: =SUM(E45:J45) | R45: =SUM(L45:Q45) | S45: =IF(E45=0,"***",L45/E45) | T45: =IF(F45=0,"***",M45/F45) | U45: =IF(G45=0,"***",N45/G45) | V45: =IF(H45=0,"***",O45/H45) | W45: =IF(I45=0,"***",P45/I45) | X45: =IF(J45=0,"***",Q45/J45) | Y45: =IF(K45=0,"***",R45/K45)
A46: 率改善0.5％ | C46: 0046 集計 | D46: 角田 | E46: =機械!E46+包装資材!E46 | F46: =機械!F46+包装資材!F46 | G46: =機械!G46+包装資材!G46 | H46: =機械!H46+包装資材!H46 | I46: =機械!I46+包装資材!I46 | J46: =機械!J46+包装資材!J46 | K46: =SUM(E46:J46) | L46: =機械!L46+包装資材!L46 | M46: =機械!M46+包装資材!M46 | N46: =機械!N46+包装資材!N46 | O46: =機械!O46+包装資材!O46 | P46: =機械!P46+包装資材!P46 | Q46: =機械!Q46+包装資材!Q46 | R46: =SUM(L46:Q46) | S46: =IF(E46=0,"***",L46/E46) | T46: =IF(F46=0,"***",M46/F46) | U46: =IF(G46=0,"***",N46/G46) | V46: =IF(H46=0,"***",O46/H46) | W46: =IF(I46=0,"***",P46/I46) | X46: =IF(J46=0,"***",Q46/J46) | Y46: =IF(K46=0,"***",R46/K46)
C47: 0047 集計 | D47: 馬場部長（静岡） | E47: =機械!E47+包装資材!E47 | F47: =機械!F47+包装資材!F47 | G47: =機械!G47+包装資材!G47 | H47: =機械!H47+包装資材!H47 | I47: =機械!I47+包装資材!I47 | J47: =機械!J47+包装資材!J47 | K47: =SUM(E47:J47) | L47: =機械!L47+包装資材!L47 | M47: =機械!M47+包装資材!M47 | N47: =機械!N47+包装資材!N47 | O47: =機械!O47+包装資材!O47 | P47: =機械!P47+包装資材!P47 | Q47: =機械!Q47+包装資材!Q47 | R47: =SUM(L47:Q47)
C48: 0550 集計 | D48: 馬場所長（東京） | E48: =機械!E48+包装資材!E48 | F48: =機械!F48+包装資材!F48 | G48: =機械!G48+包装資材!G48 | H48: =機械!H48+包装資材!H48 | I48: =機械!I48+包装資材!I48 | J48: =機械!J48+包装資材!J48 | K48: =SUM(E48:J48) | L48: =機械!L48+包装資材!L48 | M48: =機械!M48+包装資材!M48 | N48: =機械!N48+包装資材!N48 | O48: =機械!O48+包装資材!O48 | P48: =機械!P48+包装資材!P48 | Q48: =機械!Q48+包装資材!Q48 | R48: =SUM(L48:Q48) | S48: =IF(E48=0,"***",L48/E48) | T48: =IF(F48=0,"***",M48/F48) | U48: =IF(G48=0,"***",N48/G48) | V48: =IF(H48=0,"***",O48/H48) | W48: =IF(I48=0,"***",P48/I48) | X48: =IF(J48=0,"***",Q48/J48) | Y48: =IF(K48=0,"***",R48/K48)
C49: 0552 集計 | D49: 馬場部長（東京） | E49: =機械!E49+包装資材!E49 | F49: =機械!F49+包装資材!F49 | G49: =機械!G49+包装資材!G49 | H49: =機械!H49+包装資材!H49 | I49: =機械!I49+包装資材!I49 | J49: =機械!J49+包装資材!J49 | K49: =SUM(E49:J49) | L49: =機械!L49+包装資材!L49 | M49: =機械!M49+包装資材!M49 | N49: =機械!N49+包装資材!N49 | O49: =機械!O49+包装資材!O49 | P49: =機械!P49+包装資材!P49 | Q49: =機械!Q49+包装資材!Q49 | R49: =SUM(L49:Q49) | S49: =IF(E49=0,"***",L49/E49) | T49: =IF(F49=0,"***",M49/F49) | U49: =IF(G49=0,"***",N49/G49) | V49: =IF(H49=0,"***",O49/H49) | W49: =IF(I49=0,"***",P49/I49) | X49: =IF(J49=0,"***",Q49/J49) | Y49: =IF(K49=0,"***",R49/K49)
C50: 合計 | E50: =SUM(E44:E49) | F50: =SUM(F44:F49) | G50: =SUM(G44:G49) | H50: =SUM(H44:H49) | I50: =SUM(I44:I49) | J50: =SUM(J44:J49) | K50: =SUM(K44:K49) | L50: =SUM(L44:L49) | ... R50: =SUM(R44:R49) | S50: =IF(E50=0,"***",L50/E50) | T50: =IF(F50=0,"***",M50/F50) | U50: =IF(G50=0,"***",N50/G50) | V50: =IF(H50=0,"***",O50/H50) | W50: =IF(I50=0,"***",P50/I50) | X50: =IF(J50=0,"***",Q50/J50) | Y50: 0.156
C51: 内リンガーハット | E51: =(E38+E25)/2 | F51: =(F38+F25)/2 | G51: =(G38+G25)/2 | H51: =(H38+H25)/2 | I51: =(I38+I25)/2 | J51: =(J38+J25)/2 | K51: =SUM(E51:J51) | L51: =(L38+L25)/2 | M51: =(M38+M25)/2 | N51: =(N38+N25)/2 | O51: =(O38+O25)/2 | P51: =(P38+P25)/2 | Q51: =(Q38+Q25)/2 | R51: =SUM(L51:Q51) | S51: =IF(E51=0,"***",L51/E51) | T51: =IF(F51=0,"***",M51/F51) | U51: =IF(G51=0,"***",N51/G51) | V51: =IF(H51=0,"***",O51/H51) | W51: =IF(I51=0,"***",P51/I51) | X51: =IF(J51=0,"***",Q51/J51) | Y51: =IF(K51=0,"***",R51/K51) | Z51: 0042と0550からカネゲン引く
C52: リンガーハット以外 | E52: =E50-E51 | F52: =F50-F51 | G52: =G50-G51 | H52: =H50-H51 | I52: =I50-I51 | J52: =J50-J51 | K52: =SUM(E52:J52) | L52: =L50-L51 | M52: =M50-M51 | N52: =N50-N51 | O52: =O50-O51 | P52: =P50-P51 | Q52: =Q50-Q51 | R52: =SUM(L52:Q52) | S52: =IF(E52=0,"***",L52/E52) | T52: =IF(F52=0,"***",M52/F52) | U52: =IF(G52=0,"***",N52/G52) | V52: =IF(H52=0,"***",O52/H52) | W52: =IF(I52=0,"***",P52/I52) | X52: =IF(J52=0,"***",Q52/J52) | Y52: =SUM(S52:X52) | Z52: 0042と0550からカネゲン引く
C54: 5．前期比
E55: 売上 | L55: 粗利益 | S55: 粗利益率
E56: 46113 | F56: 46143 | G56: 46174 | H56: 46204 | I56: 46235 | J56: 46266 | K56: 合計 | L56: 46113 | M56: 46143 | N56: 46174 | O56: 46204 | P56: 46235 | Q56: 46266 | R56: 合計 | S56: 46113 | T56: 46143 | U56: 46174 | V56: 46204 | W56: 46235 | X56: 46266 | Y56: 合計
C57: 0042 集計 | D57: 馬場部長（鳥栖） | E57: =E44-E18 | F57: =F44-F18 | G57: =G44-G18 | H57: =H44-H18 | I57: =I44-I18 | J57: =J44-J18 | K57: =SUM(E57:J57) | L57: =L44-L18 | M57: =M44-M18 | N57: =N44-N18 | O57: =O44-O18 | P57: =P44-P18 | Q57: =Q44-Q18 | R57: =SUM(L57:Q57) | S57: =S44-S18 | T57: =T44-T18 | U57: =U44-U18 | V57: =V44-V18 | W57: =W44-W18 | X57: =X44-X18 | Y57: =Y44-Y18
C58: 0045 集計 | D58: ペーパーハグ | E58: =E45-E19 | F58: =F45-F19 | G58: =G45-G19 | H58: =H45-H19 | I58: =I45-I19 | J58: =J45-J19 | K58: =SUM(E58:J58) | L58: =L45-L19 | M58: =M45-M19 | N58: =N45-N19 | O58: =O45-O19 | P58: =P45-P19 | Q58: =Q45-Q19 | R58: =SUM(L58:Q58) | S58: =S45-S19 | T58: =T45-T19 | U58: =U45-U19 | V58: =V45-V19 | W58: =W45-W19 | X58: =X45-X19 | Y58: =Y45-Y19
C59: 0046 集計 | D59: 角田 | E59: =E46-E20 | F59: =F46-F20 | G59: =G46-G20 | H59: =H46-H20 | I59: =I46-I20 | J59: =J46-J20 | K59: =SUM(E59:J59) | L59: =L46-L20 | M59: =M46-M20 | N59: =N46-N20 | O59: =O46-O20 | P59: =P46-P20 | Q59: =Q46-Q20 | R59: =SUM(L59:Q59) | S59: =S46-S20 | T59: =T46-T20 | U59: =U46-U20 | V59: =V46-V20 | W59: =W46-W20 | X59: =X46-X20 | Y59: =Y46-Y20
C60: 0047 集計 | D60: 馬場部長（静岡） | E60: =E47-E21 | F60: =F47-F21 | G60: =G47-G21 | H60: =H47-H21 | I60: =I47-I21 | J60: =J47-J21 | K60: =SUM(E60:J60) | L60: =L47-L21 | M60: =M47-M21 | N60: =N47-N21 | O60: =O47-O21 | P60: =P47-P21 | Q60: =Q47-Q21 | R60: =SUM(L60:Q60) | S60: =S47-S21 | T60: =T47-T21 | U60: =U47-U21 | V60: =V47-V21 | W60: =W47-W21 | X60: =X47-X21 | Y60: =Y47-Y21
C61: 0550 集計 | D61: 馬場所長（東京） | E61: =E48-E22 | F61: =F48-F22 | G61: =G48-G22 | H61: =H48-H22 | I61: =I48-I22 | J61: =J48-J22 | K61: =SUM(E61:J61) | L61: =L48-L22 | M61: =M48-M22 | N61: =N48-N22 | O61: =O48-O22 | P61: =P48-P22 | Q61: =Q48-Q22 | R61: =SUM(L61:Q61) | S61: =S48-S22 | T61: =T48-T22 | U61: =U48-U22 | V61: =V48-V22 | W61: =W48-W22 | X61: =X48-X22 | Y61: =Y48-Y22
C62: 0552 集計 | D62: 馬場部長（東京） | E62: =E49-E23 | F62: =F49-F23 | G62: =G49-G23 | H62: =H49-H23 | I62: =I49-I23 | J62: =J49-J23 | K62: =SUM(E62:J62) | L62: =L49-L23 | M62: =M49-M23 | N62: =N49-N23 | O62: =O49-O23 | P62: =P49-P23 | Q62: =Q49-Q23 | R62: =SUM(L62:Q62) | S62: =S49-S23 | T62: =T49-T23 | U62: =U49-U23 | V62: =V49-V23 | W62: =W49-W23 | X62: =X49-X23 | Y62: =Y49-Y23
C63: 合計 | E63: =SUM(E57:E62) | F63: =SUM(F57:F62) | G63: =SUM(G57:G62) | H63: =SUM(H57:H62) | I63: =SUM(I57:I62) | J63: =SUM(J57:J62) | K63: =SUM(K57:K62) | L63: =SUM(L57:L62) | ... R63: =SUM(R57:R62) | S63: =S50-S24 | T63: =T50-T24 | U63: =U50-U24 | V63: =V50-V24 | W63: =W50-W24 | X63: =X50-X24 | Y63: =Y50-Y24
C64: 内リンガーハット | E64: =E51-E25 | F64: =F51-F25 | G64: =G51-G25 | H64: =H51-H25 | I64: =I51-I25 | J64: =J51-J25 | K64: =SUM(E64:J64) | L64: =L51-L25 | M64: =M51-M25 | N64: =N51-N25 | O64: =O51-O25 | P64: =P51-P25 | Q64: =Q51-Q25 | R64: =SUM(L64:Q64) | S64: =S51-S25 | T64: =T51-T25 | U64: =U51-U25 | V64: =V51-V25 | W64: =W51-W25 | X64: =X51-X25 | Y64: =Y51-Y25
C65: リンガーハット以外 | E65: =E63-E64 | F65: =F63-F64 | G65: =G63-G64 | H65: =H63-H64 | I65: =I63-I64 | J65: =J63-J64 | K65: =SUM(E65:J65) | L65: =L63-L64 | M65: =M63-M64 | N65: =N63-N64 | O65: =O63-O64 | P65: =P63-P64 | Q65: =Q63-Q64 | R65: =SUM(L65:Q65) | S65: =IF(E65=0,"***",L65/E65) | T65: =IF(F65=0,"***",M65/F65) | U65: =IF(G65=0,"***",N65/G65) | V65: =IF(H65=0,"***",O65/H65) | W65: =IF(I65=0,"***",P65/I65) | X65: =IF(J65=0,"***",Q65/J65) | Y65: =SUM(S65:X65) | Z65: 0042と0550からカネゲン引く
C67: 6．過年度平均比
E68: 売上 | L68: 粗利益 | S68: 粗利益率
E69: 46113 | F69: 46143 | G69: 46174 | H69: 46204 | I69: 46235 | J69: 46266 | K69: 合計 | L69: 46113 | M69: 46143 | N69: 46174 | O69: 46204 | P69: 46235 | Q69: 46266 | R69: 合計 | S69: 46113 | T69: 46143 | U69: 46174 | V69: 46204 | W69: 46235 | X69: 46266 | Y69: 合計
C70: 0042 集計 | D70: 馬場部長（鳥栖） | E70: =E44-E31 | F70: =F44-F31 | G70: =G44-G31 | H70: =H44-H31 | I70: =I44-I31 | J70: =J44-J31 | K70: =SUM(E70:J70) | L70: =L44-L31 | M70: =M44-M31 | N70: =N44-N31 | O70: yokat | P70: =P44-P31 | Q70: =Q44-Q31 | R70: =SUM(L70:Q70) | S70: =S44-S31 | T70: =T44-T31 | U70: =U44-U31 | V70: =V44-V31 | W70: =W44-W31 | X70: =X44-X31 | Y70: =Y44-Y31
C71: 0045 集計 | D71: ペーパーハグ | E71: =E45-E32 | F71: =F45-F32 | G71: =G45-G32 | H71: =H45-H32 | I71: =I45-I32 | J71: =J45-J32 | K71: =SUM(E71:J71) | L71: =L45-L32 | M71: =M45-M32 | N71: =N45-N32 | O71: =O45-O32 | P71: =P45-P32 | Q71: =Q45-Q32 | R71: =SUM(L71:Q71) | S71: =S45-S32 | T71: =T45-T32 | U71: =U45-U32 | V71: =V45-V32 | W71: =W45-W32 | X71: =X45-X32 | Y71: =Y45-Y32
C72: 0046 集計 | D72: 角田 | E72: =E46-E33 | F72: =F46-F33 | G72: =G46-G33 | H72: =H46-H33 | I72: =I46-I33 | J72: =J46-J33 | K72: =SUM(E72:J72) | L72: =L46-L33 | M72: =M46-M33 | N72: =N46-N33 | O72: =O46-O33 | P72: =P46-P33 | Q72: =Q46-Q33 | R72: =SUM(L72:Q72) | S72: =S46-S33 | T72: =T46-T33 | U72: =U46-U33 | V72: =V46-V33 | W72: =W46-W33 | X72: =X46-X33 | Y72: =Y46-Y33
C73: 0047 集計 | D73: 馬場部長（静岡） | E73: =E47-E34 | F73: =F47-F34 | G73: =G47-G34 | H73: =H47-H34 | I73: =I47-I34 | J73: =J47-J34 | K73: =SUM(E73:J73) | L73: =L47-L34 | M73: =M47-M34 | N73: =N47-N34 | O73: =O47-O34 | P73: =P47-P34 | Q73: =Q47-Q34 | R73: =SUM(L73:Q73) | S73: =S47-S34 | T73: =T47-T34 | U73: =U47-U34 | V73: =V47-V34 | W73: =W47-W34 | X73: =X47-X34 | Y73: =Y47-Y34
C74: 0550 集計 | D74: 馬場所長（東京） | E74: =E48-E35 | F74: =F48-F35 | G74: =G48-G35 | H74: =H48-H35 | I74: =I48-I35 | J74: =J48-J35 | K74: =SUM(E74:J74) | L74: =L48-L35 | M74: =M48-M35 | N74: =N48-N35 | O74: =O48-O35 | P74: =P48-P35 | Q74: =Q48-Q35 | R74: =SUM(L74:Q74) | S74: =S48-S35 | T74: =T48-T35 | U74: =U48-U35 | V74: =V48-V35 | W74: =W48-W35 | X74: =X48-X35 | Y74: =Y48-Y35
C75: 0552 集計 | D75: 馬場部長（東京） | E75: =E49-E36 | F75: =F49-F36 | G75: =G49-G36 | H75: =H49-H36 | I75: =I49-I36 | J75: =J49-J36 | K75: =SUM(E75:J75) | L75: =L49-L36 | M75: =M49-M36 | N75: =N49-N36 | O75: =O49-O36 | P75: =P49-P36 | Q75: =Q49-Q36 | R75: =SUM(L75:Q75) | S75: =S49-S36 | T75: =T49-T36 | U75: =U49-U36 | V75: =V49-V36 | W75: =W49-W36 | X75: =X49-X36 | Y75: =Y49-Y36
C76: 合計 | E76: =SUM(E70:E75) | F76: =SUM(F70:F75) | G76: =SUM(G70:G75) | H76: =SUM(H70:H75) | I76: =SUM(I70:I75) | J76: =SUM(J70:J75) | K76: =SUM(K70:K75) | L76: =SUM(L70:L75) | ... R76: =SUM(R70:R75) | S76: =S50-S37 | T76: =T50-T37 | U76: =U50-U37 | V76: =V50-V37 | W76: =W50-W37 | X76: =X50-X37 | Y76: =Y50-Y37
C77: 内リンガーハット | E77: =E51-E38 | F77: =F51-F38 | G77: =G51-G38 | H77: =H51-H38 | I77: =I51-I38 | J77: =J51-J38 | K77: =SUM(E77:J77) | L77: =L51-L38 | M77: =M51-M38 | N77: =N51-N38 | O77: =O51-O38 | P77: =P51-P38 | Q77: =Q51-Q38 | R77: =SUM(L77:Q77) | S77: =IF(E77=0,"***",L77/E77) | T77: =IF(F77=0,"***",M77/F77) | U77: =IF(G77=0,"***",N77/G77) | V77: =IF(H77=0,"***",O77/H77) | W77: =IF(I77=0,"***",P77/I77) | X77: =IF(J77=0,"***",Q77/J77) | Y77: =IF(K77=0,"***",R77/K77) | Z77: 0042と0550からカネゲン引く
C78: リンガーハット以外 | E78: =E76-E77 | F78: =F76-F77 | G78: =G76-G77 | H78: =H76-H77 | I78: =I76-I77 | J78: =J76-J77 | K78: =SUM(E78:J78) | L78: =L76-L77 | M78: =M76-M77 | N78: =N76-N77 | O78: =O76-O77 | P78: =P76-P77 | Q78: =Q76-Q77 | R78: =SUM(L78:Q78) | S78: =IF(E78=0,"***",L78/E78) | T78: =IF(F78=0,"***",M78/F78) | U78: =IF(G78=0,"***",N78/G78) | V78: =IF(H78=0,"***",O78/H78) | W78: =IF(I78=0,"***",P78/I78) | X78: =IF(J78=0,"***",Q78/J78) | Y78: =SUM(S78:X78) | Z78: 0042と0550からカネゲン引く
C80: 7．実績 | E80: 実績は0042と0047が分かれて出るため実績を2行にしています
E81: 売上 | L81: 粗利益 | S81: 粗利益率
E82: 46113 | F82: 46143 | G82: 46174 | H82: 46204 | I82: 46235 | J82: 46266 | K82: 合計 | L82: 46113 | M82: 46143 | N82: 46174 | O82: 46204 | P82: 46235 | Q82: 46266 | R82: 合計 | S82: 46113 | T82: 46143 | U82: 46174 | V82: 46204 | W82: 46235 | X82: 46266 | Y82: 合計
C83: 0042 集計 | D83: 馬場部長（鳥栖） | E83: 18153.657 | F83: 17951.485 | G83: 23862.275 | H83: 21612.357 | I83: 23660.445 | J83: 23931.828 | K83: =SUM(E83:J83) | L83: 3137.773 | M83: 4370.67 | N83: 5647.425 | O83: 4583.65 | P83: 4850.286 | Q83: 5051.359 | R83: =SUM(L83:Q83) | S83: =IF(E83=0,"***",L83/E83) | T83: =IF(F83=0,"***",M83/F83) | U83: =IF(G83=0,"***",N83/G83) | V83: =IF(H83=0,"***",O83/H83) | W83: =IF(I83=0,"***",P83/I83) | X83: =IF(J83=0,"***",Q83/J83) | Y83: =IF(K83=0,"***",R83/K83)
C84: 0045 集計 | D84: ペーパーハグ | I84: 0 | J84: 0 | K84: =SUM(E84:J84) | P84: 0 | Q84: 0 | R84: =SUM(L84:Q84) | S84: =IF(E84=0,"***",L84/E84) | T84: =IF(F84=0,"***",M84/F84) | U84: =IF(G84=0,"***",N84/G84) | V84: =IF(H84=0,"***",O84/H84) | W84: =IF(I84=0,"***",P84/I84) | X84: =IF(J84=0,"***",Q84/J84) | Y84: =IF(K84=0,"***",R84/K84)
C85: 0046 集計 | D85: 角田 | E85: 6727 | F85: 4624.074 | G85: 6505.671 | H85: 5687.578 | I85: 6788.099 | J85: 4327.749 | K85: =SUM(E85:J85) | L85: 1210.781 | M85: 968.966 | N85: 1316.365 | O85: 1273.791 | P85: 1199.07 | Q85: 856.58 | R85: =SUM(L85:Q85) | S85: =IF(E85=0,"***",L85/E85) | T85: =IF(F85=0,"***",M85/F85) | U85: =IF(G85=0,"***",N85/G85) | V85: =IF(H85=0,"***",O85/H85) | W85: =IF(I85=0,"***",P85/I85) | X85: =IF(J85=0,"***",Q85/J85) | Y85: =IF(K85=0,"***",R85/K85)
C86: 0047 集計 | D86: 馬場部長（静岡） | E86: 12904.127 | F86: 14611.809 | G86: 13028.232 | H86: 14519.909 | I86: 13852.311 | J86: 16187.297 | K86: =SUM(E86:J86) | L86: 1656.371 | M86: 3360.458 | N86: 2756.725 | O86: 2693.178 | P86: 2388.065 | Q86: 2724.622 | R86: =SUM(L86:Q86) | S86: =IF(E86=0,"***",L86/E86) | T86: =IF(F86=0,"***",M86/F86) | U86: =IF(G86=0,"***",N86/G86) | V86: =IF(H86=0,"***",O86/H86) | W86: =IF(I86=0,"***",P86/I86) | X86: =IF(J86=0,"***",Q86/J86) | Y86: =IF(K86=0,"***",R86/K86)
C87: 0550 集計 | D87: 馬場所長（東京） | E87: 100 | F87: 157.675 | G87: 290 | H87: 0 | I87: 0 | J87: 0 | K87: =SUM(E87:J87) | L87: 100 | M87: 103.375 | N87: 100 | O87: 0 | P87: 0 | Q87: 0 | R87: =SUM(L87:Q87) | S87: =IF(E87=0,"***",L87/E87) | T87: =IF(F87=0,"***",M87/F87) | U87: =IF(G87=0,"***",N87/G87) | V87: =IF(H87=0,"***",O87/H87) | W87: =IF(I87=0,"***",P87/I87) | X87: =IF(J87=0,"***",Q87/J87) | Y87: =IF(K87=0,"***",R87/K87)
C88: 0552 集計 | D88: 馬場部長（東京） | E88: 5089 | F88: 3321.006 | G88: 4437.165 | H88: 7195.782 | I88: 5422.219 | J88: 5618.959 | K88: =SUM(E88:J88) | L88: 618 | M88: 409.916 | N88: 510.338 | O88: 930.695 | P88: 712.8835 | Q88: 738.4465 | R88: =SUM(L88:Q88) | S88: =IF(E88=0,"***",L88/E88) | T88: =IF(F88=0,"***",M88/F88) | U88: =IF(G88=0,"***",N88/G88) | V88: =IF(H88=0,"***",O88/H88) | W88: =IF(I88=0,"***",P88/I88) | X88: =IF(J88=0,"***",Q88/J88) | Y88: =IF(K88=0,"***",R88/K88)
C89: 合計 | E89: =SUM(E83:E88) | F89: =SUM(F83:F88) | G89: =SUM(G83:G88) | H89: =SUM(H83:H88) | I89: =SUM(I83:I88) | J89: =SUM(J83:J88) | K89: =SUM(K83:K88) | L89: =SUM(L83:L88) | ... R89: =SUM(R83:R88) | S89: =IF(E89=0,"***",L89/E89) | T89: =IF(F89=0,"***",M89/F89) | U89: =IF(G89=0,"***",N89/G89) | V89: =IF(H89=0,"***",O89/H89) | W89: =IF(I89=0,"***",P89/I89) | X89: =IF(J89=0,"***",Q89/J89) | Y89: =IF(K89=0,"***",R89/K89)
C90: 内リンガーハット | E90: 29321.996 | F90: 31723.222 | G90: 36356.804 | H90: 35234.444 | I90: 37090.624 | J90: 39014.492 | K90: =SUM(E90:J90) | L90: 4712.731 | M90: 7752.55 | N90: 8432.142 | O90: 7259.191 | P90: 7289.537 | Q90: 7756.133 | R90: =SUM(L90:Q90) | S90: =IF(E90=0,"***",L90/E90) | T90: =IF(F90=0,"***",M90/F90) | U90: =IF(G90=0,"***",N90/G90) | V90: =IF(H90=0,"***",O90/H90) | W90: =IF(I90=0,"***",P90/I90) | X90: =IF(J90=0,"***",Q90/J90) | Y90: =IF(K90=0,"***",R90/K90) | Z90: 0042と0550からカネゲン引く
C91: リンガーハット以外 | E91: =E89-E90 | F91: =F89-F90 | G91: =G89-G90 | H91: =H89-H90 | I91: =I89-I90 | J91: =J89-J90 | K91: =SUM(E91:J91) | L91: =L89-L90 | M91: =M89-M90 | N91: =N89-N90 | O91: =O89-O90 | P91: =P89-P90 | Q91: =Q89-Q90 | R91: =SUM(L91:Q91) | S91: =IF(E91=0,"***",L91/E91) | T91: =IF(F91=0,"***",M91/F91) | U91: =IF(G91=0,"***",N91/G91) | V91: =IF(H91=0,"***",O91/H91) | W91: =IF(I91=0,"***",P91/I91) | X91: =IF(J91=0,"***",Q91/J91) | Y91: =SUM(S91:X91) | Z91: 0042と0550からカネゲン引く
C93: 8．計画比
E94: 売上 | L94: 粗利益 | S94: 粗利益率
E95: 46113 | F95: 46143 | G95: 46174 | H95: 46204 | I95: 46235 | J95: 46266 | K95: 合計 | L95: 46113 | M95: 46143 | N95: 46174 | O95: 46204 | P95: 46235 | Q95: 46266 | R95: 合計 | S95: 46113 | T95: 46143 | U95: 46174 | V95: 46204 | W95: 46235 | X95: 46266 | Y95: 合計
C96: 0042 集計 | D96: 馬場部長（鳥栖） | E96: =E83-E44 | F96: =F83-F44 | G96: =G83-G44 | H96: =H83-H44 | I96: =I83-I44 | J96: =J83-J44 | K96: =SUM(E96:J96) | L96: =L83-L44 | M96: =M83-M44 | N96: =N83-N44 | O96: =O83-O44 | P96: =P83-P44 | Q96: =Q83-Q44 | R96: =SUM(L96:Q96) | S96: =S83-S44 | T96: =T83-T44 | U96: =U83-U44 | V96: =V83-V44 | W96: =W83-W44 | X96: =X83-X44 | Y96: =Y83-Y44
C97: 0045 集計 | D97: ペーパーハグ | E97: =E84-E45 | F97: =F84-F45 | G97: =G84-G45 | H97: =H84-H45 | I97: =I84-I45 | J97: =J84-J45 | K97: =SUM(E97:J97) | L97: =L84-L45 | M97: =M84-M45 | N97: =N84-N45 | O97: =O84-O45 | P97: =P84-P45 | Q97: =Q84-Q45 | R97: =SUM(L97:Q97) | S97: =S84-S45 | T97: =T84-T45 | U97: =U84-U45 | V97: =V84-V45 | W97: =W84-W45 | X97: =X84-X45 | Y97: =Y84-Y45
C98: 0046 集計 | D98: 角田 | E98: =E85-E46 | F98: =F85-F46 | G98: =G85-G46 | H98: =H85-H46 | I98: =I85-I46 | J98: =J85-J46 | K98: =SUM(E98:J98) | L98: =L85-L46 | M98: =M85-M46 | N98: =N85-N46 | O98: =O85-O46 | P98: =P85-P46 | Q98: =Q85-Q46 | R98: =SUM(L98:Q98) | S98: =S85-S46 | T98: =T85-T46 | U98: =U85-U46 | V98: =V85-V46 | W98: =W85-W46 | X98: =X85-X46 | Y98: =Y85-Y46
C99: 0047 集計 | D99: 馬場部長（静岡） | E99: =E86-E47 | F99: =F86-F47 | G99: =G86-G47 | H99: =H86-H47 | I99: =I86-I47 | J99: =J86-J47 | K99: =SUM(E99:J99) | L99: =L86-L47 | M99: =M86-M47 | N99: =N86-N47 | O99: =O86-O47 | P99: =P86-P47 | Q99: =Q86-Q47 | R99: =SUM(L99:Q99) | S99: =S86-S47 | T99: =T86-T47 | U99: =U86-U47 | V99: =V86-V47 | W99: =W86-W47 | X99: =X86-X47 | Y99: =Y86-Y47
C100: 0550 集計 | D100: 馬場所長（東京） | E100: =E87-E48 | F100: =F87-F48 | G100: =G87-G48 | H100: =H87-H48 | I100: =I87-I48 | J100: =J87-J48 | K100: =SUM(E100:J100) | L100: =L87-L48 | M100: =M87-M48 | N100: =N87-N48 | O100: =O87-O48 | P100: =P87-P48 | Q100: =Q87-Q48 | R100: =SUM(L100:Q100) | S100: =S87-S48 | T100: =T87-T48 | U100: =U87-U48 | V100: =V87-V48 | W100: =W87-W48 | X100: =X87-X48 | Y100: =Y87-Y48
C101: 0552 集計 | D101: 馬場部長（東京） | E101: =E88-E49 | F101: =F88-F49 | G101: =G88-G49 | H101: =H88-H49 | I101: =I88-I49 | J101: =J88-J49 | K101: =SUM(E101:J101) | L101: =L88-L49 | M101: =M88-M49 | N101: =N88-N49 | O101: =O88-O49 | P101: =P88-P49 | Q101: =Q88-Q49 | R101: =SUM(L101:Q101) | S101: =S88-S49 | T101: =T88-T49 | U101: =U88-U49 | V101: =V88-V49 | W101: =W88-W49 | X101: =X88-X49 | Y101: =Y88-Y49
C102: 合計 | E102: =SUM(E96:E101) | F102: =SUM(F96:F101) | G102: =SUM(G96:G101) | H102: =SUM(H96:H101) | I102: =SUM(I96:I101) | J102: =SUM(J96:J101) | K102: =SUM(K96:K101) | L102: =SUM(L96:L101) | ... R102: =SUM(R96:R101) | S102: =S89-S50 | T102: =T89-T50 | U102: =U89-U50 | V102: =V89-V50 | W102: =W89-W50 | X102: =X89-X50 | Y102: =Y89-Y50
C103: 内リンガーハット | E103: =E90-E51 | F103: =F90-F51 | G103: =G90-G51 | H103: =H90-H51 | I103: =I90-I51 | J103: =J90-J51 | K103: =SUM(E103:J103) | L103: =L90-L51 | M103: =M90-M51 | N103: =N90-N51 | O103: =O90-O51 | P103: =P90-P51 | Q103: =Q90-Q51 | R103: =SUM(L103:Q103) | S103: =S90-S51 | T103: =T90-T51 | U103: =U90-U51 | V103: =V90-V51 | W103: =W90-W51 | X103: =X90-X51 | Y103: =Y90-Y51 | Z103: 0042と0550からカネゲン引く
C104: リンガーハット以外 | E104: =E102-E103 | F104: =F102-F103 | G104: =G102-G103 | H104: =H102-H103 | I104: =I102-I103 | J104: =J102-J103 | K104: =SUM(E104:J104) | L104: =L102-L103 | M104: =M102-M103 | N104: =N102-N103 | O104: =O102-O103 | P104: =P102-P103 | Q104: =Q102-Q103 | R104: =SUM(L104:Q104) | S104: =S91-S52 | T104: =T91-T52 | U104: =U91-U52 | V104: =V91-V52 | W104: =W91-W52 | X104: =X91-X52 | Y104: =Y91-Y52 | Z104: 0042と0550からカネゲン引く
C106: 9．前期比
E107: 売上 | L107: 粗利益 | S107: 粗利益率
E108: 46113 | F108: 46143 | G108: 46174 | H108: 46204 | I108: 46235 | J108: 46266 | K108: 合計 | L108: 46113 | M108: 46143 | N108: 46174 | O108: 46204 | P108: 46235 | Q108: 46266 | R108: 合計 | S108: 46113 | T108: 46143 | U108: 46174 | V108: 46204 | W108: 46235 | X108: 46266 | Y108: 合計
...

Sheet 総括
D1: 広域営業部第51期下期予算について
D3: 管理職の業務は数字責任と人材育成です。なので営業所（広域営業部）全体の目標達成に取り組みます。
D4: 部長は予算の過年度平均増加分の人員からは外した上で、営業部全体で計画を作成ます。その営業部全体の予算から所長含めて営業担当に配分するようにお願いします。
D6: *静岡も0042で計算しています。
G7: 2024年4～9月 | J7: 2025年4～9月 | M7: 過年度平均 | P7: 計画 | U7: 根拠
G8: 売上 | H8: 粗利益 | I8: 粗利益率 | J8: 売上 | K8: 粗利益 | L8: 粗利益率 | M8: 売上 | N8: 粗利益 | O8: 粗利益率 | P8: 売上 | Q8: 粗利益 | R8: 粗利益率 | S8: 売上年率 | T8: 粗利益年率
D9: 広域営業部 | G9: =G12+G15 | H9: =H12+H15 | I9: =H9/G9 | J9: =J12+J15 | K9: =K12+K15 | L9: =K9/J9 | M9: =M12+M15 | N9: =N12+N15 | O9: =N9/M9 | P9: =P12+P15 | Q9: =Q12+Q15 | R9: =Q9/P9 | S9: =P9/J9-1 | T9: =Q9/K9-1
F10: 包装資材 | G10: =G9-G11 | H10: =H9-H11 | I10: =H10/G10 | J10: =J9-J11 | K10: =K9-K11 | L10: =K10/J10 | M10: =M9-M11 | N10: =N9-N11 | O10: =N10/M10 | P10: =P9-P11 | Q10: =Q9-Q11 | R10: =Q10/P10 | S10: =P10/J10-1 | T10: =Q10/K10-1
F11: 機械 | G11: =G14+G17 | H11: =H14+H17 | I11: =H11/G11 | J11: =J14+J17 | K11: =K14+K17 | L11: =K11/J11 | M11: =M14+M17 | N11: =N14+N17 | O11: =N11/M11 | P11: =P14+P17 | Q11: =Q14+Q17 | R11: =Q11/P11 | S11: =P11/J11-1 | T11: =Q11/K11-1
E12: リンガーハット | G12: 157593.12 | H12: 22323.636 | I12: =H12/G12 | J12: 173341.61 | K12: 26263.182 | L12: =K12/J12 | M12: =(G12+J12)/2 | N12: =(H12+K12)/2 | O12: =N12/M12 | P12: =P13+P14 | Q12: =Q13+Q14 | R12: =Q12/P12 | S12: =P12/J12-1 | T12: =Q12/K12-1
F13: 包装資材 | G13: =G12-G14 | H13: =H12-H14 | I13: =H13/G13 | J13: =J12-J14 | K13: =K12-K14 | L13: =K13/J13 | M13: =(G13+J13)/2 | N13: =(H13+K13)/2 | O13: =N13/M13 | P13: 168983.24 | Q13: 25209.296 | R13: =Q13/P13 | S13: =P13/J13-1 | T13: =Q13/K13-1
F14: 機械 | G14: 353 | H14: 9 | I14: =H14/G14 | J14: 663 | K14: 37 | L14: =K14/J14 | M14: =(G14+J14)/2 | N14: =(H14+K14)/2 | O14: =N14/M14 | P14: 421.25 | Q14: 69 | R14: =Q14/P14 | S14: =P14/J14-1 | T14: =Q14/K14-1
E15: リンガーハット以外 | G15: 57505.541 | H15: 8651.6855 | I15: =H15/G15 | J15: 77393.914 | K15: 11669.6 | L15: =K15/J15 | M15: =(G15+J15)/2 | N15: =(H15+K15)/2 | O15: =N15/M15 | P15: =P16+P17 | Q15: =Q16+Q17 | R15: =Q15/P15 | S15: =P15/J15-1 | T15: =Q15/K15-1 | U15: （リンガーフーズ対応部分）
F16: 包装資材 | G16: =G15-G17 | H16: =H15-H17 | I16: =H16/G16 | J16: =J15-J17 | K16: =K15-K17 | L16: =K16/J16 | M16: =(G16+J16)/2 | N16: =(H16+K16)/2 | O16: =N16/M16 | P16: 91736.762 | Q16: 13890.704 | R16: =Q16/P16 | S16: =P16/J16-1 | T16: =Q16/K16-1
F17: 機械 | G17: 431 | H17: 58 | I17: =H17/G17 | J17: 301 | K17: 25 | L17: =K17/J17 | M17: =(G17+J17)/2 | N17: =(H17+K17)/2 | O17: =N17/M17 | P17: 5578.75 | Q17: 591 | R17: =Q17/P17 | S17: =P17/J17-1 | T17: =Q17/K17-1
