Workbook

Sheet 8月
D1: 1．単月
I3: 2024年8月売上実績 | J3: 2025年8月売上実績 | K3: 2026年8月売上計画 | L3: 2026年8月売上実績 | P3: 2024年8月粗利益実績 | Q3: 2025年8月粗利益実績 | R3: 2026年8月粗利益計画 | S3: 2026年8月粗利益実績 | W3: 2024年8月粗利益率実績 | X3: 2025年8月粗利益率実績 | Y3: 2026年8月粗利益率計画 | Z3: 2026年8月粗利益率実績 | AC3: 作成根拠
M4: 計画比 | N4: 前期比 | O4: 年率 | T4: 計画比 | U4: 前期比 | V4: 年率 | AA4: 計画比 | AB4: 前期比
F5: 石見営業所 | I5: 72108.628 | J5: 66987.523 | K5: 73080 | L5: 64244.212 | M5: =L5-K5 | N5: =L5-J5 | O5: =IF(J5=0,"***",N5/J5) | P5: 18018.943 | Q5: 18750.251 | R5: 19360 | S5: 19039.774 | T5: =S5-R5 | U5: =S5-Q5 | V5: =IF(Q5=0,"***",U5/Q5) | W5: =IF(I5=0,"***",P5/I5) | X5: =IF(J5=0,"***",Q5/J5) | Y5: =IF(K5=0,"***",R5/K5) | Z5: =IF(L5=0,"***",S5/L5) | AA5: =IF(Y5="***","***",Z5-X5) | AB5: =IF(Z5="***","***",Z5-X5)
G6: 営業 | I6: =I5-I9 | J6: =J5-J9 | K6: =K5-K9 | L6: =L5-L9 | M6: =L6-K6 | N6: =L6-J6 | O6: =IF(J6=0,"***",N6/J6) | P6: =P5-P9 | Q6: =Q5-Q9 | R6: =R5-R9 | S6: =S5-S9 | T6: =S6-R6 | U6: =S6-Q6 | V6: =IF(Q6=0,"***",U6/Q6) | W6: =IF(I6=0,"***",P6/I6) | X6: =IF(J6=0,"***",Q6/J6) | Y6: =IF(K6=0,"***",R6/K6) | Z6: =IF(L6=0,"***",S6/L6) | AA6: =IF(Y6="***","***",Z6-X6) | AB6: =IF(Z6="***","***",Z6-X6)
H7: 包装資材 | I7: =I6-I8 | J7: =J6-J8 | K7: =K6-K8 | L7: =L6-L8 | M7: =L7-K7 | N7: =L7-J7 | O7: =IF(J7=0,"***",N7/J7) | P7: =P6-P8 | Q7: =Q6-Q8 | R7: =R6-R8 | S7: =S6-S8 | T7: =S7-R7 | U7: =S7-Q7 | V7: =IF(Q7=0,"***",U7/Q7) | W7: =IF(I7=0,"***",P7/I7) | X7: =IF(J7=0,"***",Q7/J7) | Y7: =IF(K7=0,"***",R7/K7) | Z7: =IF(L7=0,"***",S7/L7) | AA7: =IF(Y7="***","***",Z7-X7) | AB7: =IF(Z7="***","***",Z7-X7)
H8: 機械 | I8: 7509.518 | J8: 1265.522 | K8: 4000 | L8: 975.121 | M8: =L8-K8 | N8: =L8-J8 | O8: =IF(J8=0,"***",N8/J8) | P8: 1071.83 | Q8: 327.011 | R8: 640 | S8: 236.88 | T8: =S8-R8 | U8: =S8-Q8 | V8: =IF(Q8=0,"***",U8/Q8) | W8: =IF(I8=0,"***",P8/I8) | X8: =IF(J8=0,"***",Q8/J8) | Y8: =IF(K8=0,"***",R8/K8) | Z8: =IF(L8=0,"***",S8/L8) | AA8: =IF(Y8="***","***",Z8-X8) | AB8: =IF(Z8="***","***",Z8-X8)
G9: 自治体 | I9: 4126.3 | J9: 0 | K9: 1340 | L9: 698 | M9: =L9-K9 | N9: =L9-J9 | O9: =IF(J9=0,"***",N9/J9) | P9: 267.6 | Q9: 0 | R9: 210 | S9: 77.7 | T9: =S9-R9 | U9: =S9-Q9 | V9: =IF(Q9=0,"***",U9/Q9) | W9: =IF(I9=0,"***",P9/I9) | X9: =IF(J9=0,"***",Q9/J9) | Y9: =IF(K9=0,"***",R9/K9) | Z9: =IF(L9=0,"***",S9/L9) | AA9: =IF(Y9="***","***",Z9-X9) | AB9: =IF(Z9="***","***",Z9-X9)
F10: 下関営業所 | I10: 42251.729 | J10: 39285.588 | K10: 43700 | L10: 44275.119 | M10: =L10-K10 | N10: =L10-J10 | O10: =IF(J10=0,"***",N10/J10) | P10: 8457.076 | Q10: 8267.92 | R10: 9100 | S10: 9189.129 | T10: =S10-R10 | U10: =S10-Q10 | V10: =IF(Q10=0,"***",U10/Q10) | W10: =IF(I10=0,"***",P10/I10) | X10: =IF(J10=0,"***",Q10/J10) | Y10: =IF(K10=0,"***",R10/K10) | Z10: =IF(L10=0,"***",S10/L10) | AA10: =IF(Y10="***","***",Z10-X10) | AB10: =IF(Z10="***","***",Z10-X10)
G11: 営業 | I11: =I10-I15-I14 | J11: =J10-J15-J14 | K11: =K10-K15-K14 | L11: =L10-L15-L14 | M11: =L11-K11 | N11: =L11-J11 | O11: =IF(J11=0,"***",N11/J11) | P11: =P10-P15-P14 | Q11: =Q10-Q15-Q14 | R11: =R10-R15-R14 | S11: =S10-S15-S14 | T11: =S11-R11 | U11: =S11-Q11 | V11: =IF(Q11=0,"***",U11/Q11) | W11: =IF(I11=0,"***",P11/I11) | X11: =IF(J11=0,"***",Q11/J11) | Y11: =IF(K11=0,"***",R11/K11) | Z11: =IF(L11=0,"***",S11/L11) | AA11: =IF(Y11="***","***",Z11-X11) | AB11: =IF(Z11="***","***",Z11-X11)
H12: 包装資材 | I12: =I11-I13 | J12: =J11-J13 | K12: =K11-K13 | L12: =L11-L13 | M12: =L12-K12 | N12: =L12-J12 | O12: =IF(J12=0,"***",N12/J12) | P12: =P11-P13 | Q12: =Q11-Q13 | R12: =R11-R13 | S12: =S11-S13 | T12: =S12-R12 | U12: =S12-Q12 | V12: =IF(Q12=0,"***",U12/Q12) | W12: =IF(I12=0,"***",P12/I12) | X12: =IF(J12=0,"***",Q12/J12) | Y12: =IF(K12=0,"***",R12/K12) | Z12: =IF(L12=0,"***",S12/L12) | AA12: =IF(Y12="***","***",Z12-X12) | AB12: =IF(Z12="***","***",Z12-X12)
H13: 機械 | I13: 173 | J13: 184 | K13: 300 | L13: 602.41 | M13: =L13-K13 | N13: =L13-J13 | O13: =IF(J13=0,"***",N13/J13) | P13: 28 | Q13: 27 | R13: 50 | S13: 110.4 | T13: =S13-R13 | U13: =S13-Q13 | V13: =IF(Q13=0,"***",U13/Q13) | W13: =IF(I13=0,"***",P13/I13) | X13: =IF(J13=0,"***",Q13/J13) | Y13: =IF(K13=0,"***",R13/K13) | Z13: =IF(L13=0,"***",S13/L13) | AA13: =IF(Y13="***","***",Z13-X13) | AB13: =IF(Z13="***","***",Z13-X13)
G14: 自治体 | I14: 0 | J14: 0 | K14: 0 | L14: 69.1 | M14: =L14-K14 | N14: =L14-J14 | O14: =IF(J14=0,"***",N14/J14) | P14: 0 | Q14: 0 | R14: 0 | S14: 2.2 | T14: =S14-R14 | U14: =S14-Q14 | V14: =IF(Q14=0,"***",U14/Q14) | W14: =IF(I14=0,"***",P14/I14) | X14: =IF(J14=0,"***",Q14/J14) | Y14: =IF(K14=0,"***",R14/K14) | Z14: =IF(L14=0,"***",S14/L14)
G15: 海外 | I15: 0 | J15: 0 | K15: 0 | L15: 0 | M15: =L15-K15 | N15: =L15-J15 | O15: =IF(J15=0,"***",N15/J15) | P15: 0 | Q15: 0 | R15: 0 | S15: 0 | T15: =S15-R15 | U15: =S15-Q15 | V15: =IF(Q15=0,"***",U15/Q15) | W15: =IF(I15=0,"***",P15/I15) | X15: =IF(J15=0,"***",Q15/J15) | Y15: =IF(K15=0,"***",R15/K15) | Z15: =IF(L15=0,"***",S15/L15) | AA15: =IF(Y15="***","***",Z15-X15) | AB15: =IF(Z15="***","***",Z15-X15)
F16: 松江営業所 | I16: 29878.207 | J16: 32089.888 | K16: 30970 | L16: 33113.79 | M16: =L16-K16 | N16: =L16-J16 | O16: =IF(J16=0,"***",N16/J16) | P16: 7280.478 | Q16: 7302.819 | R16: 8030 | S16: 9530.098 | T16: =S16-R16 | U16: =S16-Q16 | V16: =IF(Q16=0,"***",U16/Q16) | W16: =IF(I16=0,"***",P16/I16) | X16: =IF(J16=0,"***",Q16/J16) | Y16: =IF(K16=0,"***",R16/K16) | Z16: =IF(L16=0,"***",S16/L16) | AA16: =IF(Y16="***","***",Z16-X16) | AB16: =IF(Z16="***","***",Z16-X16)
G17: 営業 | I17: =I16-I20 | J17: =J16-J20 | K17: =K16-K20 | L17: =L16-L20 | M17: =L17-K17 | N17: =L17-J17 | O17: =IF(J17=0,"***",N17/J17) | P17: =P16-P20 | Q17: =Q16-Q20 | R17: =R16-R20 | S17: =S16-S20 | T17: =S17-R17 | U17: =S17-Q17 | V17: =IF(Q17=0,"***",U17/Q17) | W17: =IF(I17=0,"***",P17/I17) | X17: =IF(J17=0,"***",Q17/J17) | Y17: =IF(K17=0,"***",R17/K17) | Z17: =IF(L17=0,"***",S17/L17) | AA17: =IF(Y17="***","***",Z17-X17) | AB17: =IF(Z17="***","***",Z17-X17)
H18: 包装資材 | I18: =I17-I19 | J18: =J17-J19 | K18: =K17-K19 | L18: =L17-L19 | M18: =L18-K18 | N18: =L18-J18 | O18: =IF(J18=0,"***",N18/J18) | P18: =P17-P19 | Q18: =Q17-Q19 | R18: =R17-R19 | S18: =S17-S19 | T18: =S18-R18 | U18: =S18-Q18 | V18: =IF(Q18=0,"***",U18/Q18) | W18: =IF(I18=0,"***",P18/I18) | X18: =IF(J18=0,"***",Q18/J18) | Y18: =IF(K18=0,"***",R18/K18) | Z18: =IF(L18=0,"***",S18/L18) | AA18: =IF(Y18="***","***",Z18-X18) | AB18: =IF(Z18="***","***",Z18-X18)
H19: 機械 | I19: 300 | J19: 219 | K19: 500 | L19: 1451.84 | M19: =L19-K19 | N19: =L19-J19 | O19: =IF(J19=0,"***",N19/J19) | P19: 60 | Q19: 77 | R19: 120 | S19: 299.935 | T19: =S19-R19 | U19: =S19-Q19 | V19: =IF(Q19=0,"***",U19/Q19) | W19: =IF(I19=0,"***",P19/I19) | X19: =IF(J19=0,"***",Q19/J19) | Y19: =IF(K19=0,"***",R19/K19) | Z19: =IF(L19=0,"***",S19/L19) | AA19: =IF(Y19="***","***",Z19-X19) | AB19: =IF(Z19="***","***",Z19-X19)
G20: 自治体 | I20: 0 | J20: 6139.904 | K20: 0 | L20: 0 | M20: =L20-K20 | N20: =L20-J20 | O20: =IF(J20=0,"***",N20/J20) | P20: 0 | Q20: 115.904 | R20: 0 | S20: 0 | T20: =S20-R20 | U20: =S20-Q20 | V20: =IF(Q20=0,"***",U20/Q20) | W20: =IF(I20=0,"***",P20/I20) | X20: =IF(J20=0,"***",Q20/J20) | Y20: =IF(K20=0,"***",R20/K20) | Z20: =IF(L20=0,"***",S20/L20) | AA20: =IF(Y20="***","***",Z20-X20) | AB20: =IF(Z20="***","***",Z20-X20)
F21: 広域営業部 | I21: 38098.848 | J21: 40343.715 | K21: 44990 | L21: 49723.074 | M21: =L21-K21 | N21: =L21-J21 | O21: =IF(J21=0,"***",N21/J21) | P21: 5188.215 | Q21: 6090.348 | R21: 6810 | S21: 9152.9145 | T21: =S21-R21 | U21: =S21-Q21 | V21: =IF(Q21=0,"***",U21/Q21) | W21: =IF(I21=0,"***",P21/I21) | X21: =IF(J21=0,"***",Q21/J21) | Y21: =IF(K21=0,"***",R21/K21) | Z21: =IF(L21=0,"***",S21/L21) | AA21: =IF(Y21="***","***",Z21-X21) | AB21: =IF(Z21="***","***",Z21-X21)
H22: 包装資材 | I22: =I21-I23 | J22: =J21-J23 | K22: =K21-K23 | L22: =L21-L23 | M22: =L22-K22 | N22: =L22-J22 | O22: =IF(J22=0,"***",N22/J22) | P22: =P21-P23 | Q22: =Q21-Q23 | R22: =R21-R23 | S22: =S21-S23 | T22: =S22-R22 | U22: =S22-Q22 | V22: =IF(Q22=0,"***",U22/Q22) | W22: =IF(I22=0,"***",P22/I22) | X22: =IF(J22=0,"***",Q22/J22) | Y22: =IF(K22=0,"***",R22/K22) | Z22: =IF(L22=0,"***",S22/L22) | AA22: =IF(Y22="***","***",Z22-X22) | AB22: =IF(Z22="***","***",Z22-X22)
H23: 機械 | I23: 207 | J23: 70 | K23: 1000 | L23: 363.055 | M23: =L23-K23 | N23: =L23-J23 | O23: =IF(J23=0,"***",N23/J23) | P23: 22 | Q23: 6 | R23: 110 | S23: 40.345 | T23: =S23-R23 | U23: =S23-Q23 | V23: =IF(Q23=0,"***",U23/Q23) | W23: =IF(I23=0,"***",P23/I23) | X23: =IF(J23=0,"***",Q23/J23) | Y23: =IF(K23=0,"***",R23/K23) | Z23: =IF(L23=0,"***",S23/L23) | AA23: =IF(Y23="***","***",Z23-X23) | AB23: =IF(Z23="***","***",Z23-X23)
G24: リンガーハット | I24: 28967.532 | J24: 29499.674 | K24: 29366.639 | L24: 37090.624 | M24: =L24-K24 | N24: =L24-J24 | O24: =IF(J24=0,"***",N24/J24) | P24: 3790.54 | Q24: 4379.268 | R24: 4232.086 | S24: 7289.537 | T24: =S24-R24 | U24: =S24-Q24 | V24: =IF(Q24=0,"***",U24/Q24) | W24: =IF(I24=0,"***",P24/I24) | X24: =IF(J24=0,"***",Q24/J24) | Y24: =IF(K24=0,"***",R24/K24) | Z24: =IF(L24=0,"***",S24/L24) | AA24: =IF(Y24="***","***",Z24-X24) | AB24: =IF(Z24="***","***",Z24-X24)
H25: 包装資材 | I25: =I24-I26 | J25: =J24-J26 | K25: =K24-K26 | L25: =L24-L26 | M25: =L25-K25 | N25: =L25-J25 | O25: =IF(J25=0,"***",N25/J25) | P25: =P24-P26 | Q25: =Q24-Q26 | R25: =R24-R26 | S25: =S24-S26 | T25: =S25-R25 | U25: =S25-Q25 | V25: =IF(Q25=0,"***",U25/Q25) | W25: =IF(I25=0,"***",P25/I25) | X25: =IF(J25=0,"***",Q25/J25) | Y25: =IF(K25=0,"***",R25/K25) | Z25: =IF(L25=0,"***",S25/L25) | AA25: =IF(Y25="***","***",Z25-X25) | AB25: =IF(Z25="***","***",Z25-X25)
H26: 機械 | I26: 83 | J26: 23 | K26: 38 | L26: 286.455 | M26: =L26-K26 | N26: =L26-J26 | O26: =IF(J26=0,"***",N26/J26) | P26: 1 | Q26: 0 | R26: 0.25 | S26: 25.625 | T26: =S26-R26 | U26: =S26-Q26 | V26: =IF(Q26=0,"***",U26/Q26) | W26: =IF(I26=0,"***",P26/I26) | X26: =IF(J26=0,"***",Q26/J26) | Y26: =IF(K26=0,"***",R26/K26) | Z26: =IF(L26=0,"***",S26/L26) | AA26: =IF(Y26="***","***",Z26-X26) | AB26: =IF(Z26="***","***",Z26-X26)
G27: リンガーハット以外 | I27: =I21-I24 | J27: =J21-J24 | K27: =K21-K24 | L27: =L21-L24 | M27: =L27-K27 | N27: =L27-J27 | O27: =IF(J27=0,"***",N27/J27) | P27: =P21-P24 | Q27: =Q21-Q24 | R27: =R21-R24 | S27: =S21-S24 | T27: =S27-R27 | U27: =S27-Q27 | V27: =IF(Q27=0,"***",U27/Q27) | W27: =IF(I27=0,"***",P27/I27) | X27: =IF(J27=0,"***",Q27/J27) | Y27: =IF(K27=0,"***",R27/K27) | Z27: =IF(L27=0,"***",S27/L27) | AA27: =IF(Y27="***","***",Z27-X27) | AB27: =IF(Z27="***","***",Z27-X27)
H28: 包装資材 | I28: =I27-I29 | J28: =J27-J29 | K28: =K27-K29 | L28: =L27-L29 | M28: =L28-K28 | N28: =L28-J28 | O28: =IF(J28=0,"***",N28/J28) | P28: =P27-P29 | Q28: =Q27-Q29 | R28: =R27-R29 | S28: =S27-S29 | T28: =S28-R28 | U28: =S28-Q28 | V28: =IF(Q28=0,"***",U28/Q28) | W28: =IF(I28=0,"***",P28/I28) | X28: =IF(J28=0,"***",Q28/J28) | Y28: =IF(K28=0,"***",R28/K28) | Z28: =IF(L28=0,"***",S28/L28) | AA28: =IF(Y28="***","***",Z28-X28) | AB28: =IF(Z28="***","***",Z28-X28)
H29: 機械 | I29: =I23-I26 | J29: =J23-J26 | K29: =K23-K26 | L29: =L23-L26 | M29: =L29-K29 | N29: =L29-J29 | O29: =IF(J29=0,"***",N29/J29) | P29: =P23-P26 | Q29: =Q23-Q26 | R29: =R23-R26 | S29: =S23-S26 | T29: =S29-R29 | U29: =S29-Q29 | V29: =IF(Q29=0,"***",U29/Q29) | W29: =IF(I29=0,"***",P29/I29) | X29: =IF(J29=0,"***",Q29/J29) | Y29: =IF(K29=0,"***",R29/K29) | Z29: =IF(L29=0,"***",S29/L29) | AA29: =IF(Y29="***","***",Z29-X29) | AB29: =IF(Z29="***","***",Z29-X29)
F30: 境港営業所 | I30: 45152.173 | J30: 122048.54 | K30: 47810 | L30: 41885.331 | M30: =L30-K30 | N30: =L30-J30 | O30: =IF(J30=0,"***",N30/J30) | P30: 9612.031 | Q30: 21532.958 | R30: 9410 | S30: 8386.044 | T30: =S30-R30 | U30: =S30-Q30 | V30: =IF(Q30=0,"***",U30/Q30) | W30: =IF(I30=0,"***",P30/I30) | X30: =IF(J30=0,"***",Q30/J30) | Y30: =IF(K30=0,"***",R30/K30) | Z30: =IF(L30=0,"***",S30/L30) | AA30: =IF(Y30="***","***",Z30-X30) | AB30: =IF(Z30="***","***",Z30-X30)
G31: 営業 | I31: =I30-I35-I34 | J31: =J30-J35-J34 | K31: =K30-K35-K34 | L31: =L30-L35-L34 | M31: =L31-K31 | N31: =L31-J31 | O31: =IF(J31=0,"***",N31/J31) | P31: =P30-P35-P34 | Q31: =Q30-Q35-Q34 | R31: =R30-R35-R34 | S31: =S30-S35-S34 | T31: =S31-R31 | U31: =S31-Q31 | V31: =IF(Q31=0,"***",U31/Q31) | W31: =IF(I31=0,"***",P31/I31) | X31: =IF(J31=0,"***",Q31/J31) | Y31: =IF(K31=0,"***",R31/K31) | Z31: =IF(L31=0,"***",S31/L31) | AA31: =IF(Y31="***","***",Z31-X31) | AB31: =IF(Z31="***","***",Z31-X31)
H32: 包装資材 | I32: =I31-I33 | J32: =J31-J33 | K32: =K31-K33 | L32: =L31-L33 | M32: =L32-K32 | N32: =L32-J32 | O32: =IF(J32=0,"***",N32/J32) | P32: =P31-P33 | Q32: =Q31-Q33 | R32: =R31-R33 | S32: =S31-S33 | T32: =S32-R32 | U32: =S32-Q32 | V32: =IF(Q32=0,"***",U32/Q32) | W32: =IF(I32=0,"***",P32/I32) | X32: =IF(J32=0,"***",Q32/J32) | Y32: =IF(K32=0,"***",R32/K32) | Z32: =IF(L32=0,"***",S32/L32) | AA32: =IF(Y32="***","***",Z32-X32) | AB32: =IF(Z32="***","***",Z32-X32)
H33: 機械 | I33: 1318 | J33: 85679 | K33: 8500 | L33: 4649.01 | M33: =L33-K33 | N33: =L33-J33 | O33: =IF(J33=0,"***",N33/J33) | P33: 391 | Q33: 14899 | R33: 1880 | S33: 1001.375 | T33: =S33-R33 | U33: =S33-Q33 | V33: =IF(Q33=0,"***",U33/Q33) | W33: =IF(I33=0,"***",P33/I33) | X33: =IF(J33=0,"***",Q33/J33) | Y33: =IF(K33=0,"***",R33/K33) | Z33: =IF(L33=0,"***",S33/L33) | AA33: =IF(Y33="***","***",Z33-X33) | AB33: =IF(Z33="***","***",Z33-X33)
G34: 自治体 | I34: 0 | J34: 0 | K34: 0 | L34: 156 | M34: =L34-K34 | N34: =L34-J34 | O34: =IF(J34=0,"***",N34/J34) | P34: 0 | Q34: 0 | R34: 0 | S34: 4.8 | T34: =S34-R34 | U34: =S34-Q34 | V34: =IF(Q34=0,"***",U34/Q34) | W34: =IF(I34=0,"***",P34/I34) | X34: =IF(J34=0,"***",Q34/J34) | Y34: =IF(K34=0,"***",R34/K34) | Z34: =IF(L34=0,"***",S34/L34) | AA34: =IF(Y34="***","***",Z34-X34) | AB34: =IF(Z34="***","***",Z34-X34)
G35: 海外 | I35: 232.15 | J35: 21.15 | K35: 530 | L35: 314.45 | M35: =L35-K35 | N35: =L35-J35 | O35: =IF(J35=0,"***",N35/J35) | P35: 73.45 | Q35: 5.8 | R35: 100 | S35: 59.63 | T35: =S35-R35 | U35: =S35-Q35 | V35: =IF(Q35=0,"***",U35/Q35) | W35: =IF(I35=0,"***",P35/I35) | X35: =IF(J35=0,"***",Q35/J35) | Y35: =IF(K35=0,"***",R35/K35) | Z35: =IF(L35=0,"***",S35/L35) | AA35: =IF(Y35="***","***",Z35-X35) | AB35: =IF(Z35="***","***",Z35-X35)
E36: 営業部門合計 | I36: =I30+I21+I16+I10+I5 | J36: =J30+J21+J16+J10+J5 | K36: =K30+K21+K16+K10+K5 | L36: =L30+L21+L16+L10+L5 | M36: =L36-K36 | N36: =L36-J36 | O36: =IF(J36=0,"***",N36/J36) | P36: =P30+P21+P16+P10+P5 | Q36: =Q30+Q21+Q16+Q10+Q5 | R36: =R30+R21+R16+R10+R5 | S36: =S30+S21+S16+S10+S5 | T36: =S36-R36 | U36: =S36-Q36 | V36: =IF(Q36=0,"***",U36/Q36) | W36: =IF(I36=0,"***",P36/I36) | X36: =IF(J36=0,"***",Q36/J36) | Y36: =IF(K36=0,"***",R36/K36) | Z36: =IF(L36=0,"***",S36/L36) | AA36: =IF(Y36="***","***",Z36-X36) | AB36: =IF(Z36="***","***",Z36-X36)
H37: 機械以外 | I37: =I36-I38-I39-I40 | J37: =J36-J38-J39-J40 | K37: =K36-K38-K39-K40 | L37: =L36-L38-L39-L40 | M37: =L37-K37 | N37: =L37-J37 | O37: =IF(J37=0,"***",N37/J37) | P37: =P36-P38-P39-P40 | Q37: =Q36-Q38-Q39-Q40 | R37: =R36-R38-R39-R40 | S37: =S36-S38-S39-S40 | T37: =S37-R37 | U37: =S37-Q37 | V37: =IF(Q37=0,"***",U37/Q37) | W37: =IF(I37=0,"***",P37/I37) | X37: =IF(J37=0,"***",Q37/J37) | Y37: =IF(K37=0,"***",R37/K37) | Z37: =IF(L37=0,"***",S37/L37) | AA37: =IF(Y37="***","***",Z37-X37) | AB37: =IF(Z37="***","***",Z37-X37)
H38: 機械 | I38: =I33+I23+I19+I13+I8 | J38: =J33+J23+J19+J13+J8 | K38: =K33+K23+K19+K13+K8 | L38: =L33+L23+L19+L13+L8 | M38: =L38-K38 | N38: =L38-J38 | O38: =IF(J38=0,"***",N38/J38) | P38: =P33+P23+P19+P13+P8 | Q38: =Q33+Q23+Q19+Q13+Q8 | R38: =R33+R23+R19+R13+R8 | S38: =S33+S23+S19+S13+S8 | T38: =S38-R38 | U38: =S38-Q38 | V38: =IF(Q38=0,"***",U38/Q38) | W38: =IF(I38=0,"***",P38/I38) | X38: =IF(J38=0,"***",Q38/J38) | Y38: =IF(K38=0,"***",R38/K38) | Z38: =IF(L38=0,"***",S38/L38) | AA38: =IF(Y38="***","***",Z38-X38) | AB38: =IF(Z38="***","***",Z38-X38)
H39: 自治体 | I39: =I34+I20+I14+I9 | J39: =J34+J20+J14+J9 | K39: =K34+K20+K14+K9 | L39: =L34+L20+L14+L9 | M39: =L39-K39 | N39: =L39-J39 | O39: =IF(J39=0,"***",N39/J39) | P39: =P34+P20+P14+P9 | Q39: =Q34+Q20+Q14+Q9 | R39: =R34+R20+R14+R9 | S39: =S34+S20+S14+S9 | T39: =S39-R39 | U39: =S39-Q39 | V39: =IF(Q39=0,"***",U39/Q39) | W39: =IF(I39=0,"***",P39/I39) | X39: =IF(J39=0,"***",Q39/J39) | Y39: =IF(K39=0,"***",R39/K39) | Z39: =IF(L39=0,"***",S39/L39) | AA39: =IF(Y39="***","***",Z39-X39) | AB39: =IF(Z39="***","***",Z39-X39)
H40: 海外 | I40: =I35+I15 | J40: =J35+J15 | K40: =K35+K15 | L40: =L35+L15 | M40: =L40-K40 | N40: =L40-J40 | O40: =IF(J40=0,"***",N40/J40) | P40: =P35+P15 | Q40: =Q35+Q15 | R40: =R35+R15 | S40: =S35+S15 | T40: =S40-R40 | U40: =S40-Q40 | V40: =IF(Q40=0,"***",U40/Q40) | W40: =IF(I40=0,"***",P40/I40) | X40: =IF(J40=0,"***",Q40/J40) | Y40: =IF(K40=0,"***",R40/K40) | Z40: =IF(L40=0,"***",S40/L40) | AA40: =IF(Y40="***","***",Z40-X40) | AB40: =IF(Z40="***","***",Z40-X40)
E41: 水産部 | I41: 27052.538 | J41: 26566.747 | K41: 28670 | L41: 32703.688 | M41: =L41-K41 | N41: =L41-J41 | O41: =IF(J41=0,"***",N41/J41) | P41: 8027.116 | Q41: 7803.715 | R41: 8170 | S41: 8776.157 | T41: =S41-R41 | U41: =S41-Q41 | V41: =IF(Q41=0,"***",U41/Q41) | W41: =IF(I41=0,"***",P41/I41) | X41: =IF(J41=0,"***",Q41/J41) | Y41: =IF(K41=0,"***",R41/K41) | Z41: =IF(L41=0,"***",S41/L41) | AA41: =IF(Y41="***","***",Z41-X41) | AB41: =IF(Z41="***","***",Z41-X41)
H42: 包装資材 | I42: =I41-I43-I44 | J42: =J41-J43-J44 | K42: =K41-K43-K44 | L42: =L41-L43-L44 | M42: =L42-K42 | N42: =L42-J42 | O42: =IF(J42=0,"***",N42/J42) | P42: =P41-P43-P44 | Q42: =Q41-Q43-Q44 | R42: =R41-R43-R44 | S42: =S41-S43-S44 | T42: =S42-R42 | U42: =S42-Q42 | V42: =IF(Q42=0,"***",U42/Q42) | W42: =IF(I42=0,"***",P42/I42) | X42: =IF(J42=0,"***",Q42/J42) | Y42: =IF(K42=0,"***",R42/K42) | Z42: =IF(L42=0,"***",S42/L42) | AA42: =IF(Y42="***","***",Z42-X42) | AB42: =IF(Z42="***","***",Z42-X42)
H43: 荷役 | I43: 6750.28 | J43: 3372.415 | K43: 3840 | L43: 3402.158 | M43: =L43-K43 | N43: =L43-J43 | O43: =IF(J43=0,"***",N43/J43) | P43: 4107.718 | Q43: 2118.043 | R43: 2380 | S43: 2241.816 | T43: =S43-R43 | U43: =S43-Q43 | V43: =IF(Q43=0,"***",U43/Q43) | W43: =IF(I43=0,"***",P43/I43) | X43: =IF(J43=0,"***",Q43/J43) | Y43: =IF(K43=0,"***",R43/K43) | Z43: =IF(L43=0,"***",S43/L43)
H44: 機械 | I44: 124.2 | J44: 90.48 | K44: 90 | L44: 50.38 | M44: =L44-K44 | N44: =L44-J44 | O44: =IF(J44=0,"***",N44/J44) | P44: 17.16 | Q44: 5.48 | R44: 20 | S44: 8.91 | T44: =S44-R44 | U44: =S44-Q44 | V44: =IF(Q44=0,"***",U44/Q44) | W44: =IF(I44=0,"***",P44/I44) | X44: =IF(J44=0,"***",Q44/J44) | Y44: =IF(K44=0,"***",R44/K44) | Z44: =IF(L44=0,"***",S44/L44) | AA44: =IF(Y44="***","***",Z44-X44) | AB44: =IF(Z44="***","***",Z44-X44)
D45: 合計 | I45: =I41+I36 | J45: =J41+J36 | K45: =K41+K36 | L45: =L41+L36 | M45: =L45-K45 | N45: =L45-J45 | O45: =IF(J45=0,"***",N45/J45) | P45: =P41+P36 | Q45: =Q41+Q36 | R45: =R41+R36 | S45: =S41+S36 | T45: =S45-R45 | U45: =S45-Q45 | V45: =IF(Q45=0,"***",U45/Q45) | W45: =IF(I45=0,"***",P45/I45) | X45: =IF(J45=0,"***",Q45/J45) | Y45: =IF(K45=0,"***",R45/K45) | Z45: =IF(L45=0,"***",S45/L45) | AA45: =IF(Y45="***","***",Z45-X45) | AB45: =IF(Z45="***","***",Z45-X45)
H46: 機械以外 | I46: =I45-I47 | J46: =J45-J47 | K46: =K45-K47 | L46: =L45-L47 | M46: =L46-K46 | N46: =L46-J46 | O46: =IF(J46=0,"***",N46/J46) | P46: =P45-P47 | Q46: =Q45-Q47 | R46: =R45-R47 | S46: =S45-S47 | T46: =S46-R46 | U46: =S46-Q46 | V46: =IF(Q46=0,"***",U46/Q46) | W46: =IF(I46=0,"***",P46/I46) | X46: =IF(J46=0,"***",Q46/J46) | Y46: =IF(K46=0,"***",R46/K46) | Z46: =IF(L46=0,"***",S46/L46) | AA46: =IF(Y46="***","***",Z46-X46) | AB46: =IF(Z46="***","***",Z46-X46)
H47: 機械 | I47: =I38+I44 | J47: =J38+J44 | K47: =K38+K44 | L47: =L38+L44 | M47: =L47-K47 | N47: =L47-J47 | O47: =IF(J47=0,"***",N47/J47) | P47: =P38+P44 | Q47: =Q38+Q44 | R47: =R38+R44 | S47: =S38+S44 | T47: =S47-R47 | U47: =S47-Q47 | V47: =IF(Q47=0,"***",U47/Q47) | W47: =IF(I47=0,"***",P47/I47) | X47: =IF(J47=0,"***",Q47/J47) | Y47: =IF(K47=0,"***",R47/K47) | Z47: =IF(L47=0,"***",S47/L47) | AA47: =IF(Y47="***","***",Z47-X47) | AB47: =IF(Z47="***","***",Z47-X47)
H48: 自治体 | I48: =I39 | J48: =J39 | K48: =K39 | L48: =L39 | M48: =L48-K48 | N48: =L48-J48 | O48: =IF(J48=0,"***",N48/J48) | P48: =P39 | Q48: =Q39 | R48: =R39 | S48: =S39 | T48: =S48-R48 | U48: =S48-Q48 | V48: =IF(Q48=0,"***",U48/Q48) | W48: =IF(I48=0,"***",P48/I48) | X48: =IF(J48=0,"***",Q48/J48) | Y48: =IF(K48=0,"***",R48/K48) | Z48: =IF(L48=0,"***",S48/L48) | AA48: =IF(Y48="***","***",Z48-X48) | AB48: =IF(Z48="***","***",Z48-X48)
H49: 海外 | I49: =I40 | J49: =J40 | K49: =K40 | L49: =L40 | M49: =L49-K49 | N49: =L49-J49 | O49: =IF(J49=0,"***",N49/J49) | P49: =P40 | Q49: =Q40 | R49: =R40 | S49: =S40 | T49: =S49-R49 | U49: =S49-Q49 | V49: =IF(Q49=0,"***",U49/Q49) | W49: =IF(I49=0,"***",P49/I49) | X49: =IF(J49=0,"***",Q49/J49) | Y49: =IF(K49=0,"***",R49/K49) | Z49: =IF(L49=0,"***",S49/L49) | AA49: =IF(Y49="***","***",Z49-X49) | AB49: =IF(Z49="***","***",Z49-X49)
D50: キョウワ（税抜） | I50: 1570 | J50: 1190 | K50: 1360 | L50: 3950 | M50: =L50-K50 | N50: =L50-J50 | O50: =IF(J50=0,"***",N50/J50) | P50: 1040 | Q50: 750 | R50: 880 | S50: 1723 | T50: =S50-R50 | U50: =S50-Q50 | V50: =IF(Q50=0,"***",U50/Q50) | W50: =IF(I50=0,"***",P50/I50) | X50: =IF(J50=0,"***",Q50/J50) | Y50: =IF(K50=0,"***",R50/K50) | Z50: =IF(L50=0,"***",S50/L50) | AA50: =IF(Y50="***","***",Z50-X50) | AB50: =IF(Z50="***","***",Z50-X50)

Sheet 下期
D1: 2．下期
I3: 第49期下期売上実績 | J3: 第50期下期売上実績 | K3: 第51期下期売上計画 | L3: 第51期下期売上実績 | P3: 第49期下期粗利益実績 | Q3: 第50期下期粗利益実績 | R3: 第51期下期粗利益計画 | S3: 第51期下期粗利益実績 | W3: 第49期下期粗利益率実績 | X3: 第50期下期粗利益率実績 | Y3: 第51期下期粗利益率計画 | Z3: 第51期下期粗利益率実績 | AC3: 作成根拠
M4: 計画比 | N4: 前期比 | O4: 年率 | T4: 計画比 | U4: 前期比 | V4: 年率 | AA4: 計画比 | AB4: 前期比
F5: 石見営業所 | I5: ='8月'!I5+BACKDATA7月!I5+BACKDATA6月!I5+BACKDATA5月!I5+BACKDATA4月!I5 | J5: ='8月'!J5+BACKDATA7月!J5+BACKDATA6月!J5+BACKDATA5月!J5+BACKDATA4月!J5 | K5: ='8月'!K5+BACKDATA7月!K5+BACKDATA6月!K5+BACKDATA5月!K5+BACKDATA4月!K5 | L5: ='8月'!L5+BACKDATA7月!L5+BACKDATA6月!L5+BACKDATA5月!L5+BACKDATA4月!L5 | M5: =L5-K5 | N5: =L5-J5 | O5: =IF(J5=0,"***",N5/J5) | P5: ='8月'!P5+BACKDATA7月!P5+BACKDATA6月!P5+BACKDATA5月!P5+BACKDATA4月!P5 | Q5: ='8月'!Q5+BACKDATA7月!Q5+BACKDATA6月!Q5+BACKDATA5月!Q5+BACKDATA4月!Q5 | R5: ='8月'!R5+BACKDATA7月!R5+BACKDATA6月!R5+BACKDATA5月!R5+BACKDATA4月!R5 | S5: ='8月'!S5+BACKDATA7月!S5+BACKDATA6月!S5+BACKDATA5月!S5+BACKDATA4月!S5 | T5: =S5-R5 | U5: =S5-Q5 | V5: =IF(Q5=0,"***",U5/Q5) | W5: =IF(I5=0,"***",P5/I5) | X5: =IF(J5=0,"***",Q5/J5) | Y5: =IF(K5=0,"***",R5/K5) | Z5: =IF(L5=0,"***",S5/L5) | AA5: =IF(Y5="***","***",Z5-X5) | AB5: =IF(Z5="***","***",Z5-X5)
G6: 営業 | I6: =I5-I9 | J6: =J5-J9 | K6: =K5-K9 | L6: =L5-L9 | M6: =L6-K6 | N6: =L6-J6 | O6: =IF(J6=0,"***",N6/J6) | P6: =P5-P9 | Q6: =Q5-Q9 | R6: =R5-R9 | S6: =S5-S9 | T6: =S6-R6 | U6: =S6-Q6 | V6: =IF(Q6=0,"***",U6/Q6) | W6: =IF(I6=0,"***",P6/I6) | X6: =IF(J6=0,"***",Q6/J6) | Y6: =IF(K6=0,"***",R6/K6) | Z6: =IF(L6=0,"***",S6/L6) | AA6: =IF(Y6="***","***",Z6-X6) | AB6: =IF(Z6="***","***",Z6-X6)
H7: 包装資材 | I7: =I6-I8 | J7: =J6-J8 | K7: =K6-K8 | L7: =L6-L8 | M7: =L7-K7 | N7: =L7-J7 | O7: =IF(J7=0,"***",N7/J7) | P7: =P6-P8 | Q7: =Q6-Q8 | R7: =R6-R8 | S7: =S6-S8 | T7: =S7-R7 | U7: =S7-Q7 | V7: =IF(Q7=0,"***",U7/Q7) | W7: =IF(I7=0,"***",P7/I7) | X7: =IF(J7=0,"***",Q7/J7) | Y7: =IF(K7=0,"***",R7/K7) | Z7: =IF(L7=0,"***",S7/L7) | AA7: =IF(Y7="***","***",Z7-X7) | AB7: =IF(Z7="***","***",Z7-X7)
H8: 機械 | I8: ='8月'!I8+BACKDATA7月!I8+BACKDATA6月!I8+BACKDATA5月!I8+BACKDATA4月!I8 | J8: ='8月'!J8+BACKDATA7月!J8+BACKDATA6月!J8+BACKDATA5月!J8+BACKDATA4月!J8 | K8: ='8月'!K8+BACKDATA7月!K8+BACKDATA6月!K8+BACKDATA5月!K8+BACKDATA4月!K8 | L8: ='8月'!L8+BACKDATA7月!L8+BACKDATA6月!L8+BACKDATA5月!L8+BACKDATA4月!L8 | M8: =L8-K8 | N8: =L8-J8 | O8: =IF(J8=0,"***",N8/J8) | P8: ='8月'!P8+BACKDATA7月!P8+BACKDATA6月!P8+BACKDATA5月!P8+BACKDATA4月!P8 | Q8: ='8月'!Q8+BACKDATA7月!Q8+BACKDATA6月!Q8+BACKDATA5月!Q8+BACKDATA4月!Q8 | R8: ='8月'!R8+BACKDATA7月!R8+BACKDATA6月!R8+BACKDATA5月!R8+BACKDATA4月!R8 | S8: ='8月'!S8+BACKDATA7月!S8+BACKDATA6月!S8+BACKDATA5月!S8+BACKDATA4月!S8 | T8: =S8-R8 | U8: =S8-Q8 | V8: =IF(Q8=0,"***",U8/Q8) | W8: =IF(I8=0,"***",P8/I8) | X8: =IF(J8=0,"***",Q8/J8) | Y8: =IF(K8=0,"***",R8/K8) | Z8: =IF(L8=0,"***",S8/L8) | AA8: =IF(Y8="***","***",Z8-X8) | AB8: =IF(Z8="***","***",Z8-X8)
G9: 自治体 | I9: ='8月'!I9+BACKDATA7月!I9+BACKDATA6月!I9+BACKDATA5月!I9+BACKDATA4月!I9 | J9: ='8月'!J9+BACKDATA7月!J9+BACKDATA6月!J9+BACKDATA5月!J9+BACKDATA4月!J9 | K9: ='8月'!K9+BACKDATA7月!K9+BACKDATA6月!K9+BACKDATA5月!K9+BACKDATA4月!K9 | L9: ='8月'!L9+BACKDATA7月!L9+BACKDATA6月!L9+BACKDATA5月!L9+BACKDATA4月!L9 | M9: =L9-K9 | N9: =L9-J9 | O9: =IF(J9=0,"***",N9/J9) | P9: ='8月'!P9+BACKDATA7月!P9+BACKDATA6月!P9+BACKDATA5月!P9+BACKDATA4月!P9 | Q9: ='8月'!Q9+BACKDATA7月!Q9+BACKDATA6月!Q9+BACKDATA5月!Q9+BACKDATA4月!Q9 | R9: ='8月'!R9+BACKDATA7月!R9+BACKDATA6月!R9+BACKDATA5月!R9+BACKDATA4月!R9 | S9: ='8月'!S9+BACKDATA7月!S9+BACKDATA6月!S9+BACKDATA5月!S9+BACKDATA4月!S9 | T9: =S9-R9 | U9: =S9-Q9 | V9: =IF(Q9=0,"***",U9/Q9) | W9: =IF(I9=0,"***",P9/I9) | X9: =IF(J9=0,"***",Q9/J9) | Y9: =IF(K9=0,"***",R9/K9) | Z9: =IF(L9=0,"***",S9/L9) | AA9: =IF(Y9="***","***",Z9-X9) | AB9: =IF(Z9="***","***",Z9-X9)
F10: 下関営業所 | I10: ='8月'!I10+BACKDATA7月!I10+BACKDATA6月!I10+BACKDATA5月!I10+BACKDATA4月!I10 | J10: ='8月'!J10+BACKDATA7月!J10+BACKDATA6月!J10+BACKDATA5月!J10+BACKDATA4月!J10 | K10: ='8月'!K10+BACKDATA7月!K10+BACKDATA6月!K10+BACKDATA5月!K10+BACKDATA4月!K10 | L10: ='8月'!L10+BACKDATA7月!L10+BACKDATA6月!L10+BACKDATA5月!L10+BACKDATA4月!L10 | M10: =L10-K10 | N10: =L10-J10 | O10: =IF(J10=0,"***",N10/J10) | P10: ='8月'!P10+BACKDATA7月!P10+BACKDATA6月!P10+BACKDATA5月!P10+BACKDATA4月!P10 | Q10: ='8月'!Q10+BACKDATA7月!Q10+BACKDATA6月!Q10+BACKDATA5月!Q10+BACKDATA4月!Q10 | R10: ='8月'!R10+BACKDATA7月!R10+BACKDATA6月!R10+BACKDATA5月!R10+BACKDATA4月!R10 | S10: ='8月'!S10+BACKDATA7月!S10+BACKDATA6月!S10+BACKDATA5月!S10+BACKDATA4月!S10 | T10: =S10-R10 | U10: =S10-Q10 | V10: =IF(Q10=0,"***",U10/Q10) | W10: =IF(I10=0,"***",P10/I10) | X10: =IF(J10=0,"***",Q10/J10) | Y10: =IF(K10=0,"***",R10/K10) | Z10: =IF(L10=0,"***",S10/L10) | AA10: =IF(Y10="***","***",Z10-X10) | AB10: =IF(Z10="***","***",Z10-X10)
G11: 営業 | I11: =I10-I15-I14 | J11: =J10-J15-J14 | K11: =K10-K15-K14 | L11: =L10-L15-L14 | M11: =L11-K11 | N11: =L11-J11 | O11: =IF(J11=0,"***",N11/J11) | P11: =P10-P15-P14 | Q11: =Q10-Q15-Q14 | R11: =R10-R15-R14 | S11: =S10-S15-S14 | T11: =S11-R11 | U11: =S11-Q11 | V11: =IF(Q11=0,"***",U11/Q11) | W11: =IF(I11=0,"***",P11/I11) | X11: =IF(J11=0,"***",Q11/J11) | Y11: =IF(K11=0,"***",R11/K11) | Z11: =IF(L11=0,"***",S11/L11) | AA11: =IF(Y11="***","***",Z11-X11) | AB11: =IF(Z11="***","***",Z11-X11)
H12: 包装資材 | I12: =I11-I13 | J12: =J11-J13 | K12: =K11-K13 | L12: =L11-L13 | M12: =L12-K12 | N12: =L12-J12 | O12: =IF(J12=0,"***",N12/J12) | P12: =P11-P13 | Q12: =Q11-Q13 | R12: =R11-R13 | S12: =S11-S13 | T12: =S12-R12 | U12: =S12-Q12 | V12: =IF(Q12=0,"***",U12/Q12) | W12: =IF(I12=0,"***",P12/I12) | X12: =IF(J12=0,"***",Q12/J12) | Y12: =IF(K12=0,"***",R12/K12) | Z12: =IF(L12=0,"***",S12/L12) | AA12: =IF(Y12="***","***",Z12-X12) | AB12: =IF(Z12="***","***",Z12-X12)
H13: 機械 | I13: ='8月'!I13+BACKDATA7月!I13+BACKDATA6月!I13+BACKDATA5月!I13+BACKDATA4月!I13 | J13: ='8月'!J13+BACKDATA7月!J13+BACKDATA6月!J13+BACKDATA5月!J13+BACKDATA4月!J13 | K13: ='8月'!K13+BACKDATA7月!K13+BACKDATA6月!K13+BACKDATA5月!K13+BACKDATA4月!K13 | L13: ='8月'!L13+BACKDATA7月!L13+BACKDATA6月!L13+BACKDATA5月!L13+BACKDATA4月!L13 | M13: =L13-K13 | N13: =L13-J13 | O13: =IF(J13=0,"***",N13/J13) | P13: ='8月'!P13+BACKDATA7月!P13+BACKDATA6月!P13+BACKDATA5月!P13+BACKDATA4月!P13 | Q13: ='8月'!Q13+BACKDATA7月!Q13+BACKDATA6月!Q13+BACKDATA5月!Q13+BACKDATA4月!Q13 | R13: ='8月'!R13+BACKDATA7月!R13+BACKDATA6月!R13+BACKDATA5月!R13+BACKDATA4月!R13 | S13: ='8月'!S13+BACKDATA7月!S13+BACKDATA6月!S13+BACKDATA5月!S13+BACKDATA4月!S13 | T13: =S13-R13 | U13: =S13-Q13 | V13: =IF(Q13=0,"***",U13/Q13) | W13: =IF(I13=0,"***",P13/I13) | X13: =IF(J13=0,"***",Q13/J13) | Y13: =IF(K13=0,"***",R13/K13) | Z13: =IF(L13=0,"***",S13/L13) | AA13: =IF(Y13="***","***",Z13-X13) | AB13: =IF(Z13="***","***",Z13-X13)
G14: 自治体 | I14: ='8月'!I14+BACKDATA7月!I14+BACKDATA6月!I14+BACKDATA5月!I14+BACKDATA4月!I14 | J14: ='8月'!J14+BACKDATA7月!J14+BACKDATA6月!J14+BACKDATA5月!J14+BACKDATA4月!J14 | K14: ='8月'!K14+BACKDATA7月!K14+BACKDATA6月!K14+BACKDATA5月!K14+BACKDATA4月!K14 | L14: ='8月'!L14+BACKDATA7月!L14+BACKDATA6月!L14+BACKDATA5月!L14+BACKDATA4月!L14 | M14: =L14-K14 | N14: =L14-J14 | O14: =IF(J14=0,"***",N14/J14) | P14: ='8月'!P14+BACKDATA7月!P14+BACKDATA6月!P14+BACKDATA5月!P14+BACKDATA4月!P14 | Q14: ='8月'!Q14+BACKDATA7月!Q14+BACKDATA6月!Q14+BACKDATA5月!Q14+BACKDATA4月!Q14 | R14: ='8月'!R14+BACKDATA7月!R14+BACKDATA6月!R14+BACKDATA5月!R14+BACKDATA4月!R14 | S14: ='8月'!S14+BACKDATA7月!S14+BACKDATA6月!S14+BACKDATA5月!S14+BACKDATA4月!S14 | T14: =S14-R14 | U14: =S14-Q14 | V14: =IF(Q14=0,"***",U14/Q14) | W14: =IF(I14=0,"***",P14/I14) | X14: =IF(J14=0,"***",Q14/J14) | Y14: =IF(K14=0,"***",R14/K14) | Z14: =IF(L14=0,"***",S14/L14)
G15: 海外 | I15: ='8月'!I15+BACKDATA7月!I15+BACKDATA6月!I15+BACKDATA5月!I15+BACKDATA4月!I15 | J15: ='8月'!J15+BACKDATA7月!J15+BACKDATA6月!J15+BACKDATA5月!J15+BACKDATA4月!J15 | K15: ='8月'!K15+BACKDATA7月!K15+BACKDATA6月!K15+BACKDATA5月!K15+BACKDATA4月!K15 | L15: ='8月'!L15+BACKDATA7月!L15+BACKDATA6月!L15+BACKDATA5月!L15+BACKDATA4月!L15 | M15: =L15-K15 | N15: =L15-J15 | O15: =IF(J15=0,"***",N15/J15) | P15: ='8月'!P15+BACKDATA7月!P15+BACKDATA6月!P15+BACKDATA5月!P15+BACKDATA4月!P15 | Q15: ='8月'!Q15+BACKDATA7月!Q15+BACKDATA6月!Q15+BACKDATA5月!Q15+BACKDATA4月!Q15 | R15: ='8月'!R15+BACKDATA7月!R15+BACKDATA6月!R15+BACKDATA5月!R15+BACKDATA4月!R15 | S15: ='8月'!S15+BACKDATA7月!S15+BACKDATA6月!S15+BACKDATA5月!S15+BACKDATA4月!S15 | T15: =S15-R15 | U15: =S15-Q15 | V15: =IF(Q15=0,"***",U15/Q15) | W15: =IF(I15=0,"***",P15/I15) | X15: =IF(J15=0,"***",Q15/J15) | Y15: =IF(K15=0,"***",R15/K15) | Z15: =IF(L15=0,"***",S15/L15) | AA15: =IF(Y15="***","***",Z15-X15) | AB15: =IF(Z15="***","***",Z15-X15)
F16: 松江営業所 | I16: ='8月'!I16+BACKDATA7月!I16+BACKDATA6月!I16+BACKDATA5月!I16+BACKDATA4月!I16 | J16: ='8月'!J16+BACKDATA7月!J16+BACKDATA6月!J16+BACKDATA5月!J16+BACKDATA4月!J16 | K16: ='8月'!K16+BACKDATA7月!K16+BACKDATA6月!K16+BACKDATA5月!K16+BACKDATA4月!K16 | L16: ='8月'!L16+BACKDATA7月!L16+BACKDATA6月!L16+BACKDATA5月!L16+BACKDATA4月!L16 | M16: =L16-K16 | N16: =L16-J16 | O16: =IF(J16=0,"***",N16/J16) | P16: ='8月'!P16+BACKDATA7月!P16+BACKDATA6月!P16+BACKDATA5月!P16+BACKDATA4月!P16 | Q16: ='8月'!Q16+BACKDATA7月!Q16+BACKDATA6月!Q16+BACKDATA5月!Q16+BACKDATA4月!Q16 | R16: ='8月'!R16+BACKDATA7月!R16+BACKDATA6月!R16+BACKDATA5月!R16+BACKDATA4月!R16 | S16: ='8月'!S16+BACKDATA7月!S16+BACKDATA6月!S16+BACKDATA5月!S16+BACKDATA4月!S16 | T16: =S16-R16 | U16: =S16-Q16 | V16: =IF(Q16=0,"***",U16/Q16) | W16: =IF(I16=0,"***",P16/I16) | X16: =IF(J16=0,"***",Q16/J16) | Y16: =IF(K16=0,"***",R16/K16) | Z16: =IF(L16=0,"***",S16/L16) | AA16: =IF(Y16="***","***",Z16-X16) | AB16: =IF(Z16="***","***",Z16-X16)
G17: 営業 | I17: =I16-I20 | J17: =J16-J20 | K17: =K16-K20 | L17: =L16-L20 | M17: =L17-K17 | N17: =L17-J17 | O17: =IF(J17=0,"***",N17/J17) | P17: =P16-P20 | Q17: =Q16-Q20 | R17: =R16-R20 | S17: =S16-S20 | T17: =S17-R17 | U17: =S17-Q17 | V17: =IF(Q17=0,"***",U17/Q17) | W17: =IF(I17=0,"***",P17/I17) | X17: =IF(J17=0,"***",Q17/J17) | Y17: =IF(K17=0,"***",R17/K17) | Z17: =IF(L17=0,"***",S17/L17) | AA17: =IF(Y17="***","***",Z17-X17) | AB17: =IF(Z17="***","***",Z17-X17)
H18: 包装資材 | I18: =I17-I19 | J18: =J17-J19 | K18: =K17-K19 | L18: =L17-L19 | M18: =L18-K18 | N18: =L18-J18 | O18: =IF(J18=0,"***",N18/J18) | P18: =P17-P19 | Q18: =Q17-Q19 | R18: =R17-R19 | S18: =S17-S19 | T18: =S18-R18 | U18: =S18-Q18 | V18: =IF(Q18=0,"***",U18/Q18) | W18: =IF(I18=0,"***",P18/I18) | X18: =IF(J18=0,"***",Q18/J18) | Y18: =IF(K18=0,"***",R18/K18) | Z18: =IF(L18=0,"***",S18/L18) | AA18: =IF(Y18="***","***",Z18-X18) | AB18: =IF(Z18="***","***",Z18-X18)
H19: 機械 | I19: ='8月'!I19+BACKDATA7月!I19+BACKDATA6月!I19+BACKDATA5月!I19+BACKDATA4月!I19 | J19: ='8月'!J19+BACKDATA7月!J19+BACKDATA6月!J19+BACKDATA5月!J19+BACKDATA4月!J19 | K19: ='8月'!K19+BACKDATA7月!K19+BACKDATA6月!K19+BACKDATA5月!K19+BACKDATA4月!K19 | L19: ='8月'!L19+BACKDATA7月!L19+BACKDATA6月!L19+BACKDATA5月!L19+BACKDATA4月!L19 | M19: =L19-K19 | N19: =L19-J19 | O19: =IF(J19=0,"***",N19/J19) | P19: ='8月'!P19+BACKDATA7月!P19+BACKDATA6月!P19+BACKDATA5月!P19+BACKDATA4月!P19 | Q19: ='8月'!Q19+BACKDATA7月!Q19+BACKDATA6月!Q19+BACKDATA5月!Q19+BACKDATA4月!Q19 | R19: ='8月'!R19+BACKDATA7月!R19+BACKDATA6月!R19+BACKDATA5月!R19+BACKDATA4月!R19 | S19: ='8月'!S19+BACKDATA7月!S19+BACKDATA6月!S19+BACKDATA5月!S19+BACKDATA4月!S19 | T19: =S19-R19 | U19: =S19-Q19 | V19: =IF(Q19=0,"***",U19/Q19) | W19: =IF(I19=0,"***",P19/I19) | X19: =IF(J19=0,"***",Q19/J19) | Y19: =IF(K19=0,"***",R19/K19) | Z19: =IF(L19=0,"***",S19/L19) | AA19: =IF(Y19="***","***",Z19-X19) | AB19: =IF(Z19="***","***",Z19-X19)
G20: 自治体 | I20: ='8月'!I20+BACKDATA7月!I20+BACKDATA6月!I20+BACKDATA5月!I20+BACKDATA4月!I20 | J20: ='8月'!J20+BACKDATA7月!J20+BACKDATA6月!J20+BACKDATA5月!J20+BACKDATA4月!J20 | K20: ='8月'!K20+BACKDATA7月!K20+BACKDATA6月!K20+BACKDATA5月!K20+BACKDATA4月!K20 | L20: ='8月'!L20+BACKDATA7月!L20+BACKDATA6月!L20+BACKDATA5月!L20+BACKDATA4月!L20 | M20: =L20-K20 | N20: =L20-J20 | O20: =IF(J20=0,"***",N20/J20) | P20: ='8月'!P20+BACKDATA7月!P20+BACKDATA6月!P20+BACKDATA5月!P20+BACKDATA4月!P20 | Q20: ='8月'!Q20+BACKDATA7月!Q20+BACKDATA6月!Q20+BACKDATA5月!Q20+BACKDATA4月!Q20 | R20: ='8月'!R20+BACKDATA7月!R20+BACKDATA6月!R20+BACKDATA5月!R20+BACKDATA4月!R20 | S20: ='8月'!S20+BACKDATA7月!S20+BACKDATA6月!S20+BACKDATA5月!S20+BACKDATA4月!S20 | T20: =S20-R20 | U20: =S20-Q20 | V20: =IF(Q20=0,"***",U20/Q20) | W20: =IF(I20=0,"***",P20/I20) | X20: =IF(J20=0,"***",Q20/J20) | Y20: =IF(K20=0,"***",R20/K20) | Z20: =IF(L20=0,"***",S20/L20) | AA20: =IF(Y20="***","***",Z20-X20) | AB20: =IF(Z20="***","***",Z20-X20)
F21: 広域営業部 | I21: ='8月'!I21+BACKDATA7月!I21+BACKDATA6月!I21+BACKDATA5月!I21+BACKDATA4月!I21 | J21: ='8月'!J21+BACKDATA7月!J21+BACKDATA6月!J21+BACKDATA5月!J21+BACKDATA4月!J21 | K21: ='8月'!K21+BACKDATA7月!K21+BACKDATA6月!K21+BACKDATA5月!K21+BACKDATA4月!K21 | L21: ='8月'!L21+BACKDATA7月!L21+BACKDATA6月!L21+BACKDATA5月!L21+BACKDATA4月!L21 | M21: =L21-K21 | N21: =L21-J21 | O21: =IF(J21=0,"***",N21/J21) | P21: ='8月'!P21+BACKDATA7月!P21+BACKDATA6月!P21+BACKDATA5月!P21+BACKDATA4月!P21 | Q21: ='8月'!Q21+BACKDATA7月!Q21+BACKDATA6月!Q21+BACKDATA5月!Q21+BACKDATA4月!Q21 | R21: ='8月'!R21+BACKDATA7月!R21+BACKDATA6月!R21+BACKDATA5月!R21+BACKDATA4月!R21 | S21: ='8月'!S21+BACKDATA7月!S21+BACKDATA6月!S21+BACKDATA5月!S21+BACKDATA4月!S21 | T21: =S21-R21 | U21: =S21-Q21 | V21: =IF(Q21=0,"***",U21/Q21) | W21: =IF(I21=0,"***",P21/I21) | X21: =IF(J21=0,"***",Q21/J21) | Y21: =IF(K21=0,"***",R21/K21) | Z21: =IF(L21=0,"***",S21/L21) | AA21: =IF(Y21="***","***",Z21-X21) | AB21: =IF(Z21="***","***",Z21-X21)
H22: 包装資材 | I22: =I21-I23 | J22: =J21-J23 | K22: =K21-K23 | L22: =L21-L23 | M22: =L22-K22 | N22: =L22-J22 | O22: =IF(J22=0,"***",N22/J22) | P22: =P21-P23 | Q22: =Q21-Q23 | R22: =R21-R23 | S22: =S21-S23 | T22: =S22-R22 | U22: =S22-Q22 | V22: =IF(Q22=0,"***",U22/Q22) | W22: =IF(I22=0,"***",P22/I22) | X22: =IF(J22=0,"***",Q22/J22) | Y22: =IF(K22=0,"***",R22/K22) | Z22: =IF(L22=0,"***",S22/L22) | AA22: =IF(Y22="***","***",Z22-X22) | AB22: =IF(Z22="***","***",Z22-X22)
H23: 機械 | I23: ='8月'!I23+BACKDATA7月!I23+BACKDATA6月!I23+BACKDATA5月!I23+BACKDATA4月!I23 | J23: ='8月'!J23+BACKDATA7月!J23+BACKDATA6月!J23+BACKDATA5月!J23+BACKDATA4月!J23 | K23: ='8月'!K23+BACKDATA7月!K23+BACKDATA6月!K23+BACKDATA5月!K23+BACKDATA4月!K23 | L23: ='8月'!L23+BACKDATA7月!L23+BACKDATA6月!L23+BACKDATA5月!L23+BACKDATA4月!L23 | M23: =L23-K23 | N23: =L23-J23 | O23: =IF(J23=0,"***",N23/J23) | P23: ='8月'!P23+BACKDATA7月!P23+BACKDATA6月!P23+BACKDATA5月!P23+BACKDATA4月!P23 | Q23: ='8月'!Q23+BACKDATA7月!Q23+BACKDATA6月!Q23+BACKDATA5月!Q23+BACKDATA4月!Q23 | R23: ='8月'!R23+BACKDATA7月!R23+BACKDATA6月!R23+BACKDATA5月!R23+BACKDATA4月!R23 | S23: ='8月'!S23+BACKDATA7月!S23+BACKDATA6月!S23+BACKDATA5月!S23+BACKDATA4月!S23 | T23: =S23-R23 | U23: =S23-Q23 | V23: =IF(Q23=0,"***",U23/Q23) | W23: =IF(I23=0,"***",P23/I23) | X23: =IF(J23=0,"***",Q23/J23) | Y23: =IF(K23=0,"***",R23/K23) | Z23: =IF(L23=0,"***",S23/L23) | AA23: =IF(Y23="***","***",Z23-X23) | AB23: =IF(Z23="***","***",Z23-X23)
G24: リンガーハット | I24: ='8月'!I24+BACKDATA7月!I24+BACKDATA6月!I24+BACKDATA5月!I24+BACKDATA4月!I24 | J24: ='8月'!J24+BACKDATA7月!J24+BACKDATA6月!J24+BACKDATA5月!J24+BACKDATA4月!J24 | K24: ='8月'!K24+BACKDATA7月!K24+BACKDATA6月!K24+BACKDATA5月!K24+BACKDATA4月!K24 | L24: ='8月'!L24+BACKDATA7月!L24+BACKDATA6月!L24+BACKDATA5月!L24+BACKDATA4月!L24 | M24: =L24-K24 | N24: =L24-J24 | O24: =IF(J24=0,"***",N24/J24) | P24: ='8月'!P24+BACKDATA7月!P24+BACKDATA6月!P24+BACKDATA5月!P24+BACKDATA4月!P24 | Q24: ='8月'!Q24+BACKDATA7月!Q24+BACKDATA6月!Q24+BACKDATA5月!Q24+BACKDATA4月!Q24 | R24: ='8月'!R24+BACKDATA7月!R24+BACKDATA6月!R24+BACKDATA5月!R24+BACKDATA4月!R24 | S24: ='8月'!S24+BACKDATA7月!S24+BACKDATA6月!S24+BACKDATA5月!S24+BACKDATA4月!S24 | T24: =S24-R24 | U24: =S24-Q24 | V24: =IF(Q24=0,"***",U24/Q24) | W24: =IF(I24=0,"***",P24/I24) | X24: =IF(J24=0,"***",Q24/J24) | Y24: =IF(K24=0,"***",R24/K24) | Z24: =IF(L24=0,"***",S24/L24) | AA24: =IF(Y24="***","***",Z24-X24) | AB24: =IF(Z24="***","***",Z24-X24)
H25: 包装資材 | I25: =I24-I26 | J25: =J24-J26 | K25: =K24-K26 | L25: =L24-L26 | M25: =L25-K25 | N25: =L25-J25 | O25: =IF(J25=0,"***",N25/J25) | P25: =P24-P26 | Q25: =Q24-Q26 | R25: =R24-R26 | S25: =S24-S26 | T25: =S25-R25 | U25: =S25-Q25 | V25: =IF(Q25=0,"***",U25/Q25) | W25: =IF(I25=0,"***",P25/I25) | X25: =IF(J25=0,"***",Q25/J25) | Y25: =IF(K25=0,"***",R25/K25) | Z25: =IF(L25=0,"***",S25/L25) | AA25: =IF(Y25="***","***",Z25-X25) | AB25: =IF(Z25="***","***",Z25-X25)
H26: 機械 | I26: ='8月'!I26+BACKDATA7月!I26+BACKDATA6月!I26+BACKDATA5月!I26+BACKDATA4月!I26 | J26: ='8月'!J26+BACKDATA7月!J26+BACKDATA6月!J26+BACKDATA5月!J26+BACKDATA4月!J26 | K26: ='8月'!K26+BACKDATA7月!K26+BACKDATA6月!K26+BACKDATA5月!K26+BACKDATA4月!K26 | L26: ='8月'!L26+BACKDATA7月!L26+BACKDATA6月!L26+BACKDATA5月!L26+BACKDATA4月!L26 | M26: =L26-K26 | N26: =L26-J26 | O26: =IF(J26=0,"***",N26/J26) | P26: ='8月'!P26+BACKDATA7月!P26+BACKDATA6月!P26+BACKDATA5月!P26+BACKDATA4月!P26 | Q26: ='8月'!Q26+BACKDATA7月!Q26+BACKDATA6月!Q26+BACKDATA5月!Q26+BACKDATA4月!Q26 | R26: ='8月'!R26+BACKDATA7月!R26+BACKDATA6月!R26+BACKDATA5月!R26+BACKDATA4月!R26 | S26: ='8月'!S26+BACKDATA7月!S26+BACKDATA6月!S26+BACKDATA5月!S26+BACKDATA4月!S26 | T26: =S26-R26 | U26: =S26-Q26 | V26: =IF(Q26=0,"***",U26/Q26) | W26: =IF(I26=0,"***",P26/I26) | X26: =IF(J26=0,"***",Q26/J26) | Y26: =IF(K26=0,"***",R26/K26) | Z26: =IF(L26=0,"***",S26/L26) | AA26: =IF(Y26="***","***",Z26-X26) | AB26: =IF(Z26="***","***",Z26-X26)
G27: リンガーハット以外 | I27: =I21-I24 | J27: =J21-J24 | K27: =K21-K24 | L27: =L21-L24 | M27: =L27-K27 | N27: =L27-J27 | O27: =IF(J27=0,"***",N27/J27) | P27: =P21-P24 | Q27: =Q21-Q24 | R27: =R21-R24 | S27: =S21-S24 | T27: =S27-R27 | U27: =S27-Q27 | V27: =IF(Q27=0,"***",U27/Q27) | W27: =IF(I27=0,"***",P27/I27) | X27: =IF(J27=0,"***",Q27/J27) | Y27: =IF(K27=0,"***",R27/K27) | Z27: =IF(L27=0,"***",S27/L27) | AA27: =IF(Y27="***","***",Z27-X27) | AB27: =IF(Z27="***","***",Z27-X27)
H28: 包装資材 | I28: =I27-I29 | J28: =J27-J29 | K28: =K27-K29 | L28: =L27-L29 | M28: =L28-K28 | N28: =L28-J28 | O28: =IF(J28=0,"***",N28/J28) | P28: =P27-P29 | Q28: =Q27-Q29 | R28: =R27-R29 | S28: =S27-S29 | T28: =S28-R28 | U28: =S28-Q28 | V28: =IF(Q28=0,"***",U28/Q28) | W28: =IF(I28=0,"***",P28/I28) | X28: =IF(J28=0,"***",Q28/J28) | Y28: =IF(K28=0,"***",R28/K28) | Z28: =IF(L28=0,"***",S28/L28) | AA28: =IF(Y28="***","***",Z28-X28) | AB28: =IF(Z28="***","***",Z28-X28)
H29: 機械 | I29: =I23-I26 | J29: =J23-J26 | K29: =K23-K26 | L29: =L23-L26 | M29: =L29-K29 | N29: =L29-J29 | O29: =IF(J29=0,"***",N29/J29) | P29: =P23-P26 | Q29: =Q23-Q26 | R29: =R23-R26 | S29: =S23-S26 | T29: =S29-R29 | U29: =S29-Q29 | V29: =IF(Q29=0,"***",U29/Q29) | W29: =IF(I29=0,"***",P29/I29) | X29: =IF(J29=0,"***",Q29/J29) | Y29: =IF(K29=0,"***",R29/K29) | Z29: =IF(L29=0,"***",S29/L29) | AA29: =IF(Y29="***","***",Z29-X29) | AB29: =IF(Z29="***","***",Z29-X29)
F30: 境港営業所 | I30: ='8月'!I30+BACKDATA7月!I30+BACKDATA6月!I30+BACKDATA5月!I30+BACKDATA4月!I30 | J30: ='8月'!J30+BACKDATA7月!J30+BACKDATA6月!J30+BACKDATA5月!J30+BACKDATA4月!J30 | K30: ='8月'!K30+BACKDATA7月!K30+BACKDATA6月!K30+BACKDATA5月!K30+BACKDATA4月!K30 | L30: ='8月'!L30+BACKDATA7月!L30+BACKDATA6月!L30+BACKDATA5月!L30+BACKDATA4月!L30 | M30: =L30-K30 | N30: =L30-J30 | O30: =IF(J30=0,"***",N30/J30) | P30: ='8月'!P30+BACKDATA7月!P30+BACKDATA6月!P30+BACKDATA5月!P30+BACKDATA4月!P30 | Q30: ='8月'!Q30+BACKDATA7月!Q30+BACKDATA6月!Q30+BACKDATA5月!Q30+BACKDATA4月!Q30 | R30: ='8月'!R30+BACKDATA7月!R30+BACKDATA6月!R30+BACKDATA5月!R30+BACKDATA4月!R30 | S30: ='8月'!S30+BACKDATA7月!S30+BACKDATA6月!S30+BACKDATA5月!S30+BACKDATA4月!S30 | T30: =S30-R30 | U30: =S30-Q30 | V30: =IF(Q30=0,"***",U30/Q30) | W30: =IF(I30=0,"***",P30/I30) | X30: =IF(J30=0,"***",Q30/J30) | Y30: =IF(K30=0,"***",R30/K30) | Z30: =IF(L30=0,"***",S30/L30) | AA30: =IF(Y30="***","***",Z30-X30) | AB30: =IF(Z30="***","***",Z30-X30)
G31: 営業 | I31: =I30-I35-I34 | J31: =J30-J35-J34 | K31: =K30-K35-K34 | L31: =L30-L35-L34 | M31: =L31-K31 | N31: =L31-J31 | O31: =IF(J31=0,"***",N31/J31) | P31: =P30-P35-P34 | Q31: =Q30-Q35-Q34 | R31: =R30-R35-R34 | S31: =S30-S35-S34 | T31: =S31-R31 | U31: =S31-Q31 | V31: =IF(Q31=0,"***",U31/Q31) | W31: =IF(I31=0,"***",P31/I31) | X31: =IF(J31=0,"***",Q31/J31) | Y31: =IF(K31=0,"***",R31/K31) | Z31: =IF(L31=0,"***",S31/L31) | AA31: =IF(Y31="***","***",Z31-X31) | AB31: =IF(Z31="***","***",Z31-X31)
H32: 包装資材 | I32: =I31-I33 | J32: =J31-J33 | K32: =K31-K33 | L32: =L31-L33 | M32: =L32-K32 | N32: =L32-J32 | O32: =IF(J32=0,"***",N32/J32) | P32: =P31-P33 | Q32: =Q31-Q33 | R32: =R31-R33 | S32: =S31-S33 | T32: =S32-R32 | U32: =S32-Q32 | V32: =IF(Q32=0,"***",U32/Q32) | W32: =IF(I32=0,"***",P32/I32) | X32: =IF(J32=0,"***",Q32/J32) | Y32: =IF(K32=0,"***",R32/K32) | Z32: =IF(L32=0,"***",S32/L32) | AA32: =IF(Y32="***","***",Z32-X32) | AB32: =IF(Z32="***","***",Z32-X32)
H33: 機械 | I33: ='8月'!I33+BACKDATA7月!I33+BACKDATA6月!I33+BACKDATA5月!I33+BACKDATA4月!I33 | J33: ='8月'!J33+BACKDATA7月!J33+BACKDATA6月!J33+BACKDATA5月!J33+BACKDATA4月!J33 | K33: ='8月'!K33+BACKDATA7月!K33+BACKDATA6月!K33+BACKDATA5月!K33+BACKDATA4月!K33 | L33: ='8月'!L33+BACKDATA7月!L33+BACKDATA6月!L33+BACKDATA5月!L33+BACKDATA4月!L33 | M33: =L33-K33 | N33: =L33-J33 | O33: =IF(J33=0,"***",N33/J33) | P33: ='8月'!P33+BACKDATA7月!P33+BACKDATA6月!P33+BACKDATA5月!P33+BACKDATA4月!P33 | Q33: ='8月'!Q33+BACKDATA7月!Q33+BACKDATA6月!Q33+BACKDATA5月!Q33+BACKDATA4月!Q33 | R33: ='8月'!R33+BACKDATA7月!R33+BACKDATA6月!R33+BACKDATA5月!R33+BACKDATA4月!R33 | S33: ='8月'!S33+BACKDATA7月!S33+BACKDATA6月!S33+BACKDATA5月!S33+BACKDATA4月!S33 | T33: =S33-R33 | U33: =S33-Q33 | V33: =IF(Q33=0,"***",U33/Q33) | W33: =IF(I33=0,"***",P33/I33) | X33: =IF(J33=0,"***",Q33/J33) | Y33: =IF(K33=0,"***",R33/K33) | Z33: =IF(L33=0,"***",S33/L33) | AA33: =IF(Y33="***","***",Z33-X33) | AB33: =IF(Z33="***","***",Z33-X33)
G34: 自治体 | I34: ='8月'!I34+BACKDATA7月!I34+BACKDATA6月!I34+BACKDATA5月!I34+BACKDATA4月!I34 | J34: ='8月'!J34+BACKDATA7月!J34+BACKDATA6月!J34+BACKDATA5月!J34+BACKDATA4月!J34 | K34: ='8月'!K34+BACKDATA7月!K34+BACKDATA6月!K34+BACKDATA5月!K34+BACKDATA4月!K34 | L34: ='8月'!L34+BACKDATA7月!L34+BACKDATA6月!L34+BACKDATA5月!L34+BACKDATA4月!L34 | M34: =L34-K34 | N34: =L34-J34 | O34: =IF(J34=0,"***",N34/J34) | P34: ='8月'!P34+BACKDATA7月!P34+BACKDATA6月!P34+BACKDATA5月!P34+BACKDATA4月!P34 | Q34: ='8月'!Q34+BACKDATA7月!Q34+BACKDATA6月!Q34+BACKDATA5月!Q34+BACKDATA4月!Q34 | R34: ='8月'!R34+BACKDATA7月!R34+BACKDATA6月!R34+BACKDATA5月!R34+BACKDATA4月!R34 | S34: ='8月'!S34+BACKDATA7月!S34+BACKDATA6月!S34+BACKDATA5月!S34+BACKDATA4月!S34 | T34: =S34-R34 | U34: =S34-Q34 | V34: =IF(Q34=0,"***",U34/Q34) | W34: =IF(I34=0,"***",P34/I34) | X34: =IF(J34=0,"***",Q34/J34) | Y34: =IF(K34=0,"***",R34/K34) | Z34: =IF(L34=0,"***",S34/L34) | AA34: =IF(Y34="***","***",Z34-X34) | AB34: =IF(Z34="***","***",Z34-X34)
G35: 海外 | I35: ='8月'!I35+BACKDATA7月!I35+BACKDATA6月!I35+BACKDATA5月!I35+BACKDATA4月!I35 | J35: ='8月'!J35+BACKDATA7月!J35+BACKDATA6月!J35+BACKDATA5月!J35+BACKDATA4月!J35 | K35: ='8月'!K35+BACKDATA7月!K35+BACKDATA6月!K35+BACKDATA5月!K35+BACKDATA4月!K35 | L35: ='8月'!L35+BACKDATA7月!L35+BACKDATA6月!L35+BACKDATA5月!L35+BACKDATA4月!L35 | M35: =L35-K35 | N35: =L35-J35 | O35: =IF(J35=0,"***",N35/J35) | P35: ='8月'!P35+BACKDATA7月!P35+BACKDATA6月!P35+BACKDATA5月!P35+BACKDATA4月!P35 | Q35: ='8月'!Q35+BACKDATA7月!Q35+BACKDATA6月!Q35+BACKDATA5月!Q35+BACKDATA4月!Q35 | R35: ='8月'!R35+BACKDATA7月!R35+BACKDATA6月!R35+BACKDATA5月!R35+BACKDATA4月!R35 | S35: ='8月'!S35+BACKDATA7月!S35+BACKDATA6月!S35+BACKDATA5月!S35+BACKDATA4月!S35 | T35: =S35-R35 | U35: =S35-Q35 | V35: =IF(Q35=0,"***",U35/Q35) | W35: =IF(I35=0,"***",P35/I35) | X35: =IF(J35=0,"***",Q35/J35) | Y35: =IF(K35=0,"***",R35/K35) | Z35: =IF(L35=0,"***",S35/L35) | AA35: =IF(Y35="***","***",Z35-X35) | AB35: =IF(Z35="***","***",Z35-X35)
E36: 営業部門合計 | I36: =I30+I21+I16+I10+I5 | J36: =J30+J21+J16+J10+J5 | K36: =K30+K21+K16+K10+K5 | L36: =L30+L21+L16+L10+L5 | M36: =L36-K36 | N36: =L36-J36 | O36: =IF(J36=0,"***",N36/J36) | P36: =P30+P21+P16+P10+P5 | Q36: =Q30+Q21+Q16+Q10+Q5 | R36: =R30+R21+R16+R10+R5 | S36: =S30+S21+S16+S10+S5 | T36: =S36-R36 | U36: =S36-Q36 | V36: =IF(Q36=0,"***",U36/Q36) | W36: =IF(I36=0,"***",P36/I36) | X36: =IF(J36=0,"***",Q36/J36) | Y36: =IF(K36=0,"***",R36/K36) | Z36: =IF(L36=0,"***",S36/L36) | AA36: =IF(Y36="***","***",Z36-X36) | AB36: =IF(Z36="***","***",Z36-X36)
H37: 機械以外 | I37: =I36-I38-I39-I40 | J37: =J36-J38-J39-J40 | K37: =K36-K38-K39-K40 | L37: =L36-L38-L39-L40 | M37: =L37-K37 | N37: =L37-J37 | O37: =IF(J37=0,"***",N37/J37) | P37: =P36-P38-P39-P40 | Q37: =Q36-Q38-Q39-Q40 | R37: =R36-R38-R39-R40 | S37: =S36-S38-S39-S40 | T37: =S37-R37 | U37: =S37-Q37 | V37: =IF(Q37=0,"***",U37/Q37) | W37: =IF(I37=0,"***",P37/I37) | X37: =IF(J37=0,"***",Q37/J37) | Y37: =IF(K37=0,"***",R37/K37) | Z37: =IF(L37=0,"***",S37/L37) | AA37: =IF(Y37="***","***",Z37-X37) | AB37: =IF(Z37="***","***",Z37-X37)
H38: 機械 | I38: =I33+I23+I19+I13+I8 | J38: =J33+J23+J19+J13+J8 | K38: =K33+K23+K19+K13+K8 | L38: =L33+L23+L19+L13+L8 | M38: =L38-K38 | N38: =L38-J38 | O38: =IF(J38=0,"***",N38/J38) | P38: =P33+P23+P19+P13+P8 | Q38: =Q33+Q23+Q19+Q13+Q8 | R38: =R33+R23+R19+R13+R8 | S38: =S33+S23+S19+S13+S8 | T38: =S38-R38 | U38: =S38-Q38 | V38: =IF(Q38=0,"***",U38/Q38) | W38: =IF(I38=0,"***",P38/I38) | X38: =IF(J38=0,"***",Q38/J38) | Y38: =IF(K38=0,"***",R38/K38) | Z38: =IF(L38=0,"***",S38/L38) | AA38: =IF(Y38="***","***",Z38-X38) | AB38: =IF(Z38="***","***",Z38-X38)
H39: 自治体 | I39: =I34+I20+I14+I9 | J39: =J34+J20+J14+J9 | K39: =K34+K20+K14+K9 | L39: =L34+L20+L14+L9 | M39: =L39-K39 | N39: =L39-J39 | O39: =IF(J39=0,"***",N39/J39) | P39: =P34+P20+P14+P9 | Q39: =Q34+Q20+Q14+Q9 | R39: =R34+R20+R14+R9 | S39: =S34+S20+S14+S9 | T39: =S39-R39 | U39: =S39-Q39 | V39: =IF(Q39=0,"***",U39/Q39) | W39: =IF(I39=0,"***",P39/I39) | X39: =IF(J39=0,"***",Q39/J39) | Y39: =IF(K39=0,"***",R39/K39) | Z39: =IF(L39=0,"***",S39/L39) | AA39: =IF(Y39="***","***",Z39-X39) | AB39: =IF(Z39="***","***",Z39-X39)
H40: 海外 | I40: =I35+I15 | J40: =J35+J15 | K40: =K35+K15 | L40: =L35+L15 | M40: =L40-K40 | N40: =L40-J40 | O40: =IF(J40=0,"***",N40/J40) | P40: =P35+P15 | Q40: =Q35+Q15 | R40: =R35+R15 | S40: =S35+S15 | T40: =S40-R40 | U40: =S40-Q40 | V40: =IF(Q40=0,"***",U40/Q40) | W40: =IF(I40=0,"***",P40/I40) | X40: =IF(J40=0,"***",Q40/J40) | Y40: =IF(K40=0,"***",R40/K40) | Z40: =IF(L40=0,"***",S40/L40) | AA40: =IF(Y40="***","***",Z40-X40) | AB40: =IF(Z40="***","***",Z40-X40)
E41: 水産部 | I41: ='8月'!I41+BACKDATA7月!I41+BACKDATA6月!I41+BACKDATA5月!I41+BACKDATA4月!I41 | J41: ='8月'!J41+BACKDATA7月!J41+BACKDATA6月!J41+BACKDATA5月!J41+BACKDATA4月!J41 | K41: ='8月'!K41+BACKDATA7月!K41+BACKDATA6月!K41+BACKDATA5月!K41+BACKDATA4月!K41 | L41: ='8月'!L41+BACKDATA7月!L41+BACKDATA6月!L41+BACKDATA5月!L41+BACKDATA4月!L41 | M41: =L41-K41 | N41: =L41-J41 | O41: =IF(J41=0,"***",N41/J41) | P41: ='8月'!P41+BACKDATA7月!P41+BACKDATA6月!P41+BACKDATA5月!P41+BACKDATA4月!P41 | Q41: ='8月'!Q41+BACKDATA7月!Q41+BACKDATA6月!Q41+BACKDATA5月!Q41+BACKDATA4月!Q41 | R41: ='8月'!R41+BACKDATA7月!R41+BACKDATA6月!R41+BACKDATA5月!R41+BACKDATA4月!R41 | S41: ='8月'!S41+BACKDATA7月!S41+BACKDATA6月!S41+BACKDATA5月!S41+BACKDATA4月!S41 | T41: =S41-R41 | U41: =S41-Q41 | V41: =IF(Q41=0,"***",U41/Q41) | W41: =IF(I41=0,"***",P41/I41) | X41: =IF(J41=0,"***",Q41/J41) | Y41: =IF(K41=0,"***",R41/K41) | Z41: =IF(L41=0,"***",S41/L41) | AA41: =IF(Y41="***","***",Z41-X41) | AB41: =IF(Z41="***","***",Z41-X41)
H42: 包装資材 | I42: =I41-I43-I44 | J42: =J41-J43-J44 | K42: =K41-K43-K44 | L42: =L41-L43-L44 | M42: =L42-K42 | N42: =L42-J42 | O42: =IF(J42=0,"***",N42/J42) | P42: =P41-P43-P44 | Q42: =Q41-Q43-Q44 | R42: =R41-R43-R44 | S42: =S41-S43-S44 | T42: =S42-R42 | U42: =S42-Q42 | V42: =IF(Q42=0,"***",U42/Q42) | W42: =IF(I42=0,"***",P42/I42) | X42: =IF(J42=0,"***",Q42/J42) | Y42: =IF(K42=0,"***",R42/K42) | Z42: =IF(L42=0,"***",S42/L42) | AA42: =IF(Y42="***","***",Z42-X42) | AB42: =IF(Z42="***","***",Z42-X42)
H43: 荷役 | I43: ='8月'!I43+BACKDATA7月!I43+BACKDATA6月!I43+BACKDATA5月!I43+BACKDATA4月!I43 | J43: ='8月'!J43+BACKDATA7月!J43+BACKDATA6月!J43+BACKDATA5月!J43+BACKDATA4月!J43 | K43: ='8月'!K43+BACKDATA7月!K43+BACKDATA6月!K43+BACKDATA5月!K43+BACKDATA4月!K43 | L43: ='8月'!L43+BACKDATA7月!L43+BACKDATA6月!L43+BACKDATA5月!L43+BACKDATA4月!L43 | M43: =L43-K43 | N43: =L43-J43 | O43: =IF(J43=0,"***",N43/J43) | P43: ='8月'!P43+BACKDATA7月!P43+BACKDATA6月!P43+BACKDATA5月!P43+BACKDATA4月!P43 | Q43: ='8月'!Q43+BACKDATA7月!Q43+BACKDATA6月!Q43+BACKDATA5月!Q43+BACKDATA4月!Q43 | R43: ='8月'!R43+BACKDATA7月!R43+BACKDATA6月!R43+BACKDATA5月!R43+BACKDATA4月!R43 | S43: ='8月'!S43+BACKDATA7月!S43+BACKDATA6月!S43+BACKDATA5月!S43+BACKDATA4月!S43 | T43: =S43-R43 | U43: =S43-Q43 | V43: =IF(Q43=0,"***",U43/Q43) | W43: =IF(I43=0,"***",P43/I43) | X43: =IF(J43=0,"***",Q43/J43) | Y43: =IF(K43=0,"***",R43/K43) | Z43: =IF(L43=0,"***",S43/L43)
H44: 機械 | I44: ='8月'!I44+BACKDATA7月!I44+BACKDATA6月!I44+BACKDATA5月!I44+BACKDATA4月!I44 | J44: ='8月'!J44+BACKDATA7月!J44+BACKDATA6月!J44+BACKDATA5月!J44+BACKDATA4月!J44 | K44: ='8月'!K44+BACKDATA7月!K44+BACKDATA6月!K44+BACKDATA5月!K44+BACKDATA4月!K44 | L44: ='8月'!L44+BACKDATA7月!L44+BACKDATA6月!L44+BACKDATA5月!L44+BACKDATA4月!L44 | M44: =L44-K44 | N44: =L44-J44 | O44: =IF(J44=0,"***",N44/J44) | P44: ='8月'!P44+BACKDATA7月!P44+BACKDATA6月!P44+BACKDATA5月!P44+BACKDATA4月!P44 | Q44: ='8月'!Q44+BACKDATA7月!Q44+BACKDATA6月!Q44+BACKDATA5月!Q44+BACKDATA4月!Q44 | R44: ='8月'!R44+BACKDATA7月!R44+BACKDATA6月!R44+BACKDATA5月!R44+BACKDATA4月!R44 | S44: ='8月'!S44+BACKDATA7月!S44+BACKDATA6月!S44+BACKDATA5月!S44+BACKDATA4月!S44 | T44: =S44-R44 | U44: =S44-Q44 | V44: =IF(Q44=0,"***",U44/Q44) | W44: =IF(I44=0,"***",P44/I44) | X44: =IF(J44=0,"***",Q44/J44) | Y44: =IF(K44=0,"***",R44/K44) | Z44: =IF(L44=0,"***",S44/L44) | AA44: =IF(Y44="***","***",Z44-X44) | AB44: =IF(Z44="***","***",Z44-X44)
D45: 合計 | I45: =I41+I36 | J45: =J41+J36 | K45: =K41+K36 | L45: =L41+L36 | M45: =L45-K45 | N45: =L45-J45 | O45: =IF(J45=0,"***",N45/J45) | P45: =P41+P36 | Q45: =Q41+Q36 | R45: =R41+R36 | S45: =S41+S36 | T45: =S45-R45 | U45: =S45-Q45 | V45: =IF(Q45=0,"***",U45/Q45) | W45: =IF(I45=0,"***",P45/I45) | X45: =IF(J45=0,"***",Q45/J45) | Y45: =IF(K45=0,"***",R45/K45) | Z45: =IF(L45=0,"***",S45/L45) | AA45: =IF(Y45="***","***",Z45-X45) | AB45: =IF(Z45="***","***",Z45-X45)
H46: 機械以外 | I46: =I45-I47 | J46: =J45-J47 | K46: =K45-K47 | L46: =L45-L47 | M46: =L46-K46 | N46: =L46-J46 | O46: =IF(J46=0,"***",N46/J46) | P46: =P45-P47 | Q46: =Q45-Q47 | R46: =R45-R47 | S46: =S45-S47 | T46: =S46-R46 | U46: =S46-Q46 | V46: =IF(Q46=0,"***",U46/Q46) | W46: =IF(I46=0,"***",P46/I46) | X46: =IF(J46=0,"***",Q46/J46) | Y46: =IF(K46=0,"***",R46/K46) | Z46: =IF(L46=0,"***",S46/L46) | AA46: =IF(Y46="***","***",Z46-X46) | AB46: =IF(Z46="***","***",Z46-X46)
H47: 機械 | I47: =I38+I44 | J47: =J38+J44 | K47: =K38+K44 | L47: =L38+L44 | M47: =L47-K47 | N47: =L47-J47 | O47: =IF(J47=0,"***",N47/J47) | P47: =P38+P44 | Q47: =Q38+Q44 | R47: =R38+R44 | S47: =S38+S44 | T47: =S47-R47 | U47: =S47-Q47 | V47: =IF(Q47=0,"***",U47/Q47) | W47: =IF(I47=0,"***",P47/I47) | X47: =IF(J47=0,"***",Q47/J47) | Y47: =IF(K47=0,"***",R47/K47) | Z47: =IF(L47=0,"***",S47/L47) | AA47: =IF(Y47="***","***",Z47-X47) | AB47: =IF(Z47="***","***",Z47-X47)
H48: 自治体 | I48: =I39 | J48: =J39 | K48: =K39 | L48: =L39 | M48: =L48-K48 | N48: =L48-J48 | O48: =IF(J48=0,"***",N48/J48) | P48: =P39 | Q48: =Q39 | R48: =R39 | S48: =S39 | T48: =S48-R48 | U48: =S48-Q48 | V48: =IF(Q48=0,"***",U48/Q48) | W48: =IF(I48=0,"***",P48/I48) | X48: =IF(J48=0,"***",Q48/J48) | Y48: =IF(K48=0,"***",R48/K48) | Z48: =IF(L48=0,"***",S48/L48) | AA48: =IF(Y48="***","***",Z48-X48) | AB48: =IF(Z48="***","***",Z48-X48)
H49: 海外 | I49: =I40 | J49: =J40 | K49: =K40 | L49: =L40 | M49: =L49-K49 | N49: =L49-J49 | O49: =IF(J49=0,"***",N49/J49) | P49: =P40 | Q49: =Q40 | R49: =R40 | S49: =S40 | T49: =S49-R49 | U49: =S49-Q49 | V49: =IF(Q49=0,"***",U49/Q49) | W49: =IF(I49=0,"***",P49/I49) | X49: =IF(J49=0,"***",Q49/J49) | Y49: =IF(K49=0,"***",R49/K49) | Z49: =IF(L49=0,"***",S49/L49) | AA49: =IF(Y49="***","***",Z49-X49) | AB49: =IF(Z49="***","***",Z49-X49)
D50: キョウワ（税抜） | I50: ='8月'!I50+BACKDATA7月!I50+BACKDATA6月!I50+BACKDATA5月!I50+BACKDATA4月!I50 | J50: ='8月'!J50+BACKDATA7月!J50+BACKDATA6月!J50+BACKDATA5月!J50+BACKDATA4月!J50 | K50: ='8月'!K50+BACKDATA7月!K50+BACKDATA6月!K50+BACKDATA5月!K50+BACKDATA4月!K50 | L50: ='8月'!L50+BACKDATA7月!L50+BACKDATA6月!L50+BACKDATA5月!L50+BACKDATA4月!L50 | M50: =L50-K50 | N50: =L50-J50 | O50: =IF(J50=0,"***",N50/J50) | P50: ='8月'!P50+BACKDATA7月!P50+BACKDATA6月!P50+BACKDATA5月!P50+BACKDATA4月!P50 | Q50: ='8月'!Q50+BACKDATA7月!Q50+BACKDATA6月!Q50+BACKDATA5月!Q50+BACKDATA4月!Q50 | R50: ='8月'!R50+BACKDATA7月!R50+BACKDATA6月!R50+BACKDATA5月!R50+BACKDATA4月!R50 | S50: ='8月'!S50+BACKDATA7月!S50+BACKDATA6月!S50+BACKDATA5月!S50+BACKDATA4月!S50 | T50: =S50-R50 | U50: =S50-Q50 | V50: =IF(Q50=0,"***",U50/Q50) | W50: =IF(I50=0,"***",P50/I50) | X50: =IF(J50=0,"***",Q50/J50) | Y50: =IF(K50=0,"***",R50/K50) | Z50: =IF(L50=0,"***",S50/L50) | AA50: =IF(Y50="***","***",Z50-X50) | AB50: =IF(Z50="***","***",Z50-X50)

Sheet 期初来累計
D1: 3．期初来累計（上期＋下期）
I3: 前々期売上実績 | J3: 前期売上実績 | K3: 今期期初来計画 | L3: 今期期初来実績 | P3: 前々期粗利益実績 | Q3: 前期粗利益実績 | R3: 今期期初来粗利計画 | S3: 今期期初来粗利実績 | W3: 前々期初来粗利益率実績 | X3: 前期期初来粗利益率実績 | Y3: 今期期初来粗利益率計画 | Z3: 今期期初来粗利益率実績 | AC3: 作成根拠
M4: 計画比 | N4: 前期比 | O4: 年率 | T4: 計画比 | U4: 前期比 | V4: 年率 | AA4: 計画比 | AB4: 前期比
F5: 石見営業所 | I5: =BACKDATA上期!CO5+下期!I5 | J5: =BACKDATA上期!CP5+下期!J5 | K5: =BACKDATA上期!CQ5+下期!K5 | L5: =BACKDATA上期!CR5+下期!L5 | M5: =L5-K5 | N5: =L5-J5 | O5: =IF(J5=0,"***",N5/J5) | P5: =BACKDATA上期!CV5+下期!P5 | Q5: =BACKDATA上期!CW5+下期!Q5 | R5: =BACKDATA上期!CX5+下期!R5 | S5: =BACKDATA上期!CY5+下期!S5 | T5: =S5-R5 | U5: =S5-Q5 | V5: =IF(Q5=0,"***",U5/Q5) | W5: =IF(I5=0,"***",P5/I5) | X5: =IF(J5=0,"***",Q5/J5) | Y5: =IF(K5=0,"***",R5/K5) | Z5: =IF(L5=0,"***",S5/L5) | AA5: =IF(Y5="***","***",Z5-X5) | AB5: =IF(Z5="***","***",Z5-X5)
G6: 営業 | I6: =I5-I9 | J6: =J5-J9 | K6: =K5-K9 | L6: =L5-L9 | M6: =L6-K6 | N6: =L6-J6 | O6: =IF(J6=0,"***",N6/J6) | P6: =P5-P9 | Q6: =Q5-Q9 | R6: =R5-R9 | S6: =S5-S9 | T6: =S6-R6 | U6: =S6-Q6 | V6: =IF(Q6=0,"***",U6/Q6) | W6: =IF(I6=0,"***",P6/I6) | X6: =IF(J6=0,"***",Q6/J6) | Y6: =IF(K6=0,"***",R6/K6) | Z6: =IF(L6=0,"***",S6/L6) | AA6: =IF(Y6="***","***",Z6-X6) | AB6: =IF(Z6="***","***",Z6-X6)
H7: 包装資材 | I7: =I6-I8 | J7: =J6-J8 | K7: =K6-K8 | L7: =L6-L8 | M7: =L7-K7 | N7: =L7-J7 | O7: =IF(J7=0,"***",N7/J7) | P7: =P6-P8 | Q7: =Q6-Q8 | R7: =R6-R8 | S7: =S6-S8 | T7: =S7-R7 | U7: =S7-Q7 | V7: =IF(Q7=0,"***",U7/Q7) | W7: =IF(I7=0,"***",P7/I7) | X7: =IF(J7=0,"***",Q7/J7) | Y7: =IF(K7=0,"***",R7/K7) | Z7: =IF(L7=0,"***",S7/L7) | AA7: =IF(Y7="***","***",Z7-X7) | AB7: =IF(Z7="***","***",Z7-X7)
H8: 機械 | I8: =BACKDATA上期!CO8+下期!I8 | J8: =BACKDATA上期!CP8+下期!J8 | K8: =BACKDATA上期!CQ8+下期!K8 | L8: =BACKDATA上期!CR8+下期!L8 | M8: =L8-K8 | N8: =L8-J8 | O8: =IF(J8=0,"***",N8/J8) | P8: =BACKDATA上期!CV8+下期!P8 | Q8: =BACKDATA上期!CW8+下期!Q8 | R8: =BACKDATA上期!CX8+下期!R8 | S8: =BACKDATA上期!CY8+下期!S8 | T8: =S8-R8 | U8: =S8-Q8 | V8: =IF(Q8=0,"***",U8/Q8) | W8: =IF(I8=0,"***",P8/I8) | X8: =IF(J8=0,"***",Q8/J8) | Y8: =IF(K8=0,"***",R8/K8) | Z8: =IF(L8=0,"***",S8/L8) | AA8: =IF(Y8="***","***",Z8-X8) | AB8: =IF(Z8="***","***",Z8-X8)
G9: 自治体 | I9: =BACKDATA上期!CO9+下期!I9 | J9: =BACKDATA上期!CP9+下期!J9 | K9: =BACKDATA上期!CQ9+下期!K9 | L9: =BACKDATA上期!CR9+下期!L9 | M9: =L9-K9 | N9: =L9-J9 | O9: =IF(J9=0,"***",N9/J9) | P9: =BACKDATA上期!CV9+下期!P9 | Q9: =BACKDATA上期!CW9+下期!Q9 | R9: =BACKDATA上期!CX9+下期!R9 | S9: =BACKDATA上期!CY9+下期!S9 | T9: =S9-R9 | U9: =S9-Q9 | V9: =IF(Q9=0,"***",U9/Q9) | W9: =IF(I9=0,"***",P9/I9) | X9: =IF(J9=0,"***",Q9/J9) | Y9: =IF(K9=0,"***",R9/K9) | Z9: =IF(L9=0,"***",S9/L9) | AA9: =IF(Y9="***","***",Z9-X9) | AB9: =IF(Z9="***","***",Z9-X9)
F10: 下関営業所 | I10: =BACKDATA上期!CO10+下期!I10 | J10: =BACKDATA上期!CP10+下期!J10 | K10: =BACKDATA上期!CQ10+下期!K10 | L10: =BACKDATA上期!CR10+下期!L10 | M10: =L10-K10 | N10: =L10-J10 | O10: =IF(J10=0,"***",N10/J10) | P10: =BACKDATA上期!CV10+下期!P10 | Q10: =BACKDATA上期!CW10+下期!Q10 | R10: =BACKDATA上期!CX10+下期!R10 | S10: =BACKDATA上期!CY10+下期!S10 | T10: =S10-R10 | U10: =S10-Q10 | V10: =IF(Q10=0,"***",U10/Q10) | W10: =IF(I10=0,"***",P10/I10) | X10: =IF(J10=0,"***",Q10/J10) | Y10: =IF(K10=0,"***",R10/K10) | Z10: =IF(L10=0,"***",S10/L10) | AA10: =IF(Y10="***","***",Z10-X10) | AB10: =IF(Z10="***","***",Z10-X10)
G11: 営業 | I11: =I10-I15-I14 | J11: =J10-J15-J14 | K11: =K10-K15-K14 | L11: =L10-L15-L14 | M11: =L11-K11 | N11: =L11-J11 | O11: =IF(J11=0,"***",N11/J11) | P11: =P10-P15-P14 | Q11: =Q10-Q15-Q14 | R11: =R10-R15-R14 | S11: =S10-S15-S14 | T11: =S11-R11 | U11: =S11-Q11 | V11: =IF(Q11=0,"***",U11/Q11) | W11: =IF(I11=0,"***",P11/I11) | X11: =IF(J11=0,"***",Q11/J11) | Y11: =IF(K11=0,"***",R11/K11) | Z11: =IF(L11=0,"***",S11/L11) | AA11: =IF(Y11="***","***",Z11-X11) | AB11: =IF(Z11="***","***",Z11-X11)
H12: 包装資材 | I12: =I11-I13 | J12: =J11-J13 | K12: =K11-K13 | L12: =L11-L13 | M12: =L12-K12 | N12: =L12-J12 | O12: =IF(J12=0,"***",N12/J12) | P12: =P11-P13 | Q12: =Q11-Q13 | R12: =R11-R13 | S12: =S11-S13 | T12: =S12-R12 | U12: =S12-Q12 | V12: =IF(Q12=0,"***",U12/Q12) | W12: =IF(I12=0,"***",P12/I12) | X12: =IF(J12=0,"***",Q12/J12) | Y12: =IF(K12=0,"***",R12/K12) | Z12: =IF(L12=0,"***",S12/L12) | AA12: =IF(Y12="***","***",Z12-X12) | AB12: =IF(Z12="***","***",Z12-X12)
H13: 機械 | I13: =BACKDATA上期!CO13+下期!I13 | J13: =BACKDATA上期!CP13+下期!J13 | K13: =BACKDATA上期!CQ13+下期!K13 | L13: =BACKDATA上期!CR13+下期!L13 | M13: =L13-K13 | N13: =L13-J13 | O13: =IF(J13=0,"***",N13/J13) | P13: =BACKDATA上期!CV13+下期!P13 | Q13: =BACKDATA上期!CW13+下期!Q13 | R13: =BACKDATA上期!CX13+下期!R13 | S13: =BACKDATA上期!CY13+下期!S13 | T13: =S13-R13 | U13: =S13-Q13 | V13: =IF(Q13=0,"***",U13/Q13) | W13: =IF(I13=0,"***",P13/I13) | X13: =IF(J13=0,"***",Q13/J13) | Y13: =IF(K13=0,"***",R13/K13) | Z13: =IF(L13=0,"***",S13/L13) | AA13: =IF(Y13="***","***",Z13-X13) | AB13: =IF(Z13="***","***",Z13-X13)
G14: 自治体 | I14: =BACKDATA上期!CO14+下期!I14 | J14: =BACKDATA上期!CP14+下期!J14 | K14: =BACKDATA上期!CQ14+下期!K14 | L14: =BACKDATA上期!CR14+下期!L14 | M14: =L14-K14 | N14: =L14-J14 | O14: =IF(J14=0,"***",N14/J14) | P14: =BACKDATA上期!CV14+下期!P14 | Q14: =BACKDATA上期!CW14+下期!Q14 | R14: =BACKDATA上期!CX14+下期!R14 | S14: =BACKDATA上期!CY14+下期!S14 | T14: =S14-R14 | U14: =S14-Q14 | V14: =IF(Q14=0,"***",U14/Q14) | W14: =IF(I14=0,"***",P14/I14) | X14: =IF(J14=0,"***",Q14/J14) | Y14: =IF(K14=0,"***",R14/K14) | Z14: =IF(L14=0,"***",S14/L14) | AA14: =IF(Y14="***","***",Z14-X14) | AB14: =IF(Z14="***","***",Z14-X14)
G15: 海外 | I15: =BACKDATA上期!CO15+下期!I15 | J15: =BACKDATA上期!CP15+下期!J15 | K15: =BACKDATA上期!CQ15+下期!K15 | L15: =BACKDATA上期!CR15+下期!L15 | M15: =L15-K15 | N15: =L15-J15 | O15: =IF(J15=0,"***",N15/J15) | P15: =BACKDATA上期!CV15+下期!P15 | Q15: =BACKDATA上期!CW15+下期!Q15 | R15: =BACKDATA上期!CX15+下期!R15 | S15: =BACKDATA上期!CY15+下期!S15 | T15: =S15-R15 | U15: =S15-Q15 | V15: =IF(Q15=0,"***",U15/Q15) | W15: =IF(I15=0,"***",P15/I15) | X15: =IF(J15=0,"***",Q15/J15) | Y15: =IF(K15=0,"***",R15/K15) | Z15: =IF(L15=0,"***",S15/L15) | AA15: =IF(Y15="***","***",Z15-X15) | AB15: =IF(Z15="***","***",Z15-X15)
F16: 松江営業所 | I16: =BACKDATA上期!CO16+下期!I16 | J16: =BACKDATA上期!CP16+下期!J16 | K16: =BACKDATA上期!CQ16+下期!K16 | L16: =BACKDATA上期!CR16+下期!L16 | M16: =L16-K16 | N16: =L16-J16 | O16: =IF(J16=0,"***",N16/J16) | P16: =BACKDATA上期!CV16+下期!P16 | Q16: =BACKDATA上期!CW16+下期!Q16 | R16: =BACKDATA上期!CX16+下期!R16 | S16: =BACKDATA上期!CY16+下期!S16 | T16: =S16-R16 | U16: =S16-Q16 | V16: =IF(Q16=0,"***",U16/Q16) | W16: =IF(I16=0,"***",P16/I16) | X16: =IF(J16=0,"***",Q16/J16) | Y16: =IF(K16=0,"***",R16/K16) | Z16: =IF(L16=0,"***",S16/L16) | AA16: =IF(Y16="***","***",Z16-X16) | AB16: =IF(Z16="***","***",Z16-X16)
G17: 営業 | I17: =I16-I20 | J17: =J16-J20 | K17: =K16-K20 | L17: =L16-L20 | M17: =L17-K17 | N17: =L17-J17 | O17: =IF(J17=0,"***",N17/J17) | P17: =P16-P20 | Q17: =Q16-Q20 | R17: =R16-R20 | S17: =S16-S20 | T17: =S17-R17 | U17: =S17-Q17 | V17: =IF(Q17=0,"***",U17/Q17) | W17: =IF(I17=0,"***",P17/I17) | X17: =IF(J17=0,"***",Q17/J17) | Y17: =IF(K17=0,"***",R17/K17) | Z17: =IF(L17=0,"***",S17/L17) | AA17: =IF(Y17="***","***",Z17-X17) | AB17: =IF(Z17="***","***",Z17-X17)
H18: 包装資材 | I18: =I17-I19 | J18: =J17-J19 | K18: =K17-K19 | L18: =L17-L19 | M18: =L18-K18 | N18: =L18-J18 | O18: =IF(J18=0,"***",N18/J18) | P18: =P17-P19 | Q18: =Q17-Q19 | R18: =R17-R19 | S18: =S17-S19 | T18: =S18-R18 | U18: =S18-Q18 | V18: =IF(Q18=0,"***",U18/Q18) | W18: =IF(I18=0,"***",P18/I18) | X18: =IF(J18=0,"***",Q18/J18) | Y18: =IF(K18=0,"***",R18/K18) | Z18: =IF(L18=0,"***",S18/L18) | AA18: =IF(Y18="***","***",Z18-X18) | AB18: =IF(Z18="***","***",Z18-X18)
H19: 機械 | I19: =BACKDATA上期!CO19+下期!I19 | J19: =BACKDATA上期!CP19+下期!J19 | K19: =BACKDATA上期!CQ19+下期!K19 | L19: =BACKDATA上期!CR19+下期!L19 | M19: =L19-K19 | N19: =L19-J19 | O19: =IF(J19=0,"***",N19/J19) | P19: =BACKDATA上期!CV19+下期!P19 | Q19: =BACKDATA上期!CW19+下期!Q19 | R19: =BACKDATA上期!CX19+下期!R19 | S19: =BACKDATA上期!CY19+下期!S19 | T19: =S19-R19 | U19: =S19-Q19 | V19: =IF(Q19=0,"***",U19/Q19) | W19: =IF(I19=0,"***",P19/I19) | X19: =IF(J19=0,"***",Q19/J19) | Y19: =IF(K19=0,"***",R19/K19) | Z19: =IF(L19=0,"***",S19/L19) | AA19: =IF(Y19="***","***",Z19-X19) | AB19: =IF(Z19="***","***",Z19-X19)
G20: 自治体 | I20: =BACKDATA上期!CO20+下期!I20 | J20: =BACKDATA上期!CP20+下期!J20 | K20: =BACKDATA上期!CQ20+下期!K20 | L20: =BACKDATA上期!CR20+下期!L20 | M20: =L20-K20 | N20: =L20-J20 | O20: =IF(J20=0,"***",N20/J20) | P20: =BACKDATA上期!CV20+下期!P20 | Q20: =BACKDATA上期!CW20+下期!Q20 | R20: =BACKDATA上期!CX20+下期!R20 | S20: =BACKDATA上期!CY20+下期!S20 | T20: =S20-R20 | U20: =S20-Q20 | V20: =IF(Q20=0,"***",U20/Q20) | W20: =IF(I20=0,"***",P20/I20) | X20: =IF(J20=0,"***",Q20/J20) | Y20: =IF(K20=0,"***",R20/K20) | Z20: =IF(L20=0,"***",S20/L20) | AA20: =IF(Y20="***","***",Z20-X20) | AB20: =IF(Z20="***","***",Z20-X20)
F21: 広域営業部 | I21: =BACKDATA上期!CO21+下期!I21 | J21: =BACKDATA上期!CP21+下期!J21 | K21: =BACKDATA上期!CQ21+下期!K21 | L21: =BACKDATA上期!CR21+下期!L21 | M21: =L21-K21 | N21: =L21-J21 | O21: =IF(J21=0,"***",N21/J21) | P21: =BACKDATA上期!CV21+下期!P21 | Q21: =BACKDATA上期!CW21+下期!Q21 | R21: =BACKDATA上期!CX21+下期!R21 | S21: =BACKDATA上期!CY21+下期!S21 | T21: =S21-R21 | U21: =S21-Q21 | V21: =IF(Q21=0,"***",U21/Q21) | W21: =IF(I21=0,"***",P21/I21) | X21: =IF(J21=0,"***",Q21/J21) | Y21: =IF(K21=0,"***",R21/K21) | Z21: =IF(L21=0,"***",S21/L21) | AA21: =IF(Y21="***","***",Z21-X21) | AB21: =IF(Z21="***","***",Z21-X21)
H22: 包装資材 | I22: =I21-I23 | J22: =J21-J23 | K22: =K21-K23 | L22: =L21-L23 | M22: =L22-K22 | N22: =L22-J22 | O22: =IF(J22=0,"***",N22/J22) | P22: =P21-P23 | Q22: =Q21-Q23 | R22: =R21-R23 | S22: =S21-S23 | T22: =S22-R22 | U22: =S22-Q22 | V22: =IF(Q22=0,"***",U22/Q22) | W22: =IF(I22=0,"***",P22/I22) | X22: =IF(J22=0,"***",Q22/J22) | Y22: =IF(K22=0,"***",R22/K22) | Z22: =IF(L22=0,"***",S22/L22) | AA22: =IF(Y22="***","***",Z22-X22) | AB22: =IF(Z22="***","***",Z22-X22)
H23: 機械 | I23: =BACKDATA上期!CO23+下期!I23 | J23: =BACKDATA上期!CP23+下期!J23 | K23: =BACKDATA上期!CQ23+下期!K23 | L23: =BACKDATA上期!CR23+下期!L23 | M23: =L23-K23 | N23: =L23-J23 | O23: =IF(J23=0,"***",N23/J23) | P23: =BACKDATA上期!CV23+下期!P23 | Q23: =BACKDATA上期!CW23+下期!Q23 | R23: =BACKDATA上期!CX23+下期!R23 | S23: =BACKDATA上期!CY23+下期!S23 | T23: =S23-R23 | U23: =S23-Q23 | V23: =IF(Q23=0,"***",U23/Q23) | W23: =IF(I23=0,"***",P23/I23) | X23: =IF(J23=0,"***",Q23/J23) | Y23: =IF(K23=0,"***",R23/K23) | Z23: =IF(L23=0,"***",S23/L23) | AA23: =IF(Y23="***","***",Z23-X23) | AB23: =IF(Z23="***","***",Z23-X23)
G24: リンガーハット | I24: =BACKDATA上期!CO24+下期!I24 | J24: =BACKDATA上期!CP24+下期!J24 | K24: =BACKDATA上期!CQ24+下期!K24 | L24: =BACKDATA上期!CR24+下期!L24 | M24: =L24-K24 | N24: =L24-J24 | O24: =IF(J24=0,"***",N24/J24) | P24: =BACKDATA上期!CV24+下期!P24 | Q24: =BACKDATA上期!CW24+下期!Q24 | R24: =BACKDATA上期!CX24+下期!R24 | S24: =BACKDATA上期!CY24+下期!S24 | T24: =S24-R24 | U24: =S24-Q24 | V24: =IF(Q24=0,"***",U24/Q24) | W24: =IF(I24=0,"***",P24/I24) | X24: =IF(J24=0,"***",Q24/J24) | Y24: =IF(K24=0,"***",R24/K24) | Z24: =IF(L24=0,"***",S24/L24) | AA24: =IF(Y24="***","***",Z24-X24) | AB24: =IF(Z24="***","***",Z24-X24)
H25: 包装資材 | I25: =I24-I26 | J25: =J24-J26 | K25: =K24-K26 | L25: =L24-L26 | M25: =L25-K25 | N25: =L25-J25 | O25: =IF(J25=0,"***",N25/J25) | P25: =P24-P26 | Q25: =Q24-Q26 | R25: =R24-R26 | S25: =S24-S26 | T25: =S25-R25 | U25: =S25-Q25 | V25: =IF(Q25=0,"***",U25/Q25) | W25: =IF(I25=0,"***",P25/I25) | X25: =IF(J25=0,"***",Q25/J25) | Y25: =IF(K25=0,"***",R25/K25) | Z25: =IF(L25=0,"***",S25/L25) | AA25: =IF(Y25="***","***",Z25-X25) | AB25: =IF(Z25="***","***",Z25-X25)
H26: 機械 | I26: =BACKDATA上期!CO26+下期!I26 | J26: =BACKDATA上期!CP26+下期!J26 | K26: =BACKDATA上期!CQ26+下期!K26 | L26: =BACKDATA上期!CR26+下期!L26 | M26: =L26-K26 | N26: =L26-J26 | O26: =IF(J26=0,"***",N26/J26) | P26: =BACKDATA上期!CV26+下期!P26 | Q26: =BACKDATA上期!CW26+下期!Q26 | R26: =BACKDATA上期!CX26+下期!R26 | S26: =BACKDATA上期!CY26+下期!S26 | T26: =S26-R26 | U26: =S26-Q26 | V26: =IF(Q26=0,"***",U26/Q26) | W26: =IF(I26=0,"***",P26/I26) | X26: =IF(J26=0,"***",Q26/J26) | Y26: =IF(K26=0,"***",R26/K26) | Z26: =IF(L26=0,"***",S26/L26) | AA26: =IF(Y26="***","***",Z26-X26) | AB26: =IF(Z26="***","***",Z26-X26)
G27: リンガーハット以外 | I27: =I21-I24 | J27: =J21-J24 | K27: =K21-K24 | L27: =L21-L24 | M27: =L27-K27 | N27: =L27-J27 | O27: =IF(J27=0,"***",N27/J27) | P27: =P21-P24 | Q27: =Q21-Q24 | R27: =R21-R24 | S27: =S21-S24 | T27: =S27-R27 | U27: =S27-Q27 | V27: =IF(Q27=0,"***",U27/Q27) | W27: =IF(I27=0,"***",P27/I27) | X27: =IF(J27=0,"***",Q27/J27) | Y27: =IF(K27=0,"***",R27/K27) | Z27: =IF(L27=0,"***",S27/L27) | AA27: =IF(Y27="***","***",Z27-X27) | AB27: =IF(Z27="***","***",Z27-X27)
H28: 包装資材 | I28: =I27-I29 | J28: =J27-J29 | K28: =K27-K29 | L28: =L27-L29 | M28: =L28-K28 | N28: =L28-J28 | O28: =IF(J28=0,"***",N28/J28) | P28: =P27-P29 | Q28: =Q27-Q29 | R28: =R27-R29 | S28: =S27-S29 | T28: =S28-R28 | U28: =S28-Q28 | V28: =IF(Q28=0,"***",U28/Q28) | W28: =IF(I28=0,"***",P28/I28) | X28: =IF(J28=0,"***",Q28/J28) | Y28: =IF(K28=0,"***",R28/K28) | Z28: =IF(L28=0,"***",S28/L28) | AA28: =IF(Y28="***","***",Z28-X28) | AB28: =IF(Z28="***","***",Z28-X28)
H29: 機械 | I29: =I23-I26 | J29: =J23-J26 | K29: =K23-K26 | L29: =L23-L26 | M29: =L29-K29 | N29: =L29-J29 | O29: =IF(J29=0,"***",N29/J29) | P29: =P23-P26 | Q29: =Q23-Q26 | R29: =R23-R26 | S29: =S23-S26 | T29: =S29-R29 | U29: =S29-Q29 | V29: =IF(Q29=0,"***",U29/Q29) | W29: =IF(I29=0,"***",P29/I29) | X29: =IF(J29=0,"***",Q29/J29) | Y29: =IF(K29=0,"***",R29/K29) | Z29: =IF(L29=0,"***",S29/L29) | AA29: =IF(Y29="***","***",Z29-X29) | AB29: =IF(Z29="***","***",Z29-X29)
F30: 境港営業所 | I30: =BACKDATA上期!CO30+下期!I30 | J30: =BACKDATA上期!CP30+下期!J30 | K30: =BACKDATA上期!CQ30+下期!K30 | L30: =BACKDATA上期!CR30+下期!L30 | M30: =L30-K30 | N30: =L30-J30 | O30: =IF(J30=0,"***",N30/J30) | P30: =BACKDATA上期!CV30+下期!P30 | Q30: =BACKDATA上期!CW30+下期!Q30 | R30: =BACKDATA上期!CX30+下期!R30 | S30: =BACKDATA上期!CY30+下期!S30 | T30: =S30-R30 | U30: =S30-Q30 | V30: =IF(Q30=0,"***",U30/Q30) | W30: =IF(I30=0,"***",P30/I30) | X30: =IF(J30=0,"***",Q30/J30) | Y30: =IF(K30=0,"***",R30/K30) | Z30: =IF(L30=0,"***",S30/L30) | AA30: =IF(Y30="***","***",Z30-X30) | AB30: =IF(Z30="***","***",Z30-X30)
G31: 営業 | I31: =I30-I35-I34 | J31: =J30-J35-J34 | K31: =K30-K35-K34 | L31: =L30-L35-L34 | M31: =L31-K31 | N31: =L31-J31 | O31: =IF(J31=0,"***",N31/J31) | P31: =P30-P35-P34 | Q31: =Q30-Q35-Q34 | R31: =R30-R35-R34 | S31: =S30-S35-S34 | T31: =S31-R31 | U31: =S31-Q31 | V31: =IF(Q31=0,"***",U31/Q31) | W31: =IF(I31=0,"***",P31/I31) | X31: =IF(J31=0,"***",Q31/J31) | Y31: =IF(K31=0,"***",R31/K31) | Z31: =IF(L31=0,"***",S31/L31) | AA31: =IF(Y31="***","***",Z31-X31) | AB31: =IF(Z31="***","***",Z31-X31)
H32: 包装資材 | I32: =I31-I33 | J32: =J31-J33 | K32: =K31-K33 | L32: =L31-L33 | M32: =L32-K32 | N32: =L32-J32 | O32: =IF(J32=0,"***",N32/J32) | P32: =P31-P33 | Q32: =Q31-Q33 | R32: =R31-R33 | S32: =S31-S33 | T32: =S32-R32 | U32: =S32-Q32 | V32: =IF(Q32=0,"***",U32/Q32) | W32: =IF(I32=0,"***",P32/I32) | X32: =IF(J32=0,"***",Q32/J32) | Y32: =IF(K32=0,"***",R32/K32) | Z32: =IF(L32=0,"***",S32/L32) | AA32: =IF(Y32="***","***",Z32-X32) | AB32: =IF(Z32="***","***",Z32-X32)
H33: 機械 | I33: =BACKDATA上期!CO33+下期!I33 | J33: =BACKDATA上期!CP33+下期!J33 | K33: =BACKDATA上期!CQ33+下期!K33 | L33: =BACKDATA上期!CR33+下期!L33 | M33: =L33-K33 | N33: =L33-J33 | O33: =IF(J33=0,"***",N33/J33) | P33: =BACKDATA上期!CV33+下期!P33 | Q33: =BACKDATA上期!CW33+下期!Q33 | R33: =BACKDATA上期!CX33+下期!R33 | S33: =BACKDATA上期!CY33+下期!S33 | T33: =S33-R33 | U33: =S33-Q33 | V33: =IF(Q33=0,"***",U33/Q33) | W33: =IF(I33=0,"***",P33/I33) | X33: =IF(J33=0,"***",Q33/J33) | Y33: =IF(K33=0,"***",R33/K33) | Z33: =IF(L33=0,"***",S33/L33) | AA33: =IF(Y33="***","***",Z33-X33) | AB33: =IF(Z33="***","***",Z33-X33)
G34: 自治体 | I34: =BACKDATA上期!CO34+下期!I34 | J34: =BACKDATA上期!CP34+下期!J34 | K34: =BACKDATA上期!CQ34+下期!K34 | L34: =BACKDATA上期!CR34+下期!L34 | M34: =L34-K34 | N34: =L34-J34 | O34: =IF(J34=0,"***",N34/J34) | P34: =BACKDATA上期!CV34+下期!P34 | Q34: =BACKDATA上期!CW34+下期!Q34 | R34: =BACKDATA上期!CX34+下期!R34 | S34: =BACKDATA上期!CY34+下期!S34 | T34: =S34-R34 | U34: =S34-Q34 | V34: =IF(Q34=0,"***",U34/Q34) | W34: =IF(I34=0,"***",P34/I34) | X34: =IF(J34=0,"***",Q34/J34) | Y34: =IF(K34=0,"***",R34/K34) | Z34: =IF(L34=0,"***",S34/L34) | AA34: =IF(Y34="***","***",Z34-X34) | AB34: =IF(Z34="***","***",Z34-X34)
G35: 海外 | I35: =BACKDATA上期!CO35+下期!I35 | J35: =BACKDATA上期!CP35+下期!J35 | K35: =BACKDATA上期!CQ35+下期!K35 | L35: =BACKDATA上期!CR35+下期!L35 | M35: =L35-K35 | N35: =L35-J35 | O35: =IF(J35=0,"***",N35/J35) | P35: =BACKDATA上期!CV35+下期!P35 | Q35: =BACKDATA上期!CW35+下期!Q35 | R35: =BACKDATA上期!CX35+下期!R35 | S35: =BACKDATA上期!CY35+下期!S35 | T35: =S35-R35 | U35: =S35-Q35 | V35: =IF(Q35=0,"***",U35/Q35) | W35: =IF(I35=0,"***",P35/I35) | X35: =IF(J35=0,"***",Q35/J35) | Y35: =IF(K35=0,"***",R35/K35) | Z35: =IF(L35=0,"***",S35/L35) | AA35: =IF(Y35="***","***",Z35-X35) | AB35: =IF(Z35="***","***",Z35-X35)
E36: 営業部門合計 | I36: =I30+I21+I16+I10+I5 | J36: =J30+J21+J16+J10+J5 | K36: =K30+K21+K16+K10+K5 | L36: =L30+L21+L16+L10+L5 | M36: =L36-K36 | N36: =L36-J36 | O36: =IF(J36=0,"***",N36/J36) | P36: =P30+P21+P16+P10+P5 | Q36: =Q30+Q21+Q16+Q10+Q5 | R36: =R30+R21+R16+R10+R5 | S36: =S30+S21+S16+S10+S5 | T36: =S36-R36 | U36: =S36-Q36 | V36: =IF(Q36=0,"***",U36/Q36) | W36: =IF(I36=0,"***",P36/I36) | X36: =IF(J36=0,"***",Q36/J36) | Y36: =IF(K36=0,"***",R36/K36) | Z36: =IF(L36=0,"***",S36/L36) | AA36: =IF(Y36="***","***",Z36-X36) | AB36: =IF(Z36="***","***",Z36-X36)
H37: 機械以外 | I37: =I36-I38-I39-I40 | J37: =J36-J38-J39-J40 | K37: =K36-K38-K39-K40 | L37: =L36-L38-L39-L40 | M37: =L37-K37 | N37: =L37-J37 | O37: =IF(J37=0,"***",N37/J37) | P37: =P36-P38-P39-P40 | Q37: =Q36-Q38-Q39-Q40 | R37: =R36-R38-R39-R40 | S37: =S36-S38-S39-S40 | T37: =S37-R37 | U37: =S37-Q37 | V37: =IF(Q37=0,"***",U37/Q37) | W37: =IF(I37=0,"***",P37/I37) | X37: =IF(J37=0,"***",Q37/J37) | Y37: =IF(K37=0,"***",R37/K37) | Z37: =IF(L37=0,"***",S37/L37) | AA37: =IF(Y37="***","***",Z37-X37) | AB37: =IF(Z37="***","***",Z37-X37)
H38: 機械 | I38: =I33+I23+I19+I13+I8 | J38: =J33+J23+J19+J13+J8 | K38: =K33+K23+K19+K13+K8 | L38: =L33+L23+L19+L13+L8 | M38: =L38-K38 | N38: =L38-J38 | O38: =IF(J38=0,"***",N38/J38) | P38: =P33+P23+P19+P13+P8 | Q38: =Q33+Q23+Q19+Q13+Q8 | R38: =R33+R23+R19+R13+R8 | S38: =S33+S23+S19+S13+S8 | T38: =S38-R38 | U38: =S38-Q38 | V38: =IF(Q38=0,"***",U38/Q38) | W38: =IF(I38=0,"***",P38/I38) | X38: =IF(J38=0,"***",Q38/J38) | Y38: =IF(K38=0,"***",R38/K38) | Z38: =IF(L38=0,"***",S38/L38) | AA38: =IF(Y38="***","***",Z38-X38) | AB38: =IF(Z38="***","***",Z38-X38)
H39: 自治体 | I39: =I34+I20+I14+I9 | J39: =J34+J20+J14+J9 | K39: =K34+K20+K14+K9 | L39: =L34+L20+L14+L9 | M39: =L39-K39 | N39: =L39-J39 | O39: =IF(J39=0,"***",N39/J39) | P39: =P34+P20+P14+P9 | Q39: =Q34+Q20+Q14+Q9 | R39: =R34+R20+R14+R9 | S39: =S34+S20+S14+S9 | T39: =S39-R39 | U39: =S39-Q39 | V39: =IF(Q39=0,"***",U39/Q39) | W39: =IF(I39=0,"***",P39/I39) | X39: =IF(J39=0,"***",Q39/J39) | Y39: =IF(K39=0,"***",R39/K39) | Z39: =IF(L39=0,"***",S39/L39) | AA39: =IF(Y39="***","***",Z39-X39) | AB39: =IF(Z39="***","***",Z39-X39)
H40: 海外 | I40: =I35+I15 | J40: =J35+J15 | K40: =K35+K15 | L40: =L35+L15 | M40: =L40-K40 | N40: =L40-J40 | O40: =IF(J40=0,"***",N40/J40) | P40: =P35+P15 | Q40: =Q35+Q15 | R40: =R35+R15 | S40: =S35+S15 | T40: =S40-R40 | U40: =S40-Q40 | V40: =IF(Q40=0,"***",U40/Q40) | W40: =IF(I40=0,"***",P40/I40) | X40: =IF(J40=0,"***",Q40/J40) | Y40: =IF(K40=0,"***",R40/K40) | Z40: =IF(L40=0,"***",S40/L40) | AA40: =IF(Y40="***","***",Z40-X40) | AB40: =IF(Z40="***","***",Z40-X40)
E41: 水産部 | I41: =BACKDATA上期!CO41+下期!I41 | J41: =BACKDATA上期!CP41+下期!J41 | K41: =BACKDATA上期!CQ41+下期!K41 | L41: =BACKDATA上期!CR41+下期!L41 | M41: =L41-K41 | N41: =L41-J41 | O41: =IF(J41=0,"***",N41/J41) | P41: =BACKDATA上期!CV41+下期!P41 | Q41: =BACKDATA上期!CW41+下期!Q41 | R41: =BACKDATA上期!CX41+下期!R41 | S41: =BACKDATA上期!CY41+下期!S41 | T41: =S41-R41 | U41: =S41-Q41 | V41: =IF(Q41=0,"***",U41/Q41) | W41: =IF(I41=0,"***",P41/I41) | X41: =IF(J41=0,"***",Q41/J41) | Y41: =IF(K41=0,"***",R41/K41) | Z41: =IF(L41=0,"***",S41/L41) | AA41: =IF(Y41="***","***",Z41-X41) | AB41: =IF(Z41="***","***",Z41-X41)
H42: 包装資材 | I42: =I41-I43-I44 | J42: =J41-J43-J44 | K42: =K41-K43-K44 | L42: =L41-L43-L44 | M42: =L42-K42 | N42: =L42-J42 | O42: =IF(J42=0,"***",N42/J42) | P42: =P41-P43-P44 | Q42: =Q41-Q43-Q44 | R42: =R41-R43-R44 | S42: =S41-S43-S44 | T42: =S42-R42 | U42: =S42-Q42 | V42: =IF(Q42=0,"***",U42/Q42) | W42: =IF(I42=0,"***",P42/I42) | X42: =IF(J42=0,"***",Q42/J42) | Y42: =IF(K42=0,"***",R42/K42) | Z42: =IF(L42=0,"***",S42/L42) | AA42: =IF(Y42="***","***",Z42-X42) | AB42: =IF(Z42="***","***",Z42-X42)
H43: 荷役 | I43: =BACKDATA上期!CO43+下期!I43 | J43: =BACKDATA上期!CP43+下期!J43 | K43: =BACKDATA上期!CQ43+下期!K43 | L43: =BACKDATA上期!CR43+下期!L43 | M43: =L43-K43 | N43: =L43-J43 | O43: =IF(J43=0,"***",N43/J43) | P43: =BACKDATA上期!CV43+下期!P43 | Q43: =BACKDATA上期!CW43+下期!Q43 | R43: =BACKDATA上期!CX43+下期!R43 | S43: =BACKDATA上期!CY43+下期!S43 | T43: =S43-R43 | U43: =S43-Q43 | V43: =IF(Q43=0,"***",U43/Q43) | W43: =IF(I43=0,"***",P43/I43) | X43: =IF(J43=0,"***",Q43/J43) | Y43: =IF(K43=0,"***",R43/K43) | Z43: =IF(L43=0,"***",S43/L43) | AA43: =IF(Y43="***","***",Z43-X43) | AB43: =IF(Z43="***","***",Z43-X43)
H44: 機械 | I44: =BACKDATA上期!CO44+下期!I44 | J44: =BACKDATA上期!CP44+下期!J44 | K44: =BACKDATA上期!CQ44+下期!K44 | L44: =BACKDATA上期!CR44+下期!L44 | M44: =L44-K44 | N44: =L44-J44 | O44: =IF(J44=0,"***",N44/J44) | P44: =BACKDATA上期!CV44+下期!P44 | Q44: =BACKDATA上期!CW44+下期!Q44 | R44: =BACKDATA上期!CX44+下期!R44 | S44: =BACKDATA上期!CY44+下期!S44 | T44: =S44-R44 | U44: =S44-Q44 | V44: =IF(Q44=0,"***",U44/Q44) | W44: =IF(I44=0,"***",P44/I44) | X44: =IF(J44=0,"***",Q44/J44) | Y44: =IF(K44=0,"***",R44/K44) | Z44: =IF(L44=0,"***",S44/L44) | AA44: =IF(Y44="***","***",Z44-X44) | AB44: =IF(Z44="***","***",Z44-X44)
D45: 合計 | I45: =I41+I36 | J45: =J41+J36 | K45: =K41+K36 | L45: =L41+L36 | M45: =L45-K45 | N45: =L45-J45 | O45: =IF(J45=0,"***",N45/J45) | P45: =P41+P36 | Q45: =Q41+Q36 | R45: =R41+R36 | S45: =S41+S36 | T45: =S45-R45 | U45: =S45-Q45 | V45: =IF(Q45=0,"***",U45/Q45) | W45: =IF(I45=0,"***",P45/I45) | X45: =IF(J45=0,"***",Q45/J45) | Y45: =IF(K45=0,"***",R45/K45) | Z45: =IF(L45=0,"***",S45/L45) | AA45: =IF(Y45="***","***",Z45-X45) | AB45: =IF(Z45="***","***",Z45-X45)
H46: 機械以外 | I46: =I45-I47 | J46: =J45-J47 | K46: =K45-K47 | L46: =L45-L47 | M46: =L46-K46 | N46: =L46-J46 | O46: =IF(J46=0,"***",N46/J46) | P46: =P45-P47 | Q46: =Q45-Q47 | R46: =R45-R47 | S46: =S45-S47 | T46: =S46-R46 | U46: =S46-Q46 | V46: =IF(Q46=0,"***",U46/Q46) | W46: =IF(I46=0,"***",P46/I46) | X46: =IF(J46=0,"***",Q46/J46) | Y46: =IF(K46=0,"***",R46/K46) | Z46: =IF(L46=0,"***",S46/L46) | AA46: =IF(Y46="***","***",Z46-X46) | AB46: =IF(Z46="***","***",Z46-X46)
H47: 機械 | I47: =I38+I44 | J47: =J38+J44 | K47: =K38+K44 | L47: =L38+L44 | M47: =L47-K47 | N47: =L47-J47 | O47: =IF(J47=0,"***",N47/J47) | P47: =P38+P44 | Q47: =Q38+Q44 | R47: =R38+R44 | S47: =S38+S44 | T47: =S47-R47 | U47: =S47-Q47 | V47: =IF(Q47=0,"***",U47/Q47) | W47: =IF(I47=0,"***",P47/I47) | X47: =IF(J47=0,"***",Q47/J47) | Y47: =IF(K47=0,"***",R47/K47) | Z47: =IF(L47=0,"***",S47/L47) | AA47: =IF(Y47="***","***",Z47-X47) | AB47: =IF(Z47="***","***",Z47-X47)
H48: 自治体 | I48: =I39 | J48: =J39 | K48: =K39 | L48: =L39 | M48: =L48-K48 | N48: =L48-J48 | O48: =IF(J48=0,"***",N48/J48) | P48: =P39 | Q48: =Q39 | R48: =R39 | S48: =S39 | T48: =S48-R48 | U48: =S48-Q48 | V48: =IF(Q48=0,"***",U48/Q48) | W48: =IF(I48=0,"***",P48/I48) | X48: =IF(J48=0,"***",Q48/J48) | Y48: =IF(K48=0,"***",R48/K48) | Z48: =IF(L48=0,"***",S48/L48) | AA48: =IF(Y48="***","***",Z48-X48) | AB48: =IF(Z48="***","***",Z48-X48)
H49: 海外 | I49: =I40 | J49: =J40 | K49: =K40 | L49: =L40 | M49: =L49-K49 | N49: =L49-J49 | O49: =IF(J49=0,"***",N49/J49) | P49: =P40 | Q49: =Q40 | R49: =R40 | S49: =S40 | T49: =S49-R49 | U49: =S49-Q49 | V49: =IF(Q49=0,"***",U49/Q49) | W49: =IF(I49=0,"***",P49/I49) | X49: =IF(J49=0,"***",Q49/J49) | Y49: =IF(K49=0,"***",R49/K49) | Z49: =IF(L49=0,"***",S49/L49) | AA49: =IF(Y49="***","***",Z49-X49) | AB49: =IF(Z49="***","***",Z49-X49)
D50: キョウワ（税抜） | I50: =BACKDATA上期!CO50+下期!I50 | J50: =BACKDATA上期!CP50+下期!J50 | K50: =BACKDATA上期!CQ50+下期!K50 | L50: =BACKDATA上期!CR50+下期!L50 | M50: =L50-K50 | N50: =L50-J50 | O50: =IF(J50=0,"***",N50/J50) | P50: =BACKDATA上期!CV50+下期!P50 | Q50: =BACKDATA上期!CW50+下期!Q50 | R50: =BACKDATA上期!CX50+下期!R50 | S50: =BACKDATA上期!CY50+下期!S50 | T50: =S50-R50 | U50: =S50-Q50 | V50: =IF(Q50=0,"***",U50/Q50) | W50: =IF(I50=0,"***",P50/I50) | X50: =IF(J50=0,"***",Q50/J50) | Y50: =IF(K50=0,"***",R50/K50) | Z50: =IF(L50=0,"***",S50/L50) | AA50: =IF(Y50="***","***",Z50-X50) | AB50: =IF(Z50="***","***",Z50-X50)

Sheet BACKDATA7月
D1: 1．単月
I3: 2024年7月売上実績 | J3: 2025年7月売上実績 | K3: 2026年7月売上計画 | L3: 2026年7月売上実績 | P3: 2024年7月粗利益実績 | Q3: 2025年7月粗利益実績 | R3: 2026年7月粗利益計画 | S3: 2026年7月粗利益実績 | W3: 2024年7月粗利益率実績 | X3: 2025年7月粗利益率実績 | Y3: 2026年7月粗利益率計画 | Z3: 2026年7月粗利益率実績 | AC3: 作成根拠
M4: 計画比 | N4: 前期比 | O4: 年率 | T4: 計画比 | U4: 前期比 | V4: 年率 | AA4: 計画比 | AB4: 前期比
F5: 石見営業所 | I5: 71106.191 | J5: 71282.087 | K5: 75040 | L5: 75113.115 | M5: =L5-K5 | N5: =L5-J5 | O5: =IF(J5=0,"***",N5/J5) | P5: 18595.809 | Q5: 19835.594 | R5: 19880 | S5: 22162.975 | T5: =S5-R5 | U5: =S5-Q5 | V5: =IF(Q5=0,"***",U5/Q5) | W5: =IF(I5=0,"***",P5/I5) | X5: =IF(J5=0,"***",Q5/J5) | Y5: =IF(K5=0,"***",R5/K5) | Z5: =IF(L5=0,"***",S5/L5) | AA5: =IF(Y5="***","***",Z5-X5) | AB5: =IF(Z5="***","***",Z5-X5)
G6: 営業 | I6: =I5-I9 | J6: =J5-J9 | K6: =K5-K9 | L6: =L5-L9 | M6: =L6-K6 | N6: =L6-J6 | O6: =IF(J6=0,"***",N6/J6) | P6: =P5-P9 | Q6: =Q5-Q9 | R6: =R5-R9 | S6: =S5-S9 | T6: =S6-R6 | U6: =S6-Q6 | V6: =IF(Q6=0,"***",U6/Q6) | W6: =IF(I6=0,"***",P6/I6) | X6: =IF(J6=0,"***",Q6/J6) | Y6: =IF(K6=0,"***",R6/K6) | Z6: =IF(L6=0,"***",S6/L6) | AA6: =IF(Y6="***","***",Z6-X6) | AB6: =IF(Z6="***","***",Z6-X6)
H7: 包装資材 | I7: =I6-I8 | J7: =J6-J8 | K7: =K6-K8 | L7: =L6-L8 | M7: =L7-K7 | N7: =L7-J7 | O7: =IF(J7=0,"***",N7/J7) | P7: =P6-P8 | Q7: =Q6-Q8 | R7: =R6-R8 | S7: =S6-S8 | T7: =S7-R7 | U7: =S7-Q7 | V7: =IF(Q7=0,"***",U7/Q7) | W7: =IF(I7=0,"***",P7/I7) | X7: =IF(J7=0,"***",Q7/J7) | Y7: =IF(K7=0,"***",R7/K7) | Z7: =IF(L7=0,"***",S7/L7) | AA7: =IF(Y7="***","***",Z7-X7) | AB7: =IF(Z7="***","***",Z7-X7)
H8: 機械 | I8: 7717.633 | J8: 1450.405 | K8: 4000 | L8: 1103.275 | M8: =L8-K8 | N8: =L8-J8 | O8: =IF(J8=0,"***",N8/J8) | P8: 1664.71 | Q8: 433.454 | R8: 640 | S8: 259.615 | T8: =S8-R8 | U8: =S8-Q8 | V8: =IF(Q8=0,"***",U8/Q8) | W8: =IF(I8=0,"***",P8/I8) | X8: =IF(J8=0,"***",Q8/J8) | Y8: =IF(K8=0,"***",R8/K8) | Z8: =IF(L8=0,"***",S8/L8) | AA8: =IF(Y8="***","***",Z8-X8) | AB8: =IF(Z8="***","***",Z8-X8)
G9: 自治体 | I9: 15.3 | J9: 16.8 | K9: 1340 | L9: 0 | M9: =L9-K9 | N9: =L9-J9 | O9: =IF(J9=0,"***",N9/J9) | P9: 2.5 | Q9: 3.8 | R9: 210 | S9: 0 | T9: =S9-R9 | U9: =S9-Q9 | V9: =IF(Q9=0,"***",U9/Q9) | W9: =IF(I9=0,"***",P9/I9) | X9: =IF(J9=0,"***",Q9/J9) | Y9: =IF(K9=0,"***",R9/K9) | Z9: =IF(L9=0,"***",S9/L9) | AA9: =IF(Y9="***","***",Z9-X9) | AB9: =IF(Z9="***","***",Z9-X9)
F10: 下関営業所 | I10: 45316.337 | J10: 46644.164 | K10: 47000 | L10: 50561.591 | M10: =L10-K10 | N10: =L10-J10 | O10: =IF(J10=0,"***",N10/J10) | P10: 9137.833 | Q10: 9710.074 | R10: 9750 | S10: 10623.712 | T10: =S10-R10 | U10: =S10-Q10 | V10: =IF(Q10=0,"***",U10/Q10) | W10: =IF(I10=0,"***",P10/I10) | X10: =IF(J10=0,"***",Q10/J10) | Y10: =IF(K10=0,"***",R10/K10) | Z10: =IF(L10=0,"***",S10/L10) | AA10: =IF(Y10="***","***",Z10-X10) | AB10: =IF(Z10="***","***",Z10-X10)
G11: 営業 | I11: =I10-I15-I14 | J11: =J10-J15-J14 | K11: =K10-K15-K14 | L11: =L10-L15-L14 | M11: =L11-K11 | N11: =L11-J11 | O11: =IF(J11=0,"***",N11/J11) | P11: =P10-P15-P14 | Q11: =Q10-Q15-Q14 | R11: =R10-R15-R14 | S11: =S10-S15-S14 | T11: =S11-R11 | U11: =S11-Q11 | V11: =IF(Q11=0,"***",U11/Q11) | W11: =IF(I11=0,"***",P11/I11) | X11: =IF(J11=0,"***",Q11/J11) | Y11: =IF(K11=0,"***",R11/K11) | Z11: =IF(L11=0,"***",S11/L11) | AA11: =IF(Y11="***","***",Z11-X11) | AB11: =IF(Z11="***","***",Z11-X11)
H12: 包装資材 | I12: =I11-I13 | J12: =J11-J13 | K12: =K11-K13 | L12: =L11-L13 | M12: =L12-K12 | N12: =L12-J12 | O12: =IF(J12=0,"***",N12/J12) | P12: =P11-P13 | Q12: =Q11-Q13 | R12: =R11-R13 | S12: =S11-S13 | T12: =S12-R12 | U12: =S12-Q12 | V12: =IF(Q12=0,"***",U12/Q12) | W12: =IF(I12=0,"***",P12/I12) | X12: =IF(J12=0,"***",Q12/J12) | Y12: =IF(K12=0,"***",R12/K12) | Z12: =IF(L12=0,"***",S12/L12) | AA12: =IF(Y12="***","***",Z12-X12) | AB12: =IF(Z12="***","***",Z12-X12)
H13: 機械 | I13: 442 | J13: 519 | K13: 300 | L13: 1181.37 | M13: =L13-K13 | N13: =L13-J13 | O13: =IF(J13=0,"***",N13/J13) | P13: 72 | Q13: 172 | R13: 50 | S13: 171.443 | T13: =S13-R13 | U13: =S13-Q13 | V13: =IF(Q13=0,"***",U13/Q13) | W13: =IF(I13=0,"***",P13/I13) | X13: =IF(J13=0,"***",Q13/J13) | Y13: =IF(K13=0,"***",R13/K13) | Z13: =IF(L13=0,"***",S13/L13) | AA13: =IF(Y13="***","***",Z13-X13) | AB13: =IF(Z13="***","***",Z13-X13)
G14: 自治体 | I14: 0 | J14: 107.5 | K14: 0 | L14: 0 | M14: =L14-K14 | N14: =L14-J14 | O14: =IF(J14=0,"***",N14/J14) | P14: 0 | Q14: 3.6 | R14: 0 | S14: 0 | T14: =S14-R14 | U14: =S14-Q14 | V14: =IF(Q14=0,"***",U14/Q14) | W14: =IF(I14=0,"***",P14/I14) | X14: =IF(J14=0,"***",Q14/J14) | Y14: =IF(K14=0,"***",R14/K14) | Z14: =IF(L14=0,"***",S14/L14)
G15: 海外 | I15: 0 | J15: 0 | K15: 0 | L15: 0 | M15: =L15-K15 | N15: =L15-J15 | O15: =IF(J15=0,"***",N15/J15) | P15: 0 | Q15: 0 | R15: 0 | S15: 0 | T15: =S15-R15 | U15: =S15-Q15 | V15: =IF(Q15=0,"***",U15/Q15) | W15: =IF(I15=0,"***",P15/I15) | X15: =IF(J15=0,"***",Q15/J15) | Y15: =IF(K15=0,"***",R15/K15) | Z15: =IF(L15=0,"***",S15/L15) | AA15: =IF(Y15="***","***",Z15-X15) | AB15: =IF(Z15="***","***",Z15-X15)
F16: 松江営業所 | I16: 27604.262 | J16: 29162.289 | K16: 31450 | L16: 39461.68 | M16: =L16-K16 | N16: =L16-J16 | O16: =IF(J16=0,"***",N16/J16) | P16: 6506.135 | Q16: 7508.645 | R16: 7770 | S16: 10096.258 | T16: =S16-R16 | U16: =S16-Q16 | V16: =IF(Q16=0,"***",U16/Q16) | W16: =IF(I16=0,"***",P16/I16) | X16: =IF(J16=0,"***",Q16/J16) | Y16: =IF(K16=0,"***",R16/K16) | Z16: =IF(L16=0,"***",S16/L16) | AA16: =IF(Y16="***","***",Z16-X16) | AB16: =IF(Z16="***","***",Z16-X16)
G17: 営業 | I17: =I16-I20 | J17: =J16-J20 | K17: =K16-K20 | L17: =L16-L20 | M17: =L17-K17 | N17: =L17-J17 | O17: =IF(J17=0,"***",N17/J17) | P17: =P16-P20 | Q17: =Q16-Q20 | R17: =R16-R20 | S17: =S16-S20 | T17: =S17-R17 | U17: =S17-Q17 | V17: =IF(Q17=0,"***",U17/Q17) | W17: =IF(I17=0,"***",P17/I17) | X17: =IF(J17=0,"***",Q17/J17) | Y17: =IF(K17=0,"***",R17/K17) | Z17: =IF(L17=0,"***",S17/L17) | AA17: =IF(Y17="***","***",Z17-X17) | AB17: =IF(Z17="***","***",Z17-X17)
H18: 包装資材 | I18: =I17-I19 | J18: =J17-J19 | K18: =K17-K19 | L18: =L17-L19 | M18: =L18-K18 | N18: =L18-J18 | O18: =IF(J18=0,"***",N18/J18) | P18: =P17-P19 | Q18: =Q17-Q19 | R18: =R17-R19 | S18: =S17-S19 | T18: =S18-R18 | U18: =S18-Q18 | V18: =IF(Q18=0,"***",U18/Q18) | W18: =IF(I18=0,"***",P18/I18) | X18: =IF(J18=0,"***",Q18/J18) | Y18: =IF(K18=0,"***",R18/K18) | Z18: =IF(L18=0,"***",S18/L18) | AA18: =IF(Y18="***","***",Z18-X18) | AB18: =IF(Z18="***","***",Z18-X18)
H19: 機械 | I19: 165 | J19: 476 | K19: 1400 | L19: 892.11 | M19: =L19-K19 | N19: =L19-J19 | O19: =IF(J19=0,"***",N19/J19) | P19: 27 | Q19: 60 | R19: 210 | S19: 212.242 | T19: =S19-R19 | U19: =S19-Q19 | V19: =IF(Q19=0,"***",U19/Q19) | W19: =IF(I19=0,"***",P19/I19) | X19: =IF(J19=0,"***",Q19/J19) | Y19: =IF(K19=0,"***",R19/K19) | Z19: =IF(L19=0,"***",S19/L19) | AA19: =IF(Y19="***","***",Z19-X19) | AB19: =IF(Z19="***","***",Z19-X19)
G20: 自治体 | I20: 0 | J20: 0 | K20: 0 | L20: 0 | M20: =L20-K20 | N20: =L20-J20 | O20: =IF(J20=0,"***",N20/J20) | P20: 0 | Q20: 0 | R20: 0 | S20: 0 | T20: =S20-R20 | U20: =S20-Q20 | V20: =IF(Q20=0,"***",U20/Q20) | W20: =IF(I20=0,"***",P20/I20) | X20: =IF(J20=0,"***",Q20/J20) | Y20: =IF(K20=0,"***",R20/K20) | Z20: =IF(L20=0,"***",S20/L20) | AA20: =IF(Y20="***","***",Z20-X20) | AB20: =IF(Z20="***","***",Z20-X20)
F21: 広域営業部 | I21: 38324.3 | J21: 42304.502 | K21: 45930 | L21: 49015.626 | M21: =L21-K21 | N21: =L21-J21 | O21: =IF(J21=0,"***",N21/J21) | P21: 5340.523 | Q21: 6644.144 | R21: 7020 | S21: 9481.314 | T21: =S21-R21 | U21: =S21-Q21 | V21: =IF(Q21=0,"***",U21/Q21) | W21: =IF(I21=0,"***",P21/I21) | X21: =IF(J21=0,"***",Q21/J21) | Y21: =IF(K21=0,"***",R21/K21) | Z21: =IF(L21=0,"***",S21/L21) | AA21: =IF(Y21="***","***",Z21-X21) | AB21: =IF(Z21="***","***",Z21-X21)
H22: 包装資材 | I22: =I21-I23 | J22: =J21-J23 | K22: =K21-K23 | L22: =L21-L23 | M22: =L22-K22 | N22: =L22-J22 | O22: =IF(J22=0,"***",N22/J22) | P22: =P21-P23 | Q22: =Q21-Q23 | R22: =R21-R23 | S22: =S21-S23 | T22: =S22-R22 | U22: =S22-Q22 | V22: =IF(Q22=0,"***",U22/Q22) | W22: =IF(I22=0,"***",P22/I22) | X22: =IF(J22=0,"***",Q22/J22) | Y22: =IF(K22=0,"***",R22/K22) | Z22: =IF(L22=0,"***",S22/L22) | AA22: =IF(Y22="***","***",Z22-X22) | AB22: =IF(Z22="***","***",Z22-X22)
H23: 機械 | I23: 92 | J23: 95 | K23: 1000 | L23: 184.66 | M23: =L23-K23 | N23: =L23-J23 | O23: =IF(J23=0,"***",N23/J23) | P23: 12 | Q23: 17 | R23: 110 | S23: 27.21 | T23: =S23-R23 | U23: =S23-Q23 | V23: =IF(Q23=0,"***",U23/Q23) | W23: =IF(I23=0,"***",P23/I23) | X23: =IF(J23=0,"***",Q23/J23) | Y23: =IF(K23=0,"***",R23/K23) | Z23: =IF(L23=0,"***",S23/L23) | AA23: =IF(Y23="***","***",Z23-X23) | AB23: =IF(Z23="***","***",Z23-X23)
G24: リンガーハット | I24: 29746.479 | J24: 30161.422 | K24: 30057.686 | L24: 35234.444 | M24: =L24-K24 | N24: =L24-J24 | O24: =IF(J24=0,"***",N24/J24) | P24: 3940.045 | Q24: 4536.108 | R24: 4387.092 | S24: 7259.191 | T24: =S24-R24 | U24: =S24-Q24 | V24: =IF(Q24=0,"***",U24/Q24) | W24: =IF(I24=0,"***",P24/I24) | X24: =IF(J24=0,"***",Q24/J24) | Y24: =IF(K24=0,"***",R24/K24) | Z24: =IF(L24=0,"***",S24/L24) | AA24: =IF(Y24="***","***",Z24-X24) | AB24: =IF(Z24="***","***",Z24-X24)
H25: 包装資材 | I25: =I24-I26 | J25: =J24-J26 | K25: =K24-K26 | L25: =L24-L26 | M25: =L25-K25 | N25: =L25-J25 | O25: =IF(J25=0,"***",N25/J25) | P25: =P24-P26 | Q25: =Q24-Q26 | R25: =R24-R26 | S25: =S24-S26 | T25: =S25-R25 | U25: =S25-Q25 | V25: =IF(Q25=0,"***",U25/Q25) | W25: =IF(I25=0,"***",P25/I25) | X25: =IF(J25=0,"***",Q25/J25) | Y25: =IF(K25=0,"***",R25/K25) | Z25: =IF(L25=0,"***",S25/L25) | AA25: =IF(Y25="***","***",Z25-X25) | AB25: =IF(Z25="***","***",Z25-X25)
H26: 機械 | I26: 46 | J26: 77 | K26: 69.25 | L26: 46.2 | M26: =L26-K26 | N26: =L26-J26 | O26: =IF(J26=0,"***",N26/J26) | P26: 5 | Q26: 45 | R26: 35 | S26: 5 | T26: =S26-R26 | U26: =S26-Q26 | V26: =IF(Q26=0,"***",U26/Q26) | W26: =IF(I26=0,"***",P26/I26) | X26: =IF(J26=0,"***",Q26/J26) | Y26: =IF(K26=0,"***",R26/K26) | Z26: =IF(L26=0,"***",S26/L26) | AA26: =IF(Y26="***","***",Z26-X26) | AB26: =IF(Z26="***","***",Z26-X26)
G27: リンガーハット以外 | I27: =I21-I24 | J27: =J21-J24 | K27: =K21-K24 | L27: =L21-L24 | M27: =L27-K27 | N27: =L27-J27 | O27: =IF(J27=0,"***",N27/J27) | P27: =P21-P24 | Q27: =Q21-Q24 | R27: =R21-R24 | S27: =S21-S24 | T27: =S27-R27 | U27: =S27-Q27 | V27: =IF(Q27=0,"***",U27/Q27) | W27: =IF(I27=0,"***",P27/I27) | X27: =IF(J27=0,"***",Q27/J27) | Y27: =IF(K27=0,"***",R27/K27) | Z27: =IF(L27=0,"***",S27/L27) | AA27: =IF(Y27="***","***",Z27-X27) | AB27: =IF(Z27="***","***",Z27-X27)
H28: 包装資材 | I28: =I27-I29 | J28: =J27-J29 | K28: =K27-K29 | L28: =L27-L29 | M28: =L28-K28 | N28: =L28-J28 | O28: =IF(J28=0,"***",N28/J28) | P28: =P27-P29 | Q28: =Q27-Q29 | R28: =R27-R29 | S28: =S27-S29 | T28: =S28-R28 | U28: =S28-Q28 | V28: =IF(Q28=0,"***",U28/Q28) | W28: =IF(I28=0,"***",P28/I28) | X28: =IF(J28=0,"***",Q28/J28) | Y28: =IF(K28=0,"***",R28/K28) | Z28: =IF(L28=0,"***",S28/L28) | AA28: =IF(Y28="***","***",Z28-X28) | AB28: =IF(Z28="***","***",Z28-X28)
H29: 機械 | I29: =I23-I26 | J29: =J23-J26 | K29: =K23-K26 | L29: =L23-L26 | M29: =L29-K29 | N29: =L29-J29 | O29: =IF(J29=0,"***",N29/J29) | P29: =P23-P26 | Q29: =Q23-Q26 | R29: =R23-R26 | S29: =S23-S26 | T29: =S29-R29 | U29: =S29-Q29 | V29: =IF(Q29=0,"***",U29/Q29) | W29: =IF(I29=0,"***",P29/I29) | X29: =IF(J29=0,"***",Q29/J29) | Y29: =IF(K29=0,"***",R29/K29) | Z29: =IF(L29=0,"***",S29/L29) | AA29: =IF(Y29="***","***",Z29-X29) | AB29: =IF(Z29="***","***",Z29-X29)
F30: 境港営業所 | I30: 42847.416 | J30: 51531.491 | K30: 56000 | L30: 57288.249 | M30: =L30-K30 | N30: =L30-J30 | O30: =IF(J30=0,"***",N30/J30) | P30: 7855.741 | Q30: 10585.565 | R30: 11390 | S30: 11130.032 | T30: =S30-R30 | U30: =S30-Q30 | V30: =IF(Q30=0,"***",U30/Q30) | W30: =IF(I30=0,"***",P30/I30) | X30: =IF(J30=0,"***",Q30/J30) | Y30: =IF(K30=0,"***",R30/K30) | Z30: =IF(L30=0,"***",S30/L30) | AA30: =IF(Y30="***","***",Z30-X30) | AB30: =IF(Z30="***","***",Z30-X30)
G31: 営業 | I31: =I30-I35-I34 | J31: =J30-J35-J34 | K31: =K30-K35-K34 | L31: =L30-L35-L34 | M31: =L31-K31 | N31: =L31-J31 | O31: =IF(J31=0,"***",N31/J31) | P31: =P30-P35-P34 | Q31: =Q30-Q35-Q34 | R31: =R30-R35-R34 | S31: =S30-S35-S34 | T31: =S31-R31 | U31: =S31-Q31 | V31: =IF(Q31=0,"***",U31/Q31) | W31: =IF(I31=0,"***",P31/I31) | X31: =IF(J31=0,"***",Q31/J31) | Y31: =IF(K31=0,"***",R31/K31) | Z31: =IF(L31=0,"***",S31/L31) | AA31: =IF(Y31="***","***",Z31-X31) | AB31: =IF(Z31="***","***",Z31-X31)
H32: 包装資材 | I32: =I31-I33 | J32: =J31-J33 | K32: =K31-K33 | L32: =L31-L33 | M32: =L32-K32 | N32: =L32-J32 | O32: =IF(J32=0,"***",N32/J32) | P32: =P31-P33 | Q32: =Q31-Q33 | R32: =R31-R33 | S32: =S31-S33 | T32: =S32-R32 | U32: =S32-Q32 | V32: =IF(Q32=0,"***",U32/Q32) | W32: =IF(I32=0,"***",P32/I32) | X32: =IF(J32=0,"***",Q32/J32) | Y32: =IF(K32=0,"***",R32/K32) | Z32: =IF(L32=0,"***",S32/L32) | AA32: =IF(Y32="***","***",Z32-X32) | AB32: =IF(Z32="***","***",Z32-X32)
H33: 機械 | I33: 2422 | J33: 7489 | K33: 8100 | L33: 3988.655 | M33: =L33-K33 | N33: =L33-J33 | O33: =IF(J33=0,"***",N33/J33) | P33: 749 | Q33: 2041 | R33: 1800 | S33: 779.1 | T33: =S33-R33 | U33: =S33-Q33 | V33: =IF(Q33=0,"***",U33/Q33) | W33: =IF(I33=0,"***",P33/I33) | X33: =IF(J33=0,"***",Q33/J33) | Y33: =IF(K33=0,"***",R33/K33) | Z33: =IF(L33=0,"***",S33/L33) | AA33: =IF(Y33="***","***",Z33-X33) | AB33: =IF(Z33="***","***",Z33-X33)
G34: 自治体 | I34: 0 | J34: 0 | K34: 0 | L34: 0 | M34: =L34-K34 | N34: =L34-J34 | O34: =IF(J34=0,"***",N34/J34) | P34: 0 | Q34: 0 | R34: 0 | S34: 0 | T34: =S34-R34 | U34: =S34-Q34 | V34: =IF(Q34=0,"***",U34/Q34) | W34: =IF(I34=0,"***",P34/I34) | X34: =IF(J34=0,"***",Q34/J34) | Y34: =IF(K34=0,"***",R34/K34) | Z34: =IF(L34=0,"***",S34/L34) | AA34: =IF(Y34="***","***",Z34-X34) | AB34: =IF(Z34="***","***",Z34-X34)
G35: 海外 | I35: 1452.4 | J35: 604.22 | K35: 1390 | L35: 130.06 | M35: =L35-K35 | N35: =L35-J35 | O35: =IF(J35=0,"***",N35/J35) | P35: 218.502 | Q35: 117.704 | R35: 230 | S35: 29.11 | T35: =S35-R35 | U35: =S35-Q35 | V35: =IF(Q35=0,"***",U35/Q35) | W35: =IF(I35=0,"***",P35/I35) | X35: =IF(J35=0,"***",Q35/J35) | Y35: =IF(K35=0,"***",R35/K35) | Z35: =IF(L35=0,"***",S35/L35) | AA35: =IF(Y35="***","***",Z35-X35) | AB35: =IF(Z35="***","***",Z35-X35)
E36: 営業部門合計 | I36: =I30+I21+I16+I10+I5 | J36: =J30+J21+J16+J10+J5 | K36: =K30+K21+K16+K10+K5 | L36: =L30+L21+L16+L10+L5 | M36: =L36-K36 | N36: =L36-J36 | O36: =IF(J36=0,"***",N36/J36) | P36: =P30+P21+P16+P10+P5 | Q36: =Q30+Q21+Q16+Q10+Q5 | R36: =R30+R21+R16+R10+R5 | S36: =S30+S21+S16+S10+S5 | T36: =S36-R36 | U36: =S36-Q36 | V36: =IF(Q36=0,"***",U36/Q36) | W36: =IF(I36=0,"***",P36/I36) | X36: =IF(J36=0,"***",Q36/J36) | Y36: =IF(K36=0,"***",R36/K36) | Z36: =IF(L36=0,"***",S36/L36) | AA36: =IF(Y36="***","***",Z36-X36) | AB36: =IF(Z36="***","***",Z36-X36)
H37: 機械以外 | I37: =I36-I38-I39-I40 | J37: =J36-J38-J39-J40 | K37: =K36-K38-K39-K40 | L37: =L36-L38-L39-L40 | M37: =L37-K37 | N37: =L37-J37 | O37: =IF(J37=0,"***",N37/J37) | P37: =P36-P38-P39-P40 | Q37: =Q36-Q38-Q39-Q40 | R37: =R36-R38-R39-R40 | S37: =S36-S38-S39-S40 | T37: =S37-R37 | U37: =S37-Q37 | V37: =IF(Q37=0,"***",U37/Q37) | W37: =IF(I37=0,"***",P37/I37) | X37: =IF(J37=0,"***",Q37/J37) | Y37: =IF(K37=0,"***",R37/K37) | Z37: =IF(L37=0,"***",S37/L37) | AA37: =IF(Y37="***","***",Z37-X37) | AB37: =IF(Z37="***","***",Z37-X37)
H38: 機械 | I38: =I33+I23+I19+I13+I8 | J38: =J33+J23+J19+J13+J8 | K38: =K33+K23+K19+K13+K8 | L38: =L33+L23+L19+L13+L8 | M38: =L38-K38 | N38: =L38-J38 | O38: =IF(J38=0,"***",N38/J38) | P38: =P33+P23+P19+P13+P8 | Q38: =Q33+Q23+Q19+Q13+Q8 | R38: =R33+R23+R19+R13+R8 | S38: =S33+S23+S19+S13+S8 | T38: =S38-R38 | U38: =S38-Q38 | V38: =IF(Q38=0,"***",U38/Q38) | W38: =IF(I38=0,"***",P38/I38) | X38: =IF(J38=0,"***",Q38/J38) | Y38: =IF(K38=0,"***",R38/K38) | Z38: =IF(L38=0,"***",S38/L38) | AA38: =IF(Y38="***","***",Z38-X38) | AB38: =IF(Z38="***","***",Z38-X38)
H39: 自治体 | I39: =I34+I20+I14+I9 | J39: =J34+J20+J14+J9 | K39: =K34+K20+K14+K9 | L39: =L34+L20+L14+L9 | M39: =L39-K39 | N39: =L39-J39 | O39: =IF(J39=0,"***",N39/J39) | P39: =P34+P20+P14+P9 | Q39: =Q34+Q20+Q14+Q9 | R39: =R34+R20+R14+R9 | S39: =S34+S20+S14+S9 | T39: =S39-R39 | U39: =S39-Q39 | V39: =IF(Q39=0,"***",U39/Q39) | W39: =IF(I39=0,"***",P39/I39) | X39: =IF(J39=0,"***",Q39/J39) | Y39: =IF(K39=0,"***",R39/K39) | Z39: =IF(L39=0,"***",S39/L39) | AA39: =IF(Y39="***","***",Z39-X39) | AB39: =IF(Z39="***","***",Z39-X39)
H40: 海外 | I40: =I35+I15 | J40: =J35+J15 | K40: =K35+K15 | L40: =L35+L15 | M40: =L40-K40 | N40: =L40-J40 | O40: =IF(J40=0,"***",N40/J40) | P40: =P35+P15 | Q40: =Q35+Q15 | R40: =R35+R15 | S40: =S35+S15 | T40: =S40-R40 | U40: =S40-Q40 | V40: =IF(Q40=0,"***",U40/Q40) | W40: =IF(I40=0,"***",P40/I40) | X40: =IF(J40=0,"***",Q40/J40) | Y40: =IF(K40=0,"***",R40/K40) | Z40: =IF(L40=0,"***",S40/L40) | AA40: =IF(Y40="***","***",Z40-X40) | AB40: =IF(Z40="***","***",Z40-X40)
E41: 水産部 | I41: 24207.034 | J41: 30541.112 | K41: 33380 | L41: 34074.957 | M41: =L41-K41 | N41: =L41-J41 | O41: =IF(J41=0,"***",N41/J41) | P41: 6086.468 | Q41: 9851.241 | R41: 10330 | S41: 9682.956 | T41: =S41-R41 | U41: =S41-Q41 | V41: =IF(Q41=0,"***",U41/Q41) | W41: =IF(I41=0,"***",P41/I41) | X41: =IF(J41=0,"***",Q41/J41) | Y41: =IF(K41=0,"***",R41/K41) | Z41: =IF(L41=0,"***",S41/L41) | AA41: =IF(Y41="***","***",Z41-X41) | AB41: =IF(Z41="***","***",Z41-X41)
H42: 包装資材 | I42: =I41-I43-I44 | J42: =J41-J43-J44 | K42: =K41-K43-K44 | L42: =L41-L43-L44 | M42: =L42-K42 | N42: =L42-J42 | O42: =IF(J42=0,"***",N42/J42) | P42: =P41-P43-P44 | Q42: =Q41-Q43-Q44 | R42: =R41-R43-R44 | S42: =S41-S43-S44 | T42: =S42-R42 | U42: =S42-Q42 | V42: =IF(Q42=0,"***",U42/Q42) | W42: =IF(I42=0,"***",P42/I42) | X42: =IF(J42=0,"***",Q42/J42) | Y42: =IF(K42=0,"***",R42/K42) | Z42: =IF(L42=0,"***",S42/L42) | AA42: =IF(Y42="***","***",Z42-X42) | AB42: =IF(Z42="***","***",Z42-X42)
H43: 荷役 | I43: 4384.316 | J43: 6674.31 | K43: 8260 | L43: 7054.138 | M43: =L43-K43 | N43: =L43-J43 | O43: =IF(J43=0,"***",N43/J43) | P43: 2682.293 | Q43: 4250.887 | R43: 5060 | S43: 4182.469 | T43: =S43-R43 | U43: =S43-Q43 | V43: =IF(Q43=0,"***",U43/Q43) | W43: =IF(I43=0,"***",P43/I43) | X43: =IF(J43=0,"***",Q43/J43) | Y43: =IF(K43=0,"***",R43/K43) | Z43: =IF(L43=0,"***",S43/L43)
H44: 機械 | I44: 2222.56 | J44: 76.3 | K44: 390 | L44: 242.24 | M44: =L44-K44 | N44: =L44-J44 | O44: =IF(J44=0,"***",N44/J44) | P44: 440.665 | Q44: 24.7 | R44: 80 | S44: 39.5 | T44: =S44-R44 | U44: =S44-Q44 | V44: =IF(Q44=0,"***",U44/Q44) | W44: =IF(I44=0,"***",P44/I44) | X44: =IF(J44=0,"***",Q44/J44) | Y44: =IF(K44=0,"***",R44/K44) | Z44: =IF(L44=0,"***",S44/L44) | AA44: =IF(Y44="***","***",Z44-X44) | AB44: =IF(Z44="***","***",Z44-X44)
D45: 合計 | I45: =I41+I36 | J45: =J41+J36 | K45: =K41+K36 | L45: =L41+L36 | M45: =L45-K45 | N45: =L45-J45 | O45: =IF(J45=0,"***",N45/J45) | P45: =P41+P36 | Q45: =Q41+Q36 | R45: =R41+R36 | S45: =S41+S36 | T45: =S45-R45 | U45: =S45-Q45 | V45: =IF(Q45=0,"***",U45/Q45) | W45: =IF(I45=0,"***",P45/I45) | X45: =IF(J45=0,"***",Q45/J45) | Y45: =IF(K45=0,"***",R45/K45) | Z45: =IF(L45=0,"***",S45/L45) | AA45: =IF(Y45="***","***",Z45-X45) | AB45: =IF(Z45="***","***",Z45-X45)
H46: 機械以外 | I46: =I45-I47 | J46: =J45-J47 | K46: =K45-K47 | L46: =L45-L47 | M46: =L46-K46 | N46: =L46-J46 | O46: =IF(J46=0,"***",N46/J46) | P46: =P45-P47 | Q46: =Q45-Q47 | R46: =R45-R47 | S46: =S45-S47 | T46: =S46-R46 | U46: =S46-Q46 | V46: =IF(Q46=0,"***",U46/Q46) | W46: =IF(I46=0,"***",P46/I46) | X46: =IF(J46=0,"***",Q46/J46) | Y46: =IF(K46=0,"***",R46/K46) | Z46: =IF(L46=0,"***",S46/L46) | AA46: =IF(Y46="***","***",Z46-X46) | AB46: =IF(Z46="***","***",Z46-X46)
H47: 機械 | I47: =I38+I44 | J47: =J38+J44 | K47: =K38+K44 | L47: =L38+L44 | M47: =L47-K47 | N47: =L47-J47 | O47: =IF(J47=0,"***",N47/J47) | P47: =P38+P44 | Q47: =Q38+Q44 | R47: =R38+R44 | S47: =S38+S44 | T47: =S47-R47 | U47: =S47-Q47 | V47: =IF(Q47=0,"***",U47/Q47) | W47: =IF(I47=0,"***",P47/I47) | X47: =IF(J47=0,"***",Q47/J47) | Y47: =IF(K47=0,"***",R47/K47) | Z47: =IF(L47=0,"***",S47/L47) | AA47: =IF(Y47="***","***",Z47-X47) | AB47: =IF(Z47="***","***",Z47-X47)
H48: 自治体 | I48: =I39 | J48: =J39 | K48: =K39 | L48: =L39 | M48: =L48-K48 | N48: =L48-J48 | O48: =IF(J48=0,"***",N48/J48) | P48: =P39 | Q48: =Q39 | R48: =R39 | S48: =S39 | T48: =S48-R48 | U48: =S48-Q48 | V48: =IF(Q48=0,"***",U48/Q48) | W48: =IF(I48=0,"***",P48/I48) | X48: =IF(J48=0,"***",Q48/J48) | Y48: =IF(K48=0,"***",R48/K48) | Z48: =IF(L48=0,"***",S48/L48) | AA48: =IF(Y48="***","***",Z48-X48) | AB48: =IF(Z48="***","***",Z48-X48)
H49: 海外 | I49: =I40 | J49: =J40 | K49: =K40 | L49: =L40 | M49: =L49-K49 | N49: =L49-J49 | O49: =IF(J49=0,"***",N49/J49) | P49: =P40 | Q49: =Q40 | R49: =R40 | S49: =S40 | T49: =S49-R49 | U49: =S49-Q49 | V49: =IF(Q49=0,"***",U49/Q49) | W49: =IF(I49=0,"***",P49/I49) | X49: =IF(J49=0,"***",Q49/J49) | Y49: =IF(K49=0,"***",R49/K49) | Z49: =IF(L49=0,"***",S49/L49) | AA49: =IF(Y49="***","***",Z49-X49) | AB49: =IF(Z49="***","***",Z49-X49)
D50: キョウワ（税抜） | I50: 2390 | J50: 2100 | K50: 2190 | L50: 2329 | M50: =L50-K50 | N50: =L50-J50 | O50: =IF(J50=0,"***",N50/J50) | P50: 1080 | Q50: 1150 | R50: 1090 | S50: 1227 | T50: =S50-R50 | U50: =S50-Q50 | V50: =IF(Q50=0,"***",U50/Q50) | W50: =IF(I50=0,"***",P50/I50) | X50: =IF(J50=0,"***",Q50/J50) | Y50: =IF(K50=0,"***",R50/K50) | Z50: =IF(L50=0,"***",S50/L50) | AA50: =IF(Y50="***","***",Z50-X50) | AB50: =IF(Z50="***","***",Z50-X50)

Sheet BACKDATA6月
D1: 1．単月
I3: 2024年6月売上実績 | J3: 2025年6月売上実績 | K3: 2026年6月売上計画 | L3: 2026年6月売上実績 | P3: 2024年6月粗利益実績 | Q3: 2025年6月粗利益実績 | R3: 2026年6月粗利益計画 | S3: 2026年6月粗利益実績 | W3: 2024年6月粗利益率実績 | X3: 2025年6月粗利益率実績 | Y3: 2026年6月粗利益率計画 | Z3: 2026年6月粗利益率実績 | AC3: 作成根拠
M4: 計画比 | N4: 前期比 | O4: 年率 | T4: 計画比 | U4: 前期比 | V4: 年率 | AA4: 計画比 | AB4: 前期比
F5: 石見営業所 | I5: 63134.792 | J5: 53593.012 | K5: 68200 | L5: 70877.17 | M5: =L5-K5 | N5: =L5-J5 | O5: =IF(J5=0,"***",N5/J5) | P5: 16549.54 | Q5: 15104.354 | R5: 17730 | S5: 20534.803 | T5: =S5-R5 | U5: =S5-Q5 | V5: =IF(Q5=0,"***",U5/Q5) | W5: =IF(I5=0,"***",P5/I5) | X5: =IF(J5=0,"***",Q5/J5) | Y5: =IF(K5=0,"***",R5/K5) | Z5: =IF(L5=0,"***",S5/L5) | AA5: =IF(Y5="***","***",Z5-X5) | AB5: =IF(Z5="***","***",Z5-X5)
G6: 営業 | I6: =I5-I9 | J6: =J5-J9 | K6: =K5-K9 | L6: =L5-L9 | M6: =L6-K6 | N6: =L6-J6 | O6: =IF(J6=0,"***",N6/J6) | P6: =P5-P9 | Q6: =Q5-Q9 | R6: =R5-R9 | S6: =S5-S9 | T6: =S6-R6 | U6: =S6-Q6 | V6: =IF(Q6=0,"***",U6/Q6) | W6: =IF(I6=0,"***",P6/I6) | X6: =IF(J6=0,"***",Q6/J6) | Y6: =IF(K6=0,"***",R6/K6) | Z6: =IF(L6=0,"***",S6/L6) | AA6: =IF(Y6="***","***",Z6-X6) | AB6: =IF(Z6="***","***",Z6-X6)
H7: 包装資材 | I7: =I6-I8 | J7: =J6-J8 | K7: =K6-K8 | L7: =L6-L8 | M7: =L7-K7 | N7: =L7-J7 | O7: =IF(J7=0,"***",N7/J7) | P7: =P6-P8 | Q7: =Q6-Q8 | R7: =R6-R8 | S7: =S6-S8 | T7: =S7-R7 | U7: =S7-Q7 | V7: =IF(Q7=0,"***",U7/Q7) | W7: =IF(I7=0,"***",P7/I7) | X7: =IF(J7=0,"***",Q7/J7) | Y7: =IF(K7=0,"***",R7/K7) | Z7: =IF(L7=0,"***",S7/L7) | AA7: =IF(Y7="***","***",Z7-X7) | AB7: =IF(Z7="***","***",Z7-X7)
H8: 機械 | I8: 1286.941 | J8: 1278.963 | K8: 4000 | L8: 2907.643 | M8: =L8-K8 | N8: =L8-J8 | O8: =IF(J8=0,"***",N8/J8) | P8: 280.698 | Q8: 248.231 | R8: 640 | S8: 579.211 | T8: =S8-R8 | U8: =S8-Q8 | V8: =IF(Q8=0,"***",U8/Q8) | W8: =IF(I8=0,"***",P8/I8) | X8: =IF(J8=0,"***",Q8/J8) | Y8: =IF(K8=0,"***",R8/K8) | Z8: =IF(L8=0,"***",S8/L8) | AA8: =IF(Y8="***","***",Z8-X8) | AB8: =IF(Z8="***","***",Z8-X8)
G9: 自治体 | I9: 420 | J9: 900 | K9: 1340 | L9: 180.2 | M9: =L9-K9 | N9: =L9-J9 | O9: =IF(J9=0,"***",N9/J9) | P9: 60.9 | Q9: 83.5 | R9: 210 | S9: 13.77 | T9: =S9-R9 | U9: =S9-Q9 | V9: =IF(Q9=0,"***",U9/Q9) | W9: =IF(I9=0,"***",P9/I9) | X9: =IF(J9=0,"***",Q9/J9) | Y9: =IF(K9=0,"***",R9/K9) | Z9: =IF(L9=0,"***",S9/L9) | AA9: =IF(Y9="***","***",Z9-X9) | AB9: =IF(Z9="***","***",Z9-X9)
F10: 下関営業所 | I10: 40381.899 | J10: 38382.356 | K10: 40400 | L10: 48853.433 | M10: =L10-K10 | N10: =L10-J10 | O10: =IF(J10=0,"***",N10/J10) | P10: 7914.464 | Q10: 7913.423 | R10: 8310 | S10: 10231.525 | T10: =S10-R10 | U10: =S10-Q10 | V10: =IF(Q10=0,"***",U10/Q10) | W10: =IF(I10=0,"***",P10/I10) | X10: =IF(J10=0,"***",Q10/J10) | Y10: =IF(K10=0,"***",R10/K10) | Z10: =IF(L10=0,"***",S10/L10) | AA10: =IF(Y10="***","***",Z10-X10) | AB10: =IF(Z10="***","***",Z10-X10)
G11: 営業 | I11: =I10-I15-I14 | J11: =J10-J15-J14 | K11: =K10-K15-K14 | L11: =L10-L15-L14 | M11: =L11-K11 | N11: =L11-J11 | O11: =IF(J11=0,"***",N11/J11) | P11: =P10-P15-P14 | Q11: =Q10-Q15-Q14 | R11: =R10-R15-R14 | S11: =S10-S15-S14 | T11: =S11-R11 | U11: =S11-Q11 | V11: =IF(Q11=0,"***",U11/Q11) | W11: =IF(I11=0,"***",P11/I11) | X11: =IF(J11=0,"***",Q11/J11) | Y11: =IF(K11=0,"***",R11/K11) | Z11: =IF(L11=0,"***",S11/L11) | AA11: =IF(Y11="***","***",Z11-X11) | AB11: =IF(Z11="***","***",Z11-X11)
H12: 包装資材 | I12: =I11-I13 | J12: =J11-J13 | K12: =K11-K13 | L12: =L11-L13 | M12: =L12-K12 | N12: =L12-J12 | O12: =IF(J12=0,"***",N12/J12) | P12: =P11-P13 | Q12: =Q11-Q13 | R12: =R11-R13 | S12: =S11-S13 | T12: =S12-R12 | U12: =S12-Q12 | V12: =IF(Q12=0,"***",U12/Q12) | W12: =IF(I12=0,"***",P12/I12) | X12: =IF(J12=0,"***",Q12/J12) | Y12: =IF(K12=0,"***",R12/K12) | Z12: =IF(L12=0,"***",S12/L12) | AA12: =IF(Y12="***","***",Z12-X12) | AB12: =IF(Z12="***","***",Z12-X12)
H13: 機械 | I13: 225 | J13: 266 | K13: 300 | L13: 169.95 | M13: =L13-K13 | N13: =L13-J13 | O13: =IF(J13=0,"***",N13/J13) | P13: -33 | Q13: 40 | R13: 50 | S13: 28.82 | T13: =S13-R13 | U13: =S13-Q13 | V13: =IF(Q13=0,"***",U13/Q13) | W13: =IF(I13=0,"***",P13/I13) | X13: =IF(J13=0,"***",Q13/J13) | Y13: =IF(K13=0,"***",R13/K13) | Z13: =IF(L13=0,"***",S13/L13) | AA13: =IF(Y13="***","***",Z13-X13) | AB13: =IF(Z13="***","***",Z13-X13)
G14: 自治体 | I14: 0 | J14: 0 | K14: 100 | L14: 94.2 | M14: =L14-K14 | N14: =L14-J14 | O14: =IF(J14=0,"***",N14/J14) | P14: 0 | Q14: 0 | R14: 10 | S14: 3.15 | T14: =S14-R14 | U14: =S14-Q14 | V14: =IF(Q14=0,"***",U14/Q14) | W14: =IF(I14=0,"***",P14/I14) | X14: =IF(J14=0,"***",Q14/J14) | Y14: =IF(K14=0,"***",R14/K14) | Z14: =IF(L14=0,"***",S14/L14)
G15: 海外 | I15: 0 | J15: 0 | K15: 0 | L15: 0 | M15: =L15-K15 | N15: =L15-J15 | O15: =IF(J15=0,"***",N15/J15) | P15: 0 | Q15: 0 | R15: 0 | S15: 0 | T15: =S15-R15 | U15: =S15-Q15 | V15: =IF(Q15=0,"***",U15/Q15) | W15: =IF(I15=0,"***",P15/I15) | X15: =IF(J15=0,"***",Q15/J15) | Y15: =IF(K15=0,"***",R15/K15) | Z15: =IF(L15=0,"***",S15/L15) | AA15: =IF(Y15="***","***",Z15-X15) | AB15: =IF(Z15="***","***",Z15-X15)
F16: 松江営業所 | I16: 35151.204 | J16: 35614.253 | K16: 27100 | L16: 30509.583 | M16: =L16-K16 | N16: =L16-J16 | O16: =IF(J16=0,"***",N16/J16) | P16: 5869.811 | Q16: 6588.7728 | R16: 6710 | S16: 7800.534 | T16: =S16-R16 | U16: =S16-Q16 | V16: =IF(Q16=0,"***",U16/Q16) | W16: =IF(I16=0,"***",P16/I16) | X16: =IF(J16=0,"***",Q16/J16) | Y16: =IF(K16=0,"***",R16/K16) | Z16: =IF(L16=0,"***",S16/L16) | AA16: =IF(Y16="***","***",Z16-X16) | AB16: =IF(Z16="***","***",Z16-X16)
G17: 営業 | I17: =I16-I20 | J17: =J16-J20 | K17: =K16-K20 | L17: =L16-L20 | M17: =L17-K17 | N17: =L17-J17 | O17: =IF(J17=0,"***",N17/J17) | P17: =P16-P20 | Q17: =Q16-Q20 | R17: =R16-R20 | S17: =S16-S20 | T17: =S17-R17 | U17: =S17-Q17 | V17: =IF(Q17=0,"***",U17/Q17) | W17: =IF(I17=0,"***",P17/I17) | X17: =IF(J17=0,"***",Q17/J17) | Y17: =IF(K17=0,"***",R17/K17) | Z17: =IF(L17=0,"***",S17/L17) | AA17: =IF(Y17="***","***",Z17-X17) | AB17: =IF(Z17="***","***",Z17-X17)
H18: 包装資材 | I18: =I17-I19 | J18: =J17-J19 | K18: =K17-K19 | L18: =L17-L19 | M18: =L18-K18 | N18: =L18-J18 | O18: =IF(J18=0,"***",N18/J18) | P18: =P17-P19 | Q18: =Q17-Q19 | R18: =R17-R19 | S18: =S17-S19 | T18: =S18-R18 | U18: =S18-Q18 | V18: =IF(Q18=0,"***",U18/Q18) | W18: =IF(I18=0,"***",P18/I18) | X18: =IF(J18=0,"***",Q18/J18) | Y18: =IF(K18=0,"***",R18/K18) | Z18: =IF(L18=0,"***",S18/L18) | AA18: =IF(Y18="***","***",Z18-X18) | AB18: =IF(Z18="***","***",Z18-X18)
H19: 機械 | I19: 412 | J19: 290 | K19: 500 | L19: 1932.04 | M19: =L19-K19 | N19: =L19-J19 | O19: =IF(J19=0,"***",N19/J19) | P19: 63 | Q19: 84 | R19: 120 | S19: 444.39 | T19: =S19-R19 | U19: =S19-Q19 | V19: =IF(Q19=0,"***",U19/Q19) | W19: =IF(I19=0,"***",P19/I19) | X19: =IF(J19=0,"***",Q19/J19) | Y19: =IF(K19=0,"***",R19/K19) | Z19: =IF(L19=0,"***",S19/L19) | AA19: =IF(Y19="***","***",Z19-X19) | AB19: =IF(Z19="***","***",Z19-X19)
G20: 自治体 | I20: 10715.25 | J20: 11193.008 | K20: 0 | L20: 0 | M20: =L20-K20 | N20: =L20-J20 | O20: =IF(J20=0,"***",N20/J20) | P20: 183.74 | Q20: 196.128 | R20: 0 | S20: 0 | T20: =S20-R20 | U20: =S20-Q20 | V20: =IF(Q20=0,"***",U20/Q20) | W20: =IF(I20=0,"***",P20/I20) | X20: =IF(J20=0,"***",Q20/J20) | Y20: =IF(K20=0,"***",R20/K20) | Z20: =IF(L20=0,"***",S20/L20) | AA20: =IF(Y20="***","***",Z20-X20) | AB20: =IF(Z20="***","***",Z20-X20)
F21: 広域営業部 | I21: 37320.214 | J21: 41558.181 | K21: 42200 | L21: 48123.343 | M21: =L21-K21 | N21: =L21-J21 | O21: =IF(J21=0,"***",N21/J21) | P21: 5253.283 | Q21: 6363.87 | R21: 6270 | S21: 10330.853 | T21: =S21-R21 | U21: =S21-Q21 | V21: =IF(Q21=0,"***",U21/Q21) | W21: =IF(I21=0,"***",P21/I21) | X21: =IF(J21=0,"***",Q21/J21) | Y21: =IF(K21=0,"***",R21/K21) | Z21: =IF(L21=0,"***",S21/L21) | AA21: =IF(Y21="***","***",Z21-X21) | AB21: =IF(Z21="***","***",Z21-X21)
H22: 包装資材 | I22: =I21-I23 | J22: =J21-J23 | K22: =K21-K23 | L22: =L21-L23 | M22: =L22-K22 | N22: =L22-J22 | O22: =IF(J22=0,"***",N22/J22) | P22: =P21-P23 | Q22: =Q21-Q23 | R22: =R21-R23 | S22: =S21-S23 | T22: =S22-R22 | U22: =S22-Q22 | V22: =IF(Q22=0,"***",U22/Q22) | W22: =IF(I22=0,"***",P22/I22) | X22: =IF(J22=0,"***",Q22/J22) | Y22: =IF(K22=0,"***",R22/K22) | Z22: =IF(L22=0,"***",S22/L22) | AA22: =IF(Y22="***","***",Z22-X22) | AB22: =IF(Z22="***","***",Z22-X22)
H23: 機械 | I23: 139 | J23: 207 | K23: 1000 | L23: 360.181 | M23: =L23-K23 | N23: =L23-J23 | O23: =IF(J23=0,"***",N23/J23) | P23: 13 | Q23: 34 | R23: 110 | S23: 14.891 | T23: =S23-R23 | U23: =S23-Q23 | V23: =IF(Q23=0,"***",U23/Q23) | W23: =IF(I23=0,"***",P23/I23) | X23: =IF(J23=0,"***",Q23/J23) | Y23: =IF(K23=0,"***",R23/K23) | Z23: =IF(L23=0,"***",S23/L23) | AA23: =IF(Y23="***","***",Z23-X23) | AB23: =IF(Z23="***","***",Z23-X23)
G24: リンガーハット | I24: 26248.349 | J24: 27401.864 | K24: 27113.485 | L24: 36356.804 | M24: =L24-K24 | N24: =L24-J24 | O24: =IF(J24=0,"***",N24/J24) | P24: 3729.589 | Q24: 4290.655 | R24: 4150.3885 | S24: 8432.142 | T24: =S24-R24 | U24: =S24-Q24 | V24: =IF(Q24=0,"***",U24/Q24) | W24: =IF(I24=0,"***",P24/I24) | X24: =IF(J24=0,"***",Q24/J24) | Y24: =IF(K24=0,"***",R24/K24) | Z24: =IF(L24=0,"***",S24/L24) | AA24: =IF(Y24="***","***",Z24-X24) | AB24: =IF(Z24="***","***",Z24-X24)
H25: 包装資材 | I25: =I24-I26 | J25: =J24-J26 | K25: =K24-K26 | L25: =L24-L26 | M25: =L25-K25 | N25: =L25-J25 | O25: =IF(J25=0,"***",N25/J25) | P25: =P24-P26 | Q25: =Q24-Q26 | R25: =R24-R26 | S25: =S24-S26 | T25: =S25-R25 | U25: =S25-Q25 | V25: =IF(Q25=0,"***",U25/Q25) | W25: =IF(I25=0,"***",P25/I25) | X25: =IF(J25=0,"***",Q25/J25) | Y25: =IF(K25=0,"***",R25/K25) | Z25: =IF(L25=0,"***",S25/L25) | AA25: =IF(Y25="***","***",Z25-X25) | AB25: =IF(Z25="***","***",Z25-X25)
H26: 機械 | I26: 27 | J26: 155 | K26: 123 | L26: 29.42 | M26: =L26-K26 | N26: =L26-J26 | O26: =IF(J26=0,"***",N26/J26) | P26: -1 | Q26: 0 | R26: -0.25 | S26: 5.78 | T26: =S26-R26 | U26: =S26-Q26 | V26: =IF(Q26=0,"***",U26/Q26) | W26: =IF(I26=0,"***",P26/I26) | X26: =IF(J26=0,"***",Q26/J26) | Y26: =IF(K26=0,"***",R26/K26) | Z26: =IF(L26=0,"***",S26/L26) | AA26: =IF(Y26="***","***",Z26-X26) | AB26: =IF(Z26="***","***",Z26-X26)
G27: リンガーハット以外 | I27: =I21-I24 | J27: =J21-J24 | K27: =K21-K24 | L27: =L21-L24 | M27: =L27-K27 | N27: =L27-J27 | O27: =IF(J27=0,"***",N27/J27) | P27: =P21-P24 | Q27: =Q21-Q24 | R27: =R21-R24 | S27: =S21-S24 | T27: =S27-R27 | U27: =S27-Q27 | V27: =IF(Q27=0,"***",U27/Q27) | W27: =IF(I27=0,"***",P27/I27) | X27: =IF(J27=0,"***",Q27/J27) | Y27: =IF(K27=0,"***",R27/K27) | Z27: =IF(L27=0,"***",S27/L27) | AA27: =IF(Y27="***","***",Z27-X27) | AB27: =IF(Z27="***","***",Z27-X27)
H28: 包装資材 | I28: =I27-I29 | J28: =J27-J29 | K28: =K27-K29 | L28: =L27-L29 | M28: =L28-K28 | N28: =L28-J28 | O28: =IF(J28=0,"***",N28/J28) | P28: =P27-P29 | Q28: =Q27-Q29 | R28: =R27-R29 | S28: =S27-S29 | T28: =S28-R28 | U28: =S28-Q28 | V28: =IF(Q28=0,"***",U28/Q28) | W28: =IF(I28=0,"***",P28/I28) | X28: =IF(J28=0,"***",Q28/J28) | Y28: =IF(K28=0,"***",R28/K28) | Z28: =IF(L28=0,"***",S28/L28) | AA28: =IF(Y28="***","***",Z28-X28) | AB28: =IF(Z28="***","***",Z28-X28)
H29: 機械 | I29: =I23-I26 | J29: =J23-J26 | K29: =K23-K26 | L29: =L23-L26 | M29: =L29-K29 | N29: =L29-J29 | O29: =IF(J29=0,"***",N29/J29) | P29: =P23-P26 | Q29: =Q23-Q26 | R29: =R23-R26 | S29: =S23-S26 | T29: =S29-R29 | U29: =S29-Q29 | V29: =IF(Q29=0,"***",U29/Q29) | W29: =IF(I29=0,"***",P29/I29) | X29: =IF(J29=0,"***",Q29/J29) | Y29: =IF(K29=0,"***",R29/K29) | Z29: =IF(L29=0,"***",S29/L29) | AA29: =IF(Y29="***","***",Z29-X29) | AB29: =IF(Z29="***","***",Z29-X29)
F30: 境港営業所 | I30: 38205.584 | J30: 40249.765 | K30: 63650 | L30: 68710.341 | M30: =L30-K30 | N30: =L30-J30 | O30: =IF(J30=0,"***",N30/J30) | P30: 6910.526 | Q30: 8493.501 | R30: 14300 | S30: 14973.697 | T30: =S30-R30 | U30: =S30-Q30 | V30: =IF(Q30=0,"***",U30/Q30) | W30: =IF(I30=0,"***",P30/I30) | X30: =IF(J30=0,"***",Q30/J30) | Y30: =IF(K30=0,"***",R30/K30) | Z30: =IF(L30=0,"***",S30/L30) | AA30: =IF(Y30="***","***",Z30-X30) | AB30: =IF(Z30="***","***",Z30-X30)
G31: 営業 | I31: =I30-I35-I34 | J31: =J30-J35-J34 | K31: =K30-K35-K34 | L31: =L30-L35-L34 | M31: =L31-K31 | N31: =L31-J31 | O31: =IF(J31=0,"***",N31/J31) | P31: =P30-P35-P34 | Q31: =Q30-Q35-Q34 | R31: =R30-R35-R34 | S31: =S30-S35-S34 | T31: =S31-R31 | U31: =S31-Q31 | V31: =IF(Q31=0,"***",U31/Q31) | W31: =IF(I31=0,"***",P31/I31) | X31: =IF(J31=0,"***",Q31/J31) | Y31: =IF(K31=0,"***",R31/K31) | Z31: =IF(L31=0,"***",S31/L31) | AA31: =IF(Y31="***","***",Z31-X31) | AB31: =IF(Z31="***","***",Z31-X31)
H32: 包装資材 | I32: =I31-I33 | J32: =J31-J33 | K32: =K31-K33 | L32: =L31-L33 | M32: =L32-K32 | N32: =L32-J32 | O32: =IF(J32=0,"***",N32/J32) | P32: =P31-P33 | Q32: =Q31-Q33 | R32: =R31-R33 | S32: =S31-S33 | T32: =S32-R32 | U32: =S32-Q32 | V32: =IF(Q32=0,"***",U32/Q32) | W32: =IF(I32=0,"***",P32/I32) | X32: =IF(J32=0,"***",Q32/J32) | Y32: =IF(K32=0,"***",R32/K32) | Z32: =IF(L32=0,"***",S32/L32) | AA32: =IF(Y32="***","***",Z32-X32) | AB32: =IF(Z32="***","***",Z32-X32)
H33: 機械 | I33: 3558 | J33: 8193 | K33: 27100 | L33: 22289.31 | M33: =L33-K33 | N33: =L33-J33 | O33: =IF(J33=0,"***",N33/J33) | P33: 905 | Q33: 2229 | R33: 7210 | S33: 6004.501 | T33: =S33-R33 | U33: =S33-Q33 | V33: =IF(Q33=0,"***",U33/Q33) | W33: =IF(I33=0,"***",P33/I33) | X33: =IF(J33=0,"***",Q33/J33) | Y33: =IF(K33=0,"***",R33/K33) | Z33: =IF(L33=0,"***",S33/L33) | AA33: =IF(Y33="***","***",Z33-X33) | AB33: =IF(Z33="***","***",Z33-X33)
G34: 自治体 | I34: 56.54 | J34: 0 | K34: 0 | L34: 82.104 | M34: =L34-K34 | N34: =L34-J34 | O34: =IF(J34=0,"***",N34/J34) | P34: 1.751 | Q34: 0 | R34: 0 | S34: 2.476 | T34: =S34-R34 | U34: =S34-Q34 | V34: =IF(Q34=0,"***",U34/Q34) | W34: =IF(I34=0,"***",P34/I34) | X34: =IF(J34=0,"***",Q34/J34) | Y34: =IF(K34=0,"***",R34/K34) | Z34: =IF(L34=0,"***",S34/L34) | AA34: =IF(Y34="***","***",Z34-X34) | AB34: =IF(Z34="***","***",Z34-X34)
G35: 海外 | I35: 378.6 | J35: 1376.87 | K35: 860 | L35: 2659.97 | M35: =L35-K35 | N35: =L35-J35 | O35: =IF(J35=0,"***",N35/J35) | P35: 89.88 | Q35: 289.41 | R35: 190 | S35: 713.36 | T35: =S35-R35 | U35: =S35-Q35 | V35: =IF(Q35=0,"***",U35/Q35) | W35: =IF(I35=0,"***",P35/I35) | X35: =IF(J35=0,"***",Q35/J35) | Y35: =IF(K35=0,"***",R35/K35) | Z35: =IF(L35=0,"***",S35/L35) | AA35: =IF(Y35="***","***",Z35-X35) | AB35: =IF(Z35="***","***",Z35-X35)
E36: 営業部門合計 | I36: =I30+I21+I16+I10+I5 | J36: =J30+J21+J16+J10+J5 | K36: =K30+K21+K16+K10+K5 | L36: =L30+L21+L16+L10+L5 | M36: =L36-K36 | N36: =L36-J36 | O36: =IF(J36=0,"***",N36/J36) | P36: =P30+P21+P16+P10+P5 | Q36: =Q30+Q21+Q16+Q10+Q5 | R36: =R30+R21+R16+R10+R5 | S36: =S30+S21+S16+S10+S5 | T36: =S36-R36 | U36: =S36-Q36 | V36: =IF(Q36=0,"***",U36/Q36) | W36: =IF(I36=0,"***",P36/I36) | X36: =IF(J36=0,"***",Q36/J36) | Y36: =IF(K36=0,"***",R36/K36) | Z36: =IF(L36=0,"***",S36/L36) | AA36: =IF(Y36="***","***",Z36-X36) | AB36: =IF(Z36="***","***",Z36-X36)
H37: 機械以外 | I37: =I36-I38-I39-I40 | J37: =J36-J38-J39-J40 | K37: =K36-K38-K39-K40 | L37: =L36-L38-L39-L40 | M37: =L37-K37 | N37: =L37-J37 | O37: =IF(J37=0,"***",N37/J37) | P37: =P36-P38-P39-P40 | Q37: =Q36-Q38-Q39-Q40 | R37: =R36-R38-R39-R40 | S37: =S36-S38-S39-S40 | T37: =S37-R37 | U37: =S37-Q37 | V37: =IF(Q37=0,"***",U37/Q37) | W37: =IF(I37=0,"***",P37/I37) | X37: =IF(J37=0,"***",Q37/J37) | Y37: =IF(K37=0,"***",R37/K37) | Z37: =IF(L37=0,"***",S37/L37) | AA37: =IF(Y37="***","***",Z37-X37) | AB37: =IF(Z37="***","***",Z37-X37)
H38: 機械 | I38: =I33+I23+I19+I13+I8 | J38: =J33+J23+J19+J13+J8 | K38: =K33+K23+K19+K13+K8 | L38: =L33+L23+L19+L13+L8 | M38: =L38-K38 | N38: =L38-J38 | O38: =IF(J38=0,"***",N38/J38) | P38: =P33+P23+P19+P13+P8 | Q38: =Q33+Q23+Q19+Q13+Q8 | R38: =R33+R23+R19+R13+R8 | S38: =S33+S23+S19+S13+S8 | T38: =S38-R38 | U38: =S38-Q38 | V38: =IF(Q38=0,"***",U38/Q38) | W38: =IF(I38=0,"***",P38/I38) | X38: =IF(J38=0,"***",Q38/J38) | Y38: =IF(K38=0,"***",R38/K38) | Z38: =IF(L38=0,"***",S38/L38) | AA38: =IF(Y38="***","***",Z38-X38) | AB38: =IF(Z38="***","***",Z38-X38)
H39: 自治体 | I39: =I34+I20+I14+I9 | J39: =J34+J20+J14+J9 | K39: =K34+K20+K14+K9 | L39: =L34+L20+L14+L9 | M39: =L39-K39 | N39: =L39-J39 | O39: =IF(J39=0,"***",N39/J39) | P39: =P34+P20+P14+P9 | Q39: =Q34+Q20+Q14+Q9 | R39: =R34+R20+R14+R9 | S39: =S34+S20+S14+S9 | T39: =S39-R39 | U39: =S39-Q39 | V39: =IF(Q39=0,"***",U39/Q39) | W39: =IF(I39=0,"***",P39/I39) | X39: =IF(J39=0,"***",Q39/J39) | Y39: =IF(K39=0,"***",R39/K39) | Z39: =IF(L39=0,"***",S39/L39) | AA39: =IF(Y39="***","***",Z39-X39) | AB39: =IF(Z39="***","***",Z39-X39)
H40: 海外 | I40: =I35+I15 | J40: =J35+J15 | K40: =K35+K15 | L40: =L35+L15 | M40: =L40-K40 | N40: =L40-J40 | O40: =IF(J40=0,"***",N40/J40) | P40: =P35+P15 | Q40: =Q35+Q15 | R40: =R35+R15 | S40: =S35+S15 | T40: =S40-R40 | U40: =S40-Q40 | V40: =IF(Q40=0,"***",U40/Q40) | W40: =IF(I40=0,"***",P40/I40) | X40: =IF(J40=0,"***",Q40/J40) | Y40: =IF(K40=0,"***",R40/K40) | Z40: =IF(L40=0,"***",S40/L40) | AA40: =IF(Y40="***","***",Z40-X40) | AB40: =IF(Z40="***","***",Z40-X40)
E41: 水産部 | I41: 30689.771 | J41: 40170.488 | K41: 42680 | L41: 56375.36 | M41: =L41-K41 | N41: =L41-J41 | O41: =IF(J41=0,"***",N41/J41) | P41: 6934.191 | Q41: 13121.934 | R41: 12370 | S41: 16495.904 | T41: =S41-R41 | U41: =S41-Q41 | V41: =IF(Q41=0,"***",U41/Q41) | W41: =IF(I41=0,"***",P41/I41) | X41: =IF(J41=0,"***",Q41/J41) | Y41: =IF(K41=0,"***",R41/K41) | Z41: =IF(L41=0,"***",S41/L41) | AA41: =IF(Y41="***","***",Z41-X41) | AB41: =IF(Z41="***","***",Z41-X41)
H42: 包装資材 | I42: =I41-I43-I44 | J42: =J41-J43-J44 | K42: =K41-K43-K44 | L42: =L41-L43-L44 | M42: =L42-K42 | N42: =L42-J42 | O42: =IF(J42=0,"***",N42/J42) | P42: =P41-P43-P44 | Q42: =Q41-Q43-Q44 | R42: =R41-R43-R44 | S42: =S41-S43-S44 | T42: =S42-R42 | U42: =S42-Q42 | V42: =IF(Q42=0,"***",U42/Q42) | W42: =IF(I42=0,"***",P42/I42) | X42: =IF(J42=0,"***",Q42/J42) | Y42: =IF(K42=0,"***",R42/K42) | Z42: =IF(L42=0,"***",S42/L42) | AA42: =IF(Y42="***","***",Z42-X42) | AB42: =IF(Z42="***","***",Z42-X42)
H43: 荷役 | I43: 4445.574 | J43: 8526.431 | K43: 8820 | L43: 7930.423 | M43: =L43-K43 | N43: =L43-J43 | O43: =IF(J43=0,"***",N43/J43) | P43: 2635.511 | Q43: 5937.06 | R43: 4810 | S43: 5071.4 | T43: =S43-R43 | U43: =S43-Q43 | V43: =IF(Q43=0,"***",U43/Q43) | W43: =IF(I43=0,"***",P43/I43) | X43: =IF(J43=0,"***",Q43/J43) | Y43: =IF(K43=0,"***",R43/K43) | Z43: =IF(L43=0,"***",S43/L43)
H44: 機械 | I44: 39 | J44: 49.2 | K44: 90 | L44: 526.91 | M44: =L44-K44 | N44: =L44-J44 | O44: =IF(J44=0,"***",N44/J44) | P44: 3.8 | Q44: 6.5 | R44: 20 | S44: 140.36 | T44: =S44-R44 | U44: =S44-Q44 | V44: =IF(Q44=0,"***",U44/Q44) | W44: =IF(I44=0,"***",P44/I44) | X44: =IF(J44=0,"***",Q44/J44) | Y44: =IF(K44=0,"***",R44/K44) | Z44: =IF(L44=0,"***",S44/L44) | AA44: =IF(Y44="***","***",Z44-X44) | AB44: =IF(Z44="***","***",Z44-X44)
D45: 合計 | I45: =I41+I36 | J45: =J41+J36 | K45: =K41+K36 | L45: =L41+L36 | M45: =L45-K45 | N45: =L45-J45 | O45: =IF(J45=0,"***",N45/J45) | P45: =P41+P36 | Q45: =Q41+Q36 | R45: =R41+R36 | S45: =S41+S36 | T45: =S45-R45 | U45: =S45-Q45 | V45: =IF(Q45=0,"***",U45/Q45) | W45: =IF(I45=0,"***",P45/I45) | X45: =IF(J45=0,"***",Q45/J45) | Y45: =IF(K45=0,"***",R45/K45) | Z45: =IF(L45=0,"***",S45/L45) | AA45: =IF(Y45="***","***",Z45-X45) | AB45: =IF(Z45="***","***",Z45-X45)
H46: 機械以外 | I46: =I45-I47 | J46: =J45-J47 | K46: =K45-K47 | L46: =L45-L47 | M46: =L46-K46 | N46: =L46-J46 | O46: =IF(J46=0,"***",N46/J46) | P46: =P45-P47 | Q46: =Q45-Q47 | R46: =R45-R47 | S46: =S45-S47 | T46: =S46-R46 | U46: =S46-Q46 | V46: =IF(Q46=0,"***",U46/Q46) | W46: =IF(I46=0,"***",P46/I46) | X46: =IF(J46=0,"***",Q46/J46) | Y46: =IF(K46=0,"***",R46/K46) | Z46: =IF(L46=0,"***",S46/L46) | AA46: =IF(Y46="***","***",Z46-X46) | AB46: =IF(Z46="***","***",Z46-X46)
H47: 機械 | I47: =I38+I44 | J47: =J38+J44 | K47: =K38+K44 | L47: =L38+L44 | M47: =L47-K47 | N47: =L47-J47 | O47: =IF(J47=0,"***",N47/J47) | P47: =P38+P44 | Q47: =Q38+Q44 | R47: =R38+R44 | S47: =S38+S44 | T47: =S47-R47 | U47: =S47-Q47 | V47: =IF(Q47=0,"***",U47/Q47) | W47: =IF(I47=0,"***",P47/I47) | X47: =IF(J47=0,"***",Q47/J47) | Y47: =IF(K47=0,"***",R47/K47) | Z47: =IF(L47=0,"***",S47/L47) | AA47: =IF(Y47="***","***",Z47-X47) | AB47: =IF(Z47="***","***",Z47-X47)
H48: 自治体 | I48: =I39 | J48: =J39 | K48: =K39 | L48: =L39 | M48: =L48-K48 | N48: =L48-J48 | O48: =IF(J48=0,"***",N48/J48) | P48: =P39 | Q48: =Q39 | R48: =R39 | S48: =S39 | T48: =S48-R48 | U48: =S48-Q48 | V48: =IF(Q48=0,"***",U48/Q48) | W48: =IF(I48=0,"***",P48/I48) | X48: =IF(J48=0,"***",Q48/J48) | Y48: =IF(K48=0,"***",R48/K48) | Z48: =IF(L48=0,"***",S48/L48) | AA48: =IF(Y48="***","***",Z48-X48) | AB48: =IF(Z48="***","***",Z48-X48)
H49: 海外 | I49: =I40 | J49: =J40 | K49: =K40 | L49: =L40 | M49: =L49-K49 | N49: =L49-J49 | O49: =IF(J49=0,"***",N49/J49) | P49: =P40 | Q49: =Q40 | R49: =R40 | S49: =S40 | T49: =S49-R49 | U49: =S49-Q49 | V49: =IF(Q49=0,"***",U49/Q49) | W49: =IF(I49=0,"***",P49/I49) | X49: =IF(J49=0,"***",Q49/J49) | Y49: =IF(K49=0,"***",R49/K49) | Z49: =IF(L49=0,"***",S49/L49) | AA49: =IF(Y49="***","***",Z49-X49) | AB49: =IF(Z49="***","***",Z49-X49)
D50: キョウワ（税抜） | I50: 2810 | J50: 3860 | K50: 3250 | L50: 2382 | M50: =L50-K50 | N50: =L50-J50 | O50: =IF(J50=0,"***",N50/J50) | P50: 1030 | Q50: 2620 | R50: 1770 | S50: 1466 | T50: =S50-R50 | U50: =S50-Q50 | V50: =IF(Q50=0,"***",U50/Q50) | W50: =IF(I50=0,"***",P50/I50) | X50: =IF(J50=0,"***",Q50/J50) | Y50: =IF(K50=0,"***",R50/K50) | Z50: =IF(L50=0,"***",S50/L50) | AA50: =IF(Y50="***","***",Z50-X50) | AB50: =IF(Z50="***","***",Z50-X50)

Sheet BACKDATA5月
D1: 1．単月
I3: 2024年5月売上実績 | J3: 2025年5月売上実績 | K3: 2026年5月売上計画 | L3: 2026年5月売上実績 | P3: 2024年5月粗利益実績 | Q3: 2025年5月粗利益実績 | R3: 2026年5月粗利益計画 | S3: 2026年5月粗利益実績 | W3: 2024年5月粗利益率実績 | X3: 2025年5月粗利益率実績 | Y3: 2026年5月粗利益率計画 | Z3: 2026年5月粗利益率実績 | AC3: 作成根拠
M4: 計画比 | N4: 前期比 | O4: 年率 | T4: 計画比 | U4: 前期比 | V4: 年率 | AA4: 計画比 | AB4: 前期比
F5: 石見営業所 | I5: 68619.123 | J5: 58850.135 | K5: 68980 | L5: 67381.862 | M5: =L5-K5 | N5: =L5-J5 | O5: =IF(J5=0,"***",N5/J5) | P5: 17589.754 | Q5: 17093.582 | R5: 18460 | S5: 20280.868 | T5: =S5-R5 | U5: =S5-Q5 | V5: =IF(Q5=0,"***",U5/Q5) | W5: =IF(I5=0,"***",P5/I5) | X5: =IF(J5=0,"***",Q5/J5) | Y5: =IF(K5=0,"***",R5/K5) | Z5: =IF(L5=0,"***",S5/L5) | AA5: =IF(Y5="***","***",Z5-X5) | AB5: =IF(Z5="***","***",Z5-X5)
G6: 営業 | I6: =I5-I9 | J6: =J5-J9 | K6: =K5-K9 | L6: =L5-L9 | M6: =L6-K6 | N6: =L6-J6 | O6: =IF(J6=0,"***",N6/J6) | P6: =P5-P9 | Q6: =Q5-Q9 | R6: =R5-R9 | S6: =S5-S9 | T6: =S6-R6 | U6: =S6-Q6 | V6: =IF(Q6=0,"***",U6/Q6) | W6: =IF(I6=0,"***",P6/I6) | X6: =IF(J6=0,"***",Q6/J6) | Y6: =IF(K6=0,"***",R6/K6) | Z6: =IF(L6=0,"***",S6/L6) | AA6: =IF(Y6="***","***",Z6-X6) | AB6: =IF(Z6="***","***",Z6-X6)
H7: 包装資材 | I7: =I6-I8 | J7: =J6-J8 | K7: =K6-K8 | L7: =L6-L8 | M7: =L7-K7 | N7: =L7-J7 | O7: =IF(J7=0,"***",N7/J7) | P7: =P6-P8 | Q7: =Q6-Q8 | R7: =R6-R8 | S7: =S6-S8 | T7: =S7-R7 | U7: =S7-Q7 | V7: =IF(Q7=0,"***",U7/Q7) | W7: =IF(I7=0,"***",P7/I7) | X7: =IF(J7=0,"***",Q7/J7) | Y7: =IF(K7=0,"***",R7/K7) | Z7: =IF(L7=0,"***",S7/L7) | AA7: =IF(Y7="***","***",Z7-X7) | AB7: =IF(Z7="***","***",Z7-X7)
H8: 機械 | I8: 8338.946 | J8: 986.469 | K8: 4000 | L8: 884.859 | M8: =L8-K8 | N8: =L8-J8 | O8: =IF(J8=0,"***",N8/J8) | P8: 1204.194 | Q8: 302.817 | R8: 640 | S8: 137.62 | T8: =S8-R8 | U8: =S8-Q8 | V8: =IF(Q8=0,"***",U8/Q8) | W8: =IF(I8=0,"***",P8/I8) | X8: =IF(J8=0,"***",Q8/J8) | Y8: =IF(K8=0,"***",R8/K8) | Z8: =IF(L8=0,"***",S8/L8) | AA8: =IF(Y8="***","***",Z8-X8) | AB8: =IF(Z8="***","***",Z8-X8)
G9: 自治体 | I9: 2257.6 | J9: 0 | K9: 1340 | L9: 450 | M9: =L9-K9 | N9: =L9-J9 | O9: =IF(J9=0,"***",N9/J9) | P9: 519.756 | Q9: 0 | R9: 210 | S9: 61.1 | T9: =S9-R9 | U9: =S9-Q9 | V9: =IF(Q9=0,"***",U9/Q9) | W9: =IF(I9=0,"***",P9/I9) | X9: =IF(J9=0,"***",Q9/J9) | Y9: =IF(K9=0,"***",R9/K9) | Z9: =IF(L9=0,"***",S9/L9) | AA9: =IF(Y9="***","***",Z9-X9) | AB9: =IF(Z9="***","***",Z9-X9)
F10: 下関営業所 | I10: 41524.558 | J10: 41016.074 | K10: 42800 | L10: 49979.891 | M10: =L10-K10 | N10: =L10-J10 | O10: =IF(J10=0,"***",N10/J10) | P10: 8340.645 | Q10: 8519.39 | R10: 8750 | S10: 9724.739 | T10: =S10-R10 | U10: =S10-Q10 | V10: =IF(Q10=0,"***",U10/Q10) | W10: =IF(I10=0,"***",P10/I10) | X10: =IF(J10=0,"***",Q10/J10) | Y10: =IF(K10=0,"***",R10/K10) | Z10: =IF(L10=0,"***",S10/L10) | AA10: =IF(Y10="***","***",Z10-X10) | AB10: =IF(Z10="***","***",Z10-X10)
G11: 営業 | I11: =I10-I15-I14 | J11: =J10-J15-J14 | K11: =K10-K15-K14 | L11: =L10-L15-L14 | M11: =L11-K11 | N11: =L11-J11 | O11: =IF(J11=0,"***",N11/J11) | P11: =P10-P15-P14 | Q11: =Q10-Q15-Q14 | R11: =R10-R15-R14 | S11: =S10-S15-S14 | T11: =S11-R11 | U11: =S11-Q11 | V11: =IF(Q11=0,"***",U11/Q11) | W11: =IF(I11=0,"***",P11/I11) | X11: =IF(J11=0,"***",Q11/J11) | Y11: =IF(K11=0,"***",R11/K11) | Z11: =IF(L11=0,"***",S11/L11) | AA11: =IF(Y11="***","***",Z11-X11) | AB11: =IF(Z11="***","***",Z11-X11)
H12: 包装資材 | I12: =I11-I13 | J12: =J11-J13 | K12: =K11-K13 | L12: =L11-L13 | M12: =L12-K12 | N12: =L12-J12 | O12: =IF(J12=0,"***",N12/J12) | P12: =P11-P13 | Q12: =Q11-Q13 | R12: =R11-R13 | S12: =S11-S13 | T12: =S12-R12 | U12: =S12-Q12 | V12: =IF(Q12=0,"***",U12/Q12) | W12: =IF(I12=0,"***",P12/I12) | X12: =IF(J12=0,"***",Q12/J12) | Y12: =IF(K12=0,"***",R12/K12) | Z12: =IF(L12=0,"***",S12/L12) | AA12: =IF(Y12="***","***",Z12-X12) | AB12: =IF(Z12="***","***",Z12-X12)
H13: 機械 | I13: 1804 | J13: 298 | K13: 500 | L13: 3684.67 | M13: =L13-K13 | N13: =L13-J13 | O13: =IF(J13=0,"***",N13/J13) | P13: 334 | Q13: 51 | R13: 90 | S13: 477.469 | T13: =S13-R13 | U13: =S13-Q13 | V13: =IF(Q13=0,"***",U13/Q13) | W13: =IF(I13=0,"***",P13/I13) | X13: =IF(J13=0,"***",Q13/J13) | Y13: =IF(K13=0,"***",R13/K13) | Z13: =IF(L13=0,"***",S13/L13) | AA13: =IF(Y13="***","***",Z13-X13) | AB13: =IF(Z13="***","***",Z13-X13)
G14: 自治体 | I14: 0 | J14: 0 | K14: 0 | L14: 0 | M14: =L14-K14 | N14: =L14-J14 | O14: =IF(J14=0,"***",N14/J14) | P14: 0 | Q14: 0 | R14: 0 | S14: 0 | T14: =S14-R14 | U14: =S14-Q14 | V14: =IF(Q14=0,"***",U14/Q14) | W14: =IF(I14=0,"***",P14/I14) | X14: =IF(J14=0,"***",Q14/J14) | Y14: =IF(K14=0,"***",R14/K14) | Z14: =IF(L14=0,"***",S14/L14)
G15: 海外 | I15: 0 | J15: 0 | K15: 0 | L15: 0 | M15: =L15-K15 | N15: =L15-J15 | O15: =IF(J15=0,"***",N15/J15) | P15: 0 | Q15: 0 | R15: 0 | S15: 0 | T15: =S15-R15 | U15: =S15-Q15 | V15: =IF(Q15=0,"***",U15/Q15) | W15: =IF(I15=0,"***",P15/I15) | X15: =IF(J15=0,"***",Q15/J15) | Y15: =IF(K15=0,"***",R15/K15) | Z15: =IF(L15=0,"***",S15/L15) | AA15: =IF(Y15="***","***",Z15-X15) | AB15: =IF(Z15="***","***",Z15-X15)
F16: 松江営業所 | I16: 27154.919 | J16: 26294.918 | K16: 26670 | L16: 29622.077 | M16: =L16-K16 | N16: =L16-J16 | O16: =IF(J16=0,"***",N16/J16) | P16: 5985.344 | Q16: 6768.047 | R16: 7030 | S16: 8216.221 | T16: =S16-R16 | U16: =S16-Q16 | V16: =IF(Q16=0,"***",U16/Q16) | W16: =IF(I16=0,"***",P16/I16) | X16: =IF(J16=0,"***",Q16/J16) | Y16: =IF(K16=0,"***",R16/K16) | Z16: =IF(L16=0,"***",S16/L16) | AA16: =IF(Y16="***","***",Z16-X16) | AB16: =IF(Z16="***","***",Z16-X16)
G17: 営業 | I17: =I16-I20 | J17: =J16-J20 | K17: =K16-K20 | L17: =L16-L20 | M17: =L17-K17 | N17: =L17-J17 | O17: =IF(J17=0,"***",N17/J17) | P17: =P16-P20 | Q17: =Q16-Q20 | R17: =R16-R20 | S17: =S16-S20 | T17: =S17-R17 | U17: =S17-Q17 | V17: =IF(Q17=0,"***",U17/Q17) | W17: =IF(I17=0,"***",P17/I17) | X17: =IF(J17=0,"***",Q17/J17) | Y17: =IF(K17=0,"***",R17/K17) | Z17: =IF(L17=0,"***",S17/L17) | AA17: =IF(Y17="***","***",Z17-X17) | AB17: =IF(Z17="***","***",Z17-X17)
H18: 包装資材 | I18: =I17-I19 | J18: =J17-J19 | K18: =K17-K19 | L18: =L17-L19 | M18: =L18-K18 | N18: =L18-J18 | O18: =IF(J18=0,"***",N18/J18) | P18: =P17-P19 | Q18: =Q17-Q19 | R18: =R17-R19 | S18: =S17-S19 | T18: =S18-R18 | U18: =S18-Q18 | V18: =IF(Q18=0,"***",U18/Q18) | W18: =IF(I18=0,"***",P18/I18) | X18: =IF(J18=0,"***",Q18/J18) | Y18: =IF(K18=0,"***",R18/K18) | Z18: =IF(L18=0,"***",S18/L18) | AA18: =IF(Y18="***","***",Z18-X18) | AB18: =IF(Z18="***","***",Z18-X18)
H19: 機械 | I19: 3050 | J19: 254 | K19: 500 | L19: 442.305 | M19: =L19-K19 | N19: =L19-J19 | O19: =IF(J19=0,"***",N19/J19) | P19: 638 | Q19: 42 | R19: 120 | S19: 100.019 | T19: =S19-R19 | U19: =S19-Q19 | V19: =IF(Q19=0,"***",U19/Q19) | W19: =IF(I19=0,"***",P19/I19) | X19: =IF(J19=0,"***",Q19/J19) | Y19: =IF(K19=0,"***",R19/K19) | Z19: =IF(L19=0,"***",S19/L19) | AA19: =IF(Y19="***","***",Z19-X19) | AB19: =IF(Z19="***","***",Z19-X19)
G20: 自治体 | I20: 3182.96 | J20: 2209.46 | K20: 0 | L20: 0 | M20: =L20-K20 | N20: =L20-J20 | O20: =IF(J20=0,"***",N20/J20) | P20: 57.56 | Q20: 19.31 | R20: 0 | S20: 0 | T20: =S20-R20 | U20: =S20-Q20 | V20: =IF(Q20=0,"***",U20/Q20) | W20: =IF(I20=0,"***",P20/I20) | X20: =IF(J20=0,"***",Q20/J20) | Y20: =IF(K20=0,"***",R20/K20) | Z20: =IF(L20=0,"***",S20/L20) | AA20: =IF(Y20="***","***",Z20-X20) | AB20: =IF(Z20="***","***",Z20-X20)
F21: 広域営業部 | I21: 30502.722 | J21: 38070.247 | K21: 40000 | L21: 40666.049 | M21: =L21-K21 | N21: =L21-J21 | O21: =IF(J21=0,"***",N21/J21) | P21: 4479.711 | Q21: 5260.267 | R21: 5825 | S21: 9213.385 | T21: =S21-R21 | U21: =S21-Q21 | V21: =IF(Q21=0,"***",U21/Q21) | W21: =IF(I21=0,"***",P21/I21) | X21: =IF(J21=0,"***",Q21/J21) | Y21: =IF(K21=0,"***",R21/K21) | Z21: =IF(L21=0,"***",S21/L21) | AA21: =IF(Y21="***","***",Z21-X21) | AB21: =IF(Z21="***","***",Z21-X21)
H22: 包装資材 | I22: =I21-I23 | J22: =J21-J23 | K22: =K21-K23 | L22: =L21-L23 | M22: =L22-K22 | N22: =L22-J22 | O22: =IF(J22=0,"***",N22/J22) | P22: =P21-P23 | Q22: =Q21-Q23 | R22: =R21-R23 | S22: =S21-S23 | T22: =S22-R22 | U22: =S22-Q22 | V22: =IF(Q22=0,"***",U22/Q22) | W22: =IF(I22=0,"***",P22/I22) | X22: =IF(J22=0,"***",Q22/J22) | Y22: =IF(K22=0,"***",R22/K22) | Z22: =IF(L22=0,"***",S22/L22) | AA22: =IF(Y22="***","***",Z22-X22) | AB22: =IF(Z22="***","***",Z22-X22)
H23: 機械 | I23: 246 | J23: 80 | K23: 1000 | L23: 98.8 | M23: =L23-K23 | N23: =L23-J23 | O23: =IF(J23=0,"***",N23/J23) | P23: 12 | Q23: 11 | R23: 110 | S23: 19.64 | T23: =S23-R23 | U23: =S23-Q23 | V23: =IF(Q23=0,"***",U23/Q23) | W23: =IF(I23=0,"***",P23/I23) | X23: =IF(J23=0,"***",Q23/J23) | Y23: =IF(K23=0,"***",R23/K23) | Z23: =IF(L23=0,"***",S23/L23) | AA23: =IF(Y23="***","***",Z23-X23) | AB23: =IF(Z23="***","***",Z23-X23)
G24: リンガーハット | I24: 21871.365 | J24: 25889.141 | K24: 24884.697 | L24: 31723.222 | M24: =L24-K24 | N24: =L24-J24 | O24: =IF(J24=0,"***",N24/J24) | P24: 3148.576 | Q24: 3628.179 | R24: 3508.278 | S24: 7752.55 | T24: =S24-R24 | U24: =S24-Q24 | V24: =IF(Q24=0,"***",U24/Q24) | W24: =IF(I24=0,"***",P24/I24) | X24: =IF(J24=0,"***",Q24/J24) | Y24: =IF(K24=0,"***",R24/K24) | Z24: =IF(L24=0,"***",S24/L24) | AA24: =IF(Y24="***","***",Z24-X24) | AB24: =IF(Z24="***","***",Z24-X24)
H25: 包装資材 | I25: =I24-I26 | J25: =J24-J26 | K25: =K24-K26 | L25: =L24-L26 | M25: =L25-K25 | N25: =L25-J25 | O25: =IF(J25=0,"***",N25/J25) | P25: =P24-P26 | Q25: =Q24-Q26 | R25: =R24-R26 | S25: =S24-S26 | T25: =S25-R25 | U25: =S25-Q25 | V25: =IF(Q25=0,"***",U25/Q25) | W25: =IF(I25=0,"***",P25/I25) | X25: =IF(J25=0,"***",Q25/J25) | Y25: =IF(K25=0,"***",R25/K25) | Z25: =IF(L25=0,"***",S25/L25) | AA25: =IF(Y25="***","***",Z25-X25) | AB25: =IF(Z25="***","***",Z25-X25)
H26: 機械 | I26: 148 | J26: 62 | K26: 83.5 | L26: 49.6 | M26: =L26-K26 | N26: =L26-J26 | O26: =IF(J26=0,"***",N26/J26) | P26: 4 | Q26: 44 | R26: 34 | S26: 4.94 | T26: =S26-R26 | U26: =S26-Q26 | V26: =IF(Q26=0,"***",U26/Q26) | W26: =IF(I26=0,"***",P26/I26) | X26: =IF(J26=0,"***",Q26/J26) | Y26: =IF(K26=0,"***",R26/K26) | Z26: =IF(L26=0,"***",S26/L26) | AA26: =IF(Y26="***","***",Z26-X26) | AB26: =IF(Z26="***","***",Z26-X26)
G27: リンガーハット以外 | I27: =I21-I24 | J27: =J21-J24 | K27: =K21-K24 | L27: =L21-L24 | M27: =L27-K27 | N27: =L27-J27 | O27: =IF(J27=0,"***",N27/J27) | P27: =P21-P24 | Q27: =Q21-Q24 | R27: =R21-R24 | S27: =S21-S24 | T27: =S27-R27 | U27: =S27-Q27 | V27: =IF(Q27=0,"***",U27/Q27) | W27: =IF(I27=0,"***",P27/I27) | X27: =IF(J27=0,"***",Q27/J27) | Y27: =IF(K27=0,"***",R27/K27) | Z27: =IF(L27=0,"***",S27/L27) | AA27: =IF(Y27="***","***",Z27-X27) | AB27: =IF(Z27="***","***",Z27-X27)
H28: 包装資材 | I28: =I27-I29 | J28: =J27-J29 | K28: =K27-K29 | L28: =L27-L29 | M28: =L28-K28 | N28: =L28-J28 | O28: =IF(J28=0,"***",N28/J28) | P28: =P27-P29 | Q28: =Q27-Q29 | R28: =R27-R29 | S28: =S27-S29 | T28: =S28-R28 | U28: =S28-Q28 | V28: =IF(Q28=0,"***",U28/Q28) | W28: =IF(I28=0,"***",P28/I28) | X28: =IF(J28=0,"***",Q28/J28) | Y28: =IF(K28=0,"***",R28/K28) | Z28: =IF(L28=0,"***",S28/L28) | AA28: =IF(Y28="***","***",Z28-X28) | AB28: =IF(Z28="***","***",Z28-X28)
H29: 機械 | I29: =I23-I26 | J29: =J23-J26 | K29: =K23-K26 | L29: =L23-L26 | M29: =L29-K29 | N29: =L29-J29 | O29: =IF(J29=0,"***",N29/J29) | P29: =P23-P26 | Q29: =Q23-Q26 | R29: =R23-R26 | S29: =S23-S26 | T29: =S29-R29 | U29: =S29-Q29 | V29: =IF(Q29=0,"***",U29/Q29) | W29: =IF(I29=0,"***",P29/I29) | X29: =IF(J29=0,"***",Q29/J29) | Y29: =IF(K29=0,"***",R29/K29) | Z29: =IF(L29=0,"***",S29/L29) | AA29: =IF(Y29="***","***",Z29-X29) | AB29: =IF(Z29="***","***",Z29-X29)
F30: 境港営業所 | I30: 67323.048 | J30: 42976.807 | K30: 54050 | L30: 54709.881 | M30: =L30-K30 | N30: =L30-J30 | O30: =IF(J30=0,"***",N30/J30) | P30: 12416.884 | Q30: 8263.246 | R30: 10850 | S30: 11355.972 | T30: =S30-R30 | U30: =S30-Q30 | V30: =IF(Q30=0,"***",U30/Q30) | W30: =IF(I30=0,"***",P30/I30) | X30: =IF(J30=0,"***",Q30/J30) | Y30: =IF(K30=0,"***",R30/K30) | Z30: =IF(L30=0,"***",S30/L30) | AA30: =IF(Y30="***","***",Z30-X30) | AB30: =IF(Z30="***","***",Z30-X30)
G31: 営業 | I31: =I30-I35-I34 | J31: =J30-J35-J34 | K31: =K30-K35-K34 | L31: =L30-L35-L34 | M31: =L31-K31 | N31: =L31-J31 | O31: =IF(J31=0,"***",N31/J31) | P31: =P30-P35-P34 | Q31: =Q30-Q35-Q34 | R31: =R30-R35-R34 | S31: =S30-S35-S34 | T31: =S31-R31 | U31: =S31-Q31 | V31: =IF(Q31=0,"***",U31/Q31) | W31: =IF(I31=0,"***",P31/I31) | X31: =IF(J31=0,"***",Q31/J31) | Y31: =IF(K31=0,"***",R31/K31) | Z31: =IF(L31=0,"***",S31/L31) | AA31: =IF(Y31="***","***",Z31-X31) | AB31: =IF(Z31="***","***",Z31-X31)
H32: 包装資材 | I32: =I31-I33 | J32: =J31-J33 | K32: =K31-K33 | L32: =L31-L33 | M32: =L32-K32 | N32: =L32-J32 | O32: =IF(J32=0,"***",N32/J32) | P32: =P31-P33 | Q32: =Q31-Q33 | R32: =R31-R33 | S32: =S31-S33 | T32: =S32-R32 | U32: =S32-Q32 | V32: =IF(Q32=0,"***",U32/Q32) | W32: =IF(I32=0,"***",P32/I32) | X32: =IF(J32=0,"***",Q32/J32) | Y32: =IF(K32=0,"***",R32/K32) | Z32: =IF(L32=0,"***",S32/L32) | AA32: =IF(Y32="***","***",Z32-X32) | AB32: =IF(Z32="***","***",Z32-X32)
H33: 機械 | I33: 32157 | J33: 2878 | K33: 9100 | L33: 10613 | M33: =L33-K33 | N33: =L33-J33 | O33: =IF(J33=0,"***",N33/J33) | P33: 6276 | Q33: 674 | R33: 2050 | S33: 2668 | T33: =S33-R33 | U33: =S33-Q33 | V33: =IF(Q33=0,"***",U33/Q33) | W33: =IF(I33=0,"***",P33/I33) | X33: =IF(J33=0,"***",Q33/J33) | Y33: =IF(K33=0,"***",R33/K33) | Z33: =IF(L33=0,"***",S33/L33) | AA33: =IF(Y33="***","***",Z33-X33) | AB33: =IF(Z33="***","***",Z33-X33)
G34: 自治体 | I34: 0 | J34: 87.14 | K34: 0 | L34: 0 | M34: =L34-K34 | N34: =L34-J34 | O34: =IF(J34=0,"***",N34/J34) | P34: 0 | Q34: 4.893 | R34: 0 | S34: 0 | T34: =S34-R34 | U34: =S34-Q34 | V34: =IF(Q34=0,"***",U34/Q34) | W34: =IF(I34=0,"***",P34/I34) | X34: =IF(J34=0,"***",Q34/J34) | Y34: =IF(K34=0,"***",R34/K34) | Z34: =IF(L34=0,"***",S34/L34) | AA34: =IF(Y34="***","***",Z34-X34) | AB34: =IF(Z34="***","***",Z34-X34)
G35: 海外 | I35: 2599.656 | J35: 2423.2 | K35: 2000 | L35: 5289.97 | M35: =L35-K35 | N35: =L35-J35 | O35: =IF(J35=0,"***",N35/J35) | P35: 474.93 | Q35: 339.583 | R35: 430 | S35: 806.536 | T35: =S35-R35 | U35: =S35-Q35 | V35: =IF(Q35=0,"***",U35/Q35) | W35: =IF(I35=0,"***",P35/I35) | X35: =IF(J35=0,"***",Q35/J35) | Y35: =IF(K35=0,"***",R35/K35) | Z35: =IF(L35=0,"***",S35/L35) | AA35: =IF(Y35="***","***",Z35-X35) | AB35: =IF(Z35="***","***",Z35-X35)
E36: 営業部門合計 | I36: =I30+I21+I16+I10+I5 | J36: =J30+J21+J16+J10+J5 | K36: =K30+K21+K16+K10+K5 | L36: =L30+L21+L16+L10+L5 | M36: =L36-K36 | N36: =L36-J36 | O36: =IF(J36=0,"***",N36/J36) | P36: =P30+P21+P16+P10+P5 | Q36: =Q30+Q21+Q16+Q10+Q5 | R36: =R30+R21+R16+R10+R5 | S36: =S30+S21+S16+S10+S5 | T36: =S36-R36 | U36: =S36-Q36 | V36: =IF(Q36=0,"***",U36/Q36) | W36: =IF(I36=0,"***",P36/I36) | X36: =IF(J36=0,"***",Q36/J36) | Y36: =IF(K36=0,"***",R36/K36) | Z36: =IF(L36=0,"***",S36/L36) | AA36: =IF(Y36="***","***",Z36-X36) | AB36: =IF(Z36="***","***",Z36-X36)
H37: 機械以外 | I37: =I36-I38-I39-I40 | J37: =J36-J38-J39-J40 | K37: =K36-K38-K39-K40 | L37: =L36-L38-L39-L40 | M37: =L37-K37 | N37: =L37-J37 | O37: =IF(J37=0,"***",N37/J37) | P37: =P36-P38-P39-P40 | Q37: =Q36-Q38-Q39-Q40 | R37: =R36-R38-R39-R40 | S37: =S36-S38-S39-S40 | T37: =S37-R37 | U37: =S37-Q37 | V37: =IF(Q37=0,"***",U37/Q37) | W37: =IF(I37=0,"***",P37/I37) | X37: =IF(J37=0,"***",Q37/J37) | Y37: =IF(K37=0,"***",R37/K37) | Z37: =IF(L37=0,"***",S37/L37) | AA37: =IF(Y37="***","***",Z37-X37) | AB37: =IF(Z37="***","***",Z37-X37)
H38: 機械 | I38: =I33+I23+I19+I13+I8 | J38: =J33+J23+J19+J13+J8 | K38: =K33+K23+K19+K13+K8 | L38: =L33+L23+L19+L13+L8 | M38: =L38-K38 | N38: =L38-J38 | O38: =IF(J38=0,"***",N38/J38) | P38: =P33+P23+P19+P13+P8 | Q38: =Q33+Q23+Q19+Q13+Q8 | R38: =R33+R23+R19+R13+R8 | S38: =S33+S23+S19+S13+S8 | T38: =S38-R38 | U38: =S38-Q38 | V38: =IF(Q38=0,"***",U38/Q38) | W38: =IF(I38=0,"***",P38/I38) | X38: =IF(J38=0,"***",Q38/J38) | Y38: =IF(K38=0,"***",R38/K38) | Z38: =IF(L38=0,"***",S38/L38) | AA38: =IF(Y38="***","***",Z38-X38) | AB38: =IF(Z38="***","***",Z38-X38)
H39: 自治体 | I39: =I34+I20+I14+I9 | J39: =J34+J20+J14+J9 | K39: =K34+K20+K14+K9 | L39: =L34+L20+L14+L9 | M39: =L39-K39 | N39: =L39-J39 | O39: =IF(J39=0,"***",N39/J39) | P39: =P34+P20+P14+P9 | Q39: =Q34+Q20+Q14+Q9 | R39: =R34+R20+R14+R9 | S39: =S34+S20+S14+S9 | T39: =S39-R39 | U39: =S39-Q39 | V39: =IF(Q39=0,"***",U39/Q39) | W39: =IF(I39=0,"***",P39/I39) | X39: =IF(J39=0,"***",Q39/J39) | Y39: =IF(K39=0,"***",R39/K39) | Z39: =IF(L39=0,"***",S39/L39) | AA39: =IF(Y39="***","***",Z39-X39) | AB39: =IF(Z39="***","***",Z39-X39)
H40: 海外 | I40: =I35+I15 | J40: =J35+J15 | K40: =K35+K15 | L40: =L35+L15 | M40: =L40-K40 | N40: =L40-J40 | O40: =IF(J40=0,"***",N40/J40) | P40: =P35+P15 | Q40: =Q35+Q15 | R40: =R35+R15 | S40: =S35+S15 | T40: =S40-R40 | U40: =S40-Q40 | V40: =IF(Q40=0,"***",U40/Q40) | W40: =IF(I40=0,"***",P40/I40) | X40: =IF(J40=0,"***",Q40/J40) | Y40: =IF(K40=0,"***",R40/K40) | Z40: =IF(L40=0,"***",S40/L40) | AA40: =IF(Y40="***","***",Z40-X40) | AB40: =IF(Z40="***","***",Z40-X40)
E41: 水産部 | I41: 38673.289 | J41: 43469.795 | K41: 46340 | L41: 54652.489 | M41: =L41-K41 | N41: =L41-J41 | O41: =IF(J41=0,"***",N41/J41) | P41: 10043.395 | Q41: 13493.576 | R41: 14640 | S41: 17486.522 | T41: =S41-R41 | U41: =S41-Q41 | V41: =IF(Q41=0,"***",U41/Q41) | W41: =IF(I41=0,"***",P41/I41) | X41: =IF(J41=0,"***",Q41/J41) | Y41: =IF(K41=0,"***",R41/K41) | Z41: =IF(L41=0,"***",S41/L41) | AA41: =IF(Y41="***","***",Z41-X41) | AB41: =IF(Z41="***","***",Z41-X41)
H42: 包装資材 | I42: =I41-I43-I44 | J42: =J41-J43-J44 | K42: =K41-K43-K44 | L42: =L41-L43-L44 | M42: =L42-K42 | N42: =L42-J42 | O42: =IF(J42=0,"***",N42/J42) | P42: =P41-P43-P44 | Q42: =Q41-Q43-Q44 | R42: =R41-R43-R44 | S42: =S41-S43-S44 | T42: =S42-R42 | U42: =S42-Q42 | V42: =IF(Q42=0,"***",U42/Q42) | W42: =IF(I42=0,"***",P42/I42) | X42: =IF(J42=0,"***",Q42/J42) | Y42: =IF(K42=0,"***",R42/K42) | Z42: =IF(L42=0,"***",S42/L42) | AA42: =IF(Y42="***","***",Z42-X42) | AB42: =IF(Z42="***","***",Z42-X42)
H43: 荷役 | I43: 8874.963 | J43: 8587.513 | K43: 9740 | L43: 10152.326 | M43: =L43-K43 | N43: =L43-J43 | O43: =IF(J43=0,"***",N43/J43) | P43: 4712.972 | Q43: 5203.461 | R43: 5580 | S43: 5901.976 | T43: =S43-R43 | U43: =S43-Q43 | V43: =IF(Q43=0,"***",U43/Q43) | W43: =IF(I43=0,"***",P43/I43) | X43: =IF(J43=0,"***",Q43/J43) | Y43: =IF(K43=0,"***",R43/K43) | Z43: =IF(L43=0,"***",S43/L43)
H44: 機械 | I44: 28 | J44: 188.5 | K44: 90 | L44: 205.68 | M44: =L44-K44 | N44: =L44-J44 | O44: =IF(J44=0,"***",N44/J44) | P44: 2.7 | Q44: 45.9 | R44: 20 | S44: 26.08 | T44: =S44-R44 | U44: =S44-Q44 | V44: =IF(Q44=0,"***",U44/Q44) | W44: =IF(I44=0,"***",P44/I44) | X44: =IF(J44=0,"***",Q44/J44) | Y44: =IF(K44=0,"***",R44/K44) | Z44: =IF(L44=0,"***",S44/L44) | AA44: =IF(Y44="***","***",Z44-X44) | AB44: =IF(Z44="***","***",Z44-X44)
D45: 合計 | I45: =I41+I36 | J45: =J41+J36 | K45: =K41+K36 | L45: =L41+L36 | M45: =L45-K45 | N45: =L45-J45 | O45: =IF(J45=0,"***",N45/J45) | P45: =P41+P36 | Q45: =Q41+Q36 | R45: =R41+R36 | S45: =S41+S36 | T45: =S45-R45 | U45: =S45-Q45 | V45: =IF(Q45=0,"***",U45/Q45) | W45: =IF(I45=0,"***",P45/I45) | X45: =IF(J45=0,"***",Q45/J45) | Y45: =IF(K45=0,"***",R45/K45) | Z45: =IF(L45=0,"***",S45/L45) | AA45: =IF(Y45="***","***",Z45-X45) | AB45: =IF(Z45="***","***",Z45-X45)
H46: 機械以外 | I46: =I45-I47 | J46: =J45-J47 | K46: =K45-K47 | L46: =L45-L47 | M46: =L46-K46 | N46: =L46-J46 | O46: =IF(J46=0,"***",N46/J46) | P46: =P45-P47 | Q46: =Q45-Q47 | R46: =R45-R47 | S46: =S45-S47 | T46: =S46-R46 | U46: =S46-Q46 | V46: =IF(Q46=0,"***",U46/Q46) | W46: =IF(I46=0,"***",P46/I46) | X46: =IF(J46=0,"***",Q46/J46) | Y46: =IF(K46=0,"***",R46/K46) | Z46: =IF(L46=0,"***",S46/L46) | AA46: =IF(Y46="***","***",Z46-X46) | AB46: =IF(Z46="***","***",Z46-X46)
H47: 機械 | I47: =I38+I44 | J47: =J38+J44 | K47: =K38+K44 | L47: =L38+L44 | M47: =L47-K47 | N47: =L47-J47 | O47: =IF(J47=0,"***",N47/J47) | P47: =P38+P44 | Q47: =Q38+Q44 | R47: =R38+R44 | S47: =S38+S44 | T47: =S47-R47 | U47: =S47-Q47 | V47: =IF(Q47=0,"***",U47/Q47) | W47: =IF(I47=0,"***",P47/I47) | X47: =IF(J47=0,"***",Q47/J47) | Y47: =IF(K47=0,"***",R47/K47) | Z47: =IF(L47=0,"***",S47/L47) | AA47: =IF(Y47="***","***",Z47-X47) | AB47: =IF(Z47="***","***",Z47-X47)
H48: 自治体 | I48: =I39 | J48: =J39 | K48: =K39 | L48: =L39 | M48: =L48-K48 | N48: =L48-J48 | O48: =IF(J48=0,"***",N48/J48) | P48: =P39 | Q48: =Q39 | R48: =R39 | S48: =S39 | T48: =S48-R48 | U48: =S48-Q48 | V48: =IF(Q48=0,"***",U48/Q48) | W48: =IF(I48=0,"***",P48/I48) | X48: =IF(J48=0,"***",Q48/J48) | Y48: =IF(K48=0,"***",R48/K48) | Z48: =IF(L48=0,"***",S48/L48) | AA48: =IF(Y48="***","***",Z48-X48) | AB48: =IF(Z48="***","***",Z48-X48)
H49: 海外 | I49: =I40 | J49: =J40 | K49: =K40 | L49: =L40 | M49: =L49-K49 | N49: =L49-J49 | O49: =IF(J49=0,"***",N49/J49) | P49: =P40 | Q49: =Q40 | R49: =R40 | S49: =S40 | T49: =S49-R49 | U49: =S49-Q49 | V49: =IF(Q49=0,"***",U49/Q49) | W49: =IF(I49=0,"***",P49/I49) | X49: =IF(J49=0,"***",Q49/J49) | Y49: =IF(K49=0,"***",R49/K49) | Z49: =IF(L49=0,"***",S49/L49) | AA49: =IF(Y49="***","***",Z49-X49) | AB49: =IF(Z49="***","***",Z49-X49)
D50: キョウワ（税抜） | I50: 2310 | J50: 1800 | K50: 2010 | L50: 1869 | M50: =L50-K50 | N50: =L50-J50 | O50: =IF(J50=0,"***",N50/J50) | P50: 1130 | Q50: 1160 | R50: 1120 | S50: 1317 | T50: =S50-R50 | U50: =S50-Q50 | V50: =IF(Q50=0,"***",U50/Q50) | W50: =IF(I50=0,"***",P50/I50) | X50: =IF(J50=0,"***",Q50/J50) | Y50: =IF(K50=0,"***",R50/K50) | Z50: =IF(L50=0,"***",S50/L50) | AA50: =IF(Y50="***","***",Z50-X50) | AB50: =IF(Z50="***","***",Z50-X50)

Sheet BACKDATA4月
D1: 2．単月
I3: 2024年4月売上実績 | J3: 2025年4月売上実績 | K3: 2026年4月売上計画 | L3: 2026年4月売上実績 | P3: 2024年4月粗利益実績 | Q3: 2025年4月粗利益実績 | R3: 2026年4月粗利益計画 | S3: 2026年4月粗利益実績 | W3: 2024年4月粗利益率実績 | X3: 2025年4月粗利益率実績 | Y3: 2026年4月粗利益率計画 | Z3: 2026年4月粗利益率実績 | AC3: 作成根拠
M4: 計画比 | N4: 前期比 | O4: 年率 | T4: 計画比 | U4: 前期比 | V4: 年率 | AA4: 計画比 | AB4: 前期比
F5: 石見営業所 | I5: 62274.009 | J5: 65485.854 | K5: 73350 | L5: 86809.298 | M5: =L5-K5 | N5: =L5-J5 | O5: =IF(J5=0,"***",N5/J5) | P5: 16694.301 | Q5: 18670.176 | R5: 19540 | S5: 24673.721 | T5: =S5-R5 | U5: =S5-Q5 | V5: =IF(Q5=0,"***",U5/Q5) | W5: =IF(I5=0,"***",P5/I5) | X5: =IF(J5=0,"***",Q5/J5) | Y5: =IF(K5=0,"***",R5/K5) | Z5: =IF(L5=0,"***",S5/L5) | AA5: =IF(Y5="***","***",Z5-X5) | AB5: =IF(Z5="***","***",Z5-X5)
G6: 営業 | I6: =I5-I9 | J6: =J5-J9 | K6: =K5-K9 | L6: =L5-L9 | M6: =L6-K6 | N6: =L6-J6 | O6: =IF(J6=0,"***",N6/J6) | P6: =P5-P9 | Q6: =Q5-Q9 | R6: =R5-R9 | S6: =S5-S9 | T6: =S6-R6 | U6: =S6-Q6 | V6: =IF(Q6=0,"***",U6/Q6) | W6: =IF(I6=0,"***",P6/I6) | X6: =IF(J6=0,"***",Q6/J6) | Y6: =IF(K6=0,"***",R6/K6) | Z6: =IF(L6=0,"***",S6/L6) | AA6: =IF(Y6="***","***",Z6-X6) | AB6: =IF(Z6="***","***",Z6-X6)
H7: 包装資材 | I7: =I6-I8 | J7: =J6-J8 | K7: =K6-K8 | L7: =L6-L8 | M7: =L7-K7 | N7: =L7-J7 | O7: =IF(J7=0,"***",N7/J7) | P7: =P6-P8 | Q7: =Q6-Q8 | R7: =R6-R8 | S7: =S6-S8 | T7: =S7-R7 | U7: =S7-Q7 | V7: =IF(Q7=0,"***",U7/Q7) | W7: =IF(I7=0,"***",P7/I7) | X7: =IF(J7=0,"***",Q7/J7) | Y7: =IF(K7=0,"***",R7/K7) | Z7: =IF(L7=0,"***",S7/L7) | AA7: =IF(Y7="***","***",Z7-X7) | AB7: =IF(Z7="***","***",Z7-X7)
H8: 機械 | I8: 1423.561 | J8: 1161.392 | K8: 4000 | L8: 1935.36 | M8: =L8-K8 | N8: =L8-J8 | O8: =IF(J8=0,"***",N8/J8) | P8: 264.047 | Q8: 322.742 | R8: 640 | S8: 446.549 | T8: =S8-R8 | U8: =S8-Q8 | V8: =IF(Q8=0,"***",U8/Q8) | W8: =IF(I8=0,"***",P8/I8) | X8: =IF(J8=0,"***",Q8/J8) | Y8: =IF(K8=0,"***",R8/K8) | Z8: =IF(L8=0,"***",S8/L8) | AA8: =IF(Y8="***","***",Z8-X8) | AB8: =IF(Z8="***","***",Z8-X8)
G9: 自治体 | I9: 0.864 | J9: 7.177 | K9: 1340 | L9: 7.177 | M9: =L9-K9 | N9: =L9-J9 | O9: =IF(J9=0,"***",N9/J9) | P9: 0.302 | Q9: 1.664 | R9: 210 | S9: 1.514 | T9: =S9-R9 | U9: =S9-Q9 | V9: =IF(Q9=0,"***",U9/Q9) | W9: =IF(I9=0,"***",P9/I9) | X9: =IF(J9=0,"***",Q9/J9) | Y9: =IF(K9=0,"***",R9/K9) | Z9: =IF(L9=0,"***",S9/L9) | AA9: =IF(Y9="***","***",Z9-X9) | AB9: =IF(Z9="***","***",Z9-X9)
F10: 下関営業所 | I10: 51416.76 | J10: 50408.376 | K10: 53500 | L10: 51889.48 | M10: =L10-K10 | N10: =L10-J10 | O10: =IF(J10=0,"***",N10/J10) | P10: 9989.813 | Q10: 10299.452 | R10: 10800 | S10: 11189.149 | T10: =S10-R10 | U10: =S10-Q10 | V10: =IF(Q10=0,"***",U10/Q10) | W10: =IF(I10=0,"***",P10/I10) | X10: =IF(J10=0,"***",Q10/J10) | Y10: =IF(K10=0,"***",R10/K10) | Z10: =IF(L10=0,"***",S10/L10) | AA10: =IF(Y10="***","***",Z10-X10) | AB10: =IF(Z10="***","***",Z10-X10)
G11: 営業 | I11: =I10-I15-I14 | J11: =J10-J15-J14 | K11: =K10-K15-K14 | L11: =L10-L15-L14 | M11: =L11-K11 | N11: =L11-J11 | O11: =IF(J11=0,"***",N11/J11) | P11: =P10-P15-P14 | Q11: =Q10-Q15-Q14 | R11: =R10-R15-R14 | S11: =S10-S15-S14 | T11: =S11-R11 | U11: =S11-Q11 | V11: =IF(Q11=0,"***",U11/Q11) | W11: =IF(I11=0,"***",P11/I11) | X11: =IF(J11=0,"***",Q11/J11) | Y11: =IF(K11=0,"***",R11/K11) | Z11: =IF(L11=0,"***",S11/L11) | AA11: =IF(Y11="***","***",Z11-X11) | AB11: =IF(Z11="***","***",Z11-X11)
H12: 包装資材 | I12: =I11-I13 | J12: =J11-J13 | K12: =K11-K13 | L12: =L11-L13 | M12: =L12-K12 | N12: =L12-J12 | O12: =IF(J12=0,"***",N12/J12) | P12: =P11-P13 | Q12: =Q11-Q13 | R12: =R11-R13 | S12: =S11-S13 | T12: =S12-R12 | U12: =S12-Q12 | V12: =IF(Q12=0,"***",U12/Q12) | W12: =IF(I12=0,"***",P12/I12) | X12: =IF(J12=0,"***",Q12/J12) | Y12: =IF(K12=0,"***",R12/K12) | Z12: =IF(L12=0,"***",S12/L12) | AA12: =IF(Y12="***","***",Z12-X12) | AB12: =IF(Z12="***","***",Z12-X12)
H13: 機械 | I13: 465 | J13: 2645 | K13: 3740 | L13: 685.95 | M13: =L13-K13 | N13: =L13-J13 | O13: =IF(J13=0,"***",N13/J13) | P13: 81 | Q13: 290 | R13: 520 | S13: 104.49 | T13: =S13-R13 | U13: =S13-Q13 | V13: =IF(Q13=0,"***",U13/Q13) | W13: =IF(I13=0,"***",P13/I13) | X13: =IF(J13=0,"***",Q13/J13) | Y13: =IF(K13=0,"***",R13/K13) | Z13: =IF(L13=0,"***",S13/L13) | AA13: =IF(Y13="***","***",Z13-X13) | AB13: =IF(Z13="***","***",Z13-X13)
G14: 自治体 | I14: 0 | J14: 0 | K14: 0 | L14: 0 | M14: =L14-K14 | N14: =L14-J14 | O14: =IF(J14=0,"***",N14/J14) | P14: 0 | Q14: 0 | R14: 0 | S14: 0 | T14: =S14-R14 | U14: =S14-Q14 | V14: =IF(Q14=0,"***",U14/Q14) | W14: =IF(I14=0,"***",P14/I14) | X14: =IF(J14=0,"***",Q14/J14) | Y14: =IF(K14=0,"***",R14/K14) | Z14: =IF(L14=0,"***",S14/L14)
G15: 海外 | I15: 3244.418 | J15: 0 | K15: 0 | L15: 0 | M15: =L15-K15 | N15: =L15-J15 | O15: =IF(J15=0,"***",N15/J15) | P15: 177.043 | Q15: 0 | R15: 0 | S15: 0 | T15: =S15-R15 | U15: =S15-Q15 | V15: =IF(Q15=0,"***",U15/Q15) | W15: =IF(I15=0,"***",P15/I15) | X15: =IF(J15=0,"***",Q15/J15) | Y15: =IF(K15=0,"***",R15/K15) | Z15: =IF(L15=0,"***",S15/L15) | AA15: =IF(Y15="***","***",Z15-X15) | AB15: =IF(Z15="***","***",Z15-X15)
F16: 松江営業所 | I16: 35939.496 | J16: 40867.319 | K16: 32650 | L16: 40383.262 | M16: =L16-K16 | N16: =L16-J16 | O16: =IF(J16=0,"***",N16/J16) | P16: 7080.551 | Q16: 8820.783 | R16: 8630 | S16: 10567.872 | T16: =S16-R16 | U16: =S16-Q16 | V16: =IF(Q16=0,"***",U16/Q16) | W16: =IF(I16=0,"***",P16/I16) | X16: =IF(J16=0,"***",Q16/J16) | Y16: =IF(K16=0,"***",R16/K16) | Z16: =IF(L16=0,"***",S16/L16) | AA16: =IF(Y16="***","***",Z16-X16) | AB16: =IF(Z16="***","***",Z16-X16)
G17: 営業 | I17: =I16-I20 | J17: =J16-J20 | K17: =K16-K20 | L17: =L16-L20 | M17: =L17-K17 | N17: =L17-J17 | O17: =IF(J17=0,"***",N17/J17) | P17: =P16-P20 | Q17: =Q16-Q20 | R17: =R16-R20 | S17: =S16-S20 | T17: =S17-R17 | U17: =S17-Q17 | V17: =IF(Q17=0,"***",U17/Q17) | W17: =IF(I17=0,"***",P17/I17) | X17: =IF(J17=0,"***",Q17/J17) | Y17: =IF(K17=0,"***",R17/K17) | Z17: =IF(L17=0,"***",S17/L17) | AA17: =IF(Y17="***","***",Z17-X17) | AB17: =IF(Z17="***","***",Z17-X17)
H18: 包装資材 | I18: =I17-I19 | J18: =J17-J19 | K18: =K17-K19 | L18: =L17-L19 | M18: =L18-K18 | N18: =L18-J18 | O18: =IF(J18=0,"***",N18/J18) | P18: =P17-P19 | Q18: =Q17-Q19 | R18: =R17-R19 | S18: =S17-S19 | T18: =S18-R18 | U18: =S18-Q18 | V18: =IF(Q18=0,"***",U18/Q18) | W18: =IF(I18=0,"***",P18/I18) | X18: =IF(J18=0,"***",Q18/J18) | Y18: =IF(K18=0,"***",R18/K18) | Z18: =IF(L18=0,"***",S18/L18) | AA18: =IF(Y18="***","***",Z18-X18) | AB18: =IF(Z18="***","***",Z18-X18)
H19: 機械 | I19: 763 | J19: 881 | K19: 500 | L19: 1167.469 | M19: =L19-K19 | N19: =L19-J19 | O19: =IF(J19=0,"***",N19/J19) | P19: 175 | Q19: 173 | R19: 120 | S19: 228.819 | T19: =S19-R19 | U19: =S19-Q19 | V19: =IF(Q19=0,"***",U19/Q19) | W19: =IF(I19=0,"***",P19/I19) | X19: =IF(J19=0,"***",Q19/J19) | Y19: =IF(K19=0,"***",R19/K19) | Z19: =IF(L19=0,"***",S19/L19) | AA19: =IF(Y19="***","***",Z19-X19) | AB19: =IF(Z19="***","***",Z19-X19)
G20: 自治体 | I20: 8514.45 | J20: 9358.208 | K20: 0 | L20: 0 | M20: =L20-K20 | N20: =L20-J20 | O20: =IF(J20=0,"***",N20/J20) | P20: 154.3 | Q20: 173.928 | R20: 0 | S20: 0 | T20: =S20-R20 | U20: =S20-Q20 | V20: =IF(Q20=0,"***",U20/Q20) | W20: =IF(I20=0,"***",P20/I20) | X20: =IF(J20=0,"***",Q20/J20) | Y20: =IF(K20=0,"***",R20/K20) | Z20: =IF(L20=0,"***",S20/L20) | AA20: =IF(Y20="***","***",Z20-X20) | AB20: =IF(Z20="***","***",Z20-X20)
F21: 広域営業部 | I21: 33822.751 | J21: 46780.858 | K21: 47900 | L21: 42974 | M21: =L21-K21 | N21: =L21-J21 | O21: =IF(J21=0,"***",N21/J21) | P21: 5158.48 | Q21: 7453.164 | R21: 7125 | S21: 6723 | T21: =S21-R21 | U21: =S21-Q21 | V21: =IF(Q21=0,"***",U21/Q21) | W21: =IF(I21=0,"***",P21/I21) | X21: =IF(J21=0,"***",Q21/J21) | Y21: =IF(K21=0,"***",R21/K21) | Z21: =IF(L21=0,"***",S21/L21) | AA21: =IF(Y21="***","***",Z21-X21) | AB21: =IF(Z21="***","***",Z21-X21)
H22: 包装資材 | I22: =I21-I23 | J22: =J21-J23 | K22: =K21-K23 | L22: =L21-L23 | M22: =L22-K22 | N22: =L22-J22 | O22: =IF(J22=0,"***",N22/J22) | P22: =P21-P23 | Q22: =Q21-Q23 | R22: =R21-R23 | S22: =S21-S23 | T22: =S22-R22 | U22: =S22-Q22 | V22: =IF(Q22=0,"***",U22/Q22) | W22: =IF(I22=0,"***",P22/I22) | X22: =IF(J22=0,"***",Q22/J22) | Y22: =IF(K22=0,"***",R22/K22) | Z22: =IF(L22=0,"***",S22/L22) | AA22: =IF(Y22="***","***",Z22-X22) | AB22: =IF(Z22="***","***",Z22-X22)
H23: 機械 | I23: 55 | J23: 160 | K23: 1000 | L23: 122.985 | M23: =L23-K23 | N23: =L23-J23 | O23: =IF(J23=0,"***",N23/J23) | P23: 6 | Q23: 41 | R23: 110 | S23: 14.825 | T23: =S23-R23 | U23: =S23-Q23 | V23: =IF(Q23=0,"***",U23/Q23) | W23: =IF(I23=0,"***",P23/I23) | X23: =IF(J23=0,"***",Q23/J23) | Y23: =IF(K23=0,"***",R23/K23) | Z23: =IF(L23=0,"***",S23/L23) | AA23: =IF(Y23="***","***",Z23-X23) | AB23: =IF(Z23="***","***",Z23-X23)
G24: リンガーハット | I24: 24579.713 | J24: 29836.46 | K24: 28522.273 | L24: 29321.996 | M24: =L24-K24 | N24: =L24-J24 | O24: =IF(J24=0,"***",N24/J24) | P24: 3729.805 | Q24: 4812.843 | R24: 4542.083 | S24: 4712.731 | T24: =S24-R24 | U24: =S24-Q24 | V24: =IF(Q24=0,"***",U24/Q24) | W24: =IF(I24=0,"***",P24/I24) | X24: =IF(J24=0,"***",Q24/J24) | Y24: =IF(K24=0,"***",R24/K24) | Z24: =IF(L24=0,"***",S24/L24) | AA24: =IF(Y24="***","***",Z24-X24) | AB24: =IF(Z24="***","***",Z24-X24)
H25: 包装資材 | I25: =I24-I26 | J25: =J24-J26 | K25: =K24-K26 | L25: =L24-L26 | M25: =L25-K25 | N25: =L25-J25 | O25: =IF(J25=0,"***",N25/J25) | P25: =P24-P26 | Q25: =Q24-Q26 | R25: =R24-R26 | S25: =S24-S26 | T25: =S25-R25 | U25: =S25-Q25 | V25: =IF(Q25=0,"***",U25/Q25) | W25: =IF(I25=0,"***",P25/I25) | X25: =IF(J25=0,"***",Q25/J25) | Y25: =IF(K25=0,"***",R25/K25) | Z25: =IF(L25=0,"***",S25/L25) | AA25: =IF(Y25="***","***",Z25-X25) | AB25: =IF(Z25="***","***",Z25-X25)
H26: 機械 | I26: 22 | J26: 49 | K26: 42.25 | L26: 44 | M26: =L26-K26 | N26: =L26-J26 | O26: =IF(J26=0,"***",N26/J26) | P26: 1 | Q26: 0 | R26: 0.25 | S26: 2.8 | T26: =S26-R26 | U26: =S26-Q26 | V26: =IF(Q26=0,"***",U26/Q26) | W26: =IF(I26=0,"***",P26/I26) | X26: =IF(J26=0,"***",Q26/J26) | Y26: =IF(K26=0,"***",R26/K26) | Z26: =IF(L26=0,"***",S26/L26) | AA26: =IF(Y26="***","***",Z26-X26) | AB26: =IF(Z26="***","***",Z26-X26)
G27: リンガーハット以外 | I27: =I21-I24 | J27: =J21-J24 | K27: =K21-K24 | L27: =L21-L24 | M27: =L27-K27 | N27: =L27-J27 | O27: =IF(J27=0,"***",N27/J27) | P27: =P21-P24 | Q27: =Q21-Q24 | R27: =R21-R24 | S27: =S21-S24 | T27: =S27-R27 | U27: =S27-Q27 | V27: =IF(Q27=0,"***",U27/Q27) | W27: =IF(I27=0,"***",P27/I27) | X27: =IF(J27=0,"***",Q27/J27) | Y27: =IF(K27=0,"***",R27/K27) | Z27: =IF(L27=0,"***",S27/L27) | AA27: =IF(Y27="***","***",Z27-X27) | AB27: =IF(Z27="***","***",Z27-X27)
H28: 包装資材 | I28: =I27-I29 | J28: =J27-J29 | K28: =K27-K29 | L28: =L27-L29 | M28: =L28-K28 | N28: =L28-J28 | O28: =IF(J28=0,"***",N28/J28) | P28: =P27-P29 | Q28: =Q27-Q29 | R28: =R27-R29 | S28: =S27-S29 | T28: =S28-R28 | U28: =S28-Q28 | V28: =IF(Q28=0,"***",U28/Q28) | W28: =IF(I28=0,"***",P28/I28) | X28: =IF(J28=0,"***",Q28/J28) | Y28: =IF(K28=0,"***",R28/K28) | Z28: =IF(L28=0,"***",S28/L28) | AA28: =IF(Y28="***","***",Z28-X28) | AB28: =IF(Z28="***","***",Z28-X28)
H29: 機械 | I29: =I23-I26 | J29: =J23-J26 | K29: =K23-K26 | L29: =L23-L26 | M29: =L29-K29 | N29: =L29-J29 | O29: =IF(J29=0,"***",N29/J29) | P29: =P23-P26 | Q29: =Q23-Q26 | R29: =R23-R26 | S29: =S23-S26 | T29: =S29-R29 | U29: =S29-Q29 | V29: =IF(Q29=0,"***",U29/Q29) | W29: =IF(I29=0,"***",P29/I29) | X29: =IF(J29=0,"***",Q29/J29) | Y29: =IF(K29=0,"***",R29/K29) | Z29: =IF(L29=0,"***",S29/L29) | AA29: =IF(Y29="***","***",Z29-X29) | AB29: =IF(Z29="***","***",Z29-X29)
F30: 境港営業所 | I30: 47632.931 | J30: 46473.538 | K30: 76460 | L30: 66639.678 | M30: =L30-K30 | N30: =L30-J30 | O30: =IF(J30=0,"***",N30/J30) | P30: 8611.374 | Q30: 8849.599 | R30: 13390 | S30: 11081.419 | T30: =S30-R30 | U30: =S30-Q30 | V30: =IF(Q30=0,"***",U30/Q30) | W30: =IF(I30=0,"***",P30/I30) | X30: =IF(J30=0,"***",Q30/J30) | Y30: =IF(K30=0,"***",R30/K30) | Z30: =IF(L30=0,"***",S30/L30) | AA30: =IF(Y30="***","***",Z30-X30) | AB30: =IF(Z30="***","***",Z30-X30)
G31: 営業 | I31: =I30-I35-I34 | J31: =J30-J35-J34 | K31: =K30-K35-K34 | L31: =L30-L35-L34 | M31: =L31-K31 | N31: =L31-J31 | O31: =IF(J31=0,"***",N31/J31) | P31: =P30-P35-P34 | Q31: =Q30-Q35-Q34 | R31: =R30-R35-R34 | S31: =S30-S35-S34 | T31: =S31-R31 | U31: =S31-Q31 | V31: =IF(Q31=0,"***",U31/Q31) | W31: =IF(I31=0,"***",P31/I31) | X31: =IF(J31=0,"***",Q31/J31) | Y31: =IF(K31=0,"***",R31/K31) | Z31: =IF(L31=0,"***",S31/L31) | AA31: =IF(Y31="***","***",Z31-X31) | AB31: =IF(Z31="***","***",Z31-X31)
H32: 包装資材 | I32: =I31-I33 | J32: =J31-J33 | K32: =K31-K33 | L32: =L31-L33 | M32: =L32-K32 | N32: =L32-J32 | O32: =IF(J32=0,"***",N32/J32) | P32: =P31-P33 | Q32: =Q31-Q33 | R32: =R31-R33 | S32: =S31-S33 | T32: =S32-R32 | U32: =S32-Q32 | V32: =IF(Q32=0,"***",U32/Q32) | W32: =IF(I32=0,"***",P32/I32) | X32: =IF(J32=0,"***",Q32/J32) | Y32: =IF(K32=0,"***",R32/K32) | Z32: =IF(L32=0,"***",S32/L32) | AA32: =IF(Y32="***","***",Z32-X32) | AB32: =IF(Z32="***","***",Z32-X32)
H33: 機械 | I33: 9281 | J33: 2643 | K33: 28100 | L33: 22304.8 | M33: =L33-K33 | N33: =L33-J33 | O33: =IF(J33=0,"***",N33/J33) | P33: 1969 | Q33: 791 | R33: 4320 | S33: 3097.852 | T33: =S33-R33 | U33: =S33-Q33 | V33: =IF(Q33=0,"***",U33/Q33) | W33: =IF(I33=0,"***",P33/I33) | X33: =IF(J33=0,"***",Q33/J33) | Y33: =IF(K33=0,"***",R33/K33) | Z33: =IF(L33=0,"***",S33/L33) | AA33: =IF(Y33="***","***",Z33-X33) | AB33: =IF(Z33="***","***",Z33-X33)
G34: 自治体 | I34: 0 | J34: 0 | K34: 0 | L34: 0 | M34: =L34-K34 | N34: =L34-J34 | O34: =IF(J34=0,"***",N34/J34) | P34: 0 | Q34: 0 | R34: 0 | S34: 0 | T34: =S34-R34 | U34: =S34-Q34 | V34: =IF(Q34=0,"***",U34/Q34) | W34: =IF(I34=0,"***",P34/I34) | X34: =IF(J34=0,"***",Q34/J34) | Y34: =IF(K34=0,"***",R34/K34) | Z34: =IF(L34=0,"***",S34/L34) | AA34: =IF(Y34="***","***",Z34-X34) | AB34: =IF(Z34="***","***",Z34-X34)
G35: 海外 | I35: 462.725 | J35: 1833.894 | K35: 1230 | L35: 2165.5 | M35: =L35-K35 | N35: =L35-J35 | O35: =IF(J35=0,"***",N35/J35) | P35: 127.104 | Q35: 326.979 | R35: 260 | S35: 413.203 | T35: =S35-R35 | U35: =S35-Q35 | V35: =IF(Q35=0,"***",U35/Q35) | W35: =IF(I35=0,"***",P35/I35) | X35: =IF(J35=0,"***",Q35/J35) | Y35: =IF(K35=0,"***",R35/K35) | Z35: =IF(L35=0,"***",S35/L35) | AA35: =IF(Y35="***","***",Z35-X35) | AB35: =IF(Z35="***","***",Z35-X35)
E36: 営業部門合計 | I36: =I30+I21+I16+I10+I5 | J36: =J30+J21+J16+J10+J5 | K36: =K30+K21+K16+K10+K5 | L36: =L30+L21+L16+L10+L5 | M36: =L36-K36 | N36: =L36-J36 | O36: =IF(J36=0,"***",N36/J36) | P36: =P30+P21+P16+P10+P5 | Q36: =Q30+Q21+Q16+Q10+Q5 | R36: =R30+R21+R16+R10+R5 | S36: =S30+S21+S16+S10+S5 | T36: =S36-R36 | U36: =S36-Q36 | V36: =IF(Q36=0,"***",U36/Q36) | W36: =IF(I36=0,"***",P36/I36) | X36: =IF(J36=0,"***",Q36/J36) | Y36: =IF(K36=0,"***",R36/K36) | Z36: =IF(L36=0,"***",S36/L36) | AA36: =IF(Y36="***","***",Z36-X36) | AB36: =IF(Z36="***","***",Z36-X36)
H37: 機械以外 | I37: =I36-I38-I39-I40 | J37: =J36-J38-J39-J40 | K37: =K36-K38-K39-K40 | L37: =L36-L38-L39-L40 | M37: =L37-K37 | N37: =L37-J37 | O37: =IF(J37=0,"***",N37/J37) | P37: =P36-P38-P39-P40 | Q37: =Q36-Q38-Q39-Q40 | R37: =R36-R38-R39-R40 | S37: =S36-S38-S39-S40 | T37: =S37-R37 | U37: =S37-Q37 | V37: =IF(Q37=0,"***",U37/Q37) | W37: =IF(I37=0,"***",P37/I37) | X37: =IF(J37=0,"***",Q37/J37) | Y37: =IF(K37=0,"***",R37/K37) | Z37: =IF(L37=0,"***",S37/L37) | AA37: =IF(Y37="***","***",Z37-X37) | AB37: =IF(Z37="***","***",Z37-X37)
H38: 機械 | I38: =I33+I23+I19+I13+I8 | J38: =J33+J23+J19+J13+J8 | K38: =K33+K23+K19+K13+K8 | L38: =L33+L23+L19+L13+L8 | M38: =L38-K38 | N38: =L38-J38 | O38: =IF(J38=0,"***",N38/J38) | P38: =P33+P23+P19+P13+P8 | Q38: =Q33+Q23+Q19+Q13+Q8 | R38: =R33+R23+R19+R13+R8 | S38: =S33+S23+S19+S13+S8 | T38: =S38-R38 | U38: =S38-Q38 | V38: =IF(Q38=0,"***",U38/Q38) | W38: =IF(I38=0,"***",P38/I38) | X38: =IF(J38=0,"***",Q38/J38) | Y38: =IF(K38=0,"***",R38/K38) | Z38: =IF(L38=0,"***",S38/L38) | AA38: =IF(Y38="***","***",Z38-X38) | AB38: =IF(Z38="***","***",Z38-X38)
H39: 自治体 | I39: =I34+I20+I14+I9 | J39: =J34+J20+J14+J9 | K39: =K34+K20+K14+K9 | L39: =L34+L20+L14+L9 | M39: =L39-K39 | N39: =L39-J39 | O39: =IF(J39=0,"***",N39/J39) | P39: =P34+P20+P14+P9 | Q39: =Q34+Q20+Q14+Q9 | R39: =R34+R20+R14+R9 | S39: =S34+S20+S14+S9 | T39: =S39-R39 | U39: =S39-Q39 | V39: =IF(Q39=0,"***",U39/Q39) | W39: =IF(I39=0,"***",P39/I39) | X39: =IF(J39=0,"***",Q39/J39) | Y39: =IF(K39=0,"***",R39/K39) | Z39: =IF(L39=0,"***",S39/L39) | AA39: =IF(Y39="***","***",Z39-X39) | AB39: =IF(Z39="***","***",Z39-X39)
H40: 海外 | I40: =I35+I15 | J40: =J35+J15 | K40: =K35+K15 | L40: =L35+L15 | M40: =L40-K40 | N40: =L40-J40 | O40: =IF(J40=0,"***",N40/J40) | P40: =P35+P15 | Q40: =Q35+Q15 | R40: =R35+R15 | S40: =S35+S15 | T40: =S40-R40 | U40: =S40-Q40 | V40: =IF(Q40=0,"***",U40/Q40) | W40: =IF(I40=0,"***",P40/I40) | X40: =IF(J40=0,"***",Q40/J40) | Y40: =IF(K40=0,"***",R40/K40) | Z40: =IF(L40=0,"***",S40/L40) | AA40: =IF(Y40="***","***",Z40-X40) | AB40: =IF(Z40="***","***",Z40-X40)
E41: 水産部 | I41: 44155.16 | J41: 35119.998 | K41: 41800 | L41: 56225 | M41: =L41-K41 | N41: =L41-J41 | O41: =IF(J41=0,"***",N41/J41) | P41: 11564.993 | Q41: 10444.797 | R41: 13420 | S41: 16777 | T41: =S41-R41 | U41: =S41-Q41 | V41: =IF(Q41=0,"***",U41/Q41) | W41: =IF(I41=0,"***",P41/I41) | X41: =IF(J41=0,"***",Q41/J41) | Y41: =IF(K41=0,"***",R41/K41) | Z41: =IF(L41=0,"***",S41/L41) | AA41: =IF(Y41="***","***",Z41-X41) | AB41: =IF(Z41="***","***",Z41-X41)
H42: 包装資材 | I42: =I41-I43-I44 | J42: =J41-J43-J44 | K42: =K41-K43-K44 | L42: =L41-L43-L44 | M42: =L42-K42 | N42: =L42-J42 | O42: =IF(J42=0,"***",N42/J42) | P42: =P41-P43-P44 | Q42: =Q41-Q43-Q44 | R42: =R41-R43-R44 | S42: =S41-S43-S44 | T42: =S42-R42 | U42: =S42-Q42 | V42: =IF(Q42=0,"***",U42/Q42) | W42: =IF(I42=0,"***",P42/I42) | X42: =IF(J42=0,"***",Q42/J42) | Y42: =IF(K42=0,"***",R42/K42) | Z42: =IF(L42=0,"***",S42/L42) | AA42: =IF(Y42="***","***",Z42-X42) | AB42: =IF(Z42="***","***",Z42-X42)
H43: 荷役 | I43: 8574.503 | J43: 5954.985 | K43: 7790 | L43: 5509.048 | M43: =L43-K43 | N43: =L43-J43 | O43: =IF(J43=0,"***",N43/J43) | P43: 4902.688 | Q43: 3451.535 | R43: 4630 | S43: 3761.495 | T43: =S43-R43 | U43: =S43-Q43 | V43: =IF(Q43=0,"***",U43/Q43) | W43: =IF(I43=0,"***",P43/I43) | X43: =IF(J43=0,"***",Q43/J43) | Y43: =IF(K43=0,"***",R43/K43) | Z43: =IF(L43=0,"***",S43/L43)
H44: 機械 | I44: 22 | J44: 296.05 | K44: 90 | L44: 100 | M44: =L44-K44 | N44: =L44-J44 | O44: =IF(J44=0,"***",N44/J44) | P44: 2.2 | Q44: 44.57 | R44: 20 | S44: 21 | T44: =S44-R44 | U44: =S44-Q44 | V44: =IF(Q44=0,"***",U44/Q44) | W44: =IF(I44=0,"***",P44/I44) | X44: =IF(J44=0,"***",Q44/J44) | Y44: =IF(K44=0,"***",R44/K44) | Z44: =IF(L44=0,"***",S44/L44) | AA44: =IF(Y44="***","***",Z44-X44) | AB44: =IF(Z44="***","***",Z44-X44)
D45: 合計 | I45: =I41+I36 | J45: =J41+J36 | K45: =K41+K36 | L45: =L41+L36 | M45: =L45-K45 | N45: =L45-J45 | O45: =IF(J45=0,"***",N45/J45) | P45: =P41+P36 | Q45: =Q41+Q36 | R45: =R41+R36 | S45: =S41+S36 | T45: =S45-R45 | U45: =S45-Q45 | V45: =IF(Q45=0,"***",U45/Q45) | W45: =IF(I45=0,"***",P45/I45) | X45: =IF(J45=0,"***",Q45/J45) | Y45: =IF(K45=0,"***",R45/K45) | Z45: =IF(L45=0,"***",S45/L45) | AA45: =IF(Y45="***","***",Z45-X45) | AB45: =IF(Z45="***","***",Z45-X45)
H46: 機械以外 | I46: =I45-I47 | J46: =J45-J47 | K46: =K45-K47 | L46: =L45-L47 | M46: =L46-K46 | N46: =L46-J46 | O46: =IF(J46=0,"***",N46/J46) | P46: =P45-P47 | Q46: =Q45-Q47 | R46: =R45-R47 | S46: =S45-S47 | T46: =S46-R46 | U46: =S46-Q46 | V46: =IF(Q46=0,"***",U46/Q46) | W46: =IF(I46=0,"***",P46/I46) | X46: =IF(J46=0,"***",Q46/J46) | Y46: =IF(K46=0,"***",R46/K46) | Z46: =IF(L46=0,"***",S46/L46) | AA46: =IF(Y46="***","***",Z46-X46) | AB46: =IF(Z46="***","***",Z46-X46)
H47: 機械 | I47: =I38+I44 | J47: =J38+J44 | K47: =K38+K44 | L47: =L38+L44 | M47: =L47-K47 | N47: =L47-J47 | O47: =IF(J47=0,"***",N47/J47) | P47: =P38+P44 | Q47: =Q38+Q44 | R47: =R38+R44 | S47: =S38+S44 | T47: =S47-R47 | U47: =S47-Q47 | V47: =IF(Q47=0,"***",U47/Q47) | W47: =IF(I47=0,"***",P47/I47) | X47: =IF(J47=0,"***",Q47/J47) | Y47: =IF(K47=0,"***",R47/K47) | Z47: =IF(L47=0,"***",S47/L47) | AA47: =IF(Y47="***","***",Z47-X47) | AB47: =IF(Z47="***","***",Z47-X47)
H48: 自治体 | I48: =I39 | J48: =J39 | K48: =K39 | L48: =L39 | M48: =L48-K48 | N48: =L48-J48 | O48: =IF(J48=0,"***",N48/J48) | P48: =P39 | Q48: =Q39 | R48: =R39 | S48: =S39 | T48: =S48-R48 | U48: =S48-Q48 | V48: =IF(Q48=0,"***",U48/Q48) | W48: =IF(I48=0,"***",P48/I48) | X48: =IF(J48=0,"***",Q48/J48) | Y48: =IF(K48=0,"***",R48/K48) | Z48: =IF(L48=0,"***",S48/L48) | AA48: =IF(Y48="***","***",Z48-X48) | AB48: =IF(Z48="***","***",Z48-X48)
H49: 海外 | I49: =I40 | J49: =J40 | K49: =K40 | L49: =L40 | M49: =L49-K49 | N49: =L49-J49 | O49: =IF(J49=0,"***",N49/J49) | P49: =P40 | Q49: =Q40 | R49: =R40 | S49: =S40 | T49: =S49-R49 | U49: =S49-Q49 | V49: =IF(Q49=0,"***",U49/Q49) | W49: =IF(I49=0,"***",P49/I49) | X49: =IF(J49=0,"***",Q49/J49) | Y49: =IF(K49=0,"***",R49/K49) | Z49: =IF(L49=0,"***",S49/L49) | AA49: =IF(Y49="***","***",Z49-X49) | AB49: =IF(Z49="***","***",Z49-X49)
D50: キョウワ（税抜） | I50: 1780 | J50: 2540 | K50: 2100 | L50: 1899 | M50: =L50-K50 | N50: =L50-J50 | O50: =IF(J50=0,"***",N50/J50) | P50: 950 | Q50: 1560 | R50: 1220 | S50: 1242 | T50: =S50-R50 | U50: =S50-Q50 | V50: =IF(Q50=0,"***",U50/Q50) | W50: =IF(I50=0,"***",P50/I50) | X50: =IF(J50=0,"***",Q50/J50) | Y50: =IF(K50=0,"***",R50/K50) | Z50: =IF(L50=0,"***",S50/L50) | AA50: =IF(Y50="***","***",Z50-X50) | AB50: =IF(Z50="***","***",Z50-X50)

Sheet BACKDATA上期
D1: 1．上期
I3: 2023年10月売上実績 | J3: 2024年10月売上実績 | K3: 2025年10月売上計画 | L3: 2025年10月売上実績 | P3: 2023年10月粗利益実績 | Q3: 2024年10月粗利益実績 | R3: 2025年10月粗利益計画 | S3: 2025年10月粗利益実績 | W3: 2023年11月売上実績 | X3: 2024年11月売上実績 | Y3: 2025年11月売上計画 | Z3: 2025年11月売上実績 | AD3: 2023年11月粗利益実績 | AE3: 2024年11月粗利益実績 | AF3: 2025年11月粗利益計画 | AG3: 2025年11月粗利益実績 | AK3: 2023年12月売上実績 | AL3: 2024年12月売上実績 | AM3: 2025年12月売上計画 | AN3: 2025年12月売上実績 | AR3: 2023年12月粗利益実績 | AS3: 2024年12月粗利益実績 | AT3: 2025年12月粗利益計画 | AU3: 2025年12月粗利益実績 | AY3: 2024年1月売上実績 | AZ3: 2025年1月売上実績 | BA3: 2026年1月売上計画 | BB3: 2026年1月売上実績 | BF3: 2024年1月粗利益実績 | BG3: 2025年1月粗利益実績 | BH3: 2026年1月粗利益計画 | BI3: 2026年1月粗利益実績 | BM3: 2024年2月売上実績 | BN3: 2025年2月売上実績 | BO3: 2026年2月売上計画 | BP3: 2026年2月売上実績 | BT3: 2024年2月粗利益実績 | BU3: 2025年2月粗利益実績 | BV3: 2026年2月粗利益計画 | BW3: 2026年2月粗利益実績 | CA3: 2024年3月売上実績 | CB3: 2025年3月売上実績 | CC3: 2026年3月売上計画 | CD3: 2026年3月売上実績 | CH3: 2024年3月粗利益実績 | CI3: 2025年3月粗利益実績 | CJ3: 2026年3月粗利益計画 | CK3: 2026年3月粗利益実績 | CO3: 2024年3月売上実績 | CP3: 2025年3月売上実績 | CQ3: 2026年3月売上計画 | CR3: 2026年3月売上実績 | CV3: 2024年3月粗利益実績 | CW3: 2025年3月粗利益実績 | CX3: 2026年3月粗利益計画 | CY3: 2026年3月粗利益実績 | DC3: 2024年3月粗利益率実績 | DD3: 2025年3月粗利益率実績 | DE3: 2026年3月粗利益率計画 | DF3: 2026年3月粗利益率実績 | DI3: 作成根拠
M4: 計画比 | N4: 前期比 | O4: 年率 | T4: 計画比 | U4: 前期比 | V4: 年率 | AA4: 計画比 | AB4: 前期比 | AC4: 年率 | AH4: 計画比 | AI4: 前期比 | AJ4: 年率 | AO4: 計画比 | AP4: 前期比 | AQ4: 年率 | AV4: 計画比 | AW4: 前期比 | AX4: 年率 | BC4: 計画比 | BD4: 前期比 | BE4: 年率 | BJ4: 計画比 | BK4: 前期比 | BL4: 年率 | BQ4: 計画比 | BR4: 前期比 | BS4: 年率 | BX4: 計画比 | BY4: 前期比 | BZ4: 年率 | CE4: 計画比 | CF4: 前期比 | CG4: 年率 | CL4: 計画比 | CM4: 前期比 | CN4: 年率 | CS4: 計画比 | CT4: 前期比 | CU4: 年率 | CZ4: 計画比 | DA4: 前期比 | DB4: 年率 | DG4: 計画比 | DH4: 前期比
F5: 石見営業所 | I5: 67452 | J5: 70743 | K5: 75500 | L5: 74777 | M5: =L5-K5 | N5: =L5-J5 | O5: =IF(J5=0,"***",N5/J5) | P5: 18120 | Q5: 20002 | R5: 20280 | S5: 19993 | T5: =S5-R5 | U5: =S5-Q5 | V5: =IF(Q5=0,"***",U5/Q5) | W5: 78664 | X5: 70771 | Y5: 79300 | Z5: 81052 | AA5: =Z5-Y5 | AB5: =Z5-X5 | AC5: =IF(X5=0,"***",AB5/X5) | AD5: 19895 | AE5: 20030 | AF5: 21180 | AG5: 20184 | AH5: =AG5-AF5 | AI5: =AG5-AE5 | AJ5: =IF(AE5=0,"***",AI5/AE5) | AK5: 91866 | AL5: 86678 | AM5: 89600 | AN5: 90533 | AO5: =AN5-AM5 | AP5: =AN5-AL5 | AQ5: =IF(AL5=0,"***",AP5/AL5) | AR5: 23668 | AS5: 25002 | AT5: 24580 | AU5: 25480 | AV5: =AU5-AT5 | AW5: =AU5-AS5 | AX5: =IF(AS5=0,"***",AW5/AS5) | AY5: 51270 | AZ5: 56734 | BA5: 58700 | BB5: 55809 | BC5: =BB5-BA5 | BD5: =BB5-AZ5 | BE5: =IF(AZ5=0,"***",BD5/AZ5) | BF5: 13178 | BG5: 15391 | BH5: 15280 | BI5: 14550 | BJ5: =BI5-BH5 | BK5: =BI5-BG5 | BL5: =IF(BG5=0,"***",BK5/BG5) | BM5: 56011 | BN5: 53633 | BO5: 63700 | BP5: 62695 | BQ5: =BP5-BO5 | BR5: =BP5-BN5 | BS5: =IF(BN5=0,"***",BR5/BN5) | BT5: 16465 | BU5: 14909 | BV5: 17280 | BW5: 16492 | BX5: =BW5-BV5 | BY5: =BW5-BU5 | BZ5: =IF(BU5=0,"***",BY5/BU5) | CA5: 61246 | CB5: 65865 | CC5: 67300 | CD5: 66160 | CE5: =CD5-CC5 | CF5: =CD5-CB5 | CG5: =IF(CB5=0,"***",CF5/CB5) | CH5: 15768 | CI5: 16972 | CJ5: 17480 | CK5: 18311 | CL5: =CK5-CJ5 | CM5: =CK5-CI5 | CN5: =IF(CI5=0,"***",CM5/CI5) | CO5: 409410 | CP5: 404425 | CQ5: =K5+Y5+AM5+BA5+BO5+CC5 | CR5: =L5+Z5+AN5+BB5+BP5+CD5 | CS5: =CR5-CQ5 | CT5: =CR5-CP5 | CU5: =IF(CP5=0,"***",CT5/CP5) | CV5: 112304 | CW5: 109699 | CX5: =R5+AF5+AT5+BH5+BV5+CJ5 | CY5: =S5+AG5+AU5+BI5+BW5+CK5 | CZ5: =CY5-CX5 | DA5: =CY5-CW5 | DB5: =IF(CW5=0,"***",DA5/CW5) | DC5: =IF(CO5=0,"***",CV5/CO5) | DD5: =IF(CP5=0,"***",CW5/CP5) | DE5: =IF(CQ5=0,"***",CX5/CQ5) | DF5: =IF(CR5=0,"***",CY5/CR5) | DG5: =IF(DE5="***","***",DF5-DD5) | DH5: =IF(DF5="***","***",DF5-DD5) | DI5: 大海移管分（22,889/3,202）はそのまま前期比プラスに寄与
G6: 営業 | I6: =I5-I9 | J6: =J5-J9 | K6: =K5-K9 | L6: =L5-L9 | M6: =L6-K6 | N6: =L6-J6 | O6: =IF(J6=0,"***",N6/J6) | P6: =P5-P9 | Q6: =Q5-Q9 | R6: =R5-R9 | S6: =S5-S9 | T6: =S6-R6 | U6: =S6-Q6 | V6: =IF(Q6=0,"***",U6/Q6) | W6: =W5-W9 | X6: =X5-X9 | Y6: =Y5-Y9 | Z6: =Z5-Z9 | AA6: =Z6-Y6 | AB6: =Z6-X6 | AC6: =IF(X6=0,"***",AB6/X6) | AD6: =AD5-AD9 | AE6: =AE5-AE9 | AF6: =AF5-AF9 | AG6: =AG5-AG9 | AH6: =AG6-AF6 | AI6: =AG6-AE6 | AJ6: =IF(AE6=0,"***",AI6/AE6) | AK6: =AK5-AK9 | AL6: =AL5-AL9 | AM6: =AM5-AM9 | AN6: =AN5-AN9 | AO6: =AN6-AM6 | AP6: =AN6-AL6 | AQ6: =IF(AL6=0,"***",AP6/AL6) | AR6: =AR5-AR9 | AS6: =AS5-AS9 | AT6: =AT5-AT9 | AU6: =AU5-AU9 | AV6: =AU6-AT6 | AW6: =AU6-AS6 | AX6: =IF(AS6=0,"***",AW6/AS6) | AY6: =AY5-AY9 | AZ6: =AZ5-AZ9 | BA6: =BA5-BA9 | BB6: =BB5-BB9 | BC6: =BB6-BA6 | BD6: =BB6-AZ6 | BE6: =IF(AZ6=0,"***",BD6/AZ6) | BF6: =BF5-BF9 | BG6: =BG5-BG9 | BH6: =BH5-BH9 | BI6: =BI5-BI9 | BJ6: =BI6-BH6 | BK6: =BI6-BG6 | BL6: =IF(BG6=0,"***",BK6/BG6) | BM6: =BM5-BM9 | BN6: =BN5-BN9 | BO6: =BO5-BO9 | BP6: =BP5-BP9 | BQ6: =BP6-BO6 | BR6: =BP6-BN6 | BS6: =IF(BN6=0,"***",BR6/BN6) | BT6: =BT5-BT9 | BU6: =BU5-BU9 | BV6: =BV5-BV9 | BW6: =BW5-BW9 | BX6: =BW6-BV6 | BY6: =BW6-BU6 | BZ6: =IF(BU6=0,"***",BY6/BU6) | CA6: =CA5-CA9 | CB6: =CB5-CB9 | CC6: =CC5-CC9 | CD6: =CD5-CD9 | CE6: =CD6-CC6 | CF6: =CD6-CB6 | CG6: =IF(CB6=0,"***",CF6/CB6) | CH6: =CH5-CH9 | CI6: =CI5-CI9 | CJ6: =CJ5-CJ9 | CK6: =CK5-CK9 | CL6: =CK6-CJ6 | CM6: =CK6-CI6 | CN6: =IF(CI6=0,"***",CM6/CI6) | CO6: =CO5-CO9 | CP6: =CP5-CP9 | CQ6: =CQ5-CQ9 | CR6: =CR5-CR9 | CS6: =CR6-CQ6 | CT6: =CR6-CP6 | CU6: =IF(CP6=0,"***",CT6/CP6) | CV6: =CV5-CV9 | CW6: =CW5-CW9 | CX6: =CX5-CX9 | CY6: =CY5-CY9 | CZ6: =CY6-CX6 | DA6: =CY6-CW6 | DB6: =IF(CW6=0,"***",DA6/CW6) | DC6: =IF(CO6=0,"***",CV6/CO6) | DD6: =IF(CP6=0,"***",CW6/CP6) | DE6: =IF(CQ6=0,"***",CX6/CQ6) | DF6: =IF(CR6=0,"***",CY6/CR6) | DG6: =IF(DE6="***","***",DF6-DD6) | DH6: =IF(DF6="***","***",DF6-DD6)
H7: 包装資材 | I7: =I6-I8 | J7: =J6-J8 | K7: =K6-K8 | L7: =L6-L8 | M7: =L7-K7 | N7: =L7-J7 | O7: =IF(J7=0,"***",N7/J7) | P7: =P6-P8 | Q7: =Q6-Q8 | R7: =R6-R8 | S7: =S6-S8 | T7: =S7-R7 | U7: =S7-Q7 | V7: =IF(Q7=0,"***",U7/Q7) | W7: =W6-W8 | X7: =X6-X8 | Y7: =Y6-Y8 | Z7: =Z6-Z8 | AA7: =Z7-Y7 | AB7: =Z7-X7 | AC7: =IF(X7=0,"***",AB7/X7) | AD7: =AD6-AD8 | AE7: =AE6-AE8 | AF7: =AF6-AF8 | AG7: =AG6-AG8 | AH7: =AG7-AF7 | AI7: =AG7-AE7 | AJ7: =IF(AE7=0,"***",AI7/AE7) | AK7: =AK6-AK8 | AL7: =AL6-AL8 | AM7: =AM6-AM8 | AN7: =AN6-AN8 | AO7: =AN7-AM7 | AP7: =AN7-AL7 | AQ7: =IF(AL7=0,"***",AP7/AL7) | AR7: =AR6-AR8 | AS7: =AS6-AS8 | AT7: =AT6-AT8 | AU7: =AU6-AU8 | AV7: =AU7-AT7 | AW7: =AU7-AS7 | AX7: =IF(AS7=0,"***",AW7/AS7) | AY7: =AY6-AY8 | AZ7: =AZ6-AZ8 | BA7: =BA6-BA8 | BB7: =BB6-BB8 | BC7: =BB7-BA7 | BD7: =BB7-AZ7 | BE7: =IF(AZ7=0,"***",BD7/AZ7) | BF7: =BF6-BF8 | BG7: =BG6-BG8 | BH7: =BH6-BH8 | BI7: =BI6-BI8 | BJ7: =BI7-BH7 | BK7: =BI7-BG7 | BL7: =IF(BG7=0,"***",BK7/BG7) | BM7: =BM6-BM8 | BN7: =BN6-BN8 | BO7: =BO6-BO8 | BP7: =BP6-BP8 | BQ7: =BP7-BO7 | BR7: =BP7-BN7 | BS7: =IF(BN7=0,"***",BR7/BN7) | BT7: =BT6-BT8 | BU7: =BU6-BU8 | BV7: =BV6-BV8 | BW7: =BW6-BW8 | BX7: =BW7-BV7 | BY7: =BW7-BU7 | BZ7: =IF(BU7=0,"***",BY7/BU7) | CA7: =CA6-CA8 | CB7: =CB6-CB8 | CC7: =CC6-CC8 | CD7: =CD6-CD8 | CE7: =CD7-CC7 | CF7: =CD7-CB7 | CG7: =IF(CB7=0,"***",CF7/CB7) | CH7: =CH6-CH8 | CI7: =CI6-CI8 | CJ7: =CJ6-CJ8 | CK7: =CK6-CK8 | CL7: =CK7-CJ7 | CM7: =CK7-CI7 | CN7: =IF(CI7=0,"***",CM7/CI7) | CO7: =CO6-CO8 | CP7: =CP6-CP8 | CQ7: =CQ6-CQ8 | CR7: =CR6-CR8 | CS7: =CR7-CQ7 | CT7: =CR7-CP7 | CU7: =IF(CP7=0,"***",CT7/CP7) | CV7: =CV6-CV8 | CW7: =CW6-CW8 | CX7: =CX6-CX8 | CY7: =CY6-CY8 | CZ7: =CY7-CX7 | DA7: =CY7-CW7 | DB7: =IF(CW7=0,"***",DA7/CW7) | DC7: =IF(CO7=0,"***",CV7/CO7) | DD7: =IF(CP7=0,"***",CW7/CP7) | DE7: =IF(CQ7=0,"***",CX7/CQ7) | DF7: =IF(CR7=0,"***",CY7/CR7) | DG7: =IF(DE7="***","***",DF7-DD7) | DH7: =IF(DF7="***","***",DF7-DD7)
H8: 機械 | I8: 4052 | J8: 4720 | K8: 4000 | L8: 2322 | M8: =L8-K8 | N8: =L8-J8 | O8: =IF(J8=0,"***",N8/J8) | P8: 1052 | Q8: 879 | R8: 640 | S8: 399 | T8: =S8-R8 | U8: =S8-Q8 | V8: =IF(Q8=0,"***",U8/Q8) | W8: 8505 | X8: 2337 | Y8: 4000 | Z8: 1052 | AA8: =Z8-Y8 | AB8: =Z8-X8 | AC8: =IF(X8=0,"***",AB8/X8) | AD8: 1294 | AE8: 517 | AF8: 640 | AG8: 219 | AH8: =AG8-AF8 | AI8: =AG8-AE8 | AJ8: =IF(AE8=0,"***",AI8/AE8) | AK8: 15244 | AL8: 6064 | AM8: 4000 | AN8: 1496 | AO8: =AN8-AM8 | AP8: =AN8-AL8 | AQ8: =IF(AL8=0,"***",AP8/AL8) | AR8: 2739 | AS8: 907 | AT8: 640 | AU8: 413 | AV8: =AU8-AT8 | AW8: =AU8-AS8 | AX8: =IF(AS8=0,"***",AW8/AS8) | AY8: 6195 | AZ8: 5408 | BA8: 4000 | BB8: 2874 | BC8: =BB8-BA8 | BD8: =BB8-AZ8 | BE8: =IF(AZ8=0,"***",BD8/AZ8) | BF8: 835 | BG8: 1183 | BH8: 640 | BI8: 493 | BJ8: =BI8-BH8 | BK8: =BI8-BG8 | BL8: =IF(BG8=0,"***",BK8/BG8) | BM8: 1035 | BN8: 2470 | BO8: 4000 | BP8: 2024 | BQ8: =BP8-BO8 | BR8: =BP8-BN8 | BS8: =IF(BN8=0,"***",BR8/BN8) | BT8: 324 | BU8: 557 | BV8: 640 | BW8: 415 | BX8: =BW8-BV8 | BY8: =BW8-BU8 | BZ8: =IF(BU8=0,"***",BY8/BU8) | CA8: 3076 | CB8: 1458 | CC8: 4000 | CD8: 1270 | CE8: =CD8-CC8 | CF8: =CD8-CB8 | CG8: =IF(CB8=0,"***",CF8/CB8) | CH8: 633 | CI8: 212 | CJ8: 640 | CK8: 282 | CL8: =CK8-CJ8 | CM8: =CK8-CI8 | CN8: =IF(CI8=0,"***",CM8/CI8) | CO8: =I8+W8+AK8+AY8+BM8+CA8 | CP8: =J8+X8+AL8+AZ8+BN8+CB8 | CQ8: =K8+Y8+AM8+BA8+BO8+CC8 | CR8: =L8+Z8+AN8+BB8+BP8+CD8 | CS8: =CR8-CQ8 | CT8: =CR8-CP8 | CU8: =IF(CP8=0,"***",CT8/CP8) | CV8: =P8+AD8+AR8+BF8+BT8+CH8 | CW8: =Q8+AE8+AS8+BG8+BU8+CI8 | CX8: =R8+AF8+AT8+BH8+BV8+CJ8 | CY8: =S8+AG8+AU8+BI8+BW8+CK8 | CZ8: =CY8-CX8 | DA8: =CY8-CW8 | DB8: =IF(CW8=0,"***",DA8/CW8) | DC8: =IF(CO8=0,"***",CV8/CO8) | DD8: =IF(CP8=0,"***",CW8/CP8) | DE8: =IF(CQ8=0,"***",CX8/CQ8) | DF8: =IF(CR8=0,"***",CY8/CR8) | DG8: =IF(DE8="***","***",DF8-DD8) | DH8: =IF(DF8="***","***",DF8-DD8)
G9: 自治体 | I9: 183 | J9: 255 | K9: 1340 | L9: 0 | M9: =L9-K9 | N9: =L9-J9 | O9: =IF(J9=0,"***",N9/J9) | P9: 183 | Q9: 48 | R9: 210 | S9: 0 | T9: =S9-R9 | U9: =S9-Q9 | V9: =IF(Q9=0,"***",U9/Q9) | W9: 2103 | X9: 0 | Y9: 1340 | Z9: 11223 | AA9: =Z9-Y9 | AB9: =Z9-X9 | AC9: =IF(X9=0,"***",AB9/X9) | AD9: 503 | AE9: 0 | AF9: 210 | AG9: 564 | AH9: =AG9-AF9 | AI9: =AG9-AE9 | AJ9: =IF(AE9=0,"***",AI9/AE9) | AK9: 183 | AL9: 0 | AM9: 1340 | AN9: 0 | AO9: =AN9-AM9 | AP9: =AN9-AL9 | AQ9: =IF(AL9=0,"***",AP9/AL9) | AR9: 183 | AS9: 0 | AT9: 210 | AU9: 0 | AV9: =AU9-AT9 | AW9: =AU9-AS9 | AX9: =IF(AS9=0,"***",AW9/AS9) | AY9: 183 | AZ9: 920 | BA9: 1340 | BB9: 64 | BC9: =BB9-BA9 | BD9: =BB9-AZ9 | BE9: =IF(AZ9=0,"***",BD9/AZ9) | BF9: 183 | BG9: 83 | BH9: 210 | BI9: 12 | BJ9: =BI9-BH9 | BK9: =BI9-BG9 | BL9: =IF(BG9=0,"***",BK9/BG9) | BM9: 229 | BN9: 407 | BO9: 1340 | BP9: 1296 | BQ9: =BP9-BO9 | BR9: =BP9-BN9 | BS9: =IF(BN9=0,"***",BR9/BN9) | BT9: 493 | BU9: 114 | BV9: 210 | BW9: 168 | BX9: =BW9-BV9 | BY9: =BW9-BU9 | BZ9: =IF(BU9=0,"***",BY9/BU9) | CA9: 2525 | CB9: 7125 | CC9: 1340 | CD9: 1077 | CE9: =CD9-CC9 | CF9: =CD9-CB9 | CG9: =IF(CB9=0,"***",CF9/CB9) | CH9: 529 | CI9: 753 | CJ9: 210 | CK9: 160 | CL9: =CK9-CJ9 | CM9: =CK9-CI9 | CN9: =IF(CI9=0,"***",CM9/CI9) | CO9: =I9+W9+AK9+AY9+BM9+CA9 | CP9: =J9+X9+AL9+AZ9+BN9+CB9 | CQ9: =K9+Y9+AM9+BA9+BO9+CC9 | CR9: =L9+Z9+AN9+BB9+BP9+CD9 | CS9: =CR9-CQ9 | CT9: =CR9-CP9 | CU9: =IF(CP9=0,"***",CT9/CP9) | CV9: =P9+AD9+AR9+BF9+BT9+CH9 | CW9: =Q9+AE9+AS9+BG9+BU9+CI9 | CX9: =R9+AF9+AT9+BH9+BV9+CJ9 | CY9: =S9+AG9+AU9+BI9+BW9+CK9 | CZ9: =CY9-CX9 | DA9: =CY9-CW9 | DB9: =IF(CW9=0,"***",DA9/CW9) | DC9: =IF(CO9=0,"***",CV9/CO9) | DD9: =IF(CP9=0,"***",CW9/CP9) | DE9: =IF(CQ9=0,"***",CX9/CQ9) | DF9: =IF(CR9=0,"***",CY9/CR9) | DG9: =IF(DE9="***","***",DF9-DD9) | DH9: =IF(DF9="***","***",DF9-DD9)
F10: 下関営業所 | I10: 83885 | J10: 46237 | K10: 49100 | L10: 49629 | M10: =L10-K10 | N10: =L10-J10 | O10: =IF(J10=0,"***",N10/J10) | P10: 14299 | Q10: 9374 | R10: 10250 | S10: 10482 | T10: =S10-R10 | U10: =S10-Q10 | V10: =IF(Q10=0,"***",U10/Q10) | W10: 46162 | X10: 51400 | Y10: 54500 | Z10: 50338 | AA10: =Z10-Y10 | AB10: =Z10-X10 | AC10: =IF(X10=0,"***",AB10/X10) | AD10: 9375 | AE10: 10690 | AF10: 11400 | AG10: 10680 | AH10: =AG10-AF10 | AI10: =AG10-AE10 | AJ10: =IF(AE10=0,"***",AI10/AE10) | AK10: 57036 | AL10: 58683 | AM10: 62000 | AN10: 60022 | AO10: =AN10-AM10 | AP10: =AN10-AL10 | AQ10: =IF(AL10=0,"***",AP10/AL10) | AR10: 11709 | AS10: 12538 | AT10: 13250 | AU10: 12591 | AV10: =AU10-AT10 | AW10: =AU10-AS10 | AX10: =IF(AS10=0,"***",AW10/AS10) | AY10: 32499 | AZ10: 36008 | BA10: 42000 | BB10: 39136 | BC10: =BB10-BA10 | BD10: =BB10-AZ10 | BE10: =IF(AZ10=0,"***",BD10/AZ10) | BF10: 6727 | BG10: 7681 | BH10: 8650 | BI10: 8056 | BJ10: =BI10-BH10 | BK10: =BI10-BG10 | BL10: =IF(BG10=0,"***",BK10/BG10) | BM10: 37053 | BN10: 38016 | BO10: 46300 | BP10: 37101 | BQ10: =BP10-BO10 | BR10: =BP10-BN10 | BS10: =IF(BN10=0,"***",BR10/BN10) | BT10: 7491 | BU10: 7836 | BV10: 9300 | BW10: 7410 | BX10: =BW10-BV10 | BY10: =BW10-BU10 | BZ10: =IF(BU10=0,"***",BY10/BU10) | CA10: 39992 | CB10: 43539 | CC10: 59600 | CD10: 39253 | CE10: =CD10-CC10 | CF10: =CD10-CB10 | CG10: =IF(CB10=0,"***",CF10/CB10) | CH10: 8121 | CI10: 9169 | CJ10: 11950 | CK10: 8075 | CL10: =CK10-CJ10 | CM10: =CK10-CI10 | CN10: =IF(CI10=0,"***",CM10/CI10) | CO10: =I10+W10+AK10+AY10+BM10+CA10 | CP10: =J10+X10+AL10+AZ10+BN10+CB10 | CQ10: =K10+Y10+AM10+BA10+BO10+CC10 | CR10: =L10+Z10+AN10+BB10+BP10+CD10 | CS10: =CR10-CQ10 | CT10: =CR10-CP10 | CU10: =IF(CP10=0,"***",CT10/CP10) | CV10: =P10+AD10+AR10+BF10+BT10+CH10 | CW10: =Q10+AE10+AS10+BG10+BU10+CI10 | CX10: =R10+AF10+AT10+BH10+BV10+CJ10 | CY10: =S10+AG10+AU10+BI10+BW10+CK10 | CZ10: =CY10-CX10 | DA10: =CY10-CW10 | DB10: =IF(CW10=0,"***",DA10/CW10) | DC10: =IF(CO10=0,"***",CV10/CO10) | DD10: =IF(CP10=0,"***",CW10/CP10) | DE10: =IF(CQ10=0,"***",CX10/CQ10) | DF10: =IF(CR10=0,"***",CY10/CR10) | DG10: =IF(DE10="***","***",DF10-DD10) | DH10: =IF(DF10="***","***",DF10-DD10)
G11: 営業 | I11: =I10-I15 | J11: =J10-J15 | K11: =K10-K15 | L11: =L10-L15 | M11: =L11-K11 | N11: =L11-J11 | O11: =IF(J11=0,"***",N11/J11) | P11: =P10-P15 | Q11: =Q10-Q15 | R11: =R10-R15 | S11: =S10-S15 | T11: =S11-R11 | U11: =S11-Q11 | V11: =IF(Q11=0,"***",U11/Q11) | W11: =W10-W15 | X11: =X10-X15 | Y11: =Y10-Y15 | Z11: =Z10-Z15 | AA11: =Z11-Y11 | AB11: =Z11-X11 | AC11: =IF(X11=0,"***",AB11/X11) | AD11: =AD10-AD15 | AE11: =AE10-AE15 | AF11: =AF10-AF15 | AG11: =AG10-AG15 | AH11: =AG11-AF11 | AI11: =AG11-AE11 | AJ11: =IF(AE11=0,"***",AI11/AE11) | AK11: =AK10-AK15 | AL11: =AL10-AL15 | AM11: =AM10-AM15 | AN11: =AN10-AN15 | AO11: =AN11-AM11 | AP11: =AN11-AL11 | AQ11: =IF(AL11=0,"***",AP11/AL11) | AR11: =AR10-AR15 | AS11: =AS10-AS15 | AT11: =AT10-AT15 | AU11: =AU10-AU15 | AV11: =AU11-AT11 | AW11: =AU11-AS11 | AX11: =IF(AS11=0,"***",AW11/AS11) | AY11: =AY10-AY15 | AZ11: =AZ10-AZ15 | BA11: =BA10-BA15 | BB11: =BB10-BB15 | BC11: =BB11-BA11 | BD11: =BB11-AZ11 | BE11: =IF(AZ11=0,"***",BD11/AZ11) | BF11: =BF10-BF15 | BG11: =BG10-BG15 | BH11: =BH10-BH15 | BI11: =BI10-BI15 | BJ11: =BI11-BH11 | BK11: =BI11-BG11 | BL11: =IF(BG11=0,"***",BK11/BG11) | BM11: =BM10-BM15 | BN11: =BN10-BN15 | BO11: =BO10-BO15 | BP11: =BP10-BP15 | BQ11: =BP11-BO11 | BR11: =BP11-BN11 | BS11: =IF(BN11=0,"***",BR11/BN11) | BT11: =BT10-BT15 | BU11: =BU10-BU15 | BV11: =BV10-BV15 | BW11: =BW10-BW15 | BX11: =BW11-BV11 | BY11: =BW11-BU11 | BZ11: =IF(BU11=0,"***",BY11/BU11) | CA11: =CA10-CA15 | CB11: =CB10-CB15 | CC11: =CC10-CC15 | CD11: =CD10-CD15 | CE11: =CD11-CC11 | CF11: =CD11-CB11 | CG11: =IF(CB11=0,"***",CF11/CB11) | CH11: =CH10-CH15 | CI11: =CI10-CI15 | CJ11: =CJ10-CJ15 | CK11: =CK10-CK15 | CL11: =CK11-CJ11 | CM11: =CK11-CI11 | CN11: =IF(CI11=0,"***",CM11/CI11) | CO11: =CO10-CO15 | CP11: =CP10-CP15 | CQ11: =CQ10-CQ15 | CR11: =CR10-CR15-CR14 | CS11: =CR11-CQ11 | CT11: =CR11-CP11 | CU11: =IF(CP11=0,"***",CT11/CP11) | CV11: =CV10-CV15 | CW11: =CW10-CW15 | CX11: =CX10-CX15 | CY11: =CY10-CY15 | CZ11: =CY11-CX11 | DA11: =CY11-CW11 | DB11: =IF(CW11=0,"***",DA11/CW11) | DC11: =IF(CO11=0,"***",CV11/CO11) | DD11: =IF(CP11=0,"***",CW11/CP11) | DE11: =IF(CQ11=0,"***",CX11/CQ11) | DF11: =IF(CR11=0,"***",CY11/CR11) | DG11: =IF(DE11="***","***",DF11-DD11) | DH11: =IF(DF11="***","***",DF11-DD11)
H12: 包装資材 | I12: =I11-I13 | J12: =J11-J13 | K12: =K11-K13 | L12: =L11-L13 | M12: =L12-K12 | N12: =L12-J12 | O12: =IF(J12=0,"***",N12/J12) | P12: =P11-P13 | Q12: =Q11-Q13 | R12: =R11-R13 | S12: =S11-S13 | T12: =S12-R12 | U12: =S12-Q12 | V12: =IF(Q12=0,"***",U12/Q12) | W12: =W11-W13 | X12: =X11-X13 | Y12: =Y11-Y13 | Z12: =Z11-Z13 | AA12: =Z12-Y12 | AB12: =Z12-X12 | AC12: =IF(X12=0,"***",AB12/X12) | AD12: =AD11-AD13 | AE12: =AE11-AE13 | AF12: =AF11-AF13 | AG12: =AG11-AG13 | AH12: =AG12-AF12 | AI12: =AG12-AE12 | AJ12: =IF(AE12=0,"***",AI12/AE12) | AK12: =AK11-AK13 | AL12: =AL11-AL13 | AM12: =AM11-AM13 | AN12: =AN11-AN13 | AO12: =AN12-AM12 | AP12: =AN12-AL12 | AQ12: =IF(AL12=0,"***",AP12/AL12) | AR12: =AR11-AR13 | AS12: =AS11-AS13 | AT12: =AT11-AT13 | AU12: =AU11-AU13 | AV12: =AU12-AT12 | AW12: =AU12-AS12 | AX12: =IF(AS12=0,"***",AW12/AS12) | AY12: =AY11-AY13 | AZ12: =AZ11-AZ13 | BA12: =BA11-BA13 | BB12: =BB11-BB13 | BC12: =BB12-BA12 | BD12: =BB12-AZ12 | BE12: =IF(AZ12=0,"***",BD12/AZ12) | BF12: =BF11-BF13 | BG12: =BG11-BG13 | BH12: =BH11-BH13 | BI12: =BI11-BI13 | BJ12: =BI12-BH12 | BK12: =BI12-BG12 | BL12: =IF(BG12=0,"***",BK12/BG12) | BM12: =BM11-BM13 | BN12: =BN11-BN13 | BO12: =BO11-BO13 | BP12: =BP11-BP13 | BQ12: =BP12-BO12 | BR12: =BP12-BN12 | BS12: =IF(BN12=0,"***",BR12/BN12) | BT12: =BT11-BT13 | BU12: =BU11-BU13 | BV12: =BV11-BV13 | BW12: =BW11-BW13 | BX12: =BW12-BV12 | BY12: =BW12-BU12 | BZ12: =IF(BU12=0,"***",BY12/BU12) | CA12: =CA11-CA13 | CB12: =CB11-CB13 | CC12: =CC11-CC13 | CD12: =CD11-CD13 | CE12: =CD12-CC12 | CF12: =CD12-CB12 | CG12: =IF(CB12=0,"***",CF12/CB12) | CH12: =CH11-CH13 | CI12: =CI11-CI13 | CJ12: =CJ11-CJ13 | CK12: =CK11-CK13 | CL12: =CK12-CJ12 | CM12: =CK12-CI12 | CN12: =IF(CI12=0,"***",CM12/CI12) | CO12: =CO11-CO13 | CP12: =CP11-CP13 | CQ12: =CQ11-CQ13 | CR12: =CR11-CR13 | CS12: =CR12-CQ12 | CT12: =CR12-CP12 | CU12: =IF(CP12=0,"***",CT12/CP12) | CV12: =CV11-CV13 | CW12: =CW11-CW13 | CX12: =CX11-CX13 | CY12: =CY11-CY13 | CZ12: =CY12-CX12 | DA12: =CY12-CW12 | DB12: =IF(CW12=0,"***",DA12/CW12) | DC12: =IF(CO12=0,"***",CV12/CO12) | DD12: =IF(CP12=0,"***",CW12/CP12) | DE12: =IF(CQ12=0,"***",CX12/CQ12) | DF12: =IF(CR12=0,"***",CY12/CR12) | DG12: =IF(DE12="***","***",DF12-DD12) | DH12: =IF(DF12="***","***",DF12-DD12)
H13: 機械 | I13: 33783 | J13: 281 | K13: 300 | L13: 515 | M13: =L13-K13 | N13: =L13-J13 | O13: =IF(J13=0,"***",N13/J13) | P13: 4402 | Q13: 45 | R13: 55 | S13: 107 | T13: =S13-R13 | U13: =S13-Q13 | V13: =IF(Q13=0,"***",U13/Q13) | W13: 592 | X13: 200 | Y13: 300 | Z13: 230 | AA13: =Z13-Y13 | AB13: =Z13-X13 | AC13: =IF(X13=0,"***",AB13/X13) | AD13: 139 | AE13: 45 | AF13: 55 | AG13: 37 | AH13: =AG13-AF13 | AI13: =AG13-AE13 | AJ13: =IF(AE13=0,"***",AI13/AE13) | AK13: 134 | AL13: 203 | AM13: 300 | AN13: 611 | AO13: =AN13-AM13 | AP13: =AN13-AL13 | AQ13: =IF(AL13=0,"***",AP13/AL13) | AR13: 25 | AS13: 41 | AT13: 55 | AU13: 42 | AV13: =AU13-AT13 | AW13: =AU13-AS13 | AX13: =IF(AS13=0,"***",AW13/AS13) | AY13: 15 | AZ13: 99 | BA13: 300 | BB13: 310 | BC13: =BB13-BA13 | BD13: =BB13-AZ13 | BE13: =IF(AZ13=0,"***",BD13/AZ13) | BF13: 8 | BG13: 8 | BH13: 55 | BI13: 55 | BJ13: =BI13-BH13 | BK13: =BI13-BG13 | BL13: =IF(BG13=0,"***",BK13/BG13) | BM13: 1402 | BN13: 265 | BO13: 900 | BP13: 1253 | BQ13: =BP13-BO13 | BR13: =BP13-BN13 | BS13: =IF(BN13=0,"***",BR13/BN13) | BT13: 238 | BU13: 48 | BV13: 145 | BW13: 161 | BX13: =BW13-BV13 | BY13: =BW13-BU13 | BZ13: =IF(BU13=0,"***",BY13/BU13) | CA13: 20 | CB13: 720 | CC13: 10440 | CD13: 171 | CE13: =CD13-CC13 | CF13: =CD13-CB13 | CG13: =IF(CB13=0,"***",CF13/CB13) | CH13: 5 | CI13: 104 | CJ13: 1545 | CK13: 29 | CL13: =CK13-CJ13 | CM13: =CK13-CI13 | CN13: =IF(CI13=0,"***",CM13/CI13) | CO13: =I13+W13+AK13+AY13+BM13+CA13 | CP13: =J13+X13+AL13+AZ13+BN13+CB13 | CQ13: =K13+Y13+AM13+BA13+BO13+CC13 | CR13: =L13+Z13+AN13+BB13+BP13+CD13 | CS13: =CR13-CQ13 | CT13: =CR13-CP13 | CU13: =IF(CP13=0,"***",CT13/CP13) | CV13: =P13+AD13+AR13+BF13+BT13+CH13 | CW13: =Q13+AE13+AS13+BG13+BU13+CI13 | CX13: =R13+AF13+AT13+BH13+BV13+CJ13 | CY13: =S13+AG13+AU13+BI13+BW13+CK13 | CZ13: =CY13-CX13 | DA13: =CY13-CW13 | DB13: =IF(CW13=0,"***",DA13/CW13) | DC13: =IF(CO13=0,"***",CV13/CO13) | DD13: =IF(CP13=0,"***",CW13/CP13) | DE13: =IF(CQ13=0,"***",CX13/CQ13) | DF13: =IF(CR13=0,"***",CY13/CR13) | DG13: =IF(DE13="***","***",DF13-DD13) | DH13: =IF(DF13="***","***",DF13-DD13)
G14: 自治体 | CO14: 0 | CP14: 0 | CQ14: 0 | CR14: 222 | CV14: 0 | CW14: 0 | CX14: 0 | CY14: 8 | DC14: =IF(CO14=0,"***",CV14/CO14) | DD14: =IF(CP14=0,"***",CW14/CP14) | DE14: =IF(CQ14=0,"***",CX14/CQ14) | DF14: =IF(CR14=0,"***",CY14/CR14)
G15: 中国事業 | I15: 3478 | J15: 0 | K15: 0 | L15: 0 | M15: =L15-K15 | N15: =L15-J15 | O15: =IF(J15=0,"***",N15/J15) | P15: 166 | Q15: 0 | R15: 0 | S15: 0 | T15: =S15-R15 | U15: =S15-Q15 | V15: =IF(Q15=0,"***",U15/Q15) | W15: 0 | X15: 0 | Y15: 0 | Z15: 0 | AA15: =Z15-Y15 | AB15: =Z15-X15 | AC15: =IF(X15=0,"***",AB15/X15) | AD15: 0 | AE15: 0 | AF15: 0 | AG15: 0 | AH15: =AG15-AF15 | AI15: =AG15-AE15 | AJ15: =IF(AE15=0,"***",AI15/AE15) | AK15: 2959 | AL15: 0 | AM15: 0 | AN15: 0 | AO15: =AN15-AM15 | AP15: =AN15-AL15 | AQ15: =IF(AL15=0,"***",AP15/AL15) | AR15: 162 | AS15: 0 | AT15: 0 | AU15: 0 | AV15: =AU15-AT15 | AW15: =AU15-AS15 | AX15: =IF(AS15=0,"***",AW15/AS15) | AY15: 0 | AZ15: 0 | BA15: 0 | BB15: 0 | BC15: =BB15-BA15 | BD15: =BB15-AZ15 | BE15: =IF(AZ15=0,"***",BD15/AZ15) | BF15: 0 | BG15: 0 | BH15: 0 | BI15: 0 | BJ15: =BI15-BH15 | BK15: =BI15-BG15 | BL15: =IF(BG15=0,"***",BK15/BG15) | BM15: 0 | BN15: 0 | BO15: 0 | BP15: 0 | BQ15: =BP15-BO15 | BR15: =BP15-BN15 | BS15: =IF(BN15=0,"***",BR15/BN15) | BT15: 0 | BU15: 0 | BV15: 0 | BW15: 0 | BX15: =BW15-BV15 | BY15: =BW15-BU15 | BZ15: =IF(BU15=0,"***",BY15/BU15) | CA15: 0 | CB15: 0 | CC15: 0 | CD15: 0 | CE15: =CD15-CC15 | CF15: =CD15-CB15 | CG15: =IF(CB15=0,"***",CF15/CB15) | CH15: 0 | CI15: 0 | CJ15: 0 | CK15: 0 | CL15: =CK15-CJ15 | CM15: =CK15-CI15 | CN15: =IF(CI15=0,"***",CM15/CI15) | CO15: =I15+W15+AK15+AY15+BM15+CA15 | CP15: =J15+X15+AL15+AZ15+BN15+CB15 | CQ15: =K15+Y15+AM15+BA15+BO15+CC15 | CR15: =L15+Z15+AN15+BB15+BP15+CD15 | CS15: =CR15-CQ15 | CT15: =CR15-CP15 | CU15: =IF(CP15=0,"***",CT15/CP15) | CV15: =P15+AD15+AR15+BF15+BT15+CH15 | CW15: =Q15+AE15+AS15+BG15+BU15+CI15 | CX15: =R15+AF15+AT15+BH15+BV15+CJ15 | CY15: =S15+AG15+AU15+BI15+BW15+CK15 | CZ15: =CY15-CX15 | DA15: =CY15-CW15 | DB15: =IF(CW15=0,"***",DA15/CW15) | DC15: =IF(CO15=0,"***",CV15/CO15) | DD15: =IF(CP15=0,"***",CW15/CP15) | DE15: =IF(CQ15=0,"***",CX15/CQ15) | DF15: =IF(CR15=0,"***",CY15/CR15) | DG15: =IF(DE15="***","***",DF15-DD15) | DH15: =IF(DF15="***","***",DF15-DD15)
F16: 松江営業所 | I16: 38303 | J16: 43707 | K16: 45090 | L16: 48121 | M16: =L16-K16 | N16: =L16-J16 | O16: =IF(J16=0,"***",N16/J16) | P16: 7249 | Q16: 9663 | R16: 10090 | S16: 9325 | T16: =S16-R16 | U16: =S16-Q16 | V16: =IF(Q16=0,"***",U16/Q16) | W16: 31951 | X16: 40602 | Y16: 42290 | Z16: 39334 | AA16: =Z16-Y16 | AB16: =Z16-X16 | AC16: =IF(X16=0,"***",AB16/X16) | AD16: 7326 | AE16: 9358 | AF16: 9710 | AG16: 8378 | AH16: =AG16-AF16 | AI16: =AG16-AE16 | AJ16: =IF(AE16=0,"***",AI16/AE16) | AK16: 40329 | AL16: 46544 | AM16: 49210 | AN16: 49382 | AO16: =AN16-AM16 | AP16: =AN16-AL16 | AQ16: =IF(AL16=0,"***",AP16/AL16) | AR16: 9755 | AS16: 10682 | AT16: 11280 | AU16: 10901 | AV16: =AU16-AT16 | AW16: =AU16-AS16 | AX16: =IF(AS16=0,"***",AW16/AS16) | AY16: 15102 | AZ16: 24737 | BA16: 25250 | BB16: 26373 | BC16: =BB16-BA16 | BD16: =BB16-AZ16 | BE16: =IF(AZ16=0,"***",BD16/AZ16) | BF16: 3694 | BG16: 5072 | BH16: 5460 | BI16: 5547 | BJ16: =BI16-BH16 | BK16: =BI16-BG16 | BL16: =IF(BG16=0,"***",BK16/BG16) | BM16: 34089 | BN16: 19371 | BO16: 24610 | BP16: 26933 | BQ16: =BP16-BO16 | BR16: =BP16-BN16 | BS16: =IF(BN16=0,"***",BR16/BN16) | BT16: 6367 | BU16: 5106 | BV16: 5580 | BW16: 5672 | BX16: =BW16-BV16 | BY16: =BW16-BU16 | BZ16: =IF(BU16=0,"***",BY16/BU16) | CA16: 23305 | CB16: 28658 | CC16: 42010 | CD16: 46067 | CE16: =CD16-CC16 | CF16: =CD16-CB16 | CG16: =IF(CB16=0,"***",CF16/CB16) | CH16: 5632 | CI16: 6895 | CJ16: 9600 | CK16: 12921 | CL16: =CK16-CJ16 | CM16: =CK16-CI16 | CN16: =IF(CI16=0,"***",CM16/CI16) | CO16: =I16+W16+AK16+AY16+BM16+CA16 | CP16: =J16+X16+AL16+AZ16+BN16+CB16 | CQ16: =K16+Y16+AM16+BA16+BO16+CC16 | CR16: =L16+Z16+AN16+BB16+BP16+CD16 | CS16: =CR16-CQ16 | CT16: =CR16-CP16 | CU16: =IF(CP16=0,"***",CT16/CP16) | CV16: =P16+AD16+AR16+BF16+BT16+CH16 | CW16: =Q16+AE16+AS16+BG16+BU16+CI16 | CX16: =R16+AF16+AT16+BH16+BV16+CJ16 | CY16: =S16+AG16+AU16+BI16+BW16+CK16 | CZ16: =CY16-CX16 | DA16: =CY16-CW16 | DB16: =IF(CW16=0,"***",DA16/CW16) | DC16: =IF(CO16=0,"***",CV16/CO16) | DD16: =IF(CP16=0,"***",CW16/CP16) | DE16: =IF(CQ16=0,"***",CX16/CQ16) | DF16: =IF(CR16=0,"***",CY16/CR16) | DG16: =IF(DE16="***","***",DF16-DD16) | DH16: =IF(DF16="***","***",DF16-DD16)
G17: 営業 | I17: =I16-I20 | J17: =J16-J20 | K17: =K16-K20 | L17: =L16-L20 | M17: =L17-K17 | N17: =L17-J17 | O17: =IF(J17=0,"***",N17/J17) | P17: =P16-P20 | Q17: =Q16-Q20 | R17: =R16-R20 | S17: =S16-S20 | T17: =S17-R17 | U17: =S17-Q17 | V17: =IF(Q17=0,"***",U17/Q17) | W17: =W16-W20 | X17: =X16-X20 | Y17: =Y16-Y20 | Z17: =Z16-Z20 | AA17: =Z17-Y17 | AB17: =Z17-X17 | AC17: =IF(X17=0,"***",AB17/X17) | AD17: =AD16-AD20 | AE17: =AE16-AE20 | AF17: =AF16-AF20 | AG17: =AG16-AG20 | AH17: =AG17-AF17 | AI17: =AG17-AE17 | AJ17: =IF(AE17=0,"***",AI17/AE17) | AK17: =AK16-AK20 | AL17: =AL16-AL20 | AM17: =AM16-AM20 | AN17: =AN16-AN20 | AO17: =AN17-AM17 | AP17: =AN17-AL17 | AQ17: =IF(AL17=0,"***",AP17/AL17) | AR17: =AR16-AR20 | AS17: =AS16-AS20 | AT17: =AT16-AT20 | AU17: =AU16-AU20 | AV17: =AU17-AT17 | AW17: =AU17-AS17 | AX17: =IF(AS17=0,"***",AW17/AS17) | AY17: =AY16-AY20 | AZ17: =AZ16-AZ20 | BA17: =BA16-BA20 | BB17: =BB16-BB20 | BC17: =BB17-BA17 | BD17: =BB17-AZ17 | BE17: =IF(AZ17=0,"***",BD17/AZ17) | BF17: =BF16-BF20 | BG17: =BG16-BG20 | BH17: =BH16-BH20 | BI17: =BI16-BI20 | BJ17: =BI17-BH17 | BK17: =BI17-BG17 | BL17: =IF(BG17=0,"***",BK17/BG17) | BM17: =BM16-BM20 | BN17: =BN16-BN20 | BO17: =BO16-BO20 | BP17: =BP16-BP20 | BQ17: =BP17-BO17 | BR17: =BP17-BN17 | BS17: =IF(BN17=0,"***",BR17/BN17) | BT17: =BT16-BT20 | BU17: =BU16-BU20 | BV17: =BV16-BV20 | BW17: =BW16-BW20 | BX17: =BW17-BV17 | BY17: =BW17-BU17 | BZ17: =IF(BU17=0,"***",BY17/BU17) | CA17: =CA16-CA20 | CB17: =CB16-CB20 | CC17: =CC16-CC20 | CD17: =CD16-CD20 | CE17: =CD17-CC17 | CF17: =CD17-CB17 | CG17: =IF(CB17=0,"***",CF17/CB17) | CH17: =CH16-CH20 | CI17: =CI16-CI20 | CJ17: =CJ16-CJ20 | CK17: =CK16-CK20 | CL17: =CK17-CJ17 | CM17: =CK17-CI17 | CN17: =IF(CI17=0,"***",CM17/CI17) | CO17: =CO16-CO20 | CP17: =CP16-CP20 | CQ17: =CQ16-CQ20 | CR17: =CR16-CR20 | CS17: =CR17-CQ17 | CT17: =CR17-CP17 | CU17: =IF(CP17=0,"***",CT17/CP17) | CV17: =CV16-CV20 | CW17: =CW16-CW20 | CX17: =CX16-CX20 | CY17: =CY16-CY20 | CZ17: =CY17-CX17 | DA17: =CY17-CW17 | DB17: =IF(CW17=0,"***",DA17/CW17) | DC17: =IF(CO17=0,"***",CV17/CO17) | DD17: =IF(CP17=0,"***",CW17/CP17) | DE17: =IF(CQ17=0,"***",CX17/CQ17) | DF17: =IF(CR17=0,"***",CY17/CR17) | DG17: =IF(DE17="***","***",DF17-DD17) | DH17: =IF(DF17="***","***",DF17-DD17)
H18: 包装資材 | I18: =I17-I19 | J18: =J17-J19 | K18: =K17-K19 | L18: =L17-L19 | M18: =L18-K18 | N18: =L18-J18 | O18: =IF(J18=0,"***",N18/J18) | P18: =P17-P19 | Q18: =Q17-Q19 | R18: =R17-R19 | S18: =S17-S19 | T18: =S18-R18 | U18: =S18-Q18 | V18: =IF(Q18=0,"***",U18/Q18) | W18: =W17-W19 | X18: =X17-X19 | Y18: =Y17-Y19 | Z18: =Z17-Z19 | AA18: =Z18-Y18 | AB18: =Z18-X18 | AC18: =IF(X18=0,"***",AB18/X18) | AD18: =AD17-AD19 | AE18: =AE17-AE19 | AF18: =AF17-AF19 | AG18: =AG17-AG19 | AH18: =AG18-AF18 | AI18: =AG18-AE18 | AJ18: =IF(AE18=0,"***",AI18/AE18) | AK18: =AK17-AK19 | AL18: =AL17-AL19 | AM18: =AM17-AM19 | AN18: =AN17-AN19 | AO18: =AN18-AM18 | AP18: =AN18-AL18 | AQ18: =IF(AL18=0,"***",AP18/AL18) | AR18: =AR17-AR19 | AS18: =AS17-AS19 | AT18: =AT17-AT19 | AU18: =AU17-AU19 | AV18: =AU18-AT18 | AW18: =AU18-AS18 | AX18: =IF(AS18=0,"***",AW18/AS18) | AY18: =AY17-AY19 | AZ18: =AZ17-AZ19 | BA18: =BA17-BA19 | BB18: =BB17-BB19 | BC18: =BB18-BA18 | BD18: =BB18-AZ18 | BE18: =IF(AZ18=0,"***",BD18/AZ18) | BF18: =BF17-BF19 | BG18: =BG17-BG19 | BH18: =BH17-BH19 | BI18: =BI17-BI19 | BJ18: =BI18-BH18 | BK18: =BI18-BG18 | BL18: =IF(BG18=0,"***",BK18/BG18) | BM18: =BM17-BM19 | BN18: =BN17-BN19 | BO18: =BO17-BO19 | BP18: =BP17-BP19 | BQ18: =BP18-BO18 | BR18: =BP18-BN18 | BS18: =IF(BN18=0,"***",BR18/BN18) | BT18: =BT17-BT19 | BU18: =BU17-BU19 | BV18: =BV17-BV19 | BW18: =BW17-BW19 | BX18: =BW18-BV18 | BY18: =BW18-BU18 | BZ18: =IF(BU18=0,"***",BY18/BU18) | CA18: =CA17-CA19 | CB18: =CB17-CB19 | CC18: =CC17-CC19 | CD18: =CD17-CD19 | CE18: =CD18-CC18 | CF18: =CD18-CB18 | CG18: =IF(CB18=0,"***",CF18/CB18) | CH18: =CH17-CH19 | CI18: =CI17-CI19 | CJ18: =CJ17-CJ19 | CK18: =CK17-CK19 | CL18: =CK18-CJ18 | CM18: =CK18-CI18 | CN18: =IF(CI18=0,"***",CM18/CI18) | CO18: =CO17-CO19 | CP18: =CP17-CP19 | CQ18: =CQ17-CQ19 | CR18: =CR17-CR19 | CS18: =CR18-CQ18 | CT18: =CR18-CP18 | CU18: =IF(CP18=0,"***",CT18/CP18) | CV18: =CV17-CV19 | CW18: =CW17-CW19 | CX18: =CX17-CX19 | CY18: =CY17-CY19 | CZ18: =CY18-CX18 | DA18: =CY18-CW18 | DB18: =IF(CW18=0,"***",DA18/CW18) | DC18: =IF(CO18=0,"***",CV18/CO18) | DD18: =IF(CP18=0,"***",CW18/CP18) | DE18: =IF(CQ18=0,"***",CX18/CQ18) | DF18: =IF(CR18=0,"***",CY18/CR18) | DG18: =IF(DE18="***","***",DF18-DD18) | DH18: =IF(DF18="***","***",DF18-DD18)
H19: 機械 | I19: 241 | J19: 3010 | K19: 3000 | L19: 836 | M19: =L19-K19 | N19: =L19-J19 | O19: =IF(J19=0,"***",N19/J19) | P19: 50 | Q19: 585 | R19: 480 | S19: 142 | T19: =S19-R19 | U19: =S19-Q19 | V19: =IF(Q19=0,"***",U19/Q19) | W19: 3513 | X19: 973 | Y19: 500 | Z19: 1129 | AA19: =Z19-Y19 | AB19: =Z19-X19 | AC19: =IF(X19=0,"***",AB19/X19) | AD19: 246 | AE19: 310 | AF19: 100 | AG19: 225 | AH19: =AG19-AF19 | AI19: =AG19-AE19 | AJ19: =IF(AE19=0,"***",AI19/AE19) | AK19: 4880 | AL19: 795 | AM19: 500 | AN19: 497 | AO19: =AN19-AM19 | AP19: =AN19-AL19 | AQ19: =IF(AL19=0,"***",AP19/AL19) | AR19: 1125 | AS19: 165 | AT19: 100 | AU19: 93 | AV19: =AU19-AT19 | AW19: =AU19-AS19 | AX19: =IF(AS19=0,"***",AW19/AS19) | AY19: 380 | AZ19: 143 | BA19: 500 | BB19: 750 | BC19: =BB19-BA19 | BD19: =BB19-AZ19 | BE19: =IF(AZ19=0,"***",BD19/AZ19) | BF19: 66 | BG19: 33 | BH19: 100 | BI19: 143 | BJ19: =BI19-BH19 | BK19: =BI19-BG19 | BL19: =IF(BG19=0,"***",BK19/BG19) | BM19: 14046 | BN19: 117 | BO19: 500 | BP19: 704 | BQ19: =BP19-BO19 | BR19: =BP19-BN19 | BS19: =IF(BN19=0,"***",BR19/BN19) | BT19: 1542 | BU19: 38 | BV19: 100 | BW19: 118 | BX19: =BW19-BV19 | BY19: =BW19-BU19 | BZ19: =IF(BU19=0,"***",BY19/BU19) | CA19: 2499 | CB19: 3496 | CC19: 16500 | CD19: 18915 | CE19: =CD19-CC19 | CF19: =CD19-CB19 | CG19: =IF(CB19=0,"***",CF19/CB19) | CH19: 488 | CI19: 870 | CJ19: 3300 | CK19: 5710 | CL19: =CK19-CJ19 | CM19: =CK19-CI19 | CN19: =IF(CI19=0,"***",CM19/CI19) | CO19: =I19+W19+AK19+AY19+BM19+CA19 | CP19: =J19+X19+AL19+AZ19+BN19+CB19 | CQ19: =K19+Y19+AM19+BA19+BO19+CC19 | CR19: =L19+Z19+AN19+BB19+BP19+CD19 | CS19: =CR19-CQ19 | CT19: =CR19-CP19 | CU19: =IF(CP19=0,"***",CT19/CP19) | CV19: =P19+AD19+AR19+BF19+BT19+CH19 | CW19: =Q19+AE19+AS19+BG19+BU19+CI19 | CX19: =R19+AF19+AT19+BH19+BV19+CJ19 | CY19: =S19+AG19+AU19+BI19+BW19+CK19 | CZ19: =CY19-CX19 | DA19: =CY19-CW19 | DB19: =IF(CW19=0,"***",DA19/CW19) | DC19: =IF(CO19=0,"***",CV19/CO19) | DD19: =IF(CP19=0,"***",CW19/CP19) | DE19: =IF(CQ19=0,"***",CX19/CQ19) | DF19: =IF(CR19=0,"***",CY19/CR19) | DG19: =IF(DE19="***","***",DF19-DD19) | DH19: =IF(DF19="***","***",DF19-DD19)
G20: 自治体 | I20: 8982 | J20: 5976 | K20: 5500 | L20: 13761 | M20: =L20-K20 | N20: =L20-J20 | O20: =IF(J20=0,"***",N20/J20) | P20: 269 | Q20: 117 | R20: 100 | S20: 404 | T20: =S20-R20 | U20: =S20-Q20 | V20: =IF(Q20=0,"***",U20/Q20) | W20: 0 | X20: 6153 | Y20: 6600 | Z20: 6905 | AA20: =Z20-Y20 | AB20: =Z20-X20 | AC20: =IF(X20=0,"***",AB20/X20) | AD20: 0 | AE20: 102 | AF20: 110 | AG20: 119 | AH20: =AG20-AF20 | AI20: =AG20-AE20 | AJ20: =IF(AE20=0,"***",AI20/AE20) | AK20: 0 | AL20: 7138 | AM20: 8180 | AN20: 9060 | AO20: =AN20-AM20 | AP20: =AN20-AL20 | AQ20: =IF(AL20=0,"***",AP20/AL20) | AR20: 0 | AS20: 113 | AT20: 150 | AU20: 157 | AV20: =AU20-AT20 | AW20: =AU20-AS20 | AX20: =IF(AS20=0,"***",AW20/AS20) | AY20: 0 | AZ20: 5921 | BA20: 4870 | BB20: 5022 | BC20: =BB20-BA20 | BD20: =BB20-AZ20 | BE20: =IF(AZ20=0,"***",BD20/AZ20) | BF20: 0 | BG20: 104 | BH20: 70 | BI20: 79 | BJ20: =BI20-BH20 | BK20: =BI20-BG20 | BL20: =IF(BG20=0,"***",BK20/BG20) | BM20: 0 | BN20: 0 | BO20: 3630 | BP20: 3741 | BQ20: =BP20-BO20 | BR20: =BP20-BN20 | BS20: =IF(BN20=0,"***",BR20/BN20) | BT20: 0 | BU20: 0 | BV20: 50 | BW20: 55 | BX20: =BW20-BV20 | BY20: =BW20-BU20 | BZ20: =IF(BU20=0,"***",BY20/BU20) | CA20: 0 | CB20: 538 | CC20: 0 | CD20: 0 | CE20: =CD20-CC20 | CF20: =CD20-CB20 | CG20: =IF(CB20=0,"***",CF20/CB20) | CH20: 0 | CI20: 27 | CJ20: 0 | CK20: 0 | CL20: =CK20-CJ20 | CM20: =CK20-CI20 | CN20: =IF(CI20=0,"***",CM20/CI20) | CO20: =I20+W20+AK20+AY20+BM20+CA20 | CP20: =J20+X20+AL20+AZ20+BN20+CB20 | CQ20: =K20+Y20+AM20+BA20+BO20+CC20 | CR20: =L20+Z20+AN20+BB20+BP20+CD20 | CS20: =CR20-CQ20 | CT20: =CR20-CP20 | CU20: =IF(CP20=0,"***",CT20/CP20) | CV20: =P20+AD20+AR20+BF20+BT20+CH20 | CW20: =Q20+AE20+AS20+BG20+BU20+CI20 | CX20: =R20+AF20+AT20+BH20+BV20+CJ20 | CY20: =S20+AG20+AU20+BI20+BW20+CK20 | CZ20: =CY20-CX20 | DA20: =CY20-CW20 | DB20: =IF(CW20=0,"***",DA20/CW20) | DC20: =IF(CO20=0,"***",CV20/CO20) | DD20: =IF(CP20=0,"***",CW20/CP20) | DE20: =IF(CQ20=0,"***",CX20/CQ20) | DF20: =IF(CR20=0,"***",CY20/CR20) | DG20: =IF(DE20="***","***",DF20-DD20) | DH20: =IF(DF20="***","***",DF20-DD20)
F21: 広域営業部 | I21: =#REF!+I24+#REF! | J21: =#REF!+J24+#REF! | K21: =#REF!+K24+#REF! | L21: =#REF!+L24+#REF! | M21: =L21-K21 | N21: =L21-J21 | O21: =IF(J21=0,"***",N21/J21) | P21: =#REF!+P24+#REF! | Q21: =#REF!+Q24+#REF! | R21: =#REF!+R24+#REF! | S21: =#REF!+S24+#REF! | T21: =S21-R21 | U21: =S21-Q21 | V21: =IF(Q21=0,"***",U21/Q21) | W21: =#REF!+W24+#REF! | X21: =#REF!+X24+#REF! | Y21: =#REF!+Y24+#REF! | Z21: =#REF!+Z24+#REF! | AA21: =Z21-Y21 | AB21: =Z21-X21 | AC21: =IF(X21=0,"***",AB21/X21) | AD21: =#REF!+AD24+#REF! | AE21: =#REF!+AE24+#REF! | AF21: =#REF!+AF24+#REF! | AG21: =#REF!+AG24+#REF! | AH21: =AG21-AF21 | AI21: =AG21-AE21 | AJ21: =IF(AE21=0,"***",AI21/AE21) | AK21: =#REF!+AK24+#REF! | AL21: =#REF!+AL24+#REF! | AM21: =#REF!+AM24+#REF! | AN21: =#REF!+AN24+#REF! | AO21: =AN21-AM21 | AP21: =AN21-AL21 | AQ21: =IF(AL21=0,"***",AP21/AL21) | AR21: =#REF!+AR24+#REF! | AS21: =#REF!+AS24+#REF! | AT21: =#REF!+AT24+#REF! | AU21: =#REF!+AU24+#REF! | AV21: =AU21-AT21 | AW21: =AU21-AS21 | AX21: =IF(AS21=0,"***",AW21/AS21) | AY21: =#REF!+AY24+#REF! | AZ21: =#REF!+AZ24+#REF! | BA21: =#REF!+BA24+#REF! | BB21: =#REF!+BB24+#REF! | BC21: =BB21-BA21 | BD21: =BB21-AZ21 | BE21: =IF(AZ21=0,"***",BD21/AZ21) | BF21: =#REF!+BF24+#REF! | BG21: =#REF!+BG24+#REF! | BH21: =#REF!+BH24+#REF! | BI21: =#REF!+BI24+#REF! | BJ21: =BI21-BH21 | BK21: =BI21-BG21 | BL21: =IF(BG21=0,"***",BK21/BG21) | BM21: =#REF!+BM24+#REF! | BN21: =#REF!+BN24+#REF! | BO21: =#REF!+BO24+#REF! | BP21: =#REF!+BP24+#REF! | BQ21: =BP21-BO21 | BR21: =BP21-BN21 | BS21: =IF(BN21=0,"***",BR21/BN21) | BT21: =#REF!+BT24+#REF! | BU21: =#REF!+BU24+#REF! | BV21: =#REF!+BV24+#REF! | BW21: =#REF!+BW24+#REF! | BX21: =BW21-BV21 | BY21: =BW21-BU21 | BZ21: =IF(BU21=0,"***",BY21/BU21) | CA21: =#REF!+CA24+#REF! | CB21: =#REF!+CB24+#REF! | CC21: =#REF!+CC24+#REF! | CD21: =#REF!+CD24+#REF! | CE21: =CD21-CC21 | CF21: =CD21-CB21 | CG21: =IF(CB21=0,"***",CF21/CB21) | CH21: =#REF!+CH24+#REF! | CI21: =#REF!+CI24+#REF! | CJ21: =#REF!+CJ24+#REF! | CK21: =#REF!+CK24+#REF! | CL21: =CK21-CJ21 | CM21: =CK21-CI21 | CN21: =IF(CI21=0,"***",CM21/CI21) | CO21: 225907 | CP21: 254613 | CQ21: 290170 | CR21: 250634 | CS21: =CR21-CQ21 | CT21: =CR21-CP21 | CU21: =IF(CP21=0,"***",CT21/CP21) | CV21: 36377 | CW21: 37672 | CX21: 44430 | CY21: 36459 | CZ21: =CY21-CX21 | DA21: =CY21-CW21 | DB21: =IF(CW21=0,"***",DA21/CW21) | DC21: =IF(CO21=0,"***",CV21/CO21) | DD21: =IF(CP21=0,"***",CW21/CP21) | DE21: =IF(CQ21=0,"***",CX21/CQ21) | DF21: =IF(CR21=0,"***",CY21/CR21) | DG21: =IF(DE21="***","***",DF21-DD21) | DH21: =IF(DF21="***","***",DF21-DD21)
