Workbook

Sheet 機械
C1: 松江営業所機械
C2: 1．2024年
E3: 売上 | L3: 粗利益 | S3: 粗利益率
E4: 45383 | F4: 45413 | G4: 45444 | H4: 45474 | I4: 45505 | J4: 45536 | K4: 合計 | L4: 45383 | M4: 45413 | N4: 45444 | O4: 45474 | P4: 45505 | Q4: 45536 | R4: 合計 | S4: 45383 | T4: 45413 | U4: 45444 | V4: 45474 | W4: 45505 | X4: 45536 | Y4: 合計
C5: 0032 集計 | D5: 飯塚主任 | E5: 205 | F5: 2895 | G5: 20 | H5: 39 | I5: 210 | J5: -2216 | K5: =SUM(E5:J5) | L5: 45 | M5: 601 | N5: 6 | O5: 9 | P5: 49 | Q5: -441 | R5: =SUM(L5:Q5) | S5: =IF(E5=0,"***",L5/E5) | T5: =IF(F5=0,"***",M5/F5) | U5: =IF(G5=0,"***",N5/G5) | V5: =IF(H5=0,"***",O5/H5) | W5: =IF(I5=0,"***",P5/I5) | X5: =IF(J5=0,"***",Q5/J5) | Y5: =IF(K5=0,"***",R5/K5)
C6: 0033 集計 | D6: 前田課長代 | E6: 558 | F6: 155 | G6: 295 | H6: 126 | I6: 90 | J6: 116 | K6: =SUM(E6:J6) | L6: 130 | M6: 37 | N6: 38 | O6: 18 | P6: 11 | Q6: 35 | R6: =SUM(L6:Q6) | S6: =IF(E6=0,"***",L6/E6) | T6: =IF(F6=0,"***",M6/F6) | U6: =IF(G6=0,"***",N6/G6) | V6: =IF(H6=0,"***",O6/H6) | W6: =IF(I6=0,"***",P6/I6) | X6: =IF(J6=0,"***",Q6/J6) | Y6: =IF(K6=0,"***",R6/K6)
C7: 0034 集計 | D7: 原田 | G7: 97 | K7: =SUM(E7:J7) | N7: 19 | R7: =SUM(L7:Q7) | S7: =IF(E7=0,"***",L7/E7) | T7: =IF(F7=0,"***",M7/F7) | U7: =IF(G7=0,"***",N7/G7) | V7: =IF(H7=0,"***",O7/H7) | W7: =IF(I7=0,"***",P7/I7) | X7: =IF(J7=0,"***",Q7/J7) | Y7: =IF(K7=0,"***",R7/K7)
C8: 0035 集計 | D8: 自治体 | K8: =SUM(E8:J8) | R8: =SUM(L8:Q8) | S8: =IF(E8=0,"***",L8/E8) | T8: =IF(F8=0,"***",M8/F8) | U8: =IF(G8=0,"***",N8/G8) | V8: =IF(H8=0,"***",O8/H8) | W8: =IF(I8=0,"***",P8/I8) | X8: =IF(J8=0,"***",Q8/J8) | Y8: =IF(K8=0,"***",R8/K8)
C9: 0039 集計 | D9: その他 | K9: =SUM(E9:J9) | R9: =SUM(L9:Q9) | S9: =IF(E9=0,"***",L9/E9) | T9: =IF(F9=0,"***",M9/F9) | U9: =IF(G9=0,"***",N9/G9) | V9: =IF(H9=0,"***",O9/H9) | W9: =IF(I9=0,"***",P9/I9) | X9: =IF(J9=0,"***",Q9/J9) | Y9: =IF(K9=0,"***",R9/K9)
C10: 合計 | E10: =SUM(E5:E9) | F10: =SUM(F5:F9) | G10: =SUM(G5:G9) | H10: =SUM(H5:H9) | I10: =SUM(I5:I9) | J10: =SUM(J5:J9) | K10: =SUM(E10:J10) | L10: =SUM(L5:L9) | M10: =SUM(M5:M9) | N10: =SUM(N5:N9) | O10: =SUM(O5:O9) | P10: =SUM(P5:P9) | Q10: =SUM(Q5:Q9) | R10: =SUM(L10:Q10) | S10: =IF(E10=0,"***",L10/E10) | T10: =IF(F10=0,"***",M10/F10) | U10: =IF(G10=0,"***",N10/G10) | V10: =IF(H10=0,"***",O10/H10) | W10: =IF(I10=0,"***",P10/I10) | X10: =IF(J10=0,"***",Q10/J10) | Y10: =IF(K10=0,"***",R10/K10)
C12: 2．2025年
E13: 売上 | L13: 粗利益 | S13: 粗利益率
E14: 45748 | F14: 45778 | G14: 45809 | H14: 45839 | I14: 45870 | J14: 45901 | K14: 合計 | L14: 45748 | M14: 45778 | N14: 45809 | O14: 45839 | P14: 45870 | Q14: 45901 | R14: 合計 | S14: 45748 | T14: 45778 | U14: 45809 | V14: 45839 | W14: 45870 | X14: 45901 | Y14: 合計
C15: 0032 集計 | D15: 飯塚主任 | E15: 142 | F15: 131 | G15: 126 | H15: 48 | I15: 18 | J15: 1405 | K15: =SUM(E15:J15) | L15: 26 | M15: 26 | N15: 37 | O15: 11 | P15: 7 | Q15: 283 | R15: =SUM(L15:Q15) | S15: =IF(E15=0,"***",L15/E15) | T15: =IF(F15=0,"***",M15/F15) | U15: =IF(G15=0,"***",N15/G15) | V15: =IF(H15=0,"***",O15/H15) | W15: =IF(I15=0,"***",P15/I15) | X15: =IF(J15=0,"***",Q15/J15) | Y15: =IF(K15=0,"***",R15/K15)
C16: 0033 集計 | D16: 前田課長代 | E16: 718 | F16: 123 | G16: 164 | H16: 428 | I16: 201 | J16: 95 | K16: =SUM(E16:J16) | L16: 142 | M16: 16 | N16: 47 | O16: 49 | P16: 70 | Q16: 19 | R16: =SUM(L16:Q16) | S16: =IF(E16=0,"***",L16/E16) | T16: =IF(F16=0,"***",M16/F16) | U16: =IF(G16=0,"***",N16/G16) | V16: =IF(H16=0,"***",O16/H16) | W16: =IF(I16=0,"***",P16/I16) | X16: =IF(J16=0,"***",Q16/J16) | Y16: =IF(K16=0,"***",R16/K16)
C17: 0034 集計 | D17: 原田 | K17: =SUM(E17:J17) | R17: =SUM(L17:Q17) | S17: =IF(E17=0,"***",L17/E17) | T17: =IF(F17=0,"***",M17/F17) | U17: =IF(G17=0,"***",N17/G17) | V17: =IF(H17=0,"***",O17/H17) | W17: =IF(I17=0,"***",P17/I17) | X17: =IF(J17=0,"***",Q17/J17) | Y17: =IF(K17=0,"***",R17/K17)
C18: 0035 集計 | D18: 自治体 | E18: 0 | F18: 0 | G18: 0 | H18: 0 | I18: 0 | J18: 0 | K18: =SUM(E18:J18) | L18: 0 | M18: 0 | N18: 0 | O18: 0 | P18: 0 | Q18: 0 | R18: =SUM(L18:Q18) | S18: =IF(E18=0,"***",L18/E18) | T18: =IF(F18=0,"***",M18/F18) | U18: =IF(G18=0,"***",N18/G18) | V18: =IF(H18=0,"***",O18/H18) | W18: =IF(I18=0,"***",P18/I18) | X18: =IF(J18=0,"***",Q18/J18) | Y18: =IF(K18=0,"***",R18/K18)
C19: 0039 集計 | D19: その他 | E19: 21 | F19: 0 | G19: 0 | H19: 0 | I19: 0 | J19: 0 | K19: =SUM(E19:J19) | L19: 5 | M19: 0 | N19: 0 | O19: 0 | P19: 0 | Q19: 0 | R19: =SUM(L19:Q19) | S19: =IF(E19=0,"***",L19/E19) | T19: =IF(F19=0,"***",M19/F19) | U19: =IF(G19=0,"***",N19/G19) | V19: =IF(H19=0,"***",O19/H19) | W19: =IF(I19=0,"***",P19/I19) | X19: =IF(J19=0,"***",Q19/J19) | Y19: =IF(K19=0,"***",R19/K19)
C20: 合計 | E20: =SUM(E15:E19) | F20: =SUM(F15:F19) | G20: =SUM(G15:G19) | H20: =SUM(H15:H19) | I20: =SUM(I15:I19) | J20: =SUM(J15:J19) | K20: =SUM(E20:J20) | L20: =SUM(L15:L19) | M20: =SUM(M15:M19) | N20: =SUM(N15:N19) | O20: =SUM(O15:O19) | P20: =SUM(P15:P19) | Q20: =SUM(Q15:Q19) | R20: =SUM(L20:Q20) | S20: =IF(E20=0,"***",L20/E20) | T20: =IF(F20=0,"***",M20/F20) | U20: =IF(G20=0,"***",N20/G20) | V20: =IF(H20=0,"***",O20/H20) | W20: =IF(I20=0,"***",P20/I20) | X20: =IF(J20=0,"***",Q20/J20) | Y20: =IF(K20=0,"***",R20/K20)
C22: 3．過年度平均
E23: 売上 | L23: 粗利益 | S23: 粗利益率
E24: 45748 | F24: 45778 | G24: 45809 | H24: 45839 | I24: 45870 | J24: 45901 | K24: 合計 | L24: 45748 | M24: 45778 | N24: 45809 | O24: 45839 | P24: 45870 | Q24: 45901 | R24: 合計 | S24: 45748 | T24: 45778 | U24: 45809 | V24: 45839 | W24: 45870 | X24: 45901 | Y24: 合計
C25: 0032 集計 | D25: 飯塚主任 | E25: =(E15+E5)/2 | F25: =(F15+F5)/2 | G25: =(G15+G5)/2 | H25: =(H15+H5)/2 | I25: =(I15+I5)/2 | J25: =(J15+J5)/2 | K25: =SUM(E25:J25) | L25: =(L15+L5)/2 | M25: =(M15+M5)/2 | N25: =(N15+N5)/2 | O25: =(O15+O5)/2 | P25: =(P15+P5)/2 | Q25: =(Q15+Q5)/2 | R25: =SUM(L25:Q25) | S25: =IF(E25=0,"***",L25/E25) | T25: =IF(F25=0,"***",M25/F25) | U25: =IF(G25=0,"***",N25/G25) | V25: =IF(H25=0,"***",O25/H25) | W25: =IF(I25=0,"***",P25/I25) | X25: =IF(J25=0,"***",Q25/J25) | Y25: =IF(K25=0,"***",R25/K25)
C26: 0033 集計 | D26: 前田課長代 | E26: =(E16+E6)/2 | F26: =(F16+F6)/2 | G26: =(G16+G6)/2 | H26: =(H16+H6)/2 | I26: =(I16+I6)/2 | J26: =(J16+J6)/2 | K26: =SUM(E26:J26) | L26: =(L16+L6)/2 | M26: =(M16+M6)/2 | N26: =(N16+N6)/2 | O26: =(O16+O6)/2 | P26: =(P16+P6)/2 | Q26: =(Q16+Q6)/2 | R26: =SUM(L26:Q26) | S26: =IF(E26=0,"***",L26/E26) | T26: =IF(F26=0,"***",M26/F26) | U26: =IF(G26=0,"***",N26/G26) | V26: =IF(H26=0,"***",O26/H26) | W26: =IF(I26=0,"***",P26/I26) | X26: =IF(J26=0,"***",Q26/J26) | Y26: =IF(K26=0,"***",R26/K26)
C27: 0034 集計 | D27: 原田 | E27: =(E17+E7)/2 | F27: =(F17+F7)/2 | G27: =(G17+G7)/2 | H27: =(H17+H7)/2 | I27: =(I17+I7)/2 | J27: =(J17+J7)/2 | K27: =SUM(E27:J27) | L27: =(L17+L7)/2 | M27: =(M17+M7)/2 | N27: =(N17+N7)/2 | O27: =(O17+O7)/2 | P27: =(P17+P7)/2 | Q27: =(Q17+Q7)/2 | R27: =SUM(L27:Q27) | S27: =IF(E27=0,"***",L27/E27) | T27: =IF(F27=0,"***",M27/F27) | U27: =IF(G27=0,"***",N27/G27) | V27: =IF(H27=0,"***",O27/H27) | W27: =IF(I27=0,"***",P27/I27) | X27: =IF(J27=0,"***",Q27/J27) | Y27: =IF(K27=0,"***",R27/K27)
C28: 0035 集計 | D28: 自治体 | E28: =(E18+E8)/2 | F28: =(F18+F8)/2 | G28: =(G18+G8)/2 | H28: =(H18+H8)/2 | I28: =(I18+I8)/2 | J28: =(J18+J8)/2 | K28: =SUM(E28:J28) | L28: =(L18+L8)/2 | M28: =(M18+M8)/2 | N28: =(N18+N8)/2 | O28: =(O18+O8)/2 | P28: =(P18+P8)/2 | Q28: =(Q18+Q8)/2 | R28: =SUM(L28:Q28) | S28: =IF(E28=0,"***",L28/E28) | T28: =IF(F28=0,"***",M28/F28) | U28: =IF(G28=0,"***",N28/G28) | V28: =IF(H28=0,"***",O28/H28) | W28: =IF(I28=0,"***",P28/I28) | X28: =IF(J28=0,"***",Q28/J28) | Y28: =IF(K28=0,"***",R28/K28)
C29: 0039 集計 | D29: その他 | E29: =(E19+E9)/2 | F29: =(F19+F9)/2 | G29: =(G19+G9)/2 | H29: =(H19+H9)/2 | I29: =(I19+I9)/2 | J29: =(J19+J9)/2 | K29: =SUM(E29:J29) | L29: =(L19+L9)/2 | M29: =(M19+M9)/2 | N29: =(N19+N9)/2 | O29: =(O19+O9)/2 | P29: =(P19+P9)/2 | Q29: =(Q19+Q9)/2 | R29: =SUM(L29:Q29) | S29: =IF(E29=0,"***",L29/E29) | T29: =IF(F29=0,"***",M29/F29) | U29: =IF(G29=0,"***",N29/G29) | V29: =IF(H29=0,"***",O29/H29) | W29: =IF(I29=0,"***",P29/I29) | X29: =IF(J29=0,"***",Q29/J29) | Y29: =IF(K29=0,"***",R29/K29)
C30: 合計 | E30: =SUM(E25:E29) | F30: =SUM(F25:F29) | G30: =SUM(G25:G29) | H30: =SUM(H25:H29) | I30: =SUM(I25:I29) | J30: =SUM(J25:J29) | K30: =SUM(E30:J30) | L30: =SUM(L25:L29) | M30: =SUM(M25:M29) | N30: =SUM(N25:N29) | O30: =SUM(O25:O29) | P30: =SUM(P25:P29) | Q30: =SUM(Q25:Q29) | R30: =SUM(L30:Q30) | S30: =IF(E30=0,"***",L30/E30) | T30: =IF(F30=0,"***",M30/F30) | U30: =IF(G30=0,"***",N30/G30) | V30: =IF(H30=0,"***",O30/H30) | W30: =IF(I30=0,"***",P30/I30) | X30: =IF(J30=0,"***",Q30/J30) | Y30: =IF(K30=0,"***",R30/K30)
C32: 4．計画
E33: 売上 | L33: 粗利益 | S33: 粗利益率
E34: 46113 | F34: 46143 | G34: 46174 | H34: 46204 | I34: 46235 | J34: 46266 | K34: 合計 | L34: 46113 | M34: 46143 | N34: 46174 | O34: 46204 | P34: 46235 | Q34: 46266 | R34: 合計 | S34: 46113 | T34: 46143 | U34: 46174 | V34: 46204 | W34: 46235 | X34: 46266 | Y34: 合計
C35: 0032 集計 | D35: 飯塚主任 | E35: 200 | F35: 200 | G35: 200 | H35: 200 | I35: 200 | J35: 200 | K35: =SUM(E35:J35) | L35: 50 | M35: 50 | N35: 50 | O35: 50 | P35: 50 | Q35: 50 | R35: =SUM(L35:Q35) | S35: =IF(E35=0,"***",L35/E35) | T35: =IF(F35=0,"***",M35/F35) | U35: =IF(G35=0,"***",N35/G35) | V35: =IF(H35=0,"***",O35/H35) | W35: =IF(I35=0,"***",P35/I35) | X35: =IF(J35=0,"***",Q35/J35) | Y35: =IF(K35=0,"***",R35/K35)
C36: 0033 集計 | D36: 前田課長代 | E36: 200 | F36: 200 | G36: 200 | H36: 1100 | I36: 200 | J36: 200 | K36: =SUM(E36:J36) | L36: 50 | M36: 50 | N36: 50 | O36: 140 | P36: 50 | Q36: 50 | R36: =SUM(L36:Q36) | S36: =IF(E36=0,"***",L36/E36) | T36: =IF(F36=0,"***",M36/F36) | U36: =IF(G36=0,"***",N36/G36) | V36: =IF(H36=0,"***",O36/H36) | W36: =IF(I36=0,"***",P36/I36) | X36: =IF(J36=0,"***",Q36/J36) | Y36: =IF(K36=0,"***",R36/K36)
C37: 0034 集計 | D37: 原田 | E37: 100 | F37: 100 | G37: 100 | H37: 100 | I37: 100 | J37: 100 | K37: =SUM(E37:J37) | L37: 20 | M37: 20 | N37: 20 | O37: 20 | P37: 20 | Q37: 20 | R37: =SUM(L37:Q37) | S37: =IF(E37=0,"***",L37/E37) | T37: =IF(F37=0,"***",M37/F37) | U37: =IF(G37=0,"***",N37/G37) | V37: =IF(H37=0,"***",O37/H37) | W37: =IF(I37=0,"***",P37/I37) | X37: =IF(J37=0,"***",Q37/J37) | Y37: =IF(K37=0,"***",R37/K37)
C38: 0035 集計 | D38: 自治体 | K38: =SUM(E38:J38) | R38: =SUM(L38:Q38) | S38: =IF(E38=0,"***",L38/E38) | T38: =IF(F38=0,"***",M38/F38) | U38: =IF(G38=0,"***",N38/G38) | V38: =IF(H38=0,"***",O38/H38) | W38: =IF(I38=0,"***",P38/I38) | X38: =IF(J38=0,"***",Q38/J38) | Y38: =IF(K38=0,"***",R38/K38)
C39: 0039 集計 | D39: その他 | K39: =SUM(E39:J39) | R39: =SUM(L39:Q39) | S39: =IF(E39=0,"***",L39/E39) | T39: =IF(F39=0,"***",M39/F39) | U39: =IF(G39=0,"***",N39/G39) | V39: =IF(H39=0,"***",O39/H39) | W39: =IF(I39=0,"***",P39/I39) | X39: =IF(J39=0,"***",Q39/J39) | Y39: =IF(K39=0,"***",R39/K39)
C40: 合計 | E40: =SUM(E35:E39) | F40: =SUM(F35:F39) | G40: =SUM(G35:G39) | H40: =SUM(H35:H39) | I40: =SUM(I35:I39) | J40: =SUM(J35:J39) | K40: =SUM(E40:J40) | L40: =SUM(L35:L39) | M40: =SUM(M35:M39) | N40: =SUM(N35:N39) | O40: =SUM(O35:O39) | P40: =SUM(P35:P39) | Q40: =SUM(Q35:Q39) | R40: =SUM(L40:Q40) | S40: =IF(E40=0,"***",L40/E40) | T40: =IF(F40=0,"***",M40/F40) | U40: =IF(G40=0,"***",N40/G40) | V40: =IF(H40=0,"***",O40/H40) | W40: =IF(I40=0,"***",P40/I40) | X40: =IF(J40=0,"***",Q40/J40) | Y40: =IF(K40=0,"***",R40/K40)
C42: ５．前期比
E43: 売上 | L43: 粗利益 | S43: 粗利益率
E44: 46113 | F44: 46143 | G44: 46174 | H44: 46204 | I44: 46235 | J44: 46266 | K44: 合計 | L44: 46113 | M44: 46143 | N44: 46174 | O44: 46204 | P44: 46235 | Q44: 46266 | R44: 合計 | S44: 46113 | T44: 46143 | U44: 46174 | V44: 46204 | W44: 46235 | X44: 46266 | Y44: 合計
C45: 0032 集計 | D45: 飯塚主任 | E45: =E35-E15 | F45: =F35-F15 | G45: =G35-G15 | H45: =H35-H15 | I45: =I35-I15 | J45: =J35-J15 | K45: =SUM(E45:J45) | L45: =L35-L15 | M45: =M35-M15 | N45: =N35-N15 | O45: =O35-O15 | P45: =P35-P15 | Q45: =Q35-Q15 | R45: =SUM(L45:Q45) | S45: =S35-S15 | T45: =T35-T15 | U45: =U35-U15 | V45: =V35-V15 | W45: =W35-W15 | X45: =X35-X15 | Y45: =Y35-Y15
C46: 0033 集計 | D46: 前田課長代 | E46: =E36-E16 | F46: =F36-F16 | G46: =G36-G16 | H46: =H36-H16 | I46: =I36-I16 | J46: =J36-J16 | K46: =SUM(E46:J46) | L46: =L36-L16 | M46: =M36-M16 | N46: =N36-N16 | O46: =O36-O16 | P46: =P36-P16 | Q46: =Q36-Q16 | R46: =SUM(L46:Q46) | S46: =S36-S16 | T46: =T36-T16 | U46: =U36-U16 | V46: =V36-V16 | W46: =W36-W16 | X46: =X36-X16 | Y46: =Y36-Y16
C47: 0034 集計 | D47: 原田 | E47: =E37-E17 | F47: =F37-F17 | G47: =G37-G17 | H47: =H37-H17 | I47: =I37-I17 | J47: =J37-J17 | K47: =SUM(E47:J47) | L47: =L37-L17 | M47: =M37-M17 | N47: =N37-N17 | O47: =O37-O17 | P47: =P37-P17 | Q47: =Q37-Q17 | R47: =SUM(L47:Q47) | S47: =S37-S17 | T47: =T37-T17 | U47: =U37-U17 | V47: =V37-V17 | W47: =W37-W17 | X47: =X37-X17 | Y47: =Y37-Y17
C48: 0035 集計 | D48: 自治体 | E48: =E38-E18 | F48: =F38-F18 | G48: =G38-G18 | H48: =H38-H18 | I48: =I38-I18 | J48: =J38-J18 | K48: =SUM(E48:J48) | L48: =L38-L18 | M48: =M38-M18 | N48: =N38-N18 | O48: =O38-O18 | P48: =P38-P18 | Q48: =Q38-Q18 | R48: =SUM(L48:Q48) | S48: =S38-S18 | T48: =T38-T18 | U48: =U38-U18 | V48: =V38-V18 | W48: =W38-W18 | X48: =X38-X18 | Y48: =Y38-Y18
C49: 0039 集計 | D49: その他 | E49: =E39-E19 | F49: =F39-F19 | G49: =G39-G19 | H49: =H39-H19 | I49: =I39-I19 | J49: =J39-J19 | K49: =SUM(E49:J49) | L49: =L39-L19 | M49: =M39-M19 | N49: =N39-N19 | O49: =O39-O19 | P49: =P39-P19 | Q49: =Q39-Q19 | R49: =SUM(L49:Q49) | S49: =S39-S19 | T49: =T39-T19 | U49: =U39-U19 | V49: =V39-V19 | W49: =W39-W19 | X49: =X39-X19 | Y49: =Y39-Y19
C50: 合計 | E50: =SUM(E45:E49) | F50: =SUM(F45:F49) | G50: =SUM(G45:G49) | H50: =SUM(H45:H49) | I50: =SUM(I45:I49) | J50: =SUM(J45:J49) | K50: =SUM(E50:J50) | L50: =SUM(L45:L49) | M50: =SUM(M45:M49) | N50: =SUM(N45:N49) | O50: =SUM(O45:O49) | P50: =SUM(P45:P49) | Q50: =SUM(Q45:Q49) | R50: =SUM(L50:Q50) | S50: =S40-S20 | T50: =T40-T20 | U50: =U40-U20 | V50: =V40-V20 | W50: =W40-W20 | X50: =X40-X20 | Y50: =Y40-Y20
C52: 6．過年度平均比
E53: 売上 | L53: 粗利益 | S53: 粗利益率
E54: 46113 | F54: 46143 | G54: 46174 | H54: 46204 | I54: 46235 | J54: 46266 | K54: 合計 | L54: 46113 | M54: 46143 | N54: 46174 | O54: 46204 | P54: 46235 | Q54: 46266 | R54: 合計 | S54: 46113 | T54: 46143 | U54: 46174 | V54: 46204 | W54: 46235 | X54: 46266 | Y54: 合計
C55: 0032 集計 | D55: 飯塚主任 | E55: =E35-E25 | F55: =F35-F25 | G55: =G35-G25 | H55: =H35-H25 | I55: =I35-I25 | J55: =J35-J25 | K55: =SUM(E55:J55) | L55: =L35-L25 | M55: =M35-M25 | N55: =N35-N25 | O55: =O35-O25 | P55: =P35-P25 | Q55: =Q35-Q25 | R55: =SUM(L55:Q55) | S55: =S35-S25 | T55: =T35-T25 | U55: =U35-U25 | V55: =V35-V25 | W55: =W35-W25 | X55: =X35-X25 | Y55: =Y35-Y25
C56: 0033 集計 | D56: 前田課長代 | E56: =E36-E26 | F56: =F36-F26 | G56: =G36-G26 | H56: =H36-H26 | I56: =I36-I26 | J56: =J36-J26 | K56: =SUM(E56:J56) | L56: =L36-L26 | M56: =M36-M26 | N56: =N36-N26 | O56: =O36-O26 | P56: =P36-P26 | Q56: =Q36-Q26 | R56: =SUM(L56:Q56) | S56: =S36-S26 | T56: =T36-T26 | U56: =U36-U26 | V56: =V36-V26 | W56: =W36-W26 | X56: =X36-X26 | Y56: =Y36-Y26
C57: 0034 集計 | D57: 原田 | E57: =E37-E27 | F57: =F37-F27 | G57: =G37-G27 | H57: =H37-H27 | I57: =I37-I27 | J57: =J37-J27 | K57: =SUM(E57:J57) | L57: =L37-L27 | M57: =M37-M27 | N57: =N37-N27 | O57: =O37-O27 | P57: =P37-P27 | Q57: =Q37-Q27 | R57: =SUM(L57:Q57) | S57: =S37-S27 | T57: =T37-T27 | U57: =U37-U27 | V57: =V37-V27 | W57: =W37-W27 | X57: =X37-X27 | Y57: =Y37-Y27
C58: 0035 集計 | D58: 自治体 | E58: =E38-E28 | F58: =F38-F28 | G58: =G38-G28 | H58: =H38-H28 | I58: =I38-I28 | J58: =J38-J28 | K58: =SUM(E58:J58) | L58: =L38-L28 | M58: =M38-M28 | N58: =N38-N28 | O58: =O38-O28 | P58: =P38-P28 | Q58: =Q38-Q28 | R58: =SUM(L58:Q58) | S58: =S38-S28 | T58: =T38-T28 | U58: =U38-U28 | V58: =V38-V28 | W58: =W38-W28 | X58: =X38-X28 | Y58: =Y38-Y28
C59: 0039 集計 | D59: その他 | E59: =E39-E29 | F59: =F39-F29 | G59: =G39-G29 | H59: =H39-H29 | I59: =I39-I29 | J59: =J39-J29 | K59: =SUM(E59:J59) | L59: =L39-L29 | M59: =M39-M29 | N59: =N39-N29 | O59: =O39-O29 | P59: =P39-P29 | Q59: =Q39-Q29 | R59: =SUM(L59:Q59) | S59: =S39-S29 | T59: =T39-T29 | U59: =U39-U29 | V59: =V39-V29 | W59: =W39-W29 | X59: =X39-X29 | Y59: =Y39-Y29
C60: 合計 | E60: =SUM(E55:E59) | F60: =SUM(F55:F59) | G60: =SUM(G55:G59) | H60: =SUM(H55:H59) | I60: =SUM(I55:I59) | J60: =SUM(J55:J59) | K60: =SUM(E60:J60) | L60: =SUM(L55:L59) | M60: =SUM(M55:M59) | N60: =SUM(N55:N59) | O60: =SUM(O55:O59) | P60: =SUM(P55:P59) | Q60: =SUM(Q55:Q59) | R60: =SUM(L60:Q60) | S60: =S40-S30 | T60: =T40-T30 | U60: =U40-U30 | V60: =V40-V30 | W60: =W40-W30 | X60: =X40-X30 | Y60: =Y40-Y30
C62: 7．実績
E63: 売上 | L63: 粗利益 | S63: 粗利益率
E64: 46113 | F64: 46143 | G64: 46174 | H64: 46204 | I64: 46235 | J64: 46266 | K64: 合計 | L64: 46113 | M64: 46143 | N64: 46174 | O64: 46204 | P64: 46235 | Q64: 46266 | R64: 合計 | S64: 46113 | T64: 46143 | U64: 46174 | V64: 46204 | W64: 46235 | X64: 46266 | Y64: 合計
C65: 0032 集計 | D65: 飯塚主任 | E65: 403.225 | F65: 109.115 | G65: 67.7 | H65: 44.72 | I65: 756.14 | K65: =SUM(E65:J65) | L65: 81.835 | M65: 24.075 | N65: 24.31 | O65: 11.192 | P65: 151.195 | R65: =SUM(L65:Q65) | S65: =IF(E65=0,"***",L65/E65) | T65: =IF(F65=0,"***",M65/F65) | U65: =IF(G65=0,"***",N65/G65) | V65: =IF(H65=0,"***",O65/H65) | W65: =IF(I65=0,"***",P65/I65) | X65: =IF(J65=0,"***",Q65/J65) | Y65: =IF(K65=0,"***",R65/K65)
C66: 0033 集計 | D66: 前田課長代 | E66: 686.744 | F66: 333.19 | G66: 1864.34 | H66: 256 | I66: 695.7 | K66: =SUM(E66:J66) | L66: 136.484 | M66: 75.944 | N66: 420.08 | O66: 70.3 | P66: 148.74 | R66: =SUM(L66:Q66) | S66: =IF(E66=0,"***",L66/E66) | T66: =IF(F66=0,"***",M66/F66) | U66: =IF(G66=0,"***",N66/G66) | V66: =IF(H66=0,"***",O66/H66) | W66: =IF(I66=0,"***",P66/I66) | X66: =IF(J66=0,"***",Q66/J66) | Y66: =IF(K66=0,"***",R66/K66)
C67: 0034 集計 | D67: 原田 | E67: 69 | H67: 591.39 | I67: 0 | K67: =SUM(E67:J67) | L67: 9 | O67: 130.75 | P67: 0 | R67: =SUM(L67:Q67) | S67: =IF(E67=0,"***",L67/E67) | T67: =IF(F67=0,"***",M67/F67) | U67: =IF(G67=0,"***",N67/G67) | V67: =IF(H67=0,"***",O67/H67) | W67: =IF(I67=0,"***",P67/I67) | X67: =IF(J67=0,"***",Q67/J67) | Y67: =IF(K67=0,"***",R67/K67)
C68: 0035 集計 | D68: 自治体 | I68: 0 | K68: =SUM(E68:J68) | P68: 0 | R68: =SUM(L68:Q68) | S68: =IF(E68=0,"***",L68/E68) | T68: =IF(F68=0,"***",M68/F68) | U68: =IF(G68=0,"***",N68/G68) | V68: =IF(H68=0,"***",O68/H68) | W68: =IF(I68=0,"***",P68/I68) | X68: =IF(J68=0,"***",Q68/J68) | Y68: =IF(K68=0,"***",R68/K68)
C69: 0039 集計 | D69: その他 | E69: 8.5 | I69: 0 | K69: =SUM(E69:J69) | L69: 1.5 | P69: 0 | R69: =SUM(L69:Q69) | S69: =IF(E69=0,"***",L69/E69) | T69: =IF(F69=0,"***",M69/F69) | U69: =IF(G69=0,"***",N69/G69) | V69: =IF(H69=0,"***",O69/H69) | W69: =IF(I69=0,"***",P69/I69) | X69: =IF(J69=0,"***",Q69/J69) | Y69: =IF(K69=0,"***",R69/K69)
C70: 合計 | E70: =SUM(E65:E69) | F70: =SUM(F65:F69) | G70: =SUM(G65:G69) | H70: =SUM(H65:H69) | I70: =SUM(I65:I69) | J70: =SUM(J65:J69) | K70: =SUM(E70:J70) | L70: =SUM(L65:L69) | M70: =SUM(M65:M69) | N70: =SUM(N65:N69) | O70: =SUM(O65:O69) | P70: =SUM(P65:P69) | Q70: =SUM(Q65:Q69) | R70: =SUM(L70:Q70) | S70: =IF(E70=0,"***",L70/E70) | T70: =IF(F70=0,"***",M70/F70) | U70: =IF(G70=0,"***",N70/G70) | V70: =IF(H70=0,"***",O70/H70) | W70: =IF(I70=0,"***",P70/I70) | X70: =IF(J70=0,"***",Q70/J70) | Y70: =IF(K70=0,"***",R70/K70)
C72: 8．計画比
E73: 売上 | L73: 粗利益 | S73: 粗利益率
E74: 46113 | F74: 46143 | G74: 46174 | H74: 46204 | I74: 46235 | J74: 46266 | K74: 合計 | L74: 46113 | M74: 46143 | N74: 46174 | O74: 46204 | P74: 46235 | Q74: 46266 | R74: 合計 | S74: 46113 | T74: 46143 | U74: 46174 | V74: 46204 | W74: 46235 | X74: 46266 | Y74: 合計
C75: 0032 集計 | D75: 飯塚主任 | E75: =E65-E35 | F75: =F65-F35 | G75: =G65-G35 | H75: =H65-H35 | I75: =I65-I35 | K75: =SUM(E75:J75) | L75: =L65-L35 | M75: =M65-M35 | N75: =N65-N35 | O75: =O65-O35 | P75: =P65-P35 | R75: =SUM(L75:Q75) | S75: =S65-S35 | T75: =T65-T35 | U75: =U65-U35 | V75: =V65-V35 | W75: =W65-W35 | X75: =X65-X35 | Y75: =Y65-Y35
C76: 0033 集計 | D76: 前田課長代 | E76: =E66-E36 | F76: =F66-F36 | G76: =G66-G36 | H76: =H66-H36 | I76: =I66-I36 | K76: =SUM(E76:J76) | L76: =L66-L36 | M76: =M66-M36 | N76: =N66-N36 | O76: =O66-O36 | P76: =P66-P36 | R76: =SUM(L76:Q76) | S76: =S66-S36 | T76: =T66-T36 | U76: =U66-U36 | V76: =V66-V36 | W76: =W66-W36 | X76: =X66-X36 | Y76: =Y66-Y36
C77: 0034 集計 | D77: 原田 | E77: =E67-E37 | F77: =F67-F37 | G77: =G67-G37 | H77: =H67-H37 | I77: =I67-I37 | K77: =SUM(E77:J77) | L77: =L67-L37 | M77: =M67-M37 | N77: =N67-N37 | O77: =O67-O37 | P77: =P67-P37 | R77: =SUM(L77:Q77) | S77: =S67-S37 | T77: =T67-T37 | U77: =U67-U37 | V77: =V67-V37 | W77: =W67-W37 | X77: =X67-X37 | Y77: =Y67-Y37
C78: 0035 集計 | D78: 自治体 | E78: =E68-E38 | F78: =F68-F38 | G78: =G68-G38 | H78: =H68-H38 | I78: =I68-I38 | K78: =SUM(E78:J78) | L78: =L68-L38 | M78: =M68-M38 | N78: =N68-N38 | O78: =O68-O38 | P78: =P68-P38 | R78: =SUM(L78:Q78) | S78: =S68-S38 | T78: =T68-T38 | U78: =U68-U38 | V78: =V68-V38 | W78: =W68-W38 | X78: =X68-X38 | Y78: =Y68-Y38
C79: 0039 集計 | D79: その他 | E79: =E69-E39 | F79: =F69-F39 | G79: =G69-G39 | H79: =H69-H39 | I79: =I69-I39 | K79: =SUM(E79:J79) | L79: =L69-L39 | M79: =M69-M39 | N79: =N69-N39 | O79: =O69-O39 | P79: =P69-P39 | R79: =SUM(L79:Q79) | S79: =S69-S39 | T79: =T69-T39 | U79: =U69-U39 | V79: =V69-V39 | W79: =W69-W39 | X79: =X69-X39 | Y79: =Y69-Y39
C80: 合計 | E80: =SUM(E75:E79) | F80: =SUM(F75:F79) | G80: =SUM(G75:G79) | H80: =SUM(H75:H79) | I80: =SUM(I75:I79) | J80: =SUM(J75:J79) | K80: =SUM(E80:J80) | L80: =SUM(L75:L79) | M80: =SUM(M75:M79) | N80: =SUM(N75:N79) | O80: =SUM(O75:O79) | P80: =SUM(P75:P79) | Q80: =SUM(Q75:Q79) | R80: =SUM(L80:Q80) | S80: =S70-S40 | T80: =T70-T40 | U80: =U70-U40 | V80: =V70-V40 | W80: =W70-W40 | X80: =X70-X40 | Y80: =Y70-Y40
C82: 9．前期比
E83: 売上 | L83: 粗利益 | S83: 粗利益率
E84: 46113 | F84: 46143 | G84: 46174 | H84: 46204 | I84: 46235 | J84: 46266 | K84: 合計 | L84: 46113 | M84: 46143 | N84: 46174 | O84: 46204 | P84: 46235 | Q84: 46266 | R84: 合計 | S84: 46113 | T84: 46143 | U84: 46174 | V84: 46204 | W84: 46235 | X84: 46266 | Y84: 合計
C85: 0032 集計 | D85: 飯塚主任 | E85: =E65-E15 | F85: =F65-F15 | G85: =G65-G15 | H85: =H65-H15 | I85: =I65-I15 | K85: =SUM(E85:J85) | L85: =L65-L15 | M85: =M65-M15 | N85: =N65-N15 | O85: =O65-O15 | P85: =P65-P15 | R85: =SUM(L85:Q85) | S85: =S65-S15 | T85: =T65-T15 | U85: =U65-U15 | V85: =V65-V15 | W85: =W65-W15 | X85: =X65-X15 | Y85: =Y65-Y15
C86: 0033 集計 | D86: 前田課長代 | E86: =E66-E16 | F86: =F66-F16 | G86: =G66-G16 | H86: =H66-H16 | I86: =I66-I16 | K86: =SUM(E86:J86) | L86: =L66-L16 | M86: =M66-M16 | N86: =N66-N16 | O86: =O66-O16 | P86: =P66-P16 | R86: =SUM(L86:Q86) | S86: =S66-S16 | T86: =T66-T16 | U86: =U66-U16 | V86: =V66-V16 | W86: =W66-W16 | X86: =X66-X16 | Y86: =Y66-Y16
C87: 0034 集計 | D87: 原田 | E87: =E67-E17 | F87: =F67-F17 | G87: =G67-G17 | H87: =H67-H17 | I87: =I67-I17 | K87: =SUM(E87:J87) | L87: =L67-L17 | M87: =M67-M17 | N87: =N67-N17 | O87: =O67-O17 | P87: =P67-P17 | R87: =SUM(L87:Q87) | S87: =S67-S17 | T87: =T67-T17 | U87: =U67-U17 | V87: =V67-V17 | W87: =W67-W17 | X87: =X67-X17 | Y87: =Y67-Y17
C88: 0035 集計 | D88: 自治体 | E88: =E68-E18 | F88: =F68-F18 | G88: =G68-G18 | H88: =H68-H18 | I88: =I68-I18 | K88: =SUM(E88:J88) | L88: =L68-L18 | M88: =M68-M18 | N88: =N68-N18 | O88: =O68-O18 | P88: =P68-P18 | R88: =SUM(L88:Q88) | S88: =S68-S18 | T88: =T68-T18 | U88: =U68-U18 | V88: =V68-V18 | W88: =W68-W18 | X88: =X68-X18 | Y88: =Y68-Y18
C89: 0039 集計 | D89: その他 | E89: =E69-E19 | F89: =F69-F19 | G89: =G69-G19 | H89: =H69-H19 | I89: =I69-I19 | K89: =SUM(E89:J89) | L89: =L69-L19 | M89: =M69-M19 | N89: =N69-N19 | O89: =O69-O19 | P89: =P69-P19 | R89: =SUM(L89:Q89) | S89: =S69-S19 | T89: =T69-T19 | U89: =U69-U19 | V89: =V69-V19 | W89: =W69-W19 | X89: =X69-X19 | Y89: =Y69-Y19
C90: 合計 | E90: =SUM(E85:E89) | F90: =SUM(F85:F89) | G90: =SUM(G85:G89) | H90: =SUM(H85:H89) | I90: =SUM(I85:I89) | J90: =SUM(J85:J89) | K90: =SUM(E90:J90) | L90: =SUM(L85:L89) | M90: =SUM(M85:M89) | N90: =SUM(N85:N89) | O90: =SUM(O85:O89) | P90: =SUM(P85:P89) | Q90: =SUM(Q85:Q89) | R90: =SUM(L90:Q90) | S90: =S70-S20 | T90: =T70-T20 | U90: =U70-U20 | V90: =V70-V20 | W90: =W70-W20 | X90: =X70-X20 | Y90: =Y70-Y20

Sheet 包装資材
C1: 松江営業所包装資材
C2: 1．2024年
E3: 売上 | L3: 粗利益 | S3: 粗利益率
E4: 45383 | F4: 45413 | G4: 45444 | H4: 45474 | I4: 45505 | J4: 45536 | K4: 合計 | L4: 45383 | M4: 45413 | N4: 45444 | O4: 45474 | P4: 45505 | Q4: 45536 | R4: 合計 | S4: 45383 | T4: 45413 | U4: 45444 | V4: 45474 | W4: 45505 | X4: 45536 | Y4: 合計
C5: 0032 集計 | D5: 飯塚主任 | E5: =全体!E5-機械!E5 | F5: =全体!F5-機械!F5 | G5: =全体!G5-機械!G5 | H5: =全体!H5-機械!H5 | I5: =全体!I5-機械!I5 | J5: =全体!J5-機械!J5 | K5: =SUM(E5:J5) | L5: =全体!L5-機械!L5 | M5: =全体!M5-機械!M5 | N5: =全体!N5-機械!N5 | O5: =全体!O5-機械!O5 | P5: =全体!P5-機械!P5 | Q5: =全体!Q5-機械!Q5 | R5: =SUM(L5:Q5) | S5: =IF(E5=0,"***",L5/E5) | T5: =IF(F5=0,"***",M5/F5) | U5: =IF(G5=0,"***",N5/G5) | V5: =IF(H5=0,"***",O5/H5) | W5: =IF(I5=0,"***",P5/I5) | X5: =IF(J5=0,"***",Q5/J5) | Y5: =IF(K5=0,"***",R5/K5)
C6: 0033 集計 | D6: 前田課長代 | E6: =全体!E6-機械!E6 | F6: =全体!F6-機械!F6 | G6: =全体!G6-機械!G6 | H6: =全体!H6-機械!H6 | I6: =全体!I6-機械!I6 | J6: =全体!J6-機械!J6 | K6: =SUM(E6:J6) | L6: =全体!L6-機械!L6 | M6: =全体!M6-機械!M6 | N6: =全体!N6-機械!N6 | O6: =全体!O6-機械!O6 | P6: =全体!P6-機械!P6 | Q6: =全体!Q6-機械!Q6 | R6: =SUM(L6:Q6) | S6: =IF(E6=0,"***",L6/E6) | T6: =IF(F6=0,"***",M6/F6) | U6: =IF(G6=0,"***",N6/G6) | V6: =IF(H6=0,"***",O6/H6) | W6: =IF(I6=0,"***",P6/I6) | X6: =IF(J6=0,"***",Q6/J6) | Y6: =IF(K6=0,"***",R6/K6)
C7: 0034 集計 | D7: 原田 | E7: =全体!E7-機械!E7 | F7: =全体!F7-機械!F7 | G7: =全体!G7-機械!G7 | H7: =全体!H7-機械!H7 | I7: =全体!I7-機械!I7 | J7: =全体!J7-機械!J7 | K7: =SUM(E7:J7) | L7: =全体!L7-機械!L7 | M7: =全体!M7-機械!M7 | N7: =全体!N7-機械!N7 | O7: =全体!O7-機械!O7 | P7: =全体!P7-機械!P7 | Q7: =全体!Q7-機械!Q7 | R7: =SUM(L7:Q7) | S7: =IF(E7=0,"***",L7/E7) | T7: =IF(F7=0,"***",M7/F7) | U7: =IF(G7=0,"***",N7/G7) | V7: =IF(H7=0,"***",O7/H7) | W7: =IF(I7=0,"***",P7/I7) | X7: =IF(J7=0,"***",Q7/J7) | Y7: =IF(K7=0,"***",R7/K7)
C8: 0035 集計 | D8: 自治体 | E8: =全体!E8-機械!E8 | F8: =全体!F8-機械!F8 | G8: =全体!G8-機械!G8 | H8: =全体!H8-機械!H8 | I8: =全体!I8-機械!I8 | J8: =全体!J8-機械!J8 | K8: =SUM(E8:J8) | L8: =全体!L8-機械!L8 | M8: =全体!M8-機械!M8 | N8: =全体!N8-機械!N8 | O8: =全体!O8-機械!O8 | P8: =全体!P8-機械!P8 | Q8: =全体!Q8-機械!Q8 | R8: =SUM(L8:Q8) | S8: =IF(E8=0,"***",L8/E8) | T8: =IF(F8=0,"***",M8/F8) | U8: =IF(G8=0,"***",N8/G8) | V8: =IF(H8=0,"***",O8/H8) | W8: =IF(I8=0,"***",P8/I8) | X8: =IF(J8=0,"***",Q8/J8) | Y8: =IF(K8=0,"***",R8/K8)
C9: 0039 集計 | D9: その他 | E9: =全体!E9-機械!E9 | F9: =全体!F9-機械!F9 | G9: =全体!G9-機械!G9 | H9: =全体!H9-機械!H9 | I9: =全体!I9-機械!I9 | J9: =全体!J9-機械!J9 | K9: =SUM(E9:J9) | L9: =全体!L9-機械!L9 | M9: =全体!M9-機械!M9 | N9: =全体!N9-機械!N9 | O9: =全体!O9-機械!O9 | P9: =全体!P9-機械!P9 | Q9: =全体!Q9-機械!Q9 | R9: =SUM(L9:Q9) | S9: =IF(E9=0,"***",L9/E9) | T9: =IF(F9=0,"***",M9/F9) | U9: =IF(G9=0,"***",N9/G9) | V9: =IF(H9=0,"***",O9/H9) | W9: =IF(I9=0,"***",P9/I9) | X9: =IF(J9=0,"***",Q9/J9) | Y9: =IF(K9=0,"***",R9/K9)
C10: 合計 | E10: =SUM(E5:E9) | F10: =SUM(F5:F9) | G10: =SUM(G5:G9) | H10: =SUM(H5:H9) | I10: =SUM(I5:I9) | J10: =SUM(J5:J9) | K10: =SUM(E10:J10) | L10: =SUM(L5:L9) | M10: =SUM(M5:M9) | N10: =SUM(N5:N9) | O10: =SUM(O5:O9) | P10: =SUM(P5:P9) | Q10: =SUM(Q5:Q9) | R10: =SUM(L10:Q10) | S10: =IF(E10=0,"***",L10/E10) | T10: =IF(F10=0,"***",M10/F10) | U10: =IF(G10=0,"***",N10/G10) | V10: =IF(H10=0,"***",O10/H10) | W10: =IF(I10=0,"***",P10/I10) | X10: =IF(J10=0,"***",Q10/J10) | Y10: =IF(K10=0,"***",R10/K10)
C12: 2．2025年
E13: 売上 | L13: 粗利益 | S13: 粗利益率
E14: 45748 | F14: 45778 | G14: 45809 | H14: 45839 | I14: 45870 | J14: 45901 | K14: 合計 | L14: 45748 | M14: 45778 | N14: 45809 | O14: 45839 | P14: 45870 | Q14: 45901 | R14: 合計 | S14: 45748 | T14: 45778 | U14: 45809 | V14: 45839 | W14: 45870 | X14: 45901 | Y14: 合計
C15: 0032 集計 | D15: 飯塚主任 | E15: =全体!E15-機械!E15 | F15: =全体!F15-機械!F15 | G15: =全体!G15-機械!G15 | H15: =全体!H15-機械!H15 | I15: =全体!I15-機械!I15 | J15: =全体!J15-機械!J15 | K15: =SUM(E15:J15) | L15: =全体!L15-機械!L15 | M15: =全体!M15-機械!M15 | N15: =全体!N15-機械!N15 | O15: =全体!O15-機械!O15 | P15: =全体!P15-機械!P15 | Q15: =全体!Q15-機械!Q15 | R15: =SUM(L15:Q15) | S15: =IF(E15=0,"***",L15/E15) | T15: =IF(F15=0,"***",M15/F15) | U15: =IF(G15=0,"***",N15/G15) | V15: =IF(H15=0,"***",O15/H15) | W15: =IF(I15=0,"***",P15/I15) | X15: =IF(J15=0,"***",Q15/J15) | Y15: =IF(K15=0,"***",R15/K15)
C16: 0033 集計 | D16: 前田課長代 | E16: =全体!E16-機械!E16 | F16: =全体!F16-機械!F16 | G16: =全体!G16-機械!G16 | H16: =全体!H16-機械!H16 | I16: =全体!I16-機械!I16 | J16: =全体!J16-機械!J16 | K16: =SUM(E16:J16) | L16: =全体!L16-機械!L16 | M16: =全体!M16-機械!M16 | N16: =全体!N16-機械!N16 | O16: =全体!O16-機械!O16 | P16: =全体!P16-機械!P16 | Q16: =全体!Q16-機械!Q16 | R16: =SUM(L16:Q16) | S16: =IF(E16=0,"***",L16/E16) | T16: =IF(F16=0,"***",M16/F16) | U16: =IF(G16=0,"***",N16/G16) | V16: =IF(H16=0,"***",O16/H16) | W16: =IF(I16=0,"***",P16/I16) | X16: =IF(J16=0,"***",Q16/J16) | Y16: =IF(K16=0,"***",R16/K16)
C17: 0034 集計 | D17: 原田 | E17: =全体!E17-機械!E17 | F17: =全体!F17-機械!F17 | G17: =全体!G17-機械!G17 | H17: =全体!H17-機械!H17 | I17: =全体!I17-機械!I17 | J17: =全体!J17-機械!J17 | K17: =SUM(E17:J17) | L17: =全体!L17-機械!L17 | M17: =全体!M17-機械!M17 | N17: =全体!N17-機械!N17 | O17: =全体!O17-機械!O17 | P17: =全体!P17-機械!P17 | Q17: =全体!Q17-機械!Q17 | R17: =SUM(L17:Q17) | S17: =IF(E17=0,"***",L17/E17) | T17: =IF(F17=0,"***",M17/F17) | U17: =IF(G17=0,"***",N17/G17) | V17: =IF(H17=0,"***",O17/H17) | W17: =IF(I17=0,"***",P17/I17) | X17: =IF(J17=0,"***",Q17/J17) | Y17: =IF(K17=0,"***",R17/K17)
C18: 0035 集計 | D18: 自治体 | E18: =全体!E18-機械!E18 | F18: =全体!F18-機械!F18 | G18: =全体!G18-機械!G18 | H18: =全体!H18-機械!H18 | I18: =全体!I18-機械!I18 | J18: =全体!J18-機械!J18 | K18: =SUM(E18:J18) | L18: =全体!L18-機械!L18 | M18: =全体!M18-機械!M18 | N18: =全体!N18-機械!N18 | O18: =全体!O18-機械!O18 | P18: =全体!P18-機械!P18 | Q18: =全体!Q18-機械!Q18 | R18: =SUM(L18:Q18) | S18: =IF(E18=0,"***",L18/E18) | T18: =IF(F18=0,"***",M18/F18) | U18: =IF(G18=0,"***",N18/G18) | V18: =IF(H18=0,"***",O18/H18) | W18: =IF(I18=0,"***",P18/I18) | X18: =IF(J18=0,"***",Q18/J18) | Y18: =IF(K18=0,"***",R18/K18)
C19: 0039 集計 | D19: その他 | E19: =全体!E19-機械!E19 | F19: =全体!F19-機械!F19 | G19: =全体!G19-機械!G19 | H19: =全体!H19-機械!H19 | I19: =全体!I19-機械!I19 | J19: =全体!J19-機械!J19 | K19: =SUM(E19:J19) | L19: =全体!L19-機械!L19 | M19: =全体!M19-機械!M19 | N19: =全体!N19-機械!N19 | O19: =全体!O19-機械!O19 | P19: =全体!P19-機械!P19 | Q19: =全体!Q19-機械!Q19 | R19: =SUM(L19:Q19) | S19: =IF(E19=0,"***",L19/E19) | T19: =IF(F19=0,"***",M19/F19) | U19: =IF(G19=0,"***",N19/G19) | V19: =IF(H19=0,"***",O19/H19) | W19: =IF(I19=0,"***",P19/I19) | X19: =IF(J19=0,"***",Q19/J19) | Y19: =IF(K19=0,"***",R19/K19)
C20: 合計 | E20: =SUM(E15:E19) | F20: =SUM(F15:F19) | G20: =SUM(G15:G19) | H20: =SUM(H15:H19) | I20: =SUM(I15:I19) | J20: =SUM(J15:J19) | K20: =SUM(E20:J20) | L20: =SUM(L15:L19) | M20: =SUM(M15:M19) | N20: =SUM(N15:N19) | O20: =SUM(O15:O19) | P20: =SUM(P15:P19) | Q20: =SUM(Q15:Q19) | R20: =SUM(L20:Q20) | S20: =IF(E20=0,"***",L20/E20) | T20: =IF(F20=0,"***",M20/F20) | U20: =IF(G20=0,"***",N20/G20) | V20: =IF(H20=0,"***",O20/H20) | W20: =IF(I20=0,"***",P20/I20) | X20: =IF(J20=0,"***",Q20/J20) | Y20: =IF(K20=0,"***",R20/K20)
C22: 3．過年度平均
E23: 売上 | L23: 粗利益 | S23: 粗利益率
E24: 45748 | F24: 45778 | G24: 45809 | H24: 45839 | I24: 45870 | J24: 45901 | K24: 合計 | L24: 45748 | M24: 45778 | N24: 45809 | O24: 45839 | P24: 45870 | Q24: 45901 | R24: 合計 | S24: 45748 | T24: 45778 | U24: 45809 | V24: 45839 | W24: 45870 | X24: 45901 | Y24: 合計
C25: 0032 集計 | D25: 飯塚主任 | E25: =(E15+E5)/2 | F25: =(F15+F5)/2 | G25: =(G15+G5)/2 | H25: =(H15+H5)/2 | I25: =(I15+I5)/2 | J25: =(J15+J5)/2 | K25: =SUM(E25:J25) | L25: =(L15+L5)/2 | M25: =(M15+M5)/2 | N25: =(N15+N5)/2 | O25: =(O15+O5)/2 | P25: =(P15+P5)/2 | Q25: =(Q15+Q5)/2 | R25: =SUM(L25:Q25) | S25: =IF(E25=0,"***",L25/E25) | T25: =IF(F25=0,"***",M25/F25) | U25: =IF(G25=0,"***",N25/G25) | V25: =IF(H25=0,"***",O25/H25) | W25: =IF(I25=0,"***",P25/I25) | X25: =IF(J25=0,"***",Q25/J25) | Y25: =IF(K25=0,"***",R25/K25)
C26: 0033 集計 | D26: 前田課長代 | E26: =(E16+E6)/2 | F26: =(F16+F6)/2 | G26: =(G16+G6)/2 | H26: =(H16+H6)/2 | I26: =(I16+I6)/2 | J26: =(J16+J6)/2 | K26: =SUM(E26:J26) | L26: =(L16+L6)/2 | M26: =(M16+M6)/2 | N26: =(N16+N6)/2 | O26: =(O16+O6)/2 | P26: =(P16+P6)/2 | Q26: =(Q16+Q6)/2 | R26: =SUM(L26:Q26) | S26: =IF(E26=0,"***",L26/E26) | T26: =IF(F26=0,"***",M26/F26) | U26: =IF(G26=0,"***",N26/G26) | V26: =IF(H26=0,"***",O26/H26) | W26: =IF(I26=0,"***",P26/I26) | X26: =IF(J26=0,"***",Q26/J26) | Y26: =IF(K26=0,"***",R26/K26)
C27: 0034 集計 | D27: 原田 | E27: =(E17+E7)/2 | F27: =(F17+F7)/2 | G27: =(G17+G7)/2 | H27: =(H17+H7)/2 | I27: =(I17+I7)/2 | J27: =(J17+J7)/2 | K27: =SUM(E27:J27) | L27: =(L17+L7)/2 | M27: =(M17+M7)/2 | N27: =(N17+N7)/2 | O27: =(O17+O7)/2 | P27: =(P17+P7)/2 | Q27: =(Q17+Q7)/2 | R27: =SUM(L27:Q27) | S27: =IF(E27=0,"***",L27/E27) | T27: =IF(F27=0,"***",M27/F27) | U27: =IF(G27=0,"***",N27/G27) | V27: =IF(H27=0,"***",O27/H27) | W27: =IF(I27=0,"***",P27/I27) | X27: =IF(J27=0,"***",Q27/J27) | Y27: =IF(K27=0,"***",R27/K27)
C28: 0035 集計 | D28: 自治体 | E28: =(E18+E8)/2 | F28: =(F18+F8)/2 | G28: =(G18+G8)/2 | H28: =(H18+H8)/2 | I28: =(I18+I8)/2 | J28: =(J18+J8)/2 | K28: =SUM(E28:J28) | L28: =(L18+L8)/2 | M28: =(M18+M8)/2 | N28: =(N18+N8)/2 | O28: =(O18+O8)/2 | P28: =(P18+P8)/2 | Q28: =(Q18+Q8)/2 | R28: =SUM(L28:Q28) | S28: =IF(E28=0,"***",L28/E28) | T28: =IF(F28=0,"***",M28/F28) | U28: =IF(G28=0,"***",N28/G28) | V28: =IF(H28=0,"***",O28/H28) | W28: =IF(I28=0,"***",P28/I28) | X28: =IF(J28=0,"***",Q28/J28) | Y28: =IF(K28=0,"***",R28/K28)
C29: 0039 集計 | D29: その他 | E29: =(E19+E9)/2 | F29: =(F19+F9)/2 | G29: =(G19+G9)/2 | H29: =(H19+H9)/2 | I29: =(I19+I9)/2 | J29: =(J19+J9)/2 | K29: =SUM(E29:J29) | L29: =(L19+L9)/2 | M29: =(M19+M9)/2 | N29: =(N19+N9)/2 | O29: =(O19+O9)/2 | P29: =(P19+P9)/2 | Q29: =(Q19+Q9)/2 | R29: =SUM(L29:Q29) | S29: =IF(E29=0,"***",L29/E29) | T29: =IF(F29=0,"***",M29/F29) | U29: =IF(G29=0,"***",N29/G29) | V29: =IF(H29=0,"***",O29/H29) | W29: =IF(I29=0,"***",P29/I29) | X29: =IF(J29=0,"***",Q29/J29) | Y29: =IF(K29=0,"***",R29/K29)
C30: 合計 | E30: =SUM(E25:E29) | F30: =SUM(F25:F29) | G30: =SUM(G25:G29) | H30: =SUM(H25:H29) | I30: =SUM(I25:I29) | J30: =SUM(J25:J29) | K30: =SUM(E30:J30) | L30: =SUM(L25:L29) | M30: =SUM(M25:M29) | N30: =SUM(N25:N29) | O30: =SUM(O25:O29) | P30: =SUM(P25:P29) | Q30: =SUM(Q25:Q29) | R30: =SUM(L30:Q30) | S30: =IF(E30=0,"***",L30/E30) | T30: =IF(F30=0,"***",M30/F30) | U30: =IF(G30=0,"***",N30/G30) | V30: =IF(H30=0,"***",O30/H30) | W30: =IF(I30=0,"***",P30/I30) | X30: =IF(J30=0,"***",Q30/J30) | Y30: =IF(K30=0,"***",R30/K30)
C32: 4．計画
E33: 売上 | L33: 粗利益 | S33: 粗利益率
E34: 46113 | F34: 46143 | G34: 46174 | H34: 46204 | I34: 46235 | J34: 46266 | K34: 合計 | L34: 46113 | M34: 46143 | N34: 46174 | O34: 46204 | P34: 46235 | Q34: 46266 | R34: 合計 | S34: 46113 | T34: 46143 | U34: 46174 | V34: 46204 | W34: 46235 | X34: 46266 | Y34: 合計
C35: 0032 集計 | D35: 飯塚主任 | E35: 11600 | F35: 10220 | G35: 8550 | H35: 9970 | I35: 11590 | J35: 8200 | K35: =SUM(E35:J35) | L35: 3490 | M35: 3000 | N35: 2640 | O35: 2990 | P35: 3510 | Q35: 2800 | R35: =SUM(L35:Q35) | S35: =IF(E35=0,"***",L35/E35) | T35: =IF(F35=0,"***",M35/F35) | U35: =IF(G35=0,"***",N35/G35) | V35: =IF(H35=0,"***",O35/H35) | W35: =IF(I35=0,"***",P35/I35) | X35: =IF(J35=0,"***",Q35/J35) | Y35: =IF(K35=0,"***",R35/K35)
C36: 0033 集計 | D36: 前田課長代 | E36: 10750 | F36: 7960 | G36: 9980 | H36: 10050 | I36: 9310 | J36: 9350 | K36: =SUM(E36:J36) | L36: 2670 | M36: 2040 | N36: 2110 | O36: 2270 | P36: 2230 | Q36: 2320 | R36: =SUM(L36:Q36) | S36: =IF(E36=0,"***",L36/E36) | T36: =IF(F36=0,"***",M36/F36) | U36: =IF(G36=0,"***",N36/G36) | V36: =IF(H36=0,"***",O36/H36) | W36: =IF(I36=0,"***",P36/I36) | X36: =IF(J36=0,"***",Q36/J36) | Y36: =IF(K36=0,"***",R36/K36)
C37: 0034 集計 | D37: 原田 | E37: 9800 | F37: 7990 | G37: 8070 | H37: 10030 | I37: 9570 | J37: 9610 | K37: =SUM(E37:J37) | L37: 2350 | M37: 1870 | N37: 1840 | O37: 2300 | P37: 2170 | Q37: 2170 | R37: =SUM(L37:Q37) | S37: =IF(E37=0,"***",L37/E37) | T37: =IF(F37=0,"***",M37/F37) | U37: =IF(G37=0,"***",N37/G37) | V37: =IF(H37=0,"***",O37/H37) | W37: =IF(I37=0,"***",P37/I37) | X37: =IF(J37=0,"***",Q37/J37) | Y37: =IF(K37=0,"***",R37/K37)
C38: 0035 集計 | D38: 自治体 | K38: =SUM(E38:J38) | R38: =SUM(L38:Q38) | S38: =IF(E38=0,"***",L38/E38) | T38: =IF(F38=0,"***",M38/F38) | U38: =IF(G38=0,"***",N38/G38) | V38: =IF(H38=0,"***",O38/H38) | W38: =IF(I38=0,"***",P38/I38) | X38: =IF(J38=0,"***",Q38/J38) | Y38: =IF(K38=0,"***",R38/K38)
C39: 0039 集計 | D39: その他 | K39: =SUM(E39:J39) | R39: =SUM(L39:Q39) | S39: =IF(E39=0,"***",L39/E39) | T39: =IF(F39=0,"***",M39/F39) | U39: =IF(G39=0,"***",N39/G39) | V39: =IF(H39=0,"***",O39/H39) | W39: =IF(I39=0,"***",P39/I39) | X39: =IF(J39=0,"***",Q39/J39) | Y39: =IF(K39=0,"***",R39/K39)
C40: 合計 | E40: =SUM(E35:E39) | F40: =SUM(F35:F39) | G40: =SUM(G35:G39) | H40: =SUM(H35:H39) | I40: =SUM(I35:I39) | J40: =SUM(J35:J39) | K40: =SUM(E40:J40) | L40: =SUM(L35:L39) | M40: =SUM(M35:M39) | N40: =SUM(N35:N39) | O40: =SUM(O35:O39) | P40: =SUM(P35:P39) | Q40: =SUM(Q35:Q39) | R40: =SUM(L40:Q40) | S40: =IF(E40=0,"***",L40/E40) | T40: =IF(F40=0,"***",M40/F40) | U40: =IF(G40=0,"***",N40/G40) | V40: =IF(H40=0,"***",O40/H40) | W40: =IF(I40=0,"***",P40/I40) | X40: =IF(J40=0,"***",Q40/J40) | Y40: =IF(K40=0,"***",R40/K40)
C42: ５．前期比
E43: 売上 | L43: 粗利益 | S43: 粗利益率
E44: 46113 | F44: 46143 | G44: 46174 | H44: 46204 | I44: 46235 | J44: 46266 | K44: 合計 | L44: 46113 | M44: 46143 | N44: 46174 | O44: 46204 | P44: 46235 | Q44: 46266 | R44: 合計 | S44: 46113 | T44: 46143 | U44: 46174 | V44: 46204 | W44: 46235 | X44: 46266 | Y44: 合計
C45: 0032 集計 | D45: 飯塚主任 | E45: =E35-E15 | F45: =F35-F15 | G45: =G35-G15 | H45: =H35-H15 | I45: =I35-I15 | J45: =J35-J15 | K45: =SUM(E45:J45) | L45: =L35-L15 | M45: =M35-M15 | N45: =N35-N15 | O45: =O35-O15 | P45: =P35-P15 | Q45: =Q35-Q15 | R45: =SUM(L45:Q45) | S45: =S35-S15 | T45: =T35-T15 | U45: =U35-U15 | V45: =V35-V15 | W45: =W35-W15 | X45: =X35-X15 | Y45: =Y35-Y15
C46: 0033 集計 | D46: 前田課長代 | E46: =E36-E16 | F46: =F36-F16 | G46: =G36-G16 | H46: =H36-H16 | I46: =I36-I16 | J46: =J36-J16 | K46: =SUM(E46:J46) | L46: =L36-L16 | M46: =M36-M16 | N46: =N36-N16 | O46: =O36-O16 | P46: =P36-P16 | Q46: =Q36-Q16 | R46: =SUM(L46:Q46) | S46: =S36-S16 | T46: =T36-T16 | U46: =U36-U16 | V46: =V36-V16 | W46: =W36-W16 | X46: =X36-X16 | Y46: =Y36-Y16
C47: 0034 集計 | D47: 原田 | E47: =E37-E17 | F47: =F37-F17 | G47: =G37-G17 | H47: =H37-H17 | I47: =I37-I17 | J47: =J37-J17 | K47: =SUM(E47:J47) | L47: =L37-L17 | M47: =M37-M17 | N47: =N37-N17 | O47: =O37-O17 | P47: =P37-P17 | Q47: =Q37-Q17 | R47: =SUM(L47:Q47) | S47: =S37-S17 | T47: =T37-T17 | U47: =U37-U17 | V47: =V37-V17 | W47: =W37-W17 | X47: =X37-X17 | Y47: =Y37-Y17
C48: 0035 集計 | D48: 自治体 | E48: =E38-E18 | F48: =F38-F18 | G48: =G38-G18 | H48: =H38-H18 | I48: =I38-I18 | J48: =J38-J18 | K48: =SUM(E48:J48) | L48: =L38-L18 | M48: =M38-M18 | N48: =N38-N18 | O48: =O38-O18 | P48: =P38-P18 | Q48: =Q38-Q18 | R48: =SUM(L48:Q48) | S48: =S38-S18 | T48: =T38-T18 | U48: =U38-U18 | V48: =V38-V18 | W48: =W38-W18 | X48: =X38-X18 | Y48: =Y38-Y18
C49: 0039 集計 | D49: その他 | E49: =E39-E19 | F49: =F39-F19 | G49: =G39-G19 | H49: =H39-H19 | I49: =I39-I19 | J49: =J39-J19 | K49: =SUM(E49:J49) | L49: =L39-L19 | M49: =M39-M19 | N49: =N39-N19 | O49: =O39-O19 | P49: =P39-P19 | Q49: =Q39-Q19 | R49: =SUM(L49:Q49) | S49: =S39-S19 | T49: =T39-T19 | U49: =U39-U19 | V49: =V39-V19 | W49: =W39-W19 | X49: =X39-X19 | Y49: =Y39-Y19
C50: 合計 | E50: =SUM(E45:E49) | F50: =SUM(F45:F49) | G50: =SUM(G45:G49) | H50: =SUM(H45:H49) | I50: =SUM(I45:I49) | J50: =SUM(J45:J49) | K50: =SUM(E50:J50) | L50: =SUM(L45:L49) | M50: =SUM(M45:M49) | N50: =SUM(N45:N49) | O50: =SUM(O45:O49) | P50: =SUM(P45:P49) | Q50: =SUM(Q45:Q49) | R50: =SUM(L50:Q50) | S50: =S40-S20 | T50: =T40-T20 | U50: =U40-U20 | V50: =V40-V20 | W50: =W40-W20 | X50: =X40-X20 | Y50: =Y40-Y20
C52: 6．過年度平均比
E53: 売上 | L53: 粗利益 | S53: 粗利益率
E54: 46113 | F54: 46143 | G54: 46174 | H54: 46204 | I54: 46235 | J54: 46266 | K54: 合計 | L54: 46113 | M54: 46143 | N54: 46174 | O54: 46204 | P54: 46235 | Q54: 46266 | R54: 合計 | S54: 46113 | T54: 46143 | U54: 46174 | V54: 46204 | W54: 46235 | X54: 46266 | Y54: 合計
C55: 0032 集計 | D55: 飯塚主任 | E55: =E35-E25 | F55: =F35-F25 | G55: =G35-G25 | H55: =H35-H25 | I55: =I35-I25 | J55: =J35-J25 | K55: =SUM(E55:J55) | L55: =L35-L25 | M55: =M35-M25 | N55: =N35-N25 | O55: =O35-O25 | P55: =P35-P25 | Q55: =Q35-Q25 | R55: =SUM(L55:Q55) | S55: =IF(E55=0,"***",L55/E55) | T55: =IF(F55=0,"***",M55/F55) | U55: =IF(G55=0,"***",N55/G55) | V55: =IF(H55=0,"***",O55/H55) | W55: =IF(I55=0,"***",P55/I55) | X55: =IF(J55=0,"***",Q55/J55) | Y55: =IF(K55=0,"***",R55/K55)
C56: 0033 集計 | D56: 前田課長代 | E56: =E36-E26 | F56: =F36-F26 | G56: =G36-G26 | H56: =H36-H26 | I56: =I36-I26 | J56: =J36-J26 | K56: =SUM(E56:J56) | L56: =L36-L26 | M56: =M36-M26 | N56: =N36-N26 | O56: =O36-O26 | P56: =P36-P26 | Q56: =Q36-Q26 | R56: =SUM(L56:Q56) | S56: =IF(E56=0,"***",L56/E56) | T56: =IF(F56=0,"***",M56/F56) | U56: =IF(G56=0,"***",N56/G56) | V56: =IF(H56=0,"***",O56/H56) | W56: =IF(I56=0,"***",P56/I56) | X56: =IF(J56=0,"***",Q56/J56) | Y56: =IF(K56=0,"***",R56/K56)
C57: 0034 集計 | D57: 原田 | E57: =E37-E27 | F57: =F37-F27 | G57: =G37-G27 | H57: =H37-H27 | I57: =I37-I27 | J57: =J37-J27 | K57: =SUM(E57:J57) | L57: =L37-L27 | M57: =M37-M27 | N57: =N37-N27 | O57: =O37-O27 | P57: =P37-P27 | Q57: =Q37-Q27 | R57: =SUM(L57:Q57) | S57: =IF(E57=0,"***",L57/E57) | T57: =IF(F57=0,"***",M57/F57) | U57: =IF(G57=0,"***",N57/G57) | V57: =IF(H57=0,"***",O57/H57) | W57: =IF(I57=0,"***",P57/I57) | X57: =IF(J57=0,"***",Q57/J57) | Y57: =IF(K57=0,"***",R57/K57)
C58: 0035 集計 | D58: 自治体 | E58: =E38-E28 | F58: =F38-F28 | G58: =G38-G28 | H58: =H38-H28 | I58: =I38-I28 | J58: =J38-J28 | K58: =SUM(E58:J58) | L58: =L38-L28 | M58: =M38-M28 | N58: =N38-N28 | O58: =O38-O28 | P58: =P38-P28 | Q58: =Q38-Q28 | R58: =SUM(L58:Q58) | S58: =IF(E58=0,"***",L58/E58) | T58: =IF(F58=0,"***",M58/F58) | U58: =IF(G58=0,"***",N58/G58) | V58: =IF(H58=0,"***",O58/H58) | W58: =IF(I58=0,"***",P58/I58) | X58: =IF(J58=0,"***",Q58/J58) | Y58: =IF(K58=0,"***",R58/K58)
C59: 0039 集計 | D59: その他 | E59: =E39-E29 | F59: =F39-F29 | G59: =G39-G29 | H59: =H39-H29 | I59: =I39-I29 | J59: =J39-J29 | K59: =SUM(E59:J59) | L59: =L39-L29 | M59: =M39-M29 | N59: =N39-N29 | O59: =O39-O29 | P59: =P39-P29 | Q59: =Q39-Q29 | R59: =SUM(L59:Q59) | S59: =IF(E59=0,"***",L59/E59) | T59: =IF(F59=0,"***",M59/F59) | U59: =IF(G59=0,"***",N59/G59) | V59: =IF(H59=0,"***",O59/H59) | W59: =IF(I59=0,"***",P59/I59) | X59: =IF(J59=0,"***",Q59/J59) | Y59: =IF(K59=0,"***",R59/K59)
C60: 合計 | E60: =SUM(E55:E59) | F60: =SUM(F55:F59) | G60: =SUM(G55:G59) | H60: =SUM(H55:H59) | I60: =SUM(I55:I59) | J60: =SUM(J55:J59) | K60: =SUM(E60:J60) | L60: =SUM(L55:L59) | M60: =SUM(M55:M59) | N60: =SUM(N55:N59) | O60: =SUM(O55:O59) | P60: =SUM(P55:P59) | Q60: =SUM(Q55:Q59) | R60: =SUM(L60:Q60) | S60: =IF(E60=0,"***",L60/E60) | T60: =IF(F60=0,"***",M60/F60) | U60: =IF(G60=0,"***",N60/G60) | V60: =IF(H60=0,"***",O60/H60) | W60: =IF(I60=0,"***",P60/I60) | X60: =IF(J60=0,"***",Q60/J60) | Y60: =IF(K60=0,"***",R60/K60)
C62: 7．実績
E63: 売上 | L63: 粗利益 | S63: 粗利益率
E64: 46113 | F64: 46143 | G64: 46174 | H64: 46204 | I64: 46235 | J64: 46266 | K64: 合計 | L64: 46113 | M64: 46143 | N64: 46174 | O64: 46204 | P64: 46235 | Q64: 46266 | R64: 合計 | S64: 46113 | T64: 46143 | U64: 46174 | V64: 46204 | W64: 46235 | X64: 46266 | Y64: 合計
C65: 0032 集計 | D65: 飯塚主任 | E65: =全体!E65-機械!E65 | F65: =全体!F65-機械!F65 | G65: =全体!G65-機械!G65 | H65: =全体!H65-機械!H65 | I65: =全体!I65-機械!I65 | K65: =SUM(E65:J65) | L65: =全体!L65-機械!L65 | M65: =全体!M65-機械!M65 | N65: =全体!N65-機械!N65 | O65: =全体!O65-機械!O65 | P65: =全体!P65-機械!P65 | R65: =SUM(L65:Q65) | S65: =IF(E65=0,"***",L65/E65) | T65: =IF(F65=0,"***",M65/F65) | U65: =IF(G65=0,"***",N65/G65) | V65: =IF(H65=0,"***",O65/H65) | W65: =IF(I65=0,"***",P65/I65) | X65: =IF(J65=0,"***",Q65/J65) | Y65: =IF(K65=0,"***",R65/K65)
C66: 0033 集計 | D66: 前田課長代 | E66: =全体!E66-機械!E66 | F66: =全体!F66-機械!F66 | G66: =全体!G66-機械!G66 | H66: =全体!H66-機械!H66 | I66: =全体!I66-機械!I66 | K66: =SUM(E66:J66) | L66: =全体!L66-機械!L66 | M66: =全体!M66-機械!M66 | N66: =全体!N66-機械!N66 | O66: =全体!O66-機械!O66 | P66: =全体!P66-機械!P66 | R66: =SUM(L66:Q66) | S66: =IF(E66=0,"***",L66/E66) | T66: =IF(F66=0,"***",M66/F66) | U66: =IF(G66=0,"***",N66/G66) | V66: =IF(H66=0,"***",O66/H66) | W66: =IF(I66=0,"***",P66/I66) | X66: =IF(J66=0,"***",Q66/J66) | Y66: =IF(K66=0,"***",R66/K66)
C67: 0034 集計 | D67: 原田 | E67: =全体!E67-機械!E67 | F67: =全体!F67-機械!F67 | G67: =全体!G67-機械!G67 | H67: =全体!H67-機械!H67 | I67: =全体!I67-機械!I67 | K67: =SUM(E67:J67) | L67: =全体!L67-機械!L67 | M67: =全体!M67-機械!M67 | N67: =全体!N67-機械!N67 | O67: =全体!O67-機械!O67 | P67: =全体!P67-機械!P67 | R67: =SUM(L67:Q67) | S67: =IF(E67=0,"***",L67/E67) | T67: =IF(F67=0,"***",M67/F67) | U67: =IF(G67=0,"***",N67/G67) | V67: =IF(H67=0,"***",O67/H67) | W67: =IF(I67=0,"***",P67/I67) | X67: =IF(J67=0,"***",Q67/J67) | Y67: =IF(K67=0,"***",R67/K67)
C68: 0035 集計 | D68: 自治体 | E68: =全体!E68-機械!E68 | G68: =全体!G68-機械!G68 | H68: =全体!H68-機械!H68 | I68: =全体!I68-機械!I68 | K68: =SUM(E68:J68) | L68: =全体!L68-機械!L68 | N68: =全体!N68-機械!N68 | O68: =全体!O68-機械!O68 | P68: =全体!P68-機械!P68 | R68: =SUM(L68:Q68) | S68: =IF(E68=0,"***",L68/E68) | T68: =IF(F68=0,"***",M68/F68) | U68: =IF(G68=0,"***",N68/G68) | V68: =IF(H68=0,"***",O68/H68) | W68: =IF(I68=0,"***",P68/I68) | X68: =IF(J68=0,"***",Q68/J68) | Y68: =IF(K68=0,"***",R68/K68)
C69: 0039 集計 | D69: その他 | E69: =全体!E69-機械!E69 | F69: =全体!F69-機械!F69 | G69: =全体!G69-機械!G69 | H69: =全体!H69-機械!H69 | I69: =全体!I69-機械!I69 | K69: =SUM(E69:J69) | L69: =全体!L69-機械!L69 | M69: =全体!M69-機械!M69 | N69: =全体!N69-機械!N69 | O69: =全体!O69-機械!O69 | P69: =全体!P69-機械!P69 | R69: =SUM(L69:Q69) | S69: =IF(E69=0,"***",L69/E69) | T69: =IF(F69=0,"***",M69/F69) | U69: =IF(G69=0,"***",N69/G69) | V69: =IF(H69=0,"***",O69/H69) | W69: =IF(I69=0,"***",P69/I69) | X69: =IF(J69=0,"***",Q69/J69) | Y69: =IF(K69=0,"***",R69/K69)
C70: 合計 | E70: =SUM(E65:E69) | F70: =SUM(F65:F69) | G70: =SUM(G65:G69) | H70: =SUM(H65:H69) | I70: =SUM(I65:I69) | J70: =SUM(J65:J69) | K70: =SUM(E70:J70) | L70: =SUM(L65:L69) | M70: =SUM(M65:M69) | N70: =SUM(N65:N69) | O70: =SUM(O65:O69) | P70: =SUM(P65:P69) | Q70: =SUM(Q65:Q69) | R70: =SUM(L70:Q70) | S70: =IF(E70=0,"***",L70/E70) | T70: =IF(F70=0,"***",M70/F70) | U70: =IF(G70=0,"***",N70/G70) | V70: =IF(H70=0,"***",O70/H70) | W70: =IF(I70=0,"***",P70/I70) | X70: =IF(J70=0,"***",Q70/J70) | Y70: =IF(K70=0,"***",R70/K70)
C72: 8．計画比
E73: 売上 | L73: 粗利益 | S73: 粗利益率
E74: 46113 | F74: 46143 | G74: 46174 | H74: 46204 | I74: 46235 | J74: 46266 | K74: 合計 | L74: 46113 | M74: 46143 | N74: 46174 | O74: 46204 | P74: 46235 | Q74: 46266 | R74: 合計 | S74: 46113 | T74: 46143 | U74: 46174 | V74: 46204 | W74: 46235 | X74: 46266 | Y74: 合計
C75: 0032 集計 | D75: 飯塚主任 | E75: =E65-E35 | F75: =F65-F35 | G75: =G65-G35 | H75: =H65-H35 | I75: =I65-I35 | K75: =SUM(E75:J75) | L75: =L65-L35 | M75: =M65-M35 | N75: =N65-N35 | O75: =O65-O35 | P75: =P65-P35 | R75: =SUM(L75:Q75) | S75: =S65-S35 | T75: =T65-T35 | U75: =U65-U35 | V75: =V65-V35 | W75: =W65-W35 | X75: =X65-X35 | Y75: =Y65-Y35
C76: 0033 集計 | D76: 前田課長代 | E76: =E66-E36 | F76: =F66-F36 | G76: =G66-G36 | H76: =H66-H36 | I76: =I66-I36 | K76: =SUM(E76:J76) | L76: =L66-L36 | M76: =M66-M36 | N76: =N66-N36 | O76: =O66-O36 | P76: =P66-P36 | R76: =SUM(L76:Q76) | S76: =S66-S36 | T76: =T66-T36 | U76: =U66-U36 | V76: =V66-V36 | W76: =W66-W36 | X76: =X66-X36 | Y76: =Y66-Y36
C77: 0034 集計 | D77: 原田 | E77: =E67-E37 | F77: =F67-F37 | G77: =G67-G37 | H77: =H67-H37 | I77: =I67-I37 | K77: =SUM(E77:J77) | L77: =L67-L37 | M77: =M67-M37 | N77: =N67-N37 | O77: =O67-O37 | P77: =P67-P37 | R77: =SUM(L77:Q77) | S77: =S67-S37 | T77: =T67-T37 | U77: =U67-U37 | V77: =V67-V37 | W77: =W67-W37 | X77: =X67-X37 | Y77: =Y67-Y37
C78: 0035 集計 | D78: 自治体 | E78: =E68-E38 | F78: =F68-F38 | G78: =G68-G38 | H78: =H68-H38 | I78: =I68-I38 | K78: =SUM(E78:J78) | L78: =L68-L38 | M78: =M68-M38 | N78: =N68-N38 | O78: =O68-O38 | P78: =P68-P38 | R78: =SUM(L78:Q78) | S78: =S68-S38 | T78: =T68-T38 | U78: =U68-U38 | V78: =V68-V38 | W78: =W68-W38 | X78: =X68-X38 | Y78: =Y68-Y38
C79: 0039 集計 | D79: その他 | E79: =E69-E39 | F79: =F69-F39 | G79: =G69-G39 | H79: =H69-H39 | I79: =I69-I39 | K79: =SUM(E79:J79) | L79: =L69-L39 | M79: =M69-M39 | N79: =N69-N39 | O79: =O69-O39 | P79: =P69-P39 | R79: =SUM(L79:Q79) | S79: =S69-S39 | T79: =T69-T39 | U79: =U69-U39 | V79: =V69-V39 | W79: =W69-W39 | X79: =X69-X39 | Y79: =Y69-Y39
C80: 合計 | E80: =SUM(E75:E79) | F80: =SUM(F75:F79) | G80: =SUM(G75:G79) | H80: =SUM(H75:H79) | I80: =SUM(I75:I79) | J80: =SUM(J75:J79) | K80: =SUM(E80:J80) | L80: =SUM(L75:L79) | M80: =SUM(M75:M79) | N80: =SUM(N75:N79) | O80: =SUM(O75:O79) | P80: =SUM(P75:P79) | Q80: =SUM(Q75:Q79) | R80: =SUM(L80:Q80) | S80: =S70-S40 | T80: =T70-T40 | U80: =U70-U40 | V80: =V70-V40 | W80: =W70-W40 | X80: =X70-X40 | Y80: =Y70-Y40
C82: 9．前期比
E83: 売上 | L83: 粗利益 | S83: 粗利益率
E84: 46113 | F84: 46143 | G84: 46174 | H84: 46204 | I84: 46235 | J84: 46266 | K84: 合計 | L84: 46113 | M84: 46143 | N84: 46174 | O84: 46204 | P84: 46235 | Q84: 46266 | R84: 合計 | S84: 46113 | T84: 46143 | U84: 46174 | V84: 46204 | W84: 46235 | X84: 46266 | Y84: 合計
C85: 0032 集計 | D85: 飯塚主任 | E85: =E65-E15 | F85: =F65-F15 | G85: =G65-G15 | H85: =H65-H15 | I85: =I65-I15 | K85: =SUM(E85:J85) | L85: =L65-L15 | M85: =M65-M15 | N85: =N65-N15 | O85: =O65-O15 | P85: =P65-P15 | R85: =SUM(L85:Q85) | S85: =S65-S15 | T85: =T65-T15 | U85: =U65-U15 | V85: =V65-V15 | W85: =W65-W15 | X85: =X65-X15 | Y85: =Y65-Y15
C86: 0033 集計 | D86: 前田課長代 | E86: =E66-E16 | F86: =F66-F16 | G86: =G66-G16 | H86: =H66-H16 | I86: =I66-I16 | K86: =SUM(E86:J86) | L86: =L66-L16 | M86: =M66-M16 | N86: =N66-N16 | O86: =O66-O16 | P86: =P66-P16 | R86: =SUM(L86:Q86) | S86: =S66-S16 | T86: =T66-T16 | U86: =U66-U16 | V86: =V66-V16 | W86: =W66-W16 | X86: =X66-X16 | Y86: =Y66-Y16
C87: 0034 集計 | D87: 原田 | E87: =E67-E17 | F87: =F67-F17 | G87: =G67-G17 | H87: =H67-H17 | I87: =I67-I17 | K87: =SUM(E87:J87) | L87: =L67-L17 | M87: =M67-M17 | N87: =N67-N17 | O87: =O67-O17 | P87: =P67-P17 | R87: =SUM(L87:Q87) | S87: =S67-S17 | T87: =T67-T17 | U87: =U67-U17 | V87: =V67-V17 | W87: =W67-W17 | X87: =X67-X17 | Y87: =Y67-Y17
C88: 0035 集計 | D88: 自治体 | E88: =E68-E18 | F88: =F68-F18 | G88: =G68-G18 | H88: =H68-H18 | I88: =I68-I18 | K88: =SUM(E88:J88) | L88: =L68-L18 | M88: =M68-M18 | N88: =N68-N18 | O88: =O68-O18 | P88: =P68-P18 | R88: =SUM(L88:Q88) | S88: =S68-S18 | T88: =T68-T18 | U88: =U68-U18 | V88: =V68-V18 | W88: =W68-W18 | X88: =X68-X18 | Y88: =Y68-Y18
C89: 0039 集計 | D89: その他 | E89: =E69-E19 | F89: =F69-F19 | G89: =G69-G19 | H89: =H69-H19 | I89: =I69-I19 | K89: =SUM(E89:J89) | L89: =L69-L19 | M89: =M69-M19 | N89: =N69-N19 | O89: =O69-O19 | P89: =P69-P19 | R89: =SUM(L89:Q89) | S89: =S69-S19 | T89: =T69-T19 | U89: =U69-U19 | V89: =V69-V19 | W89: =W69-W19 | X89: =X69-X19 | Y89: =Y69-Y19
C90: 合計 | E90: =SUM(E85:E89) | F90: =SUM(F85:F89) | G90: =SUM(G85:G89) | H90: =SUM(H85:H89) | I90: =SUM(I85:I89) | J90: =SUM(J85:J89) | K90: =SUM(E90:J90) | L90: =SUM(L85:L89) | M90: =SUM(M85:M89) | N90: =SUM(N85:N89) | O90: =SUM(O85:O89) | P90: =SUM(P85:P89) | Q90: =SUM(Q85:Q89) | R90: =SUM(L90:Q90) | S90: =S70-S20 | T90: =T70-T20 | U90: =U80-U50 | V90: =V80-V50 | W90: =W80-W50 | X90: =X80-X50 | Y90: =Y70-Y20

Sheet 全体
C1: 松江営業所全体
C2: 1．2024年
E3: 売上 | L3: 粗利益 | S3: 粗利益率
E4: 45383 | F4: 45413 | G4: 45444 | H4: 45474 | I4: 45505 | J4: 45536 | K4: 合計 | L4: 45383 | M4: 45413 | N4: 45444 | O4: 45474 | P4: 45505 | Q4: 45536 | R4: 合計 | S4: 45383 | T4: 45413 | U4: 45444 | V4: 45474 | W4: 45505 | X4: 45536 | Y4: 合計
C5: 0032 集計 | D5: 飯塚主任 | E5: 9394.786 | F5: 11001.362 | G5: 7293.722 | H5: 8370.21 | I5: 10947.936 | J5: 6349.214 | K5: =SUM(E5:J5) | L5: 2690.031 | M5: 3003.793 | N5: 2140.472 | O5: 2358.244 | P5: 3179.773 | Q5: 2397.156 | R5: =SUM(L5:Q5) | S5: =IF(E5=0,"***",L5/E5) | T5: =IF(F5=0,"***",M5/F5) | U5: =IF(G5=0,"***",N5/G5) | V5: =IF(H5=0,"***",O5/H5) | W5: =IF(I5=0,"***",P5/I5) | X5: =IF(J5=0,"***",Q5/J5) | Y5: =IF(K5=0,"***",R5/K5)
C6: 0033 集計 | D6: 前田課長代 | E6: 9543.871 | F6: 5743.266 | G6: 9802.851 | H6: 10503.789 | I6: 9769.476 | J6: 9778.495 | K6: =SUM(E6:J6) | L6: 2185.0206 | M6: 1296.05 | N6: 1913.457 | O6: 2257.2438 | P6: 2149.223 | Q6: 2272.588 | R6: =SUM(L6:Q6) | S6: =IF(E6=0,"***",L6/E6) | T6: =IF(F6=0,"***",M6/F6) | U6: =IF(G6=0,"***",N6/G6) | V6: =IF(H6=0,"***",O6/H6) | W6: =IF(I6=0,"***",P6/I6) | X6: =IF(J6=0,"***",Q6/J6) | Y6: =IF(K6=0,"***",R6/K6)
C7: 0034 集計 | D7: 原田 | E7: 8422.199 | F7: 7218.111 | G7: 7325.341 | H7: 8652.573 | I7: 9130.425 | J7: 8392.639 | K7: =SUM(E7:J7) | L7: 2032.137 | M7: 1623.651 | N7: 1626.762 | O7: 1875.443 | P7: 1941.406 | Q7: 2104.958 | R7: =SUM(L7:Q7) | S7: =IF(E7=0,"***",L7/E7) | T7: =IF(F7=0,"***",M7/F7) | U7: =IF(G7=0,"***",N7/G7) | V7: =IF(H7=0,"***",O7/H7) | W7: =IF(I7=0,"***",P7/I7) | X7: =IF(J7=0,"***",Q7/J7) | Y7: =IF(K7=0,"***",R7/K7)
C8: 0035 集計 | D8: 自治体 | E8: 8514.45 | F8: 3182.96 | G8: 10715.25 | H8: 0 | I8: 0 | J8: 24111.466 | K8: =SUM(E8:J8) | L8: 154.3 | M8: 57.56 | N8: 183.74 | O8: 0 | P8: 0 | Q8: 642.976 | R8: =SUM(L8:Q8) | S8: =IF(E8=0,"***",L8/E8) | T8: =IF(F8=0,"***",M8/F8) | U8: =IF(G8=0,"***",N8/G8) | V8: =IF(H8=0,"***",O8/H8) | W8: =IF(I8=0,"***",P8/I8) | X8: =IF(J8=0,"***",Q8/J8) | Y8: =IF(K8=0,"***",R8/K8)
C9: 0039 集計 | D9: その他 | E9: 64.19 | F9: 9.22 | G9: 14.04 | H9: 77.69 | I9: 30.37 | J9: 31.444 | K9: =SUM(E9:J9) | L9: 19.062 | M9: 4.29 | N9: 5.38 | O9: 15.204 | P9: 10.076 | Q9: 13.314 | R9: =SUM(L9:Q9) | S9: =IF(E9=0,"***",L9/E9) | T9: =IF(F9=0,"***",M9/F9) | U9: =IF(G9=0,"***",N9/G9) | V9: =IF(H9=0,"***",O9/H9) | W9: =IF(I9=0,"***",P9/I9) | X9: =IF(J9=0,"***",Q9/J9) | Y9: =IF(K9=0,"***",R9/K9)
C10: 合計 | E10: =SUM(E5:E9) | F10: =SUM(F5:F9) | G10: =SUM(G5:G9) | H10: =SUM(H5:H9) | I10: =SUM(I5:I9) | J10: =SUM(J5:J9) | K10: =SUM(E10:J10) | L10: =SUM(L5:L9) | M10: =SUM(M5:M9) | N10: =SUM(N5:N9) | O10: =SUM(O5:O9) | P10: =SUM(P5:P9) | Q10: =SUM(Q5:Q9) | R10: =SUM(L10:Q10) | S10: =IF(E10=0,"***",L10/E10) | T10: =IF(F10=0,"***",M10/F10) | U10: =IF(G10=0,"***",N10/G10) | V10: =IF(H10=0,"***",O10/H10) | W10: =IF(I10=0,"***",P10/I10) | X10: =IF(J10=0,"***",Q10/J10) | Y10: =IF(K10=0,"***",R10/K10)
C12: 2．2025年
E13: 売上 | L13: 粗利益 | S13: 粗利益率
E14: 45748 | F14: 45778 | G14: 45809 | H14: 45839 | I14: 45870 | J14: 45901 | K14: 合計 | L14: 45748 | M14: 45778 | N14: 45809 | O14: 45839 | P14: 45870 | Q14: 45901 | R14: 合計 | S14: 45748 | T14: 45778 | U14: 45809 | V14: 45839 | W14: 45870 | X14: 45901 | Y14: 合計
C15: 0032 集計 | D15: 飯塚主任 | E15: 11871.789 | F15: 7775.014 | G15: 8471.81 | H15: 9957.042 | I15: 10299.5 | J15: 8786.094 | K15: =SUM(E15:J15) | L15: 3691.15 | M15: 2487.929 | N15: 2702.119 | O15: 3122.603 | P15: 3226.146 | Q15: 2730.316 | R15: =SUM(L15:Q15) | S15: =IF(E15=0,"***",L15/E15) | T15: =IF(F15=0,"***",M15/F15) | U15: =IF(G15=0,"***",N15/G15) | V15: =IF(H15=0,"***",O15/H15) | W15: =IF(I15=0,"***",P15/I15) | X15: =IF(J15=0,"***",Q15/J15) | Y15: =IF(K15=0,"***",R15/K15)
C16: 0033 集計 | D16: 前田課長代 | E16: 10187.463 | F16: 8959.196 | G16: 8546.749 | H16: 9593.01 | I16: 7366.301 | J16: 7421.947 | K16: =SUM(E16:J16) | L16: 2708.5808 | M16: 2469.716 | N16: 1977.3058 | O16: 2080.844 | P16: 1950.749 | Q16: 1998.123 | R16: =SUM(L16:Q16) | S16: =IF(E16=0,"***",L16/E16) | T16: =IF(F16=0,"***",M16/F16) | U16: =IF(G16=0,"***",N16/G16) | V16: =IF(H16=0,"***",O16/H16) | W16: =IF(I16=0,"***",P16/I16) | X16: =IF(J16=0,"***",Q16/J16) | Y16: =IF(K16=0,"***",R16/K16)
C17: 0034 集計 | D17: 原田 | E17: 9422.809 | F17: 7351.248 | G17: 7391.386 | H17: 9599.937 | I17: 8283.083 | J17: 9097.808 | K17: =SUM(E17:J17) | L17: 2241.823 | M17: 1791.092 | N17: 1710.721 | O17: 2300.398 | P17: 2009.645 | Q17: 1844.832 | R17: =SUM(L17:Q17) | S17: =IF(E17=0,"***",L17/E17) | T17: =IF(F17=0,"***",M17/F17) | U17: =IF(G17=0,"***",N17/G17) | V17: =IF(H17=0,"***",O17/H17) | W17: =IF(I17=0,"***",P17/I17) | X17: =IF(J17=0,"***",Q17/J17) | Y17: =IF(K17=0,"***",R17/K17)
C18: 0035 集計 | D18: 自治体 | E18: 9358.208 | F18: 2209.46 | G18: 11193.008 | H18: 0 | I18: 6139.904 | J18: 9994.712 | K18: =SUM(E18:J18) | L18: 173.928 | M18: 19.31 | N18: 196.128 | O18: 0 | P18: 115.904 | Q18: 197.752 | R18: =SUM(L18:Q18) | S18: =IF(E18=0,"***",L18/E18) | T18: =IF(F18=0,"***",M18/F18) | U18: =IF(G18=0,"***",N18/G18) | V18: =IF(H18=0,"***",O18/H18) | W18: =IF(I18=0,"***",P18/I18) | X18: =IF(J18=0,"***",Q18/J18) | Y18: =IF(K18=0,"***",R18/K18)
C19: 0039 集計 | D19: その他 | E19: 27.05 | F19: 0 | G19: 11.3 | H19: 12.3 | I19: 1.1 | J19: 0 | K19: =SUM(E19:J19) | L19: 5.301 | M19: 0 | N19: 2.499 | O19: 4.8 | P19: 0.375 | Q19: 0 | R19: =SUM(L19:Q19) | S19: =IF(E19=0,"***",L19/E19) | T19: =IF(F19=0,"***",M19/F19) | U19: =IF(G19=0,"***",N19/G19) | V19: =IF(H19=0,"***",O19/H19) | W19: =IF(I19=0,"***",P19/I19) | X19: =IF(J19=0,"***",Q19/J19) | Y19: =IF(K19=0,"***",R19/K19)
C20: 合計 | E20: =SUM(E15:E19) | F20: =SUM(F15:F19) | G20: =SUM(G15:G19) | H20: =SUM(H15:H19) | I20: =SUM(I15:I19) | J20: =SUM(J15:J19) | K20: =SUM(E20:J20) | L20: =SUM(L15:L19) | M20: =SUM(M15:M19) | N20: =SUM(N15:N19) | O20: =SUM(O15:O19) | P20: =SUM(P15:P19) | Q20: =SUM(Q15:Q19) | R20: =SUM(L20:Q20) | S20: =IF(E20=0,"***",L20/E20) | T20: =IF(F20=0,"***",M20/F20) | U20: =IF(G20=0,"***",N20/G20) | V20: =IF(H20=0,"***",O20/H20) | W20: =IF(I20=0,"***",P20/I20) | X20: =IF(J20=0,"***",Q20/J20) | Y20: =IF(K20=0,"***",R20/K20)
C22: 3．過年度平均
E23: 売上 | L23: 粗利益 | S23: 粗利益率
E24: 45748 | F24: 45778 | G24: 45809 | H24: 45839 | I24: 45870 | J24: 45901 | K24: 合計 | L24: 45748 | M24: 45778 | N24: 45809 | O24: 45839 | P24: 45870 | Q24: 45901 | R24: 合計 | S24: 45748 | T24: 45778 | U24: 45809 | V24: 45839 | W24: 45870 | X24: 45901 | Y24: 合計
C25: 0032 集計 | D25: 飯塚主任 | E25: =(E15+E5)/2 | F25: =(F15+F5)/2 | G25: =(G15+G5)/2 | H25: =(H15+H5)/2 | I25: =(I15+I5)/2 | J25: =(J15+J5)/2 | K25: =SUM(E25:J25) | L25: =(L15+L5)/2 | M25: =(M15+M5)/2 | N25: =(N15+N5)/2 | O25: =(O15+O5)/2 | P25: =(P15+P5)/2 | Q25: =(Q15+Q5)/2 | R25: =SUM(L25:Q25) | S25: =IF(E25=0,"***",L25/E25) | T25: =IF(F25=0,"***",M25/F25) | U25: =IF(G25=0,"***",N25/G25) | V25: =IF(H25=0,"***",O25/H25) | W25: =IF(I25=0,"***",P25/I25) | X25: =IF(J25=0,"***",Q25/J25) | Y25: =IF(K25=0,"***",R25/K25)
C26: 0033 集計 | D26: 前田課長代 | E26: =(E16+E6)/2 | F26: =(F16+F6)/2 | G26: =(G16+G6)/2 | H26: =(H16+H6)/2 | I26: =(I16+I6)/2 | J26: =(J16+J6)/2 | K26: =SUM(E26:J26) | L26: =(L16+L6)/2 | M26: =(M16+M6)/2 | N26: =(N16+N6)/2 | O26: =(O16+O6)/2 | P26: =(P16+P6)/2 | Q26: =(Q16+Q6)/2 | R26: =SUM(L26:Q26) | S26: =IF(E26=0,"***",L26/E26) | T26: =IF(F26=0,"***",M26/F26) | U26: =IF(G26=0,"***",N26/G26) | V26: =IF(H26=0,"***",O26/H26) | W26: =IF(I26=0,"***",P26/I26) | X26: =IF(J26=0,"***",Q26/J26) | Y26: =IF(K26=0,"***",R26/K26)
C27: 0034 集計 | D27: 原田 | E27: =(E17+E7)/2 | F27: =(F17+F7)/2 | G27: =(G17+G7)/2 | H27: =(H17+H7)/2 | I27: =(I17+I7)/2 | J27: =(J17+J7)/2 | K27: =SUM(E27:J27) | L27: =(L17+L7)/2 | M27: =(M17+M7)/2 | N27: =(N17+N7)/2 | O27: =(O17+O7)/2 | P27: =(P17+P7)/2 | Q27: =(Q17+Q7)/2 | R27: =SUM(L27:Q27) | S27: =IF(E27=0,"***",L27/E27) | T27: =IF(F27=0,"***",M27/F27) | U27: =IF(G27=0,"***",N27/G27) | V27: =IF(H27=0,"***",O27/H27) | W27: =IF(I27=0,"***",P27/I27) | X27: =IF(J27=0,"***",Q27/J27) | Y27: =IF(K27=0,"***",R27/K27)
C28: 0035 集計 | D28: 自治体 | E28: =(E18+E8)/2 | F28: =(F18+F8)/2 | G28: =(G18+G8)/2 | H28: =(H18+H8)/2 | I28: =(I18+I8)/2 | J28: =(J18+J8)/2 | K28: =SUM(E28:J28) | L28: =(L18+L8)/2 | M28: =(M18+M8)/2 | N28: =(N18+N8)/2 | O28: =(O18+O8)/2 | P28: =(P18+P8)/2 | Q28: =(Q18+Q8)/2 | R28: =SUM(L28:Q28) | S28: =IF(E28=0,"***",L28/E28) | T28: =IF(F28=0,"***",M28/F28) | U28: =IF(G28=0,"***",N28/G28) | V28: =IF(H28=0,"***",O28/H28) | W28: =IF(I28=0,"***",P28/I28) | X28: =IF(J28=0,"***",Q28/J28) | Y28: =IF(K28=0,"***",R28/K28)
C29: 0039 集計 | D29: その他 | E29: =(E19+E9)/2 | F29: =(F19+F9)/2 | G29: =(G19+G9)/2 | H29: =(H19+H9)/2 | I29: =(I19+I9)/2 | J29: =(J19+J9)/2 | K29: =SUM(E29:J29) | L29: =(L19+L9)/2 | M29: =(M19+M9)/2 | N29: =(N19+N9)/2 | O29: =(O19+O9)/2 | P29: =(P19+P9)/2 | Q29: =(Q19+Q9)/2 | R29: =SUM(L29:Q29) | S29: =IF(E29=0,"***",L29/E29) | T29: =IF(F29=0,"***",M29/F29) | U29: =IF(G29=0,"***",N29/G29) | V29: =IF(H29=0,"***",O29/H29) | W29: =IF(I29=0,"***",P29/I29) | X29: =IF(J29=0,"***",Q29/J29) | Y29: =IF(K29=0,"***",R29/K29)
C30: 合計 | E30: =SUM(E25:E29) | F30: =SUM(F25:F29) | G30: =SUM(G25:G29) | H30: =SUM(H25:H29) | I30: =SUM(I25:I29) | J30: =SUM(J25:J29) | K30: =SUM(E30:J30) | L30: =SUM(L25:L29) | M30: =SUM(M25:M29) | N30: =SUM(N25:N29) | O30: =SUM(O25:O29) | P30: =SUM(P25:P29) | Q30: =SUM(Q25:Q29) | R30: =SUM(L30:Q30) | S30: =IF(E30=0,"***",L30/E30) | T30: =IF(F30=0,"***",M30/F30) | U30: =IF(G30=0,"***",N30/G30) | V30: =IF(H30=0,"***",O30/H30) | W30: =IF(I30=0,"***",P30/I30) | X30: =IF(J30=0,"***",Q30/J30) | Y30: =IF(K30=0,"***",R30/K30)
C32: 4．計画
E33: 売上 | L33: 粗利益 | S33: 粗利益率
E34: 46113 | F34: 46143 | G34: 46174 | H34: 46204 | I34: 46235 | J34: 46266 | K34: 合計 | L34: 46113 | M34: 46143 | N34: 46174 | O34: 46204 | P34: 46235 | Q34: 46266 | R34: 合計 | S34: 46113 | T34: 46143 | U34: 46174 | V34: 46204 | W34: 46235 | X34: 46266 | Y34: 合計
C35: 0032 集計 | D35: 飯塚主任 | E35: 11800 | F35: 10420 | G35: 8750 | H35: 10170 | I35: 11790 | J35: 8400 | K35: =SUM(E35:J35) | L35: 3540 | M35: 3050 | N35: 2690 | O35: 3040 | P35: 3560 | Q35: 2850 | R35: =SUM(L35:Q35) | S35: =IF(E35=0,"***",L35/E35) | T35: =IF(F35=0,"***",M35/F35) | U35: =IF(G35=0,"***",N35/G35) | V35: =IF(H35=0,"***",O35/H35) | W35: =IF(I35=0,"***",P35/I35) | X35: =IF(J35=0,"***",Q35/J35) | Y35: =IF(K35=0,"***",R35/K35)
C36: 0033 集計 | D36: 前田課長代 | E36: 10950 | F36: 8160 | G36: 10180 | H36: 11150 | I36: 9510 | J36: 9550 | K36: =SUM(E36:J36) | L36: 2720 | M36: 2090 | N36: 2160 | O36: 2410 | P36: 2280 | Q36: 2370 | R36: =SUM(L36:Q36) | S36: =IF(E36=0,"***",L36/E36) | T36: =IF(F36=0,"***",M36/F36) | U36: =IF(G36=0,"***",N36/G36) | V36: =IF(H36=0,"***",O36/H36) | W36: =IF(I36=0,"***",P36/I36) | X36: =IF(J36=0,"***",Q36/J36) | Y36: =IF(K36=0,"***",R36/K36)
C37: 0034 集計 | D37: 原田 | E37: 9900 | F37: 8090 | G37: 8170 | H37: 10130 | I37: 9670 | J37: 9710 | K37: =SUM(E37:J37) | L37: 2370 | M37: 1890 | N37: 1860 | O37: 2320 | P37: 2190 | Q37: 2190 | R37: =SUM(L37:Q37) | S37: =IF(E37=0,"***",L37/E37) | T37: =IF(F37=0,"***",M37/F37) | U37: =IF(G37=0,"***",N37/G37) | V37: =IF(H37=0,"***",O37/H37) | W37: =IF(I37=0,"***",P37/I37) | X37: =IF(J37=0,"***",Q37/J37) | Y37: =IF(K37=0,"***",R37/K37)
C38: 0035 集計 | D38: 自治体 | E38: 0 | F38: 0 | G38: 0 | H38: 0 | I38: 0 | J38: 0 | K38: =SUM(E38:J38) | L38: 0 | M38: 0 | N38: 0 | O38: 0 | P38: 0 | Q38: 0 | R38: =SUM(L38:Q38) | S38: =IF(E38=0,"***",L38/E38) | T38: =IF(F38=0,"***",M38/F38) | U38: =IF(G38=0,"***",N38/G38) | V38: =IF(H38=0,"***",O38/H38) | W38: =IF(I38=0,"***",P38/I38) | X38: =IF(J38=0,"***",Q38/J38) | Y38: =IF(K38=0,"***",R38/K38)
C39: 0039 集計 | D39: その他 | K39: =SUM(E39:J39) | R39: =SUM(L39:Q39) | S39: =IF(E39=0,"***",L39/E39) | T39: =IF(F39=0,"***",M39/F39) | U39: =IF(G39=0,"***",N39/G39) | V39: =IF(H39=0,"***",O39/H39) | W39: =IF(I39=0,"***",P39/I39) | X39: =IF(J39=0,"***",Q39/J39) | Y39: =IF(K39=0,"***",R39/K39)
C40: 合計 | E40: =SUM(E35:E39) | F40: =SUM(F35:F39) | G40: =SUM(G35:G39) | H40: =SUM(H35:H39) | I40: =SUM(I35:I39) | J40: =SUM(J35:J39) | K40: =SUM(E40:J40) | L40: =SUM(L35:L39) | M40: =SUM(M35:M39) | N40: =SUM(N35:N39) | O40: =SUM(O35:O39) | P40: =SUM(P35:P39) | Q40: =SUM(Q35:Q39) | R40: =SUM(L40:Q40) | S40: =IF(E40=0,"***",L40/E40) | T40: =IF(F40=0,"***",M40/F40) | U40: =IF(G40=0,"***",N40/G40) | V40: =IF(H40=0,"***",O40/H40) | W40: =IF(I40=0,"***",P40/I40) | X40: =IF(J40=0,"***",Q40/J40) | Y40: =IF(K40=0,"***",R40/K40)
C42: ５．前期比
E43: 売上 | L43: 粗利益 | S43: 粗利益率
E44: 46113 | F44: 46143 | G44: 46174 | H44: 46204 | I44: 46235 | J44: 46266 | K44: 合計 | L44: 46113 | M44: 46143 | N44: 46174 | O44: 46204 | P44: 46235 | Q44: 46266 | R44: 合計 | S44: 46113 | T44: 46143 | U44: 46174 | V44: 46204 | W44: 46235 | X44: 46266 | Y44: 合計
C45: 0032 集計 | D45: 飯塚主任 | E45: =E35-E15 | F45: =F35-F15 | G45: =G35-G15 | H45: =H35-H15 | I45: =I35-I15 | J45: =J35-J15 | K45: =SUM(E45:J45) | L45: =L35-L15 | M45: =M35-M15 | N45: =N35-N15 | O45: =O35-O15 | P45: =P35-P15 | Q45: =Q35-Q15 | R45: =SUM(L45:Q45) | S45: =S35-S15 | T45: =T35-T15 | U45: =U35-U15 | V45: =V35-V15 | W45: =W35-W15 | X45: =X35-X15 | Y45: =Y35-Y15
C46: 0033 集計 | D46: 前田課長代 | E46: =E36-E16 | F46: =F36-F16 | G46: =G36-G16 | H46: =H36-H16 | I46: =I36-I16 | J46: =J36-J16 | K46: =SUM(E46:J46) | L46: =L36-L16 | M46: =M36-M16 | N46: =N36-N16 | O46: =O36-O16 | P46: =P36-P16 | Q46: =Q36-Q16 | R46: =SUM(L46:Q46) | S46: =S36-S16 | T46: =T36-T16 | U46: =U36-U16 | V46: =V36-V16 | W46: =W36-W16 | X46: =X36-X16 | Y46: =Y36-Y16
C47: 0034 集計 | D47: 原田 | E47: =E37-E17 | F47: =F37-F17 | G47: =G37-G17 | H47: =H37-H17 | I47: =I37-I17 | J47: =J37-J17 | K47: =SUM(E47:J47) | L47: =L37-L17 | M47: =M37-M17 | N47: =N37-N17 | O47: =O37-O17 | P47: =P37-P17 | Q47: =Q37-Q17 | R47: =SUM(L47:Q47) | S47: =S37-S17 | T47: =T37-T17 | U47: =U37-U17 | V47: =V37-V17 | W47: =W37-W17 | X47: =X37-X17 | Y47: =Y37-Y17
C48: 0035 集計 | D48: 自治体 | E48: =E38-E18 | F48: =F38-F18 | G48: =G38-G18 | H48: =H38-H18 | I48: =I38-I18 | J48: =J38-J18 | K48: =SUM(E48:J48) | L48: =L38-L18 | M48: =M38-M18 | N48: =N38-N18 | O48: =O38-O18 | P48: =P38-P18 | Q48: =Q38-Q18 | R48: =SUM(L48:Q48) | S48: =S38-S18 | T48: =T38-T18 | U48: =U38-U18 | V48: =V38-V18 | W48: =W38-W18 | X48: =X38-X18 | Y48: =Y38-Y18
C49: 0039 集計 | D49: その他 | E49: =E39-E19 | F49: =F39-F19 | G49: =G39-G19 | H49: =H39-H19 | I49: =I39-I19 | J49: =J39-J19 | K49: =SUM(E49:J49) | L49: =L39-L19 | M49: =M39-M19 | N49: =N39-N19 | O49: =O39-O19 | P49: =P39-P19 | Q49: =Q39-Q19 | R49: =SUM(L49:Q49) | S49: =S39-S19 | T49: =T39-T19 | U49: =U39-U19 | V49: =V39-V19 | W49: =W39-W19 | X49: =X39-X19 | Y49: =Y39-Y19
C50: 合計 | E50: =SUM(E45:E49) | F50: =SUM(F45:F49) | G50: =SUM(G45:G49) | H50: =SUM(H45:H49) | I50: =SUM(I45:I49) | J50: =SUM(J45:J49) | K50: =SUM(E50:J50) | L50: =SUM(L45:L49) | M50: =SUM(M45:M49) | N50: =SUM(N45:N49) | O50: =SUM(O45:O49) | P50: =SUM(P45:P49) | Q50: =SUM(Q45:Q49) | R50: =SUM(L50:Q50) | S50: =S40-S20 | T50: =T40-T20 | U50: =U40-U20 | V50: =V40-V20 | W50: =W40-W20 | X50: =X40-X20 | Y50: =Y40-Y20
C52: 6．過年度平均比
E53: 売上 | L53: 粗利益 | S53: 粗利益率
E54: 46113 | F54: 46143 | G54: 46174 | H54: 46204 | I54: 46235 | J54: 46266 | K54: 合計 | L54: 46113 | M54: 46143 | N54: 46174 | O54: 46204 | P54: 46235 | Q54: 46266 | R54: 合計 | S54: 46113 | T54: 46143 | U54: 46174 | V54: 46204 | W54: 46235 | X54: 46266 | Y54: 合計
C55: 0032 集計 | D55: 飯塚主任 | E55: =E35-E25 | F55: =F35-F25 | G55: =G35-G25 | H55: =H35-H25 | I55: =I35-I25 | J55: =J35-J25 | K55: =SUM(E55:J55) | L55: =L35-L25 | M55: =M35-M25 | N55: =N35-N25 | O55: =O35-O25 | P55: =P35-P25 | Q55: =Q35-Q25 | R55: =SUM(L55:Q55) | S55: =S35-S25 | T55: =T35-T25 | U55: =U35-U25 | V55: =V35-V25 | W55: =W35-W25 | X55: =X35-X25 | Y55: =Y35-Y25
C56: 0033 集計 | D56: 前田課長代 | E56: =E36-E26 | F56: =F36-F26 | G56: =G36-G26 | H56: =H36-H26 | I56: =I36-I26 | J56: =J36-J26 | K56: =SUM(E56:J56) | L56: =L36-L26 | M56: =M36-M26 | N56: =N36-N26 | O56: =O36-O26 | P56: =P36-P26 | Q56: =Q36-Q26 | R56: =SUM(L56:Q56) | S56: =S36-S26 | T56: =T36-T26 | U56: =U36-U26 | V56: =V36-V26 | W56: =W36-W26 | X56: =X36-X26 | Y56: =Y36-Y26
C57: 0034 集計 | D57: 原田 | E57: =E37-E27 | F57: =F37-F27 | G57: =G37-G27 | H57: =H37-H27 | I57: =I37-I27 | J57: =J37-J27 | K57: =SUM(E57:J57) | L57: =L37-L27 | M57: =M37-M27 | N57: =N37-N27 | O57: =O37-O27 | P57: =P37-P27 | Q57: =Q37-Q27 | R57: =SUM(L57:Q57) | S57: =S37-S27 | T57: =T37-T27 | U57: =U37-U27 | V57: =V37-V27 | W57: =W37-W27 | X57: =X37-X27 | Y57: =Y37-Y27
C58: 0035 集計 | D58: 自治体 | E58: =E38-E28 | F58: =F38-F28 | G58: =G38-G28 | H58: =H38-H28 | I58: =I38-I28 | J58: =J38-J28 | K58: =SUM(E58:J58) | L58: =L38-L28 | M58: =M38-M28 | N58: =N38-N28 | O58: =O38-O28 | P58: =P38-P28 | Q58: =Q38-Q28 | R58: =SUM(L58:Q58) | S58: =S38-S28 | T58: =T38-T28 | U58: =U38-U28 | V58: =V38-V28 | W58: =W38-W28 | X58: =X38-X28 | Y58: =Y38-Y28
C59: 0039 集計 | D59: その他 | E59: =E39-E29 | F59: =F39-F29 | G59: =G39-G29 | H59: =H39-H29 | I59: =I39-I29 | J59: =J39-J29 | K59: =SUM(E59:J59) | L59: =L39-L29 | M59: =M39-M29 | N59: =N39-N29 | O59: =O39-O29 | P59: =P39-P29 | Q59: =Q39-Q29 | R59: =SUM(L59:Q59) | S59: =S39-S29 | T59: =T39-T29 | U59: =U39-U29 | V59: =V39-V29 | W59: =W39-W29 | X59: =X39-X29 | Y59: =Y39-Y29
C60: 合計 | E60: =SUM(E55:E59) | F60: =SUM(F55:F59) | G60: =SUM(G55:G59) | H60: =SUM(H55:H59) | I60: =SUM(I55:I59) | J60: =SUM(J55:J59) | K60: =SUM(E60:J60) | L60: =SUM(L55:L59) | M60: =SUM(M55:M59) | N60: =SUM(N55:N59) | O60: =SUM(O55:O59) | P60: =SUM(P55:P59) | Q60: =SUM(Q55:Q59) | R60: =SUM(L60:Q60) | S60: =S40-S30 | T60: =T40-T30 | U60: =U40-U30 | V60: =V40-V30 | W60: =W40-W30 | X60: =X40-X30 | Y60: =Y40-Y30
C62: 7．実績
E63: 売上 | L63: 粗利益 | S63: 粗利益率
E64: 46113 | F64: 46143 | G64: 46174 | H64: 46204 | I64: 46235 | J64: 46266 | K64: 合計 | L64: 46113 | M64: 46143 | N64: 46174 | O64: 46204 | P64: 46235 | Q64: 46266 | R64: 合計 | S64: 46113 | T64: 46143 | U64: 46174 | V64: 46204 | W64: 46235 | X64: 46266 | Y64: 合計
C65: 0032 集計 | D65: 飯塚主任 | E65: 15047.04 | F65: 10820.014 | G65: 8876.039 | H65: 10443.425 | I65: 11940.197 | K65: =SUM(E65:J65) | L65: 4536.348 | M65: 3567.44 | N65: 3002.952 | O65: 3520.407 | P65: 3975.887 | R65: =SUM(L65:Q65) | S65: =IF(E65=0,"***",L65/E65) | T65: =IF(F65=0,"***",M65/F65) | U65: =IF(G65=0,"***",N65/G65) | V65: =IF(H65=0,"***",O65/H65) | W65: =IF(I65=0,"***",P65/I65) | X65: =IF(J65=0,"***",Q65/J65) | Y65: =IF(K65=0,"***",R65/K65)
C66: 0033 集計 | D66: 前田課長代 | E66: 15265.922 | F66: 10070.893 | G66: 12983.805 | H66: 17107.798 | I66: 10370.244 | K66: =SUM(E66:J66) | L66: 3492.024 | M66: 2365.03 | N66: 2676.518 | O66: 3549.9651 | P66: 2625.623 | R66: =SUM(L66:Q66) | S66: =IF(E66=0,"***",L66/E66) | T66: =IF(F66=0,"***",M66/F66) | U66: =IF(G66=0,"***",N66/G66) | V66: =IF(H66=0,"***",O66/H66) | W66: =IF(I66=0,"***",P66/I66) | X66: =IF(J66=0,"***",Q66/J66) | Y66: =IF(K66=0,"***",R66/K66)
C67: 0034 集計 | D67: 原田 | E67: 10061 | F67: 8724 | G67: 8649.739 | H67: 11910.007 | I67: 10792.559 | K67: =SUM(E67:J67) | L67: 2538 | M67: 2281 | N67: 2121.064 | O67: 3025.832 | P67: 2924.322 | R67: =SUM(L67:Q67) | S67: =IF(E67=0,"***",L67/E67) | T67: =IF(F67=0,"***",M67/F67) | U67: =IF(G67=0,"***",N67/G67) | V67: =IF(H67=0,"***",O67/H67) | W67: =IF(I67=0,"***",P67/I67) | X67: =IF(J67=0,"***",Q67/J67) | Y67: =IF(K67=0,"***",R67/K67)
C68: 0035 集計 | D68: 自治体 | I68: 0 | K68: =SUM(E68:J68) | P68: 0 | R68: =SUM(L68:Q68) | S68: =IF(E68=0,"***",L68/E68) | T68: =IF(F68=0,"***",M68/F68) | U68: =IF(G68=0,"***",N68/G68) | V68: =IF(H68=0,"***",O68/H68) | W68: =IF(I68=0,"***",P68/I68) | X68: =IF(J68=0,"***",Q68/J68) | Y68: =IF(K68=0,"***",R68/K68)
C69: 0039 集計 | D69: その他 | E69: 9.3 | F69: 7.17 | H69: 0.45 | I69: 10.79 | K69: =SUM(E69:J69) | L69: 1.5 | M69: 2.751 | O69: 0.054 | P69: 4.266 | R69: =SUM(L69:Q69) | S69: =IF(E69=0,"***",L69/E69) | T69: =IF(F69=0,"***",M69/F69) | U69: =IF(G69=0,"***",N69/G69) | V69: =IF(H69=0,"***",O69/H69) | W69: =IF(I69=0,"***",P69/I69) | X69: =IF(J69=0,"***",Q69/J69) | Y69: =IF(K69=0,"***",R69/K69)
C70: 合計 | E70: =SUM(E65:E69) | F70: =SUM(F65:F69) | G70: =SUM(G65:G69) | H70: =SUM(H65:H69) | I70: =SUM(I65:I69) | J70: =SUM(J65:J69) | K70: =SUM(E70:J70) | L70: =SUM(L65:L69) | M70: =SUM(M65:M69) | N70: =SUM(N65:N69) | O70: =SUM(O65:O69) | P70: =SUM(P65:P69) | Q70: =SUM(Q65:Q69) | R70: =SUM(L70:Q70) | S70: =IF(E70=0,"***",L70/E70) | T70: =IF(F70=0,"***",M70/F70) | U70: =IF(G70=0,"***",N70/G70) | V70: =IF(H70=0,"***",O70/H70) | W70: =IF(I70=0,"***",P70/I70) | X70: =IF(J70=0,"***",Q70/J70) | Y70: =IF(K70=0,"***",R70/K70)
C72: 8．計画比
E73: 売上 | L73: 粗利益 | S73: 粗利益率
E74: 46113 | F74: 46143 | G74: 46174 | H74: 46204 | I74: 46235 | J74: 46266 | K74: 合計 | L74: 46113 | M74: 46143 | N74: 46174 | O74: 46204 | P74: 46235 | Q74: 46266 | R74: 合計 | S74: 46113 | T74: 46143 | U74: 46174 | V74: 46204 | W74: 46235 | X74: 46266 | Y74: 合計
C75: 0032 集計 | D75: 飯塚主任 | E75: =E65-E35 | F75: =F65-F35 | G75: =G65-G35 | H75: =H65-H35 | I75: =I65-I35 | K75: =SUM(E75:J75) | L75: =L65-L35 | M75: =M65-M35 | N75: =N65-N35 | O75: =O65-O35 | P75: =P65-P35 | R75: =SUM(L75:Q75) | S75: =S65-S35 | T75: =T65-T35 | U75: =U65-U35 | V75: =V65-V35 | W75: =W65-W35 | X75: =X65-X35 | Y75: =Y65-Y35
C76: 0033 集計 | D76: 前田課長代 | E76: =E66-E36 | F76: =F66-F36 | G76: =G66-G36 | H76: =H66-H36 | I76: =I66-I36 | K76: =SUM(E76:J76) | L76: =L66-L36 | M76: =M66-M36 | N76: =N66-N36 | O76: =O66-O36 | P76: =P66-P36 | R76: =SUM(L76:Q76) | S76: =S66-S36 | T76: =T66-T36 | U76: =U66-U36 | V76: =V66-V36 | W76: =W66-W36 | X76: =X66-X36 | Y76: =Y66-Y36
C77: 0034 集計 | D77: 原田 | E77: =E67-E37 | F77: =F67-F37 | G77: =G67-G37 | H77: =H67-H37 | I77: =I67-I37 | K77: =SUM(E77:J77) | L77: =L67-L37 | M77: =M67-M37 | N77: =N67-N37 | O77: =O67-O37 | P77: =P67-P37 | R77: =SUM(L77:Q77) | S77: =S67-S37 | T77: =T67-T37 | U77: =U67-U37 | V77: =V67-V37 | W77: =W67-W37 | X77: =X67-X37 | Y77: =Y67-Y37
C78: 0035 集計 | D78: 自治体 | E78: =E68-E38 | F78: =F68-F38 | G78: =G68-G38 | H78: =H68-H38 | I78: =I68-I38 | K78: =SUM(E78:J78) | L78: =L68-L38 | M78: =M68-M38 | N78: =N68-N38 | O78: =O68-O38 | P78: =P68-P38 | R78: =SUM(L78:Q78) | S78: =S68-S38 | T78: =T68-T38 | U78: =U68-U38 | V78: =V68-V38 | W78: =W68-W38 | X78: =X68-X38 | Y78: =Y68-Y38
C79: 0039 集計 | D79: その他 | E79: =E69-E39 | F79: =F69-F39 | G79: =G69-G39 | H79: =H69-H39 | I79: =I69-I39 | K79: =SUM(E79:J79) | L79: =L69-L39 | M79: =M69-M39 | N79: =N69-N39 | O79: =O69-O39 | P79: =P69-P39 | R79: =SUM(L79:Q79) | S79: =S69-S39 | T79: =T69-T39 | U79: =U69-U39 | V79: =V69-V39 | W79: =W69-W39 | X79: =X69-X39 | Y79: =Y69-Y39
C80: 合計 | E80: =SUM(E75:E79) | F80: =SUM(F75:F79) | G80: =SUM(G75:G79) | H80: =SUM(H75:H79) | I80: =SUM(I75:I79) | J80: =SUM(J75:J79) | K80: =SUM(E80:J80) | L80: =SUM(L75:L79) | M80: =SUM(M75:M79) | N80: =SUM(N75:N79) | O80: =SUM(O75:O79) | P80: =SUM(P75:P79) | Q80: =SUM(Q75:Q79) | R80: =SUM(L80:Q80) | S80: =S70-S40 | T80: =T70-T40 | U80: =U70-U40 | V80: =V70-V40 | W80: =W70-W40 | X80: =X60-X10 | Y80: =Y70-Y40
C82: 9．前期比
E83: 売上 | L83: 粗利益 | S83: 粗利益率
E84: 46113 | F84: 46143 | G84: 46174 | H84: 46204 | I84: 46235 | J84: 46266 | K84: 合計 | L84: 46113 | M84: 46143 | N84: 46174 | O84: 46204 | P84: 46235 | Q84: 46266 | R84: 合計 | S84: 46113 | T84: 46143 | U84: 46174 | V84: 46204 | W84: 46235 | X84: 46266 | Y84: 合計
C85: 0032 集計 | D85: 飯塚主任 | E85: =E65-E15 | F85: =F65-F15 | G85: =G65-G15 | H85: =H65-H15 | I85: =I65-I15 | K85: =SUM(E85:J85) | L85: =L65-L15 | M85: =M65-M15 | N85: =N65-N15 | O85: =O65-O15 | P85: =P65-P15 | R85: =SUM(L85:Q85) | S85: =S65-S15 | T85: =T65-T15 | U85: =U65-U15 | V85: =V65-V15 | W85: =W65-W15 | X85: =X65-X15 | Y85: =Y65-Y15
C86: 0033 集計 | D86: 前田課長代 | E86: =E66-E16 | F86: =F66-F16 | G86: =G66-G16 | H86: =H66-H16 | I86: =I66-I16 | K86: =SUM(E86:J86) | L86: =L66-L16 | M86: =M66-M16 | N86: =N66-N16 | O86: =O66-O16 | P86: =P66-P16 | R86: =SUM(L86:Q86) | S86: =S66-S16 | T86: =T66-T16 | U86: =U66-U16 | V86: =V66-V16 | W86: =W66-W16 | X86: =X66-X16 | Y86: =Y66-Y16
C87: 0034 集計 | D87: 原田 | E87: =E67-E17 | F87: =F67-F17 | G87: =G67-G17 | H87: =H67-H17 | I87: =I67-I17 | K87: =SUM(E87:J87) | L87: =L67-L17 | M87: =M67-M17 | N87: =N67-N17 | O87: =O67-O17 | P87: =P67-P17 | R87: =SUM(L87:Q87) | S87: =S67-S17 | T87: =T67-T17 | U87: =U67-U17 | V87: =V67-V17 | W87: =W67-W17 | X87: =X67-X17 | Y87: =Y67-Y17
C88: 0035 集計 | D88: 自治体 | E88: =E68-E18 | F88: =F68-F18 | G88: =G68-G18 | H88: =H68-H18 | I88: =I68-I18 | K88: =SUM(E88:J88) | L88: =L68-L18 | M88: =M68-M18 | N88: =N68-N18 | O88: =O68-O18 | P88: =P68-P18 | R88: =SUM(L88:Q88) | S88: =S68-S18 | T88: =T68-T18 | U88: =U68-U18 | V88: =V68-V18 | W88: =W68-W18 | X88: =X68-X18 | Y88: =Y68-Y18
C89: 0039 集計 | D89: その他 | E89: =E69-E19 | F89: =F69-F19 | G89: =G69-G19 | H89: =H69-H19 | I89: =I69-I19 | K89: =SUM(E89:J89) | L89: =L69-L19 | M89: =M69-M19 | N89: =N69-N19 | O89: =O69-O19 | P89: =P69-P19 | R89: =SUM(L89:Q89) | S89: =S69-S19 | T89: =T69-T19 | U89: =U69-U19 | V89: =V69-V19 | W89: =W69-W19 | X89: =X69-X19 | Y89: =Y69-Y19
C90: 合計 | E90: =SUM(E85:E89) | F90: =SUM(F85:F89) | G90: =SUM(G85:G89) | H90: =SUM(H85:H89) | I90: =SUM(I85:I89) | J90: =SUM(J85:J89) | K90: =SUM(E90:J90) | L90: =SUM(L85:L89) | M90: =SUM(M85:M89) | N90: =SUM(N85:N89) | O90: =SUM(O85:O89) | P90: =SUM(P85:P89) | Q90: =SUM(Q85:Q89) | R90: =SUM(L90:Q90) | S90: =S70-S20 | T90: =T70-T20 | U90: =U80-U50 | V90: =V80-V50 | W90: =W80-W50 | X90: =X80-X50 | Y90: =Y70-Y20

Sheet 総括
D1: 松江営業所第51期下期予算について
D3: 管理職の業務は数字責任と人材育成です。なので営業所全体の目標達成に取り組みます。
D4: 部長は予算の過年度平均増加分の人員からは外した上で、営業所全体で計画を作成ます。その営業所全体の予算から所長含めて営業担当に配分するようにお願いします。
D5: (自治体分は別途相談）
G7: 2024年4～9月 | J7: 2025年4～9月 | M7: 過年度平均 | P7: 計画 | U7: 根拠
G8: 売上 | H8: 粗利益 | I8: 粗利益率 | J8: 売上 | K8: 粗利益 | L8: 粗利益率 | M8: 売上 | N8: 粗利益 | O8: 粗利益率 | P8: 売上 | Q8: 粗利益 | R8: 粗利益率 | S8: 売上年率 | T8: 粗利益年率
D9: 松江営業所 | G9: 204319 | H9: 40153 | I9: =H9/G9 | J9: 199329 | K9: 43760 | L9: =K9/J9 | M9: =(G9+J9)/2 | N9: =(H9+K9)/2 | O9: =N9/M9 | P9: =P13+P10 | Q9: =Q10+Q13 | R9: =Q9/P9 | S9: =P9/J9-1 | T9: =Q9/K9-1
E10: 営業 | G10: =G9-G13 | H10: =H9-H13 | I10: =H10/G10 | J10: =J9-J13 | K10: =K9-K13 | L10: =K10/J10 | M10: =M9-M13 | N10: =N9-N13 | O10: =N10/M10 | P10: =P11+P12 | Q10: =Q11+Q12 | R10: =Q10/P10 | S10: =P10/J10-1 | T10: =Q10/K10-1
F11: 包装資材 | G11: =G10-G12 | H11: =H10-H12 | I11: =H11/G11 | J11: =J10-J12 | K11: =K10-K12 | L11: =K11/J11 | M11: =M10-M12 | N11: =N10-N12 | O11: =N11/M11 | P11: 172600 | Q11: 44770 | R11: =Q11/P11 | S11: =P11/J11-1 | T11: =Q11/K11-1 | U11: 売上過年度平均10％UPで作成。粗利益率過年度平均スライド。
F12: 機械 | G12: 2590 | H12: 557 | I12: =H12/G12 | J12: 3620 | K12: 738 | L12: =K12/J12 | M12: =(G12+J12)/2 | N12: =(H12+K12)/2 | O12: =N12/M12 | P12: 3900 | Q12: 810 | R12: =Q12/P12 | S12: =P12/J12-1 | T12: =Q12/K12-1 | U12: 売上過年度平均25％UPで作成。粗利益率過年度平均スライド。
E13: 自治体 | G13: 46524 | H13: 1039 | I13: =H13/G13 | J13: 38895 | K13: 703 | L13: =K13/J13 | M13: =(G13+J13)/2 | N13: =(H13+K13)/2 | O13: =N13/M13 | P13: 0 | Q13: 0 | R13: =Q13/P13 | S13: =P13/J13-1 | T13: =Q13/K13-1 | U13: 松江市ごみ袋失注の為。

Sheet Sheet1
C1: 売上 | F1: 粗利 | I1: 粗利率
A2: 期 | B2: 期間 | C2: 計画 | D2: 見込み | E2: 計画比 | F2: 計画 | G2: 見込み | H2: 計画比 | I2: 計画 | J2: 見込 | K2: 計画比 | L2: 備考
A3: 49期 | B3: 7月～9月 | C3: 74190 | D3: 106390 | E3: =D3-C3 | F3: 17570 | G3: 24290 | H3: =G3-F3 | I3: =F3/C3 | J3: =G3/D3 | K3: =J3-I3 | L3: ごみ袋込
A4: 50期 | B4: 10月～3月 | C4: 163030 | D4: 210040 | E4: =D4-C4 | F4: 39830 | G4: 45668 | H4: =G4-F4 | I4: =F4/C4 | J4: =G4/D4 | K4: =J4-I4 | L4: ごみ袋込
A5: 合計 | B5: 7月～3月 | C5: =SUM(C3:C4) | D5: =SUM(D3:D4) | E5: =SUM(E3:E4) | F5: =F3+F4 | G5: =G3+G4 | H5: =G5-F5 | I5: =F5/C5 | J5: =G5/D5 | K5: =J5-I5 | L5: ごみ袋込
C7: 売上 | F7: 粗利
A8: 期 | B8: 期間 | C8: 計画 | D8: 見込み | E8: 計画比 | F8: 計画 | G8: 見込み | H8: 計画比 | I8: 計画 | J8: 見込 | K8: 計画比
A9: ごみ袋 | B9: 7月～3月 | C9: ー | D9: 47910 | E9: 47910 | G9: 1013 | H9: 1013 | J9: =G9/D9
A10: 資材増加額 | B10: 7月～3月 | C10: ー | E10: =E5-E9 | H10: =H5-H9
